Workbook

Sheet Sheet1
A1: 关键词 | B1: 0.6875 | D1: 0.875
B2: 广告 | C2: 自然 | D2: 广告 | E2: 自然 | F2: 广告 | G2: 自然 | H2: 广告 | I2: 自然
A3: bed vacuum cleaner uv sanitizing | B3: 3 | C3: 5 | E3: 3
A4: mattress vacuum cleaner uv sanitizing | B4: 5 | C4: 4 | E4: 3
A5: vacuum for bed mattress | B5: 2 | C5: 4 | E5: 3
A6: dust mite vacuum | B6: 7 | C6: / | E6: 5
A7: uv vacuum cleaner for mattress | B7: 3 | C7: 2 | E7: 2
A8: mattress vacuum for pet hair | B8: 3 | C8: 2 | E8: 2
A9: pet hair vacuum cleaners for bed | B9: 1 | C9: 3 | D9: 1 | E9: 3
A11: mattress vacuum cleaner | B11: 4 | C11: 1 | E11: 1
A12: pet hair vacuum cleaners for bed | B12: 2 | C12: 3 | D12: 1 | E12: 3
A13: vacuum for bed mattress | B13: 3 | C13: 4 | E13: 3
A14: bed mattress vacuum cleaner | B14: 1 | C14: 5 | E14: 3
A15: mattress vacuum | B15: / | C15: 1 | E15: 2

Sheet 除螨仪
A1: 时间 | B1: 国家 | C1: 数量 | D1: 售价 | E1: 销售额 | F1: 单个毛利 | G1: 广告预算 | H1: 实际广告 | I1: 活动费 | J1: 毛利 | K1: 毛利率 | L1: 毛利(RMB) | M1: 销售额(RMB) | N1: 广告占比 | O1: 广告订单 | P1: 自然订单 | Q1: 广告订单占比 | R1: ACOS
A2: 2025/7/8 - 2025/7/11 | B2: DE | C2: =SUMIF(B11:B1000,B2,C11:C1000) | D2: 55.85 | E2: =SUMIF(B11:B1000,B2,E11:E1000) | G2: =SUMIF(B11:B1000,B2,G11:G1000) | H2: =SUMIF(B11:B1000,B2,H11:H1000) | I2: =SUMIF(B11:B1000,B2,I11:I1000) | J2: =SUMIF(B11:B1000,B2,J11:J1000) | K2: =J2/E2 | L2: =SUMIF(B11:B1000,B2,L11:L1000) | M2: =SUMIF(B11:B1000,B2,M11:M1000) | N2: =H2/E2 | O2: =SUMIF(B11:B1000,B2,O11:O1000) | P2: =C2-O2 | Q2: =O2/C2 | R2: =H2/(E2*Q2)
B3: FR | C3: =SUMIF(B12:B1001,B3,C12:C1001) | D3: 58 | E3: =SUMIF(B12:B1001,B3,E12:E1001) | G3: =SUMIF(B12:B1001,B3,G12:G1001) | H3: =SUMIF(B12:B1001,B3,H12:H1001) | I3: =SUMIF(B12:B1001,B3,I12:I1001) | J3: =SUMIF(B12:B1001,B3,J12:J1001) | K3: =J3/E3 | L3: =SUMIF(B12:B1001,B3,L12:L1001) | M3: =SUMIF(B12:B1001,B3,M12:M1001) | N3: =H3/E3 | O3: =SUMIF(B12:B1001,B3,O12:O1001) | P3: =C3-O3 | Q3: =O3/C3 | R3: =H3/(E3*Q3)
B4: IT | C4: =SUMIF(B13:B1002,B4,C13:C1002) | D4: 58.8 | E4: =SUMIF(B13:B1002,B4,E13:E1002) | G4: =SUMIF(B13:B1002,B4,G13:G1002) | H4: =SUMIF(B13:B1002,B4,H13:H1002) | I4: =SUMIF(B13:B1002,B4,I13:I1002) | J4: =SUMIF(B13:B1002,B4,J13:J1002) | K4: =J4/E4 | L4: =SUMIF(B13:B1002,B4,L13:L1002) | M4: =SUMIF(B13:B1002,B4,M13:M1002) | N4: =H4/E4 | O4: =SUMIF(B13:B1002,B4,O13:O1002) | P4: =C4-O4 | Q4: =O4/C4 | R4: =H4/(E4*Q4)
B5: ES | C5: =SUMIF(B14:B1003,B5,C14:C1003) | D5: 59.35 | E5: =SUMIF(B14:B1003,B5,E14:E1003) | G5: =SUMIF(B14:B1003,B5,G14:G1003) | H5: =SUMIF(B14:B1003,B5,H14:H1003) | I5: =SUMIF(B14:B1003,B5,I14:I1003) | J5: =SUMIF(B14:B1003,B5,J14:J1003) | K5: =J5/E5 | L5: =SUMIF(B14:B1003,B5,L14:L1003) | M5: =SUMIF(B14:B1003,B5,M14:M1003) | N5: =H5/E5 | O5: =SUMIF(B14:B1003,B5,O14:O1003) | P5: =C5-O5 | Q5: =O5/C5 | R5: =H5/(E5*Q5)
B6: UK | C6: =SUMIF(B15:B1004,B6,C15:C1004) | D6: 67.99 | E6: =SUMIF(B15:B1004,B6,E15:E1004) | G6: =SUMIF(B15:B1004,B6,G15:G1004) | H6: =SUMIF(B15:B1004,B6,H15:H1004) | I6: =SUMIF(B15:B1004,B6,I15:I1004) | J6: =SUMIF(B15:B1004,B6,J15:J1004) | K6: =J6/E6 | L6: =SUMIF(B15:B1004,B6,L15:L1004) | M6: =SUMIF(B15:B1004,B6,M15:M1004) | N6: =H6/E6 | O6: =SUMIF(B15:B1004,B6,O15:O1004) | P6: =C6-O6 | Q6: =O6/C6 | R6: =H6/(E6*Q6)
B7: US | C7: =SUMIF(B16:B1005,B7,C16:C1005) | D7: 49.99 | E7: =SUMIF(B16:B1005,B7,E16:E1005) | G7: =SUMIF(B16:B1005,B7,G16:G1005) | H7: =SUMIF(B16:B1005,B7,H16:H1005) | I7: =SUMIF(B16:B1005,B7,I16:I1005) | J7: =SUMIF(B16:B1005,B7,J16:J1005) | K7: =J7/E7 | L7: =SUMIF(B16:B1005,B7,L16:L1005) | M7: =SUMIF(B16:B1005,B7,M16:M1005) | N7: =H7/E7 | O7: =SUMIF(B16:B1005,B7,O16:O1005) | P7: =C7-O7 | Q7: =O7/C7 | R7: =H7/(E7*Q7)
B8: 汇总 | C8: =SUM(C2:C7) | K8: =L8/M8 | L8: =SUM(L2:L7) | M8: =SUM(M2:M7) | O8: =SUM(O2:O7) | P8: =C8-O8 | Q8: =O8/C8
A10: 时间 | B10: 国家 | C10: 数量 | D10: 售价 | E10: 销售额 | F10: 单个毛利 | G10: 广告预算 | H10: 实际广告 | I10: 活动费 | J10: 毛利 | K10: 毛利率 | L10: 毛利(RMB) | M10: 销售额(RMB) | N10: 广告占比 | O10: 广告订单 | P10: 自然订单 | Q10: 广告订单占比 | R10: ACOS
A11: 45846 | B11: DE | C11: 27 | D11: 55.85 | E11: =C11*D11 | F11: 2.5 | G11: =C11*8 | H11: 141.95 | I11: =E11*0.025 | J11: =F11*C11+G11-H11-I11 | K11: =J11/E11 | L11: =J11*8 | M11: =E11*8 | N11: =H11/E11 | O11: 14 | P11: =C11-O11 | Q11: =O11/C11 | R11: =H11/(E11*Q11)
B12: FR | C12: 3 | D12: 58 | E12: =C12*D12 | F12: -1.7 | G12: =C12*8 | H12: 9.29 | I12: =E12*0.025 | J12: =F12*C12+G12-H12-I12 | K12: =J12/E12 | L12: =J12*8 | M12: =E12*8 | N12: =H12/E12 | O12: 2 | P12: =C12-O12 | Q12: =O12/C12 | R12: =H12/(E12*Q12)
B13: IT | C13: 8 | D13: 58.8 | E13: =C13*D13 | F13: 1.9 | G13: =C13*8 | H13: 147.26 | I13: =E13*0.025 | J13: =F13*C13+G13-H13-I13 | K13: =J13/E13 | L13: =J13*8 | M13: =E13*8 | N13: =H13/E13 | O13: 8 | P13: =C13-O13 | Q13: =O13/C13 | R13: =H13/(E13*Q13)
B14: ES | C14: 17 | D14: 59.35 | E14: =C14*D14 | F14: 2.53 | G14: =C14*8 | H14: 280.15 | I14: =E14*0.025 | J14: =F14*C14+G14-H14-I14 | K14: =J14/E14 | L14: =J14*8 | M14: =E14*8 | N14: =H14/E14 | O14: 18 | P14: =C14-O14 | Q14: =O14/C14 | R14: =H14/(E14*Q14)
B15: UK | C15: 29 | D15: 67.99 | E15: =C15*D15 | F15: 12.5 | G15: =C15*10 | H15: 178.07 | I15: =E15*0.025 | J15: =F15*C15+G15-H15-I15 | K15: =J15/E15 | L15: =J15*9 | M15: =E15*9 | N15: =H15/E15 | O15: 17 | P15: =C15-O15 | Q15: =O15/C15 | R15: =H15/(E15*Q15)
B16: US | C16: 20 | D16: 49.99 | E16: =C16*D16 | F16: 6.43 | H16: 236.38 | I16: 25 | J16: =C16*F16-H16-I16 | K16: =J16/E16 | L16: =J16*7 | M16: =E16*7 | N16: =H16/E16 | O16: 15 | P16: =C16-O16 | Q16: =O16/C16 | R16: =H16/(E16*Q16)
B17: 汇总 | C17: =SUM(C11:C16) | K17: =L17/M17 | L17: =SUM(L11:L16) | M17: =SUM(M11:M16) | O17: =SUM(O11:O16) | P17: =C17-O17 | Q17: =O17/C17
A19: 时间 | B19: 国家 | C19: 数量 | D19: 售价 | E19: 销售额 | F19: 单个毛利 | G19: 广告预算 | H19: 实际广告 | I19: 活动费 | J19: 毛利 | K19: 毛利率 | L19: 毛利(RMB) | M19: 销售额(RMB) | N19: 广告占比 | O19: 广告订单 | P19: 自然订单 | Q19: 广告订单占比 | R19: ACOS
A20: 45847 | B20: DE | C20: 23 | D20: 55.85 | E20: =C20*D20 | F20: =(6*2.5+17*6.5)/23 | G20: =C20*8 | H20: 144.7 | I20: =E20*0.025 | J20: =F20*C20+G20-H20-I20 | K20: =J20/E20 | L20: =J20*8 | M20: =E20*8 | N20: =H20/E20 | O20: 8 | P20: =C20-O20 | Q20: =O20/C20 | R20: =H20/(E20*Q20)
B21: FR | C21: 2 | D21: 58 | E21: =C21*D21 | F21: -1.7 | G21: =C21*8 | H21: 7.63 | I21: =E21*0.025 | J21: =F21*C21+G21-H21-I21 | K21: =J21/E21 | L21: =J21*8 | M21: =E21*8 | N21: =H21/E21 | O21: 0 | P21: =C21-O21 | Q21: =O21/C21 | R21: =H21/(E21*Q21)
B22: IT | C22: 28 | D22: 58.8 | E22: =C22*D22 | F22: =(6*1.9+21*6.23)/27 | G22: =C22*8 | H22: 142.02 | I22: =E22*0.025 | J22: =F22*C22+G22-H22-I22 | K22: =J22/E22 | L22: =J22*8 | M22: =E22*8 | N22: =H22/E22 | O22: 6 | P22: =C22-O22 | Q22: =O22/C22 | R22: =H22/(E22*Q22)
B23: ES | C23: 27 | D23: 59.35 | E23: =C23*D23 | F23: =(6*2.53+21*6.78)/27 | G23: =C23*8 | H23: 165.58 | I23: =E23*0.025 | J23: =F23*C23+G23-H23-I23 | K23: =J23/E23 | L23: =J23*8 | M23: =E23*8 | N23: =H23/E23 | O23: 7 | P23: =C23-O23 | Q23: =O23/C23 | R23: =H23/(E23*Q23)
B24: UK | C24: 16 | D24: 67.99 | E24: =67.99*12+80.61*4 | F24: =(21*4+12.5*12)/16 | G24: =C24*10 | H24: 120.44 | I24: =E24*0.025 | J24: =F24*C24+G24-H24-I24 | K24: =J24/E24 | L24: =J24*9 | M24: =E24*9 | N24: =H24/E24 | O24: 7 | P24: =C24-O24 | Q24: =O24/C24 | R24: =H24/(E24*Q24)
B25: US | C25: 23 | D25: 49.99 | E25: =C25*D25 | F25: 6.43 | H25: 200.8 | I25: 25 | J25: =C25*F25-H25-I25 | K25: =J25/E25 | L25: =J25*7 | M25: =E25*7 | N25: =H25/E25 | O25: 8 | P25: =C25-O25 | Q25: =O25/C25 | R25: =H25/(E25*Q25)
B26: 汇总 | C26: =SUM(C20:C25) | K26: =L26/M26 | L26: =SUM(L20:L25) | M26: =SUM(M20:M25) | O26: =SUM(O20:O25) | P26: =C26-O26 | Q26: =O26/C26
A28: 时间 | B28: 国家 | C28: 数量 | D28: 售价 | E28: 销售额 | F28: 单个毛利 | G28: 广告预算 | H28: 实际广告 | I28: 活动费 | J28: 毛利 | K28: 毛利率 | L28: 毛利(RMB) | M28: 销售额(RMB) | N28: 广告占比 | O28: 广告订单 | P28: 自然订单 | Q28: 广告订单占比 | R28: ACOS
A29: 45848 | B29: DE | C29: 24 | D29: 55.85 | E29: =C29*D29 | F29: 6.5 | G29: =C29*8 | H29: 176.46 | I29: =E29*0.025 | J29: =F29*C29+G29-H29-I29 | K29: =J29/E29 | L29: =J29*8 | M29: =E29*8 | N29: =H29/E29 | O29: 14 | P29: =C29-O29 | Q29: =O29/C29 | R29: =H29/(E29*Q29)
B30: FR | C30: 2 | D30: 58 | E30: =C30*D30 | F30: -1.7 | G30: =C30*8 | H30: 28.27 | I30: =E30*0.025 | J30: =F30*C30+G30-H30-I30 | K30: =J30/E30 | L30: =J30*8 | M30: =E30*8 | N30: =H30/E30 | O30: 0 | P30: =C30-O30 | Q30: =O30/C30 | R30: =H30/(E30*Q30)
B31: IT | C31: 29 | D31: 58.8 | E31: =C31*D31 | F31: 6.23 | G31: =C31*8 | H31: 103.98 | I31: =E31*0.025 | J31: =F31*C31+G31-H31-I31 | K31: =J31/E31 | L31: =J31*8 | M31: =E31*8 | N31: =H31/E31 | O31: 11 | P31: =C31-O31 | Q31: =O31/C31 | R31: =H31/(E31*Q31)
B32: ES | C32: 17 | D32: 59.35 | E32: =C32*D32 | F32: 6.78 | G32: =C32*8 | H32: 128.06 | I32: =E32*0.025 | J32: =F32*C32+G32-H32-I32 | K32: =J32/E32 | L32: =J32*8 | M32: =E32*8 | N32: =H32/E32 | O32: 7 | P32: =C32-O32 | Q32: =O32/C32 | R32: =H32/(E32*Q32)
B33: UK | C33: 9 | D33: 80.61 | E33: =C33*D33 | F33: 21 | G33: =C33*10 | H33: 64.94 | I33: =E33*0.025 | J33: =F33*C33+G33-H33-I33 | K33: =J33/E33 | L33: =J33*9 | M33: =E33*9 | N33: =H33/E33 | O33: 5 | P33: =C33-O33 | Q33: =O33/C33 | R33: =H33/(E33*Q33)
B34: US | C34: 15 | D34: 49.99 | E34: =C34*D34 | F34: 6.43 | H34: 122.35 | I34: 25 | J34: =C34*F34-H34-I34 | K34: =J34/E34 | L34: =J34*7 | M34: =E34*7 | N34: =H34/E34 | O34: 3 | P34: =C34-O34 | Q34: =O34/C34 | R34: =H34/(E34*Q34)
B35: 汇总 | C35: =SUM(C29:C34) | K35: =L35/M35 | L35: =SUM(L29:L34) | M35: =SUM(M29:M34) | O35: =SUM(O29:O34) | P35: =C35-O35 | Q35: =O35/C35
A37: 时间 | B37: 国家 | C37: 数量 | D37: 售价 | E37: 销售额 | F37: 单个毛利 | G37: 广告预算 | H37: 实际广告 | I37: 活动费 | J37: 毛利 | K37: 毛利率 | L37: 毛利(RMB) | M37: 销售额(RMB) | N37: 广告占比 | O37: 广告订单 | P37: 自然订单 | Q37: 广告订单占比 | R37: ACOS
A38: 45849 | B38: DE | C38: 29 | D38: 55.85 | E38: =C38*D38 | F38: =(6.5*12+10.5*17)/29 | G38: =C38*8 | H38: 147.15 | I38: =E38*0.025 | J38: =F38*C38+G38-H38-I38 | K38: =J38/E38 | L38: =J38*8 | M38: =E38*8 | N38: =H38/E38 | O38: 15 | P38: =C38-O38 | Q38: =O38/C38 | R38: =H38/(E38*Q38)
B39: FR | C39: 1 | D39: 58 | E39: =C39*D39 | F39: -1.7 | G39: =C39*8 | H39: 19.33 | I39: =E39*0.025 | J39: =F39*C39+G39-H39-I39 | K39: =J39/E39 | L39: =J39*8 | M39: =E39*8 | N39: =H39/E39 | O39: 1 | P39: =C39-O39 | Q39: =O39/C39 | R39: =H39/(E39*Q39)
B40: IT | C40: 19 | D40: 58.8 | E40: =C40*D40 | F40: =(6*6.23+10.48*13)/C40 | G40: =C40*8 | H40: 79.98 | I40: =E40*0.025 | J40: =F40*C40+G40-H40-I40 | K40: =J40/E40 | L40: =J40*8 | M40: =E40*8 | N40: =H40/E40 | O40: 5 | P40: =C40-O40 | Q40: =O40/C40 | R40: =H40/(E40*Q40)
B41: ES | C41: 16 | D41: 59.35 | E41: =C41*D41 | F41: =(6*6.78+11.3*10)/C41 | G41: =C41*8 | H41: 96.84 | I41: =E41*0.025 | J41: =F41*C41+G41-H41-I41 | K41: =J41/E41 | L41: =J41*8 | M41: =E41*8 | N41: =H41/E41 | O41: 4 | P41: =C41-O41 | Q41: =O41/C41 | R41: =H41/(E41*Q41)
B42: UK | C42: 7 | D42: 80.61 | E42: =C42*D42 | F42: 21 | G42: =C42*10 | H42: 39.46 | I42: =E42*0.025 | J42: =F42*C42+G42-H42-I42 | K42: =J42/E42 | L42: =J42*9 | M42: =E42*9 | N42: =H42/E42 | O42: 2 | P42: =C42-O42 | Q42: =O42/C42 | R42: =H42/(E42*Q42)
B43: US | C43: 25 | D43: 49.99 | E43: =C43*D43 | F43: 6.43 | H43: 132.78 | I43: 25 | J43: =C43*F43-H43-I43 | K43: =J43/E43 | L43: =J43*7 | M43: =E43*7 | N43: =H43/E43 | O43: 14 | P43: =C43-O43 | Q43: =O43/C43 | R43: =H43/(E43*Q43)
B44: 汇总 | C44: =SUM(C38:C43) | K44: =L44/M44 | L44: =SUM(L38:L43) | M44: =SUM(M38:M43) | O44: =SUM(O38:O43) | P44: =C44-O44 | Q44: =O44/C44
A46: 时间 | B46: 国家 | C46: 数量 | D46: 售价 | E46: 销售额 | F46: 单个毛利 | G46: 广告预算 | H46: 实际广告 | I46: 活动费 | J46: 毛利 | K46: 毛利率 | L46: 毛利(RMB) | M46: 销售额(RMB) | N46: 广告占比 | O46: 广告订单 | P46: 自然订单 | Q46: 广告订单占比 | R46: ACOS
A47: 45850 | B47: DE | D47: 55.85 | E47: =C47*D47 | F47: 10.5 | G47: =C47*8 | I47: =E47*0.025 | J47: =F47*C47+G47-H47-I47 | K47: =J47/E47 | L47: =J47*8 | M47: =E47*8 | N47: =H47/E47 | P47: =C47-O47 | Q47: =O47/C47 | R47: =H47/(E47*Q47)
B48: FR | D48: 58 | E48: =C48*D48 | F48: -1.7 | G48: =C48*8 | I48: =E48*0.025 | J48: =F48*C48+G48-H48-I48 | K48: =J48/E48 | L48: =J48*8 | M48: =E48*8 | N48: =H48/E48 | P48: =C48-O48 | Q48: =O48/C48 | R48: =H48/(E48*Q48)
B49: IT | D49: 58.8 | E49: =C49*D49 | F49: 10.48 | G49: =C49*8 | I49: =E49*0.025 | J49: =F49*C49+G49-H49-I49 | K49: =J49/E49 | L49: =J49*8 | M49: =E49*8 | N49: =H49/E49 | P49: =C49-O49 | Q49: =O49/C49 | R49: =H49/(E49*Q49)
B50: ES | D50: 59.35 | E50: =C50*D50 | F50: 11.3 | G50: =C50*8 | I50: =E50*0.025 | J50: =F50*C50+G50-H50-I50 | K50: =J50/E50 | L50: =J50*8 | M50: =E50*8 | N50: =H50/E50 | P50: =C50-O50 | Q50: =O50/C50 | R50: =H50/(E50*Q50)
B51: UK | D51: 55.3 | E51: =C51*D51 | F51: 17.8 | G51: =C51*8 | J51: =F51*C51+G51-H51-I51 | K51: =J51/E51 | L51: =J51*9 | M51: =E51*9 | N51: =H51/E51 | P51: =C51-O51 | Q51: =O51/C51 | R51: =H51/(E51*Q51)
B52: US | D52: 49.99 | E52: =C52*D52 | F52: 6.43 | J52: =C52*F52-H52-I52 | K52: =J52/E52 | L52: =J52*7 | M52: =E52*7 | N52: =H52/E52 | P52: =C52-O52 | Q52: =O52/C52 | R52: =H52/(E52*Q52)
B53: 汇总 | C53: =SUM(C47:C52) | K53: =L53/M53 | L53: =SUM(L47:L52) | M53: =SUM(M47:M52) | O53: =SUM(O47:O52) | P53: =C53-O53 | Q53: =O53/C53

Sheet SKU001MV2501
A1: 汇总 | B1: 国家 | C1: 数量 | D1: 售价 | E1: 销售额 | F1: 毛利 | G1: 广告预算 | H1: 实际广告 | I1: 活动费 | J1: 毛利 | K1: 毛利率 | L1: 毛利(RMB) | M1: 销售额(RMB) | N1: 广告占比 | O1: 广告订单 | P1: 自然订单 | Q1: 广告订单占比 | R1: ACOS | S1: 折扣
A2: 开始时间 | B2: DE | C2: =SUMIFS($C$10:$C$3498,$B$10:$B$3498,B2,$A$10:$A$3498,">="&$A$3,$A$10:$A$3498,"<="&$A$5) | D2: 55.85 | E2: =SUMIFS($E$10:$E$3498,$B$10:$B$3498,B2,$A$10:$A$3498,">="&$A$3,$A$10:$A$3498,"<="&$A$5) | G2: =SUMIFS($G$10:$G$3498,$B$10:$B$3498,B2,$A$10:$A$3498,">="&$A$3,$A$10:$A$3498,"<="&$A$5) | H2: =SUMIFS($H$10:$H$3498,$B$10:$B$3498,B2,$A$10:$A$3498,">="&$A$3,$A$10:$A$3498,"<="&$A$5) | I2: =SUMIFS($I$10:$I$3498,$B$10:$B$3498,B2,$A$10:$A$3498,">="&$A$3,$A$10:$A$3498,"<="&$A$5) | J2: =SUMIFS($J$10:$J$3498,$B$10:$B$3498,B2,$A$10:$A$3498,">="&$A$3,$A$10:$A$3498,"<="&$A$5) | K2: =J2/E2 | L2: =SUMIFS($L$10:$L$3498,$B$10:$B$3498,B2,$A$10:$A$3498,">="&$A$3,$A$10:$A$3498,"<="&$A$5) | M2: =SUMIFS($M$10:$M$3498,$B$10:$B$3498,B2,$A$10:$A$3498,">="&$A$3,$A$10:$A$3498,"<="&$A$5) | N2: =H2/E2 | O2: =SUMIFS($O$10:$O$3498,$B$10:$B$3498,B2,$A$10:$A$3498,">="&$A$3,$A$10:$A$3498,"<="&$A$5) | P2: =C2-O2 | Q2: =O2/C2 | R2: =H2/(E2*Q2)
A3: 46082 | B3: FR | C3: =SUMIFS($C$10:$C$3498,$B$10:$B$3498,B3,$A$10:$A$3498,">="&$A$3,$A$10:$A$3498,"<="&$A$5) | D3: 58 | E3: =SUMIFS($E$10:$E$3498,$B$10:$B$3498,B3,$A$10:$A$3498,">="&$A$3,$A$10:$A$3498,"<="&$A$5) | G3: =SUMIFS($G$10:$G$3498,$B$10:$B$3498,B3,$A$10:$A$3498,">="&$A$3,$A$10:$A$3498,"<="&$A$5) | H3: =SUMIFS($H$10:$H$3498,$B$10:$B$3498,B3,$A$10:$A$3498,">="&$A$3,$A$10:$A$3498,"<="&$A$5) | I3: =SUMIFS($I$10:$I$3498,$B$10:$B$3498,B3,$A$10:$A$3498,">="&$A$3,$A$10:$A$3498,"<="&$A$5) | J3: =SUMIFS($J$10:$J$3498,$B$10:$B$3498,B3,$A$10:$A$3498,">="&$A$3,$A$10:$A$3498,"<="&$A$5) | K3: =J3/E3 | L3: =SUMIFS($L$10:$L$3498,$B$10:$B$3498,B3,$A$10:$A$3498,">="&$A$3,$A$10:$A$3498,"<="&$A$5) | M3: =SUMIFS($M$10:$M$3498,$B$10:$B$3498,B3,$A$10:$A$3498,">="&$A$3,$A$10:$A$3498,"<="&$A$5) | N3: =H3/E3 | O3: =SUMIFS($O$10:$O$3498,$B$10:$B$3498,B3,$A$10:$A$3498,">="&$A$3,$A$10:$A$3498,"<="&$A$5) | P3: =C3-O3 | Q3: =O3/C3 | R3: =H3/(E3*Q3)
A4: 结束时间 | B4: IT | C4: =SUMIFS($C$10:$C$3498,$B$10:$B$3498,B4,$A$10:$A$3498,">="&$A$3,$A$10:$A$3498,"<="&$A$5) | D4: 58.8 | E4: =SUMIFS($E$10:$E$3498,$B$10:$B$3498,B4,$A$10:$A$3498,">="&$A$3,$A$10:$A$3498,"<="&$A$5) | G4: =SUMIFS($G$10:$G$3498,$B$10:$B$3498,B4,$A$10:$A$3498,">="&$A$3,$A$10:$A$3498,"<="&$A$5) | H4: =SUMIFS($H$10:$H$3498,$B$10:$B$3498,B4,$A$10:$A$3498,">="&$A$3,$A$10:$A$3498,"<="&$A$5) | I4: =SUMIFS($I$10:$I$3498,$B$10:$B$3498,B4,$A$10:$A$3498,">="&$A$3,$A$10:$A$3498,"<="&$A$5) | J4: =SUMIFS($J$10:$J$3498,$B$10:$B$3498,B4,$A$10:$A$3498,">="&$A$3,$A$10:$A$3498,"<="&$A$5) | K4: =J4/E4 | L4: =SUMIFS($L$10:$L$3498,$B$10:$B$3498,B4,$A$10:$A$3498,">="&$A$3,$A$10:$A$3498,"<="&$A$5) | M4: =SUMIFS($M$10:$M$3498,$B$10:$B$3498,B4,$A$10:$A$3498,">="&$A$3,$A$10:$A$3498,"<="&$A$5) | N4: =H4/E4 | O4: =SUMIFS($O$10:$O$3498,$B$10:$B$3498,B4,$A$10:$A$3498,">="&$A$3,$A$10:$A$3498,"<="&$A$5) | P4: =C4-O4 | Q4: =O4/C4 | R4: =H4/(E4*Q4)
A5: 46112 | B5: ES | C5: =SUMIFS($C$10:$C$3498,$B$10:$B$3498,B5,$A$10:$A$3498,">="&$A$3,$A$10:$A$3498,"<="&$A$5) | D5: 59.35 | E5: =SUMIFS($E$10:$E$3498,$B$10:$B$3498,B5,$A$10:$A$3498,">="&$A$3,$A$10:$A$3498,"<="&$A$5) | G5: =SUMIFS($G$10:$G$3498,$B$10:$B$3498,B5,$A$10:$A$3498,">="&$A$3,$A$10:$A$3498,"<="&$A$5) | H5: =SUMIFS($H$10:$H$3498,$B$10:$B$3498,B5,$A$10:$A$3498,">="&$A$3,$A$10:$A$3498,"<="&$A$5) | I5: =SUMIFS($I$10:$I$3498,$B$10:$B$3498,B5,$A$10:$A$3498,">="&$A$3,$A$10:$A$3498,"<="&$A$5) | J5: =SUMIFS($J$10:$J$3498,$B$10:$B$3498,B5,$A$10:$A$3498,">="&$A$3,$A$10:$A$3498,"<="&$A$5) | K5: =J5/E5 | L5: =SUMIFS($L$10:$L$3498,$B$10:$B$3498,B5,$A$10:$A$3498,">="&$A$3,$A$10:$A$3498,"<="&$A$5) | M5: =SUMIFS($M$10:$M$3498,$B$10:$B$3498,B5,$A$10:$A$3498,">="&$A$3,$A$10:$A$3498,"<="&$A$5) | N5: =H5/E5 | O5: =SUMIFS($O$10:$O$3498,$B$10:$B$3498,B5,$A$10:$A$3498,">="&$A$3,$A$10:$A$3498,"<="&$A$5) | P5: =C5-O5 | Q5: =O5/C5 | R5: =H5/(E5*Q5)
A6: 即日 | B6: UK | C6: =SUMIFS($C$10:$C$3498,$B$10:$B$3498,B6,$A$10:$A$3498,">="&$A$3,$A$10:$A$3498,"<="&$A$5) | D6: 55.3 | E6: =SUMIFS($E$10:$E$3498,$B$10:$B$3498,B6,$A$10:$A$3498,">="&$A$3,$A$10:$A$3498,"<="&$A$5) | G6: =SUMIFS($G$10:$G$3498,$B$10:$B$3498,B6,$A$10:$A$3498,">="&$A$3,$A$10:$A$3498,"<="&$A$5) | H6: =SUMIFS($H$10:$H$3498,$B$10:$B$3498,B6,$A$10:$A$3498,">="&$A$3,$A$10:$A$3498,"<="&$A$5) | I6: =SUMIFS($I$10:$I$3498,$B$10:$B$3498,B6,$A$10:$A$3498,">="&$A$3,$A$10:$A$3498,"<="&$A$5) | J6: =SUMIFS($J$10:$J$3498,$B$10:$B$3498,B6,$A$10:$A$3498,">="&$A$3,$A$10:$A$3498,"<="&$A$5) | K6: =J6/E6 | L6: =SUMIFS($L$10:$L$3498,$B$10:$B$3498,B6,$A$10:$A$3498,">="&$A$3,$A$10:$A$3498,"<="&$A$5) | M6: =SUMIFS($M$10:$M$3498,$B$10:$B$3498,B6,$A$10:$A$3498,">="&$A$3,$A$10:$A$3498,"<="&$A$5) | N6: =H6/E6 | O6: =SUMIFS($O$10:$O$3498,$B$10:$B$3498,B6,$A$10:$A$3498,">="&$A$3,$A$10:$A$3498,"<="&$A$5) | P6: =C6-O6 | Q6: =O6/C6 | R6: =H6/(E6*Q6)
A7: =NOW() | B7: US | C7: =SUMIFS($C$10:$C$3498,$B$10:$B$3498,B7,$A$10:$A$3498,">="&$A$3,$A$10:$A$3498,"<="&$A$5) | D7: 49.99 | E7: =SUMIFS($E$10:$E$3498,$B$10:$B$3498,B7,$A$10:$A$3498,">="&$A$3,$A$10:$A$3498,"<="&$A$5) | G7: =SUMIFS($G$10:$G$3498,$B$10:$B$3498,B7,$A$10:$A$3498,">="&$A$3,$A$10:$A$3498,"<="&$A$5) | H7: =SUMIFS($H$10:$H$3498,$B$10:$B$3498,B7,$A$10:$A$3498,">="&$A$3,$A$10:$A$3498,"<="&$A$5) | I7: =SUMIFS($I$10:$I$3498,$B$10:$B$3498,B7,$A$10:$A$3498,">="&$A$3,$A$10:$A$3498,"<="&$A$5) | J7: =SUMIFS($J$10:$J$3498,$B$10:$B$3498,B7,$A$10:$A$3498,">="&$A$3,$A$10:$A$3498,"<="&$A$5) | K7: =J7/E7 | L7: =SUMIFS($L$10:$L$3498,$B$10:$B$3498,B7,$A$10:$A$3498,">="&$A$3,$A$10:$A$3498,"<="&$A$5) | M7: =SUMIFS($M$10:$M$3498,$B$10:$B$3498,B7,$A$10:$A$3498,">="&$A$3,$A$10:$A$3498,"<="&$A$5) | N7: =H7/E7 | O7: =SUMIFS($O$10:$O$3498,$B$10:$B$3498,B7,$A$10:$A$3498,">="&$A$3,$A$10:$A$3498,"<="&$A$5) | P7: =C7-O7 | Q7: =O7/C7 | R7: =H7/(E7*Q7)
B8: 汇总 | C8: =SUM(C2:C7) | K8: =L8/M8 | L8: =SUM(L2:L7) | M8: =SUM(M2:M7) | O8: =SUM(O2:O7) | P8: =C8-O8 | Q8: =O8/C8
B9: 分割线
A10: 时间 | B10: 国家 | C10: 数量 | D10: 售价 | E10: 销售额 | F10: 毛利 | G10: 广告预算 | H10: 实际广告 | I10: 活动费 | J10: 毛利 | K10: 毛利率 | L10: 毛利(RMB) | M10: 销售额(RMB) | N10: 广告占比 | O10: 广告订单 | P10: 自然订单 | Q10: 广告订单占比 | R10: ACOS | S10: COUPON
A11: 46019 | B11: DE | D11: 55.85 | E11: 0 | F11: 15.78 | G11: 0 | I11: 0 | J11: 0 | K11: 0 | L11: 0 | M11: 0 | N11: 0 | P11: 0 | Q11: 0 | R11: 0 | S11: VC-0%
A12: 46019 | B12: FR | D12: 58 | E12: 0 | F12: 15.88 | G12: 0 | I12: 0 | J12: 0 | K12: 0 | L12: 0 | M12: 0 | N12: 0 | P12: 0 | Q12: 0 | R12: 0 | S12: VC-0%
A13: 46019 | B13: IT | C13: 1 | D13: 58.8 | E13: 58.8 | F13: 16.27 | G13: 8 | I13: 1.47 | J13: 22.8 | K13: 0.3877551 | L13: 182.4 | M13: 470.4 | N13: 0 | P13: 1 | Q13: 0 | R13: 0 | S13: VC-0%
A14: 46019 | B14: ES | D14: 59.35 | E14: 0 | F14: 15.72 | G14: 0 | I14: 0 | J14: 0 | K14: 0 | L14: 0 | M14: 0 | N14: 0 | P14: 0 | Q14: 0 | R14: 0 | S14: VC-0%
A15: 46019 | B15: UK | C15: 1 | D15: 52.3 | E15: 52.3 | F15: 14.72 | G15: 8 | H15: 14.18 | I15: 1.3075 | J15: 7.2325 | K15: 0.13828872 | L15: 65.0925 | M15: 470.7 | N15: 0.27112811 | O15: 0 | P15: 1 | Q15: 0 | R15: 0 | S15: VC-0%
A16: 46019 | B16: 汇总 | C16: 2 | E16: 111.1 | F16: 78.37 | J16: 30.0325 | K16: 0.27031953 | L16: 247.4925 | M16: 941.1 | O16: 0 | P16: 2 | Q16: 0
B17: 分割线
A18: 时间 | B18: 国家 | C18: 数量 | D18: 售价 | E18: 销售额 | F18: 毛利 | G18: 广告预算 | H18: 实际广告 | I18: 活动费 | J18: 毛利 | K18: 毛利率 | L18: 毛利(RMB) | M18: 销售额(RMB) | N18: 广告占比 | O18: 广告订单 | P18: 自然订单 | Q18: 广告订单占比 | R18: ACOS | S18: COUPON
A19: 46020 | B19: DE | D19: 55.85 | E19: 0 | F19: 15.78 | G19: 0 | I19: 0 | J19: 0 | K19: 0 | L19: 0 | M19: 0 | N19: 0 | P19: 0 | Q19: 0 | R19: 0 | S19: VC-0%
A20: 46020 | B20: FR | D20: 58 | E20: 0 | F20: 15.88 | G20: 0 | I20: 0 | J20: 0 | K20: 0 | L20: 0 | M20: 0 | N20: 0 | P20: 0 | Q20: 0 | R20: 0 | S20: VC-0%
A21: 46020 | B21: IT | D21: 58.8 | E21: 0 | F21: 16.27 | G21: 0 | I21: 0 | J21: 0 | K21: 0 | L21: 0 | M21: 0 | N21: 0 | P21: 0 | Q21: 0 | R21: 0 | S21: VC-0%
A22: 46020 | B22: ES | D22: 59.35 | E22: 0 | F22: 15.72 | G22: 0 | I22: 0 | J22: 0 | K22: 0 | L22: 0 | M22: 0 | N22: 0 | P22: 0 | Q22: 0 | R22: 0 | S22: VC-0%
A23: 46020 | B23: UK | C23: 3 | D23: 52.3 | E23: 156.9 | F23: 5.6 | G23: 24 | H23: 15.72 | I23: 3.9225 | J23: 21.1575 | K23: 0.13484704 | L23: 190.4175 | M23: 1412.1 | N23: 0.1001912 | O23: 0 | P23: 3 | Q23: 0 | R23: 0 | S23: VC-12%
A24: 46020 | B24: 汇总 | C24: 3 | E24: 156.9 | F24: 69.25 | J24: 21.1575 | K24: 0.13484704 | L24: 190.4175 | M24: 1412.1 | O24: 0 | P24: 3 | Q24: 0
B25: 分割线
A26: 时间 | B26: 国家 | C26: 数量 | D26: 售价 | E26: 销售额 | F26: 毛利 | G26: 广告预算 | H26: 实际广告 | I26: 活动费 | J26: 毛利 | K26: 毛利率 | L26: 毛利(RMB) | M26: 销售额(RMB) | N26: 广告占比 | O26: 广告订单 | P26: 自然订单 | Q26: 广告订单占比 | R26: ACOS | S26: COUPON
A27: 46021 | B27: DE | C27: 2 | D27: 55.85 | E27: 111.7 | F27: 15.78 | G27: 16 | I27: 2.7925 | J27: 44.7675 | K27: 0.40078335 | L27: 358.14 | M27: 893.6 | N27: 0 | P27: 2 | Q27: 0 | R27: 0 | S27: VC-0%
A28: 46021 | B28: FR | D28: 58 | E28: 0 | F28: 15.88 | G28: 0 | I28: 0 | J28: 0 | K28: 0 | L28: 0 | M28: 0 | N28: 0 | P28: 0 | Q28: 0 | R28: 0 | S28: VC-0%
A29: 46021 | B29: IT | D29: 58.8 | E29: 0 | F29: 16.27 | G29: 0 | I29: 0 | J29: 0 | K29: 0 | L29: 0 | M29: 0 | N29: 0 | P29: 0 | Q29: 0 | R29: 0 | S29: VC-0%
A30: 46021 | B30: ES | D30: 59.35 | E30: 0 | F30: 15.72 | G30: 0 | I30: 0 | J30: 0 | K30: 0 | L30: 0 | M30: 0 | N30: 0 | P30: 0 | Q30: 0 | R30: 0 | S30: VC-0%
A31: 46021 | B31: UK | C31: 3 | D31: 52.3 | E31: 156.9 | F31: 5.6 | G31: 24 | H31: 10.36 | I31: 3.9225 | J31: 26.5175 | K31: 0.16900892 | L31: 238.6575 | M31: 1412.1 | N31: 0.066029318 | O31: 2 | P31: 1 | Q31: 0.66666667 | R31: 0.099043977 | S31: VC-12%
A32: 46021 | B32: 汇总 | C32: 5 | E32: 268.6 | F32: 69.25 | J32: 71.285 | K32: 0.26539464 | L32: 596.7975 | M32: 2305.7 | O32: 2 | P32: 3 | Q32: 0.4
B33: 分割线
A34: 时间 | B34: 国家 | C34: 数量 | D34: 售价 | E34: 销售额 | F34: 毛利 | G34: 广告预算 | H34: 实际广告 | I34: 活动费 | J34: 毛利 | K34: 毛利率 | L34: 毛利(RMB) | M34: 销售额(RMB) | N34: 广告占比 | O34: 广告订单 | P34: 自然订单 | Q34: 广告订单占比 | R34: ACOS | S34: COUPON
A35: 46022 | B35: DE | D35: 55.85 | E35: 0 | F35: 15.78 | G35: 0 | H35: 0 | I35: 0 | J35: 0 | K35: 0 | L35: 0 | M35: 0 | N35: 0 | O35: 0 | P35: 0 | Q35: 0 | R35: 0 | S35: VC-0%
A36: 46022 | B36: FR | D36: 58 | E36: 0 | F36: 15.88 | G36: 0 | I36: 0 | J36: 0 | K36: 0 | L36: 0 | M36: 0 | N36: 0 | P36: 0 | Q36: 0 | R36: 0 | S36: VC-0%
A37: 46022 | B37: IT | C37: 1 | D37: 58.8 | E37: 58.8 | F37: 16.27 | G37: 8 | I37: 1.47 | J37: 22.8 | K37: 0.3877551 | L37: 182.4 | M37: 470.4 | N37: 0 | P37: 1 | Q37: 0 | R37: 0 | S37: VC-0%
A38: 46022 | B38: ES | C38: 1 | D38: 59.35 | E38: 59.35 | F38: 15.72 | G38: 8 | H38: 0.27 | I38: 1.48375 | J38: 21.96625 | K38: 0.37011373 | L38: 175.73 | M38: 474.8 | N38: 0.0045492839 | O38: 0 | P38: 1 | Q38: 0 | R38: 0 | S38: VC-0%
A39: 46022 | B39: UK | C39: 1 | D39: 52.3 | E39: 52.3 | F39: 14.72 | G39: 8 | H39: 12.88 | I39: 1.3075 | J39: 8.5325 | K39: 0.16314532 | L39: 76.7925 | M39: 470.7 | N39: 0.24627151 | O39: 0 | P39: 1 | Q39: 0 | R39: 0 | S39: VC-0%
A40: 46022 | B40: 汇总 | C40: 3 | E40: 170.45 | F40: 78.37 | J40: 53.29875 | K40: 0.31269434 | L40: 434.9225 | M40: 1415.9 | O40: 0 | P40: 3 | Q40: 0
B41: 分割线
A42: 时间 | B42: 国家 | C42: 数量 | D42: 售价 | E42: 销售额 | F42: 毛利 | G42: 广告预算 | H42: 实际广告 | I42: 活动费 | J42: 毛利 | K42: 毛利率 | L42: 毛利(RMB) | M42: 销售额(RMB) | N42: 广告占比 | O42: 广告订单 | P42: 自然订单 | Q42: 广告订单占比 | R42: ACOS | S42: COUPON
A43: 46023 | B43: DE | C43: 1 | D43: 55.85 | E43: 55.85 | F43: 15.78 | G43: 8 | H43: 0 | I43: 1.39625 | J43: 22.38375 | K43: 0.40078335 | L43: 179.07 | M43: 446.8 | N43: 0 | O43: 0 | P43: 1 | Q43: 0 | R43: 0 | S43: VC-0%
A44: 46023 | B44: FR | C44: 0 | D44: 58 | E44: 0 | F44: 15.88 | G44: 0 | I44: 0 | J44: 0 | K44: 0 | L44: 0 | M44: 0 | N44: 0 | P44: 0 | Q44: 0 | R44: 0 | S44: VC-0%
A45: 46023 | B45: IT | C45: 1 | D45: 58.8 | E45: 58.8 | F45: 16.27 | G45: 8 | H45: 0 | I45: 1.47 | J45: 22.8 | K45: 0.3877551 | L45: 182.4 | M45: 470.4 | N45: 0 | O45: 0 | P45: 1 | Q45: 0 | R45: 0 | S45: VC-0%
A46: 46023 | B46: ES | C46: 1 | D46: 59.35 | E46: 59.35 | F46: 15.72 | G46: 8 | H46: 0 | I46: 1.48375 | J46: 22.23625 | K46: 0.37466302 | L46: 177.89 | M46: 474.8 | N46: 0 | O46: 0 | P46: 1 | Q46: 0 | R46: 0 | S46: VC-0%
A47: 46023 | B47: UK | C47: 2 | D47: 52.3 | E47: 104.6 | F47: 14.72 | G47: 16 | H47: 14.28 | I47: 2.615 | J47: 28.545 | K47: 0.27289675 | L47: 256.905 | M47: 941.4 | N47: 0.13652008 | O47: 3 | P47: -1 | Q47: 1.5 | R47: 0.091013384 | S47: VC-0%
A48: 46023 | B48: 汇总 | C48: 5 | E48: 278.6 | F48: 78.37 | J48: 95.965 | K48: 0.34445441 | L48: 796.265 | M48: 2333.4 | O48: 3 | P48: 2 | Q48: 0.6
B49: 分割线
A50: 时间 | B50: 国家 | C50: 数量 | D50: 售价 | E50: 销售额 | F50: 毛利 | G50: 广告预算 | H50: 实际广告 | I50: 活动费 | J50: 毛利 | K50: 毛利率 | L50: 毛利(RMB) | M50: 销售额(RMB) | N50: 广告占比 | O50: 广告订单 | P50: 自然订单 | Q50: 广告订单占比 | R50: ACOS | S50: COUPON
A51: 46024 | B51: DE | C51: 1 | D51: 55.85 | E51: 55.85 | F51: 15.78 | G51: 8 | H51: 0 | I51: 1.39625 | J51: 22.38375 | K51: 0.40078335 | L51: 179.07 | M51: 446.8 | N51: 0 | O51: 0 | P51: 1 | Q51: 0 | R51: 0 | S51: VC-0%
A52: 46024 | B52: FR | C52: 0 | D52: 58 | E52: 0 | F52: 15.88 | G52: 0 | I52: 0 | J52: 0 | K52: 0 | L52: 0 | M52: 0 | N52: 0 | P52: 0 | Q52: 0 | R52: 0 | S52: VC-0%
A53: 46024 | B53: IT | C53: 0 | D53: 58.8 | E53: 0 | F53: 16.27 | G53: 0 | H53: 0 | I53: 0 | J53: 0 | K53: 0 | L53: 0 | M53: 0 | N53: 0 | O53: 0 | P53: 0 | Q53: 0 | R53: 0 | S53: VC-0%
A54: 46024 | B54: ES | C54: 1 | D54: 59.35 | E54: 59.35 | F54: 15.72 | G54: 8 | H54: 0.51 | I54: 1.48375 | J54: 21.72625 | K54: 0.36606992 | L54: 173.81 | M54: 474.8 | N54: 0.0085930918 | O54: 0 | P54: 1 | Q54: 0 | R54: 0 | S54: VC-0%
A55: 46024 | B55: UK | C55: 3 | D55: 52.3 | E55: 156.9 | F55: 14.72 | G55: 24 | H55: 17.64 | I55: 3.9225 | J55: 46.5975 | K55: 0.29698853 | L55: 419.3775 | M55: 1412.1 | N55: 0.1124283 | O55: 1 | P55: 2 | Q55: 0.33333333 | R55: 0.33728489 | S55: VC-0%
A56: 46024 | B56: 汇总 | C56: 5 | E56: 272.1 | F56: 78.37 | J56: 90.7075 | K56: 0.3333609 | L56: 772.2575 | M56: 2333.7 | O56: 1 | P56: 4 | Q56: 0.2
B57: 分割线
A58: 时间 | B58: 国家 | C58: 数量 | D58: 售价 | E58: 销售额 | F58: 毛利 | G58: 广告预算 | H58: 实际广告 | I58: 活动费 | J58: 毛利 | K58: 毛利率 | L58: 毛利(RMB) | M58: 销售额(RMB) | N58: 广告占比 | O58: 广告订单 | P58: 自然订单 | Q58: 广告订单占比 | R58: ACOS | S58: COUPON
A59: 46025 | B59: DE | C59: 4 | D59: 55.85 | E59: 223.4 | F59: 15.78 | G59: 32 | H59: 63.98 | I59: 5.585 | J59: 25.555 | K59: 0.11439123 | L59: 204.44 | M59: 1787.2 | N59: 0.28639212 | O59: 3 | P59: 1 | Q59: 0.75 | R59: 0.38185616 | S59: VC-0%
A60: 46025 | B60: FR | C60: 0 | D60: 58 | E60: 0 | F60: 15.88 | G60: 0 | I60: 0 | J60: 0 | K60: 0 | L60: 0 | M60: 0 | N60: 0 | P60: 0 | Q60: 0 | R60: 0 | S60: VC-0%
A61: 46025 | B61: IT | C61: 0 | D61: 58.8 | E61: 0 | F61: 16.27 | G61: 0 | H61: 0 | I61: 0 | J61: 0 | K61: 0 | L61: 0 | M61: 0 | N61: 0 | O61: 0 | P61: 0 | Q61: 0 | R61: 0 | S61: VC-0%
A62: 46025 | B62: ES | C62: 1 | D62: 59.35 | E62: 59.35 | F62: 15.72 | G62: 8 | H62: 0.49 | I62: 1.48375 | J62: 21.74625 | K62: 0.36640691 | L62: 173.97 | M62: 474.8 | N62: 0.0082561078 | O62: 0 | P62: 1 | Q62: 0 | R62: 0 | S62: VC-0%
A63: 46025 | B63: UK | C63: 0 | D63: 52.3 | E63: 0 | F63: 14.72 | G63: 0 | H63: 11.92 | I63: 0 | J63: -11.92 | K63: 0 | L63: -107.28 | M63: 0 | N63: 0 | O63: 0 | P63: 0 | Q63: 0 | R63: 0 | S63: VC-0%
A64: 46025 | B64: 汇总 | C64: 5 | E64: 282.75 | F64: 63.65 | J64: 47.30125 | K64: 0.16729001 | L64: 378.41 | M64: 2262 | O64: 3 | P64: 2 | Q64: 0.6
B65: 分割线
A66: 时间 | B66: 国家 | C66: 数量 | D66: 售价 | E66: 销售额 | F66: 毛利 | G66: 广告预算 | H66: 实际广告 | I66: 活动费 | J66: 毛利 | K66: 毛利率 | L66: 毛利(RMB) | M66: 销售额(RMB) | N66: 广告占比 | O66: 广告订单 | P66: 自然订单 | Q66: 广告订单占比 | R66: ACOS | S66: COUPON
A67: 46026 | B67: DE | C67: 6 | D67: 55.85 | E67: 335.1 | F67: 15.78 | G67: 48 | H67: 82.26 | I67: 8.3775 | J67: 52.0425 | K67: 0.15530439 | L67: 416.34 | M67: 2680.8 | N67: 0.24547896 | O67: 4 | P67: 2 | Q67: 0.66666667 | R67: 0.36821844 | S67: VC-0%
A68: 46026 | B68: FR | C68: 2 | D68: 58 | E68: 116 | F68: 3.13 | G68: 16 | H68: 2.25 | I68: 2.9 | J68: 17.11 | K68: 0.1475 | L68: 136.88 | M68: 928 | N68: 0.019396552 | O68: 2 | P68: 0 | Q68: 1 | R68: 0.019396552 | S68: VC-15%
A69: 46026 | B69: IT | C69: 0 | D69: 58.8 | E69: 0 | F69: 16.27 | G69: 0 | H69: 50.73 | I69: 0 | J69: -50.73 | K69: 0 | L69: -405.84 | M69: 0 | N69: 0 | O69: 1 | P69: -1 | Q69: 0 | R69: 0 | S69: VC-0%
A70: 46026 | B70: ES | C70: 1 | D70: 59.35 | E70: 59.35 | F70: 15.72 | G70: 8 | H70: 0 | I70: 1.48375 | J70: 22.23625 | K70: 0.37466302 | L70: 177.89 | M70: 474.8 | N70: 0 | O70: 0 | P70: 1 | Q70: 0 | R70: 0 | S70: VC-0%
A71: 46026 | B71: UK | C71: 2 | D71: 52.3 | E71: 104.6 | F71: 14.72 | G71: 16 | H71: 14.88 | I71: 2.615 | J71: 27.945 | K71: 0.26716061 | L71: 251.505 | M71: 941.4 | N71: 0.14225621 | O71: 1 | P71: 1 | Q71: 0.5 | R71: 0.28451243 | S71: VC-0%
A72: 46026 | B72: 汇总 | C72: 11 | E72: 279.95 | F72: 49.84 | J72: 16.56125 | K72: 0.059157885 | L72: 160.435 | M72: 2344.2 | O72: 4 | P72: 7 | Q72: 0.36363636
B73: 分割线
A74: 时间 | B74: 国家 | C74: 数量 | D74: 售价 | E74: 销售额 | F74: 毛利 | G74: 广告预算 | H74: 实际广告 | I74: 活动费 | J74: 毛利 | K74: 毛利率 | L74: 毛利(RMB) | M74: 销售额(RMB) | N74: 广告占比 | O74: 广告订单 | P74: 自然订单 | Q74: 广告订单占比 | R74: ACOS | S74: COUPON
A75: 46027 | B75: DE | C75: 5 | D75: 55.85 | E75: 279.25 | F75: 15.78 | G75: 40 | H75: 63.98 | I75: 6.98125 | J75: 47.93875 | K75: 0.17166965 | L75: 383.51 | M75: 2234 | N75: 0.2291137 | O75: 6 | P75: -1 | Q75: 1.2 | R75: 0.19092808 | S75: VC-0%
A76: 46027 | B76: FR | C76: 3 | D76: 58 | E76: 174 | F76: 3.13 | G76: 24 | H76: 2.93 | I76: 4.35 | J76: 26.11 | K76: 0.15005747 | L76: 208.88 | M76: 1392 | N76: 0.01683908 | O76: 1 | P76: 2 | Q76: 0.33333333 | R76: 0.050517241 | S76: VC-15%
A77: 46027 | B77: IT | C77: 1 | D77: 58.8 | E77: 58.8 | F77: 16.27 | G77: 8 | H77: 26.06 | I77: 1.47 | J77: -3.26 | K77: -0.055442177 | L77: -26.08 | M77: 470.4 | N77: 0.44319728 | O77: 0 | P77: 1 | Q77: 0 | R77: 0 | S77: VC-0%
A78: 46027 | B78: ES | C78: 1 | D78: 59.35 | E78: 59.35 | F78: 15.72 | G78: 8 | H78: 11.08 | I78: 1.48375 | J78: 11.15625 | K78: 0.18797388 | L78: 89.25 | M78: 474.8 | N78: 0.18668913 | O78: 1 | P78: 0 | Q78: 1 | R78: 0.18668913 | S78: VC-0%
A79: 46027 | B79: UK | C79: 0 | D79: 52.3 | E79: 0 | F79: 14.72 | G79: 0 | H79: 13.6 | I79: 0 | J79: -13.6 | K79: 0 | L79: -122.4 | M79: 0 | N79: 0 | O79: 0 | P79: 0 | Q79: 0 | R79: 0 | S79: VC-0%
A80: 46027 | B80: 汇总 | C80: 10 | E80: 571.4 | F80: 65.62 | J80: 68.345 | K80: 0.11960973 | L80: 533.16 | M80: 4571.2 | O80: 8 | P80: 2 | Q80: 0.8
B81: 分割线
A82: 时间 | B82: 国家 | C82: 数量 | D82: 售价 | E82: 销售额 | F82: 毛利 | G82: 广告预算 | H82: 实际广告 | I82: 活动费 | J82: 毛利 | K82: 毛利率 | L82: 毛利(RMB) | M82: 销售额(RMB) | N82: 广告占比 | O82: 广告订单 | P82: 自然订单 | Q82: 广告订单占比 | R82: ACOS | S82: COUPON
A83: 46028 | B83: DE | C83: 8 | D83: 55.85 | E83: 446.8 | F83: 15.78 | G83: 64 | H83: 104.96 | I83: 11.17 | J83: 74.11 | K83: 0.1658684 | L83: 592.88 | M83: 3574.4 | N83: 0.23491495 | O83: 6 | P83: 2 | Q83: 0.75 | R83: 0.31321993 | S83: VC-0%
A84: 46028 | B84: FR | C84: 1 | D84: 58 | E84: 58 | F84: 3.13 | G84: 8 | H84: 6.69 | I84: 1.45 | J84: 2.99 | K84: 0.051551724 | L84: 23.92 | M84: 464 | N84: 0.11534483 | O84: 0 | P84: 1 | Q84: 0 | R84: 0 | S84: VC-15%
A85: 46028 | B85: IT | C85: 3 | D85: 58.8 | E85: 176.4 | F85: 16.27 | G85: 24 | H85: 27.68 | I85: 4.41 | J85: 40.72 | K85: 0.230839 | L85: 325.76 | M85: 1411.2 | N85: 0.1569161 | O85: 2 | P85: 1 | Q85: 0.66666667 | R85: 0.23537415 | S85: VC-0%
A86: 46028 | B86: ES | C86: 2 | D86: 59.35 | E86: 118.7 | F86: 15.72 | G86: 16 | H86: 41.67 | I86: 2.9675 | J86: 2.8025 | K86: 0.023609941 | L86: 22.42 | M86: 949.6 | N86: 0.35105307 | O86: 3 | P86: -1 | Q86: 1.5 | R86: 0.23403538 | S86: VC-0%
A87: 46028 | B87: UK | C87: 1 | D87: 52.3 | E87: 52.3 | F87: 14.72 | G87: 8 | H87: 10.36 | I87: 1.3075 | J87: 11.0525 | K87: 0.21132887 | L87: 99.4725 | M87: 470.7 | N87: 0.19808795 | O87: 1 | P87: 0 | Q87: 1 | R87: 0.19808795 | S87: VC-0%
A88: 46028 | B88: 汇总 | C88: 15 | E88: 852.2 | F88: 65.62 | J88: 131.675 | K88: 0.15451185 | L88: 1064.4525 | M88: 6869.9 | O88: 12 | P88: 3 | Q88: 0.8
B89: 分割线
A90: 时间 | B90: 国家 | C90: 数量 | D90: 售价 | E90: 销售额 | F90: 毛利 | G90: 广告预算 | H90: 实际广告 | I90: 活动费 | J90: 毛利 | K90: 毛利率 | L90: 毛利(RMB) | M90: 销售额(RMB) | N90: 广告占比 | O90: 广告订单 | P90: 自然订单 | Q90: 广告订单占比 | R90: ACOS | S90: COUPON
A91: 46029 | B91: DE | C91: 16 | D91: 55.85 | E91: 893.6 | F91: 3.78 | G91: 128 | H91: 195.62 | I91: 22.34 | J91: -29.48 | K91: -0.032990152 | L91: -235.84 | M91: 7148.8 | N91: 0.21891226 | O91: 15 | P91: 1 | Q91: 0.9375 | R91: 0.23350642 | S91: VC-15%
A92: 46029 | B92: FR | C92: 0 | D92: 58 | E92: 0 | F92: 3.13 | G92: 0 | H92: 8.79 | I92: 0 | J92: -8.79 | K92: 0 | L92: -70.32 | M92: 0 | N92: 0 | O92: 0 | P92: 0 | Q92: 0 | R92: 0 | S92: VC-15%
A93: 46029 | B93: IT | C93: 11 | D93: 58.8 | E93: 646.8 | F93: 6.26 | G93: 88 | H93: 32.57 | I93: 16.17 | J93: 108.12 | K93: 0.16716141 | L93: 864.96 | M93: 5174.4 | N93: 0.050355597 | O93: 3 | P93: 8 | Q93: 0.27272727 | R93: 0.18463719 | S93: BD-9.46
A94: 46029 | B94: ES | C94: 6 | D94: 59.35 | E94: 356.1 | F94: 15.72 | G94: 48 | H94: 54.82 | I94: 8.9025 | J94: 78.5975 | K94: 0.2207175 | L94: 628.78 | M94: 2848.8 | N94: 0.15394552 | O94: 1 | P94: 5 | Q94: 0.16666667 | R94: 0.92367313 | S94: VC-0%
A95: 46029 | B95: UK | C95: 3 | D95: 52.3 | E95: 156.9 | F95: 14.72 | G95: 24 | H95: 17.2 | I95: 3.9225 | J95: 47.0375 | K95: 0.29979286 | L95: 423.3375 | M95: 1412.1 | N95: 0.10962396 | O95: 1 | P95: 2 | Q95: 0.33333333 | R95: 0.32887189 | S95: VC-0%
A96: 46029 | B96: 汇总 | C96: 36 | E96: 2053.4 | F96: 43.61 | J96: 195.485 | K96: 0.095200643 | L96: 1610.9175 | M96: 16584.1 | O96: 20 | P96: 16 | Q96: 0.55555556
B97: 分割线
A98: 时间 | B98: 国家 | C98: 数量 | D98: 售价 | E98: 销售额 | F98: 毛利 | G98: 广告预算 | H98: 实际广告 | I98: 活动费 | J98: 毛利 | K98: 毛利率 | L98: 毛利(RMB) | M98: 销售额(RMB) | N98: 广告占比 | O98: 广告订单 | P98: 自然订单 | Q98: 广告订单占比 | R98: ACOS | S98: COUPON
A99: 46030 | B99: DE | C99: 22 | D99: 55.85 | E99: 1228.7 | F99: 3.78 | G99: 176 | H99: 198.13 | I99: 30.7175 | J99: 30.3125 | K99: 0.024670383 | L99: 242.5 | M99: 9829.6 | N99: 0.16125173 | O99: 15 | P99: 7 | Q99: 0.68181818 | R99: 0.23650254 | S99: VC-15%
A100: 46030 | B100: FR | C100: 2 | D100: 58 | E100: 116 | F100: 3.13 | G100: 16 | H100: 8.79 | I100: 2.9 | J100: 10.57 | K100: 0.09112069 | L100: 84.56 | M100: 928 | N100: 0.075775862 | O100: 1 | P100: 1 | Q100: 0.5 | R100: 0.15155172 | S100: VC-15%
...

Sheet 除-价格-毛利
A1: 国家 | B1: COUPON | C1: 利润 | D1: PO价 | E1: 售价
A2: DE | B2: VC-0% | C2: 15.78 | D2: 55.85 | E2: 67.99
A3: DE | B3: VC-5% | C3: 11.78 | D3: 55.85 | E3: 67.99
A4: DE | B4: VC-10% | C4: 7.78 | D4: 55.85 | E4: 67.99
A5: DE | B5: VC-15% | C5: 3.78 | D5: 55.85 | E5: 67.99
A6: DE | B6: BD-10.09 | C6: 5.69 | D6: 55.85 | E6: 67.99
A7: DE | B7: BD-12.97 | C7: 4.06 | D7: 55.85 | E7: 67.99
A8: FR | B8: VC-0% | C8: 15.01 | D8: 55.35 | E8: 67.99
A9: FR | B9: VC-5% | C9: 11.01 | D9: 55.35 | E9: 67.99
A10: FR | B10: VC-10% | C10: 7.01 | D10: 55.35 | E10: 67.99
A11: FR | B11: VC-15% | C11: 3.01 | D11: 55.35 | E11: 67.99
A12: FR | B12: BD-9.21 | C12: 6.67 | D12: 55.35 | E12: 67.99
A13: FR | B13: BD-5.87 | C13: 10.01 | D13: 55.35 | E13: 67.99
... A28: UK | B28: BD-10.42 | C28: 2.72 | D28: 48.3 | E28: 55.88

Sheet AP100A
A1: 汇总 | B1: 国家 | C1: 数量 | D1: 售价 | E1: 销售额 | F1: 毛利 | G1: 广告预算 | H1: 实际广告 | I1: 活动费 | J1: 毛利 | K1: 毛利率 | L1: 毛利(RMB) | M1: 销售额(RMB) | N1: 广告占比 | O1: 广告订单 | P1: 自然订单 | Q1: 广告订单占比 | R1: ACOS | S1: 折扣
A2: 开始时间 | B2: DE | C2: =SUMIFS($C$10:$C$3487,$B$10:$B$3487,B2,$A$10:$A$3487,">="&$A$3,$A$10:$A$3487,"<="&$A$5) | D2: 55.85 | E2: =SUMIFS($E$10:$E$3487,$B$10:$B$3487,B2,$A$10:$A$3487,">="&$A$3,$A$10:$A$3487,"<="&$A$5) | G2: =SUMIFS($G$10:$G$3487,$B$10:$B$3487,B2,$A$10:$A$3487,">="&$A$3,$A$10:$A$3487,"<="&$A$5) | H2: =SUMIFS($H$10:$H$3487,$B$10:$B$3487,B2,$A$10:$A$3487,">="&$A$3,$A$10:$A$3487,"<="&$A$5) | I2: =SUMIFS($I$10:$I$3487,$B$10:$B$3487,B2,$A$10:$A$3487,">="&$A$3,$A$10:$A$3487,"<="&$A$5) | J2: =SUMIFS($J$10:$J$3487,$B$10:$B$3487,B2,$A$10:$A$3487,">="&$A$3,$A$10:$A$3487,"<="&$A$5) | K2: =J2/E2 | L2: =SUMIFS($L$10:$L$3487,$B$10:$B$3487,B2,$A$10:$A$3487,">="&$A$3,$A$10:$A$3487,"<="&$A$5) | M2: =SUMIFS($M$10:$M$3487,$B$10:$B$3487,B2,$A$10:$A$3487,">="&$A$3,$A$10:$A$3487,"<="&$A$5) | N2: =H2/E2 | O2: =SUMIFS($O$10:$O$3487,$B$10:$B$3487,B2,$A$10:$A$3487,">="&$A$3,$A$10:$A$3487,"<="&$A$5) | P2: =C2-O2 | Q2: =O2/C2 | R2: =H2/(E2*Q2)
A3: 46082 | B3: FR | C3: =SUMIFS($C$10:$C$3487,$B$10:$B$3487,B3,$A$10:$A$3487,">="&$A$3,$A$10:$A$3487,"<="&$A$5) | D3: 58 | E3: =SUMIFS($E$10:$E$3487,$B$10:$B$3487,B3,$A$10:$A$3487,">="&$A$3,$A$10:$A$3487,"<="&$A$5) | G3: =SUMIFS($G$10:$G$3487,$B$10:$B$3487,B3,$A$10:$A$3487,">="&$A$3,$A$10:$A$3487,"<="&$A$5) | H3: =SUMIFS($H$10:$H$3487,$B$10:$B$3487,B3,$A$10:$A$3487,">="&$A$3,$A$10:$A$3487,"<="&$A$5) | I3: =SUMIFS($I$10:$I$3487,$B$10:$B$3487,B3,$A$10:$A$3487,">="&$A$3,$A$10:$A$3487,"<="&$A$5) | J3: =SUMIFS($J$10:$J$3487,$B$10:$B$3487,B3,$A$10:$A$3487,">="&$A$3,$A$10:$A$3487,"<="&$A$5) | K3: =J3/E3 | L3: =SUMIFS($L$10:$L$3487,$B$10:$B$3487,B3,$A$10:$A$3487,">="&$A$3,$A$10:$A$3487,"<="&$A$5) | M3: =SUMIFS($M$10:$M$3487,$B$10:$B$3487,B3,$A$10:$A$3487,">="&$A$3,$A$10:$A$3487,"<="&$A$5) | N3: =H3/E3 | O3: =SUMIFS($O$10:$O$3487,$B$10:$B$3487,B3,$A$10:$A$3487,">="&$A$3,$A$10:$A$3487,"<="&$A$5) | P3: =C3-O3 | Q3: =O3/C3 | R3: =H3/(E3*Q3)
A4: 结束时间 | B4: IT | C4: =SUMIFS($C$10:$C$3487,$B$10:$B$3487,B4,$A$10:$A$3487,">="&$A$3,$A$10:$A$3487,"<="&$A$5) | D4: 58.8 | E4: =SUMIFS($E$10:$E$3487,$B$10:$B$3487,B4,$A$10:$A$3487,">="&$A$3,$A$10:$A$3487,"<="&$A$5) | G4: =SUMIFS($G$10:$G$3487,$B$10:$B$3487,B4,$A$10:$A$3487,">="&$A$3,$A$10:$A$3487,"<="&$A$5) | H4: =SUMIFS($H$10:$H$3487,$B$10:$B$3487,B4,$A$10:$A$3487,">="&$A$3,$A$10:$A$3487,"<="&$A$5) | I4: =SUMIFS($I$10:$I$3487,$B$10:$B$3487,B4,$A$10:$A$3487,">="&$A$3,$A$10:$A$3487,"<="&$A$5) | J4: =SUMIFS($J$10:$J$3487,$B$10:$B$3487,B4,$A$10:$A$3487,">="&$A$3,$A$10:$A$3487,"<="&$A$5) | K4: =J4/E4 | L4: =SUMIFS($L$10:$L$3487,$B$10:$B$3487,B4,$A$10:$A$3487,">="&$A$3,$A$10:$A$3487,"<="&$A$5) | M4: =SUMIFS($M$10:$M$3487,$B$10:$B$3487,B4,$A$10:$A$3487,">="&$A$3,$A$10:$A$3487,"<="&$A$5) | N4: =H4/E4 | O4: =SUMIFS($O$10:$O$3487,$B$10:$B$3487,B4,$A$10:$A$3487,">="&$A$3,$A$10:$A$3487,"<="&$A$5) | P4: =C4-O4 | Q4: =O4/C4 | R4: =H4/(E4*Q4)
A5: 46112 | B5: ES | C5: =SUMIFS($C$10:$C$3487,$B$10:$B$3487,B5,$A$10:$A$3487,">="&$A$3,$A$10:$A$3487,"<="&$A$5) | D5: 59.35 | E5: =SUMIFS($E$10:$E$3487,$B$10:$B$3487,B5,$A$10:$A$3487,">="&$A$3,$A$10:$A$3487,"<="&$A$5) | G5: =SUMIFS($G$10:$G$3487,$B$10:$B$3487,B5,$A$10:$A$3487,">="&$A$3,$A$10:$A$3487,"<="&$A$5) | H5: =SUMIFS($H$10:$H$3487,$B$10:$B$3487,B5,$A$10:$A$3487,">="&$A$3,$A$10:$A$3487,"<="&$A$5) | I5: =SUMIFS($I$10:$I$3487,$B$10:$B$3487,B5,$A$10:$A$3487,">="&$A$3,$A$10:$A$3487,"<="&$A$5) | J5: =SUMIFS($J$10:$J$3487,$B$10:$B$3487,B5,$A$10:$A$3487,">="&$A$3,$A$10:$A$3487,"<="&$A$5) | K5: =J5/E5 | L5: =SUMIFS($L$10:$L$3487,$B$10:$B$3487,B5,$A$10:$A$3487,">="&$A$3,$A$10:$A$3487,"<="&$A$5) | M5: =SUMIFS($M$10:$M$3487,$B$10:$B$3487,B5,$A$10:$A$3487,">="&$A$3,$A$10:$A$3487,"<="&$A$5) | N5: =H5/E5 | O5: =SUMIFS($O$10:$O$3487,$B$10:$B$3487,B5,$A$10:$A$3487,">="&$A$3,$A$10:$A$3487,"<="&$A$5) | P5: =C5-O5 | Q5: =O5/C5 | R5: =H5/(E5*Q5)
A6: 即日 | B6: UK | C6: =SUMIFS($C$10:$C$3487,$B$10:$B$3487,B6,$A$10:$A$3487,">="&$A$3,$A$10:$A$3487,"<="&$A$5) | D6: 55.3 | E6: =SUMIFS($E$10:$E$3487,$B$10:$B$3487,B6,$A$10:$A$3487,">="&$A$3,$A$10:$A$3487,"<="&$A$5) | G6: =SUMIFS($G$10:$G$3487,$B$10:$B$3487,B6,$A$10:$A$3487,">="&$A$3,$A$10:$A$3487,"<="&$A$5) | H6: =SUMIFS($H$10:$H$3487,$B$10:$B$3487,B6,$A$10:$A$3487,">="&$A$3,$A$10:$A$3487,"<="&$A$5) | I6: =SUMIFS($I$10:$I$3487,$B$10:$B$3487,B6,$A$10:$A$3487,">="&$A$3,$A$10:$A$3487,"<="&$A$5) | J6: =SUMIFS($J$10:$J$3487,$B$10:$B$3487,B6,$A$10:$A$3487,">="&$A$3,$A$10:$A$3487,"<="&$A$5) | K6: =J6/E6 | L6: =SUMIFS($L$10:$L$3487,$B$10:$B$3487,B6,$A$10:$A$3487,">="&$A$3,$A$10:$A$3487,"<="&$A$5) | M6: =SUMIFS($M$10:$M$3487,$B$10:$B$3487,B6,$A$10:$A$3487,">="&$A$3,$A$10:$A$3487,"<="&$A$5) | N6: =H6/E6 | O6: =SUMIFS($O$10:$O$3487,$B$10:$B$3487,B6,$A$10:$A$3487,">="&$A$3,$A$10:$A$3487,"<="&$A$5) | P6: =C6-O6 | Q6: =O6/C6 | R6: =H6/(E6*Q6)
A7: =NOW() | B7: US | C7: =SUMIFS($C$10:$C$3487,$B$10:$B$3487,B7,$A$10:$A$3487,">="&$A$3,$A$10:$A$3487,"<="&$A$5) | D7: 49.99 | E7: =SUMIFS($E$10:$E$3487,$B$10:$B$3487,B7,$A$10:$A$3487,">="&$A$3,$A$10:$A$3487,"<="&$A$5) | G7: =SUMIFS($G$10:$G$3487,$B$10:$B$3487,B7,$A$10:$A$3487,">="&$A$3,$A$10:$A$3487,"<="&$A$5) | H7: =SUMIFS($H$10:$H$3487,$B$10:$B$3487,B7,$A$10:$A$3487,">="&$A$3,$A$10:$A$3487,"<="&$A$5) | I7: =SUMIFS($I$10:$I$3487,$B$10:$B$3487,B7,$A$10:$A$3487,">="&$A$3,$A$10:$A$3487,"<="&$A$5) | J7: =SUMIFS($J$10:$J$3487,$B$10:$B$3487,B7,$A$10:$A$3487,">="&$A$3,$A$10:$A$3487,"<="&$A$5) | K7: =J7/E7 | L7: =SUMIFS($L$10:$L$3487,$B$10:$B$3487,B7,$A$10:$A$3487,">="&$A$3,$A$10:$A$3487,"<="&$A$5) | M7: =SUMIFS($M$10:$M$3487,$B$10:$B$3487,B7,$A$10:$A$3487,">="&$A$3,$A$10:$A$3487,"<="&$A$5) | N7: =H7/E7 | O7: =SUMIFS($O$10:$O$3487,$B$10:$B$3487,B7,$A$10:$A$3487,">="&$A$3,$A$10:$A$3487,"<="&$A$5) | P7: =C7-O7 | Q7: =O7/C7 | R7: =H7/(E7*Q7)
B8: 汇总 | C8: =SUM(C2:C7) | K8: =L8/M8 | L8: =SUM(L2:L7) | M8: =SUM(M2:M7) | O8: =SUM(O2:O7) | P8: =C8-O8 | Q8: =O8/C8
B9: 分割线
A10: 时间 | B10: 国家 | C10: 数量 | D10: 售价 | E10: 销售额 | F10: 毛利 | G10: 广告预算 | H10: 实际广告 | I10: 活动费 | J10: 毛利 | K10: 毛利率 | L10: 毛利(RMB) | M10: 销售额(RMB) | N10: 广告占比 | O10: 广告订单 | P10: 自然订单 | Q10: 广告订单占比 | R10: ACOS | S10: COUPON
A11: 46034 | B11: DE | C11: 0 | D11: {=_xlfn.XLOOKUP(B11&S11,'净-价格-毛利'!A:A&'净-价格-毛利'!B:B,'净-价格-毛利'!D:D,0)} | E11: =C11*D11 | F11: {=_xlfn.XLOOKUP(B11&S11,'净-价格-毛利'!A:A&'净-价格-毛利'!B:B,'净-价格-毛利'!C:C,0)} | G11: =C11*5 | I11: =E11*0.025 | J11: =F11*C11+G11-H11-I11 | K11: =IFERROR(J11/E11,0) | L11: =J11*8 | M11: =E11*8 | N11: =IFERROR(H11/E11,0) | P11: =C11-O11 | Q11: =IFERROR(O11/C11,0) | R11: =IFERROR(H11/(E11*Q11),0) | S11: VC-0%
A12: 46034 | B12: DE | C12: 4 | D12: {=_xlfn.XLOOKUP(B12&S12,'净-价格-毛利'!A:A&'净-价格-毛利'!B:B,'净-价格-毛利'!D:D,0)} | E12: =C12*D12 | F12: {=_xlfn.XLOOKUP(B12&S12,'净-价格-毛利'!A:A&'净-价格-毛利'!B:B,'净-价格-毛利'!C:C,0)} | G12: =C12*6 | H12: 111.54 | I12: =E12*0.025 | J12: =F12*C12+G12-H12-I12 | K12: =IFERROR(J12/E12,0) | L12: =J12*8 | M12: =E12*8 | N12: =IFERROR(H12/E12,0) | O12: 4 | P12: =C12-O12 | Q12: =IFERROR(O12/C12,0) | R12: =IFERROR(H12/(E12*Q12),0) | S12: SC-49.99
A13: 46034 | B13: FR | C13: 0 | D13: {=_xlfn.XLOOKUP(B13&S13,'净-价格-毛利'!A:A&'净-价格-毛利'!B:B,'净-价格-毛利'!D:D,0)} | E13: =C13*D13 | F13: {=_xlfn.XLOOKUP(B13&S13,'净-价格-毛利'!A:A&'净-价格-毛利'!B:B,'净-价格-毛利'!C:C,0)} | G13: =C13*5 | I13: =E13*0.025 | J13: =F13*C13+G13-H13-I13 | K13: =IFERROR(J13/E13,0) | L13: =J13*8 | M13: =E13*8 | N13: =IFERROR(H13/E13,0) | P13: =C13-O13 | Q13: =IFERROR(O13/C13,0) | R13: =IFERROR(H13/(E13*Q13),0) | S13: VC-0%
A14: 46034 | B14: FR | C14: 1 | D14: {=_xlfn.XLOOKUP(B14&S14,'净-价格-毛利'!A:A&'净-价格-毛利'!B:B,'净-价格-毛利'!D:D,0)} | E14: =C14*D14 | F14: {=_xlfn.XLOOKUP(B14&S14,'净-价格-毛利'!A:A&'净-价格-毛利'!B:B,'净-价格-毛利'!C:C,0)} | G14: =C14*6 | H14: 26.33 | I14: =E14*0.025 | J14: =F14*C14+G14-H14-I14 | K14: =IFERROR(J14/E14,0) | L14: =J14*8 | M14: =E14*8 | N14: =IFERROR(H14/E14,0) | O14: 1 | P14: =C14-O14 | Q14: =IFERROR(O14/C14,0) | R14: =IFERROR(H14/(E14*Q14),0) | S14: SC-51.99
A15: 46034 | B15: IT | C15: 0 | D15: {=_xlfn.XLOOKUP(B15&S15,'净-价格-毛利'!A:A&'净-价格-毛利'!B:B,'净-价格-毛利'!D:D,0)} | E15: =C15*D15 | F15: {=_xlfn.XLOOKUP(B15&S15,'净-价格-毛利'!A:A&'净-价格-毛利'!B:B,'净-价格-毛利'!C:C,0)} | G15: =C15*5 | I15: =E15*0.025 | J15: =F15*C15+G15-H15-I15 | K15: =IFERROR(J15/E15,0) | L15: =J15*8 | M15: =E15*8 | N15: =IFERROR(H15/E15,0) | P15: =C15-O15 | Q15: =IFERROR(O15/C15,0) | R15: =IFERROR(H15/(E15*Q15),0) | S15: VC-0%
A16: 46034 | B16: IT | C16: 0 | D16: {=_xlfn.XLOOKUP(B16&S16,'净-价格-毛利'!A:A&'净-价格-毛利'!B:B,'净-价格-毛利'!D:D,0)} | E16: =C16*D16 | F16: {=_xlfn.XLOOKUP(B16&S16,'净-价格-毛利'!A:A&'净-价格-毛利'!B:B,'净-价格-毛利'!C:C,0)} | G16: =C16*6 | I16: =E16*0.025 | J16: =F16*C16+G16-H16-I16 | K16: =IFERROR(J16/E16,0) | L16: =J16*8 | M16: =E16*8 | N16: =IFERROR(H16/E16,0) | P16: =C16-O16 | Q16: =IFERROR(O16/C16,0) | R16: =IFERROR(H16/(E16*Q16),0) | S16: SC-51.99
A17: 46034 | B17: ES | C17: 0 | D17: {=_xlfn.XLOOKUP(B17&S17,'净-价格-毛利'!A:A&'净-价格-毛利'!B:B,'净-价格-毛利'!D:D,0)} | E17: =C17*D17 | F17: {=_xlfn.XLOOKUP(B17&S17,'净-价格-毛利'!A:A&'净-价格-毛利'!B:B,'净-价格-毛利'!C:C,0)} | G17: =C17*5 | I17: =E17*0.025 | J17: =F17*C17+G17-H17-I17 | K17: =IFERROR(J17/E17,0) | L17: =J17*8 | M17: =E17*8 | N17: =IFERROR(H17/E17,0) | P17: =C17-O17 | Q17: =IFERROR(O17/C17,0) | R17: =IFERROR(H17/(E17*Q17),0) | S17: VC-0%
A18: 46034 | B18: ES | C18: 1 | D18: {=_xlfn.XLOOKUP(B18&S18,'净-价格-毛利'!A:A&'净-价格-毛利'!B:B,'净-价格-毛利'!D:D,0)} | E18: =C18*D18 | F18: {=_xlfn.XLOOKUP(B18&S18,'净-价格-毛利'!A:A&'净-价格-毛利'!B:B,'净-价格-毛利'!C:C,0)} | G18: =C18*6 | H18: 5.72 | I18: =E18*0.025 | J18: =F18*C18+G18-H18-I18 | K18: =IFERROR(J18/E18,0) | L18: =J18*8 | M18: =E18*8 | N18: =IFERROR(H18/E18,0) | O18: 0 | P18: =C18-O18 | Q18: =IFERROR(O18/C18,0) | R18: =IFERROR(H18/(E18*Q18),0) | S18: SC-51.99
A19: 46034 | B19: UK | C19: 0 | D19: {=_xlfn.XLOOKUP(B19&S19,'净-价格-毛利'!A:A&'净-价格-毛利'!B:B,'净-价格-毛利'!D:D,0)} | E19: =C19*D19 | F19: {=_xlfn.XLOOKUP(B19&S19,'净-价格-毛利'!A:A&'净-价格-毛利'!B:B,'净-价格-毛利'!C:C,0)} | G19: =C19*5 | H19: 23.42 | I19: =E19*0.025 | J19: =F19*C19+G19-H19-I19 | K19: =IFERROR(J19/E19,0) | L19: =J19*9 | M19: =E19*9 | N19: =IFERROR(H19/E19,0) | O19: 0 | P19: =C19-O19 | Q19: =IFERROR(O19/C19,0) | R19: =IFERROR(H19/(E19*Q19),0) | S19: VC-0%
A20: 46034 | B20: UK | C20: 0 | D20: {=_xlfn.XLOOKUP(B20&S20,'净-价格-毛利'!A:A&'净-价格-毛利'!B:B,'净-价格-毛利'!D:D,0)} | E20: =C20*D20 | F20: {=_xlfn.XLOOKUP(B20&S20,'净-价格-毛利'!A:A&'净-价格-毛利'!B:B,'净-价格-毛利'!C:C,0)} | G20: =C20*6 | H20: 0 | I20: =E20*0.025 | J20: =F20*C20+G20-H20-I20 | K20: =IFERROR(J20/E20,0) | L20: =J20*9 | M20: =E20*9 | N20: =IFERROR(H20/E20,0) | O20: 0 | P20: =C20-O20 | Q20: =IFERROR(O20/C20,0) | R20: =IFERROR(H20/(E20*Q20),0) | S20: SC-45.99
A21: 46034 | B21: US | C21: 0 | D21: {=_xlfn.XLOOKUP(B21&S21,'净-价格-毛利'!A:A&'净-价格-毛利'!B:B,'净-价格-毛利'!D:D,0)} | E21: =C21*D21 | F21: {=_xlfn.XLOOKUP(B21&S21,'净-价格-毛利'!A:A&'净-价格-毛利'!B:B,'净-价格-毛利'!C:C,0)} | I21: =E21*0.025 | J21: =C21*F21-H21-I21 | K21: =IFERROR(J21/E21,0) | L21: =J21*7 | M21: =E21*7 | N21: =IFERROR(H21/E21,0) | P21: =C21-O21 | Q21: =IFERROR(O21/C21,0)
A22: 46034 | B22: 汇总 | C22: =SUM(C11:C21) | E22: =SUM(E11:E21) | F22: =SUM(F11:F20) | J22: =SUM(J11:J21) | K22: =IFERROR(J22/E22,0) | L22: =SUM(L11:L21) | M22: =SUM(M11:M21) | O22: =SUM(O11:O20) | P22: =C22-O22 | Q22: =IFERROR(O22/C22,0)
B23: 分割线
A24: 时间 | B24: 国家 | C24: 数量 | D24: 售价 | E24: 销售额 | F24: 毛利 | G24: 广告预算 | H24: 实际广告 | I24: 活动费 | J24: 毛利 | K24: 毛利率 | L24: 毛利(RMB) | M24: 销售额(RMB) | N24: 广告占比 | O24: 广告订单 | P24: 自然订单 | Q24: 广告订单占比 | R24: ACOS | S24: COUPON
A25: 46035 | B25: DE | C25: 0 | D25: {=_xlfn.XLOOKUP(B25&S25,'净-价格-毛利'!A:A&'净-价格-毛利'!B:B,'净-价格-毛利'!D:D,0)} | E25: =C25*D25 | F25: {=_xlfn.XLOOKUP(B25&S25,'净-价格-毛利'!A:A&'净-价格-毛利'!B:B,'净-价格-毛利'!C:C,0)} | G25: =C25*5 | I25: =E25*0.025 | J25: =F25*C25+G25-H25-I25 | K25: =IFERROR(J25/E25,0) | L25: =J25*8 | M25: =E25*8 | N25: =IFERROR(H25/E25,0) | P25: =C25-O25 | Q25: =IFERROR(O25/C25,0) | R25: =IFERROR(H25/(E25*Q25),0) | S25: VC-0%
A26: 46035 | B26: DE | C26: 4 | D26: {=_xlfn.XLOOKUP(B26&S26,'净-价格-毛利'!A:A&'净-价格-毛利'!B:B,'净-价格-毛利'!D:D,0)} | E26: =C26*D26 | F26: {=_xlfn.XLOOKUP(B26&S26,'净-价格-毛利'!A:A&'净-价格-毛利'!B:B,'净-价格-毛利'!C:C,0)} | G26: =C26*6 | H26: 118.37 | I26: =E26*0.025 | J26: =F26*C26+G26-H26-I26 | K26: =IFERROR(J26/E26,0) | L26: =J26*8 | M26: =E26*8 | N26: =IFERROR(H26/E26,0) | O26: 3 | P26: =C26-O26 | Q26: =IFERROR(O26/C26,0) | R26: =IFERROR(H26/(E26*Q26),0) | S26: SC-49.99
A27: 46035 | B27: FR | C27: 0 | D27: {=_xlfn.XLOOKUP(B27&S27,'净-价格-毛利'!A:A&'净-价格-毛利'!B:B,'净-价格-毛利'!D:D,0)} | E27: =C27*D27 | F27: {=_xlfn.XLOOKUP(B27&S27,'净-价格-毛利'!A:A&'净-价格-毛利'!B:B,'净-价格-毛利'!C:C,0)} | G27: =C27*5 | I27: =E27*0.025 | J27: =F27*C27+G27-H27-I27 | K27: =IFERROR(J27/E27,0) | L27: =J27*8 | M27: =E27*8 | N27: =IFERROR(H27/E27,0) | P27: =C27-O27 | Q27: =IFERROR(O27/C27,0) | R27: =IFERROR(H27/(E27*Q27),0) | S27: VC-0%
A28: 46035 | B28: FR | C28: 0 | D28: {=_xlfn.XLOOKUP(B28&S28,'净-价格-毛利'!A:A&'净-价格-毛利'!B:B,'净-价格-毛利'!D:D,0)} | E28: =C28*D28 | F28: {=_xlfn.XLOOKUP(B28&S28,'净-价格-毛利'!A:A&'净-价格-毛利'!B:B,'净-价格-毛利'!C:C,0)} | G28: =C28*6 | H28: 30.92 | I28: =E28*0.025 | J28: =F28*C28+G28-H28-I28 | K28: =IFERROR(J28/E28,0) | L28: =J28*8 | M28: =E28*8 | N28: =IFERROR(H28/E28,0) | O28: 0 | P28: =C28-O28 | Q28: =IFERROR(O28/C28,0) | R28: =IFERROR(H28/(E28*Q28),0) | S28: SC-51.99
A29: 46035 | B29: IT | C29: 0 | D29: {=_xlfn.XLOOKUP(B29&S29,'净-价格-毛利'!A:A&'净-价格-毛利'!B:B,'净-价格-毛利'!D:D,0)} | E29: =C29*D29 | F29: {=_xlfn.XLOOKUP(B29&S29,'净-价格-毛利'!A:A&'净-价格-毛利'!B:B,'净-价格-毛利'!C:C,0)} | G29: =C29*5 | I29: =E29*0.025 | J29: =F29*C29+G29-H29-I29 | K29: =IFERROR(J29/E29,0) | L29: =J29*8 | M29: =E29*8 | N29: =IFERROR(H29/E29,0) | P29: =C29-O29 | Q29: =IFERROR(O29/C29,0) | R29: =IFERROR(H29/(E29*Q29),0) | S29: VC-0%
A30: 46035 | B30: IT | C30: 0 | D30: {=_xlfn.XLOOKUP(B30&S30,'净-价格-毛利'!A:A&'净-价格-毛利'!B:B,'净-价格-毛利'!D:D,0)} | E30: =C30*D30 | F30: {=_xlfn.XLOOKUP(B30&S30,'净-价格-毛利'!A:A&'净-价格-毛利'!B:B,'净-价格-毛利'!C:C,0)} | G30: =C30*6 | I30: =E30*0.025 | J30: =F30*C30+G30-H30-I30 | K30: =IFERROR(J30/E30,0) | L30: =J30*8 | M30: =E30*8 | N30: =IFERROR(H30/E30,0) | P30: =C30-O30 | Q30: =IFERROR(O30/C30,0) | R30: =IFERROR(H30/(E30*Q30),0) | S30: SC-51.99
A31: 46035 | B31: ES | C31: 0 | D31: {=_xlfn.XLOOKUP(B31&S31,'净-价格-毛利'!A:A&'净-价格-毛利'!B:B,'净-价格-毛利'!D:D,0)} | E31: =C31*D31 | F31: {=_xlfn.XLOOKUP(B31&S31,'净-价格-毛利'!A:A&'净-价格-毛利'!B:B,'净-价格-毛利'!C:C,0)} | G31: =C31*5 | I31: =E31*0.025 | J31: =F31*C31+G31-H31-I31 | K31: =IFERROR(J31/E31,0) | L31: =J31*8 | M31: =E31*8 | N31: =IFERROR(H31/E31,0) | P31: =C31-O31 | Q31: =IFERROR(O31/C31,0) | R31: =IFERROR(H31/(E31*Q31),0) | S31: VC-0%
A32: 46035 | B32: ES | C32: 3 | D32: {=_xlfn.XLOOKUP(B32&S32,'净-价格-毛利'!A:A&'净-价格-毛利'!B:B,'净-价格-毛利'!D:D,0)} | E32: =C32*D32 | F32: {=_xlfn.XLOOKUP(B32&S32,'净-价格-毛利'!A:A&'净-价格-毛利'!B:B,'净-价格-毛利'!C:C,0)} | G32: =C32*6 | H32: 29.39 | I32: =E32*0.025 | J32: =F32*C32+G32-H32-I32 | K32: =IFERROR(J32/E32,0) | L32: =J32*8 | M32: =E32*8 | N32: =IFERROR(H32/E32,0) | O32: 0 | P32: =C32-O32 | Q32: =IFERROR(O32/C32,0) | R32: =IFERROR(H32/(E32*Q32),0) | S32: SC-51.99
A33: 46035 | B33: UK | C33: 0 | D33: {=_xlfn.XLOOKUP(B33&S33,'净-价格-毛利'!A:A&'净-价格-毛利'!B:B,'净-价格-毛利'!D:D,0)} | E33: =C33*D33 | F33: {=_xlfn.XLOOKUP(B33&S33,'净-价格-毛利'!A:A&'净-价格-毛利'!B:B,'净-价格-毛利'!C:C,0)} | G33: =C33*5 | H33: 8.2 | I33: =E33*0.025 | J33: =F33*C33+G33-H33-I33 | K33: =IFERROR(J33/E33,0) | L33: =J33*9 | M33: =E33*9 | N33: =IFERROR(H33/E33,0) | O33: 0 | P33: =C33-O33 | Q33: =IFERROR(O33/C33,0) | R33: =IFERROR(H33/(E33*Q33),0) | S33: VC-0%
A34: 46035 | B34: UK | C34: 0 | D34: {=_xlfn.XLOOKUP(B34&S34,'净-价格-毛利'!A:A&'净-价格-毛利'!B:B,'净-价格-毛利'!D:D,0)} | E34: =C34*D34 | F34: {=_xlfn.XLOOKUP(B34&S34,'净-价格-毛利'!A:A&'净-价格-毛利'!B:B,'净-价格-毛利'!C:C,0)} | G34: =C34*6 | I34: =E34*0.025 | J34: =F34*C34+G34-H34-I34 | K34: =IFERROR(J34/E34,0) | L34: =J34*9 | M34: =E34*9 | N34: =IFERROR(H34/E34,0) | P34: =C34-O34 | Q34: =IFERROR(O34/C34,0) | R34: =IFERROR(H34/(E34*Q34),0) | S34: SC-45.99
A35: 46035 | B35: US | C35: 0 | D35: {=_xlfn.XLOOKUP(B35&S35,'净-价格-毛利'!A:A&'净-价格-毛利'!B:B,'净-价格-毛利'!D:D,0)} | E35: =C35*D35 | F35: {=_xlfn.XLOOKUP(B35&S35,'净-价格-毛利'!A:A&'净-价格-毛利'!B:B,'净-价格-毛利'!C:C,0)} | I35: =E35*0.025 | J35: =C35*F35-H35-I35 | K35: =IFERROR(J35/E35,0) | L35: =J35*7 | M35: =E35*7 | N35: =IFERROR(H35/E35,0) | P35: =C35-O35 | Q35: =IFERROR(O35/C35,0)
A36: 46035 | B36: 汇总 | C36: =SUM(C25:C35) | E36: =SUM(E25:E35) | F36: =SUM(F25:F34) | J36: =SUM(J25:J35) | K36: =IFERROR(J36/E36,0) | L36: =SUM(L25:L35) | M36: =SUM(M25:M35) | O36: =SUM(O25:O34) | P36: =C36-O36 | Q36: =IFERROR(O36/C36,0)
B37: 分割线
A38: 时间 | B38: 国家 | C38: 数量 | D38: 售价 | E38: 销售额 | F38: 毛利 | G38: 广告预算 | H38: 实际广告 | I38: 活动费 | J38: 毛利 | K38: 毛利率 | L38: 毛利(RMB) | M38: 销售额(RMB) | N38: 广告占比 | O38: 广告订单 | P38: 自然订单 | Q38: 广告订单占比 | R38: ACOS | S38: COUPON
A39: 46036 | B39: DE | C39: 0 | D39: {=_xlfn.XLOOKUP(B39&S39,'净-价格-毛利'!A:A&'净-价格-毛利'!B:B,'净-价格-毛利'!D:D,0)} | E39: =C39*D39 | F39: {=_xlfn.XLOOKUP(B39&S39,'净-价格-毛利'!A:A&'净-价格-毛利'!B:B,'净-价格-毛利'!C:C,0)} | G39: =C39*5 | I39: =E39*0.025 | J39: =F39*C39+G39-H39-I39 | K39: =IFERROR(J39/E39,0) | L39: =J39*8 | M39: =E39*8 | N39: =IFERROR(H39/E39,0) | P39: =C39-O39 | Q39: =IFERROR(O39/C39,0) | R39: =IFERROR(H39/(E39*Q39),0) | S39: VC-0%
A40: 46036 | B40: DE | C40: 1 | D40: {=_xlfn.XLOOKUP(B40&S40,'净-价格-毛利'!A:A&'净-价格-毛利'!B:B,'净-价格-毛利'!D:D,0)} | E40: =C40*D40 | F40: {=_xlfn.XLOOKUP(B40&S40,'净-价格-毛利'!A:A&'净-价格-毛利'!B:B,'净-价格-毛利'!C:C,0)} | G40: =C40*6 | H40: 108.23 | I40: =E40*0.025 | J40: =F40*C40+G40-H40-I40 | K40: =IFERROR(J40/E40,0) | L40: =J40*8 | M40: =E40*8 | N40: =IFERROR(H40/E40,0) | O40: 1 | P40: =C40-O40 | Q40: =IFERROR(O40/C40,0) | R40: =IFERROR(H40/(E40*Q40),0) | S40: SC-49.99
A41: 46036 | B41: FR | C41: 0 | D41: {=_xlfn.XLOOKUP(B41&S41,'净-价格-毛利'!A:A&'净-价格-毛利'!B:B,'净-价格-毛利'!D:D,0)} | E41: =C41*D41 | F41: {=_xlfn.XLOOKUP(B41&S41,'净-价格-毛利'!A:A&'净-价格-毛利'!B:B,'净-价格-毛利'!C:C,0)} | G41: =C41*5 | I41: =E41*0.025 | J41: =F41*C41+G41-H41-I41 | K41: =IFERROR(J41/E41,0) | L41: =J41*8 | M41: =E41*8 | N41: =IFERROR(H41/E41,0) | P41: =C41-O41 | Q41: =IFERROR(O41/C41,0) | R41: =IFERROR(H41/(E41*Q41),0) | S41: VC-0%
A42: 46036 | B42: FR | C42: 0 | D42: {=_xlfn.XLOOKUP(B42&S42,'净-价格-毛利'!A:A&'净-价格-毛利'!B:B,'净-价格-毛利'!D:D,0)} | E42: =C42*D42 | F42: {=_xlfn.XLOOKUP(B42&S42,'净-价格-毛利'!A:A&'净-价格-毛利'!B:B,'净-价格-毛利'!C:C,0)} | G42: =C42*6 | H42: 29.92 | I42: =E42*0.025 | J42: =F42*C42+G42-H42-I42 | K42: =IFERROR(J42/E42,0) | L42: =J42*8 | M42: =E42*8 | N42: =IFERROR(H42/E42,0) | O42: 0 | P42: =C42-O42 | Q42: =IFERROR(O42/C42,0) | R42: =IFERROR(H42/(E42*Q42),0) | S42: SC-51.99
A43: 46036 | B43: IT | C43: 0 | D43: {=_xlfn.XLOOKUP(B43&S43,'净-价格-毛利'!A:A&'净-价格-毛利'!B:B,'净-价格-毛利'!D:D,0)} | E43: =C43*D43 | F43: {=_xlfn.XLOOKUP(B43&S43,'净-价格-毛利'!A:A&'净-价格-毛利'!B:B,'净-价格-毛利'!C:C,0)} | G43: =C43*5 | I43: =E43*0.025 | J43: =F43*C43+G43-H43-I43 | K43: =IFERROR(J43/E43,0) | L43: =J43*8 | M43: =E43*8 | N43: =IFERROR(H43/E43,0) | P43: =C43-O43 | Q43: =IFERROR(O43/C43,0) | R43: =IFERROR(H43/(E43*Q43),0) | S43: VC-0%
A44: 46036 | B44: IT | C44: 0 | D44: {=_xlfn.XLOOKUP(B44&S44,'净-价格-毛利'!A:A&'净-价格-毛利'!B:B,'净-价格-毛利'!D:D,0)} | E44: =C44*D44 | F44: {=_xlfn.XLOOKUP(B44&S44,'净-价格-毛利'!A:A&'净-价格-毛利'!B:B,'净-价格-毛利'!C:C,0)} | G44: =C44*6 | I44: =E44*0.025 | J44: =F44*C44+G44-H44-I44 | K44: =IFERROR(J44/E44,0) | L44: =J44*8 | M44: =E44*8 | N44: =IFERROR(H44/E44,0) | P44: =C44-O44 | Q44: =IFERROR(O44/C44,0) | R44: =IFERROR(H44/(E44*Q44),0) | S44: SC-51.99
A45: 46036 | B45: ES | C45: 0 | D45: {=_xlfn.XLOOKUP(B45&S45,'净-价格-毛利'!A:A&'净-价格-毛利'!B:B,'净-价格-毛利'!D:D,0)} | E45: =C45*D45 | F45: {=_xlfn.XLOOKUP(B45&S45,'净-价格-毛利'!A:A&'净-价格-毛利'!B:B,'净-价格-毛利'!C:C,0)} | G45: =C45*5 | I45: =E45*0.025 | J45: =F45*C45+G45-H45-I45 | K45: =IFERROR(J45/E45,0) | L45: =J45*8 | M45: =E45*8 | N45: =IFERROR(H45/E45,0) | P45: =C45-O45 | Q45: =IFERROR(O45/C45,0) | R45: =IFERROR(H45/(E45*Q45),0) | S45: VC-0%
A46: 46036 | B46: ES | C46: 2 | D46: {=_xlfn.XLOOKUP(B46&S46,'净-价格-毛利'!A:A&'净-价格-毛利'!B:B,'净-价格-毛利'!D:D,0)} | E46: =C46*D46 | F46: {=_xlfn.XLOOKUP(B46&S46,'净-价格-毛利'!A:A&'净-价格-毛利'!B:B,'净-价格-毛利'!C:C,0)} | G46: =C46*6 | H46: 31.34 | I46: =E46*0.025 | J46: =F46*C46+G46-H46-I46 | K46: =IFERROR(J46/E46,0) | L46: =J46*8 | M46: =E46*8 | N46: =IFERROR(H46/E46,0) | O46: 1 | P46: =C46-O46 | Q46: =IFERROR(O46/C46,0) | R46: =IFERROR(H46/(E46*Q46),0) | S46: SC-51.99
A47: 46036 | B47: UK | C47: 0 | D47: {=_xlfn.XLOOKUP(B47&S47,'净-价格-毛利'!A:A&'净-价格-毛利'!B:B,'净-价格-毛利'!D:D,0)} | E47: =C47*D47 | F47: {=_xlfn.XLOOKUP(B47&S47,'净-价格-毛利'!A:A&'净-价格-毛利'!B:B,'净-价格-毛利'!C:C,0)} | G47: =C47*5 | H47: 10.12 | I47: =E47*0.025 | J47: =F47*C47+G47-H47-I47 | K47: =IFERROR(J47/E47,0) | L47: =J47*9 | M47: =E47*9 | N47: =IFERROR(H47/E47,0) | O47: 0 | P47: =C47-O47 | Q47: =IFERROR(O47/C47,0) | R47: =IFERROR(H47/(E47*Q47),0) | S47: VC-0%
A48: 46036 | B48: UK | C48: 0 | D48: {=_xlfn.XLOOKUP(B48&S48,'净-价格-毛利'!A:A&'净-价格-毛利'!B:B,'净-价格-毛利'!D:D,0)} | E48: =C48*D48 | F48: {=_xlfn.XLOOKUP(B48&S48,'净-价格-毛利'!A:A&'净-价格-毛利'!B:B,'净-价格-毛利'!C:C,0)} | G48: =C48*6 | H48: 0 | I48: =E48*0.025 | J48: =F48*C48+G48-H48-I48 | K48: =IFERROR(J48/E48,0) | L48: =J48*9 | M48: =E48*9 | N48: =IFERROR(H48/E48,0) | O48: 0 | P48: =C48-O48 | Q48: =IFERROR(O48/C48,0) | R48: =IFERROR(H48/(E48*Q48),0) | S48: SC-45.99
A49: 46036 | B49: US | C49: 0 | D49: {=_xlfn.XLOOKUP(B49&S49,'净-价格-毛利'!A:A&'净-价格-毛利'!B:B,'净-价格-毛利'!D:D,0)} | E49: =C49*D49 | F49: {=_xlfn.XLOOKUP(B49&S49,'净-价格-毛利'!A:A&'净-价格-毛利'!B:B,'净-价格-毛利'!C:C,0)} | H49: 0 | I49: =E49*0.025 | J49: =C49*F49-H49-I49 | K49: =IFERROR(J49/E49,0) | L49: =J49*7 | M49: =E49*7 | N49: =IFERROR(H49/E49,0) | O49: 0 | P49: =C49-O49 | Q49: =IFERROR(O49/C49,0)
A50: 46036 | B50: 汇总 | C50: =SUM(C39:C49) | E50: =SUM(E39:E49) | F50: =SUM(F39:F48) | J50: =SUM(J39:J49) | K50: =IFERROR(J50/E50,0) | L50: =SUM(L39:L49) | M50: =SUM(M39:M49) | O50: =SUM(O39:O48) | P50: =C50-O50 | Q50: =IFERROR(O50/C50,0)
B51: 分割线
A52: 时间 | B52: 国家 | C52: 数量 | D52: 售价 | E52: 销售额 | F52: 毛利 | G52: 广告预算 | H52: 实际广告 | I52: 活动费 | J52: 毛利 | K52: 毛利率 | L52: 毛利(RMB) | M52: 销售额(RMB) | N52: 广告占比 | O52: 广告订单 | P52: 自然订单 | Q52: 广告订单占比 | R52: ACOS | S52: COUPON
A53: 46037 | B53: DE | C53: 0 | D53: {=_xlfn.XLOOKUP(B53&S53,'净-价格-毛利'!A:A&'净-价格-毛利'!B:B,'净-价格-毛利'!D:D,0)} | E53: =C53*D53 | F53: {=_xlfn.XLOOKUP(B53&S53,'净-价格-毛利'!A:A&'净-价格-毛利'!B:B,'净-价格-毛利'!C:C,0)} | G53: =C53*5 | I53: =E53*0.025 | J53: =F53*C53+G53-H53-I53 | K53: =IFERROR(J53/E53,0) | L53: =J53*8 | M53: =E53*8 | N53: =IFERROR(H53/E53,0) | P53: =C53-O53 | Q53: =IFERROR(O53/C53,0) | R53: =IFERROR(H53/(E53*Q53),0) | S53: VC-0%
A54: 46037 | B54: DE | C54: 1 | D54: {=_xlfn.XLOOKUP(B54&S54,'净-价格-毛利'!A:A&'净-价格-毛利'!B:B,'净-价格-毛利'!D:D,0)} | E54: =C54*D54 | F54: {=_xlfn.XLOOKUP(B54&S54,'净-价格-毛利'!A:A&'净-价格-毛利'!B:B,'净-价格-毛利'!C:C,0)} | G54: =C54*6 | H54: 113.67 | I54: =E54*0.025 | J54: =F54*C54+G54-H54-I54 | K54: =IFERROR(J54/E54,0) | L54: =J54*8 | M54: =E54*8 | N54: =IFERROR(H54/E54,0) | O54: 0 | P54: =C54-O54 | Q54: =IFERROR(O54/C54,0) | R54: =IFERROR(H54/(E54*Q54),0) | S54: SC-49.99
A55: 46037 | B55: FR | C55: 0 | D55: {=_xlfn.XLOOKUP(B55&S55,'净-价格-毛利'!A:A&'净-价格-毛利'!B:B,'净-价格-毛利'!D:D,0)} | E55: =C55*D55 | F55: {=_xlfn.XLOOKUP(B55&S55,'净-价格-毛利'!A:A&'净-价格-毛利'!B:B,'净-价格-毛利'!C:C,0)} | G55: =C55*5 | I55: =E55*0.025 | J55: =F55*C55+G55-H55-I55 | K55: =IFERROR(J55/E55,0) | L55: =J55*8 | M55: =E55*8 | N55: =IFERROR(H55/E55,0) | P55: =C55-O55 | Q55: =IFERROR(O55/C55,0) | R55: =IFERROR(H55/(E55*Q55),0) | S55: VC-0%
A56: 46037 | B56: FR | C56: 0 | D56: {=_xlfn.XLOOKUP(B56&S56,'净-价格-毛利'!A:A&'净-价格-毛利'!B:B,'净-价格-毛利'!D:D,0)} | E56: =C56*D56 | F56: {=_xlfn.XLOOKUP(B56&S56,'净-价格-毛利'!A:A&'净-价格-毛利'!B:B,'净-价格-毛利'!C:C,0)} | G56: =C56*6 | H56: 23.32 | I56: =E56*0.025 | J56: =F56*C56+G56-H56-I56 | K56: =IFERROR(J56/E56,0) | L56: =J56*8 | M56: =E56*8 | N56: =IFERROR(H56/E56,0) | O56: 0 | P56: =C56-O56 | Q56: =IFERROR(O56/C56,0) | R56: =IFERROR(H56/(E56*Q56),0) | S56: SC-51.99
A57: 46037 | B57: IT | C57: 1 | D57: {=_xlfn.XLOOKUP(B57&S57,'净-价格-毛利'!A:A&'净-价格-毛利'!B:B,'净-价格-毛利'!D:D,0)} | E57: =C57*D57 | F57: {=_xlfn.XLOOKUP(B57&S57,'净-价格-毛利'!A:A&'净-价格-毛利'!B:B,'净-价格-毛利'!C:C,0)} | G57: =C57*5 | I57: =E57*0.025 | J57: =F57*C57+G57-H57-I57 | K57: =IFERROR(J57/E57,0) | L57: =J57*8 | M57: =E57*8 | N57: =IFERROR(H57/E57,0) | P57: =C57-O57 | Q57: =IFERROR(O57/C57,0) | R57: =IFERROR(H57/(E57*Q57),0) | S57: VC-0%
A58: 46037 | B58: IT | C58: 0 | D58: {=_xlfn.XLOOKUP(B58&S58,'净-价格-毛利'!A:A&'净-价格-毛利'!B:B,'净-价格-毛利'!D:D,0)} | E58: =C58*D58 | F58: {=_xlfn.XLOOKUP(B58&S58,'净-价格-毛利'!A:A&'净-价格-毛利'!B:B,'净-价格-毛利'!C:C,0)} | G58: =C58*6 | I58: =E58*0.025 | J58: =F58*C58+G58-H58-I58 | K58: =IFERROR(J58/E58,0) | L58: =J58*8 | M58: =E58*8 | N58: =IFERROR(H58/E58,0) | P58: =C58-O58 | Q58: =IFERROR(O58/C58,0) | R58: =IFERROR(H58/(E58*Q58),0) | S58: SC-51.99
A59: 46037 | B59: ES | C59: 1 | D59: {=_xlfn.XLOOKUP(B59&S59,'净-价格-毛利'!A:A&'净-价格-毛利'!B:B,'净-价格-毛利'!D:D,0)} | E59: =C59*D59 | F59: {=_xlfn.XLOOKUP(B59&S59,'净-价格-毛利'!A:A&'净-价格-毛利'!B:B,'净-价格-毛利'!C:C,0)} | G59: =C59*5 | H59: 29.98 | I59: =E59*0.025 | J59: =F59*C59+G59-H59-I59 | K59: =IFERROR(J59/E59,0) | L59: =J59*8 | M59: =E59*8 | N59: =IFERROR(H59/E59,0) | O59: 0 | P59: =C59-O59 | Q59: =IFERROR(O59/C59,0) | R59: =IFERROR(H59/(E59*Q59),0) | S59: VC-0%
A60: 46037 | B60: ES | C60: 0 | D60: {=_xlfn.XLOOKUP(B60&S60,'净-价格-毛利'!A:A&'净-价格-毛利'!B:B,'净-价格-毛利'!D:D,0)} | E60: =C60*D60 | F60: {=_xlfn.XLOOKUP(B60&S60,'净-价格-毛利'!A:A&'净-价格-毛利'!B:B,'净-价格-毛利'!C:C,0)} | G60: =C60*6 | I60: =E60*0.025 | J60: =F60*C60+G60-H60-I60 | K60: =IFERROR(J60/E60,0) | L60: =J60*8 | M60: =E60*8 | N60: =IFERROR(H60/E60,0) | P60: =C60-O60 | Q60: =IFERROR(O60/C60,0) | R60: =IFERROR(H60/(E60*Q60),0) | S60: SC-51.99
A61: 46037 | B61: UK | C61: 0 | D61: {=_xlfn.XLOOKUP(B61&S61,'净-价格-毛利'!A:A&'净-价格-毛利'!B:B,'净-价格-毛利'!D:D,0)} | E61: =C61*D61 | F61: {=_xlfn.XLOOKUP(B61&S61,'净-价格-毛利'!A:A&'净-价格-毛利'!B:B,'净-价格-毛利'!C:C,0)} | G61: =C61*5 | H61: 19.98 | I61: =E61*0.025 | J61: =F61*C61+G61-H61-I61 | K61: =IFERROR(J61/E61,0) | L61: =J61*9 | M61: =E61*9 | N61: =IFERROR(H61/E61,0) | O61: 0 | P61: =C61-O61 | Q61: =IFERROR(O61/C61,0) | R61: =IFERROR(H61/(E61*Q61),0) | S61: VC-0%
A62: 46037 | B62: UK | C62: 0 | D62: {=_xlfn.XLOOKUP(B62&S62,'净-价格-毛利'!A:A&'净-价格-毛利'!B:B,'净-价格-毛利'!D:D,0)} | E62: =C62*D62 | F62: {=_xlfn.XLOOKUP(B62&S62,'净-价格-毛利'!A:A&'净-价格-毛利'!B:B,'净-价格-毛利'!C:C,0)} | G62: =C62*6 | I62: =E62*0.025 | J62: =F62*C62+G62-H62-I62 | K62: =IFERROR(J62/E62,0) | L62: =J62*9 | M62: =E62*9 | N62: =IFERROR(H62/E62,0) | P62: =C62-O62 | Q62: =IFERROR(O62/C62,0) | R62: =IFERROR(H62/(E62*Q62),0) | S62: SC-45.99
A63: 46037 | B63: US | C63: 0 | D63: {=_xlfn.XLOOKUP(B63&S63,'净-价格-毛利'!A:A&'净-价格-毛利'!B:B,'净-价格-毛利'!D:D,0)} | E63: =C63*D63 | F63: {=_xlfn.XLOOKUP(B63&S63,'净-价格-毛利'!A:A&'净-价格-毛利'!B:B,'净-价格-毛利'!C:C,0)} | I63: =E63*0.025 | J63: =C63*F63-H63-I63 | K63: =IFERROR(J63/E63,0) | L63: =J63*7 | M63: =E63*7 | N63: =IFERROR(H63/E63,0) | P63: =C63-O63 | Q63: =IFERROR(O63/C63,0)
A64: 46037 | B64: 汇总 | C64: =SUM(C53:C63) | E64: =SUM(E53:E63) | F64: =SUM(F53:F62) | J64: =SUM(J53:J63) | K64: =IFERROR(J64/E64,0) | L64: =SUM(L53:L63) | M64: =SUM(M53:M63) | O64: =SUM(O53:O62) | P64: =C64-O64 | Q64: =IFERROR(O64/C64,0)
B65: 分割线
A66: 时间 | B66: 国家 | C66: 数量 | D66: 售价 | E66: 销售额 | F66: 毛利 | G66: 广告预算 | H66: 实际广告 | I66: 活动费 | J66: 毛利 | K66: 毛利率 | L66: 毛利(RMB) | M66: 销售额(RMB) | N66: 广告占比 | O66: 广告订单 | P66: 自然订单 | Q66: 广告订单占比 | R66: ACOS | S66: COUPON
A67: 46038 | B67: DE | D67: {=_xlfn.XLOOKUP(B67&S67,'净-价格-毛利'!A:A&'净-价格-毛利'!B:B,'净-价格-毛利'!D:D,0)} | E67: =C67*D67 | F67: {=_xlfn.XLOOKUP(B67&S67,'净-价格-毛利'!A:A&'净-价格-毛利'!B:B,'净-价格-毛利'!C:C,0)} | G67: =C67*5 | H67: 33.55 | I67: =E67*0.025 | J67: =F67*C67+G67-H67-I67 | K67: =IFERROR(J67/E67,0) | L67: =J67*8 | M67: =E67*8 | N67: =IFERROR(H67/E67,0) | O67: 0 | P67: =C67-O67 | Q67: =IFERROR(O67/C67,0) | R67: =IFERROR(H67/(E67*Q67),0) | S67: VC-10%
A68: 46038 | B68: DE | D68: {=_xlfn.XLOOKUP(B68&S68,'净-价格-毛利'!A:A&'净-价格-毛利'!B:B,'净-价格-毛利'!D:D,0)} | E68: =C68*D68 | F68: {=_xlfn.XLOOKUP(B68&S68,'净-价格-毛利'!A:A&'净-价格-毛利'!B:B,'净-价格-毛利'!C:C,0)} | G68: =C68*6 | I68: =E68*0.025 | J68: =F68*C68+G68-H68-I68 | K68: =IFERROR(J68/E68,0) | L68: =J68*8 | M68: =E68*8 | N68: =IFERROR(H68/E68,0) | O68: 0 | P68: =C68-O68 | Q68: =IFERROR(O68/C68,0) | R68: =IFERROR(H68/(E68*Q68),0) | S68: SC-52.99
A69: 46038 | B69: FR | D69: {=_xlfn.XLOOKUP(B69&S69,'净-价格-毛利'!A:A&'净-价格-毛利'!B:B,'净-价格-毛利'!D:D,0)} | E69: =C69*D69 | F69: {=_xlfn.XLOOKUP(B69&S69,'净-价格-毛利'!A:A&'净-价格-毛利'!B:B,'净-价格-毛利'!C:C,0)} | G69: =C69*5 | H69: 6.82 | I69: =E69*0.025 | J69: =F69*C69+G69-H69-I69 | K69: =IFERROR(J69/E69,0) | L69: =J69*8 | M69: =E69*8 | N69: =IFERROR(H69/E69,0) | O69: 0 | P69: =C69-O69 | Q69: =IFERROR(O69/C69,0) | R69: =IFERROR(H69/(E69*Q69),0) | S69: VC-10%
A70: 46038 | B70: FR | C70: 1 | D70: {=_xlfn.XLOOKUP(B70&S70,'净-价格-毛利'!A:A&'净-价格-毛利'!B:B,'净-价格-毛利'!D:D,0)} | E70: =C70*D70 | F70: {=_xlfn.XLOOKUP(B70&S70,'净-价格-毛利'!A:A&'净-价格-毛利'!B:B,'净-价格-毛利'!C:C,0)} | G70: =C70*6 | I70: =E70*0.025 | J70: =F70*C70+G70-H70-I70 | K70: =IFERROR(J70/E70,0) | L70: =J70*8 | M70: =E70*8 | N70: =IFERROR(H70/E70,0) | O70: 0 | P70: =C70-O70 | Q70: =IFERROR(O70/C70,0) | R70: =IFERROR(H70/(E70*Q70),0) | S70: SC-54.99
A71: 46038 | B71: IT | D71: {=_xlfn.XLOOKUP(B71&S71,'净-价格-毛利'!A:A&'净-价格-毛利'!B:B,'净-价格-毛利'!D:D,0)} | E71: =C71*D71 | F71: {=_xlfn.XLOOKUP(B71&S71,'净-价格-毛利'!A:A&'净-价格-毛利'!B:B,'净-价格-毛利'!C:C,0)} | G71: =C71*5 | H71: 32.09 | I71: =E71*0.025 | J71: =F71*C71+G71-H71-I71 | K71: =IFERROR(J71/E71,0) | L71: =J71*8 | M71: =E71*8 | N71: =IFERROR(H71/E71,0) | O71: 0 | P71: =C71-O71 | Q71: =IFERROR(O71/C71,0) | R71: =IFERROR(H71/(E71*Q71),0) | S71: VC-10%
A72: 46038 | B72: IT | D72: {=_xlfn.XLOOKUP(B72&S72,'净-价格-毛利'!A:A&'净-价格-毛利'!B:B,'净-价格-毛利'!D:D,0)} | E72: =C72*D72 | F72: {=_xlfn.XLOOKUP(B72&S72,'净-价格-毛利'!A:A&'净-价格-毛利'!B:B,'净-价格-毛利'!C:C,0)} | G72: =C72*6 | I72: =E72*0.025 | J72: =F72*C72+G72-H72-I72 | K72: =IFERROR(J72/E72,0) | L72: =J72*8 | M72: =E72*8 | N72: =IFERROR(H72/E72,0) | O72: 0 | P72: =C72-O72 | Q72: =IFERROR(O72/C72,0) | R72: =IFERROR(H72/(E72*Q72),0) | S72: SC-51.99
A73: 46038 | B73: ES | C73: 1 | D73: {=_xlfn.XLOOKUP(B73&S73,'净-价格-毛利'!A:A&'净-价格-毛利'!B:B,'净-价格-毛利'!D:D,0)} | E73: =C73*D73 | F73: {=_xlfn.XLOOKUP(B73&S73,'净-价格-毛利'!A:A&'净-价格-毛利'!B:B,'净-价格-毛利'!C:C,0)} | G73: =C73*5 | H73: 38.76 | I73: =E73*0.025 | J73: =F73*C73+G73-H73-I73 | K73: =IFERROR(J73/E73,0) | L73: =J73*8 | M73: =E73*8 | N73: =IFERROR(H73/E73,0) | O73: 1 | P73: =C73-O73 | Q73: =IFERROR(O73/C73,0) | R73: =IFERROR(H73/(E73*Q73),0) | S73: VC-10%
A74: 46038 | B74: ES | C74: 3 | D74: {=_xlfn.XLOOKUP(B74&S74,'净-价格-毛利'!A:A&'净-价格-毛利'!B:B,'净-价格-毛利'!D:D,0)} | E74: =C74*D74 | F74: {=_xlfn.XLOOKUP(B74&S74,'净-价格-毛利'!A:A&'净-价格-毛利'!B:B,'净-价格-毛利'!C:C,0)} | G74: =C74*6 | H74: 0 | I74: =E74*0.025 | J74: =F74*C74+G74-H74-I74 | K74: =IFERROR(J74/E74,0) | L74: =J74*8 | M74: =E74*8 | N74: =IFERROR(H74/E74,0) | O74: 0 | P74: =C74-O74 | Q74: =IFERROR(O74/C74,0) | R74: =IFERROR(H74/(E74*Q74),0) | S74: SC-54.99
A75: 46038 | B75: UK | D75: {=_xlfn.XLOOKUP(B75&S75,'净-价格-毛利'!A:A&'净-价格-毛利'!B:B,'净-价格-毛利'!D:D,0)} | E75: =C75*D75 | F75: {=_xlfn.XLOOKUP(B75&S75,'净-价格-毛利'!A:A&'净-价格-毛利'!B:B,'净-价格-毛利'!C:C,0)} | G75: =C75*5 | H75: 4.29 | I75: =E75*0.025 | J75: =F75*C75+G75-H75-I75 | K75: =IFERROR(J75/E75,0) | L75: =J75*9 | M75: =E75*9 | N75: =IFERROR(H75/E75,0) | O75: 0 | P75: =C75-O75 | Q75: =IFERROR(O75/C75,0) | R75: =IFERROR(H75/(E75*Q75),0) | S75: BD-6.25
A76: 46038 | B76: UK | D76: {=_xlfn.XLOOKUP(B76&S76,'净-价格-毛利'!A:A&'净-价格-毛利'!B:B,'净-价格-毛利'!D:D,0)} | E76: =C76*D76 | F76: {=_xlfn.XLOOKUP(B76&S76,'净-价格-毛利'!A:A&'净-价格-毛利'!B:B,'净-价格-毛利'!C:C,0)} | G76: =C76*6 | I76: =E76*0.025 | J76: =F76*C76+G76-H76-I76 | K76: =IFERROR(J76/E76,0) | L76: =J76*9 | M76: =E76*9 | N76: =IFERROR(H76/E76,0) | O76: 0 | P76: =C76-O76 | Q76: =IFERROR(O76/C76,0) | R76: =IFERROR(H76/(E76*Q76),0) | S76: SC-45.99
A77: 46038 | B77: US | D77: {=_xlfn.XLOOKUP(B77&S77,'净-价格-毛利'!A:A&'净-价格-毛利'!B:B,'净-价格-毛利'!D:D,0)} | E77: =C77*D77 | F77: {=_xlfn.XLOOKUP(B77&S77,'净-价格-毛利'!A:A&'净-价格-毛利'!B:B,'净-价格-毛利'!C:C,0)} | I77: =E77*0.025 | J77: =C77*F77-H77-I77 | K77: =IFERROR(J77/E77,0) | L77: =J77*7 | M77: =E77*7 | N77: =IFERROR(H77/E77,0) | O77: 0 | P77: =C77-O77 | Q77: =IFERROR(O77/C77,0)
A78: 46038 | B78: 汇总 | C78: =SUM(C67:C77) | E78: =SUM(E67:E77) | F78: =SUM(F67:F76) | J78: =SUM(J67:J77) | K78: =IFERROR(J78/E78,0) | L78: =SUM(L67:L77) | M78: =SUM(M67:M77) | O78: =SUM(O67:O76) | P78: =C78-O78 | Q78: =IFERROR(O78/C78,0)
B79: 分割线
A80: 时间 | B80: 国家 | C80: 数量 | D80: 售价 | E80: 销售额 | F80: 毛利 | G80: 广告预算 | H80: 实际广告 | I80: 活动费 | J80: 毛利 | K80: 毛利率 | L80: 毛利(RMB) | M80: 销售额(RMB) | N80: 广告占比 | O80: 广告订单 | P80: 自然订单 | Q80: 广告订单占比 | R80: ACOS | S80: COUPON
A81: 46039 | B81: DE | C81: 3 | D81: {=_xlfn.XLOOKUP(B81&S81,'净-价格-毛利'!A:A&'净-价格-毛利'!B:B,'净-价格-毛利'!D:D,0)} | E81: =C81*D81 | F81: {=_xlfn.XLOOKUP(B81&S81,'净-价格-毛利'!A:A&'净-价格-毛利'!B:B,'净-价格-毛利'!C:C,0)} | G81: =C81*5 | H81: 54.24 | I81: =E81*0.025 | J81: =F81*C81+G81-H81-I81 | K81: =IFERROR(J81/E81,0) | L81: =J81*8 | M81: =E81*8 | N81: =IFERROR(H81/E81,0) | O81: 2 | P81: =C81-O81 | Q81: =IFERROR(O81/C81,0) | R81: =IFERROR(H81/(E81*Q81),0) | S81: VC-10%
A82: 46039 | B82: DE | D82: {=_xlfn.XLOOKUP(B82&S82,'净-价格-毛利'!A:A&'净-价格-毛利'!B:B,'净-价格-毛利'!D:D,0)} | E82: =C82*D82 | F82: {=_xlfn.XLOOKUP(B82&S82,'净-价格-毛利'!A:A&'净-价格-毛利'!B:B,'净-价格-毛利'!C:C,0)} | G82: =C82*6 | I82: =E82*0.025 | J82: =F82*C82+G82-H82-I82 | K82: =IFERROR(J82/E82,0) | L82: =J82*8 | M82: =E82*8 | N82: =IFERROR(H82/E82,0) | P82: =C82-O82 | Q82: =IFERROR(O82/C82,0) | R82: =IFERROR(H82/(E82*Q82),0) | S82: SC-52.99
A83: 46039 | B83: FR | D83: {=_xlfn.XLOOKUP(B83&S83,'净-价格-毛利'!A:A&'净-价格-毛利'!B:B,'净-价格-毛利'!D:D,0)} | E83: =C83*D83 | F83: {=_xlfn.XLOOKUP(B83&S83,'净-价格-毛利'!A:A&'净-价格-毛利'!B:B,'净-价格-毛利'!C:C,0)} | G83: =C83*5 | H83: 7.1 | I83: =E83*0.025 | J83: =F83*C83+G83-H83-I83 | K83: =IFERROR(J83/E83,0) | L83: =J83*8 | M83: =E83*8 | N83: =IFERROR(H83/E83,0) | P83: =C83-O83 | Q83: =IFERROR(O83/C83,0) | R83: =IFERROR(H83/(E83*Q83),0) | S83: VC-10%
A84: 46039 | B84: FR | D84: {=_xlfn.XLOOKUP(B84&S84,'净-价格-毛利'!A:A&'净-价格-毛利'!B:B,'净-价格-毛利'!D:D,0)} | E84: =C84*D84 | F84: {=_xlfn.XLOOKUP(B84&S84,'净-价格-毛利'!A:A&'净-价格-毛利'!B:B,'净-价格-毛利'!C:C,0)} | G84: =C84*6 | I84: =E84*0.025 | J84: =F84*C84+G84-H84-I84 | K84: =IFERROR(J84/E84,0) | L84: =J84*8 | M84: =E84*8 | N84: =IFERROR(H84/E84,0) | P84: =C84-O84 | Q84: =IFERROR(O84/C84,0) | R84: =IFERROR(H84/(E84*Q84),0) | S84: SC-54.99
A85: 46039 | B85: IT | C85: 1 | D85: {=_xlfn.XLOOKUP(B85&S85,'净-价格-毛利'!A:A&'净-价格-毛利'!B:B,'净-价格-毛利'!D:D,0)} | E85: =C85*D85 | F85: {=_xlfn.XLOOKUP(B85&S85,'净-价格-毛利'!A:A&'净-价格-毛利'!B:B,'净-价格-毛利'!C:C,0)} | G85: =C85*5 | H85: 40.2 | I85: =E85*0.025 | J85: =F85*C85+G85-H85-I85 | K85: =IFERROR(J85/E85,0) | L85: =J85*8 | M85: =E85*8 | N85: =IFERROR(H85/E85,0) | O85: 1 | P85: =C85-O85 | Q85: =IFERROR(O85/C85,0) | R85: =IFERROR(H85/(E85*Q85),0) | S85: VC-10%
A86: 46039 | B86: IT | D86: {=_xlfn.XLOOKUP(B86&S86,'净-价格-毛利'!A:A&'净-价格-毛利'!B:B,'净-价格-毛利'!D:D,0)} | E86: =C86*D86 | F86: {=_xlfn.XLOOKUP(B86&S86,'净-价格-毛利'!A:A&'净-价格-毛利'!B:B,'净-价格-毛利'!C:C,0)} | G86: =C86*6 | I86: =E86*0.025 | J86: =F86*C86+G86-H86-I86 | K86: =IFERROR(J86/E86,0) | L86: =J86*8 | M86: =E86*8 | N86: =IFERROR(H86/E86,0) | P86: =C86-O86 | Q86: =IFERROR(O86/C86,0) | R86: =IFERROR(H86/(E86*Q86),0) | S86: SC-51.99
A87: 46039 | B87: ES | D87: {=_xlfn.XLOOKUP(B87&S87,'净-价格-毛利'!A:A&'净-价格-毛利'!B:B,'净-价格-毛利'!D:D,0)} | E87: =C87*D87 | F87: {=_xlfn.XLOOKUP(B87&S87,'净-价格-毛利'!A:A&'净-价格-毛利'!B:B,'净-价格-毛利'!C:C,0)} | G87: =C87*5 | H87: 49.25 | I87: =E87*0.025 | J87: =F87*C87+G87-H87-I87 | K87: =IFERROR(J87/E87,0) | L87: =J87*8 | M87: =E87*8 | N87: =IFERROR(H87/E87,0) | P87: =C87-O87 | Q87: =IFERROR(O87/C87,0) | R87: =IFERROR(H87/(E87*Q87),0) | S87: VC-10%
A88: 46039 | B88: ES | D88: {=_xlfn.XLOOKUP(B88&S88,'净-价格-毛利'!A:A&'净-价格-毛利'!B:B,'净-价格-毛利'!D:D,0)} | E88: =C88*D88 | F88: {=_xlfn.XLOOKUP(B88&S88,'净-价格-毛利'!A:A&'净-价格-毛利'!B:B,'净-价格-毛利'!C:C,0)} | G88: =C88*6 | I88: =E88*0.025 | J88: =F88*C88+G88-H88-I88 | K88: =IFERROR(J88/E88,0) | L88: =J88*8 | M88: =E88*8 | N88: =IFERROR(H88/E88,0) | P88: =C88-O88 | Q88: =IFERROR(O88/C88,0) | R88: =IFERROR(H88/(E88*Q88),0) | S88: SC-54.99
A89: 46039 | B89: UK | D89: {=_xlfn.XLOOKUP(B89&S89,'净-价格-毛利'!A:A&'净-价格-毛利'!B:B,'净-价格-毛利'!D:D,0)} | E89: =C89*D89 | F89: {=_xlfn.XLOOKUP(B89&S89,'净-价格-毛利'!A:A&'净-价格-毛利'!B:B,'净-价格-毛利'!C:C,0)} | G89: =C89*5 | H89: 12.57 | I89: =E89*0.025 | J89: =F89*C89+G89-H89-I89 | K89: =IFERROR(J89/E89,0) | L89: =J89*9 | M89: =E89*9 | N89: =IFERROR(H89/E89,0) | P89: =C89-O89 | Q89: =IFERROR(O89/C89,0) | R89: =IFERROR(H89/(E89*Q89),0) | S89: BD-6.25
A90: 46039 | B90: UK | D90: {=_xlfn.XLOOKUP(B90&S90,'净-价格-毛利'!A:A&'净-价格-毛利'!B:B,'净-价格-毛利'!D:D,0)} | E90: =C90*D90 | F90: {=_xlfn.XLOOKUP(B90&S90,'净-价格-毛利'!A:A&'净-价格-毛利'!B:B,'净-价格-毛利'!C:C,0)} | G90: =C90*6 | I90: =E90*0.025 | J90: =F90*C90+G90-H90-I90 | K90: =IFERROR(J90/E90,0) | L90: =J90*9 | M90: =E90*9 | N90: =IFERROR(H90/E90,0) | P90: =C90-O90 | Q90: =IFERROR(O90/C90,0) | R90: =IFERROR(H90/(E90*Q90),0) | S90: SC-45.99
A91: 46039 | B91: US | D91: {=_xlfn.XLOOKUP(B91&S91,'净-价格-毛利'!A:A&'净-价格-毛利'!B:B,'净-价格-毛利'!D:D,0)} | E91: =C91*D91 | F91: {=_xlfn.XLOOKUP(B91&S91,'净-价格-毛利'!A:A&'净-价格-毛利'!B:B,'净-价格-毛利'!C:C,0)} | I91: =E91*0.025 | J91: =C91*F91-H91-I91 | K91: =IFERROR(J91/E91,0) | L91: =J91*7 | M91: =E91*7 | N91: =IFERROR(H91/E91,0) | P91: =C91-O91 | Q91: =IFERROR(O91/C91,0)
A92: 46039 | B92: 汇总 | C92: =SUM(C81:C91) | E92: =SUM(E81:E91) | F92: =SUM(F81:F90) | J92: =SUM(J81:J91) | K92: =IFERROR(J92/E92,0) | L92: =SUM(L81:L91) | M92: =SUM(M81:M91) | O92: =SUM(O81:O90) | P92: =C92-O92 | Q92: =IFERROR(O92/C92,0)
B93: 分割线
A94: 时间 | B94: 国家 | C94: 数量 | D94: 售价 | E94: 销售额 | F94: 毛利 | G94: 广告预算 | H94: 实际广告 | I94: 活动费 | J94: 毛利 | K94: 毛利率 | L94: 毛利(RMB) | M94: 销售额(RMB) | N94: 广告占比 | O94: 广告订单 | P94: 自然订单 | Q94: 广告订单占比 | R94: ACOS | S94: COUPON
A95: 46040 | B95: DE | D95: {=_xlfn.XLOOKUP(B95&S95,'净-价格-毛利'!A:A&'净-价格-毛利'!B:B,'净-价格-毛利'!D:D,0)} | E95: =C95*D95 | F95: {=_xlfn.XLOOKUP(B95&S95,'净-价格-毛利'!A:A&'净-价格-毛利'!B:B,'净-价格-毛利'!C:C,0)} | G95: =C95*5 | H95: 103.42 | I95: =E95*0.025 | J95: =F95*C95+G95-H95-I95 | K95: =IFERROR(J95/E95,0) | L95: =J95*8 | M95: =E95*8 | N95: =IFERROR(H95/E95,0) | O95: 0 | P95: =C95-O95 | Q95: =IFERROR(O95/C95,0) | R95: =IFERROR(H95/(E95*Q95),0) | S95: VC-10%
A96: 46040 | B96: DE | D96: {=_xlfn.XLOOKUP(B96&S96,'净-价格-毛利'!A:A&'净-价格-毛利'!B:B,'净-价格-毛利'!D:D,0)} | E96: =C96*D96 | F96: {=_xlfn.XLOOKUP(B96&S96,'净-价格-毛利'!A:A&'净-价格-毛利'!B:B,'净-价格-毛利'!C:C,0)} | G96: =C96*6 | I96: =E96*0.025 | J96: =F96*C96+G96-H96-I96 | K96: =IFERROR(J96/E96,0) | L96: =J96*8 | M96: =E96*8 | N96: =IFERROR(H96/E96,0) | P96: =C96-O96 | Q96: =IFERROR(O96/C96,0) | R96: =IFERROR(H96/(E96*Q96),0) | S96: SC-52.99
A97: 46040 | B97: FR | C97: 2 | D97: {=_xlfn.XLOOKUP(B97&S97,'净-价格-毛利'!A:A&'净-价格-毛利'!B:B,'净-价格-毛利'!D:D,0)} | E97: =C97*D97 | F97: {=_xlfn.XLOOKUP(B97&S97,'净-价格-毛利'!A:A&'净-价格-毛利'!B:B,'净-价格-毛利'!C:C,0)} | G97: =C97*5 | H97: 7.95 | I97: =E97*0.025 | J97: =F97*C97+G97-H97-I97 | K97: =IFERROR(J97/E97,0) | L97: =J97*8 | M97: =E97*8 | N97: =IFERROR(H97/E97,0) | O97: 2 | P97: =C97-O97 | Q97: =IFERROR(O97/C97,0) | R97: =IFERROR(H97/(E97*Q97),0) | S97: VC-10%
A98: 46040 | B98: FR | D98: {=_xlfn.XLOOKUP(B98&S98,'净-价格-毛利'!A:A&'净-价格-毛利'!B:B,'净-价格-毛利'!D:D,0)} | E98: =C98*D98 | F98: {=_xlfn.XLOOKUP(B98&S98,'净-价格-毛利'!A:A&'净-价格-毛利'!B:B,'净-价格-毛利'!C:C,0)} | G98: =C98*6 | I98: =E98*0.025 | J98: =F98*C98+G98-H98-I98 | K98: =IFERROR(J98/E98,0) | L98: =J98*8 | M98: =E98*8 | N98: =IFERROR(H98/E98,0) | P98: =C98-O98 | Q98: =IFERROR(O98/C98,0) | R98: =IFERROR(H98/(E98*Q98),0) | S98: SC-54.99
A99: 46040 | B99: IT | C99: 3 | D99: {=_xlfn.XLOOKUP(B99&S99,'净-价格-毛利'!A:A&'净-价格-毛利'!B:B,'净-价格-毛利'!D:D,0)} | E99: =C99*D99 | F99: {=_xlfn.XLOOKUP(B99&S99,'净-价格-毛利'!A:A&'净-价格-毛利'!B:B,'净-价格-毛利'!C:C,0)} | G99: =C99*5 | H99: 30.6 | I99: =E99*0.025 | J99: =F99*C99+G99-H99-I99 | K99: =IFERROR(J99/E99,0) | L99: =J99*8 | M99: =E99*8 | N99: =IFERROR(H99/E99,0) | O99: 3 | P99: =C99-O99 | Q99: =IFERROR(O99/C99,0) | R99: =IFERROR(H99/(E99*Q99),0) | S99: VC-10%
A100: 46040 | B100: IT | D100: {=_xlfn.XLOOKUP(B100&S100,'净-价格-毛利'!A:A&'净-价格-毛利'!B:B,'净-价格-毛利'!D:D,0)} | E100: =C100*D100 | F100: {=_xlfn.XLOOKUP(B100&S100,'净-价格-毛利'!A:A&'净-价格-毛利'!B:B,'净-价格-毛利'!C:C,0)} | G100: =C100*6 | I100: =E100*0.025 | J100: =F100*C100+G100-H100-I100 | K100: =IFERROR(J100/E100,0) | L100: =J100*8 | M100: =E100*8 | N100: =IFERROR(H100/E100,0) | P100: =C100-O100 | Q100: =IFERROR(O100/C100,0) | R100: =IFERROR(H100/(E100*Q100),0) | S100: SC-51.99
...

Sheet 净-价格-毛利
A1: 国家 | B1: COUPON | C1: 利润 | D1: PO价 | E1: 售价
A2: DE | B2: VC-0% | C2: 9.49 | D2: 34.5 | E2: 49.99
A3: DE | B3: VC-5% | C3: 6.99 | D3: 34.5 | E3: =E2*0.95
A4: DE | B4: VC-10% | C4: 4.49 | D4: 34.5 | E4: =49.99*0.9
A5: DE | B5: VC-15% | C5: 1.99 | D5: 34.5 | E5: =49.99*0.85
A6: DE | B6: BD-6.31 | C6: 2.93 | D6: 34.5
A7: DE | B7: BD-7.56 | C7: 1.68 | D7: 34.5 | E7: 42.49
A8: DE | B8: BD-7.5 | C8: 1.74 | D8: 34.5 | E8: 42.49
A9: DE | B9: SC-49.99 | C9: 6.68 | D9: 49.99 | E9: 49.99
A10: DE | B10: SC-52.99 | C10: 8.85 | D10: 52.99 | E10: 52.99
A11: FR | B11: VC-0% | C11: 8.77 | D11: 34.5 | E11: 51.99
A12: FR | B12: VC-5% | C12: 6.27 | D12: 34.5 | E12: =E11*0.95
A13: FR | B13: VC-10% | C13: 3.77 | D13: 34.5 | E13: =51.99*0.9
A14: FR | B14: VC-15% | C14: 1.27 | D14: 34.5 | E14: =51.99*0.85
A15: FR | B15: BD-7.56 | C15: 2.48 | D15: 34.5 | E15: 45.59
A16: FR | B16: BD-1.9 | C16: 7.58 | D16: 34.5 | E16: 43.31
A17: FR | B17: SC-51.99 | C17: 6.33 | D17: 51.99 | E17: 51.99
A18: FR | B18: SC-54.99 | C18: 8.19 | D18: 54.99 | E18: 54.99
A19: IT | B19: VC-0% | C19: 8.66 | D19: 34.5 | E19: 51.99
A20: IT | B20: VC-5% | C20: 6.16 | D20: 34.5 | E20: =E19*0.95
A21: IT | B21: VC-10% | C21: 3.66 | D21: 34.5 | E21: =51.99*0.9
A22: IT | B22: VC-15% | C22: 1.16 | D22: 34.5 | E22: =51.99*0.85
A23: IT | B23: BD-8.25 | C23: 1.12 | D23: 34.5 | E23: 46.74
A24: IT | B24: BD-7.02 | C24: 2.35 | D24: 34.5 | E24: 39.72
A25: IT | B25: SC-51.99 | C25: 8.11 | D25: 51.99 | E25: 51.99
A26: ES | B26: VC-0% | C26: 8.21 | D26: 34.5 | E26: 51.99
A27: ES | B27: VC-5% | C27: 5.71 | D27: 34.5 | E27: =E26*0.95
A28: ES | B28: VC-10% | C28: 3.21 | D28: 34.5 | E28: =51.99*0.9
A29: ES | B29: VC-15% | C29: 0.71 | D29: 34.5 | E29: =51.99*0.85
A30: ES | B30: BD-6.82 | C30: 2.11 | D30: 34.5 | E30: 46.74
A31: ES | B31: BD-5.8 | C31: 3.13 | D31: 34.5 | E31: 39.72
A32: ES | B32: SC-51.99 | C32: 8.43 | D32: 51.99 | E32: 51.99
A33: ES | B33: SC-54.99 | C33: 10.29 | D33: 54.99 | E33: 54.99
A34: UK | B34: VC-0% | C34: 8.52 | D34: 27.5 | E34: 45.99
A35: UK | B35: VC-10% | C35: 3.92 | D35: 27.5 | E35: =E34*0.9
A36: UK | B36: VC-15% | C36: 1.63 | D36: 27.5 | E36: =E34*0.85
A37: UK | B37: BD-6.25 | C37: 2.27 | D37: 27.5 | E37: 42.49
A38: UK | B38: BD-5.32 | C38: 3.2 | D38: 27.5
A39: UK | B39: BD-5.63 | C39: 2.89 | D39: 27.5 | E39: 38.24
A40: UK | B40: SC-45.99 | C40: 6.32 | D40: 45.99 | E40: 45.99

Sheet 气泵
A1: 汇总 | B1: 国家 | C1: 数量 | D1: 售价 | E1: 销售额 | F1: 毛利 | G1: 广告预算 | H1: 实际广告 | I1: 活动费 | J1: 毛利 | K1: 毛利率 | L1: 毛利(RMB) | M1: 销售额(RMB) | N1: 广告占比 | O1: 广告订单 | P1: 自然订单 | Q1: 广告订单占比 | R1: ACOS | S1: 折扣
A2: 开始时间 | B2: DE | C2: =SUMIFS($C$10:$C$666,$B$10:$B$666,B2,$A$10:$A$666,">="&$A$3,$A$10:$A$666,"<="&$A$5) | D2: 65 | E2: =SUMIFS($E$10:$E$666,$B$10:$B$666,B2,$A$10:$A$666,">="&$A$3,$A$10:$A$666,"<="&$A$5) | G2: =SUMIFS($G$10:$G$666,$B$10:$B$666,B2,$A$10:$A$666,">="&$A$3,$A$10:$A$666,"<="&$A$5) | H2: =SUMIFS($H$10:$H$666,$B$10:$B$666,B2,$A$10:$A$666,">="&$A$3,$A$10:$A$666,"<="&$A$5) | I2: =SUMIFS($I$10:$I$666,$B$10:$B$666,B2,$A$10:$A$666,">="&$A$3,$A$10:$A$666,"<="&$A$5) | J2: =SUMIFS($J$10:$J$666,$B$10:$B$666,B2,$A$10:$A$666,">="&$A$3,$A$10:$A$666,"<="&$A$5) | K2: =J2/E2 | L2: =SUMIFS($L$10:$L$666,$B$10:$B$666,B2,$A$10:$A$666,">="&$A$3,$A$10:$A$666,"<="&$A$5) | M2: =SUMIFS($M$10:$M$666,$B$10:$B$666,B2,$A$10:$A$666,">="&$A$3,$A$10:$A$666,"<="&$A$5) | N2: =H2/E2 | O2: =SUMIFS($O$10:$O$666,$B$10:$B$666,B2,$A$10:$A$666,">="&$A$3,$A$10:$A$666,"<="&$A$5) | P2: =C2-O2 | Q2: =O2/C2 | R2: =H2/(E2*Q2)
A3: 45931 | B3: FR | C3: =SUMIFS($C$10:$C$666,$B$10:$B$666,B3,$A$10:$A$666,">="&$A$3,$A$10:$A$666,"<="&$A$5) | D3: 65 | E3: =SUMIFS($E$10:$E$666,$B$10:$B$666,B3,$A$10:$A$666,">="&$A$3,$A$10:$A$666,"<="&$A$5) | G3: =SUMIFS($G$10:$G$666,$B$10:$B$666,B3,$A$10:$A$666,">="&$A$3,$A$10:$A$666,"<="&$A$5) | H3: =SUMIFS($H$10:$H$666,$B$10:$B$666,B3,$A$10:$A$666,">="&$A$3,$A$10:$A$666,"<="&$A$5) | I3: =SUMIFS($I$10:$I$666,$B$10:$B$666,B3,$A$10:$A$666,">="&$A$3,$A$10:$A$666,"<="&$A$5) | J3: =SUMIFS($J$10:$J$666,$B$10:$B$666,B3,$A$10:$A$666,">="&$A$3,$A$10:$A$666,"<="&$A$5) | K3: =J3/E3 | L3: =SUMIFS($L$10:$L$666,$B$10:$B$666,B3,$A$10:$A$666,">="&$A$3,$A$10:$A$666,"<="&$A$5) | M3: =SUMIFS($M$10:$M$666,$B$10:$B$666,B3,$A$10:$A$666,">="&$A$3,$A$10:$A$666,"<="&$A$5) | N3: =H3/E3 | O3: =SUMIFS($O$10:$O$666,$B$10:$B$666,B3,$A$10:$A$666,">="&$A$3,$A$10:$A$666,"<="&$A$5) | P3: =C3-O3 | Q3: =O3/C3 | R3: =H3/(E3*Q3)
A4: 结束时间 | B4: IT | C4: =SUMIFS($C$10:$C$666,$B$10:$B$666,B4,$A$10:$A$666,">="&$A$3,$A$10:$A$666,"<="&$A$5) | D4: 65 | E4: =SUMIFS($E$10:$E$666,$B$10:$B$666,B4,$A$10:$A$666,">="&$A$3,$A$10:$A$666,"<="&$A$5) | G4: =SUMIFS($G$10:$G$666,$B$10:$B$666,B4,$A$10:$A$666,">="&$A$3,$A$10:$A$666,"<="&$A$5) | H4: =SUMIFS($H$10:$H$666,$B$10:$B$666,B4,$A$10:$A$666,">="&$A$3,$A$10:$A$666,"<="&$A$5) | I4: =SUMIFS($I$10:$I$666,$B$10:$B$666,B4,$A$10:$A$666,">="&$A$3,$A$10:$A$666,"<="&$A$5) | J4: =SUMIFS($J$10:$J$666,$B$10:$B$666,B4,$A$10:$A$666,">="&$A$3,$A$10:$A$666,"<="&$A$5) | K4: =J4/E4 | L4: =SUMIFS($L$10:$L$666,$B$10:$B$666,B4,$A$10:$A$666,">="&$A$3,$A$10:$A$666,"<="&$A$5) | M4: =SUMIFS($M$10:$M$666,$B$10:$B$666,B4,$A$10:$A$666,">="&$A$3,$A$10:$A$666,"<="&$A$5) | N4: =H4/E4 | O4: =SUMIFS($O$10:$O$666,$B$10:$B$666,B4,$A$10:$A$666,">="&$A$3,$A$10:$A$666,"<="&$A$5) | P4: =C4-O4 | Q4: =O4/C4 | R4: =H4/(E4*Q4)
A5: =NOW() | B5: ES | C5: =SUMIFS($C$10:$C$666,$B$10:$B$666,B5,$A$10:$A$666,">="&$A$3,$A$10:$A$666,"<="&$A$5) | D5: 65 | E5: =SUMIFS($E$10:$E$666,$B$10:$B$666,B5,$A$10:$A$666,">="&$A$3,$A$10:$A$666,"<="&$A$5) | G5: =SUMIFS($G$10:$G$666,$B$10:$B$666,B5,$A$10:$A$666,">="&$A$3,$A$10:$A$666,"<="&$A$5) | H5: =SUMIFS($H$10:$H$666,$B$10:$B$666,B5,$A$10:$A$666,">="&$A$3,$A$10:$A$666,"<="&$A$5) | I5: =SUMIFS($I$10:$I$666,$B$10:$B$666,B5,$A$10:$A$666,">="&$A$3,$A$10:$A$666,"<="&$A$5) | J5: =SUMIFS($J$10:$J$666,$B$10:$B$666,B5,$A$10:$A$666,">="&$A$3,$A$10:$A$666,"<="&$A$5) | K5: =J5/E5 | L5: =SUMIFS($L$10:$L$666,$B$10:$B$666,B5,$A$10:$A$666,">="&$A$3,$A$10:$A$666,"<="&$A$5) | M5: =SUMIFS($M$10:$M$666,$B$10:$B$666,B5,$A$10:$A$666,">="&$A$3,$A$10:$A$666,"<="&$A$5) | N5: =H5/E5 | O5: =SUMIFS($O$10:$O$666,$B$10:$B$666,B5,$A$10:$A$666,">="&$A$3,$A$10:$A$666,"<="&$A$5) | P5: =C5-O5 | Q5: =O5/C5 | R5: =H5/(E5*Q5)
A6: 即日 | B6: UK | C6: =SUMIFS($C$10:$C$666,$B$10:$B$666,B6,$A$10:$A$666,">="&$A$3,$A$10:$A$666,"<="&$A$5) | E6: =SUMIFS($E$10:$E$666,$B$10:$B$666,B6,$A$10:$A$666,">="&$A$3,$A$10:$A$666,"<="&$A$5) | G6: =SUMIFS($G$10:$G$666,$B$10:$B$666,B6,$A$10:$A$666,">="&$A$3,$A$10:$A$666,"<="&$A$5) | H6: =SUMIFS($H$10:$H$666,$B$10:$B$666,B6,$A$10:$A$666,">="&$A$3,$A$10:$A$666,"<="&$A$5) | I6: =SUMIFS($I$10:$I$666,$B$10:$B$666,B6,$A$10:$A$666,">="&$A$3,$A$10:$A$666,"<="&$A$5) | J6: =SUMIFS($J$10:$J$666,$B$10:$B$666,B6,$A$10:$A$666,">="&$A$3,$A$10:$A$666,"<="&$A$5) | K6: =J6/E6 | L6: =SUMIFS($L$10:$L$666,$B$10:$B$666,B6,$A$10:$A$666,">="&$A$3,$A$10:$A$666,"<="&$A$5) | M6: =SUMIFS($M$10:$M$666,$B$10:$B$666,B6,$A$10:$A$666,">="&$A$3,$A$10:$A$666,"<="&$A$5) | N6: =H6/E6 | O6: =SUMIFS($O$10:$O$666,$B$10:$B$666,B6,$A$10:$A$666,">="&$A$3,$A$10:$A$666,"<="&$A$5) | P6: =C6-O6 | Q6: =O6/C6 | R6: =H6/(E6*Q6)
A7: =NOW() | B7: US | C7: =SUMIFS($C$10:$C$666,$B$10:$B$666,B7,$A$10:$A$666,">="&$A$3,$A$10:$A$666,"<="&$A$5) | E7: =SUMIFS($E$10:$E$666,$B$10:$B$666,B7,$A$10:$A$666,">="&$A$3,$A$10:$A$666,"<="&$A$5) | G7: =SUMIFS($G$10:$G$666,$B$10:$B$666,B7,$A$10:$A$666,">="&$A$3,$A$10:$A$666,"<="&$A$5) | H7: =SUMIFS($H$10:$H$666,$B$10:$B$666,B7,$A$10:$A$666,">="&$A$3,$A$10:$A$666,"<="&$A$5) | I7: =SUMIFS($I$10:$I$666,$B$10:$B$666,B7,$A$10:$A$666,">="&$A$3,$A$10:$A$666,"<="&$A$5) | J7: =SUMIFS($J$10:$J$666,$B$10:$B$666,B7,$A$10:$A$666,">="&$A$3,$A$10:$A$666,"<="&$A$5) | K7: =J7/E7 | L7: =SUMIFS($L$10:$L$666,$B$10:$B$666,B7,$A$10:$A$666,">="&$A$3,$A$10:$A$666,"<="&$A$5) | M7: =SUMIFS($M$10:$M$666,$B$10:$B$666,B7,$A$10:$A$666,">="&$A$3,$A$10:$A$666,"<="&$A$5) | N7: =H7/E7 | O7: =SUMIFS($O$10:$O$666,$B$10:$B$666,B7,$A$10:$A$666,">="&$A$3,$A$10:$A$666,"<="&$A$5) | P7: =C7-O7 | Q7: =O7/C7 | R7: =H7/(E7*Q7)
B8: 汇总 | C8: =SUM(C2:C7) | K8: =L8/M8 | L8: =SUM(L2:L7) | M8: =SUM(M2:M7) | O8: =SUM(O2:O7) | P8: =C8-O8 | Q8: =O8/C8
B9: 分割线
A10: 时间 | B10: 国家 | C10: 数量 | D10: 售价 | E10: 销售额 | F10: 毛利 | G10: 广告预算 | H10: 实际广告 | I10: 活动费 | J10: 毛利 | K10: 毛利率 | L10: 毛利(RMB) | M10: 销售额(RMB) | N10: 广告占比 | O10: 广告订单 | P10: 自然订单 | Q10: 广告订单占比 | R10: ACOS | S10: COUPON
A11: 45931 | B11: DE | C11: 0 | D11: {=_xlfn.XLOOKUP(B11&S11,'气-价格-毛利'!A:A&'气-价格-毛利'!B:B,'气-价格-毛利'!D:D,0)} | E11: =C11*D11 | F11: {=_xlfn.XLOOKUP(B11&S11,'气-价格-毛利'!A:A&'气-价格-毛利'!B:B,'气-价格-毛利'!C:C,0)} | G11: =C11*8 | I11: =E11*0.025 | J11: =F11*C11+G11-H11-I11 | K11: =IFERROR(J11/E11,0) | L11: =J11*8 | M11: =E11*8 | N11: =IFERROR(H11/E11,0) | P11: =C11-O11 | Q11: =IFERROR(O11/C11,0) | R11: =IFERROR(H11/(E11*Q11),0) | S11: VC-0%
A12: 45931 | B12: DE | C12: 1 | D12: {=_xlfn.XLOOKUP(B12&S12,'气-价格-毛利'!A:A&'气-价格-毛利'!B:B,'气-价格-毛利'!D:D,0)} | E12: =C12*D12 | F12: {=_xlfn.XLOOKUP(B12&S12,'气-价格-毛利'!A:A&'气-价格-毛利'!B:B,'气-价格-毛利'!C:C,0)} | G12: =C12*10 | I12: =E12*0.025 | J12: =F12*C12+G12-H12-I12 | K12: =IFERROR(J12/E12,0) | L12: =J12*8 | M12: =E12*8 | N12: =IFERROR(H12/E12,0) | P12: =C12-O12 | Q12: =IFERROR(O12/C12,0) | R12: =IFERROR(H12/(E12*Q12),0) | S12: SC-15%
A13: 45931 | B13: FR | C13: 0 | D13: {=_xlfn.XLOOKUP(B13&S13,'气-价格-毛利'!A:A&'气-价格-毛利'!B:B,'气-价格-毛利'!D:D,0)} | E13: =C13*D13 | F13: {=_xlfn.XLOOKUP(B13&S13,'气-价格-毛利'!A:A&'气-价格-毛利'!B:B,'气-价格-毛利'!C:C,0)} | G13: =C13*8 | I13: =E13*0.025 | J13: =F13*C13+G13-H13-I13 | K13: =IFERROR(J13/E13,0) | L13: =J13*8 | M13: =E13*8 | N13: =IFERROR(H13/E13,0) | P13: =C13-O13 | Q13: =IFERROR(O13/C13,0) | R13: =IFERROR(H13/(E13*Q13),0) | S13: VC-0%
A14: 45931 | B14: FR | C14: 0 | D14: {=_xlfn.XLOOKUP(B14&S14,'气-价格-毛利'!A:A&'气-价格-毛利'!B:B,'气-价格-毛利'!D:D,0)} | E14: =C14*D14 | F14: {=_xlfn.XLOOKUP(B14&S14,'气-价格-毛利'!A:A&'气-价格-毛利'!B:B,'气-价格-毛利'!C:C,0)} | G14: =C14*10 | I14: =E14*0.025 | J14: =F14*C14+G14-H14-I14 | K14: =IFERROR(J14/E14,0) | L14: =J14*8 | M14: =E14*8 | N14: =IFERROR(H14/E14,0) | P14: =C14-O14 | Q14: =IFERROR(O14/C14,0) | R14: =IFERROR(H14/(E14*Q14),0) | S14: SC-15%
A15: 45931 | B15: IT | C15: 0 | D15: {=_xlfn.XLOOKUP(B15&S15,'气-价格-毛利'!A:A&'气-价格-毛利'!B:B,'气-价格-毛利'!D:D,0)} | E15: =C15*D15 | F15: {=_xlfn.XLOOKUP(B15&S15,'气-价格-毛利'!A:A&'气-价格-毛利'!B:B,'气-价格-毛利'!C:C,0)} | G15: =C15*8 | I15: =E15*0.025 | J15: =F15*C15+G15-H15-I15 | K15: =IFERROR(J15/E15,0) | L15: =J15*8 | M15: =E15*8 | N15: =IFERROR(H15/E15,0) | P15: =C15-O15 | Q15: =IFERROR(O15/C15,0) | R15: =IFERROR(H15/(E15*Q15),0) | S15: VC-0%
A16: 45931 | B16: IT | C16: 3 | D16: {=_xlfn.XLOOKUP(B16&S16,'气-价格-毛利'!A:A&'气-价格-毛利'!B:B,'气-价格-毛利'!D:D,0)} | E16: =C16*D16 | F16: {=_xlfn.XLOOKUP(B16&S16,'气-价格-毛利'!A:A&'气-价格-毛利'!B:B,'气-价格-毛利'!C:C,0)} | G16: =C16*10 | I16: =E16*0.025 | J16: =F16*C16+G16-H16-I16 | K16: =IFERROR(J16/E16,0) | L16: =J16*8 | M16: =E16*8 | N16: =IFERROR(H16/E16,0) | P16: =C16-O16 | Q16: =IFERROR(O16/C16,0) | R16: =IFERROR(H16/(E16*Q16),0) | S16: SC-15%
A17: 45931 | B17: ES | C17: 0 | D17: {=_xlfn.XLOOKUP(B17&S17,'气-价格-毛利'!A:A&'气-价格-毛利'!B:B,'气-价格-毛利'!D:D,0)} | E17: =C17*D17 | F17: {=_xlfn.XLOOKUP(B17&S17,'气-价格-毛利'!A:A&'气-价格-毛利'!B:B,'气-价格-毛利'!C:C,0)} | G17: =C17*8 | I17: =E17*0.025 | J17: =F17*C17+G17-H17-I17 | K17: =IFERROR(J17/E17,0) | L17: =J17*8 | M17: =E17*8 | N17: =IFERROR(H17/E17,0) | P17: =C17-O17 | Q17: =IFERROR(O17/C17,0) | R17: =IFERROR(H17/(E17*Q17),0) | S17: VC-0%
A18: 45931 | B18: ES | C18: 1 | D18: {=_xlfn.XLOOKUP(B18&S18,'气-价格-毛利'!A:A&'气-价格-毛利'!B:B,'气-价格-毛利'!D:D,0)} | E18: =C18*D18 | F18: {=_xlfn.XLOOKUP(B18&S18,'气-价格-毛利'!A:A&'气-价格-毛利'!B:B,'气-价格-毛利'!C:C,0)} | G18: =C18*10 | I18: =E18*0.025 | J18: =F18*C18+G18-H18-I18 | K18: =IFERROR(J18/E18,0) | L18: =J18*8 | M18: =E18*8 | N18: =IFERROR(H18/E18,0) | P18: =C18-O18 | Q18: =IFERROR(O18/C18,0) | R18: =IFERROR(H18/(E18*Q18),0) | S18: SC-15%
A19: 45931 | B19: UK | D19: {=_xlfn.XLOOKUP(B19&S19,'气-价格-毛利'!A:A&'气-价格-毛利'!B:B,'气-价格-毛利'!D:D,0)} | E19: =C19*D19 | F19: {=_xlfn.XLOOKUP(B19&S19,'气-价格-毛利'!A:A&'气-价格-毛利'!B:B,'气-价格-毛利'!C:C,0)} | G19: =C19*8 | I19: =E19*0.025 | J19: =F19*C19+G19-H19-I19 | K19: =IFERROR(J19/E19,0) | L19: =J19*9 | M19: =E19*9 | N19: =IFERROR(H19/E19,0) | P19: =C19-O19 | Q19: =IFERROR(O19/C19,0) | R19: =IFERROR(H19/(E19*Q19),0)
A20: 45931 | B20: UK | D20: {=_xlfn.XLOOKUP(B20&S20,'气-价格-毛利'!A:A&'气-价格-毛利'!B:B,'气-价格-毛利'!D:D,0)} | E20: =C20*D20 | F20: {=_xlfn.XLOOKUP(B20&S20,'气-价格-毛利'!A:A&'气-价格-毛利'!B:B,'气-价格-毛利'!C:C,0)} | G20: =C20*8 | I20: =E20*0.025 | J20: =F20*C20+G20-H20-I20 | K20: =IFERROR(J20/E20,0) | L20: =J20*9 | M20: =E20*9 | N20: =IFERROR(H20/E20,0) | P20: =C20-O20 | Q20: =IFERROR(O20/C20,0) | R20: =IFERROR(H20/(E20*Q20),0)
A21: 45931 | B21: US | D21: {=_xlfn.XLOOKUP(B21&S21,'气-价格-毛利'!A:A&'气-价格-毛利'!B:B,'气-价格-毛利'!D:D,0)} | E21: =C21*D21 | F21: {=_xlfn.XLOOKUP(B21&S21,'气-价格-毛利'!A:A&'气-价格-毛利'!B:B,'气-价格-毛利'!C:C,0)} | I21: =E21*0.025 | J21: =C21*F21-H21-I21 | K21: =IFERROR(J21/E21,0) | L21: =J21*7 | M21: =E21*7 | N21: =IFERROR(H21/E21,0) | P21: =C21-O21 | Q21: =IFERROR(O21/C21,0)
A22: 45931 | B22: 汇总 | C22: =SUM(C11:C21) | E22: =SUM(E11:E21) | F22: =SUM(F11:F20) | J22: =SUM(J11:J21) | K22: =IFERROR(J22/E22,0) | L22: =SUM(L11:L21) | M22: =SUM(M11:M21) | O22: =SUM(O11:O20) | P22: =C22-O22 | Q22: =IFERROR(O22/C22,0)
B23: 分割线
A24: 时间 | B24: 国家 | C24: 数量 | D24: 售价 | E24: 销售额 | F24: 毛利 | G24: 广告预算 | H24: 实际广告 | I24: 活动费 | J24: 毛利 | K24: 毛利率 | L24: 毛利(RMB) | M24: 销售额(RMB) | N24: 广告占比 | O24: 广告订单 | P24: 自然订单 | Q24: 广告订单占比 | R24: ACOS | S24: COUPON
A25: 45932 | B25: DE | C25: 0 | D25: {=_xlfn.XLOOKUP(B25&S25,'气-价格-毛利'!A:A&'气-价格-毛利'!B:B,'气-价格-毛利'!D:D,0)} | E25: =C25*D25 | F25: {=_xlfn.XLOOKUP(B25&S25,'气-价格-毛利'!A:A&'气-价格-毛利'!B:B,'气-价格-毛利'!C:C,0)} | G25: =C25*8 | I25: =E25*0.025 | J25: =F25*C25+G25-H25-I25 | K25: =IFERROR(J25/E25,0) | L25: =J25*8 | M25: =E25*8 | N25: =IFERROR(H25/E25,0) | P25: =C25-O25 | Q25: =IFERROR(O25/C25,0) | R25: =IFERROR(H25/(E25*Q25),0) | S25: VC-0%
A26: 45932 | B26: DE | C26: 3 | D26: {=_xlfn.XLOOKUP(B26&S26,'气-价格-毛利'!A:A&'气-价格-毛利'!B:B,'气-价格-毛利'!D:D,0)} | E26: =C26*D26 | F26: {=_xlfn.XLOOKUP(B26&S26,'气-价格-毛利'!A:A&'气-价格-毛利'!B:B,'气-价格-毛利'!C:C,0)} | G26: =C26*10 | I26: =E26*0.025 | J26: =F26*C26+G26-H26-I26 | K26: =IFERROR(J26/E26,0) | L26: =J26*8 | M26: =E26*8 | N26: =IFERROR(H26/E26,0) | P26: =C26-O26 | Q26: =IFERROR(O26/C26,0) | R26: =IFERROR(H26/(E26*Q26),0) | S26: SC-15%
A27: 45932 | B27: FR | C27: 0 | D27: {=_xlfn.XLOOKUP(B27&S27,'气-价格-毛利'!A:A&'气-价格-毛利'!B:B,'气-价格-毛利'!D:D,0)} | E27: =C27*D27 | F27: {=_xlfn.XLOOKUP(B27&S27,'气-价格-毛利'!A:A&'气-价格-毛利'!B:B,'气-价格-毛利'!C:C,0)} | G27: =C27*8 | I27: =E27*0.025 | J27: =F27*C27+G27-H27-I27 | K27: =IFERROR(J27/E27,0) | L27: =J27*8 | M27: =E27*8 | N27: =IFERROR(H27/E27,0) | P27: =C27-O27 | Q27: =IFERROR(O27/C27,0) | R27: =IFERROR(H27/(E27*Q27),0) | S27: VC-0%
A28: 45932 | B28: FR | C28: 0 | D28: {=_xlfn.XLOOKUP(B28&S28,'气-价格-毛利'!A:A&'气-价格-毛利'!B:B,'气-价格-毛利'!D:D,0)} | E28: =C28*D28 | F28: {=_xlfn.XLOOKUP(B28&S28,'气-价格-毛利'!A:A&'气-价格-毛利'!B:B,'气-价格-毛利'!C:C,0)} | G28: =C28*10 | I28: =E28*0.025 | J28: =F28*C28+G28-H28-I28 | K28: =IFERROR(J28/E28,0) | L28: =J28*8 | M28: =E28*8 | N28: =IFERROR(H28/E28,0) | P28: =C28-O28 | Q28: =IFERROR(O28/C28,0) | R28: =IFERROR(H28/(E28*Q28),0) | S28: SC-15%
A29: 45932 | B29: IT | C29: 0 | D29: {=_xlfn.XLOOKUP(B29&S29,'气-价格-毛利'!A:A&'气-价格-毛利'!B:B,'气-价格-毛利'!D:D,0)} | E29: =C29*D29 | F29: {=_xlfn.XLOOKUP(B29&S29,'气-价格-毛利'!A:A&'气-价格-毛利'!B:B,'气-价格-毛利'!C:C,0)} | G29: =C29*8 | I29: =E29*0.025 | J29: =F29*C29+G29-H29-I29 | K29: =IFERROR(J29/E29,0) | L29: =J29*8 | M29: =E29*8 | N29: =IFERROR(H29/E29,0) | P29: =C29-O29 | Q29: =IFERROR(O29/C29,0) | R29: =IFERROR(H29/(E29*Q29),0) | S29: VC-0%
A30: 45932 | B30: IT | C30: 4 | D30: {=_xlfn.XLOOKUP(B30&S30,'气-价格-毛利'!A:A&'气-价格-毛利'!B:B,'气-价格-毛利'!D:D,0)} | E30: =C30*D30 | F30: {=_xlfn.XLOOKUP(B30&S30,'气-价格-毛利'!A:A&'气-价格-毛利'!B:B,'气-价格-毛利'!C:C,0)} | G30: =C30*10 | I30: =E30*0.025 | J30: =F30*C30+G30-H30-I30 | K30: =IFERROR(J30/E30,0) | L30: =J30*8 | M30: =E30*8 | N30: =IFERROR(H30/E30,0) | P30: =C30-O30 | Q30: =IFERROR(O30/C30,0) | R30: =IFERROR(H30/(E30*Q30),0) | S30: SC-15%
A31: 45932 | B31: ES | C31: 0 | D31: {=_xlfn.XLOOKUP(B31&S31,'气-价格-毛利'!A:A&'气-价格-毛利'!B:B,'气-价格-毛利'!D:D,0)} | E31: =C31*D31 | F31: {=_xlfn.XLOOKUP(B31&S31,'气-价格-毛利'!A:A&'气-价格-毛利'!B:B,'气-价格-毛利'!C:C,0)} | G31: =C31*8 | I31: =E31*0.025 | J31: =F31*C31+G31-H31-I31 | K31: =IFERROR(J31/E31,0) | L31: =J31*8 | M31: =E31*8 | N31: =IFERROR(H31/E31,0) | P31: =C31-O31 | Q31: =IFERROR(O31/C31,0) | R31: =IFERROR(H31/(E31*Q31),0) | S31: VC-0%
A32: 45932 | B32: ES | C32: 2 | D32: {=_xlfn.XLOOKUP(B32&S32,'气-价格-毛利'!A:A&'气-价格-毛利'!B:B,'气-价格-毛利'!D:D,0)} | E32: =C32*D32 | F32: {=_xlfn.XLOOKUP(B32&S32,'气-价格-毛利'!A:A&'气-价格-毛利'!B:B,'气-价格-毛利'!C:C,0)} | G32: =C32*10 | I32: =E32*0.025 | J32: =F32*C32+G32-H32-I32 | K32: =IFERROR(J32/E32,0) | L32: =J32*8 | M32: =E32*8 | N32: =IFERROR(H32/E32,0) | P32: =C32-O32 | Q32: =IFERROR(O32/C32,0) | R32: =IFERROR(H32/(E32*Q32),0) | S32: SC-15%
A33: 45932 | B33: UK | D33: {=_xlfn.XLOOKUP(B33&S33,'气-价格-毛利'!A:A&'气-价格-毛利'!B:B,'气-价格-毛利'!D:D,0)} | E33: =C33*D33 | F33: {=_xlfn.XLOOKUP(B33&S33,'气-价格-毛利'!A:A&'气-价格-毛利'!B:B,'气-价格-毛利'!C:C,0)} | G33: =C33*8 | I33: =E33*0.025 | J33: =F33*C33+G33-H33-I33 | K33: =IFERROR(J33/E33,0) | L33: =J33*9 | M33: =E33*9 | N33: =IFERROR(H33/E33,0) | P33: =C33-O33 | Q33: =IFERROR(O33/C33,0) | R33: =IFERROR(H33/(E33*Q33),0)
A34: 45932 | B34: UK | D34: {=_xlfn.XLOOKUP(B34&S34,'气-价格-毛利'!A:A&'气-价格-毛利'!B:B,'气-价格-毛利'!D:D,0)} | E34: =C34*D34 | F34: {=_xlfn.XLOOKUP(B34&S34,'气-价格-毛利'!A:A&'气-价格-毛利'!B:B,'气-价格-毛利'!C:C,0)} | G34: =C34*8 | I34: =E34*0.025 | J34: =F34*C34+G34-H34-I34 | K34: =IFERROR(J34/E34,0) | L34: =J34*9 | M34: =E34*9 | N34: =IFERROR(H34/E34,0) | P34: =C34-O34 | Q34: =IFERROR(O34/C34,0) | R34: =IFERROR(H34/(E34*Q34),0)
A35: 45932 | B35: US | D35: {=_xlfn.XLOOKUP(B35&S35,'气-价格-毛利'!A:A&'气-价格-毛利'!B:B,'气-价格-毛利'!D:D,0)} | E35: =C35*D35 | F35: {=_xlfn.XLOOKUP(B35&S35,'气-价格-毛利'!A:A&'气-价格-毛利'!B:B,'气-价格-毛利'!C:C,0)} | I35: =E35*0.025 | J35: =C35*F35-H35-I35 | K35: =IFERROR(J35/E35,0) | L35: =J35*7 | M35: =E35*7 | N35: =IFERROR(H35/E35,0) | P35: =C35-O35 | Q35: =IFERROR(O35/C35,0)
A36: 45932 | B36: 汇总 | C36: =SUM(C25:C35) | E36: =SUM(E25:E35) | F36: =SUM(F25:F34) | J36: =SUM(J25:J35) | K36: =IFERROR(J36/E36,0) | L36: =SUM(L25:L35) | M36: =SUM(M25:M35) | O36: =SUM(O25:O34) | P36: =C36-O36 | Q36: =IFERROR(O36/C36,0)
B37: 分割线
A38: 时间 | B38: 国家 | C38: 数量 | D38: 售价 | E38: 销售额 | F38: 毛利 | G38: 广告预算 | H38: 实际广告 | I38: 活动费 | J38: 毛利 | K38: 毛利率 | L38: 毛利(RMB) | M38: 销售额(RMB) | N38: 广告占比 | O38: 广告订单 | P38: 自然订单 | Q38: 广告订单占比 | R38: ACOS | S38: COUPON
A39: 45933 | B39: DE | C39: 0 | D39: {=_xlfn.XLOOKUP(B39&S39,'气-价格-毛利'!A:A&'气-价格-毛利'!B:B,'气-价格-毛利'!D:D,0)} | E39: =C39*D39 | F39: {=_xlfn.XLOOKUP(B39&S39,'气-价格-毛利'!A:A&'气-价格-毛利'!B:B,'气-价格-毛利'!C:C,0)} | G39: =C39*8 | I39: =E39*0.025 | J39: =F39*C39+G39-H39-I39 | K39: =IFERROR(J39/E39,0) | L39: =J39*8 | M39: =E39*8 | N39: =IFERROR(H39/E39,0) | P39: =C39-O39 | Q39: =IFERROR(O39/C39,0) | R39: =IFERROR(H39/(E39*Q39),0) | S39: VC-0%
A40: 45933 | B40: DE | C40: 1 | D40: {=_xlfn.XLOOKUP(B40&S40,'气-价格-毛利'!A:A&'气-价格-毛利'!B:B,'气-价格-毛利'!D:D,0)} | E40: =C40*D40 | F40: {=_xlfn.XLOOKUP(B40&S40,'气-价格-毛利'!A:A&'气-价格-毛利'!B:B,'气-价格-毛利'!C:C,0)} | G40: =C40*10 | I40: =E40*0.025 | J40: =F40*C40+G40-H40-I40 | K40: =IFERROR(J40/E40,0) | L40: =J40*8 | M40: =E40*8 | N40: =IFERROR(H40/E40,0) | P40: =C40-O40 | Q40: =IFERROR(O40/C40,0) | R40: =IFERROR(H40/(E40*Q40),0) | S40: SC-15%
A41: 45933 | B41: FR | C41: 0 | D41: {=_xlfn.XLOOKUP(B41&S41,'气-价格-毛利'!A:A&'气-价格-毛利'!B:B,'气-价格-毛利'!D:D,0)} | E41: =C41*D41 | F41: {=_xlfn.XLOOKUP(B41&S41,'气-价格-毛利'!A:A&'气-价格-毛利'!B:B,'气-价格-毛利'!C:C,0)} | G41: =C41*8 | I41: =E41*0.025 | J41: =F41*C41+G41-H41-I41 | K41: =IFERROR(J41/E41,0) | L41: =J41*8 | M41: =E41*8 | N41: =IFERROR(H41/E41,0) | P41: =C41-O41 | Q41: =IFERROR(O41/C41,0) | R41: =IFERROR(H41/(E41*Q41),0) | S41: VC-0%
A42: 45933 | B42: FR | C42: 0 | D42: {=_xlfn.XLOOKUP(B42&S42,'气-价格-毛利'!A:A&'气-价格-毛利'!B:B,'气-价格-毛利'!D:D,0)} | E42: =C42*D42 | F42: {=_xlfn.XLOOKUP(B42&S42,'气-价格-毛利'!A:A&'气-价格-毛利'!B:B,'气-价格-毛利'!C:C,0)} | G42: =C42*10 | I42: =E42*0.025 | J42: =F42*C42+G42-H42-I42 | K42: =IFERROR(J42/E42,0) | L42: =J42*8 | M42: =E42*8 | N42: =IFERROR(H42/E42,0) | P42: =C42-O42 | Q42: =IFERROR(O42/C42,0) | R42: =IFERROR(H42/(E42*Q42),0) | S42: SC-15%
A43: 45933 | B43: IT | C43: 0 | D43: {=_xlfn.XLOOKUP(B43&S43,'气-价格-毛利'!A:A&'气-价格-毛利'!B:B,'气-价格-毛利'!D:D,0)} | E43: =C43*D43 | F43: {=_xlfn.XLOOKUP(B43&S43,'气-价格-毛利'!A:A&'气-价格-毛利'!B:B,'气-价格-毛利'!C:C,0)} | G43: =C43*8 | I43: =E43*0.025 | J43: =F43*C43+G43-H43-I43 | K43: =IFERROR(J43/E43,0) | L43: =J43*8 | M43: =E43*8 | N43: =IFERROR(H43/E43,0) | P43: =C43-O43 | Q43: =IFERROR(O43/C43,0) | R43: =IFERROR(H43/(E43*Q43),0) | S43: VC-0%
A44: 45933 | B44: IT | C44: 3 | D44: {=_xlfn.XLOOKUP(B44&S44,'气-价格-毛利'!A:A&'气-价格-毛利'!B:B,'气-价格-毛利'!D:D,0)} | E44: =C44*D44 | F44: {=_xlfn.XLOOKUP(B44&S44,'气-价格-毛利'!A:A&'气-价格-毛利'!B:B,'气-价格-毛利'!C:C,0)} | G44: =C44*10 | I44: =E44*0.025 | J44: =F44*C44+G44-H44-I44 | K44: =IFERROR(J44/E44,0) | L44: =J44*8 | M44: =E44*8 | N44: =IFERROR(H44/E44,0) | P44: =C44-O44 | Q44: =IFERROR(O44/C44,0) | R44: =IFERROR(H44/(E44*Q44),0) | S44: SC-15%
A45: 45933 | B45: ES | C45: 0 | D45: {=_xlfn.XLOOKUP(B45&S45,'气-价格-毛利'!A:A&'气-价格-毛利'!B:B,'气-价格-毛利'!D:D,0)} | E45: =C45*D45 | F45: {=_xlfn.XLOOKUP(B45&S45,'气-价格-毛利'!A:A&'气-价格-毛利'!B:B,'气-价格-毛利'!C:C,0)} | G45: =C45*8 | I45: =E45*0.025 | J45: =F45*C45+G45-H45-I45 | K45: =IFERROR(J45/E45,0) | L45: =J45*8 | M45: =E45*8 | N45: =IFERROR(H45/E45,0) | P45: =C45-O45 | Q45: =IFERROR(O45/C45,0) | R45: =IFERROR(H45/(E45*Q45),0) | S45: VC-0%
A46: 45933 | B46: ES | C46: 1 | D46: {=_xlfn.XLOOKUP(B46&S46,'气-价格-毛利'!A:A&'气-价格-毛利'!B:B,'气-价格-毛利'!D:D,0)} | E46: =C46*D46 | F46: {=_xlfn.XLOOKUP(B46&S46,'气-价格-毛利'!A:A&'气-价格-毛利'!B:B,'气-价格-毛利'!C:C,0)} | G46: =C46*10 | I46: =E46*0.025 | J46: =F46*C46+G46-H46-I46 | K46: =IFERROR(J46/E46,0) | L46: =J46*8 | M46: =E46*8 | N46: =IFERROR(H46/E46,0) | P46: =C46-O46 | Q46: =IFERROR(O46/C46,0) | R46: =IFERROR(H46/(E46*Q46),0) | S46: SC-15%
A47: 45933 | B47: UK | D47: {=_xlfn.XLOOKUP(B47&S47,'气-价格-毛利'!A:A&'气-价格-毛利'!B:B,'气-价格-毛利'!D:D,0)} | E47: =C47*D47 | F47: {=_xlfn.XLOOKUP(B47&S47,'气-价格-毛利'!A:A&'气-价格-毛利'!B:B,'气-价格-毛利'!C:C,0)} | G47: =C47*8 | I47: =E47*0.025 | J47: =F47*C47+G47-H47-I47 | K47: =IFERROR(J47/E47,0) | L47: =J47*9 | M47: =E47*9 | N47: =IFERROR(H47/E47,0) | P47: =C47-O47 | Q47: =IFERROR(O47/C47,0) | R47: =IFERROR(H47/(E47*Q47),0)
A48: 45933 | B48: UK | D48: {=_xlfn.XLOOKUP(B48&S48,'气-价格-毛利'!A:A&'气-价格-毛利'!B:B,'气-价格-毛利'!D:D,0)} | E48: =C48*D48 | F48: {=_xlfn.XLOOKUP(B48&S48,'气-价格-毛利'!A:A&'气-价格-毛利'!B:B,'气-价格-毛利'!C:C,0)} | G48: =C48*8 | I48: =E48*0.025 | J48: =F48*C48+G48-H48-I48 | K48: =IFERROR(J48/E48,0) | L48: =J48*9 | M48: =E48*9 | N48: =IFERROR(H48/E48,0) | P48: =C48-O48 | Q48: =IFERROR(O48/C48,0) | R48: =IFERROR(H48/(E48*Q48),0)
A49: 45933 | B49: US | D49: {=_xlfn.XLOOKUP(B49&S49,'气-价格-毛利'!A:A&'气-价格-毛利'!B:B,'气-价格-毛利'!D:D,0)} | E49: =C49*D49 | F49: {=_xlfn.XLOOKUP(B49&S49,'气-价格-毛利'!A:A&'气-价格-毛利'!B:B,'气-价格-毛利'!C:C,0)} | I49: =E49*0.025 | J49: =C49*F49-H49-I49 | K49: =IFERROR(J49/E49,0) | L49: =J49*7 | M49: =E49*7 | N49: =IFERROR(H49/E49,0) | P49: =C49-O49 | Q49: =IFERROR(O49/C49,0)
A50: 45933 | B50: 汇总 | C50: =SUM(C39:C49) | E50: =SUM(E39:E49) | F50: =SUM(F39:F48) | J50: =SUM(J39:J49) | K50: =IFERROR(J50/E50,0) | L50: =SUM(L39:L49) | M50: =SUM(M39:M49) | O50: =SUM(O39:O48) | P50: =C50-O50 | Q50: =IFERROR(O50/C50,0)
B51: 分割线
A52: 时间 | B52: 国家 | C52: 数量 | D52: 售价 | E52: 销售额 | F52: 毛利 | G52: 广告预算 | H52: 实际广告 | I52: 活动费 | J52: 毛利 | K52: 毛利率 | L52: 毛利(RMB) | M52: 销售额(RMB) | N52: 广告占比 | O52: 广告订单 | P52: 自然订单 | Q52: 广告订单占比 | R52: ACOS | S52: COUPON
A53: 45934 | B53: DE | C53: 0 | D53: {=_xlfn.XLOOKUP(B53&S53,'气-价格-毛利'!A:A&'气-价格-毛利'!B:B,'气-价格-毛利'!D:D,0)} | E53: =C53*D53 | F53: {=_xlfn.XLOOKUP(B53&S53,'气-价格-毛利'!A:A&'气-价格-毛利'!B:B,'气-价格-毛利'!C:C,0)} | G53: =C53*8 | I53: =E53*0.025 | J53: =F53*C53+G53-H53-I53 | K53: =IFERROR(J53/E53,0) | L53: =J53*8 | M53: =E53*8 | N53: =IFERROR(H53/E53,0) | P53: =C53-O53 | Q53: =IFERROR(O53/C53,0) | R53: =IFERROR(H53/(E53*Q53),0) | S53: VC-0%
A54: 45934 | B54: DE | C54: 0 | D54: {=_xlfn.XLOOKUP(B54&S54,'气-价格-毛利'!A:A&'气-价格-毛利'!B:B,'气-价格-毛利'!D:D,0)} | E54: =C54*D54 | F54: {=_xlfn.XLOOKUP(B54&S54,'气-价格-毛利'!A:A&'气-价格-毛利'!B:B,'气-价格-毛利'!C:C,0)} | G54: =C54*10 | I54: =E54*0.025 | J54: =F54*C54+G54-H54-I54 | K54: =IFERROR(J54/E54,0) | L54: =J54*8 | M54: =E54*8 | N54: =IFERROR(H54/E54,0) | P54: =C54-O54 | Q54: =IFERROR(O54/C54,0) | R54: =IFERROR(H54/(E54*Q54),0) | S54: SC-15%
A55: 45934 | B55: FR | C55: 0 | D55: {=_xlfn.XLOOKUP(B55&S55,'气-价格-毛利'!A:A&'气-价格-毛利'!B:B,'气-价格-毛利'!D:D,0)} | E55: =C55*D55 | F55: {=_xlfn.XLOOKUP(B55&S55,'气-价格-毛利'!A:A&'气-价格-毛利'!B:B,'气-价格-毛利'!C:C,0)} | G55: =C55*8 | I55: =E55*0.025 | J55: =F55*C55+G55-H55-I55 | K55: =IFERROR(J55/E55,0) | L55: =J55*8 | M55: =E55*8 | N55: =IFERROR(H55/E55,0) | P55: =C55-O55 | Q55: =IFERROR(O55/C55,0) | R55: =IFERROR(H55/(E55*Q55),0) | S55: VC-0%
A56: 45934 | B56: FR | C56: 0 | D56: {=_xlfn.XLOOKUP(B56&S56,'气-价格-毛利'!A:A&'气-价格-毛利'!B:B,'气-价格-毛利'!D:D,0)} | E56: =C56*D56 | F56: {=_xlfn.XLOOKUP(B56&S56,'气-价格-毛利'!A:A&'气-价格-毛利'!B:B,'气-价格-毛利'!C:C,0)} | G56: =C56*10 | I56: =E56*0.025 | J56: =F56*C56+G56-H56-I56 | K56: =IFERROR(J56/E56,0) | L56: =J56*8 | M56: =E56*8 | N56: =IFERROR(H56/E56,0) | P56: =C56-O56 | Q56: =IFERROR(O56/C56,0) | R56: =IFERROR(H56/(E56*Q56),0) | S56: SC-15%
A57: 45934 | B57: IT | C57: 0 | D57: {=_xlfn.XLOOKUP(B57&S57,'气-价格-毛利'!A:A&'气-价格-毛利'!B:B,'气-价格-毛利'!D:D,0)} | E57: =C57*D57 | F57: {=_xlfn.XLOOKUP(B57&S57,'气-价格-毛利'!A:A&'气-价格-毛利'!B:B,'气-价格-毛利'!C:C,0)} | G57: =C57*8 | I57: =E57*0.025 | J57: =F57*C57+G57-H57-I57 | K57: =IFERROR(J57/E57,0) | L57: =J57*8 | M57: =E57*8 | N57: =IFERROR(H57/E57,0) | P57: =C57-O57 | Q57: =IFERROR(O57/C57,0) | R57: =IFERROR(H57/(E57*Q57),0) | S57: VC-0%
A58: 45934 | B58: IT | C58: 2 | D58: {=_xlfn.XLOOKUP(B58&S58,'气-价格-毛利'!A:A&'气-价格-毛利'!B:B,'气-价格-毛利'!D:D,0)} | E58: =C58*D58 | F58: {=_xlfn.XLOOKUP(B58&S58,'气-价格-毛利'!A:A&'气-价格-毛利'!B:B,'气-价格-毛利'!C:C,0)} | G58: =C58*10 | I58: =E58*0.025 | J58: =F58*C58+G58-H58-I58 | K58: =IFERROR(J58/E58,0) | L58: =J58*8 | M58: =E58*8 | N58: =IFERROR(H58/E58,0) | P58: =C58-O58 | Q58: =IFERROR(O58/C58,0) | R58: =IFERROR(H58/(E58*Q58),0) | S58: SC-15%
A59: 45934 | B59: ES | C59: 0 | D59: {=_xlfn.XLOOKUP(B59&S59,'气-价格-毛利'!A:A&'气-价格-毛利'!B:B,'气-价格-毛利'!D:D,0)} | E59: =C59*D59 | F59: {=_xlfn.XLOOKUP(B59&S59,'气-价格-毛利'!A:A&'气-价格-毛利'!B:B,'气-价格-毛利'!C:C,0)} | G59: =C59*8 | I59: =E59*0.025 | J59: =F59*C59+G59-H59-I59 | K59: =IFERROR(J59/E59,0) | L59: =J59*8 | M59: =E59*8 | N59: =IFERROR(H59/E59,0) | P59: =C59-O59 | Q59: =IFERROR(O59/C59,0) | R59: =IFERROR(H59/(E59*Q59),0) | S59: VC-0%
A60: 45934 | B60: ES | C60: 1 | D60: {=_xlfn.XLOOKUP(B60&S60,'气-价格-毛利'!A:A&'气-价格-毛利'!B:B,'气-价格-毛利'!D:D,0)} | E60: =C60*D60 | F60: {=_xlfn.XLOOKUP(B60&S60,'气-价格-毛利'!A:A&'气-价格-毛利'!B:B,'气-价格-毛利'!C:C,0)} | G60: =C60*10 | I60: =E60*0.025 | J60: =F60*C60+G60-H60-I60 | K60: =IFERROR(J60/E60,0) | L60: =J60*8 | M60: =E60*8 | N60: =IFERROR(H60/E60,0) | P60: =C60-O60 | Q60: =IFERROR(O60/C60,0) | R60: =IFERROR(H60/(E60*Q60),0) | S60: SC-15%
A61: 45934 | B61: UK | D61: {=_xlfn.XLOOKUP(B61&S61,'气-价格-毛利'!A:A&'气-价格-毛利'!B:B,'气-价格-毛利'!D:D,0)} | E61: =C61*D61 | F61: {=_xlfn.XLOOKUP(B61&S61,'气-价格-毛利'!A:A&'气-价格-毛利'!B:B,'气-价格-毛利'!C:C,0)} | G61: =C61*8 | I61: =E61*0.025 | J61: =F61*C61+G61-H61-I61 | K61: =IFERROR(J61/E61,0) | L61: =J61*9 | M61: =E61*9 | N61: =IFERROR(H61/E61,0) | P61: =C61-O61 | Q61: =IFERROR(O61/C61,0) | R61: =IFERROR(H61/(E61*Q61),0)
A62: 45934 | B62: UK | D62: {=_xlfn.XLOOKUP(B62&S62,'气-价格-毛利'!A:A&'气-价格-毛利'!B:B,'气-价格-毛利'!D:D,0)} | E62: =C62*D62 | F62: {=_xlfn.XLOOKUP(B62&S62,'气-价格-毛利'!A:A&'气-价格-毛利'!B:B,'气-价格-毛利'!C:C,0)} | G62: =C62*8 | I62: =E62*0.025 | J62: =F62*C62+G62-H62-I62 | K62: =IFERROR(J62/E62,0) | L62: =J62*9 | M62: =E62*9 | N62: =IFERROR(H62/E62,0) | P62: =C62-O62 | Q62: =IFERROR(O62/C62,0) | R62: =IFERROR(H62/(E62*Q62),0)
A63: 45934 | B63: US | D63: {=_xlfn.XLOOKUP(B63&S63,'气-价格-毛利'!A:A&'气-价格-毛利'!B:B,'气-价格-毛利'!D:D,0)} | E63: =C63*D63 | F63: {=_xlfn.XLOOKUP(B63&S63,'气-价格-毛利'!A:A&'气-价格-毛利'!B:B,'气-价格-毛利'!C:C,0)} | I63: =E63*0.025 | J63: =C63*F63-H63-I63 | K63: =IFERROR(J63/E63,0) | L63: =J63*7 | M63: =E63*7 | N63: =IFERROR(H63/E63,0) | P63: =C63-O63 | Q63: =IFERROR(O63/C63,0)
A64: 45934 | B64: 汇总 | C64: =SUM(C53:C63) | E64: =SUM(E53:E63) | F64: =SUM(F53:F62) | J64: =SUM(J53:J63) | K64: =IFERROR(J64/E64,0) | L64: =SUM(L53:L63) | M64: =SUM(M53:M63) | O64: =SUM(O53:O62) | P64: =C64-O64 | Q64: =IFERROR(O64/C64,0)
B65: 分割线
A66: 时间 | B66: 国家 | C66: 数量 | D66: 售价 | E66: 销售额 | F66: 毛利 | G66: 广告预算 | H66: 实际广告 | I66: 活动费 | J66: 毛利 | K66: 毛利率 | L66: 毛利(RMB) | M66: 销售额(RMB) | N66: 广告占比 | O66: 广告订单 | P66: 自然订单 | Q66: 广告订单占比 | R66: ACOS | S66: COUPON
A67: 45935 | B67: DE | C67: 0 | D67: {=_xlfn.XLOOKUP(B67&S67,'气-价格-毛利'!A:A&'气-价格-毛利'!B:B,'气-价格-毛利'!D:D,0)} | E67: =C67*D67 | F67: {=_xlfn.XLOOKUP(B67&S67,'气-价格-毛利'!A:A&'气-价格-毛利'!B:B,'气-价格-毛利'!C:C,0)} | G67: =C67*8 | I67: =E67*0.025 | J67: =F67*C67+G67-H67-I67 | K67: =IFERROR(J67/E67,0) | L67: =J67*8 | M67: =E67*8 | N67: =IFERROR(H67/E67,0) | P67: =C67-O67 | Q67: =IFERROR(O67/C67,0) | R67: =IFERROR(H67/(E67*Q67),0) | S67: VC-0%
A68: 45935 | B68: DE | C68: 1 | D68: {=_xlfn.XLOOKUP(B68&S68,'气-价格-毛利'!A:A&'气-价格-毛利'!B:B,'气-价格-毛利'!D:D,0)} | E68: =C68*D68 | F68: {=_xlfn.XLOOKUP(B68&S68,'气-价格-毛利'!A:A&'气-价格-毛利'!B:B,'气-价格-毛利'!C:C,0)} | G68: =C68*10 | I68: =E68*0.025 | J68: =F68*C68+G68-H68-I68 | K68: =IFERROR(J68/E68,0) | L68: =J68*8 | M68: =E68*8 | N68: =IFERROR(H68/E68,0) | P68: =C68-O68 | Q68: =IFERROR(O68/C68,0) | R68: =IFERROR(H68/(E68*Q68),0) | S68: SC-15%
A69: 45935 | B69: FR | C69: 0 | D69: {=_xlfn.XLOOKUP(B69&S69,'气-价格-毛利'!A:A&'气-价格-毛利'!B:B,'气-价格-毛利'!D:D,0)} | E69: =C69*D69 | F69: {=_xlfn.XLOOKUP(B69&S69,'气-价格-毛利'!A:A&'气-价格-毛利'!B:B,'气-价格-毛利'!C:C,0)} | G69: =C69*8 | I69: =E69*0.025 | J69: =F69*C69+G69-H69-I69 | K69: =IFERROR(J69/E69,0) | L69: =J69*8 | M69: =E69*8 | N69: =IFERROR(H69/E69,0) | P69: =C69-O69 | Q69: =IFERROR(O69/C69,0) | R69: =IFERROR(H69/(E69*Q69),0) | S69: VC-0%
A70: 45935 | B70: FR | C70: 0 | D70: {=_xlfn.XLOOKUP(B70&S70,'气-价格-毛利'!A:A&'气-价格-毛利'!B:B,'气-价格-毛利'!D:D,0)} | E70: =C70*D70 | F70: {=_xlfn.XLOOKUP(B70&S70,'气-价格-毛利'!A:A&'气-价格-毛利'!B:B,'气-价格-毛利'!C:C,0)} | G70: =C70*10 | I70: =E70*0.025 | J70: =F70*C70+G70-H70-I70 | K70: =IFERROR(J70/E70,0) | L70: =J70*8 | M70: =E70*8 | N70: =IFERROR(H70/E70,0) | P70: =C70-O70 | Q70: =IFERROR(O70/C70,0) | R70: =IFERROR(H70/(E70*Q70),0) | S70: SC-15%
A71: 45935 | B71: IT | C71: 0 | D71: {=_xlfn.XLOOKUP(B71&S71,'气-价格-毛利'!A:A&'气-价格-毛利'!B:B,'气-价格-毛利'!D:D,0)} | E71: =C71*D71 | F71: {=_xlfn.XLOOKUP(B71&S71,'气-价格-毛利'!A:A&'气-价格-毛利'!B:B,'气-价格-毛利'!C:C,0)} | G71: =C71*8 | I71: =E71*0.025 | J71: =F71*C71+G71-H71-I71 | K71: =IFERROR(J71/E71,0) | L71: =J71*8 | M71: =E71*8 | N71: =IFERROR(H71/E71,0) | P71: =C71-O71 | Q71: =IFERROR(O71/C71,0) | R71: =IFERROR(H71/(E71*Q71),0) | S71: VC-0%
A72: 45935 | B72: IT | C72: 2 | D72: {=_xlfn.XLOOKUP(B72&S72,'气-价格-毛利'!A:A&'气-价格-毛利'!B:B,'气-价格-毛利'!D:D,0)} | E72: =C72*D72 | F72: {=_xlfn.XLOOKUP(B72&S72,'气-价格-毛利'!A:A&'气-价格-毛利'!B:B,'气-价格-毛利'!C:C,0)} | G72: =C72*10 | I72: =E72*0.025 | J72: =F72*C72+G72-H72-I72 | K72: =IFERROR(J72/E72,0) | L72: =J72*8 | M72: =E72*8 | N72: =IFERROR(H72/E72,0) | P72: =C72-O72 | Q72: =IFERROR(O72/C72,0) | R72: =IFERROR(H72/(E72*Q72),0) | S72: SC-15%
A73: 45935 | B73: ES | C73: 0 | D73: {=_xlfn.XLOOKUP(B73&S73,'气-价格-毛利'!A:A&'气-价格-毛利'!B:B,'气-价格-毛利'!D:D,0)} | E73: =C73*D73 | F73: {=_xlfn.XLOOKUP(B73&S73,'气-价格-毛利'!A:A&'气-价格-毛利'!B:B,'气-价格-毛利'!C:C,0)} | G73: =C73*8 | I73: =E73*0.025 | J73: =F73*C73+G73-H73-I73 | K73: =IFERROR(J73/E73,0) | L73: =J73*8 | M73: =E73*8 | N73: =IFERROR(H73/E73,0) | P73: =C73-O73 | Q73: =IFERROR(O73/C73,0) | R73: =IFERROR(H73/(E73*Q73),0) | S73: VC-0%
A74: 45935 | B74: ES | C74: 2 | D74: {=_xlfn.XLOOKUP(B74&S74,'气-价格-毛利'!A:A&'气-价格-毛利'!B:B,'气-价格-毛利'!D:D,0)} | E74: =C74*D74 | F74: {=_xlfn.XLOOKUP(B74&S74,'气-价格-毛利'!A:A&'气-价格-毛利'!B:B,'气-价格-毛利'!C:C,0)} | G74: =C74*10 | I74: =E74*0.025 | J74: =F74*C74+G74-H74-I74 | K74: =IFERROR(J74/E74,0) | L74: =J74*8 | M74: =E74*8 | N74: =IFERROR(H74/E74,0) | P74: =C74-O74 | Q74: =IFERROR(O74/C74,0) | R74: =IFERROR(H74/(E74*Q74),0) | S74: SC-15%
A75: 45935 | B75: UK | D75: {=_xlfn.XLOOKUP(B75&S75,'气-价格-毛利'!A:A&'气-价格-毛利'!B:B,'气-价格-毛利'!D:D,0)} | E75: =C75*D75 | F75: {=_xlfn.XLOOKUP(B75&S75,'气-价格-毛利'!A:A&'气-价格-毛利'!B:B,'气-价格-毛利'!C:C,0)} | G75: =C75*8 | I75: =E75*0.025 | J75: =F75*C75+G75-H75-I75 | K75: =IFERROR(J75/E75,0) | L75: =J75*9 | M75: =E75*9 | N75: =IFERROR(H75/E75,0) | P75: =C75-O75 | Q75: =IFERROR(O75/C75,0) | R75: =IFERROR(H75/(E75*Q75),0)
A76: 45935 | B76: UK | D76: {=_xlfn.XLOOKUP(B76&S76,'气-价格-毛利'!A:A&'气-价格-毛利'!B:B,'气-价格-毛利'!D:D,0)} | E76: =C76*D76 | F76: {=_xlfn.XLOOKUP(B76&S76,'气-价格-毛利'!A:A&'气-价格-毛利'!B:B,'气-价格-毛利'!C:C,0)} | G76: =C76*8 | I76: =E76*0.025 | J76: =F76*C76+G76-H76-I76 | K76: =IFERROR(J76/E76,0) | L76: =J76*9 | M76: =E76*9 | N76: =IFERROR(H76/E76,0) | P76: =C76-O76 | Q76: =IFERROR(O76/C76,0) | R76: =IFERROR(H76/(E76*Q76),0)
A77: 45935 | B77: US | D77: {=_xlfn.XLOOKUP(B77&S77,'气-价格-毛利'!A:A&'气-价格-毛利'!B:B,'气-价格-毛利'!D:D,0)} | E77: =C77*D77 | F77: {=_xlfn.XLOOKUP(B77&S77,'气-价格-毛利'!A:A&'气-价格-毛利'!B:B,'气-价格-毛利'!C:C,0)} | I77: =E77*0.025 | J77: =C77*F77-H77-I77 | K77: =IFERROR(J77/E77,0) | L77: =J77*7 | M77: =E77*7 | N77: =IFERROR(H77/E77,0) | P77: =C77-O77 | Q77: =IFERROR(O77/C77,0)
A78: 45935 | B78: 汇总 | C78: =SUM(C67:C77) | E78: =SUM(E67:E77) | F78: =SUM(F67:F76) | J78: =SUM(J67:J77) | K78: =IFERROR(J78/E78,0) | L78: =SUM(L67:L77) | M78: =SUM(M67:M77) | O78: =SUM(O67:O76) | P78: =C78-O78 | Q78: =IFERROR(O78/C78,0)
B79: 分割线
A80: 时间 | B80: 国家 | C80: 数量 | D80: 售价 | E80: 销售额 | F80: 毛利 | G80: 广告预算 | H80: 实际广告 | I80: 活动费 | J80: 毛利 | K80: 毛利率 | L80: 毛利(RMB) | M80: 销售额(RMB) | N80: 广告占比 | O80: 广告订单 | P80: 自然订单 | Q80: 广告订单占比 | R80: ACOS | S80: COUPON
A81: 45936 | B81: DE | C81: 0 | D81: {=_xlfn.XLOOKUP(B81&S81,'气-价格-毛利'!A:A&'气-价格-毛利'!B:B,'气-价格-毛利'!D:D,0)} | E81: =C81*D81 | F81: {=_xlfn.XLOOKUP(B81&S81,'气-价格-毛利'!A:A&'气-价格-毛利'!B:B,'气-价格-毛利'!C:C,0)} | G81: =C81*8 | I81: =E81*0.025 | J81: =F81*C81+G81-H81-I81 | K81: =IFERROR(J81/E81,0) | L81: =J81*8 | M81: =E81*8 | N81: =IFERROR(H81/E81,0) | P81: =C81-O81 | Q81: =IFERROR(O81/C81,0) | R81: =IFERROR(H81/(E81*Q81),0) | S81: VC-0%
A82: 45936 | B82: DE | C82: 0 | D82: {=_xlfn.XLOOKUP(B82&S82,'气-价格-毛利'!A:A&'气-价格-毛利'!B:B,'气-价格-毛利'!D:D,0)} | E82: =C82*D82 | F82: {=_xlfn.XLOOKUP(B82&S82,'气-价格-毛利'!A:A&'气-价格-毛利'!B:B,'气-价格-毛利'!C:C,0)} | G82: =C82*10 | I82: =E82*0.025 | J82: =F82*C82+G82-H82-I82 | K82: =IFERROR(J82/E82,0) | L82: =J82*8 | M82: =E82*8 | N82: =IFERROR(H82/E82,0) | P82: =C82-O82 | Q82: =IFERROR(O82/C82,0) | R82: =IFERROR(H82/(E82*Q82),0) | S82: SC-15%
A83: 45936 | B83: FR | C83: 0 | D83: {=_xlfn.XLOOKUP(B83&S83,'气-价格-毛利'!A:A&'气-价格-毛利'!B:B,'气-价格-毛利'!D:D,0)} | E83: =C83*D83 | F83: {=_xlfn.XLOOKUP(B83&S83,'气-价格-毛利'!A:A&'气-价格-毛利'!B:B,'气-价格-毛利'!C:C,0)} | G83: =C83*8 | I83: =E83*0.025 | J83: =F83*C83+G83-H83-I83 | K83: =IFERROR(J83/E83,0) | L83: =J83*8 | M83: =E83*8 | N83: =IFERROR(H83/E83,0) | P83: =C83-O83 | Q83: =IFERROR(O83/C83,0) | R83: =IFERROR(H83/(E83*Q83),0) | S83: VC-0%
A84: 45936 | B84: FR | C84: 1 | D84: {=_xlfn.XLOOKUP(B84&S84,'气-价格-毛利'!A:A&'气-价格-毛利'!B:B,'气-价格-毛利'!D:D,0)} | E84: =C84*D84 | F84: {=_xlfn.XLOOKUP(B84&S84,'气-价格-毛利'!A:A&'气-价格-毛利'!B:B,'气-价格-毛利'!C:C,0)} | G84: =C84*10 | I84: =E84*0.025 | J84: =F84*C84+G84-H84-I84 | K84: =IFERROR(J84/E84,0) | L84: =J84*8 | M84: =E84*8 | N84: =IFERROR(H84/E84,0) | P84: =C84-O84 | Q84: =IFERROR(O84/C84,0) | R84: =IFERROR(H84/(E84*Q84),0) | S84: SC-15%
A85: 45936 | B85: IT | C85: 0 | D85: {=_xlfn.XLOOKUP(B85&S85,'气-价格-毛利'!A:A&'气-价格-毛利'!B:B,'气-价格-毛利'!D:D,0)} | E85: =C85*D85 | F85: {=_xlfn.XLOOKUP(B85&S85,'气-价格-毛利'!A:A&'气-价格-毛利'!B:B,'气-价格-毛利'!C:C,0)} | G85: =C85*8 | I85: =E85*0.025 | J85: =F85*C85+G85-H85-I85 | K85: =IFERROR(J85/E85,0) | L85: =J85*8 | M85: =E85*8 | N85: =IFERROR(H85/E85,0) | P85: =C85-O85 | Q85: =IFERROR(O85/C85,0) | R85: =IFERROR(H85/(E85*Q85),0) | S85: VC-0%
A86: 45936 | B86: IT | C86: 3 | D86: {=_xlfn.XLOOKUP(B86&S86,'气-价格-毛利'!A:A&'气-价格-毛利'!B:B,'气-价格-毛利'!D:D,0)} | E86: =C86*D86 | F86: {=_xlfn.XLOOKUP(B86&S86,'气-价格-毛利'!A:A&'气-价格-毛利'!B:B,'气-价格-毛利'!C:C,0)} | G86: =C86*10 | I86: =E86*0.025 | J86: =F86*C86+G86-H86-I86 | K86: =IFERROR(J86/E86,0) | L86: =J86*8 | M86: =E86*8 | N86: =IFERROR(H86/E86,0) | P86: =C86-O86 | Q86: =IFERROR(O86/C86,0) | R86: =IFERROR(H86/(E86*Q86),0) | S86: SC-15%
A87: 45936 | B87: ES | C87: 0 | D87: {=_xlfn.XLOOKUP(B87&S87,'气-价格-毛利'!A:A&'气-价格-毛利'!B:B,'气-价格-毛利'!D:D,0)} | E87: =C87*D87 | F87: {=_xlfn.XLOOKUP(B87&S87,'气-价格-毛利'!A:A&'气-价格-毛利'!B:B,'气-价格-毛利'!C:C,0)} | G87: =C87*8 | I87: =E87*0.025 | J87: =F87*C87+G87-H87-I87 | K87: =IFERROR(J87/E87,0) | L87: =J87*8 | M87: =E87*8 | N87: =IFERROR(H87/E87,0) | P87: =C87-O87 | Q87: =IFERROR(O87/C87,0) | R87: =IFERROR(H87/(E87*Q87),0) | S87: VC-0%
A88: 45936 | B88: ES | C88: 0 | D88: {=_xlfn.XLOOKUP(B88&S88,'气-价格-毛利'!A:A&'气-价格-毛利'!B:B,'气-价格-毛利'!D:D,0)} | E88: =C88*D88 | F88: {=_xlfn.XLOOKUP(B88&S88,'气-价格-毛利'!A:A&'气-价格-毛利'!B:B,'气-价格-毛利'!C:C,0)} | G88: =C88*10 | I88: =E88*0.025 | J88: =F88*C88+G88-H88-I88 | K88: =IFERROR(J88/E88,0) | L88: =J88*8 | M88: =E88*8 | N88: =IFERROR(H88/E88,0) | P88: =C88-O88 | Q88: =IFERROR(O88/C88,0) | R88: =IFERROR(H88/(E88*Q88),0) | S88: SC-15%
A89: 45936 | B89: UK | D89: {=_xlfn.XLOOKUP(B89&S89,'气-价格-毛利'!A:A&'气-价格-毛利'!B:B,'气-价格-毛利'!D:D,0)} | E89: =C89*D89 | F89: {=_xlfn.XLOOKUP(B89&S89,'气-价格-毛利'!A:A&'气-价格-毛利'!B:B,'气-价格-毛利'!C:C,0)} | G89: =C89*8 | I89: =E89*0.025 | J89: =F89*C89+G89-H89-I89 | K89: =IFERROR(J89/E89,0) | L89: =J89*9 | M89: =E89*9 | N89: =IFERROR(H89/E89,0) | P89: =C89-O89 | Q89: =IFERROR(O89/C89,0) | R89: =IFERROR(H89/(E89*Q89),0)
A90: 45936 | B90: UK | D90: {=_xlfn.XLOOKUP(B90&S90,'气-价格-毛利'!A:A&'气-价格-毛利'!B:B,'气-价格-毛利'!D:D,0)} | E90: =C90*D90 | F90: {=_xlfn.XLOOKUP(B90&S90,'气-价格-毛利'!A:A&'气-价格-毛利'!B:B,'气-价格-毛利'!C:C,0)} | G90: =C90*8 | I90: =E90*0.025 | J90: =F90*C90+G90-H90-I90 | K90: =IFERROR(J90/E90,0) | L90: =J90*9 | M90: =E90*9 | N90: =IFERROR(H90/E90,0) | P90: =C90-O90 | Q90: =IFERROR(O90/C90,0) | R90: =IFERROR(H90/(E90*Q90),0)
A91: 45936 | B91: US | D91: {=_xlfn.XLOOKUP(B91&S91,'气-价格-毛利'!A:A&'气-价格-毛利'!B:B,'气-价格-毛利'!D:D,0)} | E91: =C91*D91 | F91: {=_xlfn.XLOOKUP(B91&S91,'气-价格-毛利'!A:A&'气-价格-毛利'!B:B,'气-价格-毛利'!C:C,0)} | I91: =E91*0.025 | J91: =C91*F91-H91-I91 | K91: =IFERROR(J91/E91,0) | L91: =J91*7 | M91: =E91*7 | N91: =IFERROR(H91/E91,0) | P91: =C91-O91 | Q91: =IFERROR(O91/C91,0)
A92: 45936 | B92: 汇总 | C92: =SUM(C81:C91) | E92: =SUM(E81:E91) | F92: =SUM(F81:F90) | J92: =SUM(J81:J91) | K92: =IFERROR(J92/E92,0) | L92: =SUM(L81:L91) | M92: =SUM(M81:M91) | O92: =SUM(O81:O90) | P92: =C92-O92 | Q92: =IFERROR(O92/C92,0)
B93: 分割线
A94: 时间 | B94: 国家 | C94: 数量 | D94: 售价 | E94: 销售额 | F94: 毛利 | G94: 广告预算 | H94: 实际广告 | I94: 活动费 | J94: 毛利 | K94: 毛利率 | L94: 毛利(RMB) | M94: 销售额(RMB) | N94: 广告占比 | O94: 广告订单 | P94: 自然订单 | Q94: 广告订单占比 | R94: ACOS | S94: COUPON
A95: 45937 | B95: DE | C95: 0 | D95: {=_xlfn.XLOOKUP(B95&S95,'气-价格-毛利'!A:A&'气-价格-毛利'!B:B,'气-价格-毛利'!D:D,0)} | E95: =C95*D95 | F95: {=_xlfn.XLOOKUP(B95&S95,'气-价格-毛利'!A:A&'气-价格-毛利'!B:B,'气-价格-毛利'!C:C,0)} | G95: =C95*8 | I95: =E95*0.025 | J95: =F95*C95+G95-H95-I95 | K95: =IFERROR(J95/E95,0) | L95: =J95*8 | M95: =E95*8 | N95: =IFERROR(H95/E95,0) | P95: =C95-O95 | Q95: =IFERROR(O95/C95,0) | R95: =IFERROR(H95/(E95*Q95),0) | S95: VC-0%
A96: 45937 | B96: DE | C96: 1 | D96: {=_xlfn.XLOOKUP(B96&S96,'气-价格-毛利'!A:A&'气-价格-毛利'!B:B,'气-价格-毛利'!D:D,0)} | E96: =C96*D96 | F96: {=_xlfn.XLOOKUP(B96&S96,'气-价格-毛利'!A:A&'气-价格-毛利'!B:B,'气-价格-毛利'!C:C,0)} | G96: =C96*10 | I96: =E96*0.025 | J96: =F96*C96+G96-H96-I96 | K96: =IFERROR(J96/E96,0) | L96: =J96*8 | M96: =E96*8 | N96: =IFERROR(H96/E96,0) | P96: =C96-O96 | Q96: =IFERROR(O96/C96,0) | R96: =IFERROR(H96/(E96*Q96),0) | S96: SC-15%
A97: 45937 | B97: FR | C97: 0 | D97: {=_xlfn.XLOOKUP(B97&S97,'气-价格-毛利'!A:A&'气-价格-毛利'!B:B,'气-价格-毛利'!D:D,0)} | E97: =C97*D97 | F97: {=_xlfn.XLOOKUP(B97&S97,'气-价格-毛利'!A:A&'气-价格-毛利'!B:B,'气-价格-毛利'!C:C,0)} | G97: =C97*8 | I97: =E97*0.025 | J97: =F97*C97+G97-H97-I97 | K97: =IFERROR(J97/E97,0) | L97: =J97*8 | M97: =E97*8 | N97: =IFERROR(H97/E97,0) | P97: =C97-O97 | Q97: =IFERROR(O97/C97,0) | R97: =IFERROR(H97/(E97*Q97),0) | S97: VC-0%
A98: 45937 | B98: FR | C98: 0 | D98: {=_xlfn.XLOOKUP(B98&S98,'气-价格-毛利'!A:A&'气-价格-毛利'!B:B,'气-价格-毛利'!D:D,0)} | E98: =C98*D98 | F98: {=_xlfn.XLOOKUP(B98&S98,'气-价格-毛利'!A:A&'气-价格-毛利'!B:B,'气-价格-毛利'!C:C,0)} | G98: =C98*10 | I98: =E98*0.025 | J98: =F98*C98+G98-H98-I98 | K98: =IFERROR(J98/E98,0) | L98: =J98*8 | M98: =E98*8 | N98: =IFERROR(H98/E98,0) | P98: =C98-O98 | Q98: =IFERROR(O98/C98,0) | R98: =IFERROR(H98/(E98*Q98),0) | S98: SC-15%
A99: 45937 | B99: IT | C99: 0 | D99: {=_xlfn.XLOOKUP(B99&S99,'气-价格-毛利'!A:A&'气-价格-毛利'!B:B,'气-价格-毛利'!D:D,0)} | E99: =C99*D99 | F99: {=_xlfn.XLOOKUP(B99&S99,'气-价格-毛利'!A:A&'气-价格-毛利'!B:B,'气-价格-毛利'!C:C,0)} | G99: =C99*8 | I99: =E99*0.025 | J99: =F99*C99+G99-H99-I99 | K99: =IFERROR(J99/E99,0) | L99: =J99*8 | M99: =E99*8 | N99: =IFERROR(H99/E99,0) | P99: =C99-O99 | Q99: =IFERROR(O99/C99,0) | R99: =IFERROR(H99/(E99*Q99),0) | S99: VC-0%
A100: 45937 | B100: IT | C100: 0 | D100: {=_xlfn.XLOOKUP(B100&S100,'气-价格-毛利'!A:A&'气-价格-毛利'!B:B,'气-价格-毛利'!D:D,0)} | E100: =C100*D100 | F100: {=_xlfn.XLOOKUP(B100&S100,'气-价格-毛利'!A:A&'气-价格-毛利'!B:B,'气-价格-毛利'!C:C,0)} | G100: =C100*10 | I100: =E100*0.025 | J100: =F100*C100+G100-H100-I100 | K100: =IFERROR(J100/E100,0) | L100: =J100*8 | M100: =E100*8 | N100: =IFERROR(H100/E100,0) | P100: =C100-O100 | Q100: =IFERROR(O100/C100,0) | R100: =IFERROR(H100/(E100*Q100),0) | S100: SC-12%
...

Sheet 气-价格-毛利
A1: 国家 | B1: COUPON | C1: 利润 | D1: PO价 | E1: 售价
A2: DE | B2: VC-0% | C2: 20.05 | D2: 65 | E2: 94.99
A3: DE | B3: VC-5% | D3: 65 | E3: =E2*0.95
A4: DE | B4: VC-10% | C4: 10.55 | D4: 65 | E4: =E2*0.9
A5: DE | B5: VC-15% | C5: 5.8 | D5: 65 | E5: =E2*0.85
A6: DE | B6: SC-0% | C6: 19.28 | D6: =E6 | E6: 94.99
A7: DE | B7: SC-10% | C7: 13.49 | D7: =E7*0.9 | E7: 94.99
A8: DE | B8: SC-12% | C8: 12.33 | D8: =E8*0.88 | E8: 94.99
A9: DE | B9: SC-15% | C9: 10.59 | D9: =E9*0.85 | E9: 94.99
A10: FR | B10: VC-0% | C10: 17.66 | D10: 65 | E10: 94.99
A11: FR | B11: VC-5% | D11: 65 | E11: =E10*0.95
A12: FR | B12: VC-10% | C12: 8.16 | D12: 65 | E12: =E10*0.9
A13: FR | B13: VC-15% | C13: 3.41 | D13: 65 | E13: =E10*0.85
A14: FR | B14: SC-0% | C14: 17.44 | D14: =E14 | E14: 94.99
A15: FR | B15: SC-10% | C15: 11.65 | D15: =E15*0.9 | E15: 94.99
A16: FR | B16: SC-12% | C16: 10.49 | D16: =E16*0.88 | E16: 94.99
A17: FR | B17: SC-15% | C17: 8.75 | D17: =E17*0.85 | E17: 94.99
A18: IT | B18: VC-0% | C18: 18.45 | D18: 65 | E18: 94.99
A19: IT | B19: VC-5% | D19: 65 | E19: =E18*0.95
A20: IT | B20: VC-10% | C20: 8.95 | D20: 65 | E20: =E18*0.9
A21: IT | B21: VC-12% | D21: 65 | E21: =E18*0.88
A22: IT | B22: VC-15% | C22: 4.2 | D22: 65 | E22: =E18*0.85
A23: IT | B23: SC-0% | C23: 17.8 | D23: =E23 | E23: 94.99
A24: IT | B24: SC-10% | C24: 12.01 | D24: =E24*0.9 | E24: 94.99
A25: IT | B25: SC-12% | C25: 10.5 | D25: =E25*0.88 | E25: 94.99
A26: IT | B26: SC-15% | C26: 9.11 | D26: =E26*0.85 | E26: 94.99
A27: ES | B27: VC-0% | C27: 19.41 | D27: 65 | E27: 94.99
A28: ES | B28: VC-5% | D28: 65 | E28: =E27*0.95
A29: ES | B29: VC-10% | C29: 9.91 | D29: 65 | E29: =E27*0.9
A30: ES | B30: VC-12% | D30: 65 | E30: =E27*0.88
A31: ES | B31: VC-15% | C31: 5.16 | D31: 65 | E31: =E27*0.85
A32: ES | B32: SC-0% | C32: 19.1 | D32: =E32 | E32: 94.99
A33: ES | B33: SC-10% | C33: 13.31 | D33: =E33*0.9 | E33: 94.99
A34: ES | B34: SC-12% | C34: 12.15 | D34: =E34*0.88 | E34: 94.99
A35: ES | B35: SC-15% | C35: 8.75 | D35: =E35*0.85 | E35: 94.99
A36: ES | B36: 2VC-10% | C36: 4.88 | D36: 56.5 | E36: =81.99*0.9
A37: IT | B37: 2VC-10% | C37: 3.4 | D37: 56.5 | E37: =81.99*0.9
A38: FR | B38: 2VC-10% | C38: 2.73 | D38: 56.5 | E38: =81.99*0.9
A39: ES | B39: 2SC-10% | C39: 6.52 | D39: =E39*0.9 | E39: 84.99
A40: FR | B40: 2SC-10% | C40: 6.16 | D40: =E40*0.9 | E40: 84.99
A41: DE | B41: 2SC-10% | C41: 6.96 | D41: =E41*0.88 | E41: 84.99

Sheet Sheet2
A2: 79.99 | B2: 55.38 | C2: 0.1 | D2: 79.99 | E2: 55.38 | F2: =D2*C2 | G2: 0.15 | H2: 79.99 | I2: 55.38 | J2: =H2*G2
A3: =A2/1.2 | D3: =D2*(1-C2)/1.2 | H3: =H2*(1-G2)/1.2
A4: =A3-B2 | D4: =D3-E2 | H4: =H3-I2
B5: =(A4+15.7%*B2)/A3 | E5: =(D4+15.7%*E2+F2)/D3 | I5: =(H4+15.7%*I2+J2)/H3
H9: BD=(67.99-55.85+12+15.7%*55.85）/67.99 =51.48%（不含税促销后67.99）
H10: =(67.99/1.19-55.85+12+15.7%*55.85)/(67.99/1.19)

Sheet Sheet3
L3: Power Off
L6: Suction Mode
L11: Cold Water Mode
L16: Hot Water Mode
L19: Steam Mode
