Workbook

Sheet 市场概览（开发数据）
A1: 市场一览 | B1: Y-2总日销 | C1: Y-1总日销 | D1: Y总日销 | E1: Y-2均单价 | F1: Y-1均单价 | G1: Y均单价 | H1: 3年日销趋势图 | I1: 3年均单价趋势图 | J1: 核心词近3年变化 | K1: 月均搜索 | L1: Y-2 | M1: Y-1 | N1: Y
K2: grass pee pads for dogs with tray | L2: 6643 | M2: 2662 | N2: 1746
K3: puppy grass pee pad with tray | L3: 4847 | M3: 1646 | N3: 4945
B4: 350 | C4: 503 | D4: 1296.6 | E4: 49.99 | F4: 37.03 | G4: 38.52 | K4: indoor dog potty | L4: 9080 | M4: 12813 | N4: 12395
K5: dog toilet | L5: 4407 | M5: 4612 | N5: 4624
K6: dog potty tray | L6: 7114 | M6: 10600 | N6: 14161
A7: 链接数量 | C7: 品牌数量 | E7: 卖家数量 | G7: 平均评论数 | H7: 品牌占比饼状图 | I7: 卖家占比饼状图 | J7: 产品定价区间分析 | L7: Y-2 | M7: Y-1 | N7: Y
A8: 100 | C8: 79 | E8: 75 | G8: 734 | K8: 链接数量 | L8: 43 | M8: 56 | N8: 54
A9: TOP5品牌名 | B9: 链接数 | C9: 销售额占比 | D9: TOP5卖家名 | E9: 链接数 | F9: 销售额占比 | G9: 平均评分值 | K9: 平均评分数 | L9: 799.4 | M9: 751.8 | N9: 754.3
A10: PETMAKER | B10: 3 | C10: 0.448 | D10: Amazon | E10: 7 | F10: 0.5114 | G10: 4.1 | K10: 平均评分值 | L10: 3.9 | M10: 4.07 | N10: 4.12
A11: LOOBANI | B11: 5 | C11: 0.0884 | D11: ColoBright | E11: 5 | F11: 0.0938 | G11: 最早上架时间 | K11: 平均销量 | L11: 169.9 | M11: 193.6 | N11: 486.6
A12: Iris Ohyama | B12: 1 | C12: 0.0508 | D12: Key Savings | E12: 5 | F12: 0.0345 | G12: 38278 | K12: 销量占比 | L12: 0.6823 | M12: 0.7101 | N12: 0.5661
A13: Skywin | B13: 5 | C13: 0.0325 | D13: AMAN LIFE | E13: 3 | F13: 0.0273 | G13: 节点分布 | J13: 核心竞对分析 | L13: B0DLH3TBYC | M13: B0F32KMV8Y | N13: B0F5QRY8FW
A14: HQ4US 4LEGS | B14: 3 | C14: 0.0258 | D14: eenk | E14: 1 | F14: 0.0245 | G14: Trays | K14: 月销量 | L14: 1239 | M14: 457 | N14: 193
A15: 其他 | B15: =A8-B10-B11-B12-B13-B14 | C15: =1-C10-C11-C12-C13-C14 | D15: 其他 | E15: =A8-E10-E11-E12-E13-E14 | F15: =1-F10-F11-F12-F13-F14 | K15: 成交价 | L15: 19.99 | M15: 18.99 | N15: 18.74
A16: 关键词趋势分析 | K16: 评分数 | L16: 257 | M16: 47 | N16: 39
H17: 从关键词对比可看出，传统仿真草皮款式呈明显下滑趋势；室内狗厕所+狗用便盆托盘俩个词呈明显领先。 | K17: 评分值 | L17: 4.6 | M17: 4.1 | N17: 4.5
K18: 收录词数 | L18: 289 | M18: 119 | N18: 69
J19: 产品对比分析 | L19: 新品 | M19: 竞品asin1 | N19: 竞品asin2 | O19: 产品主要优势为隐藏磁吸固定（工厂有申请专利）
K20: 包装信息 | L20: 9.9*9.8*2.1in | M20: 11.6*6.9*2.1in | N20: 9.9*8.5*2.9in
K21: 材质 | L21: 硅胶 | M21: 硅胶 | N21: 硅胶
A22: 集中度分析 | K22: 尺寸 | L22: 24*24in | M22: 24*24in | N22: 24*24in
A23: TOP10均销量 | B23: TOP10均销售额 | C23: NO.50月销量 | D23: NO.50月销售额 | E23: NO.100月销量 | F23: NO.100月销售额 | G23: 快速增长的品类，目前头部垄断较高，多为塑料隔板老款型号。前十中有3个为硅胶材质，趋势优于传统款 | K23: 尿垫固定方式 | L23: 磁铁吸附 | M23: / | N23: 独立塑料扣
A24: 2980 | B24: 107166.58 | C24: 148 | D24: 5919 | E24: 56 | F24: 1977 | K24: 唇边高度 | L24: 0.7in | M24: 0.59in | N24: 0.79in
A25: 销售类型分析 | K25: 产品表面处理 | L25: 无 | M25: 菱形图案 | N25: 无
A26: 发货类型 | B26: 链接数量 | C26: 销量占比 | D26: 平均评论数 | E26: 平均评分值 | F26: 亚马逊自营权重较大，为美国品牌传统硬塑料+草皮款。与开发款式不一样，开发为针对训练器的小狗+全生命期母狗的室内场景隔尿垫，这类产品增长迅速，建议以慢节奏方式进场，放狗狗店铺 场景化运营。 | J26: 客户需求（评价）分析 | L26: 描述 | O26: BS1 | P26: BS2 | Q26: B0DLH3TBYC | R26: B0F32KMV8Y | S26: B0F5QRY8FW
A27: FBA | B27: 75 | C27: 0.3928 | D27: 482 | E27: 4.1 | K27: 场景一 | L27: 室内狗狗宠物将其与尿垫组合使用——多为中小型犬
A28: FBM | B28: 5 | C28: 0.033 | D28: 221 | E28: 4.3 | K28: 场景二 | L28: 室内狗笼训练期定点上厕所使用——多为小狗刚到家训练 | R28: / | S28: /
A29: AMZ | B29: 7 | C29: 0.4819 | D29: 1885 | E29: 4.2 | K29: 场景三 | L29: 室内特殊的猫咪种类使用——多为抗拒猫砂盆or后肢不便 | S29: /
A30: 其他 | B30: 13 | C30: 0.0923 | D30: 1671 | E30: 3.9 | K30: 好评点NO.1 | L30: 防水性好，保护了木板 | O30: BS1 | P30: BS2 | Q30: B0DLH3TBYC | R30: B0F32KMV8Y | S30: B0F5QRY8FW
A31: 账号国家 | B31: 链接数量 | C31: 销量占比 | D31: / | K31: 好评点NO.2 | L31: 易于清洁
A32: 中国 | B32: 60 | C32: 0.302 | K32: 好评点NO.3 | L32: 稳定性强（地面放置+固定尿垫两方面）
A33: 美国 | B33: 37 | C33: 0.6785 | K33: 差评点NO.1 | L33: 尺寸问题
A34: 其他 | B34: 3 | C34: 0.0195 | K34: 差评点NO.2 | L34: 耐用性（狗狗破坏）
A35: 上架时间分析 | J35: 开发产品自述 | K35: 价格段市场概括 | L35: 20-40价格段近三年一直占比最高，这个价格段评分逐年缓慢提升，说明这一价格段，新硅胶新材质售后更低，销量近三年均上升，尤其24年出现翻倍增长趋势。说明这类产品为刚需。评分数无明显增长，说明该价格段新品进入难度低。
H36: 近期上架多为硅胶材质款/三面隔板款（针对公狗）新品更加细分场景，老品多为搭建塑料隔板款/仿真草皮款
A41: 价格段分析 | K41: 产品销售切入点 | L41: ①通过隐形磁铁固定尿垫，优化了安装步骤，并通过隐形减少狗啃咬固定器概率，降低因狗狗啃咬导致的退款概率；
H42: 价格段分散，销量主要集中在20-40美金，开发款式建议小尺寸在20左右，大尺寸在30左右两款变体进行布局 | L42: ②通过市调尿垫尺寸，确认选择主流尺寸链接围绕选定尺寸进行埋词，减少因尺寸不合适的差评与退款；（需运营一同确认）
L43: ③通过增加2元左右纸盒包装，比竞对opp袋缩小物流成本；（需运营一同确认）
L44: ④通过主推如厕训练期小狗+小型狗+母狗+特殊情况猫咪，链接围绕细分宠物，减少不适配的宠物购买导致的差评与退款
L45: ⑤结束训练期后（针对庭院养狗人群），产品可作为餐饮垫，一物两用，提高附加值；
L46: /

Sheet 竞对推广分析（运营数据）
A1: 链接 分析 | B1: 主图 | C1: ASIN | D1: 链接 | E1: 类目/节点 | F1: 排名（大类/小类） | G1: 品牌 | H1: 最终售价 | I1: 划线价比率 | J1: 评分 | K1: 评论数 | L1: 预估日销 | M1: 月销量 | N1: 上架时间 | O1: 推广用时 | P1: 变体数 | Q1: 促销力度 | R1: 是否捆绑促销 | S1: 是否有视频 | T1: 测评力度（首月） | V1: 评论质量 | W1: 站外信息（判断站外类型是内容推广，对应的内容信息是什么；还是放量出单，对应价格折扣比是多少 效果如何？） | AC1: 竞对日销多少，持续多长时间激活秒杀的？ | AD1: 竞对的活动效果如何？ | AE1: 竞品推广期间是否有断货 | AF1: 竞对是什么时候开始的站内广告的？ | AG1: 站内广告用的是什么打法？ | AH1: 流量的分布流量的来源入口，收录词数量 | AI1: 推广类型 | AJ1: 卖家背景 | AL1: 品牌背景检索 | AN1: 策略 总结
W2: Facebook | X2: INS | Y2: Youtube | Z2: Google | AA2: Tiktok | AB2: 独立站（品牌流量，私域水平）
T3: 首月排名 | U3: 评论数
A4: 新品 | C4: B0DZNVSXT3 | D4: https://www.amazon.com/dp/B0DZNVSXT3 | E4: Wheel & Tire Air Compressors & Inflators | F4: 6971 | G4: Infloza | H4: 29.99 | J4: 5 | K4: 4 | L4: =M4/K4 | M4: 117 | N4: 45733 | O4: 30天 | P4: 1 | Q4: 15% off | R4: 无 | S4: 2个视频 1个展示 1个红人 | T4: 6917 | U4: 5 | V4: 通过服务商刷单为主，评论质量一般。 | AD4: / | AF4: 有评论之后开广告 | AG4: sp+sb+sd | AH4: 自然流量：43.11%，广告流量：53.71% 流量词：321 | AI4: 链接质量可以 前期以刷单为主，先刷划线价然后叠加站内优惠券、折后价在整个新品类目较有竞争力，有评论基础后开了少量广告，广告占比高达85%，属于站内广告猛推+免评单的暴力打法 | AJ4: 账号公司地址为广州，店铺主做办公椅产品，除该新链接外，无突出链接，运营深度一般 另一品牌X xishe是安吉工厂背景，在供应链上有深耕，但是精细化运营和品牌化能力较弱 | AL4: Owner：Zhao Fugang 同源品牌： X xishe CHAIROYAL CHAIRELAX SAMOFU | AN4: 视觉差异：突出电池续航和多用功能，主图采用45°侧视场景图方案，附图A+多采用场景化素材，突出不同人群和使用需求 广告打法：在有评论的基础下，结合刷单以及站内折扣逐步推进。 产品差异：目前在功能上均为一致，主要质感差异在于电池续航方面，需在这方面优化体验感 突出产品的性价比，提升整体链接的转化率 卖点差异：更多强调产品硬件参数项优势，以及便携性
A5: 热销品 | C5: B0D6BGPQKW | D5: https://www.amazon.com/dp/B0D6BGPQKW | E5: Wheel & Tire Air Compressors & Inflators | F5: 867 | G5: Powools | H5: 34.99 | J5: 4.4 | K5: 450 | L5: =M5/30 | M5: 3800 | N5: 45571 | O5: 30天 | P5: 2 | Q5: 10 | R5: 无 | S5: 13个视频 2个场景 5个安装 6个买家秀 | T5: 339 | U5: 57 | V5: 一开始 先刷单 、免评+留评都刷，三天后合并评论、大概20天左右 合并的变体被拆、刷出的单已经回评、评分在4.7以上不影响推广节奏、 | AC5: 日销100左右，不到1个月激活秒杀 | AD5: 1.5倍增长 | AF5: 有评论之后开广告 | AG5: sp+sb+sd | AH5: 自然流量：66.52%，广告流量：7.57% 流量词：723 | AI5: 前期高定价且站内叠加大额折扣 ，订单销量保持2500-3500， 12月份断货、 1月份恢复推广增加+视频广告。这时候也开始有推荐流量了 ，销量也开始恢复且保持增长 近 30天销量大概4000+ 。1月份标价59.99，叠加50%优惠券之后29.99。效果不如预期。随之下调为39.98+30%优惠券 ，折后价：27.99， 价格又调整59.99，会员折后价格仅会员可见39.99 ，叠加30%优惠券 折后价41.99，站外20天+bd连报28天，销量恢复到3000+，最近的购物车价格是49.99 会员折扣价格39.99 春促活动价34.99 | AJ5: 账号公司地址为杭州，垂直店铺，只做办公椅，运营能力较强 另一品牌Razzor账号注册公司为安吉一办公椅厂，推测为工厂背景 | AL5: Owner：Dai, Mingyue 同源品牌： RAZZOR
A6: 选择的竞对分析 | C6: B0DNLYRCPL | D6: https://www.amazon.com/dp/B0DNLYRCPL | E6: Wheel & Tire Air Compressors & Inflators | F6: 4151 | G6: Olgeo | H6: 29.99 | J6: 4.5 | K6: 44 | L6: =M6/30 | M6: 900 | N6: 45639 | O6: 60天 | P6: 1 | Q6: / | R6: 无 | S6: 无视频 | T6: 3436 | U6: 15 | V6: 直接合并链接、然后在刷单、再拆分出来单独推 | W6: 无站外 | AC6: 目前日销40左右，大概用1个半月激活秒杀 | AD6: 1.5倍增长 | AF6: 有评论之后开广告 | AG6: sp | AH6: 自然流量：93.69%，广告流量：3.68% 流量词：321 | AI6: 一开始获取绿标+刷单获取评论，都是自然流量，后面慢慢打一点广告，截止目前自然流量占比还在70%以上 其中父体发生了4次变更，竞对不仅做了站外，也合并到不同变体中去带，今年2月份正式分离出来单独推 2月份销量300+、3月份价格下调到29.99,参加活动，月销量冲到800+
A7: 失败品分析 （） | C7: B0DQY1PL59 | D7: https://www.amazon.com/dp/B0DQY1PL59 | E7: Wheel & Tire Air Compressors & Inflators | F7: 72610 | G7: Jrapotu | H7: 39.99 | J7: 2 | K7: 1 | L7: =M7/30 | M7: 50 | N7: 45644 | O7: 120天 | P7: 1 | Q7: / | R7: 无 | S7: 无视频 | T7: 312942 | U7: 3 | V7: 刷了3个评论全掉了、被上了一个直评之后也不及时补分数 | W7: 无站外 | AC7: 暂无数据 | AD7: / | AI7: 前期推广力度很低，基本没有干预且广告花费很少，没有投放核心词，属于精铺提供方式 失败原因为推广力度太小，前期干预太少，以及产品品质不佳
A9: 评论策略 | B9: 上评方式 | C9: 数量
A10: 前置动作 | B10: QC全检 | C10: 出货前全检、试装，减少产品品质问题
B11: 质保承诺 | C11: 说明书提供售后邮箱，承诺质保，提供换货和退款
B12: 差评拦截 | C12: 针对到货后5天的订单，发送关怀邮件
A13: 早期评论 | B13: 提前发Vine链接 | C13: 20
B14: 网红测评 | C14: 2
B15: TOP测评 | C15: 2
B16: 主链接Vine | C16: 10
A17: 应急评论（前期来差评） | B17: CA站点测评 | C17: 5 | H17: 直接在CA刷同ASIN好评 评论同步
B18: 低价种子链接 | C18: 20
B19: 站外联系删差评 | C19: /
A20: 中长期评论 | B20: 明信片邀评 | C20: 4%回评率
B21: 延长质保卡邀评 | C21: 1%回评率
B22: 后台点击邀评 | C22: 1%回评率
A24: 关键词分析 | C24: 搜索排名 | E24: 搜索量 | F24: 品牌ABA分析数据 | S24: 前三转化之和 | U24: 自然位首行ASIN | AK24: 广告建议CPC | AM24: 差异判断 | AO24: 这个产品分到了20%，它分到 20 次点击，然后按照类目 10% 的平均转化率来讲，这个类目给到 100 个流量应该出百一十单，但这个卖家只出了一单。它的转化的共享是10%，点击共有 20% 这两个字比就是 50% ，说明它没有利用好这个流量给它带来转化，那如果它这个两者之比越低，说明它的这个词里面会越不稳定。就低于类目平均。他就他在这个词里面就相当于他是劣势的，那如果你的产品力跟产品价格都在这个词上能跟他去衡量的话，你就可以针对性去打这个词。
F25: 第一 | K25: 第二 | O25: 第三
F26: ASIN | G26: 点击共享 | H26: 转化共享 | J26: 两者之比 | K26: ASIN | L26: 点击共享 | M26: 转化共享 | N26: 两者之比 | O26: ASIN | P26: 点击共享 | Q26: 转化共享 | R26: 两者之比 | AK26: 最低 | AL26: 最高
A27: 核心词 | B27: tire inflator portable air compressor | C27: 2339 | E27: 289620 | J27: #DIV/0! | N27: #DIV/0! | R27: #DIV/0! | S27: 0
B28: air compressor | C28: 3558 | E28: 189232 | J28: #DIV/0! | N28: #DIV/0! | R28: #DIV/0! | S28: 0
B29: tire inflator | C29: 3550 | E29: 185799 | J29: #DIV/0! | N29: #DIV/0! | R29: #DIV/0! | S29: 0
B30: air pump for car tires | C30: 6899 | E30: 125771 | J30: #DIV/0! | N30: #DIV/0! | R30: #DIV/0! | S30: 0
B31: air compressor for car | C31: 5899 | E31: 87093 | J31: #DIV/0! | N31: #DIV/0! | R31: #DIV/0! | S31: 0
B32: air compressor for car | J32: #DIV/0! | N32: #DIV/0! | R32: #DIV/0! | S32: 0
A33: 长尾词 | B33: air compressor | J33: #DIV/0! | N33: #DIV/0! | R33: #DIV/0! | S33: 0
B34: tire inflator | J34: #DIV/0! | N34: #DIV/0! | R34: #DIV/0! | S34: 0
B35: air pump for car tires | J35: #DIV/0! | N35: #DIV/0! | R35: #DIV/0! | S35: 0
B36: air compressor for car | J36: #DIV/0! | N36: #DIV/0! | R36: #DIV/0! | S36: 0
B37: air compressor for car | J37: #DIV/0! | N37: #DIV/0! | R37: #DIV/0! | S37: 0
B38: air compressor for car | J38: #DIV/0! | N38: #DIV/0! | R38: #DIV/0! | S38: 0
A39: 流量词 | B39: air compressor | J39: #DIV/0! | N39: #DIV/0! | R39: #DIV/0! | S39: 0
B40: tire inflator | J40: #DIV/0! | N40: #DIV/0! | R40: #DIV/0! | S40: 0
B41: air pump for car tires | J41: #DIV/0! | N41: #DIV/0! | R41: #DIV/0! | S41: 0
A42: 品牌词 | B42: HYCJ | J42: #DIV/0! | N42: #DIV/0! | R42: #DIV/0! | S42: 0
B43: ABS | J43: #DIV/0! | N43: #DIV/0! | R43: #DIV/0! | S43: 0
B44: OUP | J44: #DIV/0! | N44: #DIV/0! | R44: #DIV/0! | S44: 0

Sheet 产品定位（产品数据）
A1: 产品定位 | B1: 销售品牌 | D1: 核心 卖点 | E1: 产品上的卖点 | L1: 标准 | M1: 目的 | N1: 备货标准 | O1: 销量标准 | P1: 利润标准
L2: 规模款 | M2: 为了市场占有率和降低我们的生产成本，类目市场占有率达到30%以上，才可以形成品牌扩张。 | N2: 根据推广计划备货不能断货，可备总数分批发货 | O2: 日销100单以上 | P2: 5%-15% | Q2: 注意规模款和利润款因为客单不一样，针对的人群不一样，所以就算再一个店铺也要区分品牌，最好是不在同一个店铺
A3: 定价 | C3: 折扣 | L3: 利润款 | M3: 利润款占整个产品数量的60%，让公司形成竞争力，利润款的销量是规模款的60%，但是利润是他的1.5倍。 | N3: 根据推广计划备货不能断货，可备总数分批发货 | O3: 日销50单以上 | P3: 15%-25%
L4: 结构款 | M4: 促进其他产品的销售，带给客户更高的满意度和完整的购物体验（为了让流量在店铺里面闭环），以及老客户多频次的进入店铺。 | N4: 可以断货不可以冗余 | O4: 日销10单以上 | P4: 5%-15%
A5: 类目节点 | L5: 止损款 | M5: 退市产品，要淘汰的产品，当月净毛利小于1000，且月净毛利小于 起订货值的33% | O5: 尽量不亏本清库 | P5: 0%-10%
E6: 打法或者策略上的竞争优势 | L6: 流量款 | M6: 为了引流量，给其他产品带来销量，不管是连带还是复购，还是跳转，如果只是买了引流的产品，叫引流失败；引流款可以在规模款里面，也可以在利润款和结构款里面，具体看目的是什么。 | N6: 如果是规模款就跟着规模款走，结构就跟着结构款走，如果是利润款就跟着利润款走。
A7: 目标人群 | B7: 使用场景
A13: 类目评论分析
A14: 使用人群 | B14: 使用人群：携带宠物出行的宠物主人 使用场景：普通宠物出行、宠物受伤行动不便出行、老年宠物出行、小型犬（幼犬出行）、要去人多的地方，保护宠物安全（由于提到具体使用场景的数量很少，所以没有进行数量统计） 用户需求：推车能够平稳推动，不颠簸、空间大，宠物可在推车上活动、带有收纳空间，便于携带一些小物件 | I14: 该产品主要面对的用户群体是携带宠物出行的宠物主人，用户主要需求是推车能够平稳推动，不颠簸，空间大。综合用户提及的好评点在购买产品时会重点关注产品的组装方式、空间大小、是否带有收纳区、是否带有网格窗口。这款产品产生差评主要是由车轮质量、置物架、拉链、提篮织物质量、安全扣造成的。 通过看用户的评论图片，这类产品主要用于中小型犬和多宠家庭出行，建议将这两个场景作为产品的主推场景
A15: 正面评价 | B15: 1、易于组装 23.21% 2、空间大 16.07% 3、底部有收纳区 10.71% 4、带有网格布料，能见度大 8.93% 5、面料好 8.93% 6、可折叠 5.36% 7、易于使用 3.57% 8、推杆高度合适 3.57% 其余好评有车轮质量好 3.57%、车轮平稳 3.57%、置物架 1.79%、有安全扣 1.79%、颜色和设计 1.79%、通风 1.79%、铝制结构 1.79%、开口大，宠物容易进去 1.79%、车轮360度旋转 1.79%
A16: 负面评价 | B16: 1、车轮质量差 摇晃、不稳 29.41% 2、杯架浅、放东西容易倒 10.29% 3、拉链难用、难找、质量差 8.82% 4、提篮织物裂开 5.88% 5、安全扣不牢固 5.88% 6、配件遗漏 4.41% 7、内衬薄 4.41% 其余差评有空间小 4.41%、车轮脱落 4.41%、推车不稳，容易倾斜 2.94%、质量差 1.47%、织物不能拆卸、不易于清洗 1.47%、折叠困难 1.47%、有塑料味 1.47%、推手高度不可调节 1.47%、提篮难拆卸 1.47%、配件不合适 1.47%、没有安全扣 1.47%、金属杆断裂 1.47%、车轮生锈 1.47%、车轮难拆卸 1.47%、产品重 1.47%、产品有划痕 1.47%。
A17: 已满足需求 | C17: 样品满足需求点 | E17: 待满足需求 | G17: 样品优化需求点 | I17: 产品改良方案
A18: 易于组装 | C18: √ | E18: 车轮质量差 摇晃、不稳 | G18: 车轮360度旋转，带有减震弹簧
A19: 空间大 | C19: √ | E19: 拉链难用、难找、质量差 | G19: 提篮采用卡扣设计
A20: 底部有收纳区 | C20: √ | E20: 杯架浅、放东西容易倒
A21: 有网格窗口、可见度大 | C21: √ | E21: 提篮织物裂开 | G21: 牛津布材质
A22: 可折叠收纳 | C22: √ | E22: 安全扣不牢固

Sheet 定价表
A1: 汇率 | B1: 美元 | C1: 欧元 | D1: 英镑 | E1: 加元 | F1: 运输方式 | G1: 空运 | H1: 慢船 | I1: 以星 | J1: 合德快船 | K1: 美森快船 | L1: 欧洲海运 | M1: 卡航 | N1: 铁路
A2: 兑人民币 | B2: 6.8 | C2: 7.1 | D2: 8.3 | E2: 5 | G2: =50 | H2: 7.5 | I2: 11.5 | J2: 12.5 | K2: 17 | L2: 8 | M2: 22 | N2: 14
A3: VC活动价 | B3: 汇率 | C3: 国家 | D3: 报价比例 | E3: 售价美金 | F3: 报价美金 | G3: 物流方式 | H3: 头程价格 | I3: 采购价 | J3: 国内总成本 | K3: 装箱数量 | L3: 移仓费/个 | M3: 换标费 0.5/个 | N3: 入库费/箱/1.5 | O3: 装箱费 2.5/箱 | P3: 箱唛 0.5/张/箱 | Q3: 出库费 1.5/箱 | R3: 自提费 1.5/箱 | S3: 入库总费用 | T3: 入库单个费用 | U3: 利润P0 | V3: 回款扣点 | W3: 广告费占比 | X3: 广告费 | Y3: 活动促销比例 | Z3: 活动促销/美金 | AA3: 最低活动价/美金 | AB3: 利润P3 | AC3: P1--VC | AD3: P1--SC | AE3: P3对应的投资回报率=P3/国内成本 | AF3: 国内成本占比 | AG3: 一期回款金额70%/美金 | AH3: 一期回款毛利P2=回款-国内总成本-海外仓费用 | AI3: 一期回款比例=一期回款/商品成本 | AJ3: 一期回款比例=一期回款/（国内+海外仓） | AK3: 一期投资回报=70^%部分的毛利/成本 | AL3: 营销费/cost
A4: 打气泵S | B4: =IF(C4="US",$B$2,IF(C4="UK",$D$2,IF(C4="ES",$C$2,IF(C4="CA",$E$2,$C$2)))) | C4: UK | D4: 0.62 | E4: 33.32 | F4: =E4*D4 | G4: 空运 | H4: =INDEX($G$2:$N$2, MATCH(G4, $G$1:$N$1, 0)) | I4: 70 | J4: =SUM(H4:I4) | K4: 16 | L4: 0 | M4: 0 | N4: 1.5 | O4: 0 | P4: 1 | Q4: 1.5 | R4: 1.5 | S4: =SUM(N4:R4)+(L4+M4)*K4 | T4: =S4/K4*B4 | U4: =F4*B4-J4-T4 | V4: 0.02 | W4: 0.08 | X4: =E4*W4*B4 | Y4: 0.1 | Z4: =E4*Y4 | AA4: =E4-Z4 | AB4: =U4-F4*V4*B4-X4-Z4*B4 | AC4: =AB4/(F4*B4) | AD4: =AB4/(E4*B4) | AE4: =AB4/J4 | AF4: =J4/B4/F4 | AG4: =F4*0.7 | AH4: =AG4*B4-T4-J4 | AI4: =AG4*B4/J4 | AJ4: =AG4*B4/(J4+T4) | AK4: =AH4/J4 | AL4: =(X4/B4+Z4)/F4
A5: 打气泵 A | B5: =IF(C5="US",$B$2,IF(C5="UK",$D$2,IF(C5="ES",$C$2,IF(C5="CA",$E$2,$C$2)))) | C5: UK | D5: 0.62 | E5: 33.32 | F5: =E5*D5 | G5: 美森快船 | H5: =INDEX($G$2:$N$2, MATCH(G5, $G$1:$N$1, 0)) | I5: 70 | J5: =SUM(H5:I5) | K5: 16 | L5: 0 | M5: 0 | N5: 1.5 | O5: 0 | P5: 1 | Q5: 1.5 | R5: 1.5 | S5: =SUM(N5:R5)+(L5+M5)*K5 | T5: =S5/K5*B5 | U5: =F5*B5-J5-T5 | V5: 0.02 | W5: 0.08 | X5: =E5*W5*B5 | Y5: 0.1 | Z5: =E5*Y5 | AA5: =E5-Z5 | AB5: =U5-F5*V5*B5-X5-Z5*B5 | AC5: =AB5/(F5*B5) | AD5: =AB5/(E5*B5) | AE5: =AB5/J5 | AF5: =J5/B5/F5 | AG5: =F5*0.7 | AH5: =AG5*B5-T5-J5 | AI5: =AG5*B5/J5 | AJ5: =AG5*B5/(J5+T5) | AK5: =AH5/J5 | AL5: =(X5/B5+Z5)/F5
A6: 打气泵 V | B6: =IF(C6="US",$B$2,IF(C6="UK",$D$2,IF(C6="ES",$C$2,IF(C6="CA",$E$2,$C$2)))) | C6: UK | D6: 0.62 | E6: 33.32 | F6: =E6*D6 | G6: 美森快船 | H6: =INDEX($G$2:$N$2, MATCH(G6, $G$1:$N$1, 0)) | I6: 70 | J6: =SUM(H6:I6) | K6: 16 | L6: 0 | M6: 0 | N6: 1.5 | O6: 0 | P6: 1 | Q6: 1.5 | R6: 1.5 | S6: =SUM(N6:R6)+(L6+M6)*K6 | T6: =S6/K6*B6 | U6: =F6*B6-J6-T6 | V6: 0.02 | W6: 0.08 | X6: =E6*W6*B6 | Y6: 0.1 | Z6: =E6*Y6 | AA6: =E6-Z6 | AB6: =U6-F6*V6*B6-X6-Z6*B6 | AC6: =AB6/(F6*B6) | AD6: =AB6/(E6*B6) | AE6: =AB6/J6 | AF6: =J6/B6/F6 | AG6: =F6*0.7 | AH6: =AG6*B6-T6-J6 | AI6: =AG6*B6/J6 | AJ6: =AG6*B6/(J6+T6) | AK6: =AH6/J6 | AL6: =(X6/B6+Z6)/F6
A7: 竞对价格 | B7: =IF(C7="US",$B$2,IF(C7="UK",$D$2,IF(C7="ES",$C$2,IF(C7="CA",$E$2,$C$2)))) | C7: US | D7: 0.62 | E7: 33.32 | F7: =E7*D7 | G7: 美森快船 | H7: =INDEX($G$2:$N$2, MATCH(G7, $G$1:$N$1, 0)) | I7: 70 | J7: =SUM(H7:I7) | K7: 16 | L7: 0 | M7: 0 | N7: 1.5 | O7: 0 | P7: 1 | Q7: 1.5 | R7: 1.5 | S7: =SUM(N7:R7)+(L7+M7)*K7 | T7: =S7/K7*B7 | U7: =F7*B7-J7-T7 | V7: 0.02 | W7: 0.08 | X7: =E7*W7*B7 | Y7: 0.1 | Z7: =E7*Y7 | AA7: =E7-Z7 | AB7: =U7-F7*V7*B7-X7-Z7*B7 | AC7: =AB7/(F7*B7) | AD7: =AB7/(E7*B7) | AE7: =AB7/J7 | AF7: =J7/B7/F7 | AG7: =F7*0.7 | AH7: =AG7*B7-T7-J7 | AI7: =AG7*B7/J7 | AJ7: =AG7*B7/(J7+T7) | AK7: =AH7/J7 | AL7: =(X7/B7+Z7)/F7
A9: SC站内推广 | B9: 汇率 | C9: 国家 | D9: 有无VAT | E9: 成本价(0边利) | F9: 建议价(20%边利) | G9: 实际定价 | H9: 采购价 | I9: FBA Fee | J9: 佣金比例 | K9: VAT | L9: 预估退货率 | M9: 推广费率 | N9: FBA仓储费 | O9: 其他费用 | P9: 长 | Q9: 宽 | R9: 高 | S9: 包装后实重 | T9: 体积重 | U9: 计费重 | V9: 运输方式 | W9: 运费单价 | X9: 运费 | Y9: 利润/USD | Z9: 利润率
A10: 打气泵日常价 | B10: 6.8 | C10: US | D10: 无 | E10: =IF(D10="有",(H10/B10+I10+X10/B10)/(0.99999-J10-K10-L10-M10),(H10/B10+I10+X10/B10)/(0.99999-J10-L10-M10)) | F10: =IF(D10="有",(H10/B10+I10+X10/B10)/(0.8-J10-K10-L10-M10-N10-O10),(H10/B10+I10+X10/B10)/(0.8-J10-L10-M10-N10-O10)) | G10: 29.99 | H10: 56 | I10: 5 | J10: 0.15 | K10: 0 | L10: 0 | M10: 0 | N10: 0.01 | O10: 0.02 | P10: 14.6 | Q10: 8.8 | R10: 4.9 | S10: 0.46 | T10: =P10*Q10*R10/6000 | U10: =MAX(S10:T10) | V10: 慢船 | W10: =INDEX($G$2:$N$2, MATCH(V10, $G$1:$N$1, 0)) | X10: =U10*W10 | Y10: =G10-SUM(J10:O10)*G10-I10-H10/B10-X10/B10 | Z10: =Y10/G10
A11: 打气泵活动价 | B11: =IF(C11="US",$B$2,IF(C11="UK",$D$2,IF(C11="ES",$C$2,IF(C11="CA",$E$2,$C$2)))) | C11: US | D11: 无 | E11: =IF(D11="有",(H11/B11+I11+X11/B11)/(0.99999-J11-K11-L11-M11),(H11/B11+I11+X11/B11)/(0.99999-J11-L11-M11)) | F11: =IF(D11="有",(H11/B11+I11+X11/B11)/(0.8-J11-K11-L11-M11-N11-O11),(H11/B11+I11+X11/B11)/(0.8-J11-L11-M11-N11-O11)) | G11: 25.49 | H11: 56 | I11: 5 | J11: 0.15 | K11: 0 | L11: 0.05 | M11: 0.08 | N11: 0.01 | O11: 0.02 | P11: 14.6 | Q11: 8.8 | R11: 4.9 | S11: 0.46 | T11: =P11*Q11*R11/6000 | U11: =MAX(S11:T11) | V11: 慢船 | W11: =INDEX($G$2:$N$2, MATCH(V11, $G$1:$N$1, 0)) | X11: =U11*W11 | Y11: =G11-SUM(J11:O11)*G11-I11-H11/B11-X11/B11 | Z11: =Y11/G11
A12: 竞对日常价 | B12: =IF(C12="US",$B$2,IF(C12="UK",$D$2,IF(C12="ES",$C$2,IF(C12="CA",$E$2,$C$2)))) | C12: US | D12: 无 | E12: =IF(D12="有",(H12/B12+I12+X12/B12)/(0.99999-J12-K12-L12-M12),(H12/B12+I12+X12/B12)/(0.99999-J12-L12-M12)) | F12: =IF(D12="有",(H12/B12+I12+X12/B12)/(0.8-J12-K12-L12-M12-N12-O12),(H12/B12+I12+X12/B12)/(0.8-J12-L12-M12-N12-O12)) | G12: 29.99 | H12: 56 | I12: 5 | J12: 0.15 | K12: 0 | L12: 0.05 | M12: 0.15 | N12: 0.01 | O12: 0.02 | P12: 14.6 | Q12: 8.8 | R12: 4.9 | S12: 0.46 | T12: =P12*Q12*R12/6000 | U12: =MAX(S12:T12) | V12: 以星 | W12: =INDEX($G$2:$N$2, MATCH(V12, $G$1:$N$1, 0)) | X12: =U12*W12 | Y12: =G12-SUM(J12:O12)*G12-I12-H12/B12-X12/B12 | Z12: =Y12/G12
A13: 竞对活动价 | B13: 6.8 | C13: US | D13: 无 | E13: =IF(D13="有",(H13/B13+I13+X13/B13)/(0.99999-J13-K13-L13-M13),(H13/B13+I13+X13/B13)/(0.99999-J13-L13-M13)) | F13: =IF(D13="有",(H13/B13+I13+X13/B13)/(0.8-J13-K13-L13-M13-N13-O13),(H13/B13+I13+X13/B13)/(0.8-J13-L13-M13-N13-O13)) | G13: 23.99 | H13: 56 | I13: 5 | J13: 0.15 | K13: 0 | L13: 0.05 | M13: 0.08 | N13: 1 | O13: 0.02 | P13: 14.6 | Q13: 8.8 | R13: 4.9 | S13: 0.46 | T13: =P13*Q13*R13/6000 | U13: =MAX(S13:T13) | V13: 以星 | W13: =INDEX($G$2:$N$2, MATCH(V13, $G$1:$N$1, 0)) | X13: =U13*W13 | Y13: =G13-SUM(J13:O13)*G13-I13-H13/B13-X13/B13 | Z13: =Y13/G13
A14: 竞对活动价 | B14: 7 | C14: US | D14: 无 | E14: =IF(D14="有",(H14/B14+I14+X14/B14)/(0.99999-J14-K14-L14-M14),(H14/B14+I14+X14/B14)/(0.99999-J14-L14-M14)) | F14: =IF(D14="有",(H14/B14+I14+X14/B14)/(0.8-J14-K14-L14-M14-N14-O14),(H14/B14+I14+X14/B14)/(0.8-J14-L14-M14-N14-O14)) | G14: 29.99 | H14: 61 | I14: 8 | J14: 0.06 | K14: 0 | L14: 0.05 | M14: 0.08 | N14: 1 | O14: 0.02 | P14: 23 | Q14: 23 | R14: 13 | S14: 0.8 | T14: =P14*Q14*R14/6000 | U14: =MAX(S14:T14) | V14: 以星 | W14: =INDEX($G$2:$N$2, MATCH(V14, $G$1:$N$1, 0)) | X14: =U14*W14 | Y14: =G14-SUM(J14:O14)*G14-I14-H14/B14-X14/B14 | Z14: =Y14/G14
A16: 站外推广 | B16: 汇率 | C16: 国家 | D16: 有无VAT | E16: 成本价(0边利) | F16: 建议价(20%边利) | G16: 实际定价 | H16: 采购价 | I16: FBA Fee | J16: 佣金比例 | K16: VAT | L16: 预估退货率 | M16: 折扣力度 | N16: FBA仓储费 | O16: 其他费用 | P16: 长 | Q16: 宽 | R16: 高 | S16: 包装后实重 | T16: 体积重 | U16: 计费重 | V16: 运输方式 | W16: 运费单价 | X16: 运费 | Y16: 利润/USD | Z16: 利润率
A17: 打气泵 | B17: 6.8 | C17: US | D17: 无 | E17: =H17/B17+I17+X17/B17+(G17*(1-M17)*(J17+L17+N17+O17)) | F17: =(H17/B17+I17+X17/B17+(G17*(1-M17)*(J17+L17+N17+O17)))/0.8 | G17: 59.99 | H17: 56 | I17: 5.48 | J17: 0.15 | K17: 0 | L17: 0.03 | M17: 0.6 | N17: 0.01 | O17: 0.02 | P17: 13.8 | Q17: 10.8 | R17: 3.7 | S17: 0.35 | T17: =P17*Q17*R17/6000 | U17: =MAX(S17:T17) | V17: 铁路 | W17: =INDEX($G$2:$N$2, MATCH(V17, $G$1:$N$1, 0)) | X17: =U17*W17 | Y17: =(G17*(1-M17))-H17/B17-I17-X17/B17-(J17+L17+N17+O17)*(G17*(1-M17)) | Z17: =Y17/G17
A18: 竞对站外价格 | B18: =IF(C18="US",$B$2,IF(C18="UK",$D$2,IF(C18="ES",$C$2,IF(C18="CA",$E$2,$C$2)))) | C18: US | D18: 无 | E18: =H18/B18+I18+X18/B18+(G18*(1-M18)*(J18+L18+N18+O18)) | F18: =(H18/B18+I18+X18/B18+(G18*(1-M18)*(J18+L18+N18+O18)))/0.8 | G18: 59.99 | H18: 56 | I18: 5.48 | J18: 0.15 | K18: 0 | L18: 0.05 | M18: 0.6 | N18: 0.01 | O18: 0.02 | P18: 13.8 | Q18: 10.8 | R18: 3.7 | S18: 0.35 | T18: =P18*Q18*R18/6000 | U18: =MAX(S18:T18) | V18: 以星 | W18: =INDEX($G$2:$N$2, MATCH(V18, $G$1:$N$1, 0)) | X18: =U18*W18 | Y18: =(G18*(1-M18))-H18/B18-I18-X18/B18-(J18+L18+N18+O18)*(G18*(1-M18)) | Z18: =Y18/G18
A21: Woot | B21: 汇率 | C21: 国家 | D21: 报价比例 | E21: 售价美金 | F21: 报价美金 | G21: 采购价 | H21: 头程 | I21: 国内总成本 | J21: 广告费占比 | K21: 广告费 | L21: 利润/RMB | M21: Woot利润率
A22: 打气泵 | B22: =IF(C22="US",$B$2,IF(C22="UK",$D$2,IF(C22="ES",$C$2,IF(C22="CA",$E$2,$C$2)))) | C22: US | D22: 0.44 | E22: 29.99 | F22: =E22*D22 | G22: 56 | H22: =X9 | I22: =SUM(G22:H22) | J22: 0.15 | K22: =E22*B22*J22 | L22: =F22*B22-I22-K22 | M22: =L22/(E22*B22)
A23: 回款定价表
A24: 售价 | B24: 月销量 | C24: 销售总额 | D24: MC | E24: 佣金 | F24: 配送费 | G24: RMA扣减 | H24: 广告费 | I24: 促销费 | J24: FBA仓储 | K24: 弃置费用 | L24: VAT | M24: 成本总计 | N24: 回款额 | O24: 回款率 | P24: 净毛利 | Q24: 净毛利率
A25: =$G$10 | B25: 1 | C25: =A25*B25 | D25: =(H10+X10)/$B$10*B25 | E25: =A25*B25*$J$10 | F25: =B25*$I$10 | G25: =B25*A25*$L$10 | H25: =$M$10*C25 | I25: 0 | J25: =$N$10 | K25: 0 | L25: =K10 | M25: =D25+E25+F25+G25+H25+I25+J25+K25+L25 | N25: =C25-E25-L25-J25-D25-F25-H25-I25-K25 | O25: =N25/C25 | P25: =C25-M25 | Q25: =P25/C25
A26: =$G$10 | B26: 200 | C26: =A26*B26 | D26: =(H11+X11)/$B$10*B26 | E26: =A26*B26*$J$10 | F26: =B26*$I$10 | G26: =B26*A26*$L$10 | H26: =$M$10*C26 | I26: 0 | J26: =$N$10 | K26: 0 | L26: =K11 | M26: =D26+E26+F26+G26+H26+I26+J26+K26+L26 | N26: =C26-E26-L26-J26-D26-F26-H26-I26-K26 | O26: =N26/C26 | P26: =C26-M26 | Q26: =P26/C26
A27: 底价定价表
A28: Asin | B28: SKU | C28: Price | D28: All cost | E28: Profit | F28: Profit% | G28: MC | H28: 佣金 | I28: 配送费 | J28: 退货均摊 | K28: VAT税率 | L28: 佣金率 | M28: 退货率 | N28: 折扣% off | O28: 底价
A29: WOOT | B29: WWW0 | C29: =G10 | D29: =G29+H29+I29+J29+K29*C29+C29*N29 | E29: =C29-D29 | F29: =E29/C29 | G29: =(H10+X10)/$B$10 | H29: =C29*$J$10 | I29: =$I$10 | J29: =C29*$L$10 | K29: 0 | L29: =$J$10 | M29: =L18*$L$10 | N29: =$M$10 | O29: =(G29+I29)/(1-K29-L29-M29)

Sheet SC+VC推广计划拆解
A1: 第一阶段：0~7天 | C1: 阶段目标：安排完划线价就要转vc的做DF，开售一周（刷单+报活动）活动全年拉满就转回SC； | J1: 推广计划根据库存量来定，不断货，不冗余
A2: 步骤 | B2: 目标 | C2: 处理的结果
A3: 第一步 | B3: 划线价（30%）
A4: 第二步 | B4: 刷单数量安排
A5: 第三步 | B5: VC测试报活动
A6: 第四步 | B6: 开启PO,同时申请手动订单
A8: 第二阶段：8~28天 | C8: 阶段目标：转SC推广，提升刷单关键词自然位，拉大流量提升单量和排名，为VC BD做准备；
A9: ASIN | D9: 定价 | E9: 139 | L9: M01 | M9: M02 | N9: M03
A10: 终期流量目标 | B10: =IFERROR(B11/B13,0) | D10: 折扣 | E10: 30 | K10: 广告花费 | L10: =SUM(I30,I50,I70,I99) | M10: =SUM(I119,#REF!,B188,E188) | N10: =SUM(H188:Q188)
A11: 终期日销目标 | B11: 10 | D11: 成交价 | E11: =E9-E10 | K11: 总销售额 | L11: =I102+I73+I53+I33 | M11: =SUM(I122,#REF!,B191,E191) | N11: =SUM(H191:Q191)
A12: CTR目标 | B12: 0.003 | D12: 不含广告利润额 | E12: 28.43 | F12: 利润额扣除退货率，不扣除广告占比 | K12: 广告占比 | L12: =L10/L11 | M12: =M10/M11 | N12: =N10/N11
A13: CVR目标 | B13: 0.05
A14: 广告单占比目标 | B14: 0.8
A15: 目标评论数 | B15: 5
A16: 站外目标出单
A17: 联盟目标出单
A19: （目标）第二阶段详细计划 Part1 | C19: 开售W2 | M19: 实际完成数据 | O19: 开售W2 | Y19: 完成差额 | AA19: 开售W2
A20: 数据预测 | B20: Day 1 | C20: Day 2 | D20: Day 3 | E20: Day 4 | F20: Day 5 | G20: Day 6 | H20: Day 7 | I20: 合计 | M20: 数据预测 | N20: Day 1 | O20: Day 2 | P20: Day 3 | Q20: Day 4 | R20: Day 5 | S20: Day 6 | T20: Day 7 | U20: 合计 | Y20: 数据预测 | Z20: Day 1 | AA20: Day 2 | AB20: Day 3 | AC20: Day 4 | AD20: Day 5 | AE20: Day 6 | AF20: Day 7 | AG20: 合计
A21: 目标总单量 | B21: 1 | C21: 2 | D21: 3 | E21: 4 | F21: 5 | G21: 5 | H21: 6 | I21: =SUM(B21:H21) | M21: 总单量 | N21: 12 | O21: 23 | P21: 26 | Q21: 25 | R21: 11 | S21: 52 | T21: 12 | U21: =SUM(N21:T21) | Y21: 总单量 | Z21: =N21-B21 | AA21: =O21-C21 | AB21: =P21-D21 | AC21: =Q21-E21 | AD21: =R21-F21 | AE21: =S21-G21 | AF21: =T21-H21 | AG21: =SUM(Z21:AF21)
A22: 总流量 | B22: =B21/B28 | C22: =C21/C28 | D22: =D21/D28 | E22: =E21/E28 | F22: =F21/F28 | G22: =G21/G28 | H22: =H21/H28 | I22: =SUM(B22:H22) | M22: 总流量 | N22: =N21/N28 | O22: =O21/O28 | P22: =P21/P28 | Q22: =Q21/Q28 | R22: =R21/R28 | S22: =S21/S28 | T22: =T21/T28 | U22: =SUM(N22:T22) | Y22: 总流量 | Z22: =N22-B22 | AA22: =O22-C22 | AB22: =P22-D22 | AC22: =Q22-E22 | AD22: =R22-F22 | AE22: =S22-G22 | AF22: =T22-H22 | AG22: =SUM(Z22:AF22)
A23: 广告单占比 | B23: 1 | C23: 1 | D23: 1 | E23: 1 | F23: 1 | G23: 0.9 | H23: 0.9 | I23: =I25/I21 | M23: 广告单占比 | N23: 1 | O23: 1 | P23: 1 | Q23: 1 | R23: 1 | S23: 0.9 | T23: 0.9 | U23: =U25/U21 | Y23: 广告单占比 | Z23: =N23-B23 | AA23: =O23-C23 | AB23: =P23-D23 | AC23: =Q23-E23 | AD23: =R23-F23 | AE23: =S23-G23 | AF23: =T23-H23 | AG23: =AG25/AG21
A24: 自然单量 | B24: =B21-B25 | C24: =C21-C25 | D24: =D21-D25 | E24: =E21-E25 | F24: =F21-F25 | G24: =G21-G25 | H24: =H21-H25 | I24: =SUM(B24:H24) | M24: 自然单量 | N24: 12 | O24: =O21-O25 | P24: =P21-P25 | Q24: =Q21-Q25 | R24: =R21-R25 | S24: =S21-S25 | T24: =T21-T25 | U24: =SUM(N24:T24) | Y24: 自然单量 | Z24: =N24-B24 | AA24: =O24-C24 | AB24: =P24-D24 | AC24: =Q24-E24 | AD24: =R24-F24 | AE24: =S24-G24 | AF24: =T24-H24 | AG24: =SUM(Z24:AF24)
A25: 广告单量 | B25: =B21*B23 | C25: =C21*C23 | D25: =D21*D23 | E25: =E21*E23 | F25: =F21*F23 | G25: =G21*G23 | H25: =H21*H23 | I25: =SUM(B25:H25) | M25: 广告单量 | N25: =N21*N23 | O25: =O21*O23 | P25: =P21*P23 | Q25: =Q21*Q23 | R25: =R21*R23 | S25: =S21*S23 | T25: =T21*T23 | U25: =SUM(N25:T25) | Y25: 广告单量 | Z25: =N25-B25 | AA25: =O25-C25 | AB25: =P25-D25 | AC25: =Q25-E25 | AD25: =R25-F25 | AE25: =S25-G25 | AF25: =T25-H25 | AG25: =SUM(Z25:AF25)
A26: CPC | B26: 3.8 | C26: 3.8 | D26: 3.8 | E26: 3.8 | F26: 3.8 | G26: 3.8 | H26: 3.8 | I26: =AVERAGE(B26:H26) | M26: CPC | N26: 3.8 | O26: 3.8 | P26: 3.8 | Q26: 3.8 | R26: 3.8 | S26: 3.8 | T26: 3.8 | U26: =AVERAGE(N26:T26) | Y26: CPC | Z26: =N26-B26 | AA26: =O26-C26 | AB26: =P26-D26 | AC26: =Q26-E26 | AD26: =R26-F26 | AE26: =S26-G26 | AF26: =T26-H26 | AG26: =AVERAGE(Z26:AF26)
A27: 点击率CTR | B27: 0.003 | C27: 0.003 | D27: 0.003 | E27: 0.003 | F27: 0.003 | G27: 0.003 | H27: 0.003 | I27: =AVERAGE(B27:H27) | M27: 点击率CTR | N27: 0.003 | O27: 0.003 | P27: 0.003 | Q27: 0.003 | R27: 0.003 | S27: 0.003 | T27: 0.003 | U27: =AVERAGE(N27:T27) | Y27: 点击率CTR | Z27: =N27-B27 | AA27: =O27-C27 | AB27: =P27-D27 | AC27: =Q27-E27 | AD27: =R27-F27 | AE27: =S27-G27 | AF27: =T27-H27 | AG27: =AVERAGE(Z27:AF27)
A28: 转化率CVR | B28: 0.04 | C28: 0.04 | D28: 0.04 | E28: 0.04 | F28: 0.04 | G28: 0.04 | H28: 0.04 | I28: =AVERAGE(B28:H28) | J28: 累计出单 | K28: =I21 | M28: 转化率CVR | N28: 0.04 | O28: 0.04 | P28: 0.04 | Q28: 0.04 | R28: 0.04 | S28: 0.04 | T28: 0.04 | U28: =AVERAGE(N28:T28) | V28: 累计出单 | W28: =U21 | Y28: 转化率CVR | Z28: =N28-B28 | AA28: =O28-C28 | AB28: =P28-D28 | AC28: =Q28-E28 | AD28: =R28-F28 | AE28: =S28-G28 | AF28: =T28-H28 | AG28: =AVERAGE(Z28:AF28) | AH28: 累计出单 | AI28: =AG21
A29: 广告点击量 | B29: =B25/B28 | C29: =C25/C28 | D29: =D25/D28 | E29: =E25/E28 | F29: =F25/F28 | G29: =G25/G28 | H29: =H25/H28 | I29: =SUM(B29:H29) | J29: 本周CPA | K29: =I30/I25 | M29: 广告点击量 | N29: =N25/N28 | O29: =O25/O28 | P29: =P25/P28 | Q29: =Q25/Q28 | R29: =R25/R28 | S29: =S25/S28 | T29: =T25/T28 | U29: =SUM(N29:T29) | V29: 本周CPA | W29: =U30/U25 | Y29: 广告点击量 | Z29: =N29-B29 | AA29: =O29-C29 | AB29: =P29-D29 | AC29: =Q29-E29 | AD29: =R29-F29 | AE29: =S29-G29 | AF29: =T29-H29 | AG29: =SUM(Z29:AF29) | AH29: 本周CPA | AI29: =AG30/AG25
A30: 广告花费 | B30: =B26*B29 | C30: =C26*C29 | D30: =D26*D29 | E30: =E26*E29 | F30: =F26*F29 | G30: =G26*G29 | H30: =H26*H29 | I30: =SUM(B30:H30) | J30: 本周广告占比 | K30: =I30/I33 | M30: 广告花费 | N30: =N26*N29 | O30: =O26*O29 | P30: =P26*P29 | Q30: =Q26*Q29 | R30: =R26*R29 | S30: =S26*S29 | T30: =T26*T29 | U30: =SUM(N30:T30) | V30: 本周广告占比 | W30: =U30/U33 | Y30: 广告花费 | Z30: =N30-B30 | AA30: =O30-C30 | AB30: =P30-D30 | AC30: =Q30-E30 | AD30: =R30-F30 | AE30: =S30-G30 | AF30: =T30-H30 | AG30: =SUM(Z30:AF30) | AH30: 本周广告占比 | AI30: =AG30/AG33
A31: 广告ACOS | B31: =B30/B32 | C31: =C30/C32 | D31: =D30/D32 | E31: =E30/E32 | F31: =F30/F32 | G31: =G30/G32 | H31: =H30/H32 | I31: =I30/I32 | M31: 广告ACOS | N31: =N30/N32 | O31: =O30/O32 | P31: =P30/P32 | Q31: =Q30/Q32 | R31: =R30/R32 | S31: =S30/S32 | T31: =T30/T32 | U31: =U30/U32 | Y31: 广告ACOS | Z31: =N31-B31 | AA31: =O31-C31 | AB31: =P31-D31 | AC31: =Q31-E31 | AD31: =R31-F31 | AE31: =S31-G31 | AF31: =T31-H31 | AG31: =AG30/AG32
A32: 广告销售额 | B32: =B25*$E$11 | C32: =C25*$E$11 | D32: =D25*$E$11 | E32: =E25*$E$11 | F32: =F25*$E$11 | G32: =G25*$E$11 | H32: =H25*$E$11 | I32: =SUM(B32:H32) | J32: 本周利润额 | K32: =I34 | M32: 广告销售额 | N32: =N25*$E$11 | O32: =O25*$E$11 | P32: =P25*$E$11 | Q32: =Q25*$E$11 | R32: =R25*$E$11 | S32: =S25*$E$11 | T32: =T25*$E$11 | U32: =SUM(N32:T32) | V32: 本周利润额 | W32: =U34 | Y32: 广告销售额 | Z32: =N32-B32 | AA32: =O32-C32 | AB32: =P32-D32 | AC32: =Q32-E32 | AD32: =R32-F32 | AE32: =S32-G32 | AF32: =T32-H32 | AG32: =SUM(Z32:AF32) | AH32: 本周利润额 | AI32: =AG34
A33: 总销售额 | B33: =B21*$E$11 | C33: =C21*$E$11 | D33: =D21*$E$11 | E33: =E21*$E$11 | F33: =F21*$E$11 | G33: =G21*$E$11 | H33: =H21*$E$11 | I33: =SUM(B33:H33) | J33: 本周利润率 | K33: =K32/I33 | M33: 总销售额 | N33: =N21*$E$11 | O33: =O21*$E$11 | P33: =P21*$E$11 | Q33: =Q21*$E$11 | R33: =R21*$E$11 | S33: =S21*$E$11 | T33: =T21*$E$11 | U33: =SUM(N33:T33) | V33: 本周利润率 | W33: =W32/U33 | Y33: 总销售额 | Z33: =N33-B33 | AA33: =O33-C33 | AB33: =P33-D33 | AC33: =Q33-E33 | AD33: =R33-F33 | AE33: =S33-G33 | AF33: =T33-H33 | AG33: =SUM(Z33:AF33) | AH33: 本周利润率 | AI33: =AI32/AG33
A34: 利润 | B34: =B21*$E$12-B30 | C34: =C21*$E$12-C30 | D34: =D21*$E$12-D30 | E34: =E21*$E$12-E30 | F34: =F21*$E$12-F30 | G34: =G21*$E$12-G30 | H34: =H21*$E$12-H30 | I34: =SUM(B34:H34) | J34: 结余利润额 | K34: =K32 | M34: 利润 | N34: =N21*$E$12-N30 | O34: =O21*$E$12-O30 | P34: =P21*$E$12-P30 | Q34: =Q21*$E$12-Q30 | R34: =R21*$E$12-R30 | S34: =S21*$E$12-S30 | T34: =T21*$E$12-T30 | U34: =SUM(N34:T34) | V34: 结余利润额 | W34: =W32 | Y34: 利润 | Z34: =N34-B34 | AA34: =O34-C34 | AB34: =P34-D34 | AC34: =Q34-E34 | AD34: =R34-F34 | AE34: =S34-G34 | AF34: =T34-H34 | AG34: =SUM(Z34:AF34) | AH34: 结余利润额 | AI34: =AI32
A35: 执行策略
A39: （目标）第二阶段详细计划 Part2 | C39: 开售W3 | M39: 实际完成数据 | O39: 开售W3 | Y39: 完成差额 | AA39: 开售W3
A40: 数据预测 | B40: Day 1 | C40: Day 2 | D40: Day 3 | E40: Day 4 | F40: Day 5 | G40: Day 6 | H40: Day 7 | I40: 合计 | M40: 数据预测 | N40: Day 1 | O40: Day 2 | P40: Day 3 | Q40: Day 4 | R40: Day 5 | S40: Day 6 | T40: Day 7 | U40: 合计 | Y40: 数据预测 | Z40: Day 1 | AA40: Day 2 | AB40: Day 3 | AC40: Day 4 | AD40: Day 5 | AE40: Day 6 | AF40: Day 7 | AG40: 合计
A41: 目标总单量 | B41: 1 | C41: 2 | D41: 3 | E41: 4 | F41: 5 | G41: 5 | H41: 6 | I41: =SUM(B41:H41) | M41: 总单量 | N41: 12 | O41: 23 | P41: 26 | Q41: 25 | R41: 11 | S41: 52 | T41: 12 | U41: =SUM(N41:T41) | Y41: 总单量 | Z41: =N41-B41 | AA41: =O41-C41 | AB41: =P41-D41 | AC41: =Q41-E41 | AD41: =R41-F41 | AE41: =S41-G41 | AF41: =T41-H41 | AG41: =SUM(Z41:AF41)
A42: 总流量 | B42: =B41/B48 | C42: =C41/C48 | D42: =D41/D48 | E42: =E41/E48 | F42: =F41/F48 | G42: =G41/G48 | H42: =H41/H48 | I42: =SUM(B42:H42) | M42: 总流量 | N42: =N41/N48 | O42: =O41/O48 | P42: =P41/P48 | Q42: =Q41/Q48 | R42: =R41/R48 | S42: =S41/S48 | T42: =T41/T48 | U42: =SUM(N42:T42) | Y42: 总流量 | Z42: =N42-B42 | AA42: =O42-C42 | AB42: =P42-D42 | AC42: =Q42-E42 | AD42: =R42-F42 | AE42: =S42-G42 | AF42: =T42-H42 | AG42: =SUM(Z42:AF42)
A43: 广告单占比 | B43: 1 | C43: 1 | D43: 1 | E43: 1 | F43: 1 | G43: 0.9 | H43: 0.9 | I43: =I45/I41 | M43: 广告单占比 | N43: 1 | O43: 1 | P43: 1 | Q43: 1 | R43: 1 | S43: 0.9 | T43: 0.9 | U43: =U45/U41 | Y43: 广告单占比 | Z43: =N43-B43 | AA43: =O43-C43 | AB43: =P43-D43 | AC43: =Q43-E43 | AD43: =R43-F43 | AE43: =S43-G43 | AF43: =T43-H43 | AG43: =AG45/AG41
A44: 自然单量 | B44: =B41-B45 | C44: =C41-C45 | D44: =D41-D45 | E44: =E41-E45 | F44: =F41-F45 | G44: =G41-G45 | H44: =H41-H45 | I44: =SUM(B44:H44) | M44: 自然单量 | N44: 12 | O44: =O41-O45 | P44: =P41-P45 | Q44: =Q41-Q45 | R44: =R41-R45 | S44: =S41-S45 | T44: =T41-T45 | U44: =SUM(N44:T44) | Y44: 自然单量 | Z44: =N44-B44 | AA44: =O44-C44 | AB44: =P44-D44 | AC44: =Q44-E44 | AD44: =R44-F44 | AE44: =S44-G44 | AF44: =T44-H44 | AG44: =SUM(Z44:AF44)
A45: 广告单量 | B45: =B41*B43 | C45: =C41*C43 | D45: =D41*D43 | E45: =E41*E43 | F45: =F41*F43 | G45: =G41*G43 | H45: =H41*H43 | I45: =SUM(B45:H45) | M45: 广告单量 | N45: =N41*N43 | O45: =O41*O43 | P45: =P41*P43 | Q45: =Q41*Q43 | R45: =R41*R43 | S45: =S41*S43 | T45: =T41*T43 | U45: =SUM(N45:T45) | Y45: 广告单量 | Z45: =N45-B45 | AA45: =O45-C45 | AB45: =P45-D45 | AC45: =Q45-E45 | AD45: =R45-F45 | AE45: =S45-G45 | AF45: =T45-H45 | AG45: =SUM(Z45:AF45)
A46: CPC | B46: 3.8 | C46: 3.8 | D46: 3.8 | E46: 3.8 | F46: 3.8 | G46: 3.8 | H46: 3.8 | I46: =AVERAGE(B46:H46) | M46: CPC | N46: 3.8 | O46: 3.8 | P46: 3.8 | Q46: 3.8 | R46: 3.8 | S46: 3.8 | T46: 3.8 | U46: =AVERAGE(N46:T46) | Y46: CPC | Z46: =N46-B46 | AA46: =O46-C46 | AB46: =P46-D46 | AC46: =Q46-E46 | AD46: =R46-F46 | AE46: =S46-G46 | AF46: =T46-H46 | AG46: =AVERAGE(Z46:AF46)
A47: 点击率CTR | B47: 0.003 | C47: 0.003 | D47: 0.003 | E47: 0.003 | F47: 0.003 | G47: 0.003 | H47: 0.003 | I47: =AVERAGE(B47:H47) | M47: 点击率CTR | N47: 0.003 | O47: 0.003 | P47: 0.003 | Q47: 0.003 | R47: 0.003 | S47: 0.003 | T47: 0.003 | U47: =AVERAGE(N47:T47) | Y47: 点击率CTR | Z47: =N47-B47 | AA47: =O47-C47 | AB47: =P47-D47 | AC47: =Q47-E47 | AD47: =R47-F47 | AE47: =S47-G47 | AF47: =T47-H47 | AG47: =AVERAGE(Z47:AF47)
A48: 转化率CVR | B48: 0.04 | C48: 0.04 | D48: 0.04 | E48: 0.04 | F48: 0.04 | G48: 0.04 | H48: 0.04 | I48: =AVERAGE(B48:H48) | J48: 累计出单 | K48: =I41 | M48: 转化率CVR | N48: 0.04 | O48: 0.04 | P48: 0.04 | Q48: 0.04 | R48: 0.04 | S48: 0.04 | T48: 0.04 | U48: =AVERAGE(N48:T48) | V48: 累计出单 | W48: =U41 | Y48: 转化率CVR | Z48: =N48-B48 | AA48: =O48-C48 | AB48: =P48-D48 | AC48: =Q48-E48 | AD48: =R48-F48 | AE48: =S48-G48 | AF48: =T48-H48 | AG48: =AVERAGE(Z48:AF48) | AH48: 累计出单 | AI48: =AG41
A49: 广告点击量 | B49: =B45/B48 | C49: =C45/C48 | D49: =D45/D48 | E49: =E45/E48 | F49: =F45/F48 | G49: =G45/G48 | H49: =H45/H48 | I49: =SUM(B49:H49) | J49: 本周CPA | K49: =I50/I45 | M49: 广告点击量 | N49: =N45/N48 | O49: =O45/O48 | P49: =P45/P48 | Q49: =Q45/Q48 | R49: =R45/R48 | S49: =S45/S48 | T49: =T45/T48 | U49: =SUM(N49:T49) | V49: 本周CPA | W49: =U50/U45 | Y49: 广告点击量 | Z49: =N49-B49 | AA49: =O49-C49 | AB49: =P49-D49 | AC49: =Q49-E49 | AD49: =R49-F49 | AE49: =S49-G49 | AF49: =T49-H49 | AG49: =SUM(Z49:AF49) | AH49: 本周CPA | AI49: =AG50/AG45
A50: 广告花费 | B50: =B46*B49 | C50: =C46*C49 | D50: =D46*D49 | E50: =E46*E49 | F50: =F46*F49 | G50: =G46*G49 | H50: =H46*H49 | I50: =SUM(B50:H50) | J50: 本周广告占比 | K50: =I50/I53 | M50: 广告花费 | N50: =N46*N49 | O50: =O46*O49 | P50: =P46*P49 | Q50: =Q46*Q49 | R50: =R46*R49 | S50: =S46*S49 | T50: =T46*T49 | U50: =SUM(N50:T50) | V50: 本周广告占比 | W50: =U50/U53 | Y50: 广告花费 | Z50: =N50-B50 | AA50: =O50-C50 | AB50: =P50-D50 | AC50: =Q50-E50 | AD50: =R50-F50 | AE50: =S50-G50 | AF50: =T50-H50 | AG50: =SUM(Z50:AF50) | AH50: 本周广告占比 | AI50: =AG50/AG53
A51: 广告ACOS | B51: =B50/B52 | C51: =C50/C52 | D51: =D50/D52 | E51: =E50/E52 | F51: =F50/F52 | G51: =G50/G52 | H51: =H50/H52 | I51: =I50/I52 | M51: 广告ACOS | N51: =N50/N52 | O51: =O50/O52 | P51: =P50/P52 | Q51: =Q50/Q52 | R51: =R50/R52 | S51: =S50/S52 | T51: =T50/T52 | U51: =U50/U52 | Y51: 广告ACOS | Z51: =N51-B51 | AA51: =O51-C51 | AB51: =P51-D51 | AC51: =Q51-E51 | AD51: =R51-F51 | AE51: =S51-G51 | AF51: =T51-H51 | AG51: =AG50/AG52
A52: 广告销售额 | B52: =B45*$E$11 | C52: =C45*$E$11 | D52: =D45*$E$11 | E52: =E45*$E$11 | F52: =F45*$E$11 | G52: =G45*$E$11 | H52: =H45*$E$11 | I52: =SUM(B52:H52) | J52: 本周利润额 | K52: =I54 | M52: 广告销售额 | N52: =N45*$E$11 | O52: =O45*$E$11 | P52: =P45*$E$11 | Q52: =Q45*$E$11 | R52: =R45*$E$11 | S52: =S45*$E$11 | T52: =T45*$E$11 | U52: =SUM(N52:T52) | V52: 本周利润额 | W52: =U54 | Y52: 广告销售额 | Z52: =N52-B52 | AA52: =O52-C52 | AB52: =P52-D52 | AC52: =Q52-E52 | AD52: =R52-F52 | AE52: =S52-G52 | AF52: =T52-H52 | AG52: =SUM(Z52:AF52) | AH52: 本周利润额 | AI52: =AG54
A53: 总销售额 | B53: =B41*$E$11 | C53: =C41*$E$11 | D53: =D41*$E$11 | E53: =E41*$E$11 | F53: =F41*$E$11 | G53: =G41*$E$11 | H53: =H41*$E$11 | I53: =SUM(B53:H53) | J53: 本周利润率 | K53: =K52/I53 | M53: 总销售额 | N53: =N41*$E$11 | O53: =O41*$E$11 | P53: =P41*$E$11 | Q53: =Q41*$E$11 | R53: =R41*$E$11 | S53: =S41*$E$11 | T53: =T41*$E$11 | U53: =SUM(N53:T53) | V53: 本周利润率 | W53: =W52/U53 | Y53: 总销售额 | Z53: =N53-B53 | AA53: =O53-C53 | AB53: =P53-D53 | AC53: =Q53-E53 | AD53: =R53-F53 | AE53: =S53-G53 | AF53: =T53-H53 | AG53: =SUM(Z53:AF53) | AH53: 本周利润率 | AI53: =AI52/AG53
A54: 利润 | B54: =B41*$E$12-B50 | C54: =C41*$E$12-C50 | D54: =D41*$E$12-D50 | E54: =E41*$E$12-E50 | F54: =F41*$E$12-F50 | G54: =G41*$E$12-G50 | H54: =H41*$E$12-H50 | I54: =SUM(B54:H54) | J54: 结余利润额 | K54: =K52 | M54: 利润 | N54: =N41*$E$12-N50 | O54: =O41*$E$12-O50 | P54: =P41*$E$12-P50 | Q54: =Q41*$E$12-Q50 | R54: =R41*$E$12-R50 | S54: =S41*$E$12-S50 | T54: =T41*$E$12-T50 | U54: =SUM(N54:T54) | V54: 结余利润额 | W54: =W52 | Y54: 利润 | Z54: =N54-B54 | AA54: =O54-C54 | AB54: =P54-D54 | AC54: =Q54-E54 | AD54: =R54-F54 | AE54: =S54-G54 | AF54: =T54-H54 | AG54: =SUM(Z54:AF54) | AH54: 结余利润额 | AI54: =AI52
A55: 执行策略
A59: （目标）第二阶段详细计划 Part3 | C59: 开售W4 | M59: 实际完成数据 | O59: 开售W4 | Y59: 完成差额 | AA59: 开售W4
A60: 数据预测 | B60: Day 1 | C60: Day 2 | D60: Day 3 | E60: Day 4 | F60: Day 5 | G60: Day 6 | H60: Day 7 | I60: 合计 | M60: 数据预测 | N60: Day 1 | O60: Day 2 | P60: Day 3 | Q60: Day 4 | R60: Day 5 | S60: Day 6 | T60: Day 7 | U60: 合计 | Y60: 数据预测 | Z60: Day 1 | AA60: Day 2 | AB60: Day 3 | AC60: Day 4 | AD60: Day 5 | AE60: Day 6 | AF60: Day 7 | AG60: 合计
A61: 目标总单量 | B61: 1 | C61: 2 | D61: 3 | E61: 4 | F61: 5 | G61: 5 | H61: 6 | I61: =SUM(B61:H61) | M61: 总单量 | N61: 12 | O61: 23 | P61: 26 | Q61: 25 | R61: 11 | S61: 52 | T61: 12 | U61: =SUM(N61:T61) | Y61: 总单量 | Z61: =N61-B61 | AA61: =O61-C61 | AB61: =P61-D61 | AC61: =Q61-E61 | AD61: =R61-F61 | AE61: =S61-G61 | AF61: =T61-H61 | AG61: =SUM(Z61:AF61)
A62: 总流量 | B62: =B61/B68 | C62: =C61/C68 | D62: =D61/D68 | E62: =E61/E68 | F62: =F61/F68 | G62: =G61/G68 | H62: =H61/H68 | I62: =SUM(B62:H62) | M62: 总流量 | N62: =N61/N68 | O62: =O61/O68 | P62: =P61/P68 | Q62: =Q61/Q68 | R62: =R61/R68 | S62: =S61/S68 | T62: =T61/T68 | U62: =SUM(N62:T62) | Y62: 总流量 | Z62: =N62-B62 | AA62: =O62-C62 | AB62: =P62-D62 | AC62: =Q62-E62 | AD62: =R62-F62 | AE62: =S62-G62 | AF62: =T62-H62 | AG62: =SUM(Z62:AF62)
A63: 广告单占比 | B63: 1 | C63: 1 | D63: 1 | E63: 1 | F63: 1 | G63: 0.9 | H63: 0.9 | I63: =I65/I61 | M63: 广告单占比 | N63: 1 | O63: 1 | P63: 1 | Q63: 1 | R63: 1 | S63: 0.9 | T63: 0.9 | U63: =U65/U61 | Y63: 广告单占比 | Z63: =N63-B63 | AA63: =O63-C63 | AB63: =P63-D63 | AC63: =Q63-E63 | AD63: =R63-F63 | AE63: =S63-G63 | AF63: =T63-H63 | AG63: =AG65/AG61
A64: 自然单量 | B64: =B61-B65 | C64: =C61-C65 | D64: =D61-D65 | E64: =E61-E65 | F64: =F61-F65 | G64: =G61-G65 | H64: =H61-H65 | I64: =SUM(B64:H64) | M64: 自然单量 | N64: 12 | O64: =O61-O65 | P64: =P61-P65 | Q64: =Q61-Q65 | R64: =R61-R65 | S64: =S61-S65 | T64: =T61-T65 | U64: =SUM(N64:T64) | Y64: 自然单量 | Z64: =N64-B64 | AA64: =O64-C64 | AB64: =P64-D64 | AC64: =Q64-E64 | AD64: =R64-F64 | AE64: =S64-G64 | AF64: =T64-H64 | AG64: =SUM(Z64:AF64)
A65: 广告单量 | B65: =B61*B63 | C65: =C61*C63 | D65: =D61*D63 | E65: =E61*E63 | F65: =F61*F63 | G65: =G61*G63 | H65: =H61*H63 | I65: =SUM(B65:H65) | M65: 广告单量 | N65: =N61*N63 | O65: =O61*O63 | P65: =P61*P63 | Q65: =Q61*Q63 | R65: =R61*R63 | S65: =S61*S63 | T65: =T61*T63 | U65: =SUM(N65:T65) | Y65: 广告单量 | Z65: =N65-B65 | AA65: =O65-C65 | AB65: =P65-D65 | AC65: =Q65-E65 | AD65: =R65-F65 | AE65: =S65-G65 | AF65: =T65-H65 | AG65: =SUM(Z65:AF65)
A66: CPC | B66: 3.8 | C66: 3.8 | D66: 3.8 | E66: 3.8 | F66: 3.8 | G66: 3.8 | H66: 3.8 | I66: =AVERAGE(B66:H66) | M66: CPC | N66: 3.8 | O66: 3.8 | P66: 3.8 | Q66: 3.8 | R66: 3.8 | S66: 3.8 | T66: 3.8 | U66: =AVERAGE(N66:T66) | Y66: CPC | Z66: =N66-B66 | AA66: =O66-C66 | AB66: =P66-D66 | AC66: =Q66-E66 | AD66: =R66-F66 | AE66: =S66-G66 | AF66: =T66-H66 | AG66: =AVERAGE(Z66:AF66)
A67: 点击率CTR | B67: 0.003 | C67: 0.003 | D67: 0.003 | E67: 0.003 | F67: 0.003 | G67: 0.003 | H67: 0.003 | I67: =AVERAGE(B67:H67) | M67: 点击率CTR | N67: 0.003 | O67: 0.003 | P67: 0.003 | Q67: 0.003 | R67: 0.003 | S67: 0.003 | T67: 0.003 | U67: =AVERAGE(N67:T67) | Y67: 点击率CTR | Z67: =N67-B67 | AA67: =O67-C67 | AB67: =P67-D67 | AC67: =Q67-E67 | AD67: =R67-F67 | AE67: =S67-G67 | AF67: =T67-H67 | AG67: =AVERAGE(Z67:AF67)
A68: 转化率CVR | B68: 0.04 | C68: 0.04 | D68: 0.04 | E68: 0.04 | F68: 0.04 | G68: 0.04 | H68: 0.04 | I68: =AVERAGE(B68:H68) | J68: 累计出单 | K68: =I61 | M68: 转化率CVR | N68: 0.04 | O68: 0.04 | P68: 0.04 | Q68: 0.04 | R68: 0.04 | S68: 0.04 | T68: 0.04 | U68: =AVERAGE(N68:T68) | V68: 累计出单 | W68: =U61 | Y68: 转化率CVR | Z68: =N68-B68 | AA68: =O68-C68 | AB68: =P68-D68 | AC68: =Q68-E68 | AD68: =R68-F68 | AE68: =S68-G68 | AF68: =T68-H68 | AG68: =AVERAGE(Z68:AF68) | AH68: 累计出单 | AI68: =AG61
A69: 广告点击量 | B69: =B65/B68 | C69: =C65/C68 | D69: =D65/D68 | E69: =E65/E68 | F69: =F65/F68 | G69: =G65/G68 | H69: =H65/H68 | I69: =SUM(B69:H69) | J69: 本周CPA | K69: =I70/I65 | M69: 广告点击量 | N69: =N65/N68 | O69: =O65/O68 | P69: =P65/P68 | Q69: =Q65/Q68 | R69: =R65/R68 | S69: =S65/S68 | T69: =T65/T68 | U69: =SUM(N69:T69) | V69: 本周CPA | W69: =U70/U65 | Y69: 广告点击量 | Z69: =N69-B69 | AA69: =O69-C69 | AB69: =P69-D69 | AC69: =Q69-E69 | AD69: =R69-F69 | AE69: =S69-G69 | AF69: =T69-H69 | AG69: =SUM(Z69:AF69) | AH69: 本周CPA | AI69: =AG70/AG65
A70: 广告花费 | B70: =B66*B69 | C70: =C66*C69 | D70: =D66*D69 | E70: =E66*E69 | F70: =F66*F69 | G70: =G66*G69 | H70: =H66*H69 | I70: =SUM(B70:H70) | J70: 本周广告占比 | K70: =I70/I73 | M70: 广告花费 | N70: =N66*N69 | O70: =O66*O69 | P70: =P66*P69 | Q70: =Q66*Q69 | R70: =R66*R69 | S70: =S66*S69 | T70: =T66*T69 | U70: =SUM(N70:T70) | V70: 本周广告占比 | W70: =U70/U73 | Y70: 广告花费 | Z70: =N70-B70 | AA70: =O70-C70 | AB70: =P70-D70 | AC70: =Q70-E70 | AD70: =R70-F70 | AE70: =S70-G70 | AF70: =T70-H70 | AG70: =SUM(Z70:AF70) | AH70: 本周广告占比 | AI70: =AG70/AG73
A71: 广告ACOS | B71: =B70/B72 | C71: =C70/C72 | D71: =D70/D72 | E71: =E70/E72 | F71: =F70/F72 | G71: =G70/G72 | H71: =H70/H72 | I71: =I70/I72 | M71: 广告ACOS | N71: =N70/N72 | O71: =O70/O72 | P71: =P70/P72 | Q71: =Q70/Q72 | R71: =R70/R72 | S71: =S70/S72 | T71: =T70/T72 | U71: =U70/U72 | Y71: 广告ACOS | Z71: =N71-B71 | AA71: =O71-C71 | AB71: =P71-D71 | AC71: =Q71-E71 | AD71: =R71-F71 | AE71: =S71-G71 | AF71: =T71-H71 | AG71: =AG70/AG72
A72: 广告销售额 | B72: =B65*$E$11 | C72: =C65*$E$11 | D72: =D65*$E$11 | E72: =E65*$E$11 | F72: =F65*$E$11 | G72: =G65*$E$11 | H72: =H65*$E$11 | I72: =SUM(B72:H72) | J72: 本周利润额 | K72: =I74 | M72: 广告销售额 | N72: =N65*$E$11 | O72: =O65*$E$11 | P72: =P65*$E$11 | Q72: =Q65*$E$11 | R72: =R65*$E$11 | S72: =S65*$E$11 | T72: =T65*$E$11 | U72: =SUM(N72:T72) | V72: 本周利润额 | W72: =U74 | Y72: 广告销售额 | Z72: =N72-B72 | AA72: =O72-C72 | AB72: =P72-D72 | AC72: =Q72-E72 | AD72: =R72-F72 | AE72: =S72-G72 | AF72: =T72-H72 | AG72: =SUM(Z72:AF72) | AH72: 本周利润额 | AI72: =AG74
A73: 总销售额 | B73: =B61*$E$11 | C73: =C61*$E$11 | D73: =D61*$E$11 | E73: =E61*$E$11 | F73: =F61*$E$11 | G73: =G61*$E$11 | H73: =H61*$E$11 | I73: =SUM(B73:H73) | J73: 本周利润率 | K73: =K72/I73 | M73: 总销售额 | N73: =N61*$E$11 | O73: =O61*$E$11 | P73: =P61*$E$11 | Q73: =Q61*$E$11 | R73: =R61*$E$11 | S73: =S61*$E$11 | T73: =T61*$E$11 | U73: =SUM(N73:T73) | V73: 本周利润率 | W73: =W72/U73 | Y73: 总销售额 | Z73: =N73-B73 | AA73: =O73-C73 | AB73: =P73-D73 | AC73: =Q73-E73 | AD73: =R73-F73 | AE73: =S73-G73 | AF73: =T73-H73 | AG73: =SUM(Z73:AF73) | AH73: 本周利润率 | AI73: =AI72/AG73
A74: 利润 | B74: =B61*$E$12-B70 | C74: =C61*$E$12-C70 | D74: =D61*$E$12-D70 | E74: =E61*$E$12-E70 | F74: =F61*$E$12-F70 | G74: =G61*$E$12-G70 | H74: =H61*$E$12-H70 | I74: =SUM(B74:H74) | J74: 结余利润额 | K74: =K72 | M74: 利润 | N74: =N61*$E$12-N70 | O74: =O61*$E$12-O70 | P74: =P61*$E$12-P70 | Q74: =Q61*$E$12-Q70 | R74: =R61*$E$12-R70 | S74: =S61*$E$12-S70 | T74: =T61*$E$12-T70 | U74: =SUM(N74:T74) | V74: 结余利润额 | W74: =W72 | Y74: 利润 | Z74: =N74-B74 | AA74: =O74-C74 | AB74: =P74-D74 | AC74: =Q74-E74 | AD74: =R74-F74 | AE74: =S74-G74 | AF74: =T74-H74 | AG74: =SUM(Z74:AF74) | AH74: 结余利润额 | AI74: =AI72
A75: 执行策略
A79: 第三阶段：29~42天 | C79: 阶段目标：转VC BD，借助活动流量扶持，进一步提升单量和冲击大词自然位；
A80: ASIN | D80: 定价 | E80: 139
A81: 终期流量目标 | B81: =IFERROR(B82/B84,0) | D81: 折扣 | E81: 30
A82: 终期日销目标 | B82: 23 | D82: 成交价 | E82: =E80-E81
A83: CTR目标 | B83: 0.004 | D83: 不含广告利润额 | E83: 28.43 | F83: 利润额扣除退货率，不扣除广告占比
A84: CVR目标 | B84: 0.06
A85: 广告单占比目标 | B85: 0.6
A86: 目标评论数 | B86: 30
A88: （目标）第三阶段详细计划 Part1 | C88: 开售W5 | M88: 实际完成数据 | O88: 开售W5 | Y88: 完成差额 | AA88: 开售W5
A89: 数据预测 | B89: Day 1 | C89: Day 2 | D89: Day 3 | E89: Day 4 | F89: Day 5 | G89: Day 6 | H89: Day 7 | I89: 合计 | M89: 数据预测 | N89: Day 1 | O89: Day 2 | P89: Day 3 | Q89: Day 4 | R89: Day 5 | S89: Day 6 | T89: Day 7 | U89: 合计 | Y89: 数据预测 | Z89: Day 1 | AA89: Day 2 | AB89: Day 3 | AC89: Day 4 | AD89: Day 5 | AE89: Day 6 | AF89: Day 7 | AG89: 合计
A90: 目标总单量 | B90: 1 | C90: 2 | D90: 3 | E90: 4 | F90: 5 | G90: 5 | H90: 6 | I90: =SUM(B90:H90) | M90: 总单量 | N90: 12 | O90: 23 | P90: 26 | Q90: 25 | R90: 11 | S90: 52 | T90: 12 | U90: =SUM(N90:T90) | Y90: 总单量 | Z90: =N90-B90 | AA90: =O90-C90 | AB90: =P90-D90 | AC90: =Q90-E90 | AD90: =R90-F90 | AE90: =S90-G90 | AF90: =T90-H90 | AG90: =SUM(Z90:AF90)
A91: 总流量 | B91: =B90/B97 | C91: =C90/C97 | D91: =D90/D97 | E91: =E90/E97 | F91: =F90/F97 | G91: =G90/G97 | H91: =H90/H97 | I91: =SUM(B91:H91) | M91: 总流量 | N91: =N90/N97 | O91: =O90/O97 | P91: =P90/P97 | Q91: =Q90/Q97 | R91: =R90/R97 | S91: =S90/S97 | T91: =T90/T97 | U91: =SUM(N91:T91) | Y91: 总流量 | Z91: =N91-B91 | AA91: =O91-C91 | AB91: =P91-D91 | AC91: =Q91-E91 | AD91: =R91-F91 | AE91: =S91-G91 | AF91: =T91-H91 | AG91: =SUM(Z91:AF91)
A92: 广告单占比 | B92: 1 | C92: 1 | D92: 1 | E92: 1 | F92: 1 | G92: 0.9 | H92: 0.9 | I92: =I94/I90 | M92: 广告单占比 | N92: 1 | O92: 1 | P92: 1 | Q92: 1 | R92: 1 | S92: 0.9 | T92: 0.9 | U92: =U94/U90 | Y92: 广告单占比 | Z92: =N92-B92 | AA92: =O92-C92 | AB92: =P92-D92 | AC92: =Q92-E92 | AD92: =R92-F92 | AE92: =S92-G92 | AF92: =T92-H92 | AG92: =AG94/AG90
A93: 自然单量 | B93: =B90-B94 | C93: =C90-C94 | D93: =D90-D94 | E93: =E90-E94 | F93: =F90-F94 | G93: =G90-G94 | H93: =H90-H94 | I93: =SUM(B93:H93) | M93: 自然单量 | N93: 12 | O93: =O90-O94 | P93: =P90-P94 | Q93: =Q90-Q94 | R93: =R90-R94 | S93: =S90-S94 | T93: =T90-T94 | U93: =SUM(N93:T93) | Y93: 自然单量 | Z93: =N93-B93 | AA93: =O93-C93 | AB93: =P93-D93 | AC93: =Q93-E93 | AD93: =R93-F93 | AE93: =S93-G93 | AF93: =T93-H93 | AG93: =SUM(Z93:AF93)
A94: 广告单量 | B94: =B90*B92 | C94: =C90*C92 | D94: =D90*D92 | E94: =E90*E92 | F94: =F90*F92 | G94: =G90*G92 | H94: =H90*H92 | I94: =SUM(B94:H94) | M94: 广告单量 | N94: =N90*N92 | O94: =O90*O92 | P94: =P90*P92 | Q94: =Q90*Q92 | R94: =R90*R92 | S94: =S90*S92 | T94: =T90*T92 | U94: =SUM(N94:T94) | Y94: 广告单量 | Z94: =N94-B94 | AA94: =O94-C94 | AB94: =P94-D94 | AC94: =Q94-E94 | AD94: =R94-F94 | AE94: =S94-G94 | AF94: =T94-H94 | AG94: =SUM(Z94:AF94)
A95: CPC | B95: 3.8 | C95: 3.8 | D95: 3.8 | E95: 3.8 | F95: 3.8 | G95: 3.8 | H95: 3.8 | I95: =AVERAGE(B95:H95) | M95: CPC | N95: 3.8 | O95: 3.8 | P95: 3.8 | Q95: 3.8 | R95: 3.8 | S95: 3.8 | T95: 3.8 | U95: =AVERAGE(N95:T95) | Y95: CPC | Z95: =N95-B95 | AA95: =O95-C95 | AB95: =P95-D95 | AC95: =Q95-E95 | AD95: =R95-F95 | AE95: =S95-G95 | AF95: =T95-H95 | AG95: =AVERAGE(Z95:AF95)
A96: 点击率CTR | B96: 0.003 | C96: 0.003 | D96: 0.003 | E96: 0.003 | F96: 0.003 | G96: 0.003 | H96: 0.003 | I96: =AVERAGE(B96:H96) | M96: 点击率CTR | N96: 0.003 | O96: 0.003 | P96: 0.003 | Q96: 0.003 | R96: 0.003 | S96: 0.003 | T96: 0.003 | U96: =AVERAGE(N96:T96) | Y96: 点击率CTR | Z96: =N96-B96 | AA96: =O96-C96 | AB96: =P96-D96 | AC96: =Q96-E96 | AD96: =R96-F96 | AE96: =S96-G96 | AF96: =T96-H96 | AG96: =AVERAGE(Z96:AF96)
A97: 转化率CVR | B97: 0.04 | C97: 0.04 | D97: 0.04 | E97: 0.04 | F97: 0.04 | G97: 0.04 | H97: 0.04 | I97: =AVERAGE(B97:H97) | J97: 累计出单 | K97: =I90 | M97: 转化率CVR | N97: 0.04 | O97: 0.04 | P97: 0.04 | Q97: 0.04 | R97: 0.04 | S97: 0.04 | T97: 0.04 | U97: =AVERAGE(N97:T97) | V97: 累计出单 | W97: =U90 | Y97: 转化率CVR | Z97: =N97-B97 | AA97: =O97-C97 | AB97: =P97-D97 | AC97: =Q97-E97 | AD97: =R97-F97 | AE97: =S97-G97 | AF97: =T97-H97 | AG97: =AVERAGE(Z97:AF97) | AH97: 累计出单 | AI97: =AG90
A98: 广告点击量 | B98: =B94/B97 | C98: =C94/C97 | D98: =D94/D97 | E98: =E94/E97 | F98: =F94/F97 | G98: =G94/G97 | H98: =H94/H97 | I98: =SUM(B98:H98) | J98: 本周CPA | K98: =I99/I94 | M98: 广告点击量 | N98: =N94/N97 | O98: =O94/O97 | P98: =P94/P97 | Q98: =Q94/Q97 | R98: =R94/R97 | S98: =S94/S97 | T98: =T94/T97 | U98: =SUM(N98:T98) | V98: 本周CPA | W98: =U99/U94 | Y98: 广告点击量 | Z98: =N98-B98 | AA98: =O98-C98 | AB98: =P98-D98 | AC98: =Q98-E98 | AD98: =R98-F98 | AE98: =S98-G98 | AF98: =T98-H98 | AG98: =SUM(Z98:AF98) | AH98: 本周CPA | AI98: =AG99/AG94
A99: 广告花费 | B99: =B95*B98 | C99: =C95*C98 | D99: =D95*D98 | E99: =E95*E98 | F99: =F95*F98 | G99: =G95*G98 | H99: =H95*H98 | I99: =SUM(B99:H99) | J99: 本周广告占比 | K99: =I99/I102 | M99: 广告花费 | N99: =N95*N98 | O99: =O95*O98 | P99: =P95*P98 | Q99: =Q95*Q98 | R99: =R95*R98 | S99: =S95*S98 | T99: =T95*T98 | U99: =SUM(N99:T99) | V99: 本周广告占比 | W99: =U99/U102 | Y99: 广告花费 | Z99: =N99-B99 | AA99: =O99-C99 | AB99: =P99-D99 | AC99: =Q99-E99 | AD99: =R99-F99 | AE99: =S99-G99 | AF99: =T99-H99 | AG99: =SUM(Z99:AF99) | AH99: 本周广告占比 | AI99: =AG99/AG102
A100: 广告ACOS | B100: =B99/B101 | C100: =C99/C101 | D100: =D99/D101 | E100: =E99/E101 | F100: =F99/F101 | G100: =G99/G101 | H100: =H99/H101 | I100: =I99/I101 | M100: 广告ACOS | N100: =N99/N101 | O100: =O99/O101 | P100: =P99/P101 | Q100: =Q99/Q101 | R100: =R99/R101 | S100: =S99/S101 | T100: =T99/T101 | U100: =U99/U101 | Y100: 广告ACOS | Z100: =N100-B100 | AA100: =O100-C100 | AB100: =P100-D100 | AC100: =Q100-E100 | AD100: =R100-F100 | AE100: =S100-G100 | AF100: =T100-H100 | AG100: =AG99/AG101
A101: 广告销售额 | B101: =B94*$E$11 | C101: =C94*$E$11 | D101: =D94*$E$11 | E101: =E94*$E$11 | F101: =F94*$E$11 | G101: =G94*$E$11 | H101: =H94*$E$11 | I101: =SUM(B101:H101) | J101: 本周利润额 | K101: =I103 | M101: 广告销售额 | N101: =N94*$E$11 | O101: =O94*$E$11 | P101: =P94*$E$11 | Q101: =Q94*$E$11 | R101: =R94*$E$11 | S101: =S94*$E$11 | T101: =T94*$E$11 | U101: =SUM(N101:T101) | V101: 本周利润额 | W101: =U103 | Y101: 广告销售额 | Z101: =N101-B101 | AA101: =O101-C101 | AB101: =P101-D101 | AC101: =Q101-E101 | AD101: =R101-F101 | AE101: =S101-G101 | AF101: =T101-H101 | AG101: =SUM(Z101:AF101) | AH101: 本周利润额 | AI101: =AG103
A102: 总销售额 | B102: =B90*$E$11 | C102: =C90*$E$11 | D102: =D90*$E$11 | E102: =E90*$E$11 | F102: =F90*$E$11 | G102: =G90*$E$11 | H102: =H90*$E$11 | I102: =SUM(B102:H102) | J102: 本周利润率 | K102: =K101/I102 | M102: 总销售额 | N102: =N90*$E$11 | O102: =O90*$E$11 | P102: =P90*$E$11 | Q102: =Q90*$E$11 | R102: =R90*$E$11 | S102: =S90*$E$11 | T102: =T90*$E$11 | U102: =SUM(N102:T102) | V102: 本周利润率 | W102: =W101/U102 | Y102: 总销售额 | Z102: =N102-B102 | AA102: =O102-C102 | AB102: =P102-D102 | AC102: =Q102-E102 | AD102: =R102-F102 | AE102: =S102-G102 | AF102: =T102-H102 | AG102: =SUM(Z102:AF102) | AH102: 本周利润率 | AI102: =AI101/AG102
A103: 利润 | B103: =B90*$E$12-B99 | C103: =C90*$E$12-C99 | D103: =D90*$E$12-D99 | E103: =E90*$E$12-E99 | F103: =F90*$E$12-F99 | G103: =G90*$E$12-G99 | H103: =H90*$E$12-H99 | I103: =SUM(B103:H103) | J103: 结余利润额 | K103: =K101 | M103: 利润 | N103: =N90*$E$12-N99 | O103: =O90*$E$12-O99 | P103: =P90*$E$12-P99 | Q103: =Q90*$E$12-Q99 | R103: =R90*$E$12-R99 | S103: =S90*$E$12-S99 | T103: =T90*$E$12-T99 | U103: =SUM(N103:T103) | V103: 结余利润额 | W103: =W101 | Y103: 利润 | Z103: =N103-B103 | AA103: =O103-C103 | AB103: =P103-D103 | AC103: =Q103-E103 | AD103: =R103-F103 | AE103: =S103-G103 | AF103: =T103-H103 | AG103: =SUM(Z103:AF103) | AH103: 结余利润额 | AI103: =AI101
A104: 执行策略
A108: （目标）第三阶段详细计划 Part2 | C108: 开售W6 | M108: 实际完成数据 | O108: 开售W6 | Y108: 完成差额 | AA108: 开售W6
A109: 数据预测 | B109: Day 1 | C109: Day 2 | D109: Day 3 | E109: Day 4 | F109: Day 5 | G109: Day 6 | H109: Day 7 | I109: 合计 | M109: 数据预测 | N109: Day 1 | O109: Day 2 | P109: Day 3 | Q109: Day 4 | R109: Day 5 | S109: Day 6 | T109: Day 7 | U109: 合计 | Y109: 数据预测 | Z109: Day 1 | AA109: Day 2 | AB109: Day 3 | AC109: Day 4 | AD109: Day 5 | AE109: Day 6 | AF109: Day 7 | AG109: 合计
A110: 目标总单量 | B110: 1 | C110: 2 | D110: 3 | E110: 4 | F110: 5 | G110: 5 | H110: 6 | I110: =SUM(B110:H110) | M110: 总单量 | N110: 12 | O110: 23 | P110: 26 | Q110: 25 | R110: 11 | S110: 52 | T110: 12 | U110: =SUM(N110:T110) | Y110: 总单量 | Z110: =N110-B110 | AA110: =O110-C110 | AB110: =P110-D110 | AC110: =Q110-E110 | AD110: =R110-F110 | AE110: =S110-G110 | AF110: =T110-H110 | AG110: =SUM(Z110:AF110)
A111: 总流量 | B111: =B110/B117 | C111: =C110/C117 | D111: =D110/D117 | E111: =E110/E117 | F111: =F110/F117 | G111: =G110/G117 | H111: =H110/H117 | I111: =SUM(B111:H111) | M111: 总流量 | N111: =N110/N117 | O111: =O110/O117 | P111: =P110/P117 | Q111: =Q110/Q117 | R111: =R110/R117 | S111: =S110/S117 | T111: =T110/T117 | U111: =SUM(N111:T111) | Y111: 总流量 | Z111: =N111-B111 | AA111: =O111-C111 | AB111: =P111-D111 | AC111: =Q111-E111 | AD111: =R111-F111 | AE111: =S111-G111 | AF111: =T111-H111 | AG111: =SUM(Z111:AF111)
A112: 广告单占比 | B112: 1 | C112: 1 | D112: 1 | E112: 1 | F112: 1 | G112: 0.9 | H112: 0.9 | I112: =I114/I110 | M112: 广告单占比 | N112: 1 | O112: 1 | P112: 1 | Q112: 1 | R112: 1 | S112: 0.9 | T112: 0.9 | U112: =U114/U110 | Y112: 广告单占比 | Z112: =N112-B112 | AA112: =O112-C112 | AB112: =P112-D112 | AC112: =Q112-E112 | AD112: =R112-F112 | AE112: =S112-G112 | AF112: =T112-H112 | AG112: =AG114/AG110
A113: 自然单量 | B113: =B110-B114 | C113: =C110-C114 | D113: =D110-D114 | E113: =E110-E114 | F113: =F110-F114 | G113: =G110-G114 | H113: =H110-H114 | I113: =SUM(B113:H113) | M113: 自然单量 | N113: 12 | O113: =O110-O114 | P113: =P110-P114 | Q113: =Q110-Q114 | R113: =R110-R114 | S113: =S110-S114 | T113: =T110-T114 | U113: =SUM(N113:T113) | Y113: 自然单量 | Z113: =N113-B113 | AA113: =O113-C113 | AB113: =P113-D113 | AC113: =Q113-E113 | AD113: =R113-F113 | AE113: =S113-G113 | AF113: =T113-H113 | AG113: =SUM(Z113:AF113)
A114: 广告单量 | B114: =B110*B112 | C114: =C110*C112 | D114: =D110*D112 | E114: =E110*E112 | F114: =F110*F112 | G114: =G110*G112 | H114: =H110*H112 | I114: =SUM(B114:H114) | M114: 广告单量 | N114: =N110*N112 | O114: =O110*O112 | P114: =P110*P112 | Q114: =Q110*Q112 | R114: =R110*R112 | S114: =S110*S112 | T114: =T110*T112 | U114: =SUM(N114:T114) | Y114: 广告单量 | Z114: =N114-B114 | AA114: =O114-C114 | AB114: =P114-D114 | AC114: =Q114-E114 | AD114: =R114-F114 | AE114: =S114-G114 | AF114: =T114-H114 | AG114: =SUM(Z114:AF114)
A115: CPC | B115: 3.8 | C115: 3.8 | D115: 3.8 | E115: 3.8 | F115: 3.8 | G115: 3.8 | H115: 3.8 | I115: =AVERAGE(B115:H115) | M115: CPC | N115: 3.8 | O115: 3.8 | P115: 3.8 | Q115: 3.8 | R115: 3.8 | S115: 3.8 | T115: 3.8 | U115: =AVERAGE(N115:T115) | Y115: CPC | Z115: =N115-B115 | AA115: =O115-C115 | AB115: =P115-D115 | AC115: =Q115-E115 | AD115: =R115-F115 | AE115: =S115-G115 | AF115: =T115-H115 | AG115: =AVERAGE(Z115:AF115)
...

Sheet SC推广计划拆解
A1: 第一阶段：0~14天 | C1: 阶段目标：打收录、等首评、找到流量入口后再放大广告 | J1: 推广计划根据库存量来定，不断货，不冗余
A2: ASIN | D2: 定价 | E2: US$139.00
A3: 终期流量目标 | B3: 160 | D3: 折扣 | E3: 30
A4: 终期日销目标 | B4: 8 | D4: 成交价 | E4: US$109.00
A5: CTR目标 | B5: 0.003 | D5: 利润额 | E5: US$28.43 | F5: 利润额扣除退货率，不扣除广告占比
A6: CVR目标 | B6: 0.05
A7: 广告单占比目标 | B7: 0.8
A8: 目标评论数 | B8: 5
A9: 划线价（30%）
A10: 刷单数量安排
A11: 站外目标出单
A12: 联盟目标出单
A14: （目标）第一阶段详细计划 Part1 | C14: 开售W1 | M14: 实际完成数据 | O14: 开售W1 | Y14: 完成差额 | AA14: 开售W1
A15: 数据预测 | B15: Day 1 | C15: Day 2 | D15: Day 3 | E15: Day 4 | F15: Day 5 | G15: Day 6 | H15: Day 7 | I15: 合计 | M15: 数据预测 | N15: Day 1 | O15: Day 2 | P15: Day 3 | Q15: Day 4 | R15: Day 5 | S15: Day 6 | T15: Day 7 | U15: 合计 | Y15: 数据预测 | Z15: Day 1 | AA15: Day 2 | AB15: Day 3 | AC15: Day 4 | AD15: Day 5 | AE15: Day 6 | AF15: Day 7 | AG15: 合计
A16: 目标总单量 | B16: 1 | C16: 2 | D16: 3 | E16: 4 | F16: 5 | G16: 5 | H16: 6 | I16: =SUM(B16:H16) | M16: 总单量 | N16: 12 | O16: 23 | P16: 26 | Q16: 25 | R16: 11 | S16: 52 | T16: 12 | U16: =SUM(N16:T16) | Y16: 总单量 | Z16: =N16-B16 | AA16: =O16-C16 | AB16: =P16-D16 | AC16: =Q16-E16 | AD16: =R16-F16 | AE16: =S16-G16 | AF16: =T16-H16 | AG16: =SUM(Z16:AF16)
A17: 总流量 | B17: =B16/B23 | C17: =C16/C23 | D17: =D16/D23 | E17: =E16/E23 | F17: =F16/F23 | G17: =G16/G23 | H17: =H16/H23 | I17: =SUM(B17:H17) | M17: 总流量 | N17: =N16/N23 | O17: =O16/O23 | P17: =P16/P23 | Q17: =Q16/Q23 | R17: =R16/R23 | S17: =S16/S23 | T17: =T16/T23 | U17: =SUM(N17:T17) | Y17: 总流量 | Z17: =N17-B17 | AA17: =O17-C17 | AB17: =P17-D17 | AC17: =Q17-E17 | AD17: =R17-F17 | AE17: =S17-G17 | AF17: =T17-H17 | AG17: =SUM(Z17:AF17)
A18: 广告单占比 | B18: 1 | C18: 1 | D18: 1 | E18: 1 | F18: 1 | G18: 0.9 | H18: 0.9 | I18: =I20/I16 | M18: 广告单占比 | N18: 1 | O18: 1 | P18: 1 | Q18: 1 | R18: 1 | S18: 0.9 | T18: 0.9 | U18: =U20/U16 | Y18: 广告单占比 | Z18: =N18-B18 | AA18: =O18-C18 | AB18: =P18-D18 | AC18: =Q18-E18 | AD18: =R18-F18 | AE18: =S18-G18 | AF18: =T18-H18 | AG18: =AG20/AG16
A19: 自然单量 | B19: =B16-B20 | C19: =C16-C20 | D19: =D16-D20 | E19: =E16-E20 | F19: =F16-F20 | G19: =G16-G20 | H19: =H16-H20 | I19: =SUM(B19:H19) | M19: 自然单量 | N19: 12 | O19: =O16-O20 | P19: =P16-P20 | Q19: =Q16-Q20 | R19: =R16-R20 | S19: =S16-S20 | T19: =T16-T20 | U19: =SUM(N19:T19) | Y19: 自然单量 | Z19: =N19-B19 | AA19: =O19-C19 | AB19: =P19-D19 | AC19: =Q19-E19 | AD19: =R19-F19 | AE19: =S19-G19 | AF19: =T19-H19 | AG19: =SUM(Z19:AF19)
A20: 广告单量 | B20: =B16*B18 | C20: =C16*C18 | D20: =D16*D18 | E20: =E16*E18 | F20: =F16*F18 | G20: =G16*G18 | H20: =H16*H18 | I20: =SUM(B20:H20) | M20: 广告单量 | N20: =N16*N18 | O20: =O16*O18 | P20: =P16*P18 | Q20: =Q16*Q18 | R20: =R16*R18 | S20: =S16*S18 | T20: =T16*T18 | U20: =SUM(N20:T20) | Y20: 广告单量 | Z20: =N20-B20 | AA20: =O20-C20 | AB20: =P20-D20 | AC20: =Q20-E20 | AD20: =R20-F20 | AE20: =S20-G20 | AF20: =T20-H20 | AG20: =SUM(Z20:AF20)
A21: CPC | B21: 3.8 | C21: 3.8 | D21: 3.8 | E21: 3.8 | F21: 3.8 | G21: 3.8 | H21: 3.8 | I21: =AVERAGE(B21:H21) | M21: CPC | N21: 3.8 | O21: 3.8 | P21: 3.8 | Q21: 3.8 | R21: 3.8 | S21: 3.8 | T21: 3.8 | U21: =AVERAGE(N21:T21) | Y21: CPC | Z21: =N21-B21 | AA21: =O21-C21 | AB21: =P21-D21 | AC21: =Q21-E21 | AD21: =R21-F21 | AE21: =S21-G21 | AF21: =T21-H21 | AG21: =AVERAGE(Z21:AF21)
A22: 点击率CTR | B22: 0.003 | C22: 0.003 | D22: 0.003 | E22: 0.003 | F22: 0.003 | G22: 0.003 | H22: 0.003 | I22: =AVERAGE(B22:H22) | M22: 点击率CTR | N22: 0.003 | O22: 0.003 | P22: 0.003 | Q22: 0.003 | R22: 0.003 | S22: 0.003 | T22: 0.003 | U22: =AVERAGE(N22:T22) | Y22: 点击率CTR | Z22: =N22-B22 | AA22: =O22-C22 | AB22: =P22-D22 | AC22: =Q22-E22 | AD22: =R22-F22 | AE22: =S22-G22 | AF22: =T22-H22 | AG22: =AVERAGE(Z22:AF22)
A23: 转化率CVR | B23: 0.04 | C23: 0.04 | D23: 0.04 | E23: 0.04 | F23: 0.04 | G23: 0.04 | H23: 0.04 | I23: =AVERAGE(B23:H23) | J23: 累计出单 | K23: =I16 | M23: 转化率CVR | N23: 0.04 | O23: 0.04 | P23: 0.04 | Q23: 0.04 | R23: 0.04 | S23: 0.04 | T23: 0.04 | U23: =AVERAGE(N23:T23) | V23: 累计出单 | W23: =U16 | Y23: 转化率CVR | Z23: =N23-B23 | AA23: =O23-C23 | AB23: =P23-D23 | AC23: =Q23-E23 | AD23: =R23-F23 | AE23: =S23-G23 | AF23: =T23-H23 | AG23: =AVERAGE(Z23:AF23) | AH23: 累计出单 | AI23: =AG16
A24: 广告点击量 | B24: =B20/B23 | C24: =C20/C23 | D24: =D20/D23 | E24: =E20/E23 | F24: =F20/F23 | G24: =G20/G23 | H24: =H20/H23 | I24: =SUM(B24:H24) | J24: 本周CPA | K24: =I25/I20 | M24: 广告点击量 | N24: =N20/N23 | O24: =O20/O23 | P24: =P20/P23 | Q24: =Q20/Q23 | R24: =R20/R23 | S24: =S20/S23 | T24: =T20/T23 | U24: =SUM(N24:T24) | V24: 本周CPA | W24: =U25/U20 | Y24: 广告点击量 | Z24: =N24-B24 | AA24: =O24-C24 | AB24: =P24-D24 | AC24: =Q24-E24 | AD24: =R24-F24 | AE24: =S24-G24 | AF24: =T24-H24 | AG24: =SUM(Z24:AF24) | AH24: 本周CPA | AI24: =AG25/AG20
A25: 广告花费 | B25: =B21*B24 | C25: =C21*C24 | D25: =D21*D24 | E25: =E21*E24 | F25: =F21*F24 | G25: =G21*G24 | H25: =H21*H24 | I25: =SUM(B25:H25) | J25: 本周广告占比 | K25: =I25/I28 | M25: 广告花费 | N25: =N21*N24 | O25: =O21*O24 | P25: =P21*P24 | Q25: =Q21*Q24 | R25: =R21*R24 | S25: =S21*S24 | T25: =T21*T24 | U25: =SUM(N25:T25) | V25: 本周广告占比 | W25: =U25/U28 | Y25: 广告花费 | Z25: =N25-B25 | AA25: =O25-C25 | AB25: =P25-D25 | AC25: =Q25-E25 | AD25: =R25-F25 | AE25: =S25-G25 | AF25: =T25-H25 | AG25: =SUM(Z25:AF25) | AH25: 本周广告占比 | AI25: =AG25/AG28
A26: 广告ACOS | B26: =B25/B27 | C26: =C25/C27 | D26: =D25/D27 | E26: =E25/E27 | F26: =F25/F27 | G26: =G25/G27 | H26: =H25/H27 | I26: =I25/I27 | M26: 广告ACOS | N26: =N25/N27 | O26: =O25/O27 | P26: =P25/P27 | Q26: =Q25/Q27 | R26: =R25/R27 | S26: =S25/S27 | T26: =T25/T27 | U26: =U25/U27 | Y26: 广告ACOS | Z26: =N26-B26 | AA26: =O26-C26 | AB26: =P26-D26 | AC26: =Q26-E26 | AD26: =R26-F26 | AE26: =S26-G26 | AF26: =T26-H26 | AG26: =AG25/AG27
A27: 广告销售额 | B27: =B20*$E$11 | C27: =C20*$E$11 | D27: =D20*$E$11 | E27: =E20*$E$11 | F27: =F20*$E$11 | G27: =G20*$E$11 | H27: =H20*$E$11 | I27: =SUM(B27:H27) | J27: 本周利润额 | K27: =I29 | M27: 广告销售额 | N27: =N20*$E$11 | O27: =O20*$E$11 | P27: =P20*$E$11 | Q27: =Q20*$E$11 | R27: =R20*$E$11 | S27: =S20*$E$11 | T27: =T20*$E$11 | U27: =SUM(N27:T27) | V27: 本周利润额 | W27: =U29 | Y27: 广告销售额 | Z27: =N27-B27 | AA27: =O27-C27 | AB27: =P27-D27 | AC27: =Q27-E27 | AD27: =R27-F27 | AE27: =S27-G27 | AF27: =T27-H27 | AG27: =SUM(Z27:AF27) | AH27: 本周利润额 | AI27: =AG29
A28: 总销售额 | B28: =B16*$E$11 | C28: =C16*$E$11 | D28: =D16*$E$11 | E28: =E16*$E$11 | F28: =F16*$E$11 | G28: =G16*$E$11 | H28: =H16*$E$11 | I28: =SUM(B28:H28) | J28: 本周利润率 | K28: =K27/I28 | M28: 总销售额 | N28: =N16*$E$11 | O28: =O16*$E$11 | P28: =P16*$E$11 | Q28: =Q16*$E$11 | R28: =R16*$E$11 | S28: =S16*$E$11 | T28: =T16*$E$11 | U28: =SUM(N28:T28) | V28: 本周利润率 | W28: =W27/U28 | Y28: 总销售额 | Z28: =N28-B28 | AA28: =O28-C28 | AB28: =P28-D28 | AC28: =Q28-E28 | AD28: =R28-F28 | AE28: =S28-G28 | AF28: =T28-H28 | AG28: =SUM(Z28:AF28) | AH28: 本周利润率 | AI28: =AI27/AG28
A29: 利润 | B29: =B16*$E$12-B25 | C29: =C16*$E$12-C25 | D29: =D16*$E$12-D25 | E29: =E16*$E$12-E25 | F29: =F16*$E$12-F25 | G29: =G16*$E$12-G25 | H29: =H16*$E$12-H25 | I29: =SUM(B29:H29) | J29: 结余利润额 | K29: =K27 | M29: 利润 | N29: =N16*$E$12-N25 | O29: =O16*$E$12-O25 | P29: =P16*$E$12-P25 | Q29: =Q16*$E$12-Q25 | R29: =R16*$E$12-R25 | S29: =S16*$E$12-S25 | T29: =T16*$E$12-T25 | U29: =SUM(N29:T29) | V29: 结余利润额 | W29: =W27 | Y29: 利润 | Z29: =N29-B29 | AA29: =O29-C29 | AB29: =P29-D29 | AC29: =Q29-E29 | AD29: =R29-F29 | AE29: =S29-G29 | AF29: =T29-H29 | AG29: =SUM(Z29:AF29) | AH29: 结余利润额 | AI29: =AI27
A30: 执行策略
A34: （目标）第一阶段详细计划 Part1 | C34: 开售W2 | M34: 实际完成数据 | O34: 开售W2 | Y34: 完成差额 | AA34: 开售W2
A35: 数据预测 | B35: Day 1 | C35: Day 2 | D35: Day 3 | E35: Day 4 | F35: Day 5 | G35: Day 6 | H35: Day 7 | I35: 合计 | M35: 数据预测 | N35: Day 1 | O35: Day 2 | P35: Day 3 | Q35: Day 4 | R35: Day 5 | S35: Day 6 | T35: Day 7 | U35: 合计 | Y35: 数据预测 | Z35: Day 1 | AA35: Day 2 | AB35: Day 3 | AC35: Day 4 | AD35: Day 5 | AE35: Day 6 | AF35: Day 7 | AG35: 合计
A36: 目标总单量 | B36: 1 | C36: 2 | D36: 3 | E36: 4 | F36: 5 | G36: 5 | H36: 6 | I36: =SUM(B36:H36) | M36: 总单量 | N36: 12 | O36: 23 | P36: 26 | Q36: 25 | R36: 11 | S36: 52 | T36: 12 | U36: =SUM(N36:T36) | Y36: 总单量 | Z36: =N36-B36 | AA36: =O36-C36 | AB36: =P36-D36 | AC36: =Q36-E36 | AD36: =R36-F36 | AE36: =S36-G36 | AF36: =T36-H36 | AG36: =SUM(Z36:AF36)
A37: 总流量 | B37: =B36/B43 | C37: =C36/C43 | D37: =D36/D43 | E37: =E36/E43 | F37: =F36/F43 | G37: =G36/G43 | H37: =H36/H43 | I37: =SUM(B37:H37) | M37: 总流量 | N37: =N36/N43 | O37: =O36/O43 | P37: =P36/P43 | Q37: =Q36/Q43 | R37: =R36/R43 | S37: =S36/S43 | T37: =T36/T43 | U37: =SUM(N37:T37) | Y37: 总流量 | Z37: =N37-B37 | AA37: =O37-C37 | AB37: =P37-D37 | AC37: =Q37-E37 | AD37: =R37-F37 | AE37: =S37-G37 | AF37: =T37-H37 | AG37: =SUM(Z37:AF37)
A38: 广告单占比 | B38: 1 | C38: 1 | D38: 1 | E38: 1 | F38: 1 | G38: 0.9 | H38: 0.9 | I38: =I40/I36 | M38: 广告单占比 | N38: 1 | O38: 1 | P38: 1 | Q38: 1 | R38: 1 | S38: 0.9 | T38: 0.9 | U38: =U40/U36 | Y38: 广告单占比 | Z38: =N38-B38 | AA38: =O38-C38 | AB38: =P38-D38 | AC38: =Q38-E38 | AD38: =R38-F38 | AE38: =S38-G38 | AF38: =T38-H38 | AG38: =AG40/AG36
A39: 自然单量 | B39: =B36-B40 | C39: =C36-C40 | D39: =D36-D40 | E39: =E36-E40 | F39: =F36-F40 | G39: =G36-G40 | H39: =H36-H40 | I39: =SUM(B39:H39) | M39: 自然单量 | N39: 12 | O39: =O36-O40 | P39: =P36-P40 | Q39: =Q36-Q40 | R39: =R36-R40 | S39: =S36-S40 | T39: =T36-T40 | U39: =SUM(N39:T39) | Y39: 自然单量 | Z39: =N39-B39 | AA39: =O39-C39 | AB39: =P39-D39 | AC39: =Q39-E39 | AD39: =R39-F39 | AE39: =S39-G39 | AF39: =T39-H39 | AG39: =SUM(Z39:AF39)
A40: 广告单量 | B40: =B36*B38 | C40: =C36*C38 | D40: =D36*D38 | E40: =E36*E38 | F40: =F36*F38 | G40: =G36*G38 | H40: =H36*H38 | I40: =SUM(B40:H40) | M40: 广告单量 | N40: =N36*N38 | O40: =O36*O38 | P40: =P36*P38 | Q40: =Q36*Q38 | R40: =R36*R38 | S40: =S36*S38 | T40: =T36*T38 | U40: =SUM(N40:T40) | Y40: 广告单量 | Z40: =N40-B40 | AA40: =O40-C40 | AB40: =P40-D40 | AC40: =Q40-E40 | AD40: =R40-F40 | AE40: =S40-G40 | AF40: =T40-H40 | AG40: =SUM(Z40:AF40)
A41: CPC | B41: 3.8 | C41: 3.8 | D41: 3.8 | E41: 3.8 | F41: 3.8 | G41: 3.8 | H41: 3.8 | I41: =AVERAGE(B41:H41) | M41: CPC | N41: 3.8 | O41: 3.8 | P41: 3.8 | Q41: 3.8 | R41: 3.8 | S41: 3.8 | T41: 3.8 | U41: =AVERAGE(N41:T41) | Y41: CPC | Z41: =N41-B41 | AA41: =O41-C41 | AB41: =P41-D41 | AC41: =Q41-E41 | AD41: =R41-F41 | AE41: =S41-G41 | AF41: =T41-H41 | AG41: =AVERAGE(Z41:AF41)
A42: 点击率CTR | B42: 0.003 | C42: 0.003 | D42: 0.003 | E42: 0.003 | F42: 0.003 | G42: 0.003 | H42: 0.003 | I42: =AVERAGE(B42:H42) | M42: 点击率CTR | N42: 0.003 | O42: 0.003 | P42: 0.003 | Q42: 0.003 | R42: 0.003 | S42: 0.003 | T42: 0.003 | U42: =AVERAGE(N42:T42) | Y42: 点击率CTR | Z42: =N42-B42 | AA42: =O42-C42 | AB42: =P42-D42 | AC42: =Q42-E42 | AD42: =R42-F42 | AE42: =S42-G42 | AF42: =T42-H42 | AG42: =AVERAGE(Z42:AF42)
A43: 转化率CVR | B43: 0.04 | C43: 0.04 | D43: 0.04 | E43: 0.04 | F43: 0.04 | G43: 0.04 | H43: 0.04 | I43: =AVERAGE(B43:H43) | J43: 累计出单 | K43: =I36 | M43: 转化率CVR | N43: 0.04 | O43: 0.04 | P43: 0.04 | Q43: 0.04 | R43: 0.04 | S43: 0.04 | T43: 0.04 | U43: =AVERAGE(N43:T43) | V43: 累计出单 | W43: =U36 | Y43: 转化率CVR | Z43: =N43-B43 | AA43: =O43-C43 | AB43: =P43-D43 | AC43: =Q43-E43 | AD43: =R43-F43 | AE43: =S43-G43 | AF43: =T43-H43 | AG43: =AVERAGE(Z43:AF43) | AH43: 累计出单 | AI43: =AG36
A44: 广告点击量 | B44: =B40/B43 | C44: =C40/C43 | D44: =D40/D43 | E44: =E40/E43 | F44: =F40/F43 | G44: =G40/G43 | H44: =H40/H43 | I44: =SUM(B44:H44) | J44: 本周CPA | K44: =I45/I40 | M44: 广告点击量 | N44: =N40/N43 | O44: =O40/O43 | P44: =P40/P43 | Q44: =Q40/Q43 | R44: =R40/R43 | S44: =S40/S43 | T44: =T40/T43 | U44: =SUM(N44:T44) | V44: 本周CPA | W44: =U45/U40 | Y44: 广告点击量 | Z44: =N44-B44 | AA44: =O44-C44 | AB44: =P44-D44 | AC44: =Q44-E44 | AD44: =R44-F44 | AE44: =S44-G44 | AF44: =T44-H44 | AG44: =SUM(Z44:AF44) | AH44: 本周CPA | AI44: =AG45/AG40
A45: 广告花费 | B45: =B41*B44 | C45: =C41*C44 | D45: =D41*D44 | E45: =E41*E44 | F45: =F41*F44 | G45: =G41*G44 | H45: =H41*H44 | I45: =SUM(B45:H45) | J45: 本周广告占比 | K45: =I45/I48 | M45: 广告花费 | N45: =N41*N44 | O45: =O41*O44 | P45: =P41*P44 | Q45: =Q41*Q44 | R45: =R41*R44 | S45: =S41*S44 | T45: =T41*T44 | U45: =SUM(N45:T45) | V45: 本周广告占比 | W45: =U45/U48 | Y45: 广告花费 | Z45: =N45-B45 | AA45: =O45-C45 | AB45: =P45-D45 | AC45: =Q45-E45 | AD45: =R45-F45 | AE45: =S45-G45 | AF45: =T45-H45 | AG45: =SUM(Z45:AF45) | AH45: 本周广告占比 | AI45: =AG45/AG48
A46: 广告ACOS | B46: =B45/B47 | C46: =C45/C47 | D46: =D45/D47 | E46: =E45/E47 | F46: =F45/F47 | G46: =G45/G47 | H46: =H45/H47 | I46: =I45/I47 | M46: 广告ACOS | N46: =N45/N47 | O46: =O45/O47 | P46: =P45/P47 | Q46: =Q45/Q47 | R46: =R45/R47 | S46: =S45/S47 | T46: =T45/T47 | U46: =U45/U47 | Y46: 广告ACOS | Z46: =N46-B46 | AA46: =O46-C46 | AB46: =P46-D46 | AC46: =Q46-E46 | AD46: =R46-F46 | AE46: =S46-G46 | AF46: =T46-H46 | AG46: =AG45/AG47
A47: 广告销售额 | B47: =B40*$E$11 | C47: =C40*$E$11 | D47: =D40*$E$11 | E47: =E40*$E$11 | F47: =F40*$E$11 | G47: =G40*$E$11 | H47: =H40*$E$11 | I47: =SUM(B47:H47) | J47: 本周利润额 | K47: =I49 | M47: 广告销售额 | N47: =N40*$E$11 | O47: =O40*$E$11 | P47: =P40*$E$11 | Q47: =Q40*$E$11 | R47: =R40*$E$11 | S47: =S40*$E$11 | T47: =T40*$E$11 | U47: =SUM(N47:T47) | V47: 本周利润额 | W47: =U49 | Y47: 广告销售额 | Z47: =N47-B47 | AA47: =O47-C47 | AB47: =P47-D47 | AC47: =Q47-E47 | AD47: =R47-F47 | AE47: =S47-G47 | AF47: =T47-H47 | AG47: =SUM(Z47:AF47) | AH47: 本周利润额 | AI47: =AG49
A48: 总销售额 | B48: =B36*$E$11 | C48: =C36*$E$11 | D48: =D36*$E$11 | E48: =E36*$E$11 | F48: =F36*$E$11 | G48: =G36*$E$11 | H48: =H36*$E$11 | I48: =SUM(B48:H48) | J48: 本周利润率 | K48: =K47/I48 | M48: 总销售额 | N48: =N36*$E$11 | O48: =O36*$E$11 | P48: =P36*$E$11 | Q48: =Q36*$E$11 | R48: =R36*$E$11 | S48: =S36*$E$11 | T48: =T36*$E$11 | U48: =SUM(N48:T48) | V48: 本周利润率 | W48: =W47/U48 | Y48: 总销售额 | Z48: =N48-B48 | AA48: =O48-C48 | AB48: =P48-D48 | AC48: =Q48-E48 | AD48: =R48-F48 | AE48: =S48-G48 | AF48: =T48-H48 | AG48: =SUM(Z48:AF48) | AH48: 本周利润率 | AI48: =AI47/AG48
A49: 利润 | B49: =B36*$E$12-B45 | C49: =C36*$E$12-C45 | D49: =D36*$E$12-D45 | E49: =E36*$E$12-E45 | F49: =F36*$E$12-F45 | G49: =G36*$E$12-G45 | H49: =H36*$E$12-H45 | I49: =SUM(B49:H49) | J49: 结余利润额 | K49: =K47 | M49: 利润 | N49: =N36*$E$12-N45 | O49: =O36*$E$12-O45 | P49: =P36*$E$12-P45 | Q49: =Q36*$E$12-Q45 | R49: =R36*$E$12-R45 | S49: =S36*$E$12-S45 | T49: =T36*$E$12-T45 | U49: =SUM(N49:T49) | V49: 结余利润额 | W49: =W47 | Y49: 利润 | Z49: =N49-B49 | AA49: =O49-C49 | AB49: =P49-D49 | AC49: =Q49-E49 | AD49: =R49-F49 | AE49: =S49-G49 | AF49: =T49-H49 | AG49: =SUM(Z49:AF49) | AH49: 结余利润额 | AI49: =AI47
A50: 执行策略
A54: 第二阶段：15~45天 | C54: 阶段目标：5个以上评论基础，冲大词自然位首页，扩词提升单量
A55: ASIN | D55: 定价 | E55: US$139.00
A56: 终期流量目标 | B56: 333 | D56: 折扣 | E56: 30
A57: 终期日销目标 | B57: 20 | D57: 成交价 | E57: US$109.00
A58: CTR目标 | B58: 0.004 | D58: 利润额 | E58: US$28.43 | F58: 利润额扣除退货率，不扣除广告占比
A59: CVR目标 | B59: 0.06
A60: 广告单占比目标 | B60: 0.6
A61: 目标评论数 | B61: 30
A63: （目标）第二阶段详细计划 Part1 | C63: 开售W3 | M63: 实际完成数据 | O63: 开售W3 | Y63: 完成差额 | AA63: 开售W3
A64: 数据预测 | B64: Day 1 | C64: Day 2 | D64: Day 3 | E64: Day 4 | F64: Day 5 | G64: Day 6 | H64: Day 7 | I64: 合计 | M64: 数据预测 | N64: Day 1 | O64: Day 2 | P64: Day 3 | Q64: Day 4 | R64: Day 5 | S64: Day 6 | T64: Day 7 | U64: 合计 | Y64: 数据预测 | Z64: Day 1 | AA64: Day 2 | AB64: Day 3 | AC64: Day 4 | AD64: Day 5 | AE64: Day 6 | AF64: Day 7 | AG64: 合计
A65: 目标总单量 | B65: 1 | C65: 2 | D65: 3 | E65: 4 | F65: 5 | G65: 5 | H65: 6 | I65: =SUM(B65:H65) | M65: 总单量 | N65: 12 | O65: 23 | P65: 26 | Q65: 25 | R65: 11 | S65: 52 | T65: 12 | U65: =SUM(N65:T65) | Y65: 总单量 | Z65: =N65-B65 | AA65: =O65-C65 | AB65: =P65-D65 | AC65: =Q65-E65 | AD65: =R65-F65 | AE65: =S65-G65 | AF65: =T65-H65 | AG65: =SUM(Z65:AF65)
A66: 总流量 | B66: =B65/B72 | C66: =C65/C72 | D66: =D65/D72 | E66: =E65/E72 | F66: =F65/F72 | G66: =G65/G72 | H66: =H65/H72 | I66: =SUM(B66:H66) | M66: 总流量 | N66: =N65/N72 | O66: =O65/O72 | P66: =P65/P72 | Q66: =Q65/Q72 | R66: =R65/R72 | S66: =S65/S72 | T66: =T65/T72 | U66: =SUM(N66:T66) | Y66: 总流量 | Z66: =N66-B66 | AA66: =O66-C66 | AB66: =P66-D66 | AC66: =Q66-E66 | AD66: =R66-F66 | AE66: =S66-G66 | AF66: =T66-H66 | AG66: =SUM(Z66:AF66)
A67: 广告单占比 | B67: 1 | C67: 1 | D67: 1 | E67: 1 | F67: 1 | G67: 0.9 | H67: 0.9 | I67: =I69/I65 | M67: 广告单占比 | N67: 1 | O67: 1 | P67: 1 | Q67: 1 | R67: 1 | S67: 0.9 | T67: 0.9 | U67: =U69/U65 | Y67: 广告单占比 | Z67: =N67-B67 | AA67: =O67-C67 | AB67: =P67-D67 | AC67: =Q67-E67 | AD67: =R67-F67 | AE67: =S67-G67 | AF67: =T67-H67 | AG67: =AG69/AG65
A68: 自然单量 | B68: =B65-B69 | C68: =C65-C69 | D68: =D65-D69 | E68: =E65-E69 | F68: =F65-F69 | G68: =G65-G69 | H68: =H65-H69 | I68: =SUM(B68:H68) | M68: 自然单量 | N68: 12 | O68: =O65-O69 | P68: =P65-P69 | Q68: =Q65-Q69 | R68: =R65-R69 | S68: =S65-S69 | T68: =T65-T69 | U68: =SUM(N68:T68) | Y68: 自然单量 | Z68: =N68-B68 | AA68: =O68-C68 | AB68: =P68-D68 | AC68: =Q68-E68 | AD68: =R68-F68 | AE68: =S68-G68 | AF68: =T68-H68 | AG68: =SUM(Z68:AF68)
A69: 广告单量 | B69: =B65*B67 | C69: =C65*C67 | D69: =D65*D67 | E69: =E65*E67 | F69: =F65*F67 | G69: =G65*G67 | H69: =H65*H67 | I69: =SUM(B69:H69) | M69: 广告单量 | N69: =N65*N67 | O69: =O65*O67 | P69: =P65*P67 | Q69: =Q65*Q67 | R69: =R65*R67 | S69: =S65*S67 | T69: =T65*T67 | U69: =SUM(N69:T69) | Y69: 广告单量 | Z69: =N69-B69 | AA69: =O69-C69 | AB69: =P69-D69 | AC69: =Q69-E69 | AD69: =R69-F69 | AE69: =S69-G69 | AF69: =T69-H69 | AG69: =SUM(Z69:AF69)
A70: CPC | B70: 3.8 | C70: 3.8 | D70: 3.8 | E70: 3.8 | F70: 3.8 | G70: 3.8 | H70: 3.8 | I70: =AVERAGE(B70:H70) | M70: CPC | N70: 3.8 | O70: 3.8 | P70: 3.8 | Q70: 3.8 | R70: 3.8 | S70: 3.8 | T70: 3.8 | U70: =AVERAGE(N70:T70) | Y70: CPC | Z70: =N70-B70 | AA70: =O70-C70 | AB70: =P70-D70 | AC70: =Q70-E70 | AD70: =R70-F70 | AE70: =S70-G70 | AF70: =T70-H70 | AG70: =AVERAGE(Z70:AF70)
A71: 点击率CTR | B71: 0.003 | C71: 0.003 | D71: 0.003 | E71: 0.003 | F71: 0.003 | G71: 0.003 | H71: 0.003 | I71: =AVERAGE(B71:H71) | M71: 点击率CTR | N71: 0.003 | O71: 0.003 | P71: 0.003 | Q71: 0.003 | R71: 0.003 | S71: 0.003 | T71: 0.003 | U71: =AVERAGE(N71:T71) | Y71: 点击率CTR | Z71: =N71-B71 | AA71: =O71-C71 | AB71: =P71-D71 | AC71: =Q71-E71 | AD71: =R71-F71 | AE71: =S71-G71 | AF71: =T71-H71 | AG71: =AVERAGE(Z71:AF71)
A72: 转化率CVR | B72: 0.04 | C72: 0.04 | D72: 0.04 | E72: 0.04 | F72: 0.04 | G72: 0.04 | H72: 0.04 | I72: =AVERAGE(B72:H72) | J72: 累计出单 | K72: =I65 | M72: 转化率CVR | N72: 0.04 | O72: 0.04 | P72: 0.04 | Q72: 0.04 | R72: 0.04 | S72: 0.04 | T72: 0.04 | U72: =AVERAGE(N72:T72) | V72: 累计出单 | W72: =U65 | Y72: 转化率CVR | Z72: =N72-B72 | AA72: =O72-C72 | AB72: =P72-D72 | AC72: =Q72-E72 | AD72: =R72-F72 | AE72: =S72-G72 | AF72: =T72-H72 | AG72: =AVERAGE(Z72:AF72) | AH72: 累计出单 | AI72: =AG65
A73: 广告点击量 | B73: =B69/B72 | C73: =C69/C72 | D73: =D69/D72 | E73: =E69/E72 | F73: =F69/F72 | G73: =G69/G72 | H73: =H69/H72 | I73: =SUM(B73:H73) | J73: 本周CPA | K73: =I74/I69 | M73: 广告点击量 | N73: =N69/N72 | O73: =O69/O72 | P73: =P69/P72 | Q73: =Q69/Q72 | R73: =R69/R72 | S73: =S69/S72 | T73: =T69/T72 | U73: =SUM(N73:T73) | V73: 本周CPA | W73: =U74/U69 | Y73: 广告点击量 | Z73: =N73-B73 | AA73: =O73-C73 | AB73: =P73-D73 | AC73: =Q73-E73 | AD73: =R73-F73 | AE73: =S73-G73 | AF73: =T73-H73 | AG73: =SUM(Z73:AF73) | AH73: 本周CPA | AI73: =AG74/AG69
A74: 广告花费 | B74: =B70*B73 | C74: =C70*C73 | D74: =D70*D73 | E74: =E70*E73 | F74: =F70*F73 | G74: =G70*G73 | H74: =H70*H73 | I74: =SUM(B74:H74) | J74: 本周广告占比 | K74: =I74/I77 | M74: 广告花费 | N74: =N70*N73 | O74: =O70*O73 | P74: =P70*P73 | Q74: =Q70*Q73 | R74: =R70*R73 | S74: =S70*S73 | T74: =T70*T73 | U74: =SUM(N74:T74) | V74: 本周广告占比 | W74: =U74/U77 | Y74: 广告花费 | Z74: =N74-B74 | AA74: =O74-C74 | AB74: =P74-D74 | AC74: =Q74-E74 | AD74: =R74-F74 | AE74: =S74-G74 | AF74: =T74-H74 | AG74: =SUM(Z74:AF74) | AH74: 本周广告占比 | AI74: =AG74/AG77
A75: 广告ACOS | B75: =B74/B76 | C75: =C74/C76 | D75: =D74/D76 | E75: =E74/E76 | F75: =F74/F76 | G75: =G74/G76 | H75: =H74/H76 | I75: =I74/I76 | M75: 广告ACOS | N75: =N74/N76 | O75: =O74/O76 | P75: =P74/P76 | Q75: =Q74/Q76 | R75: =R74/R76 | S75: =S74/S76 | T75: =T74/T76 | U75: =U74/U76 | Y75: 广告ACOS | Z75: =N75-B75 | AA75: =O75-C75 | AB75: =P75-D75 | AC75: =Q75-E75 | AD75: =R75-F75 | AE75: =S75-G75 | AF75: =T75-H75 | AG75: =AG74/AG76
A76: 广告销售额 | B76: =B69*$E$11 | C76: =C69*$E$11 | D76: =D69*$E$11 | E76: =E69*$E$11 | F76: =F69*$E$11 | G76: =G69*$E$11 | H76: =H69*$E$11 | I76: =SUM(B76:H76) | J76: 本周利润额 | K76: =I78 | M76: 广告销售额 | N76: =N69*$E$11 | O76: =O69*$E$11 | P76: =P69*$E$11 | Q76: =Q69*$E$11 | R76: =R69*$E$11 | S76: =S69*$E$11 | T76: =T69*$E$11 | U76: =SUM(N76:T76) | V76: 本周利润额 | W76: =U78 | Y76: 广告销售额 | Z76: =N76-B76 | AA76: =O76-C76 | AB76: =P76-D76 | AC76: =Q76-E76 | AD76: =R76-F76 | AE76: =S76-G76 | AF76: =T76-H76 | AG76: =SUM(Z76:AF76) | AH76: 本周利润额 | AI76: =AG78
A77: 总销售额 | B77: =B65*$E$11 | C77: =C65*$E$11 | D77: =D65*$E$11 | E77: =E65*$E$11 | F77: =F65*$E$11 | G77: =G65*$E$11 | H77: =H65*$E$11 | I77: =SUM(B77:H77) | J77: 本周利润率 | K77: =K76/I77 | M77: 总销售额 | N77: =N65*$E$11 | O77: =O65*$E$11 | P77: =P65*$E$11 | Q77: =Q65*$E$11 | R77: =R65*$E$11 | S77: =S65*$E$11 | T77: =T65*$E$11 | U77: =SUM(N77:T77) | V77: 本周利润率 | W77: =W76/U77 | Y77: 总销售额 | Z77: =N77-B77 | AA77: =O77-C77 | AB77: =P77-D77 | AC77: =Q77-E77 | AD77: =R77-F77 | AE77: =S77-G77 | AF77: =T77-H77 | AG77: =SUM(Z77:AF77) | AH77: 本周利润率 | AI77: =AI76/AG77
A78: 利润 | B78: =B65*$E$12-B74 | C78: =C65*$E$12-C74 | D78: =D65*$E$12-D74 | E78: =E65*$E$12-E74 | F78: =F65*$E$12-F74 | G78: =G65*$E$12-G74 | H78: =H65*$E$12-H74 | I78: =SUM(B78:H78) | J78: 结余利润额 | K78: =K76 | M78: 利润 | N78: =N65*$E$12-N74 | O78: =O65*$E$12-O74 | P78: =P65*$E$12-P74 | Q78: =Q65*$E$12-Q74 | R78: =R65*$E$12-R74 | S78: =S65*$E$12-S74 | T78: =T65*$E$12-T74 | U78: =SUM(N78:T78) | V78: 结余利润额 | W78: =W76 | Y78: 利润 | Z78: =N78-B78 | AA78: =O78-C78 | AB78: =P78-D78 | AC78: =Q78-E78 | AD78: =R78-F78 | AE78: =S78-G78 | AF78: =T78-H78 | AG78: =SUM(Z78:AF78) | AH78: 结余利润额 | AI78: =AI76
A79: 执行策略
A83: （目标）第二阶段详细计划 Part2 | C83: 开售W4 | M83: 实际完成数据 | O83: 开售W4 | Y83: 完成差额 | AA83: 开售W4
A84: 数据预测 | B84: Day 1 | C84: Day 2 | D84: Day 3 | E84: Day 4 | F84: Day 5 | G84: Day 6 | H84: Day 7 | I84: 合计 | M84: 数据预测 | N84: Day 1 | O84: Day 2 | P84: Day 3 | Q84: Day 4 | R84: Day 5 | S84: Day 6 | T84: Day 7 | U84: 合计 | Y84: 数据预测 | Z84: Day 1 | AA84: Day 2 | AB84: Day 3 | AC84: Day 4 | AD84: Day 5 | AE84: Day 6 | AF84: Day 7 | AG84: 合计
A85: 目标总单量 | B85: 1 | C85: 2 | D85: 3 | E85: 4 | F85: 5 | G85: 5 | H85: 6 | I85: =SUM(B85:H85) | M85: 总单量 | N85: 12 | O85: 23 | P85: 26 | Q85: 25 | R85: 11 | S85: 52 | T85: 12 | U85: =SUM(N85:T85) | Y85: 总单量 | Z85: =N85-B85 | AA85: =O85-C85 | AB85: =P85-D85 | AC85: =Q85-E85 | AD85: =R85-F85 | AE85: =S85-G85 | AF85: =T85-H85 | AG85: =SUM(Z85:AF85)
A86: 总流量 | B86: =B85/B92 | C86: =C85/C92 | D86: =D85/D92 | E86: =E85/E92 | F86: =F85/F92 | G86: =G85/G92 | H86: =H85/H92 | I86: =SUM(B86:H86) | M86: 总流量 | N86: =N85/N92 | O86: =O85/O92 | P86: =P85/P92 | Q86: =Q85/Q92 | R86: =R85/R92 | S86: =S85/S92 | T86: =T85/T92 | U86: =SUM(N86:T86) | Y86: 总流量 | Z86: =N86-B86 | AA86: =O86-C86 | AB86: =P86-D86 | AC86: =Q86-E86 | AD86: =R86-F86 | AE86: =S86-G86 | AF86: =T86-H86 | AG86: =SUM(Z86:AF86)
A87: 广告单占比 | B87: 1 | C87: 1 | D87: 1 | E87: 1 | F87: 1 | G87: 0.9 | H87: 0.9 | I87: =I89/I85 | M87: 广告单占比 | N87: 1 | O87: 1 | P87: 1 | Q87: 1 | R87: 1 | S87: 0.9 | T87: 0.9 | U87: =U89/U85 | Y87: 广告单占比 | Z87: =N87-B87 | AA87: =O87-C87 | AB87: =P87-D87 | AC87: =Q87-E87 | AD87: =R87-F87 | AE87: =S87-G87 | AF87: =T87-H87 | AG87: =AG89/AG85
A88: 自然单量 | B88: =B85-B89 | C88: =C85-C89 | D88: =D85-D89 | E88: =E85-E89 | F88: =F85-F89 | G88: =G85-G89 | H88: =H85-H89 | I88: =SUM(B88:H88) | M88: 自然单量 | N88: 12 | O88: =O85-O89 | P88: =P85-P89 | Q88: =Q85-Q89 | R88: =R85-R89 | S88: =S85-S89 | T88: =T85-T89 | U88: =SUM(N88:T88) | Y88: 自然单量 | Z88: =N88-B88 | AA88: =O88-C88 | AB88: =P88-D88 | AC88: =Q88-E88 | AD88: =R88-F88 | AE88: =S88-G88 | AF88: =T88-H88 | AG88: =SUM(Z88:AF88)
A89: 广告单量 | B89: =B85*B87 | C89: =C85*C87 | D89: =D85*D87 | E89: =E85*E87 | F89: =F85*F87 | G89: =G85*G87 | H89: =H85*H87 | I89: =SUM(B89:H89) | M89: 广告单量 | N89: =N85*N87 | O89: =O85*O87 | P89: =P85*P87 | Q89: =Q85*Q87 | R89: =R85*R87 | S89: =S85*S87 | T89: =T85*T87 | U89: =SUM(N89:T89) | Y89: 广告单量 | Z89: =N89-B89 | AA89: =O89-C89 | AB89: =P89-D89 | AC89: =Q89-E89 | AD89: =R89-F89 | AE89: =S89-G89 | AF89: =T89-H89 | AG89: =SUM(Z89:AF89)
A90: CPC | B90: 3.8 | C90: 3.8 | D90: 3.8 | E90: 3.8 | F90: 3.8 | G90: 3.8 | H90: 3.8 | I90: =AVERAGE(B90:H90) | M90: CPC | N90: 3.8 | O90: 3.8 | P90: 3.8 | Q90: 3.8 | R90: 3.8 | S90: 3.8 | T90: 3.8 | U90: =AVERAGE(N90:T90) | Y90: CPC | Z90: =N90-B90 | AA90: =O90-C90 | AB90: =P90-D90 | AC90: =Q90-E90 | AD90: =R90-F90 | AE90: =S90-G90 | AF90: =T90-H90 | AG90: =AVERAGE(Z90:AF90)
A91: 点击率CTR | B91: 0.003 | C91: 0.003 | D91: 0.003 | E91: 0.003 | F91: 0.003 | G91: 0.003 | H91: 0.003 | I91: =AVERAGE(B91:H91) | M91: 点击率CTR | N91: 0.003 | O91: 0.003 | P91: 0.003 | Q91: 0.003 | R91: 0.003 | S91: 0.003 | T91: 0.003 | U91: =AVERAGE(N91:T91) | Y91: 点击率CTR | Z91: =N91-B91 | AA91: =O91-C91 | AB91: =P91-D91 | AC91: =Q91-E91 | AD91: =R91-F91 | AE91: =S91-G91 | AF91: =T91-H91 | AG91: =AVERAGE(Z91:AF91)
A92: 转化率CVR | B92: 0.04 | C92: 0.04 | D92: 0.04 | E92: 0.04 | F92: 0.04 | G92: 0.04 | H92: 0.04 | I92: =AVERAGE(B92:H92) | J92: 累计出单 | K92: =I85 | M92: 转化率CVR | N92: 0.04 | O92: 0.04 | P92: 0.04 | Q92: 0.04 | R92: 0.04 | S92: 0.04 | T92: 0.04 | U92: =AVERAGE(N92:T92) | V92: 累计出单 | W92: =U85 | Y92: 转化率CVR | Z92: =N92-B92 | AA92: =O92-C92 | AB92: =P92-D92 | AC92: =Q92-E92 | AD92: =R92-F92 | AE92: =S92-G92 | AF92: =T92-H92 | AG92: =AVERAGE(Z92:AF92) | AH92: 累计出单 | AI92: =AG85
A93: 广告点击量 | B93: =B89/B92 | C93: =C89/C92 | D93: =D89/D92 | E93: =E89/E92 | F93: =F89/F92 | G93: =G89/G92 | H93: =H89/H92 | I93: =SUM(B93:H93) | J93: 本周CPA | K93: =I94/I89 | M93: 广告点击量 | N93: =N89/N92 | O93: =O89/O92 | P93: =P89/P92 | Q93: =Q89/Q92 | R93: =R89/R92 | S93: =S89/S92 | T93: =T89/T92 | U93: =SUM(N93:T93) | V93: 本周CPA | W93: =U94/U89 | Y93: 广告点击量 | Z93: =N93-B93 | AA93: =O93-C93 | AB93: =P93-D93 | AC93: =Q93-E93 | AD93: =R93-F93 | AE93: =S93-G93 | AF93: =T93-H93 | AG93: =SUM(Z93:AF93) | AH93: 本周CPA | AI93: =AG94/AG89
A94: 广告花费 | B94: =B90*B93 | C94: =C90*C93 | D94: =D90*D93 | E94: =E90*E93 | F94: =F90*F93 | G94: =G90*G93 | H94: =H90*H93 | I94: =SUM(B94:H94) | J94: 本周广告占比 | K94: =I94/I97 | M94: 广告花费 | N94: =N90*N93 | O94: =O90*O93 | P94: =P90*P93 | Q94: =Q90*Q93 | R94: =R90*R93 | S94: =S90*S93 | T94: =T90*T93 | U94: =SUM(N94:T94) | V94: 本周广告占比 | W94: =U94/U97 | Y94: 广告花费 | Z94: =N94-B94 | AA94: =O94-C94 | AB94: =P94-D94 | AC94: =Q94-E94 | AD94: =R94-F94 | AE94: =S94-G94 | AF94: =T94-H94 | AG94: =SUM(Z94:AF94) | AH94: 本周广告占比 | AI94: =AG94/AG97
A95: 广告ACOS | B95: =B94/B96 | C95: =C94/C96 | D95: =D94/D96 | E95: =E94/E96 | F95: =F94/F96 | G95: =G94/G96 | H95: =H94/H96 | I95: =I94/I96 | M95: 广告ACOS | N95: =N94/N96 | O95: =O94/O96 | P95: =P94/P96 | Q95: =Q94/Q96 | R95: =R94/R96 | S95: =S94/S96 | T95: =T94/T96 | U95: =U94/U96 | Y95: 广告ACOS | Z95: =N95-B95 | AA95: =O95-C95 | AB95: =P95-D95 | AC95: =Q95-E95 | AD95: =R95-F95 | AE95: =S95-G95 | AF95: =T95-H95 | AG95: =AG94/AG96
A96: 广告销售额 | B96: =B89*$E$11 | C96: =C89*$E$11 | D96: =D89*$E$11 | E96: =E89*$E$11 | F96: =F89*$E$11 | G96: =G89*$E$11 | H96: =H89*$E$11 | I96: =SUM(B96:H96) | J96: 本周利润额 | K96: =I98 | M96: 广告销售额 | N96: =N89*$E$11 | O96: =O89*$E$11 | P96: =P89*$E$11 | Q96: =Q89*$E$11 | R96: =R89*$E$11 | S96: =S89*$E$11 | T96: =T89*$E$11 | U96: =SUM(N96:T96) | V96: 本周利润额 | W96: =U98 | Y96: 广告销售额 | Z96: =N96-B96 | AA96: =O96-C96 | AB96: =P96-D96 | AC96: =Q96-E96 | AD96: =R96-F96 | AE96: =S96-G96 | AF96: =T96-H96 | AG96: =SUM(Z96:AF96) | AH96: 本周利润额 | AI96: =AG98
A97: 总销售额 | B97: =B85*$E$11 | C97: =C85*$E$11 | D97: =D85*$E$11 | E97: =E85*$E$11 | F97: =F85*$E$11 | G97: =G85*$E$11 | H97: =H85*$E$11 | I97: =SUM(B97:H97) | J97: 本周利润率 | K97: =K96/I97 | M97: 总销售额 | N97: =N85*$E$11 | O97: =O85*$E$11 | P97: =P85*$E$11 | Q97: =Q85*$E$11 | R97: =R85*$E$11 | S97: =S85*$E$11 | T97: =T85*$E$11 | U97: =SUM(N97:T97) | V97: 本周利润率 | W97: =W96/U97 | Y97: 总销售额 | Z97: =N97-B97 | AA97: =O97-C97 | AB97: =P97-D97 | AC97: =Q97-E97 | AD97: =R97-F97 | AE97: =S97-G97 | AF97: =T97-H97 | AG97: =SUM(Z97:AF97) | AH97: 本周利润率 | AI97: =AI96/AG97
A98: 利润 | B98: =B85*$E$12-B94 | C98: =C85*$E$12-C94 | D98: =D85*$E$12-D94 | E98: =E85*$E$12-E94 | F98: =F85*$E$12-F94 | G98: =G85*$E$12-G94 | H98: =H85*$E$12-H94 | I98: =SUM(B98:H98) | J98: 结余利润额 | K98: =K96 | M98: 利润 | N98: =N85*$E$12-N94 | O98: =O85*$E$12-O94 | P98: =P85*$E$12-P94 | Q98: =Q85*$E$12-Q94 | R98: =R85*$E$12-R94 | S98: =S85*$E$12-S94 | T98: =T85*$E$12-T94 | U98: =SUM(N98:T98) | V98: 结余利润额 | W98: =W96 | Y98: 利润 | Z98: =N98-B98 | AA98: =O98-C98 | AB98: =P98-D98 | AC98: =Q98-E98 | AD98: =R98-F98 | AE98: =S98-G98 | AF98: =T98-H98 | AG98: =SUM(Z98:AF98) | AH98: 结余利润额 | AI98: =AI96
A99: 执行策略
A103: （目标）第二阶段详细计划 Part3 | C103: 开售W5 | M103: 实际完成数据 | O103: 开售W5 | Y103: 完成差额 | AA103: 开售W5
A104: 数据预测 | B104: Day 1 | C104: Day 2 | D104: Day 3 | E104: Day 4 | F104: Day 5 | G104: Day 6 | H104: Day 7 | I104: 合计 | M104: 数据预测 | N104: Day 1 | O104: Day 2 | P104: Day 3 | Q104: Day 4 | R104: Day 5 | S104: Day 6 | T104: Day 7 | U104: 合计 | Y104: 数据预测 | Z104: Day 1 | AA104: Day 2 | AB104: Day 3 | AC104: Day 4 | AD104: Day 5 | AE104: Day 6 | AF104: Day 7 | AG104: 合计
A105: 目标总单量 | B105: 1 | C105: 2 | D105: 3 | E105: 4 | F105: 5 | G105: 5 | H105: 6 | I105: =SUM(B105:H105) | M105: 总单量 | N105: 12 | O105: 23 | P105: 26 | Q105: 25 | R105: 11 | S105: 52 | T105: 12 | U105: =SUM(N105:T105) | Y105: 总单量 | Z105: =N105-B105 | AA105: =O105-C105 | AB105: =P105-D105 | AC105: =Q105-E105 | AD105: =R105-F105 | AE105: =S105-G105 | AF105: =T105-H105 | AG105: =SUM(Z105:AF105)
A106: 总流量 | B106: =B105/B112 | C106: =C105/C112 | D106: =D105/D112 | E106: =E105/E112 | F106: =F105/F112 | G106: =G105/G112 | H106: =H105/H112 | I106: =SUM(B106:H106) | M106: 总流量 | N106: =N105/N112 | O106: =O105/O112 | P106: =P105/P112 | Q106: =Q105/Q112 | R106: =R105/R112 | S106: =S105/S112 | T106: =T105/T112 | U106: =SUM(N106:T106) | Y106: 总流量 | Z106: =N106-B106 | AA106: =O106-C106 | AB106: =P106-D106 | AC106: =Q106-E106 | AD106: =R106-F106 | AE106: =S106-G106 | AF106: =T106-H106 | AG106: =SUM(Z106:AF106)
A107: 广告单占比 | B107: 1 | C107: 1 | D107: 1 | E107: 1 | F107: 1 | G107: 0.9 | H107: 0.9 | I107: =I109/I105 | M107: 广告单占比 | N107: 1 | O107: 1 | P107: 1 | Q107: 1 | R107: 1 | S107: 0.9 | T107: 0.9 | U107: =U109/U105 | Y107: 广告单占比 | Z107: =N107-B107 | AA107: =O107-C107 | AB107: =P107-D107 | AC107: =Q107-E107 | AD107: =R107-F107 | AE107: =S107-G107 | AF107: =T107-H107 | AG107: =AG109/AG105
A108: 自然单量 | B108: =B105-B109 | C108: =C105-C109 | D108: =D105-D109 | E108: =E105-E109 | F108: =F105-F109 | G108: =G105-G109 | H108: =H105-H109 | I108: =SUM(B108:H108) | M108: 自然单量 | N108: 12 | O108: =O105-O109 | P108: =P105-P109 | Q108: =Q105-Q109 | R108: =R105-R109 | S108: =S105-S109 | T108: =T105-T109 | U108: =SUM(N108:T108) | Y108: 自然单量 | Z108: =N108-B108 | AA108: =O108-C108 | AB108: =P108-D108 | AC108: =Q108-E108 | AD108: =R108-F108 | AE108: =S108-G108 | AF108: =T108-H108 | AG108: =SUM(Z108:AF108)
A109: 广告单量 | B109: =B105*B107 | C109: =C105*C107 | D109: =D105*D107 | E109: =E105*E107 | F109: =F105*F107 | G109: =G105*G107 | H109: =H105*H107 | I109: =SUM(B109:H109) | M109: 广告单量 | N109: =N105*N107 | O109: =O105*O107 | P109: =P105*P107 | Q109: =Q105*Q107 | R109: =R105*R107 | S109: =S105*S107 | T109: =T105*T107 | U109: =SUM(N109:T109) | Y109: 广告单量 | Z109: =N109-B109 | AA109: =O109-C109 | AB109: =P109-D109 | AC109: =Q109-E109 | AD109: =R109-F109 | AE109: =S109-G109 | AF109: =T109-H109 | AG109: =SUM(Z109:AF109)
A110: CPC | B110: 3.8 | C110: 3.8 | D110: 3.8 | E110: 3.8 | F110: 3.8 | G110: 3.8 | H110: 3.8 | I110: =AVERAGE(B110:H110) | M110: CPC | N110: 3.8 | O110: 3.8 | P110: 3.8 | Q110: 3.8 | R110: 3.8 | S110: 3.8 | T110: 3.8 | U110: =AVERAGE(N110:T110) | Y110: CPC | Z110: =N110-B110 | AA110: =O110-C110 | AB110: =P110-D110 | AC110: =Q110-E110 | AD110: =R110-F110 | AE110: =S110-G110 | AF110: =T110-H110 | AG110: =AVERAGE(Z110:AF110)
A111: 点击率CTR | B111: 0.003 | C111: 0.003 | D111: 0.003 | E111: 0.003 | F111: 0.003 | G111: 0.003 | H111: 0.003 | I111: =AVERAGE(B111:H111) | M111: 点击率CTR | N111: 0.003 | O111: 0.003 | P111: 0.003 | Q111: 0.003 | R111: 0.003 | S111: 0.003 | T111: 0.003 | U111: =AVERAGE(N111:T111) | Y111: 点击率CTR | Z111: =N111-B111 | AA111: =O111-C111 | AB111: =P111-D111 | AC111: =Q111-E111 | AD111: =R111-F111 | AE111: =S111-G111 | AF111: =T111-H111 | AG111: =AVERAGE(Z111:AF111)
A112: 转化率CVR | B112: 0.04 | C112: 0.04 | D112: 0.04 | E112: 0.04 | F112: 0.04 | G112: 0.04 | H112: 0.04 | I112: =AVERAGE(B112:H112) | J112: 累计出单 | K112: =I105 | M112: 转化率CVR | N112: 0.04 | O112: 0.04 | P112: 0.04 | Q112: 0.04 | R112: 0.04 | S112: 0.04 | T112: 0.04 | U112: =AVERAGE(N112:T112) | V112: 累计出单 | W112: =U105 | Y112: 转化率CVR | Z112: =N112-B112 | AA112: =O112-C112 | AB112: =P112-D112 | AC112: =Q112-E112 | AD112: =R112-F112 | AE112: =S112-G112 | AF112: =T112-H112 | AG112: =AVERAGE(Z112:AF112) | AH112: 累计出单 | AI112: =AG105
A113: 广告点击量 | B113: =B109/B112 | C113: =C109/C112 | D113: =D109/D112 | E113: =E109/E112 | F113: =F109/F112 | G113: =G109/G112 | H113: =H109/H112 | I113: =SUM(B113:H113) | J113: 本周CPA | K113: =I114/I109 | M113: 广告点击量 | N113: =N109/N112 | O113: =O109/O112 | P113: =P109/P112 | Q113: =Q109/Q112 | R113: =R109/R112 | S113: =S109/S112 | T113: =T109/T112 | U113: =SUM(N113:T113) | V113: 本周CPA | W113: =U114/U109 | Y113: 广告点击量 | Z113: =N113-B113 | AA113: =O113-C113 | AB113: =P113-D113 | AC113: =Q113-E113 | AD113: =R113-F113 | AE113: =S113-G113 | AF113: =T113-H113 | AG113: =SUM(Z113:AF113) | AH113: 本周CPA | AI113: =AG114/AG109
A114: 广告花费 | B114: =B110*B113 | C114: =C110*C113 | D114: =D110*D113 | E114: =E110*E113 | F114: =F110*F113 | G114: =G110*G113 | H114: =H110*H113 | I114: =SUM(B114:H114) | J114: 本周广告占比 | K114: =I114/I117 | M114: 广告花费 | N114: =N110*N113 | O114: =O110*O113 | P114: =P110*P113 | Q114: =Q110*Q113 | R114: =R110*R113 | S114: =S110*S113 | T114: =T110*T113 | U114: =SUM(N114:T114) | V114: 本周广告占比 | W114: =U114/U117 | Y114: 广告花费 | Z114: =N114-B114 | AA114: =O114-C114 | AB114: =P114-D114 | AC114: =Q114-E114 | AD114: =R114-F114 | AE114: =S114-G114 | AF114: =T114-H114 | AG114: =SUM(Z114:AF114) | AH114: 本周广告占比 | AI114: =AG114/AG117
...

Sheet 流量入口布局
A1: 词的定位
A2: 优先级 | B2: Keyword | C2: 月ABA排名 | D2: 相关性 | E2: 词的属性 | F2: 建议CPC | G2: 广告策略
A3: P0 | D3: 高相关 | E3: 核心词 | F3: 1.5
A4: P1 | D4: 中相关 | E4: 长尾词 | F4: 1.1
A5: P2 | D5: 弱相关 | E5: 品牌词 | F5: 0.8
A6: P3 | D6: 不相关 | E6: 流量词 | F6: 0.45
A14: 广告架构及策略（参考）
A15: 序号 | B15: 广告类型 | C15: 广告目的 | D15: 包含词 | E15: 总预算 | F15: 核心指标 | G15: 广告活动命名 | H15: 具体设置
A16: 广告1 | B16: 自动广告-低价 | C16: 捡漏 | E16: 20 | F16: Acos和订单增量 | G16: SKU-Auto-宽泛-捡漏 | H16: 0.1-0.3的竞价，5-10美金预算即可 如果有变体的话，可以把SKU都放进去，低价，捡漏，跑关联位，预算不用太高5-10美金即可，后续根据表现调整预算
A17: 广告2 | B17: 自动广告-正常价/高价 | C17: 跑词 | E17: 30 | F17: 词的相关性 Acos和订单增量 | G17: SKU-Auto-紧密-跑词 | H17: 前期竞价给高一些（建议竞价+0.2/建议竞价*1.25/极限值竞价），可以更快的跑出来词，更快的积累数据，1周后根据数据优化 可以酌情考虑把宽泛匹配比例调为0，有变体的话，前期测试，选择表现最好的SKU，单SKU测款+跑词（也可以开2个高价自动，在设置页面调整比例，一个跑词，一个跑关联）
A18: 广告3 | B18: 手动广告-大词-广泛 | C18: 跑流量，促进亚马逊收录 | E18: 50 | F18: 词的质量 CVR和Acos | G18: SKU-keyword-广泛-跑词 | H18: 前一周可以给高点竞价，一周之后，竞价逐步优化 单个SKU，1-3个关键词大词，注意词的精准度，曝光和点击率的关系变化，有没有达到自己的预期。还有就是CPC和位置。
A19: 广告4 | B19: 手动广告-大词-词组 | C19: 获取大词相关词组最顶层的精准流量，提升词组的整体自然位 | E19: 20 | F19: 自然位上升速度 CTR和CVR | G19: SKU-keyword-词组-冲位 | H19: 通过关键词广告控制预算来控制单量放量，竞价比广泛高一些，想办法让这些词出广告单，一个订单多买个（适合客单价低的产品），增加转化 单个SKU，可以1-3个核心关键词，方便控制广告预算和广告关键词位置，可以多开几组，把产品的核心大词测试一下看哪一个比较好
A20: 广告5 | B20: 手动广告-大词-精准 | C20: 获取大词单一词最顶层的精准流量，抢广告位，拉升自然位 | E20: 30 | F20: 自然位上升速度 CTR和CVR | G20: SKU-keyword-精准-冲位 | H20: 通过关键词广告控制预算来控制单量放量，竞价比词组高一些，通过CPC和Bid+调控到精准想打的广告位置，大多数用于首行和搜索结果其余位置 在精准组开了的词，在其他组避开相同CPC，错开广告位置或直接精准否定，以免互抢
A21: 广告6 | B21: 手动广告-长尾-精准 | C21: 获取最精准的直接客户搜索，提高做转化率，更好的抢占精准词流量 | E21: 30 | F21: 自然位上升速度 CTR和CVR | G21: SKU-长尾组-精准-冲位 | H21: 高竞价 单个SKU，10-15个关键词一组，根据数据表现可以开多组，通过广告报表筛选CTR>30%，转化>20%的优质词开广告
A22: 广告7 | B22: 商品投放-ASIN | C22: 选择有优势的竞品，提高曝光，蹭关联流量 | E22: 20 | F22: 订单增量 CVR和Acos | G22: SKU-ASIN-互补品-拓单 | H22: 如果有多个互补或者相似的SKU，可以相互投放，打造流量闭环 竞品的新品，还有断货的产品，也可以进行投放
A24: 广告种类集合
A25: 广告类型 | F25: 竞价策略 | I25: 广告位置竞价
A26: 商品推广 SP广告 | B26: 定向策略 | C26: 投放 | D26: 匹配模式 | E26: 筛选条件 | F26: 仅降低 | G26: 提升和降低 | H26: 固定 | I26: 首页 | J26: 详情页 | K26: 商品页面
B27: 自动投放 | C27: 关键字 | D27: 紧密匹配
D28: 宽泛匹配
C29: 商品 | D29: 同类商品
D30: 关联商品
B31: 手动投放 | C31: 商品 | D31: 分类 | E31: 品牌
E32: 价格范围
E33: 星级
E34: 配送
D35: 商品列表
C36: 关键字 | D36: 广泛
D37: 短语
D38: 精准
A40: 广告类型 | E40: 投放格式
A41: 品牌推广 SB广告 | B41: 投放类型 | C41: 投放匹配条件 | D41: 投放条件 | E41: 商品集详情页 | F41: 旗舰店 | G41: 视频 | H41: 竞价
B42: 关键字 | C42: 广泛
C43: 短语
C44: 精准
B45: 商品 | C45: 分类 | D45: 品牌
D46: 价格范围
D47: 星级
D48: 配送
C49: 商品
A51: 广告类型 | E51: 竞价优化方式
A52: 展示型广告 | B52: 投放类型 | C52: 投放二级分类 | D52: 投放条件 | E52: 曝光 | F52: 点击 | G52: 转化
B53: 商品 | C53: 分类 | D53: 品牌
D54: 价格范围
D55: 星级
D56: 配送
C57: 商品
B58: 受众 | C58: 亚马逊客户 | D58: 生活方式
D59: 兴趣
D60: 生活事件
D61: 场内客群
C62: 再营销浏览 | D62: 浏览过自家产品的
D63: 浏览过相关产品
C64: 购买再营销 | D64: 购买过自家产品的
D65: 购买过相关产品

Sheet 日常跟踪表US
A1: 时间 | B1: 星期 | C1: 工作内容 B09DSVFNRW | D1: 售价 | E1: PD | F1: 划线价折扣 | G1: CP | H1: 最低 成交价 | I1: SC最低 成交价毛利率 | J1: VC采购价毛利率 | K1: 移动 | L1: PC | M1: 访问 | N1: 总转化率 | O1: 实际自然订单 | P1: 自然订单 | Q1: 总订单 | R1: VC订单 | S1: 测评计划出单 | T1: 测评总出单 | U1: 测评完成率 | V1: Vine | W1: 销售额 | X1: 核心词ABA排名 | AB1: sif前三页关键词收录数量 | AC1: 大类排名 | AD1: 小类排名 | AE1: 评分 | AF1: 广告数据 | AQ1: 毛利数据 | AY1: 站外 | BC1: 库存监控
X2: dog water fountain | Y2: dog fountain | Z2: dog stainless steel cat water fountain | AA2: dog water fountain stainless steel | AF2: 曝光 | AG2: 点击 | AH2: 点击率 | AI2: 订单 | AJ2: CPC | AK2: ACOS | AL2: 广告转化 | AM2: 广告订单占比 | AN2: 花费（$） | AO2: 广告花费占比 | AP2: CPA | AQ2: 退款率 | AR2: 广告订单毛利P1$ | AS2: 自然订单毛利P1$ | AT2: 总订单毛利P1$ | AU2: 总订单毛利率P1 | AV2: 国内总成本$ | AW2: 回款金额 | AX2: 测评亏损 | AY2: 站外毛利$ | AZ2: 站外出单 | BA2: 站外售价 | BB2: 站外折扣 | BC2: VC仓库存 | BD2: 海外仓库存 | BE2: FBA仓 | BF2: 总库存 | BG2: 超90天以上的库存 | BH2: 备注
A3: 45908 | B3: 日 | C3: \ | D3: 26.98 | F3: 0 | G3: 0 | H3: 26.98 | I3: 0.232 | J3: 0.099 | K3: 669 | L3: 338 | M3: =K3+L3 | N3: =Q3/M3 | O3: =P3-AI3 | P3: =Q3-T3-AZ3 | Q3: 137 | R3: 134 | S3: 2 | T3: 2 | U3: =T3/S3 | V3: 20 | W3: =Q3*D3 | X3: 8 | Y3: 10 | Z3: 4 | AA3: 5 | AB3: 944 | AC3: 2176 | AD3: 24 | AE3: 4.2 | AF3: 52825 | AG3: 508 | AH3: =AG3/AF3 | AI3: 60 | AJ3: =AN3/AG3 | AK3: =AN3/(AI3*D3) | AL3: =AI3/AG3 | AM3: =AI3/P3 | AN3: 721.69 | AO3: =AN3/W3 | AP3: =AN3/AI3 | AQ3: 0 | AR3: =AS3-AP3 | AS3: 4.91 | AT3: =(AY3*AZ3)+(AR3*AI3)+(O3*AS3)+AX3-W3*AQ3 | AU3: =AT3/W3 | AV3: 10.67 | AW3: =Q3*AV3+AT3 | AX3: =-22*T3 | AY3: -2.17 | AZ3: 0 | BA3: 19.99 | BB3: 0.5 | BC3: =BC4+R4 | BD3: 10287 | BF3: =BC3+BD3 | BG3: 0
A4: 45909 | B4: 一 | C4: VC BD结束 | D4: 29.98 | F4: 0 | G4: 0 | H4: 29.98 | I4: 0.232 | J4: 0.099 | K4: 745 | L4: 394 | M4: =K4+L4 | N4: =Q4/M4 | O4: =P4-AI4 | P4: =Q4-T4-AZ4 | Q4: 59 | R4: 27 | S4: 2 | T4: 2 | U4: =T4/S4 | V4: 0 | W4: =Q4*D4 | X4: 8 | Y4: 10 | Z4: 4 | AA4: 5 | AB4: 944 | AC4: 2252 | AD4: 26 | AE4: 4.2 | AF4: 14124 | AG4: 111 | AH4: =AG4/AF4 | AI4: 12 | AJ4: =AN4/AG4 | AK4: =AN4/(AI4*D4) | AL4: =AI4/AG4 | AM4: =AI4/P4 | AN4: 167.76 | AO4: =AN4/W4 | AP4: =AN4/AI4 | AQ4: 0 | AR4: =AS4-AP4 | AS4: 4.91 | AT4: =(AY4*AZ4)+(AR4*AI4)+(O4*AS4)+AX4-W4*AQ4 | AU4: =AT4/W4 | AV4: 10.67 | AW4: =Q4*AV4+AT4 | AX4: =-22*T4 | AY4: -2.17 | AZ4: 0 | BA4: 19.99 | BB4: 0.5 | BC4: =BC5+R5 | BD4: 10287 | BF4: =BC4+BD4 | BG4: 0
A5: 45910 | B5: 二 | C5: \ | D5: 29.98 | F5: 0 | G5: 0 | H5: 29.98 | I5: 0.232 | J5: 0.099 | K5: 278 | L5: 203 | M5: =K5+L5 | N5: =Q5/M5 | O5: =P5-AI5 | P5: =Q5-T5-AZ5 | Q5: 52 | R5: 17 | S5: 2 | T5: 2 | U5: =T5/S5 | V5: 0 | W5: =Q5*D5 | X5: 8 | Y5: 10 | Z5: 4 | AA5: 5 | AB5: 944 | AC5: 2706 | AD5: 28 | AE5: 4.2 | AF5: 14419 | AG5: 71 | AH5: =AG5/AF5 | AI5: 10 | AJ5: =AN5/AG5 | AK5: =AN5/(AI5*D5) | AL5: =AI5/AG5 | AM5: =AI5/P5 | AN5: 90.43 | AO5: =AN5/W5 | AP5: =AN5/AI5 | AQ5: 0 | AR5: =AS5-AP5 | AS5: 4.91 | AT5: =(AY5*AZ5)+(AR5*AI5)+(O5*AS5)+AX5-W5*AQ5 | AU5: =AT5/W5 | AV5: 10.67 | AW5: =Q5*AV5+AT5 | AX5: =-22*T5 | AY5: -2.17 | AZ5: 0 | BA5: 19.99 | BB5: 0.5 | BC5: =BC6+R6 | BD5: 10287 | BF5: =BC5+BD5 | BG5: 0
A6: 45911 | B6: 四 | C6: \ | D6: 29.98 | F6: 0 | G6: 0 | H6: 29.98 | I6: 0.232 | J6: 0.099 | K6: 246 | L6: 187 | M6: =K6+L6 | N6: =Q6/M6 | O6: =P6-AI6 | P6: =Q6-T6-AZ6 | Q6: 66 | R6: 20 | S6: 3 | T6: 2 | U6: =T6/S6 | V6: 0 | W6: =Q6*D6 | X6: 8 | Y6: 10 | Z6: 4 | AA6: 5 | AB6: 944 | AC6: 2589 | AD6: 27 | AE6: 4.2 | AF6: 15000 | AG6: 107 | AH6: =AG6/AF6 | AI6: 23 | AJ6: =AN6/AG6 | AK6: =AN6/(AI6*D6) | AL6: =AI6/AG6 | AM6: =AI6/P6 | AN6: 171.27 | AO6: =AN6/W6 | AP6: =AN6/AI6 | AQ6: 0 | AR6: =AS6-AP6 | AS6: 4.91 | AT6: =(AY6*AZ6)+(AR6*AI6)+(O6*AS6)+AX6-W6*AQ6 | AU6: =AT6/W6 | AV6: 10.67 | AW6: =Q6*AV6+AT6 | AX6: =-22*T6 | AY6: -2.17 | AZ6: 0 | BA6: 19.99 | BB6: 0.5 | BC6: =BC7+R7 | BD6: 10287 | BF6: =BC6+BD6 | BG6: 0
A7: 45912 | B7: 五 | C7: \ | D7: 29.98 | F7: 0 | G7: 0 | H7: 29.98 | I7: 0.232 | J7: 0.099 | K7: 256 | L7: 169 | M7: =K7+L7 | N7: =Q7/M7 | O7: =P7-AI7 | P7: =Q7-T7-AZ7 | Q7: 46 | R7: 17 | S7: 3 | T7: 2 | U7: =T7/S7 | V7: 0 | W7: =Q7*D7 | X7: 8 | Y7: 10 | Z7: 4 | AA7: 5 | AB7: 944 | AC7: 3019 | AD7: 35 | AE7: 4.2 | AF7: 12401 | AG7: 71 | AH7: =AG7/AF7 | AI7: 9 | AJ7: =AN7/AG7 | AK7: =AN7/(AI7*D7) | AL7: =AI7/AG7 | AM7: =AI7/P7 | AN7: 115.22 | AO7: =AN7/W7 | AP7: =AN7/AI7 | AQ7: 0 | AR7: =AS7-AP7 | AS7: 4.91 | AT7: =(AY7*AZ7)+(AR7*AI7)+(O7*AS7)+AX7-W7*AQ7 | AU7: =AT7/W7 | AV7: 10.67 | AW7: =Q7*AV7+AT7 | AX7: =-22*T7 | AY7: -2.17 | AZ7: 0 | BA7: 19.99 | BB7: 0.5 | BC7: =BC8+R8 | BD7: 10287 | BF7: =BC7+BD7 | BG7: 0
A8: 45913 | B8: 六 | C8: VC BD开始 | D8: 26.98 | F8: 0 | G8: 0 | H8: 26.98 | I8: 0.232 | J8: 0.099 | K8: 192 | L8: 139 | M8: =K8+L8 | N8: =Q8/M8 | O8: =P8-AI8 | P8: =Q8-T8-AZ8 | Q8: 93 | R8: 84 | S8: 5 | T8: 3 | U8: =T8/S8 | V8: 0 | W8: =Q8*D8 | X8: 8 | Y8: 10 | Z8: 4 | AA8: 5 | AB8: 944 | AC8: 3153 | AD8: 35 | AE8: 4.2 | AF8: 46831 | AG8: 181 | AH8: =AG8/AF8 | AI8: 23 | AJ8: =AN8/AG8 | AK8: =AN8/(AI8*D8) | AL8: =AI8/AG8 | AM8: =AI8/P8 | AN8: 281.66 | AO8: =AN8/W8 | AP8: =AN8/AI8 | AQ8: 0 | AR8: =AS8-AP8 | AS8: 4.91 | AT8: =(AY8*AZ8)+(AR8*AI8)+(O8*AS8)+AX8-W8*AQ8 | AU8: =AT8/W8 | AV8: 10.67 | AW8: =Q8*AV8+AT8 | AX8: =-22*T8 | AY8: -2.17 | AZ8: 0 | BA8: 19.99 | BB8: 0.5 | BC8: =BC9+R9 | BD8: 10287 | BF8: =BC8+BD8 | BG8: 0
A9: 45914 | B9: 日 | C9: \ | D9: 26.98 | F9: 0 | G9: 0 | H9: 26.98 | I9: 0.232 | J9: 0.099 | K9: 726 | L9: 220 | M9: =K9+L9 | N9: =Q9/M9 | O9: =P9-AI9 | P9: =Q9-T9-AZ9 | Q9: 95 | R9: 95 | S9: 5 | T9: 3 | U9: =T9/S9 | V9: 0 | W9: =Q9*D9 | X9: 8 | Y9: 10 | Z9: 4 | AA9: 5 | AB9: 944 | AC9: 3370 | AD9: 38 | AE9: 4.2 | AF9: 50446 | AG9: 218 | AH9: =AG9/AF9 | AI9: 37 | AJ9: =AN9/AG9 | AK9: =AN9/(AI9*D9) | AL9: =AI9/AG9 | AM9: =AI9/P9 | AN9: 339.9 | AO9: =AN9/W9 | AP9: =AN9/AI9 | AQ9: 0 | AR9: =AS9-AP9 | AS9: 4.91 | AT9: =(AY9*AZ9)+(AR9*AI9)+(O9*AS9)+AX9-W9*AQ9 | AU9: =AT9/W9 | AV9: 10.67 | AW9: =Q9*AV9+AT9 | AX9: =-22*T9 | AY9: -2.17 | AZ9: 0 | BA9: 19.99 | BB9: 0.5 | BC9: =BC10+R10 | BD9: 10287 | BF9: =BC9+BD9 | BG9: 0
A10: 45915 | B10: 一 | C10: \ | D10: 26.98 | F10: 0 | G10: 0 | H10: 26.98 | I10: 0.232 | J10: 0.099 | K10: 539 | L10: 264 | M10: =K10+L10 | N10: =Q10/M10 | O10: =P10-AI10 | P10: =Q10-T10-AZ10 | Q10: 135 | R10: 130 | S10: 5 | T10: 3 | U10: =T10/S10 | V10: 0 | W10: =Q10*D10 | X10: 8 | Y10: 10 | Z10: 4 | AA10: 5 | AB10: 944 | AC10: 2909 | AD10: 33 | AE10: 4.2 | AF10: 63764 | AG10: 299 | AH10: =AG10/AF10 | AI10: 60 | AJ10: =AN10/AG10 | AK10: =AN10/(AI10*D10) | AL10: =AI10/AG10 | AM10: =AI10/P10 | AN10: 484.74 | AO10: =AN10/W10 | AP10: =AN10/AI10 | AQ10: 0 | AR10: =AS10-AP10 | AS10: 4.91 | AT10: =(AY10*AZ10)+(AR10*AI10)+(O10*AS10)+AX10-W10*AQ10 | AU10: =AT10/W10 | AV10: 10.67 | AW10: =Q10*AV10+AT10 | AX10: =-22*T10 | AY10: -2.17 | AZ10: 0 | BA10: 19.99 | BB10: 0.5 | BC10: =BC11+R11 | BD10: 10287 | BF10: =BC10+BD10 | BG10: 0
A11: 45916 | B11: 二 | C11: \ | D11: 26.98 | F11: 0 | G11: 0 | H11: 26.98 | I11: 0.232 | J11: 0.099 | K11: 632 | L11: 295 | M11: =K11+L11 | N11: =Q11/M11 | O11: =P11-AI11 | P11: =Q11-T11-AZ11 | Q11: 107 | R11: 106 | S11: 4 | T11: 3 | U11: =T11/S11 | V11: 0 | W11: =Q11*D11 | X11: 8 | Y11: 10 | Z11: 4 | AA11: 5 | AB11: 944 | AC11: 2550 | AD11: 28 | AE11: 4.2 | AF11: 63713 | AG11: 219 | AH11: =AG11/AF11 | AI11: 38 | AJ11: =AN11/AG11 | AK11: =AN11/(AI11*D11) | AL11: =AI11/AG11 | AM11: =AI11/P11 | AN11: 335.45 | AO11: =AN11/W11 | AP11: =AN11/AI11 | AQ11: 0 | AR11: =AS11-AP11 | AS11: 4.91 | AT11: =(AY11*AZ11)+(AR11*AI11)+(O11*AS11)+AX11-W11*AQ11 | AU11: =AT11/W11 | AV11: 10.67 | AW11: =Q11*AV11+AT11 | AX11: =-22*T11 | AY11: -2.17 | AZ11: 0 | BA11: 19.99 | BB11: 0.5 | BC11: =BC12+R12 | BD11: 10287 | BF11: =BC11+BD11 | BG11: 0
A12: 45917 | B12: 三 | C12: \ | D12: 26.98 | F12: 0 | G12: 0 | H12: 26.98 | I12: 0.232 | J12: 0.099 | K12: 557 | L12: 260 | M12: =K12+L12 | N12: =Q12/M12 | O12: =P12-AI12 | P12: =Q12-T12-AZ12 | Q12: 121 | R12: 118 | S12: 1 | T12: 1 | U12: =T12/S12 | V12: 0 | W12: =Q12*D12 | X12: 8 | Y12: 10 | Z12: 4 | AA12: 5 | AB12: 944 | AC12: 2585 | AD12: 27 | AE12: 4.2 | AF12: 67904 | AG12: 243 | AH12: =AG12/AF12 | AI12: 40 | AJ12: =AN12/AG12 | AK12: =AN12/(AI12*D12) | AL12: =AI12/AG12 | AM12: =AI12/P12 | AN12: 381.37 | AO12: =AN12/W12 | AP12: =AN12/AI12 | AQ12: 0 | AR12: =AS12-AP12 | AS12: 4.91 | AT12: =(AY12*AZ12)+(AR12*AI12)+(O12*AS12)+AX12-W12*AQ12 | AU12: =AT12/W12 | AV12: 10.67 | AW12: =Q12*AV12+AT12 | AX12: =-22*T12 | AY12: -2.17 | AZ12: 0 | BA12: 19.99 | BB12: 0.5 | BC12: =BC13+R13 | BD12: 10287 | BF12: =BC12+BD12 | BG12: 0
A13: 45918 | B13: 四 | C13: \ | D13: 26.98 | F13: 0 | G13: 0 | H13: 26.98 | I13: 0.232 | J13: 0.099 | K13: 556 | L13: 283 | M13: =K13+L13 | N13: =Q13/M13 | O13: =P13-AI13 | P13: =Q13-T13-AZ13 | Q13: 109 | R13: 106 | S13: 1 | T13: 1 | U13: =T13/S13 | V13: 0 | W13: =Q13*D13 | X13: 8 | Y13: 10 | Z13: 4 | AA13: 5 | AB13: 944 | AC13: 2482 | AD13: 26 | AE13: 4.2 | AF13: 66565 | AG13: 195 | AH13: =AG13/AF13 | AI13: 30 | AJ13: =AN13/AG13 | AK13: =AN13/(AI13*D13) | AL13: =AI13/AG13 | AM13: =AI13/P13 | AN13: 294.73 | AO13: =AN13/W13 | AP13: =AN13/AI13 | AQ13: 0 | AR13: =AS13-AP13 | AS13: 4.91 | AT13: =(AY13*AZ13)+(AR13*AI13)+(O13*AS13)+AX13-W13*AQ13 | AU13: =AT13/W13 | AV13: 10.67 | AW13: =Q13*AV13+AT13 | AX13: =-22*T13 | AY13: -2.17 | AZ13: 0 | BA13: 19.99 | BB13: 0.5 | BC13: =BC14+R14 | BD13: 10287 | BF13: =BC13+BD13 | BG13: 0
A14: 45919 | B14: 五 | C14: \ | D14: 26.98 | F14: 0 | G14: 0 | H14: 26.98 | I14: 0.232 | J14: 0.099 | K14: 522 | L14: 272 | M14: =K14+L14 | N14: =Q14/M14 | O14: =P14-AI14 | P14: =Q14-T14-AZ14 | Q14: 112 | R14: 112 | S14: 1 | T14: 1 | U14: =T14/S14 | V14: 0 | W14: =Q14*D14 | X14: 8 | Y14: 10 | Z14: 4 | AA14: 5 | AB14: 944 | AC14: 2466 | AD14: 21 | AE14: 4.2 | AF14: 63826 | AG14: 189 | AH14: =AG14/AF14 | AI14: 35 | AJ14: =AN14/AG14 | AK14: =AN14/(AI14*D14) | AL14: =AI14/AG14 | AM14: =AI14/P14 | AN14: 273.66 | AO14: =AN14/W14 | AP14: =AN14/AI14 | AQ14: 0 | AR14: =AS14-AP14 | AS14: 4.91 | AT14: =(AY14*AZ14)+(AR14*AI14)+(O14*AS14)+AX14-W14*AQ14 | AU14: =AT14/W14 | AV14: 10.67 | AW14: =Q14*AV14+AT14 | AX14: =-22*T14 | AY14: -2.17 | AZ14: 0 | BA14: 19.99 | BB14: 0.5 | BC14: =BC15+R15 | BD14: 10287 | BF14: =BC14+BD14 | BG14: 0
... A22: 45927 | B22: 六 | C22: \ | D22: 26.98 | F22: 0 | G22: 0 | H22: 26.98 | I22: 0.232 | J22: 0.099 | K22: 140 | L22: 140 | M22: =K22+L22 | N22: =Q22/M22 | O22: =P22-AI22 | P22: =Q22-T22-AZ22 | Q22: 79 | R22: 70 | S22: 1 | T22: 1 | U22: =T22/S22 | V22: 0 | W22: =Q22*D22 | X22: 8 | Y22: 10 | Z22: 4 | AA22: 5 | AB22: 944 | AC22: 3515 | AD22: 47 | AE22: 4.2 | AF22: 47185 | AG22: 164 | AH22: =AG22/AF22 | AI22: 21 | AJ22: =AN22/AG22 | AK22: =AN22/(AI22*D22) | AL22: =AI22/AG22 | AM22: =AI22/P22 | AN22: 219.84 | AO22: =AN22/W22 | AP22: =AN22/AI22 | AQ22: 0 | AR22: =AS22-AP22 | AS22: 4.91 | AT22: =(AY22*AZ22)+(AR22*AI22)+(O22*AS22)+AX22-W22*AQ22 | AU22: =AT22/W22 | AV22: 10.67 | AW22: =Q22*AV22+AT22 | AX22: =-22*T22 | AY22: -2.17 | AZ22: 0 | BA22: 19.99 | BB22: 0.5 | BC22: =BC23+R23 | BD22: 10287 | BF22: =BC22+BD22 | BG22: 0
A23: 45928 | B23: 日 | C23: \ | D23: 26.98 | F23: 0 | G23: 0 | H23: 26.98 | I23: 0.232 | J23: 0.099 | K23: 203 | L23: 162 | M23: =K23+L23 | N23: =Q23/M23 | O23: =P23-AI23 | P23: =Q23-T23-AZ23 | Q23: 107 | R23: 97 | S23: 1 | T23: 1 | U23: =T23/S23 | V23: 0 | W23: =Q23*D23 | X23: 8 | Y23: 10 | Z23: 4 | AA23: 5 | AB23: 944 | AC23: 3344 | AD23: 40 | AE23: 4.2 | AF23: 55902 | AG23: 239 | AH23: =AG23/AF23 | AI23: 32 | AJ23: =AN23/AG23 | AK23: =AN23/(AI23*D23) | AL23: =AI23/AG23 | AM23: =AI23/P23 | AN23: 352.08 | AO23: =AN23/W23 | AP23: =AN23/AI23 | AQ23: 0 | AR23: =AS23-AP23 | AS23: 4.91 | AT23: =(AY23*AZ23)+(AR23*AI23)+(O23*AS23)+AX23-W23*AQ23 | AU23: =AT23/W23 | AV23: 10.67 | AW23: =Q23*AV23+AT23 | AX23: =-22*T23 | AY23: -2.17 | AZ23: 0 | BA23: 19.99 | BB23: 0.5 | BC23: =BC24+R24 | BD23: 10287 | BF23: =BC23+BD23+BE23
A24: 45929 | B24: 一 | C24: VC BD结束 | D24: 29.98 | F24: 0 | G24: 0 | H24: 29.98 | I24: 0.232 | J24: 0.099 | K24: 211 | L24: 157 | M24: =K24+L24 | N24: =Q24/M24 | O24: =P24-AI24 | P24: =Q24-T24-AZ24 | Q24: 60 | R24: 28 | S24: 1 | T24: 1 | U24: =T24/S24 | V24: 0 | W24: =Q24*D24 | X24: 8 | Y24: 10 | Z24: 4 | AA24: 5 | AB24: 944 | AC24: 3265 | AD24: 46 | AE24: 4.2 | AF24: 11043 | AG24: 32 | AH24: =AG24/AF24 | AI24: 5 | AJ24: =AN24/AG24 | AK24: =AN24/(AI24*D24) | AL24: =AI24/AG24 | AM24: =AI24/P24 | AN24: 33.2 | AO24: =AN24/W24 | AP24: =AN24/AI24 | AQ24: 0 | AR24: =AS24-AP24 | AS24: 4.91 | AT24: =(AY24*AZ24)+(AR24*AI24)+(O24*AS24)+AX24-W24*AQ24 | AU24: =AT24/W24 | AV24: 10.67 | AW24: =Q24*AV24+AT24 | AX24: =-22*T24 | AY24: -2.17 | AZ24: 0 | BA24: 19.99 | BB24: 0.5 | BC24: =BC25+R25 | BD24: 10287 | BF24: =BC24+BD24+BE24
A25: 45930 | B25: 二 | C25: \ | D25: 29.98 | F25: 0 | G25: 0 | H25: 29.98 | I25: 0.232 | J25: 0.099 | K25: 297 | L25: 196 | M25: =K25+L25 | N25: =Q25/M25 | O25: =P25-AI25 | P25: =Q25-T25-AZ25 | Q25: 45 | R25: 4 | S25: 1 | T25: 1 | U25: =T25/S25 | V25: 0 | W25: =Q25*D25 | X25: 8 | Y25: 10 | Z25: 4 | AA25: 5 | AB25: 944 | AC25: 3412 | AD25: 48 | AE25: 4.2 | AF25: 12528 | AG25: 84 | AH25: =AG25/AF25 | AI25: 12 | AJ25: =AN25/AG25 | AK25: =AN25/(AI25*D25) | AL25: =AI25/AG25 | AM25: =AI25/P25 | AN25: 108.98 | AO25: =AN25/W25 | AP25: =AN25/AI25 | AQ25: 0 | AR25: =AS25-AP25 | AS25: 4.91 | AT25: =(AY25*AZ25)+(AR25*AI25)+(O25*AS25)+AX25-W25*AQ25 | AU25: =AT25/W25 | AV25: 10.67 | AW25: =Q25*AV25+AT25 | AX25: =-22*T25 | AY25: -2.17 | AZ25: 0 | BA25: 19.99 | BB25: 0.5 | BC25: =BC26+R26 | BD25: 10287 | BF25: =BC25+BD25+BE25
A26: 45931 | B26: 三 | C26: \ | D26: 29.98 | F26: 0 | G26: 0 | H26: 29.98 | I26: 0.232 | J26: 0.099 | K26: 177 | L26: 135 | M26: =K26+L26 | N26: =Q26/M26 | O26: =P26-AI26 | P26: =Q26-T26-AZ26 | Q26: 45 | R26: 2 | S26: 1 | T26: 1 | U26: =T26/S26 | V26: 0 | W26: =Q26*D26 | X26: 8 | Y26: 10 | Z26: 4 | AA26: 5 | AB26: 944 | AC26: 3721 | AD26: 51 | AE26: 4.2 | AF26: 12805 | AG26: 70 | AH26: =AG26/AF26 | AI26: 17 | AJ26: =AN26/AG26 | AK26: =AN26/(AI26*D26) | AL26: =AI26/AG26 | AM26: =AI26/P26 | AN26: 100.86 | AO26: =AN26/W26 | AP26: =AN26/AI26 | AQ26: 0 | AR26: =AS26-AP26 | AS26: 4.91 | AT26: =(AY26*AZ26)+(AR26*AI26)+(O26*AS26)+AX26-W26*AQ26 | AU26: =AT26/W26 | AV26: 10.67 | AW26: =Q26*AV26+AT26 | AX26: =-22*T26 | AY26: -2.17 | AZ26: 0 | BA26: 19.99 | BB26: 0.5 | BC26: =BC27+R27 | BD26: 10287 | BF26: =BC26+BD26+BE26
A27: 45932 | B27: 四 | C27: \ | D27: 29.98 | F27: 0 | G27: 0 | H27: 29.98 | I27: 0.232 | J27: 0.099 | K27: 154 | L27: 134 | M27: =K27+L27 | N27: =Q27/M27 | O27: =P27-AI27 | P27: =Q27-T27-AZ27 | Q27: 35 | R27: 2 | S27: 1 | T27: 1 | U27: =T27/S27 | V27: 0 | W27: =Q27*D27 | X27: 8 | Y27: 10 | Z27: 4 | AA27: 5 | AB27: 944 | AC27: 3974 | AD27: 52 | AE27: 4.2 | AF27: 12170 | AG27: 56 | AH27: =AG27/AF27 | AI27: 7 | AJ27: =AN27/AG27 | AK27: =AN27/(AI27*D27) | AL27: =AI27/AG27 | AM27: =AI27/P27 | AN27: 80.29 | AO27: =AN27/W27 | AP27: =AN27/AI27 | AQ27: 0 | AR27: =AS27-AP27 | AS27: 4.91 | AT27: =(AY27*AZ27)+(AR27*AI27)+(O27*AS27)+AX27-W27*AQ27 | AU27: =AT27/W27 | AV27: 10.67 | AW27: =Q27*AV27+AT27 | AX27: =-22*T27 | AY27: -2.17 | AZ27: 0 | BA27: 19.99 | BB27: 0.5 | BC27: =BC28+R28 | BD27: 10287 | BF27: =BC27+BD27+BE27
A28: 45933 | B28: 五 | C28: VC BD开始 | D28: 26.98 | F28: 0 | G28: 0 | H28: 26.98 | I28: 0.232 | J28: 0.099 | K28: 144 | L28: 113 | M28: =K28+L28 | N28: =Q28/M28 | O28: =P28-AI28 | P28: =Q28-T28-AZ28 | Q28: 54 | R28: 50 | S28: 1 | T28: 1 | U28: =T28/S28 | V28: 0 | W28: =Q28*D28 | X28: 8 | Y28: 10 | Z28: 4 | AA28: 5 | AB28: 944 | AC28: 4427 | AD28: 60 | AE28: 4.2 | AF28: 20262 | AG28: 145 | AH28: =AG28/AF28 | AI28: 21 | AJ28: =AN28/AG28 | AK28: =AN28/(AI28*D28) | AL28: =AI28/AG28 | AM28: =AI28/P28 | AN28: 227.26 | AO28: =AN28/W28 | AP28: =AN28/AI28 | AQ28: 0 | AR28: =AS28-AP28 | AS28: 4.91 | AT28: =(AY28*AZ28)+(AR28*AI28)+(O28*AS28)+AX28-W28*AQ28 | AU28: =AT28/W28 | AV28: 10.67 | AW28: =Q28*AV28+AT28 | AX28: =-22*T28 | AY28: -2.17 | AZ28: 0 | BA28: 19.99 | BB28: 0.5 | BC28: =BC29+R29 | BD28: 10287 | BF28: =BC28+BD28+BE28
A29: 45934 | B29: 六 | C29: \ | D29: 26.98 | F29: 0 | G29: 0 | H29: 26.98 | I29: 0.232 | J29: 0.099 | K29: 132 | L29: 110 | M29: =K29+L29 | N29: =Q29/M29 | O29: =P29-AI29 | P29: =Q29-T29-AZ29 | Q29: 76 | R29: 66 | S29: 1 | T29: 1 | U29: =T29/S29 | V29: 0 | W29: =Q29*D29 | X29: 8 | Y29: 10 | Z29: 4 | AA29: 5 | AB29: 944 | AC29: 4172 | AD29: 57 | AE29: 4.2 | AF29: 27806 | AG29: 205 | AH29: =AG29/AF29 | AI29: 29 | AJ29: =AN29/AG29 | AK29: =AN29/(AI29*D29) | AL29: =AI29/AG29 | AM29: =AI29/P29 | AN29: 296.81 | AO29: =AN29/W29 | AP29: =AN29/AI29 | AQ29: 0 | AR29: =AS29-AP29 | AS29: 4.91 | AT29: =(AY29*AZ29)+(AR29*AI29)+(O29*AS29)+AX29-W29*AQ29 | AU29: =AT29/W29 | AV29: 10.67 | AW29: =Q29*AV29+AT29 | AX29: =-22*T29 | AY29: -2.17 | AZ29: 0 | BA29: 19.99 | BB29: 0.5 | BC29: =BC30+R30 | BD29: 10287 | BF29: =BC29+BD29+BE29
A30: 45935 | B30: 日 | C30: \ | D30: 26.98 | F30: 0 | G30: 0 | H30: 26.98 | I30: 0.232 | J30: 0.099 | K30: 191 | L30: 117 | M30: =K30+L30 | N30: =Q30/M30 | O30: =P30-AI30 | P30: =Q30-T30-AZ30 | Q30: 79 | R30: 72 | S30: 1 | T30: 1 | U30: =T30/S30 | V30: 0 | W30: =Q30*D30 | X30: 8 | Y30: 10 | Z30: 4 | AA30: 5 | AB30: 944 | AC30: 3803 | AD30: 49 | AE30: 4.2 | AF30: 26799 | AG30: 251 | AH30: =AG30/AF30 | AI30: 30 | AJ30: =AN30/AG30 | AK30: =AN30/(AI30*D30) | AL30: =AI30/AG30 | AM30: =AI30/P30 | AN30: 358.64 | AO30: =AN30/W30 | AP30: =AN30/AI30 | AQ30: 0 | AR30: =AS30-AP30 | AS30: 4.91 | AT30: =(AY30*AZ30)+(AR30*AI30)+(O30*AS30)+AX30-W30*AQ30 | AU30: =AT30/W30 | AV30: 10.67 | AW30: =Q30*AV30+AT30 | AX30: =-22*T30 | AY30: -2.17 | AZ30: 0 | BA30: 19.99 | BB30: 0.5 | BC30: =BC31+R31 | BD30: 10287 | BF30: =BC30+BD30+BE30
A31: 45936 | B31: 一 | C31: \ | D31: 26.98 | F31: 0 | G31: 0 | H31: 26.98 | I31: 0.232 | J31: 0.099 | K31: 263 | L31: 160 | M31: =K31+L31 | N31: =Q31/M31 | O31: =P31-AI31 | P31: =Q31-T31-AZ31 | Q31: 87 | R31: 80 | S31: 1 | T31: 1 | U31: =T31/S31 | V31: 0 | W31: =Q31*D31 | X31: 8 | Y31: 10 | Z31: 4 | AA31: 5 | AB31: 944 | AC31: 3568 | AD31: 51 | AE31: 4.2 | AF31: 33933 | AG31: 243 | AH31: =AG31/AF31 | AI31: 37 | AJ31: =AN31/AG31 | AK31: =AN31/(AI31*D31) | AL31: =AI31/AG31 | AM31: =AI31/P31 | AN31: 369.65 | AO31: =AN31/W31 | AP31: =AN31/AI31 | AQ31: 0 | AR31: =AS31-AP31 | AS31: 4.91 | AT31: =(AY31*AZ31)+(AR31*AI31)+(O31*AS31)+AX31-W31*AQ31 | AU31: =AT31/W31 | AV31: 10.67 | AW31: =Q31*AV31+AT31 | AX31: =-22*T31 | AY31: -2.17 | AZ31: 0 | BA31: 19.99 | BB31: 0.5 | BC31: =BC32+R32 | BD31: 10287 | BF31: =BC31+BD31+BE31
A32: 45937 | B32: 二 | C32: 秋季大促，参考价抓取问题无活动标 | D32: 26.98 | F32: 0 | G32: 0 | H32: 26.98 | I32: 0.232 | J32: 0.099 | K32: 279 | L32: 193 | M32: =K32+L32 | N32: =Q32/M32 | O32: =P32-AI32 | P32: =Q32-T32-AZ32 | Q32: 107 | R32: 100 | S32: 1 | T32: 1 | U32: =T32/S32 | V32: 0 | W32: =Q32*D32 | X32: 30 | Y32: 37 | Z32: 8 | AA32: 16 | AB32: 1088 | AC32: 3349 | AD32: 37 | AE32: 4.2 | AF32: 36994 | AG32: 328 | AH32: =AG32/AF32 | AI32: 50 | AJ32: =AN32/AG32 | AK32: =AN32/(AI32*D32) | AL32: =AI32/AG32 | AM32: =AI32/P32 | AN32: 563.38 | AO32: =AN32/W32 | AP32: =AN32/AI32 | AQ32: 0 | AR32: =AS32-AP32 | AS32: 4.91 | AT32: =(AY32*AZ32)+(AR32*AI32)+(O32*AS32)+AX32-W32*AQ32 | AU32: =AT32/W32 | AV32: 10.67 | AW32: =Q32*AV32+AT32 | AX32: =-22*T32 | AY32: -2.17 | AZ32: 0 | BA32: 19.99 | BB32: 0.5 | BC32: =BC33+R33 | BD32: 10287 | BF32: =BC32+BD32+BE32
A33: 45938 | B33: 三 | C33: \ | D33: 26.98 | F33: 0 | G33: 0 | H33: 26.98 | I33: 0.232 | J33: 0.099 | K33: 250 | L33: 209 | M33: =K33+L33 | N33: =Q33/M33 | O33: =P33-AI33 | P33: =Q33-T33-AZ33 | Q33: 93 | R33: 89 | S33: 1 | T33: 1 | U33: =T33/S33 | V33: 0 | W33: =Q33*D33 | X33: 38 | Y33: 24 | Z33: 9 | AA33: 18 | AB33: 1088 | AC33: 3670 | AD33: 47 | AE33: 4.2 | AF33: 44077 | AG33: 305 | AH33: =AG33/AF33 | AI33: 49 | AJ33: =AN33/AG33 | AK33: =AN33/(AI33*D33) | AL33: =AI33/AG33 | AM33: =AI33/P33 | AN33: 507.8 | AO33: =AN33/W33 | AP33: =AN33/AI33 | AQ33: 0 | AR33: =AS33-AP33 | AS33: 4.91 | AT33: =(AY33*AZ33)+(AR33*AI33)+(O33*AS33)+AX33-W33*AQ33 | AU33: =AT33/W33 | AV33: 10.67 | AW33: =Q33*AV33+AT33 | AX33: =-22*T33 | AY33: -2.17 | AZ33: 0 | BA33: 19.99 | BB33: 0.5 | BC33: 3310 | BD33: 10287 | BF33: =BC33+BD33+BE33
A34: 45939 | B34: 四 | C34: \ | D34: 26.98 | F34: 0 | G34: 0 | H34: 26.98 | I34: 0.232 | J34: 0.099 | K34: 252 | L34: 209 | M34: =K34+L34 | N34: =Q34/M34 | O34: =P34-AI34 | P34: =Q34-T34-AZ34 | Q34: 93 | R34: 89 | S34: 1 | T34: 1 | U34: =T34/S34 | V34: 0 | W34: =Q34*D34 | X34: 38 | Y34: 24 | Z34: 9 | AA34: 18 | AB34: 1088 | AC34: 3670 | AD34: 47 | AE34: 4.2 | AF34: 44077 | AG34: 305 | AH34: =AG34/AF34 | AI34: 49 | AJ34: =AN34/AG34 | AK34: =AN34/(AI34*D34) | AL34: =AI34/AG34 | AM34: =AI34/P34 | AN34: 507.8 | AO34: =AN34/W34 | AP34: =AN34/AI34 | AQ34: 0 | AR34: =AS34-AP34 | AS34: 4.91 | AT34: =(AY34*AZ34)+(AR34*AI34)+(O34*AS34)+AX34-W34*AQ34 | AU34: =AT34/W34 | AV34: 10.67 | AW34: =Q34*AV34+AT34 | AX34: =-22*T34 | AY34: -2.17 | AZ34: 0 | BA34: 19.99 | BB34: 0.5 | BC34: 3310 | BD34: 10287 | BF34: =BC34+BD34+BE34
A35: 45940 | B35: 五 | C35: \ | D35: 26.98 | F35: 0 | G35: 0 | H35: 26.98 | I35: 0.232 | J35: 0.099 | K35: 252 | L35: 209 | M35: =K35+L35 | N35: =Q35/M35 | O35: =P35-AI35 | P35: =Q35-T35-AZ35 | Q35: 93 | R35: 89 | S35: 1 | T35: 1 | U35: =T35/S35 | V35: 0 | W35: =Q35*D35 | X35: 38 | Y35: 24 | Z35: 9 | AA35: 18 | AB35: 1088 | AC35: 3670 | AD35: 47 | AE35: 4.2 | AF35: 44077 | AG35: 305 | AH35: =AG35/AF35 | AI35: 49 | AJ35: =AN35/AG35 | AK35: =AN35/(AI35*D35) | AL35: =AI35/AG35 | AM35: =AI35/P35 | AN35: 507.8 | AO35: =AN35/W35 | AP35: =AN35/AI35 | AQ35: 0 | AR35: =AS35-AP35 | AS35: 4.91 | AT35: =(AY35*AZ35)+(AR35*AI35)+(O35*AS35)+AX35-W35*AQ35 | AU35: =AT35/W35 | AV35: 10.67 | AW35: =Q35*AV35+AT35 | AX35: =-22*T35 | AY35: -2.17 | AZ35: 0 | BA35: 19.99 | BB35: 0.5 | BC35: 3310 | BD35: 10287 | BF35: =BC35+BD35+BE35
A36: 45941 | B36: 六 | C36: \ | D36: 26.98 | F36: 0 | G36: 0 | H36: 26.98 | I36: 0.232 | J36: 0.099 | K36: 255 | L36: 210 | M36: =K36+L36 | N36: =Q36/M36 | O36: =P36-AI36 | P36: =Q36-T36-AZ36 | Q36: 93 | R36: 89 | S36: 1 | T36: 1 | U36: =T36/S36 | V36: 0 | W36: =Q36*D36 | X36: 38 | Y36: 24 | Z36: 9 | AA36: 18 | AB36: 1088 | AC36: 3670 | AD36: 47 | AE36: 4.2 | AF36: 44077 | AG36: 305 | AH36: =AG36/AF36 | AI36: 49 | AJ36: =AN36/AG36 | AK36: =AN36/(AI36*D36) | AL36: =AI36/AG36 | AM36: =AI36/P36 | AN36: 507.8 | AO36: =AN36/W36 | AP36: =AN36/AI36 | AQ36: 0 | AR36: =AS36-AP36 | AS36: 4.91 | AT36: =(AY36*AZ36)+(AR36*AI36)+(O36*AS36)+AX36-W36*AQ36 | AU36: =AT36/W36 | AV36: 10.67 | AW36: =Q36*AV36+AT36 | AX36: =-22*T36 | AY36: -2.17 | AZ36: 0 | BA36: 19.99 | BB36: 0.5 | BC36: 3310 | BD36: 10287 | BF36: =BC36+BD36+BE36
A37: 45942 | B37: 日 | C37: \ | D37: 26.98 | F37: 0 | G37: 0 | H37: 26.98 | I37: 0.232 | J37: 0.099 | K37: 249 | L37: 200 | M37: =K37+L37 | N37: =Q37/M37 | O37: =P37-AI37 | P37: =Q37-T37-AZ37 | Q37: 93 | R37: 89 | S37: 1 | T37: 1 | U37: =T37/S37 | V37: 0 | W37: =Q37*D37 | X37: 38 | Y37: 24 | Z37: 9 | AA37: 18 | AB37: 1088 | AC37: 3670 | AD37: 47 | AE37: 4.2 | AF37: 44077 | AG37: 305 | AH37: =AG37/AF37 | AI37: 49 | AJ37: =AN37/AG37 | AK37: =AN37/(AI37*D37) | AL37: =AI37/AG37 | AM37: =AI37/P37 | AN37: 507.8 | AO37: =AN37/W37 | AP37: =AN37/AI37 | AQ37: 0 | AR37: =AS37-AP37 | AS37: 4.91 | AT37: =(AY37*AZ37)+(AR37*AI37)+(O37*AS37)+AX37-W37*AQ37 | AU37: =AT37/W37 | AV37: 10.67 | AW37: =Q37*AV37+AT37 | AX37: =-22*T37 | AY37: -2.17 | AZ37: 0 | BA37: 19.99 | BB37: 0.5 | BC37: 3310 | BD37: 10287 | BF37: =BC37+BD37+BE37
A38: 45943 | B38: 一 | C38: \ | D38: 26.98 | F38: 0 | G38: 0 | H38: 26.98 | I38: 0.232 | J38: 0.099 | K38: 249 | L38: 209 | M38: =K38+L38 | N38: =Q38/M38 | O38: =P38-AI38 | P38: =Q38-T38-AZ38 | Q38: 93 | R38: 89 | S38: 1 | T38: 1 | U38: =T38/S38 | V38: 0 | W38: =Q38*D38 | X38: 38 | Y38: 24 | Z38: 9 | AA38: 18 | AB38: 1088 | AC38: 3670 | AD38: 47 | AE38: 4.2 | AF38: 44077 | AG38: 305 | AH38: =AG38/AF38 | AI38: 49 | AJ38: =AN38/AG38 | AK38: =AN38/(AI38*D38) | AL38: =AI38/AG38 | AM38: =AI38/P38 | AN38: 507.8 | AO38: =AN38/W38 | AP38: =AN38/AI38 | AQ38: 0 | AR38: =AS38-AP38 | AS38: 4.91 | AT38: =(AY38*AZ38)+(AR38*AI38)+(O38*AS38)+AX38-W38*AQ38 | AU38: =AT38/W38 | AV38: 10.67 | AW38: =Q38*AV38+AT38 | AX38: =-22*T38 | AY38: -2.17 | AZ38: 0 | BA38: 19.99 | BB38: 0.5 | BC38: 3310 | BD38: 10287 | BF38: =BC38+BD38+BE38
A39: 45944 | B39: 二 | C39: \ | D39: 26.98 | F39: 0 | G39: 0 | H39: 26.98 | I39: 0.232 | J39: 0.099 | K39: 249 | L39: 209 | M39: =K39+L39 | N39: =Q39/M39 | O39: =P39-AI39 | P39: =Q39-T39-AZ39 | Q39: 93 | R39: 89 | S39: 1 | T39: 1 | U39: =T39/S39 | V39: 0 | W39: =Q39*D39 | X39: 38 | Y39: 24 | Z39: 9 | AA39: 18 | AB39: 1088 | AC39: 3670 | AD39: 47 | AE39: 4.2 | AF39: 44077 | AG39: 305 | AH39: =AG39/AF39 | AI39: 49 | AJ39: =AN39/AG39 | AK39: =AN39/(AI39*D39) | AL39: =AI39/AG39 | AM39: =AI39/P39 | AN39: 507.8 | AO39: =AN39/W39 | AP39: =AN39/AI39 | AQ39: 0 | AR39: =AS39-AP39 | AS39: 4.91 | AT39: =(AY39*AZ39)+(AR39*AI39)+(O39*AS39)+AX39-W39*AQ39 | AU39: =AT39/W39 | AV39: 10.67 | AW39: =Q39*AV39+AT39 | AX39: =-22*T39 | AY39: -2.17 | AZ39: 0 | BA39: 19.99 | BB39: 0.5 | BC39: 3310 | BD39: 10287 | BF39: =BC39+BD39+BE39
A40: 汇总 这一行不编辑，增加行 插入就行 | D40: 29.98 | M40: =SUM(M3:M39) | N40: =Q40/M40 | O40: =SUM(O3:O39) | P40: =SUM(P3:P39) | Q40: =SUM(Q3:Q39) | W40: =SUM(W3:W39) | AF40: =SUM(AF3:AF39) | AG40: =SUM(AG3:AG39) | AH40: =AG40/AF40 | AI40: =SUM(AI3:AI39) | AJ40: =AN40/AG40 | AK40: =AN40/(AI40*D40) | AL40: =AI40/AG40 | AM40: =AI40/P40 | AN40: =SUM(AN3:AN39) | AO40: =AN40/W40 | AP40: =AN40/AI40 | AT40: =SUM(AT3:AT39) | AU40: =AT40/W40 | AW40: =SUM(AW3:AW39) | AY40: =SUM(#REF!) | AZ40: =SUM(#REF!)

Sheet 日常跟踪表US--14天汇总
A1: 开始时间 | B1: 结束时间 | C1: 售价 | D1: 移动流量 | E1: PC流量 | F1: 总流量 | G1: 目标流量VS实际流量 | I1: 总转化率 | J1: 目标转化VS实际转化 | L1: 实际自然订单 | M1: 自然订单 | N1: 总订单 | O1: VC订单 | P1: 测评总出单 | Q1: 目标销量VS实际销量 | S1: 销售额 | T1: sif前三页关键词收录数量 | U1: 大类排名 | V1: 小类排名 | W1: 评分 | X1: 广告数据 | AT1: 广告分析与目标对比 | AX1: 广告分析与上个14天对比 | BA1: 毛利数据 | BD1: 目标毛利VS实际毛利 | BF1: CPC趋势VS广告曝光趋势VS自然流量占比趋势VS售价趋势（14天数据） | BI1: 站外 | BK1: 库存监控 | BP1: 点击量趋势VS售价趋势VS转化率趋势VS销量趋势VS库存趋势（14天数据） | BS1: 运营分析总结
G2: 目标流量 | H2: 与目标值对比偏差 | J2: 目标转化 | K2: 与目标值对比偏差 | Q2: 目标销量 | R2: 与目标值对比偏差 | X2: 曝光 | Y2: 目标曝光VS实际曝光 | AA2: 点击 | AB2: 目标点击VS实际点击 | AD2: 点击率 | AE2: 自然流量 | AF2: 订单 | AG2: CPC | AH2: ACOS | AI2: 广告转化 | AJ2: 目标转化VS实际转化 | AL2: 广告订单占比 | AM2: 目标广单占比VS实际广单占比 | AO2: 花费（$） | AP2: 目标花费VS实际花费 | AR2: 广告花费占比 | AS2: CPA | AT2: 曝光VS点击VS花费 | AV2: 点击VS转化VS花费 | AX2: CPC趋势VS广告曝光趋势VS自然流量占比趋势 | BA2: 退款率 | BB2: 总订单毛利P1$ | BC2: 总订单毛利率P1 | BD2: 目标毛利 | BE2: 与目标值对比偏差 | BI2: 站外毛利$ | BJ2: 站外出单 | BK2: VC仓库存 | BL2: 海外仓库存 | BM2: FBA仓 | BN2: 总库存 | BO2: 超90天以上的库存 | BS2: 分析给出根因（重点核心问题） | BT2: 调整方向和步骤 | BU2: 效果体现
Y3: 目标曝光 | Z3: 与目标值对比偏差 | AB3: 目标点击 | AC3: 与目标值对比偏差 | AJ3: 目标转化 | AK3: 与目标值对比偏差 | AM3: 目标广单占比 | AN3: 与目标值对比偏差 | AP3: 目标花费 | AQ3: 与目标值对比偏差 | AT3: 总结 | AU3: 建议应对方向 | AV3: 总结 | AW3: 建议应对方向 | AX3: 总结 | AY3: 可能得原因 | AZ3: 建议应对方向 | BF3: 总结 | BG3: 可能得原因 | BH3: 建议应对方向 | BP3: 总结 | BQ3: 可能得原因 | BR3: 建议应对方向
A4: =_xlfn.MINIFS('日常跟踪表US'!$A$3:$A$9713,'日常跟踪表US'!A3:A9713,'日常跟踪表US'!A3) | B4: =A4+13 | C4: =S4/N4 | D4: =SUM(OFFSET('日常跟踪表US'!$K$3,(ROW('日常跟踪表US'!K3)-3)*14,0,14,1)) | E4: =SUM(OFFSET('日常跟踪表US'!$L$3,(ROW('日常跟踪表US'!L3)-3)*14,0,14,1)) | F4: =SUM(OFFSET('日常跟踪表US'!$M$3,(ROW('日常跟踪表US'!M3)-3)*14,0,14,1)) | G4: 30000 | H4: =IF(F4/G4<0.9,"<90% （低流量）",IF(F4/G4<=1.2,"90%-120% （正常）","＞120%（高流量）")) | I4: =N4/F4 | J4: 0.1 | K4: =IF(I4/J4<0.8,"<80% （低转化）",IF(I4/J4<=1.2,"80%-120% （正常）","＞120%（过度转化）")) | L4: =SUM(OFFSET('日常跟踪表US'!$O$3,(ROW('日常跟踪表US'!O3)-3)*14,0,14,1)) | M4: =SUM(OFFSET('日常跟踪表US'!$P$3,(ROW('日常跟踪表US'!P3)-3)*14,0,14,1)) | N4: =SUM(OFFSET('日常跟踪表US'!$Q$3,(ROW('日常跟踪表US'!Q3)-3)*14,0,14,1)) | O4: =SUM(OFFSET('日常跟踪表US'!$R$3,(ROW('日常跟踪表US'!R3)-3)*14,0,14,1)) | P4: =SUM(OFFSET('日常跟踪表US'!$T$3,(ROW('日常跟踪表US'!T3)-3)*14,0,14,1)) | Q4: 3000 | R4: =IF(N4/Q4<0.8,"<80% （低卖）",IF(N4/Q4<=1.2,"80%-120% （正常）","＞120%（超卖）")) | S4: =SUM(OFFSET('日常跟踪表US'!$W$3,(ROW('日常跟踪表US'!W3)-3)*14,0,14,1)) | T4: {=_xlfn.XLOOKUP(B4,'日常跟踪表US'!A:A,'日常跟踪表US'!AB:AB)} | U4: {=_xlfn.XLOOKUP(B4,'日常跟踪表US'!A:A,'日常跟踪表US'!AC:AC)} | V4: {=_xlfn.XLOOKUP(B4,'日常跟踪表US'!A:A,'日常跟踪表US'!AD:AD)} | W4: {=_xlfn.XLOOKUP(B4,'日常跟踪表US'!A:A,'日常跟踪表US'!AE:AE)} | X4: =SUM(OFFSET('日常跟踪表US'!$AF$3,(ROW('日常跟踪表US'!AF3)-3)*14,0,14,1)) | Y4: 2000000 | Z4: =IF(X4/Y4<0.9,"<90% （低曝光）",IF(X4/Y4<=1.2,"90%-120% （正常）","＞120%（高曝光）")) | AA4: =SUM(OFFSET('日常跟踪表US'!$AG$3,(ROW('日常跟踪表US'!AG3)-3)*14,0,14,1)) | AB4: 8000 | AC4: =IF(AA4/AB4<0.9,"<90% （低点击）",IF(AA4/AB4<=1.2,"90%-120% （正常）","＞120%（高点击）")) | AD4: =AA4/X4 | AE4: =AA4 | AF4: =SUM(OFFSET('日常跟踪表US'!$AI$3,(ROW('日常跟踪表US'!AI3)-3)*14,0,14,1)) | AG4: =AO4/AA4 | AH4: =AO4/(AF4*C4) | AI4: =AF4/AA4 | AJ4: 0.15 | AK4: =IF(AI4/AJ4<0.9,"<90% （低转化）",IF(AI4/AJ4<=1.2,"90%-120% （正常）","＞120%（高转化）")) | AL4: =AF4/M4 | AM4: 0.4 | AN4: =IF(AL4/AM4<0.95,"<95% （自然单超额）",IF(AL4/AM4<=1.05,"95%-105% （正常）","＞105%（广单超额）")) | AO4: =SUM(OFFSET('日常跟踪表US'!$AN$3,(ROW('日常跟踪表US'!AN3)-3)*14,0,14,1)) | AP4: 12800 | AQ4: =IF(AO4/AP4<0.95,"<95% （低花费）",IF(AO4/AP4<=1.05,"95%-105% （正常）","＞105%（高花费）")) | AR4: =AO4/S4 | AS4: =AO4/AF4 | AT4: =Z4&AC4&AQ4 | AU4: =IF(AND(Z4="＞120%（高曝光）",AC4="＞120%（高点击）",AQ4="＞105%（高花费）")," 建议1.该入口的该位置上竞争力不足； 2.主图与产品不符",IF(AND(Z4="＞120%（高曝光）",AC4="<90% （低点击）",AQ4="＞105%（高花费）")," 建议1.弱相关入口切入 2.主图表现力不足 3.位置靠后，天然点击率低 4.评分太差或者价格过高",IF(AND(Z4="<90% （低曝光）",AC4="＞120%（高点击）",AQ4="<95% （低花费）")," 建议1.曝光入口小，竞争低-维持投入，建议使用宽泛匹配扩大曝光 2.广告预算不足(未能覆盖24小时)--提高预算 3.竞价过低--适当提高竞价，CTR的降幅小于CPC的增幅，则继续加大投入",IF(AND(Z4="<90% （低曝光）",AC4="<90% （低点击）",AQ4="<95% （低花费）"),"建议1.竟价太低，跑不出来曝光--提高竞价 2.入口过小--增加或扩大入口 3.产品质量评分很低--断货/评分下降/价格过高等","建议人工判断")))) | AV4: =AC4&AK4&AQ4 | AW4: =IF(AND(AC4="＞120%（高点击）",AK4="＞120%（高转化）",AQ4="＞105%（高花费）"),"建议1.CPC与入口质量不匹配-CPC高于目标值(如弱相关流 量采用了强相关的竞价等) 2.详情页竞争力不足-CVR低于目标值(价格过高/评分 下降/竞争对手活动/详情页被截流/页面描述与引流入口 不匹配等)",IF(AND(AC4="＞120%（高点击）",AK4="<90% （低转化）",AQ4="＞105%（高花费）"),"建议 1.CPC与入口质量不匹配-CPC高于目标值(如弱相关 流量采用了强相关的竞价等) 2.详情页竞争力不足-CVR低于目标值(价格过高/评分 下降/竞争对手活动/详情页被截流/页面描述与引流入 口不匹配等)",IF(AND(AC4="<90% （低点击）",AK4="＞120%（高转化）",AQ4="<95% （低花费）"),"建议1.扩充流量入口 增加曝光 2.考虑优化主图",IF(AND(AC4="<90% （低点击）",AK4="<90% （低转化）",AQ4="<95% （低花费）"),"建议看是否存在曝光不足，竞价过低的问题","需要人工判断")))) | BA4: =SUM(OFFSET('日常跟踪表US'!$AQ$3,(ROW('日常跟踪表US'!AQ3)-3)*14,0,14,1))/14 | BB4: =SUM(OFFSET('日常跟踪表US'!$AT$3,(ROW('日常跟踪表US'!AT3)-3)*14,0,14,1)) | BC4: =BB4/S4 | BD4: 4047 | BE4: =IF(BC4/BD4<0.95,"<95%（过低）",IF(BC4/BD4<=1.2,"95%-120% （正常）","＞120%（过高）")) | BI4: =SUM(OFFSET('日常跟踪表US'!$AY$3,(ROW('日常跟踪表US'!AY3)-3)*14,0,14,1)) | BJ4: =SUM(OFFSET('日常跟踪表US'!$AZ$3,(ROW('日常跟踪表US'!AZ3)-3)*14,0,14,1)) | BK4: {=_xlfn.XLOOKUP(B4,'日常跟踪表US'!A:A,'日常跟踪表US'!BC:BC)} | BL4: {=_xlfn.XLOOKUP(B4,'日常跟踪表US'!A:A,'日常跟踪表US'!BD:BD)} | BM4: {=_xlfn.XLOOKUP(B4,'日常跟踪表US'!A:A,'日常跟踪表US'!BE:BE)} | BN4: {=_xlfn.XLOOKUP(B4,'日常跟踪表US'!A:A,'日常跟踪表US'!BF:BF)} | BO4: {=_xlfn.XLOOKUP(B4,'日常跟踪表US'!A:A,'日常跟踪表US'!BG:BG)}
A5: =B4+1 | B5: =A5+13 | C5: =S5/N5 | D5: =SUM(OFFSET('日常跟踪表US'!$K$3,(ROW('日常跟踪表US'!K4)-3)*14,0,14,1)) | E5: =SUM(OFFSET('日常跟踪表US'!$L$3,(ROW('日常跟踪表US'!L4)-3)*14,0,14,1)) | F5: =SUM(OFFSET('日常跟踪表US'!$M$3,(ROW('日常跟踪表US'!M4)-3)*14,0,14,1)) | G5: 30000 | H5: =IF(F5/G5<0.9,"<90% （低流量）",IF(F5/G5<=1.2,"90%-120% （正常）","＞120%（高流量）")) | I5: =N5/F5 | J5: 0.1 | K5: =IF(I5/J5<0.8,"<80% （低转化））",IF(I5/J5<=1.2,"80%-120% （正常）","＞120%（过度转化）")) | L5: =SUM(OFFSET('日常跟踪表US'!$O$3,(ROW('日常跟踪表US'!O4)-3)*14,0,14,1)) | M5: =SUM(OFFSET('日常跟踪表US'!$P$3,(ROW('日常跟踪表US'!P4)-3)*14,0,14,1)) | N5: =SUM(OFFSET('日常跟踪表US'!$Q$3,(ROW('日常跟踪表US'!Q4)-3)*14,0,14,1)) | O5: =SUM(OFFSET('日常跟踪表US'!$R$3,(ROW('日常跟踪表US'!R4)-3)*14,0,14,1)) | P5: =SUM(OFFSET('日常跟踪表US'!$T$3,(ROW('日常跟踪表US'!T4)-3)*14,0,14,1)) | Q5: 3000 | R5: =IF(N5/Q5<0.8,"<80% （低卖）",IF(N5/Q5<=1.2,"80%-120% （正常）","＞120%（超卖）")) | S5: =SUM(OFFSET('日常跟踪表US'!$W$3,(ROW('日常跟踪表US'!W4)-3)*14,0,14,1)) | T5: {=_xlfn.XLOOKUP(B5,'日常跟踪表US'!A:A,'日常跟踪表US'!AB:AB)} | U5: {=_xlfn.XLOOKUP(B5,'日常跟踪表US'!A:A,'日常跟踪表US'!AC:AC)} | V5: {=_xlfn.XLOOKUP(B5,'日常跟踪表US'!A:A,'日常跟踪表US'!AD:AD)} | W5: {=_xlfn.XLOOKUP(B5,'日常跟踪表US'!A:A,'日常跟踪表US'!AE:AE)} | X5: =SUM(OFFSET('日常跟踪表US'!$AF$3,(ROW('日常跟踪表US'!AF4)-3)*14,0,14,1)) | Y5: 2000000 | Z5: =IF(X5/Y5<0.9,"<90% （低曝光）",IF(X5/Y5<=1.2,"90%-120% （正常）","＞120%（高曝光）")) | AA5: =SUM(OFFSET('日常跟踪表US'!$AG$3,(ROW('日常跟踪表US'!AG4)-3)*14,0,14,1)) | AB5: 8000 | AC5: =IF(AA5/AB5<0.9,"<90% （低点击）",IF(AA5/AB5<=1.2,"90%-120% （正常）","＞120%（高点击）")) | AD5: =AA5/X5 | AE5: =AA5 | AF5: =SUM(OFFSET('日常跟踪表US'!$AI$3,(ROW('日常跟踪表US'!AI4)-3)*14,0,14,1)) | AG5: =AO5/AA5 | AH5: =AO5/(AF5*C5) | AI5: =AF5/AA5 | AJ5: 0.15 | AK5: =IF(AI5/AJ5<0.9,"<90% （低转化）",IF(AI5/AJ5<=1.2,"90%-120% （正常）","＞120%（高转化）")) | AL5: =AF5/M5 | AM5: 0.4 | AN5: =IF(AL5/AM5<0.95,"<95% （自然单超额）",IF(AL5/AM5<=1.05,"95%-105% （正常）","＞105%（广单超额）")) | AO5: =SUM(OFFSET('日常跟踪表US'!$AN$3,(ROW('日常跟踪表US'!AN4)-3)*14,0,14,1)) | AP5: 12800 | AQ5: =IF(AO5/AP5<0.95,"<95% （低花费）",IF(AO5/AP5<=1.05,"95%-105% （正常）","＞105%（高花费）")) | AR5: =AO5/S5 | AS5: =AO5/AF5 | AT5: =Z5&AC5&AQ5 | AU5: =IF(AND(Z5="＞120%（高曝光）",AC5="＞120%（高点击）",AQ5="＞105%（高花费）")," 建议1.该入口的该位置上竞争力不足； 2.主图与产品不符",IF(AND(Z5="＞120%（高曝光）",AC5="<90% （低点击）",AQ5="＞105%（高花费）")," 建议1.弱相关入口切入 2.主图表现力不足 3.位置靠后，天然点击率低 4.评分太差或者价格过高",IF(AND(Z5="<90% （低曝光）",AC5="＞120%（高点击）",AQ5="<95% （低花费）")," 建议1.曝光入口小，竞争低-维持投入，建议使用宽泛匹配扩大曝光 2.广告预算不足(未能覆盖24小时)--提高预算 3.竞价过低--适当提高竞价，CTR的降幅小于CPC的增幅，则继续加大投入",IF(AND(Z5="<90% （低曝光）",AC5="<90% （低点击）",AQ5="<95% （低花费）"),"建议1.竟价太低，跑不出来曝光--提高竞价 2.入口过小--增加或扩大入口 3.产品质量评分很低--断货/评分下降/价格过高等","建议人工判断")))) | AV5: =AC5&AK5&AQ5 | AW5: 需要人工判断 | AX5: =IF(AG5-AG4<0, "CPC趋势下降", IF(AG5-AG4>0.1, "CPC趋势显著上涨", IF(AG5-AG4=0, "CPC趋势持平", "CPC趋势小幅度上涨")))&IF(X5-X4<0, "广告曝光趋势下降", IF(X5-X4=0, "广告曝光趋势持平", "广告曝光趋势上涨"))&IF(AE5-AE4<0, "自然流量占比趋势下降", IF(AE5-AE4=0, "自然流量占比趋势下降持平", "自然流量占比趋势下降上涨")) | AY5: =IF(AX5="CPC趋势显著上涨广告曝光趋势下降自然流量占比趋势下降", "付费与自然流量双萎缩，核心入口流量被竞品抢占，SEO/SEM双失效", IF(AX5="CPC趋势显著上涨广告曝光趋势下降自然流量占比趋势上升", "广告竞争激烈但品牌自然认知提升，用户主动搜索增加(如品牌词SEO优化见效)", IF(AX5="CPC趋势显著上涨广告曝光趋势持平自然流量占比趋势下降", "广告币强维持刀光但挤压自然流量(如过度竞价导致自然排名下滑)", IF(AX5="CPC趋势小幅度上涨广告曝光趋势下降自然流量占比趋势上升", "广告效率降低，但自然流量增长对冲风险(如优质内容带来病毒传播)", IF(AX5="CPC趋势持平广告曝光趋势下降自然流量占比趋势上升", "广告策略僵化，自然流量通过其他渠道(如社媒/KOL)补量", IF(AX5="CPC趋势下降广告曝光趋势上涨自然流量占比趋势下降", "广告效率提升但过度依赖付费流量，自然流量基础薄弱", IF(AX5="CPC趋势下降广告曝光趋势上涨自然流量占比趋势上升", "广告与自然流量形成正向循环(如广告带来新用户，自然分享反哺流量)", IF(AX5="CPC趋势持平广告曝光趋势持平自然流量占比趋势上升", "市场进入稳态竞争，自然流量逐步取代付费流量(如品牌忠诚度成型)", "人工判断")))))))) | AZ5: =IF(AX5="CPC趋势显著上涨广告曝光趋势下降自然流量占比趋势下降", "紧急排查流量入口(如搜索引擎权重/推荐算法变化)，启动备选渠道(社媒/联盟)", IF(AX5="CPC趋势显著上涨广告曝光趋势下降自然流量占比趋势上升", "维持广告基础曝光，加大内容营销/口碑运营，强化品牌词与长尾词布向", IF(AX5="CPC趋势显著上涨广告曝光趋势持平自然流量占比趋势下降", "调整竞价策略避免蚕食自然流量，优化页面相关性，修复SEO技术漏洞)", IF(AX5="CPC趋势小幅度上涨广告曝光趋势下降自然流量占比趋势上升", "将部分广告预算转向内容生产/用户运营，优化广告与自然流量的协同触点(如再营销))", IF(AX5="CPC趋势持平广告曝光趋势下降自然流量占比趋势上升", "重新分配广告预算至新兴渠道，建立自然流量与广告的交叉转化漏斗", IF(AX5="CPC趋势下降广告曝光趋势上涨自然流量占比趋势下降", "利用广告带来的短期流量红利，加速搭建用户留存体系(如会员/社群)", IF(AX5="CPC趋势下降广告曝光趋势上涨自然流量占比趋势上升", "放大成功模式，设计激励分享机制，优化UGC(用户生成内容)引导策略", IF(AX5="CPC趋势持平广告曝光趋势持平自然流量占比趋势上升", "逐步降低广告依赖度，将预算转向品牌建设/用户生命周期管理)", "人工判断")))))))) | BA5: =SUM(OFFSET('日常跟踪表US'!$AQ$3,(ROW('日常跟踪表US'!AQ4)-3)*14,0,14,1))/14 | BB5: =SUM(OFFSET('日常跟踪表US'!$AT$3,(ROW('日常跟踪表US'!AT4)-3)*14,0,14,1)) | BC5: =BB5/S5 | BD5: 4047 | BE5: =IF(BC5/BD5<0.95,"<95%（过低）",IF(BC5/BD5<=1.2,"95%-120% （正常）","＞120%（过高）")) | BF5: =IF(AG5-AG4<0, "CPC趋势下降", IF(AG5-AG4>0.1, "CPC趋势显著上涨", IF(AG5-AG4=0, "CPC趋势持平", "CPC趋势小幅度上涨")))&IF(X5-X4<0, "曝光趋势下降", IF(X5-X4=0, "曝光趋势持平", "曝光趋势上涨"))&IF(AE5-AE4<0, "自然流量占比趋势下降", IF(AE5-AE4=0, "自然流量占比趋势持平", "自然流量占比趋势上涨"))&IF(C5-C4<0, "售价趋势下降", IF(C5-C4=0, "售价趋势持平", "售价趋势上涨")) | BG5: =IF(BF5="CPC趋势显著上涨曝光趋势下降自然流量占比趋势下降售价趋势上涨", "售价提升导致转化率降低，广告竞争力减弱，自然流量被高价竞品截流", IF(BF5="CPC趋势显著上涨曝光趋势下降自然流量占比趋势上升售价趋势下降", "降价吸引自然搜索流量，但广告竞争激烈导致CPC飙升", IF(BF5="CPC趋势持平曝光趋势上涨自然流量占比趋势上升售价趋势上涨", "品牌溢价能力增强，用户主动搜索增加(高价策略筛选优质用户)", IF(BF5="CPC趋势下降曝光趋势上涨自然流量占比趋势下降售价趋势下降", "低价策略刺激广告点击，但自然流量被低价竞品压制", IF(BF5="CPC趋势下降曝光趋势持平自然流量占比趋势上升售价趋势持平", "价格稳定下广告效率优化，自然流量因复购/口碑增长", IF(BF5="CPC趋势上涨曝光趋势上涨自然流量占比趋势下降售价趋势下降", "降价引发需求激增，但广告竞下降争加剧且自然流量未同步响应(可能用户比价行为增加)", IF(BF5="CPC趋势持平曝光趋势下降自然流量占比趋势上升售价趋势上涨", "提价导致广告吸引力不足，但自然流量因品牌升级吸引高净值用户", IF(BF5="CPC趋势下降曝光趋势下降自然流量占比趋势下降售价趋势上涨", "提价幅度过大，广告与自然流量双输(用户流失至替代品)", "人工判断")))))))) | BH5: =IF(BF5="CPC趋势显著上涨曝光趋势下降自然流量占比趋势下降售价趋势上涨", "重新测算价格弹性，广告中强化价值主张(如赠品/服务)，修复自然流量SEO漏洞", IF(BF5="CPC趋势显著上涨曝光趋势下降自然流量占比趋势上升售价趋势下降", "集中预算投放高转化关键词，优化落地页促销信息，利用自然流量提升广告质量得分", IF(BF5="CPC趋势持平曝光趋势上涨自然流量占比趋势上升售价趋势上涨", "广告侧重精准人群触达(如回头客/高消费群体)，自然流量强化品牌内容教育", IF(BF5="CPC趋势下降曝光趋势上涨自然流量占比趋势下降售价趋势下降", "监控利润空间，设置价格底线;通过广告快速抢占市场同步优化自然流量价格锚定", IF(BF5="CPC趋势下降曝光趋势持平自然流量占比趋势上升售价趋势持平", "将广告节省的预算投入用户忠诚计划，自然流量加强UGC(用户生成内容)引导", IF(BF5="CPC趋势上涨曝光趋势上涨自然流量占比趋势下降售价趋势下降", "缩短广告转化路径，设置限时折扣标识;自然流量优化比价工具(如价格对比插件)", IF(BF5="CPC趋势持平曝光趋势下降自然流量占比趋势上升售价趋势上涨", "广告定向高收入人群，自然流量突出差异化服务(如VIP权益)，同步监控客单价变化", IF(BF5="CPC趋势下降曝光趋势下降自然流量占比趋势下降售价趋势上涨", "紧急进行价格AB测试，广告投放竟品关键词拦截流量，自然流量启动危机公关预案", "人工判断")))))))) | BI5: =SUM(OFFSET('日常跟踪表US'!$AY$3,(ROW('日常跟踪表US'!AY4)-3)*14,0,14,1)) | BJ5: =SUM(OFFSET('日常跟踪表US'!$AZ$3,(ROW('日常跟踪表US'!AZ4)-3)*14,0,14,1)) | BK5: {=_xlfn.XLOOKUP(B5,'日常跟踪表US'!A:A,'日常跟踪表US'!BC:BC)} | BL5: {=_xlfn.XLOOKUP(B5,'日常跟踪表US'!A:A,'日常跟踪表US'!BD:BD)} | BM5: {=_xlfn.XLOOKUP(B5,'日常跟踪表US'!A:A,'日常跟踪表US'!BE:BE)} | BN5: {=_xlfn.XLOOKUP(B5,'日常跟踪表US'!A:A,'日常跟踪表US'!BF:BF)} | BO5: {=_xlfn.XLOOKUP(B5,'日常跟踪表US'!A:A,'日常跟踪表US'!BG:BG)} | BP5: =IF(AA5-AA4>0.2,"点击量趋势暴涨",IF(AA5-AA4>=0.1,"点击量趋势显著上升",IF(AA5-AA4>0,"点击量趋势上升",IF(AA5-AA4=0,"点击量趋势持平",IF(AA5-AA4>=-0.05,"点击量趋势小幅下降","点击量趋势下降"))))&IF(C5-C4<0, "售价趋势下降", IF(C5-C4=0, "售价趋势持平", "售价趋势上升"))&IF(I5-I4>0.2,"转化率趋势大幅上升",IF(I5-I4>=0.05,"转化率趋势小幅上升",IF(I5-I4>0,"转化率趋势上升",IF(I5-I4=0,"转化率趋势持平",IF(I5-I4>=-0.2,"转化率趋势小幅下降","转化率趋势暴跌"))))&IF(N5-N4>0.2,"销量趋势暴涨",IF(N5-N4>=0.05,"销量趋势小幅上升",IF(N5-N4>0,"销量趋势上升",IF(N5-N4=0,"销量趋势持平",IF(N5-N4>=-0.2,"销量趋势小幅下降","销量趋势暴跌"))))&IF(BN5-BN4>0,"库存趋势上升",IF(BN5-BN4=0,"库存趋势持平",IF(BN5-BN4>=-0.05,"库存趋势缓慢下降",IF(BN5-BN4>=-0.1,"库存趋势下降","库存趋势快速下降"))))))) | BQ5: =IF(BP5="点击量趋势显著上升售价趋势下降转化率趋势上升销量趋势暴涨库存趋势快速下降", "促销活动成功(如限时折扣)，流量精准度与转化效率双高", IF(BP5="点击量趋势上升售价趋势持平转化率趋势下降销量趋势小幅上升库存趋势缓慢下降", "点击量增长但流量质量下滑(如泛流量涌入)，价格缺乏竞争力", IF(BP5="点击量趋势下降售价趋势上升转化率趋势下降销量趋势暴跌库存趋势持平", "提价幅度过大超出用户心理预期，同时流量获取能力衰退", IF(BP5="点击量趋势持平售价趋势下降转化率趋势上升销量趋势上升库存趋势下降", "降价策略有效激活存量流量，但未扩大新流量入口", IF(BP5="点击量趋势小幅下降售价趋势持平转化率趋势大幅上升销量趋势上升库存趋势快速下降", "流量精准度提升(如优化关键词)，转化漏斗效率改进", IF(BP5="点击量趋势暴涨售价趋势下降转化率趋势暴跌销量趋势小幅上升库存趋势缓慢下降", "超低价吸引大量点击但用户怀疑质量(如“低价陷阱“感知)", IF(BP5="点击量趋势上升售价趋势上升转化率趋势上升销量趋势上升库存趋势快速下降", "高端化策略成，品牌溢价能力增强且精准用户占比提升", IF(BP5="点击量趋势下降售价趋势下降转化率趋势小幅上升销量趋势持平库存趋势上升", "降价未触达目标用户(如渠道偏差)，库存积压导致系统降低曝光权重", "人工判断")))))))) | BR5: =IF(BP5="点击量趋势显著上升售价趋势下降转化率趋势上升销量趋势暴涨库存趋势快速下降", "启动库存预警，协调供应链补货;逐步回调售价至合理区间，延长流量红利期", IF(BP5="点击量趋势上升售价趋势持平转化率趋势下降销量趋势小幅上升库存趋势缓慢下降", "点击量增长但流量质量下滑(如泛流量涌入)，价格缺乏竞争力", IF(BP5="点击量趋势下降售价趋势上升转化率趋势下降销量趋势暴跌库存趋势持平", "提价幅度过大超出用户心理预期，同时流量获取能力衰退", IF(BP5="点击量趋势持平售价趋势下降转化率趋势上升销量趋势上升库存趋势下降", "降价策略有效激活存量流量，但未扩大新流量入口", IF(BP5="点击量趋势小幅下降售价趋势持平转化率趋势大幅上升销量趋势上升库存趋势快速下降", "流量精准度提升(如优化关键词)，转化漏斗效率改进", IF(BP5="点击量趋势暴涨售价趋势下降转化率趋势暴跌销量趋势小幅上升库存趋势缓慢下降", "超低价吸引大量点击但用户怀疑质量(如“低价陷阱“感知)", IF(BP5="点击量趋势上升售价趋势上升转化率趋势上升销量趋势上升库存趋势快速下降", "高端化策略成，品牌溢价能力增强且精准用户占比提升", IF(BP5="点击量趋势下降售价趋势下降转化率趋势小幅上升销量趋势持平库存趋势上升", "降价未触达目标用户(如渠道偏差)，库存积压导致系统降低曝光权重", "人工判断"))))))))
A6: =B5+1 | B6: =A6+13 | C6: =S6/N6 | D6: =SUM(OFFSET('日常跟踪表US'!$K$3,(ROW('日常跟踪表US'!K5)-3)*14,0,14,1)) | E6: =SUM(OFFSET('日常跟踪表US'!$L$3,(ROW('日常跟踪表US'!L5)-3)*14,0,14,1)) | F6: =SUM(OFFSET('日常跟踪表US'!$M$3,(ROW('日常跟踪表US'!M5)-3)*14,0,14,1)) | G6: 22500 | H6: =IF(F6/G6<0.9,"<90% （低流量）",IF(F6/G6<=1.2,"90%-120% （正常）","＞120%（高流量）")) | I6: =N6/F6 | J6: 0.1 | K6: =IF(I6/J6<0.8,"<80% （低转化）",IF(I6/J6<=1.2,"80%-120% （正常）","＞120%（过度转化）")) | L6: =SUM(OFFSET('日常跟踪表US'!$O$3,(ROW('日常跟踪表US'!O5)-3)*14,0,14,1)) | M6: =SUM(OFFSET('日常跟踪表US'!$P$3,(ROW('日常跟踪表US'!P5)-3)*14,0,14,1)) | N6: =SUM(OFFSET('日常跟踪表US'!$Q$3,(ROW('日常跟踪表US'!Q5)-3)*14,0,14,1)) | O6: =SUM(OFFSET('日常跟踪表US'!$R$3,(ROW('日常跟踪表US'!R5)-3)*14,0,14,1)) | P6: =SUM(OFFSET('日常跟踪表US'!$T$3,(ROW('日常跟踪表US'!T5)-3)*14,0,14,1)) | Q6: 2250 | R6: =IF(N6/Q6<0.8,"<80% （低卖）",IF(N6/Q6<=1.2,"80%-120% （正常）","＞120%（超卖）")) | S6: =SUM(OFFSET('日常跟踪表US'!$W$3,(ROW('日常跟踪表US'!W5)-3)*14,0,14,1)) | T6: {=_xlfn.XLOOKUP(B6,'日常跟踪表US'!A:A,'日常跟踪表US'!AB:AB)} | U6: {=_xlfn.XLOOKUP(B6,'日常跟踪表US'!A:A,'日常跟踪表US'!AC:AC)} | V6: {=_xlfn.XLOOKUP(B6,'日常跟踪表US'!A:A,'日常跟踪表US'!AD:AD)} | W6: {=_xlfn.XLOOKUP(B6,'日常跟踪表US'!A:A,'日常跟踪表US'!AE:AE)} | X6: =SUM(OFFSET('日常跟踪表US'!$AF$3,(ROW('日常跟踪表US'!AF5)-3)*14,0,14,1)) | Y6: 1500000 | Z6: =IF(X6/Y6<0.9,"<90% （低曝光）",IF(X6/Y6<=1.2,"90%-120% （正常）","＞120%（高曝光）")) | AA6: =SUM(OFFSET('日常跟踪表US'!$AG$3,(ROW('日常跟踪表US'!AG5)-3)*14,0,14,1)) | AB6: 6000 | AC6: =IF(AA6/AB6<0.9,"<90% （低点击）",IF(AA6/AB6<=1.2,"90%-120% （正常）","＞120%（高点击）")) | AD6: =AA6/X6 | AE6: =AA6 | AF6: =SUM(OFFSET('日常跟踪表US'!$AI$3,(ROW('日常跟踪表US'!AI5)-3)*14,0,14,1)) | AG6: =AO6/AA6 | AH6: =AO6/(AF6*C6) | AI6: =AF6/AA6 | AJ6: 0.15 | AK6: =IF(AI6/AJ6<0.9,"<90% （低转化）",IF(AI6/AJ6<=1.2,"90%-120% （正常）","＞120%（高转化）")) | AL6: =AF6/M6 | AM6: 0.4 | AN6: =IF(AL6/AM6<0.95,"<95% （自然单超额）",IF(AL6/AM6<=1.05,"95%-105% （正常）","＞105%（广单超额）")) | AO6: =SUM(OFFSET('日常跟踪表US'!$AN$3,(ROW('日常跟踪表US'!AN5)-3)*14,0,14,1)) | AP6: 9600 | AQ6: =IF(AO6/AP6<0.95,"<95% （低花费）",IF(AO6/AP6<=1.05,"95%-105% （正常）","＞105%（高花费）")) | AR6: =AO6/S6 | AS6: =AO6/AF6 | AT6: =Z6&AC6&AQ6 | AU6: =IF(AND(Z6="＞120%（高曝光）",AC6="＞120%（高点击）",AQ6="＞105%（高花费）")," 建议1.该入口的该位置上竞争力不足； 2.主图与产品不符",IF(AND(Z6="＞120%（高曝光）",AC6="<90% （低点击）",AQ6="＞105%（高花费）")," 建议1.弱相关入口切入 2.主图表现力不足 3.位置靠后，天然点击率低 4.评分太差或者价格过高",IF(AND(Z6="<90% （低曝光）",AC6="＞120%（高点击）",AQ6="<95% （低花费）")," 建议1.曝光入口小，竞争低-维持投入，建议使用宽泛匹配扩大曝光 2.广告预算不足(未能覆盖24小时)--提高预算 3.竞价过低--适当提高竞价，CTR的降幅小于CPC的增幅，则继续加大投入",IF(AND(Z6="<90% （低曝光）",AC6="<90% （低点击）",AQ6="<95% （低花费）"),"建议1.竟价太低，跑不出来曝光--提高竞价 2.入口过小--增加或扩大入口 3.产品质量评分很低--断货/评分下降/价格过高等","建议人工判断")))) | AV6: =AC6&AK6&AQ6 | AW6: 需要人工判断 | AX6: =IF(AG6-AG5<0, "CPC趋势下降", IF(AG6-AG5>0.1, "CPC趋势显著上涨", IF(AG6-AG5=0, "CPC趋势持平", "CPC趋势小幅度上涨")))&IF(X6-X5<0, "广告曝光趋势下降", IF(X6-X5=0, "广告曝光趋势持平", "广告曝光趋势上涨"))&IF(AE6-AE5<0, "自然流量占比趋势下降", IF(AE6-AE5=0, "自然流量占比趋势下降持平", "自然流量占比趋势下降上涨")) | AY6: =IF(AX6="CPC趋势显著上涨广告曝光趋势下降自然流量占比趋势下降", "付费与自然流量双萎缩，核心入口流量被竞品抢占，SEO/SEM双失效", IF(AX6="CPC趋势显著上涨广告曝光趋势下降自然流量占比趋势上升", "广告竞争激烈但品牌自然认知提升，用户主动搜索增加(如品牌词SEO优化见效)", IF(AX6="CPC趋势显著上涨广告曝光趋势持平自然流量占比趋势下降", "广告币强维持刀光但挤压自然流量(如过度竞价导致自然排名下滑)", IF(AX6="CPC趋势小幅度上涨广告曝光趋势下降自然流量占比趋势上升", "广告效率降低，但自然流量增长对冲风险(如优质内容带来病毒传播)", IF(AX6="CPC趋势持平广告曝光趋势下降自然流量占比趋势上升", "广告策略僵化，自然流量通过其他渠道(如社媒/KOL)补量", IF(AX6="CPC趋势下降广告曝光趋势上涨自然流量占比趋势下降", "广告效率提升但过度依赖付费流量，自然流量基础薄弱", IF(AX6="CPC趋势下降广告曝光趋势上涨自然流量占比趋势上升", "广告与自然流量形成正向循环(如广告带来新用户，自然分享反哺流量)", IF(AX6="CPC趋势持平广告曝光趋势持平自然流量占比趋势上升", "市场进入稳态竞争，自然流量逐步取代付费流量(如品牌忠诚度成型)", "人工判断")))))))) | AZ6: =IF(AX6="CPC趋势显著上涨广告曝光趋势下降自然流量占比趋势下降", "紧急排查流量入口(如搜索引擎权重/推荐算法变化)，启动备选渠道(社媒/联盟)", IF(AX6="CPC趋势显著上涨广告曝光趋势下降自然流量占比趋势上升", "维持广告基础曝光，加大内容营销/口碑运营，强化品牌词与长尾词布向", IF(AX6="CPC趋势显著上涨广告曝光趋势持平自然流量占比趋势下降", "调整竞价策略避免蚕食自然流量，优化页面相关性，修复SEO技术漏洞)", IF(AX6="CPC趋势小幅度上涨广告曝光趋势下降自然流量占比趋势上升", "将部分广告预算转向内容生产/用户运营，优化广告与自然流量的协同触点(如再营销))", IF(AX6="CPC趋势持平广告曝光趋势下降自然流量占比趋势上升", "重新分配广告预算至新兴渠道，建立自然流量与广告的交叉转化漏斗", IF(AX6="CPC趋势下降广告曝光趋势上涨自然流量占比趋势下降", "利用广告带来的短期流量红利，加速搭建用户留存体系(如会员/社群)", IF(AX6="CPC趋势下降广告曝光趋势上涨自然流量占比趋势上升", "放大成功模式，设计激励分享机制，优化UGC(用户生成内容)引导策略", IF(AX6="CPC趋势持平广告曝光趋势持平自然流量占比趋势上升", "逐步降低广告依赖度，将预算转向品牌建设/用户生命周期管理)", "人工判断")))))))) | BA6: =SUM(OFFSET('日常跟踪表US'!$AQ$3,(ROW('日常跟踪表US'!AQ5)-3)*14,0,14,1))/14 | BB6: =SUM(OFFSET('日常跟踪表US'!$AT$3,(ROW('日常跟踪表US'!AT5)-3)*14,0,14,1)) | BC6: =BB6/S6 | BD6: 3035 | BE6: =IF(BC6/BD6<0.95,"<95%（过低）",IF(BC6/BD6<=1.2,"95%-120% （正常）","＞120%（过高）")) | BF6: =IF(AG6-AG5<0, "CPC趋势下降", IF(AG6-AG5>0.1, "CPC趋势显著上涨", IF(AG6-AG5=0, "CPC趋势持平", "CPC趋势小幅度上涨")))&IF(X6-X5<0, "曝光趋势下降", IF(X6-X5=0, "曝光趋势持平", "曝光趋势上涨"))&IF(AE6-AE5<0, "自然流量占比趋势下降", IF(AE6-AE5=0, "自然流量占比趋势持平", "自然流量占比趋势上涨"))&IF(C6-C5<0, "售价趋势下降", IF(C6-C5=0, "售价趋势持平", "售价趋势上涨")) | BG6: =IF(BF6="CPC趋势显著上涨曝光趋势下降自然流量占比趋势下降售价趋势上涨", "售价提升导致转化率降低，广告竞争力减弱，自然流量被高价竞品截流", IF(BF6="CPC趋势显著上涨曝光趋势下降自然流量占比趋势上升售价趋势下降", "降价吸引自然搜索流量，但广告竞争激烈导致CPC飙升", IF(BF6="CPC趋势持平曝光趋势上涨自然流量占比趋势上升售价趋势上涨", "品牌溢价能力增强，用户主动搜索增加(高价策略筛选优质用户)", IF(BF6="CPC趋势下降曝光趋势上涨自然流量占比趋势下降售价趋势下降", "低价策略刺激广告点击，但自然流量被低价竞品压制", IF(BF6="CPC趋势下降曝光趋势持平自然流量占比趋势上升售价趋势持平", "价格稳定下广告效率优化，自然流量因复购/口碑增长", IF(BF6="CPC趋势上涨曝光趋势上涨自然流量占比趋势下降售价趋势下降", "降价引发需求激增，但广告竞下降争加剧且自然流量未同步响应(可能用户比价行为增加)", IF(BF6="CPC趋势持平曝光趋势下降自然流量占比趋势上升售价趋势上涨", "提价导致广告吸引力不足，但自然流量因品牌升级吸引高净值用户", IF(BF6="CPC趋势下降曝光趋势下降自然流量占比趋势下降售价趋势上涨", "提价幅度过大，广告与自然流量双输(用户流失至替代品)", "人工判断")))))))) | BH6: =IF(BF6="CPC趋势显著上涨曝光趋势下降自然流量占比趋势下降售价趋势上涨", "重新测算价格弹性，广告中强化价值主张(如赠品/服务)，修复自然流量SEO漏洞", IF(BF6="CPC趋势显著上涨曝光趋势下降自然流量占比趋势上升售价趋势下降", "集中预算投放高转化关键词，优化落地页促销信息，利用自然流量提升广告质量得分", IF(BF6="CPC趋势持平曝光趋势上涨自然流量占比趋势上升售价趋势上涨", "广告侧重精准人群触达(如回头客/高消费群体)，自然流量强化品牌内容教育", IF(BF6="CPC趋势下降曝光趋势上涨自然流量占比趋势下降售价趋势下降", "监控利润空间，设置价格底线;通过广告快速抢占市场同步优化自然流量价格锚定", IF(BF6="CPC趋势下降曝光趋势持平自然流量占比趋势上升售价趋势持平", "将广告节省的预算投入用户忠诚计划，自然流量加强UGC(用户生成内容)引导", IF(BF6="CPC趋势上涨曝光趋势上涨自然流量占比趋势下降售价趋势下降", "缩短广告转化路径，设置限时折扣标识;自然流量优化比价工具(如价格对比插件)", IF(BF6="CPC趋势持平曝光趋势下降自然流量占比趋势上升售价趋势上涨", "广告定向高收入人群，自然流量突出差异化服务(如VIP权益)，同步监控客单价变化", IF(BF6="CPC趋势下降曝光趋势下降自然流量占比趋势下降售价趋势上涨", "紧急进行价格AB测试，广告投放竟品关键词拦截流量，自然流量启动危机公关预案", "人工判断")))))))) | BI6: =SUM(OFFSET('日常跟踪表US'!$AY$3,(ROW('日常跟踪表US'!AY5)-3)*14,0,14,1)) | BJ6: =SUM(OFFSET('日常跟踪表US'!$AZ$3,(ROW('日常跟踪表US'!AZ5)-3)*14,0,14,1)) | BK6: {=_xlfn.XLOOKUP(B6,'日常跟踪表US'!A:A,'日常跟踪表US'!BC:BC)} | BL6: {=_xlfn.XLOOKUP(B6,'日常跟踪表US'!A:A,'日常跟踪表US'!BD:BD)} | BM6: {=_xlfn.XLOOKUP(B6,'日常跟踪表US'!A:A,'日常跟踪表US'!BE:BE)} | BN6: {=_xlfn.XLOOKUP(B6,'日常跟踪表US'!A:A,'日常跟踪表US'!BF:BF)} | BO6: {=_xlfn.XLOOKUP(B6,'日常跟踪表US'!A:A,'日常跟踪表US'!BG:BG)} | BP6: =IF(AA6-AA5>0.2,"点击量趋势暴涨",IF(AA6-AA5>=0.1,"点击量趋势显著上升",IF(AA6-AA5>0,"点击量趋势上升",IF(AA6-AA5=0,"点击量趋势持平",IF(AA6-AA5>=-0.05,"点击量趋势小幅下降","点击量趋势下降"))))&IF(C6-C5<0, "售价趋势下降", IF(C6-C5=0, "售价趋势持平", "售价趋势上升"))&IF(I6-I5>0.2,"转化率趋势大幅上升",IF(I6-I5>=0.05,"转化率趋势小幅上升",IF(I6-I5>0,"转化率趋势上升",IF(I6-I5=0,"转化率趋势持平",IF(I6-I5>=-0.2,"转化率趋势小幅下降","转化率趋势暴跌"))))&IF(N6-N5>0.2,"销量趋势暴涨",IF(N6-N5>=0.05,"销量趋势小幅上升",IF(N6-N5>0,"销量趋势上升",IF(N6-N5=0,"销量趋势持平",IF(N6-N5>=-0.2,"销量趋势小幅下降","销量趋势暴跌"))))&IF(BN6-BN5>0,"库存趋势上升",IF(BN6-BN5=0,"库存趋势持平",IF(BN6-BN5>=-0.05,"库存趋势缓慢下降",IF(BN6-BN5>=-0.1,"库存趋势下降","库存趋势快速下降"))))))) | BQ6: =IF(BP6="点击量趋势显著上升售价趋势下降转化率趋势上升销量趋势暴涨库存趋势快速下降", "促销活动成功(如限时折扣)，流量精准度与转化效率双高", IF(BP6="点击量趋势上升售价趋势持平转化率趋势下降销量趋势小幅上升库存趋势缓慢下降", "点击量增长但流量质量下滑(如泛流量涌入)，价格缺乏竞争力", IF(BP6="点击量趋势下降售价趋势上升转化率趋势下降销量趋势暴跌库存趋势持平", "提价幅度过大超出用户心理预期，同时流量获取能力衰退", IF(BP6="点击量趋势持平售价趋势下降转化率趋势上升销量趋势上升库存趋势下降", "降价策略有效激活存量流量，但未扩大新流量入口", IF(BP6="点击量趋势小幅下降售价趋势持平转化率趋势大幅上升销量趋势上升库存趋势快速下降", "流量精准度提升(如优化关键词)，转化漏斗效率改进", IF(BP6="点击量趋势暴涨售价趋势下降转化率趋势暴跌销量趋势小幅上升库存趋势缓慢下降", "超低价吸引大量点击但用户怀疑质量(如“低价陷阱“感知)", IF(BP6="点击量趋势上升售价趋势上升转化率趋势上升销量趋势上升库存趋势快速下降", "高端化策略成，品牌溢价能力增强且精准用户占比提升", IF(BP6="点击量趋势下降售价趋势下降转化率趋势小幅上升销量趋势持平库存趋势上升", "降价未触达目标用户(如渠道偏差)，库存积压导致系统降低曝光权重", "人工判断")))))))) | BR6: =IF(BP6="点击量趋势显著上升售价趋势下降转化率趋势上升销量趋势暴涨库存趋势快速下降", "启动库存预警，协调供应链补货;逐步回调售价至合理区间，延长流量红利期", IF(BP6="点击量趋势上升售价趋势持平转化率趋势下降销量趋势小幅上升库存趋势缓慢下降", "点击量增长但流量质量下滑(如泛流量涌入)，价格缺乏竞争力", IF(BP6="点击量趋势下降售价趋势上升转化率趋势下降销量趋势暴跌库存趋势持平", "提价幅度过大超出用户心理预期，同时流量获取能力衰退", IF(BP6="点击量趋势持平售价趋势下降转化率趋势上升销量趋势上升库存趋势下降", "降价策略有效激活存量流量，但未扩大新流量入口", IF(BP6="点击量趋势小幅下降售价趋势持平转化率趋势大幅上升销量趋势上升库存趋势快速下降", "流量精准度提升(如优化关键词)，转化漏斗效率改进", IF(BP6="点击量趋势暴涨售价趋势下降转化率趋势暴跌销量趋势小幅上升库存趋势缓慢下降", "超低价吸引大量点击但用户怀疑质量(如“低价陷阱“感知)", IF(BP6="点击量趋势上升售价趋势上升转化率趋势上升销量趋势上升库存趋势快速下降", "高端化策略成，品牌溢价能力增强且精准用户占比提升", IF(BP6="点击量趋势下降售价趋势下降转化率趋势小幅上升销量趋势持平库存趋势上升", "降价未触达目标用户(如渠道偏差)，库存积压导致系统降低曝光权重", "人工判断")))))))) | BS6: 1. 广告曝光和点击远低于目标值； 2. 总流量远低于目标流量； 3. 广告转化和总转化是达标的，关键在于扩充流量； | BT6: 增加广告花费，日均花费需达到685以上，每日点击目标428以上，每日广告订单目标64单，具体步骤如下： 1. 目前每日广告花费250左右，广告出单24单，出单主要集中在cat water fountain和cat water fountain stainless steel精准和广泛上，这部分出单占70%左右出单，先继续维持并增加效果好预算，目标每日36单； 2. 自动广告和其他低价广泛广告表现还可以，但仅占出单比例10%每日平均3单，这部分需要扩大自动广告的覆盖面以及增加更多广泛广告词，达到每日出单10单以上； 3. 品牌广告流量出单占据10%左右，平均每日3单，但视频广告出单较少，增加这部分投入，目标达到每日出单6单； 4. 展示型广告目前基本未覆盖，可重点拓展几个有优势的竞对，目标每日出单2-5单； 5. 相关类目关联流量拓展，目标每日2-5单；
A7: =B6+1 | B7: =A7+13 | C7: =S7/N7 | D7: =SUM(OFFSET('日常跟踪表US'!$K$3,(ROW('日常跟踪表US'!K6)-3)*14,0,14,1)) | E7: =SUM(OFFSET('日常跟踪表US'!$L$3,(ROW('日常跟踪表US'!L6)-3)*14,0,14,1)) | F7: =SUM(OFFSET('日常跟踪表US'!$M$3,(ROW('日常跟踪表US'!M6)-3)*14,0,14,1)) | G7: 22500 | H7: =IF(F7/G7<0.9,"<90% （低流量）",IF(F7/G7<=1.2,"90%-120% （正常）","＞120%（高流量）")) | I7: =N7/F7 | J7: 0.1 | K7: =IF(I7/J7<0.8,"<80% （低转化）",IF(I7/J7<=1.2,"80%-120% （正常）","＞120%（过度转化）")) | L7: =SUM(OFFSET('日常跟踪表US'!$O$3,(ROW('日常跟踪表US'!O6)-3)*14,0,14,1)) | M7: =SUM(OFFSET('日常跟踪表US'!$P$3,(ROW('日常跟踪表US'!P6)-3)*14,0,14,1)) | N7: =SUM(OFFSET('日常跟踪表US'!$Q$3,(ROW('日常跟踪表US'!Q6)-3)*14,0,14,1)) | O7: =SUM(OFFSET('日常跟踪表US'!$R$3,(ROW('日常跟踪表US'!R6)-3)*14,0,14,1)) | P7: =SUM(OFFSET('日常跟踪表US'!$T$3,(ROW('日常跟踪表US'!T6)-3)*14,0,14,1)) | Q7: 2250 | R7: =IF(N7/Q7<0.8,"<80% （低卖）",IF(N7/Q7<=1.2,"80%-120% （正常）","＞120%（超卖）")) | S7: =SUM(OFFSET('日常跟踪表US'!$W$3,(ROW('日常跟踪表US'!W6)-3)*14,0,14,1)) | T7: {=_xlfn.XLOOKUP(B7,'日常跟踪表US'!A:A,'日常跟踪表US'!AB:AB)} | U7: {=_xlfn.XLOOKUP(B7,'日常跟踪表US'!A:A,'日常跟踪表US'!AC:AC)} | V7: {=_xlfn.XLOOKUP(B7,'日常跟踪表US'!A:A,'日常跟踪表US'!AD:AD)} | W7: {=_xlfn.XLOOKUP(B7,'日常跟踪表US'!A:A,'日常跟踪表US'!AE:AE)} | X7: =SUM(OFFSET('日常跟踪表US'!$AF$3,(ROW('日常跟踪表US'!AF6)-3)*14,0,14,1)) | Y7: 1500000 | Z7: =IF(X7/Y7<0.9,"<90% （低曝光）",IF(X7/Y7<=1.2,"90%-120% （正常）","＞120%（高曝光）")) | AA7: =SUM(OFFSET('日常跟踪表US'!$AG$3,(ROW('日常跟踪表US'!AG6)-3)*14,0,14,1)) | AB7: 6000 | AC7: =IF(AA7/AB7<0.9,"<90% （低点击）",IF(AA7/AB7<=1.2,"90%-120% （正常）","＞120%（高点击）")) | AD7: =AA7/X7 | AE7: =AA7 | AF7: =SUM(OFFSET('日常跟踪表US'!$AI$3,(ROW('日常跟踪表US'!AI6)-3)*14,0,14,1)) | AG7: =AO7/AA7 | AH7: =AO7/(AF7*C7) | AI7: =AF7/AA7 | AJ7: 0.15 | AK7: =IF(AI7/AJ7<0.9,"<90% （低转化）",IF(AI7/AJ7<=1.2,"90%-120% （正常）","＞120%（高转化）")) | AL7: =AF7/M7 | AM7: 0.4 | AN7: =IF(AL7/AM7<0.95,"<95% （自然单超额）",IF(AL7/AM7<=1.05,"95%-105% （正常）","＞105%（广单超额）")) | AO7: =SUM(OFFSET('日常跟踪表US'!$AN$3,(ROW('日常跟踪表US'!AN6)-3)*14,0,14,1)) | AP7: 9600 | AQ7: =IF(AO7/AP7<0.95,"<95% （低花费）",IF(AO7/AP7<=1.05,"95%-105% （正常）","＞105%（高花费）")) | AR7: =AO7/S7 | AS7: =AO7/AF7 | AT7: =Z7&AC7&AQ7 | AU7: =IF(AND(Z7="＞120%（高曝光）",AC7="＞120%（高点击）",AQ7="＞105%（高花费）")," 建议1.该入口的该位置上竞争力不足； 2.主图与产品不符",IF(AND(Z7="＞120%（高曝光）",AC7="<90% （低点击）",AQ7="＞105%（高花费）")," 建议1.弱相关入口切入 2.主图表现力不足 3.位置靠后，天然点击率低 4.评分太差或者价格过高",IF(AND(Z7="<90% （低曝光）",AC7="＞120%（高点击）",AQ7="<95% （低花费）")," 建议1.曝光入口小，竞争低-维持投入，建议使用宽泛匹配扩大曝光 2.广告预算不足(未能覆盖24小时)--提高预算 3.竞价过低--适当提高竞价，CTR的降幅小于CPC的增幅，则继续加大投入",IF(AND(Z7="<90% （低曝光）",AC7="<90% （低点击）",AQ7="<95% （低花费）"),"建议1.竟价太低，跑不出来曝光--提高竞价 2.入口过小--增加或扩大入口 3.产品质量评分很低--断货/评分下降/价格过高等","建议人工判断")))) | AV7: =AC7&AK7&AQ7 | AW7: 需要人工判断 | AX7: =IF(AG7-AG6<0, "CPC趋势下降", IF(AG7-AG6>0.1, "CPC趋势显著上涨", IF(AG7-AG6=0, "CPC趋势持平", "CPC趋势小幅度上涨")))&IF(X7-X6<0, "广告曝光趋势下降", IF(X7-X6=0, "广告曝光趋势持平", "广告曝光趋势上涨"))&IF(AE7-AE6<0, "自然流量占比趋势下降", IF(AE7-AE6=0, "自然流量占比趋势下降持平", "自然流量占比趋势下降上涨")) | AY7: =IF(AX7="CPC趋势显著上涨广告曝光趋势下降自然流量占比趋势下降", "付费与自然流量双萎缩，核心入口流量被竞品抢占，SEO/SEM双失效", IF(AX7="CPC趋势显著上涨广告曝光趋势下降自然流量占比趋势上升", "广告竞争激烈但品牌自然认知提升，用户主动搜索增加(如品牌词SEO优化见效)", IF(AX7="CPC趋势显著上涨广告曝光趋势持平自然流量占比趋势下降", "广告币强维持刀光但挤压自然流量(如过度竞价导致自然排名下滑)", IF(AX7="CPC趋势小幅度上涨广告曝光趋势下降自然流量占比趋势上升", "广告效率降低，但自然流量增长对冲风险(如优质内容带来病毒传播)", IF(AX7="CPC趋势持平广告曝光趋势下降自然流量占比趋势上升", "广告策略僵化，自然流量通过其他渠道(如社媒/KOL)补量", IF(AX7="CPC趋势下降广告曝光趋势上涨自然流量占比趋势下降", "广告效率提升但过度依赖付费流量，自然流量基础薄弱", IF(AX7="CPC趋势下降广告曝光趋势上涨自然流量占比趋势上升", "广告与自然流量形成正向循环(如广告带来新用户，自然分享反哺流量)", IF(AX7="CPC趋势持平广告曝光趋势持平自然流量占比趋势上升", "市场进入稳态竞争，自然流量逐步取代付费流量(如品牌忠诚度成型)", "人工判断")))))))) | AZ7: =IF(AX7="CPC趋势显著上涨广告曝光趋势下降自然流量占比趋势下降", "紧急排查流量入口(如搜索引擎权重/推荐算法变化)，启动备选渠道(社媒/联盟)", IF(AX7="CPC趋势显著上涨广告曝光趋势下降自然流量占比趋势上升", "维持广告基础曝光，加大内容营销/口碑运营，强化品牌词与长尾词布向", IF(AX7="CPC趋势显著上涨广告曝光趋势持平自然流量占比趋势下降", "调整竞价策略避免蚕食自然流量，优化页面相关性，修复SEO技术漏洞)", IF(AX7="CPC趋势小幅度上涨广告曝光趋势下降自然流量占比趋势上升", "将部分广告预算转向内容生产/用户运营，优化广告与自然流量的协同触点(如再营销))", IF(AX7="CPC趋势持平广告曝光趋势下降自然流量占比趋势上升", "重新分配广告预算至新兴渠道，建立自然流量与广告的交叉转化漏斗", IF(AX7="CPC趋势下降广告曝光趋势上涨自然流量占比趋势下降", "利用广告带来的短期流量红利，加速搭建用户留存体系(如会员/社群)", IF(AX7="CPC趋势下降广告曝光趋势上涨自然流量占比趋势上升", "放大成功模式，设计激励分享机制，优化UGC(用户生成内容)引导策略", IF(AX7="CPC趋势持平广告曝光趋势持平自然流量占比趋势上升", "逐步降低广告依赖度，将预算转向品牌建设/用户生命周期管理)", "人工判断")))))))) | BA7: =SUM(OFFSET('日常跟踪表US'!$AQ$3,(ROW('日常跟踪表US'!AQ6)-3)*14,0,14,1))/14 | BB7: =SUM(OFFSET('日常跟踪表US'!$AT$3,(ROW('日常跟踪表US'!AT6)-3)*14,0,14,1)) | BC7: =BB7/S7 | BD7: 3035 | BE7: =IF(BC7/BD7<0.95,"<95%（过低）",IF(BC7/BD7<=1.2,"95%-120% （正常）","＞120%（过高）")) | BF7: =IF(AG7-AG6<0, "CPC趋势下降", IF(AG7-AG6>0.1, "CPC趋势显著上涨", IF(AG7-AG6=0, "CPC趋势持平", "CPC趋势小幅度上涨")))&IF(X7-X6<0, "曝光趋势下降", IF(X7-X6=0, "曝光趋势持平", "曝光趋势上涨"))&IF(AE7-AE6<0, "自然流量占比趋势下降", IF(AE7-AE6=0, "自然流量占比趋势持平", "自然流量占比趋势上涨"))&IF(C7-C6<0, "售价趋势下降", IF(C7-C6=0, "售价趋势持平", "售价趋势上涨")) | BG7: =IF(BF7="CPC趋势显著上涨曝光趋势下降自然流量占比趋势下降售价趋势上涨", "售价提升导致转化率降低，广告竞争力减弱，自然流量被高价竞品截流", IF(BF7="CPC趋势显著上涨曝光趋势下降自然流量占比趋势上升售价趋势下降", "降价吸引自然搜索流量，但广告竞争激烈导致CPC飙升", IF(BF7="CPC趋势持平曝光趋势上涨自然流量占比趋势上升售价趋势上涨", "品牌溢价能力增强，用户主动搜索增加(高价策略筛选优质用户)", IF(BF7="CPC趋势下降曝光趋势上涨自然流量占比趋势下降售价趋势下降", "低价策略刺激广告点击，但自然流量被低价竞品压制", IF(BF7="CPC趋势下降曝光趋势持平自然流量占比趋势上升售价趋势持平", "价格稳定下广告效率优化，自然流量因复购/口碑增长", IF(BF7="CPC趋势上涨曝光趋势上涨自然流量占比趋势下降售价趋势下降", "降价引发需求激增，但广告竞下降争加剧且自然流量未同步响应(可能用户比价行为增加)", IF(BF7="CPC趋势持平曝光趋势下降自然流量占比趋势上升售价趋势上涨", "提价导致广告吸引力不足，但自然流量因品牌升级吸引高净值用户", IF(BF7="CPC趋势下降曝光趋势下降自然流量占比趋势下降售价趋势上涨", "提价幅度过大，广告与自然流量双输(用户流失至替代品)", "人工判断")))))))) | BH7: =IF(BF7="CPC趋势显著上涨曝光趋势下降自然流量占比趋势下降售价趋势上涨", "重新测算价格弹性，广告中强化价值主张(如赠品/服务)，修复自然流量SEO漏洞", IF(BF7="CPC趋势显著上涨曝光趋势下降自然流量占比趋势上升售价趋势下降", "集中预算投放高转化关键词，优化落地页促销信息，利用自然流量提升广告质量得分", IF(BF7="CPC趋势持平曝光趋势上涨自然流量占比趋势上升售价趋势上涨", "广告侧重精准人群触达(如回头客/高消费群体)，自然流量强化品牌内容教育", IF(BF7="CPC趋势下降曝光趋势上涨自然流量占比趋势下降售价趋势下降", "监控利润空间，设置价格底线;通过广告快速抢占市场同步优化自然流量价格锚定", IF(BF7="CPC趋势下降曝光趋势持平自然流量占比趋势上升售价趋势持平", "将广告节省的预算投入用户忠诚计划，自然流量加强UGC(用户生成内容)引导", IF(BF7="CPC趋势上涨曝光趋势上涨自然流量占比趋势下降售价趋势下降", "缩短广告转化路径，设置限时折扣标识;自然流量优化比价工具(如价格对比插件)", IF(BF7="CPC趋势持平曝光趋势下降自然流量占比趋势上升售价趋势上涨", "广告定向高收入人群，自然流量突出差异化服务(如VIP权益)，同步监控客单价变化", IF(BF7="CPC趋势下降曝光趋势下降自然流量占比趋势下降售价趋势上涨", "紧急进行价格AB测试，广告投放竟品关键词拦截流量，自然流量启动危机公关预案", "人工判断")))))))) | BI7: =SUM(OFFSET('日常跟踪表US'!$AY$3,(ROW('日常跟踪表US'!AY6)-3)*14,0,14,1)) | BJ7: =SUM(OFFSET('日常跟踪表US'!$AZ$3,(ROW('日常跟踪表US'!AZ6)-3)*14,0,14,1)) | BK7: {=_xlfn.XLOOKUP(B7,'日常跟踪表US'!A:A,'日常跟踪表US'!BC:BC)} | BL7: {=_xlfn.XLOOKUP(B7,'日常跟踪表US'!A:A,'日常跟踪表US'!BD:BD)} | BM7: {=_xlfn.XLOOKUP(B7,'日常跟踪表US'!A:A,'日常跟踪表US'!BE:BE)} | BN7: {=_xlfn.XLOOKUP(B7,'日常跟踪表US'!A:A,'日常跟踪表US'!BF:BF)} | BO7: {=_xlfn.XLOOKUP(B7,'日常跟踪表US'!A:A,'日常跟踪表US'!BG:BG)} | BP7: =IF(AA7-AA6>0.2,"点击量趋势暴涨",IF(AA7-AA6>=0.1,"点击量趋势显著上升",IF(AA7-AA6>0,"点击量趋势上升",IF(AA7-AA6=0,"点击量趋势持平",IF(AA7-AA6>=-0.05,"点击量趋势小幅下降","点击量趋势下降"))))&IF(C7-C6<0, "售价趋势下降", IF(C7-C6=0, "售价趋势持平", "售价趋势上升"))&IF(I7-I6>0.2,"转化率趋势大幅上升",IF(I7-I6>=0.05,"转化率趋势小幅上升",IF(I7-I6>0,"转化率趋势上升",IF(I7-I6=0,"转化率趋势持平",IF(I7-I6>=-0.2,"转化率趋势小幅下降","转化率趋势暴跌"))))&IF(N7-N6>0.2,"销量趋势暴涨",IF(N7-N6>=0.05,"销量趋势小幅上升",IF(N7-N6>0,"销量趋势上升",IF(N7-N6=0,"销量趋势持平",IF(N7-N6>=-0.2,"销量趋势小幅下降","销量趋势暴跌"))))&IF(BN7-BN6>0,"库存趋势上升",IF(BN7-BN6=0,"库存趋势持平",IF(BN7-BN6>=-0.05,"库存趋势缓慢下降",IF(BN7-BN6>=-0.1,"库存趋势下降","库存趋势快速下降"))))))) | BQ7: =IF(BP7="点击量趋势显著上升售价趋势下降转化率趋势上升销量趋势暴涨库存趋势快速下降", "促销活动成功(如限时折扣)，流量精准度与转化效率双高", IF(BP7="点击量趋势上升售价趋势持平转化率趋势下降销量趋势小幅上升库存趋势缓慢下降", "点击量增长但流量质量下滑(如泛流量涌入)，价格缺乏竞争力", IF(BP7="点击量趋势下降售价趋势上升转化率趋势下降销量趋势暴跌库存趋势持平", "提价幅度过大超出用户心理预期，同时流量获取能力衰退", IF(BP7="点击量趋势持平售价趋势下降转化率趋势上升销量趋势上升库存趋势下降", "降价策略有效激活存量流量，但未扩大新流量入口", IF(BP7="点击量趋势小幅下降售价趋势持平转化率趋势大幅上升销量趋势上升库存趋势快速下降", "流量精准度提升(如优化关键词)，转化漏斗效率改进", IF(BP7="点击量趋势暴涨售价趋势下降转化率趋势暴跌销量趋势小幅上升库存趋势缓慢下降", "超低价吸引大量点击但用户怀疑质量(如“低价陷阱“感知)", IF(BP7="点击量趋势上升售价趋势上升转化率趋势上升销量趋势上升库存趋势快速下降", "高端化策略成，品牌溢价能力增强且精准用户占比提升", IF(BP7="点击量趋势下降售价趋势下降转化率趋势小幅上升销量趋势持平库存趋势上升", "降价未触达目标用户(如渠道偏差)，库存积压导致系统降低曝光权重", "人工判断")))))))) | BR7: =IF(BP7="点击量趋势显著上升售价趋势下降转化率趋势上升销量趋势暴涨库存趋势快速下降", "启动库存预警，协调供应链补货;逐步回调售价至合理区间，延长流量红利期", IF(BP7="点击量趋势上升售价趋势持平转化率趋势下降销量趋势小幅上升库存趋势缓慢下降", "点击量增长但流量质量下滑(如泛流量涌入)，价格缺乏竞争力", IF(BP7="点击量趋势下降售价趋势上升转化率趋势下降销量趋势暴跌库存趋势持平", "提价幅度过大超出用户心理预期，同时流量获取能力衰退", IF(BP7="点击量趋势持平售价趋势下降转化率趋势上升销量趋势上升库存趋势下降", "降价策略有效激活存量流量，但未扩大新流量入口", IF(BP7="点击量趋势小幅下降售价趋势持平转化率趋势大幅上升销量趋势上升库存趋势快速下降", "流量精准度提升(如优化关键词)，转化漏斗效率改进", IF(BP7="点击量趋势暴涨售价趋势下降转化率趋势暴跌销量趋势小幅上升库存趋势缓慢下降", "超低价吸引大量点击但用户怀疑质量(如“低价陷阱“感知)", IF(BP7="点击量趋势上升售价趋势上升转化率趋势上升销量趋势上升库存趋势快速下降", "高端化策略成，品牌溢价能力增强且精准用户占比提升", IF(BP7="点击量趋势下降售价趋势下降转化率趋势小幅上升销量趋势持平库存趋势上升", "降价未触达目标用户(如渠道偏差)，库存积压导致系统降低曝光权重", "人工判断")))))))) | BS7: 1. 广告曝光和点击远低于目标值； 2. 总流量远低于目标流量； 3. 广告转化和总转化是达标的，关键在于扩充流量； | BT7: 增加广告花费，日均花费需达到685以上，每日点击目标428以上，每日广告订单目标64单，具体步骤如下： 1. 目前每日广告花费250左右，广告出单24单，出单主要集中在cat water fountain和cat water fountain stainless steel精准和广泛上，这部分出单占70%左右出单，先继续维持并增加效果好预算，目标每日36单； 2. 自动广告和其他低价广泛广告表现还可以，但仅占出单比例10%每日平均3单，这部分需要扩大自动广告的覆盖面以及增加更多广泛广告词，达到每日出单10单以上； 3. 品牌广告流量出单占据10%左右，平均每日3单，但视频广告出单较少，增加这部分投入，目标达到每日出单6单； 4. 展示型广告目前基本未覆盖，可重点拓展几个有优势的竞对，目标每日出单2-5单； 5. 相关类目关联流量拓展，目标每日2-5单；
A13: 汇总 | D13: =SUM(D4:D12) | E13: =SUM(E4:E12) | F13: =SUM(F4:F12) | I13: =L13/F13 | L13: =SUM(L4:L12) | M13: =SUM(M4:M12) | N13: =SUM(N4:N12) | O13: =SUM(O4:O12) | P13: =SUM(P4:P12) | S13: =SUM(S4:S12) | X13: =SUM(X4:X12) | AA13: =SUM(AA4:AA12) | AD13: =AA13/X13 | AF13: =SUM(AF4:AF12) | AG13: =AO13/AA13 | AH13: =AO13/(AF13*C13) | AI13: =AF13/AA13 | AL13: =AF13/M13 | AO13: =SUM(AO4:AO12) | AR13: =AO13/S13 | AS13: =AO13/AF13 | BB13: =SUM(BB4:BB12) | BC13: =BB13/S13 | BI13: =SUM(BI4:BI12) | BJ13: =SUM(BJ4:BJ12) | BK13: =SUM(BK4:BK12) | BL13: =SUM(BL4:BL12) | BN13: =SUM(BN4:BN12)

Sheet 新品备货逻辑表
A1: 预估销量 | D1: 1月销量&安全库存： | F1: 73 | H1: 2月销量&安全库存： | J1: 174 | L1: 3月销量&安全库存： | N1: 294 | P1: 4月销量&安全库存： | R1: 406 | T1: 5月销量&安全库存： | V1: 518 | X1: 6月销量&安全库存： | Z1: 518 | AB1: 国内交期 | AC1: 物流时效 | AD1: 安全库存/天
D2: 第1个月第一周 | E2: 第1个月第二周 | F2: 第1个月第三周 | G2: 第1个月第四周 | H2: 第2个月第一周 | I2: 第2个月第二周 | J2: 第2个月第三周 | K2: 第2个月第四周 | L2: 第3个月第一周 | M2: 第3个月第二周 | N2: 第3个月第三周 | O2: 第3个月第四周 | P2: 第4个月第一周 | Q2: 第4个月第二周 | R2: 第4个月第三周 | S2: 第4个月第四周 | T2: 第5个月第一周 | U2: 第5个月第二周 | V2: 第5个月第三周 | W2: 第5个月第四周 | X2: 第6个月第一周 | Y2: 第6个月第二周 | Z2: 第6个月第三周 | AA2: 第6个月第四周 | AB2: 7 | AC2: 30 | AD2: 30
D3: =F1/30*7 | E3: =F1/30*7 | F3: =F1/30*7 | G3: =F1/30*7 | H3: =J1/30*7 | I3: =J1/30*7 | J3: =J1/30*7 | K3: =J1/30*7 | L3: =N1/30*7 | M3: =N1/30*7 | N3: =N1/30*7 | O3: =N1/30*7 | P3: =R1/30*7 | Q3: =R1/30*7 | R3: =R1/30*7 | S3: =R1/30*7 | T3: =V1/30*7 | U3: =V1/30*7 | V3: =V1/30*7 | W3: =V1/30*7 | X3: =Z1/30*7 | Y3: =Z1/30*7 | Z3: =Z1/30*7 | AA3: =Z1/30*7
A4: 实际销量
A5: 对比差额 | D5: =D4-D3 | E5: =E4-E3 | F5: =F4-F3 | G5: =G4-G3 | H5: =H4-H3 | I5: =I4-I3 | J5: =J4-J3 | K5: =K4-K3 | ... AA5: =AA4-AA3
A6: 备货轴 | B6: 备&发&到时间轴 | D6: 第1个月第一周 | E6: 第1个月第二周 | F6: 第1个月第三周 | G6: 第1个月第四周 | H6: 第2个月第一周 | I6: 第2个月第二周 | J6: 第2个月第三周 | K6: 第2个月第四周 | L6: 第3个月第一周 | M6: 第3个月第二周 | N6: 第3个月第三周 | O6: 第3个月第四周 | P6: 第4个月第一周 | Q6: 第4个月第二周 | R6: 第4个月第三周 | S6: 第4个月第四周 | T6: 第5个月第一周 | U6: 第5个月第二周 | V6: 第5个月第三周 | W6: 第5个月第四周 | X6: 第6个月第一周 | Y6: 第6个月第二周 | Z6: 第6个月第三周 | AA6: 第6个月第四周 | AB6: 第7个月第一周 | AC6: 第7个月第二周 | AD6: 第7个月第三周 | AE6: 第7个月第四周 | AF6: 第8个月第一周 | AG6: 第8个月第二周 | AH6: 第8个月第三周 | AI6: 第8个月第四周
B7: 首单备货量 | C7: =J1+F1+N1-1 | K7: 第二次备货量 | P7: 第三次备货量 | U7: 第四次备货量
B8: 验证备货量 | K8: =S16+T16+U16+V16 | P8: =W16+X16+Y16+Z16 | U8: =AA16+AB16+AC16+AD16
A9: 发货轴 | B9: 发货时间轴 | J9: 首批单二次发货 | M9: 第二次备货的发货 | R9: 第三次备货的发货 | W9: 第四次备货的发货
B10: 应发货数量 | D10: =(F1/30)*(AD3+7) | E10: =E3 | F10: =F3 | G10: =G3 | H10: =H3 | I10: =I3 | J10: =J3 | K10: =K3 | L10: =L3 | ... AA10: =AA3
B11: 实发数量 | D11: 306 | J11: =C7-D11 | M11: =K8 | R11: =P8 | W11: =U8
B12: 验证发货数据
A13: 到货轴 | B13: 到货时间轴 | H13: 首批第一次到货开售时间 | O13: 首批第二次到货开售时间 | R13: 第二批备货到货开售 | V13: 第三批备货到货开售 | Z13: 第四批备货到货开售 | AD13: 第五批备货到货开售
B14: 实际到货数 | H14: 306 | O14: =J11 | R14: =M11 | V14: =R11 | Z14: =W11
A15: 销售计划轴 | B15: 销售时间轴 | H15: 第1个月第一周 | I15: 第1个月第二周 | J15: 第1个月第三周 | K15: 第1个月第四周 | L15: 第2个月第一周 | M15: 第2个月第二周 | N15: 第2个月第三周 | O15: 第2个月第四周 | P15: 第3个月第一周 | Q15: 第3个月第二周 | R15: 第3个月第三周 | S15: 第3个月第四周 | T15: 第4个月第一周 | U15: 第4个月第二周 | V15: 第4个月第三周 | W15: 第4个月第四周 | X15: 第5个月第一周 | Y15: 第5个月第二周 | Z15: 第5个月第三周 | AA15: 第5个月第四周 | AB15: 第6个月第一周 | AC15: 第6个月第二周 | AD15: 第6个月第三周 | AE15: 第6个月第四周
B16: 销售数量 | H16: =D3 | I16: =E3 | J16: =F3 | K16: =G3 | L16: =H3 | M16: =I3 | N16: =J3 | O16: =K3 | ... AE16: =AA3
A17: 结余库存
A18: 应有安全库数量 | H18: =F1 | L18: =J1
A19: 安全库存剩余

Sheet 后续补货计划表
A1: 基础资料 | I1: 库存信息 | S1: 备货量参考数据 | AL1: 发货需求
A2: 申请备货日期 | B2: 账号 | C2: 站点 | D2: Asin | E2: 系统SKU | F2: 产品中文名 | G2: 产品定位 | H2: 采购价 | I2: 工厂余货（采购中） | J2: VC在途数量 | K2: 海外仓库存数量 | L2: VC亚马逊仓数量 | M2: 总库存数量 | N2: 一周销量 | O2: 两周销量 | P2: 当月销量 | Q2: 当下在售产品的利润率 | R2: 产品退款率 | S2: 加权销量（日均） | T2: 根据历史数据该产品到货时间段的销量预估（平均/天） | U2: 运输方式 | V2: 接收仓 | W2: 预计发货时间 | X2: 预计到货时间 | Y2: 运输时间 | Z2: 采购天数 | AA2: 上架天数 | AB2: 安全天数 | AC2: 在途+在库可售天数 | AD2: 本次备货可售天数 | AE2: 申请备货数量 | AF2: 申请备货总金额 | AG2: 历史是否申请过折扣 清库等 | AH2: 店铺库容 | AI2: 最终备货数量 | AJ2: 最终的备货金额 | AK2: 备注 | AL2: 发货计划（写清楚什么阶段发多少货走什么渠道，一次备货需在一个月内发完）
A3: 45579 | B3: VC | C3: US | D3: B09DSVFNRW | E3: BE-0004C | F3: 3.2L不锈钢水龙头饮水机-美规 | G3: 战略款 | H3: 70 | I3: 0 | J3: 0 | K3: 0 | L3: 0 | M3: =I3+J3+K3+L3 | N3: 2675 | O3: 5350 | P3: 10000 | Q3: 0.08 | R3: 0.042 | S3: =N3/7*0.5+O3/14*0.3+P3/30*0.2 | T3: 30 | U3: 慢船 | V3: 直发海外仓 | W3: 45590 | X3: =W3+Y3 | Y3: 40 | Z3: 15 | AA3: 0 | AB3: =Y3+Z3 | AC3: =(K3+J3)/S3 | AD3: =AE3/S3 | AE3: 19200 | AF3: =AE3*H3 | AG3: 否 | AH3: - | AI3: 19200 | AJ3: 1344000 | AL3: 计划10.25发货4800个慢船，预计12.04到海外仓； 计划11.01发货4800个慢船，预计12.10到海外仓； 计划11.08发货4800个慢船，预计12.18到海外仓； 计划11.15发货4800个慢船，预计12.20到海外仓；
A6: 申请备货日期 | B6: 账号 | C6: 站点 | D6: Asin | E6: 系统SKU | F6: 产品中文名 | G6: 产品定位 | H6: 采购价 | I6: 工厂余货（采购中） | J6: FBA在途数量 | K6: FBA在库数量 | L6: 第三方海外仓数量 | M6: 总库存数量 | N6: 一周销量 | O6: 两周销量 | P6: 当月销量 | Q6: 当下在售产品的利润率 | R6: 产品退款率 | S6: 加权销量（日均） | T6: 根据历史数据该产品到货时间段的销量预估（平均/天） | U6: 运输方式 | V6: 接收仓 | W6: 预计发货时间 | X6: 预计到货时间 | Y6: 运输时间 | Z6: 采购天数 | AA6: 上架天数 | AB6: 安全天数 | AC6: 在途+在库可售天数 | AD6: 本次备货可售天数 | AE6: 申请备货数量 | AF6: 申请备货总金额 | AG6: 历史是否申请过折扣 清库等 | AH6: 店铺库容 | AI6: 最终备货数量 | AJ6: 最终的备货金额 | AK6: 备注 | AL6: 发货需求（分别在什么时间段发走多少数量）/考虑旺季三倍仓租
A7: 45579 | B7: SC | C7: US | D7: B09DSVFNRW | E7: BE-0004C | F7: 3.2L不锈钢水龙头饮水机-美规 | G7: 战略款 | H7: 70 | I7: 0 | J7: 8848 | K7: 2561 | L7: 0 | M7: =I7+J7+K7+L7 | N7: 789 | O7: 1769 | P7: 5800 | Q7: 0.0266 | R7: 0.042 | S7: =N7/7*0.5+O7/14*0.3+P7/30*0.2 | T7: 30 | U7: 慢船 | V7: 海外仓发FBA仓 | W7: 45590 | X7: =W7+Y7 | Y7: 40 | Z7: 15 | AA7: 0 | AB7: =Y7+Z7 | AC7: =(K7+J7)/S7 | AD7: =AE7/S7 | AE7: 7200 | AF7: =AE7*H7 | AG7: 否 | AH7: - | AI7: 7200 | AJ7: 504000 | AL7: 计划10.25发货2400个慢船，预计12.04到FBA仓； 计划11.01发货2400个慢船，预计12.10到FBA仓； 计划11.08发货2400个慢船，预计12.18到FBA仓；

Sheet 站外计划跟进表
A1: 站外计划出单节奏
A2: 时间 | B2: 45625 | C2: 45626 | D2: 45627 | E2: 45628 | F2: 45629 | G2: 45630 | H2: 45631 | I2: 45632 | J2: 45633 | K2: 45634 | L2: 45635 | M2: 45636 | N2: 45637 | O2: 45638 | P2: 45639 | Q2: 45640 | R2: 45641 | S2: 45642 | T2: 45643 | U2: 45644 | V2: 45645 | W2: 45646 | X2: 45647 | Y2: 45648 | Z2: 45649 | AA2: 45650 | AB2: 45651 | AC2: 45652 | AD2: 45653 | AE2: 45654
A3: 服务商 | B3: 周五 | C3: 周六 | D3: 周天 | E3: 周一 | F3: 周二 | G3: 周三 | H3: 周四 | I3: 周五 | J3: 周六 | K3: 周天 | L3: 周一 | M3: 周二 | N3: 周三 | O3: 周四 | P3: 周五 | Q3: 周六 | R3: 周天 | S3: 周一 | T3: 周二 | U3: 周三 | V3: 周四 | W3: 周五 | X3: 周六 | Y3: 周天 | Z3: 周一 | AA3: 周二 | AB3: 周三 | AC3: 周四 | AD3: 周五 | AE3: 周六
A4: A出单量 | B4: 30 | C4: 10 | D4: 5 | E4: 1 | F4: 1
A5: B出单量 | B5: 15 | C5: 6 | D5: 2 | E5: 1 | F5: 1
A6: C出单量 | B6: / | C6: 35 | D6: 10 | E6: 5 | F6: 1
A7: D出单量 | B7: / | C7: 20 | D7: 8 | E7: 2 | F7: 1 | O7: 1
A8: E出单量 | B8: / | C8: / | D8: 30 | E8: 10 | F8: 5 | G8: 1
A9: F出单量 | B9: / | C9: / | D9: / | E9: 25 | F9: 10 | G9: 3 | H9: 1 | I9: 1 | J9: 1 | K9: 1
A10: G出单量 | B10: / | C10: / | D10: / | E10: / | F10: / | G10: /
A11: 汇总出单量 | B11: =SUM(B4:B10) | C11: =SUM(C4:C10) | D11: =SUM(D4:D10) | E11: =SUM(E4:E10) | F11: =SUM(F4:F10) | G11: =SUM(G4:G10) | H11: =SUM(H4:H10) | I11: =SUM(I4:I10) | ... AC11: =SUM(AC4:AC10) | AD11: 0 | AE11: 0
A14: 站外投放实际出单节奏
A15: 时间 | B15: 45625 | C15: 45626 | D15: 45627 | E15: 45628 | F15: 45629 | G15: 45630 | H15: 45631 | I15: 45632 | J15: 45633 | K15: 45634 | L15: 45635 | M15: 45636 | N15: 45637 | O15: 45638 | P15: 45639 | Q15: 45640 | R15: 45641 | S15: 45642 | T15: 45643 | U15: 45644 | V15: 45645 | W15: 45646 | X15: 45647 | Y15: 45648 | Z15: 45649 | AA15: 45650 | AB15: 45651 | AC15: 45652 | AD15: 45653 | AE15: 45654
A16: 服务商 | B16: 周五 | C16: 周六 | D16: 周天 | E16: 周一 | F16: 周二 | G16: 周三 | H16: 周四 | I16: 周五 | J16: 周六 | K16: 周天 | L16: 周一 | M16: 周二 | N16: 周三 | O16: 周四 | P16: 周五 | Q16: 周六 | R16: 周天 | S16: 周一 | T16: 周二 | U16: 周三 | V16: 周四 | W16: 周五 | X16: 周六 | Y16: 周天 | Z16: 周一 | AA16: 周二 | AB16: 周三 | AC16: 周四 | AD16: 周五 | AE16: 周六
A17: A出单量
A18: B出单量
A19: C出单量
A20: D出单量
A21: E出单量
A22: F出单量
A23: G出单量
A24: 汇总出单量 | B24: 0 | C24: 0 | D24: 0 | E24: 0 | F24: 0 | G24: 0 | H24: 0 | I24: 0 | J24: 0 | K24: 0 | L24: 0 | M24: 0 | N24: 0 | O24: 0 | P24: 0 | Q24: 0 | R24: 0 | S24: 0 | T24: 0 | U24: 0 | V24: 0 | W24: 0 | X24: 0 | Y24: 0 | Z24: 0 | AA24: 0 | AB24: 0 | AC24: 0 | AD24: 0 | AE24: 0

Sheet 刷单节奏跟进表
A1: 计划刷单节奏跟进表
A2: 时间 | B2: 45716 | C2: 45717 | D2: 45718 | E2: 45719 | F2: 45720 | G2: 45721 | H2: 45722 | I2: 45723 | J2: 45724 | K2: 45725 | L2: 45726 | M2: 45727 | N2: 45728 | O2: 45729
A3: 指标 | B3: 周五 | C3: 周六 | D3: 周天 | E3: 周一 | F3: 周二 | G3: 周三 | H3: 周四 | I3: 周五 | J3: 周六 | K3: 周天 | L3: 周一 | M3: 周二 | N3: 周三 | O3: 周四
A4: 计划刷单数量 | B4: 5 | C4: 5 | D4: 5 | E4: 5 | F4: 7 | G4: 9 | H4: 10 | I4: 10 | J4: 15 | K4: 15 | L4: 15
A5: 实际刷单数量
A6: 竞对转化率 | B6: 0.15
A7: 类目转化率 | B7: 0.12
A8: 目标转化率 | B8: 0.12 | C8: 0.13 | D8: 0.15 | E8: 0.15 | F8: 0.16 | G8: 0.16 | H8: 0.18
A9: 实际转化率
A10: 是否需要补单

Sheet 广告须知
A1: 投放广告须知
A2: 投放广告的核心思维：在做好listing转化的前提下，最大范围覆盖精准流量，排除无效流量，占领点击率高的广告位，让好的词获得更多曝光，不好的词控制曝光，最终实现自然订单最大化
A3: 树立正确的广告认知 | B3: (1)广告只是性价比较高的引流工具 | C3: 不同流量入口的类目对广告侧重不同，部分类目更适合直接低价低广告
B4: (2)只能锦上添花，不会雪中送炭 | C4: listing基础不好，是不可能只靠广告盘活的
B5: (3)好的广告打法是测试出来的，不是模仿出来的 | C5: 方法可以大胆去尝试，但是仍然要按照实际情况调整
B6: (4)广告是动态的，不是一劳永逸的 | C6: 广告生态环境变化很大，随着市场环境而改变。新品要不断尝试不同广告位置，稳定的产品要不断尝试优化CPC
B7: (5)最重要是要清楚自己开广告的目的 | C7: 不同的目的广告的打法不同，关注的指标数据也不同。打自然位置的广告主要关注CTR、CVR和位置上升情况；打长尾和拓单的广告主要关注广告本身可不可以赚钱（利润率大于Acos） 影响广告决策的核心因素：产品定位+广告目的+词的竞争情况 Campaign命名建议：SKU-关键词-匹配类型-广告目的，如：ABZ-01-iphone case-Exact-首行抢位
A8: 广告的作用 | B8: (1)快速提升关键词排名，SP广告有助于提升关键词自然排名 | C8: 和自然排名高度相关的指标是点击率和点击量，能否长期稳住自然排名的指标是转化率。 SP广告中的首行广告对自然位影响最大，其次是其余位置
B9: (2)开发产品，增加变体 | C9: 可以从领星ERP或广告搜索词报告里的客户搜索词里挖掘用户需求 Tips：定期（每个月）整理搜索词报告里的客户搜索词
B10: (3)快速获得流量入口 | C10: 亚马逊3大主要流量入口：关键词搜索(SP/SBV)，产品页面(SP/ASIN)，目标消费人群定位(SD/DSP)
B11: (4)提升品牌知名度，增加用户对品牌的心理暗示 | C11: 营销界通行一个“七次法则”，即潜在顾客平均只有在接收广告宣传信息七次以上才可能考虑发生购买行为，所以SB头条广告的主要作用不应是盈利，而是增加曝光
B12: (5)新品测款，测款：快速测试市场反应，用户喜好 | C12: Tips：用手动广告精准匹配模式测款， 不同颜色的变体，开同样的位置，每种卡首页第二位广告持续一周 固定竞价的情况下，bid调高，先出高bid再下调至首页第二位
B13: (6)增加账号安全等级 | C13: 毕竟花了钱的
B14: (7)指导“爆款”运作方式 | C14: (a)爆款是指，躺赚的不依赖广告的产品。如长期依赖广告的产品，不适合继续做下去。是否依赖的判断依据是：稳定销量后，广告订单占比是否超过30-40%（竞争激烈的类目） (b)依靠广告数据去优化listing，点击率至少0.3%，0.8%算优秀
B15: (8)检测listing是否被A9收录 | C15: 利用自动广告检验文案质量，检查从自动广告发散出来的asin和关键词是否相关 (a)如果发散asin和产品跑偏了，就立马停下来优化； (b)太多场景词，太泛的人群词的话，要精减Title和ST，新品烧不起
A16: 适合/不适合用广告当做主要推广方法的产品 | B16: ✘超低单价的产品，除非转化率做得非常好 | C16: 打广告就容易没利润，最好周期性开广告稳位置，然后关广告获取利润
B17: ✘血海产品 | C17: 血海指的是一个关键词下有10w+的listing且CPC很高，但如果对单量要求不高，也OK
B18: ✘转化率超低的产品
B19: ✘好评量少，整个页面优化很差 | C19: 转化率太低
B20: ✘利润低的产品 | C20: 尽量靠自然流量
B21: ✘自发货产品 | C21: 但是可以用广告测款
B22: ✘小众冷门产品 | C22: 市场太小，流量太小
B23: ✔高客单价产品 | C23: 高客单产品广告占比一般较低
B24: ✔高利润产品 | C24: 该类产品适合高定价高广告，用预算规模拉开和对手的差距
B25: ✔多变体产品 | C25: 标品：测款之后，开1~2个有更大机会抢占自然位的变体，其余变体也可以低投入打对应属性(如颜色、尺寸等) 非标品：按照Acos而定，可以海量铺长尾流量，瀑布流+赛马跑法，不断筛选优质广告组
B26: ✔自主研发，微创新产品（本身具有一定市场竞争力） | C26: 有市场的话，要加大广告，加快市场占有的速度，尽快甩开竞争对手 但不适合做独一无二的产品，因为市场不确定，这类产品适合做众筹
A27: 常见的错误思维 | B27: (1)过分控制Acos | C27: 新品期打自然位的广告不要过于控制Acos而忽略广告目的； 老品不要过于控制Acos而打一些本来已经有很高自然位的长尾词
B28: (2)过低预算 | C28: 亚马逊流量分配会受广告组预算影响，如打位置的广告给太低预算的话，亚马逊不会给非常好的广告展示位 核心广告尽量保持全天开满的状态，否则影响广告学习的节奏，导致数据波动，如预算很快花完，多采用分时策略
B29: (3)过低/高CPC和Bid | C29: 结合广告目的，实测出目标广告位的最优CPC，过高会产生不必要的浪费。 新品的核心广告词尽量控制在搜索结果前两页，再逐步打至首页
B30: (4)自动or广泛等泛流量组未及时否定无效流量 | C30: 导致广告质量越来越差，可用领星的搜索词报告更快速分析否词 | D30: 路径：领星广告--分析--搜索词分析--筛选目标广告活动
B31: (5)仅看后台，不定期汇总分析广告搜索词报表 | C31: 老品SP广告每7天，SB和SD广告每14天分析一次广告报表，新品需每天保持分析调整
B32: (6)故意让预算超出一点点 | C32: 合适的预算是，预算不消耗完的情况下，高出20%-30%
B33: (7)同一个词在多个广告组未做区分重复投放 | C33: 同一个词如在不同组投放，要么在其他组否掉，要么做好CPC和广告位差异，否则两个组会互相竞争抬高CPC
B34: (8)随意布局广告结构 | C34: 广告组为了避免不同group之间会相互影响质量得分和抢预算，一个SKU一个group一个Campaign
A35: 了解广告展现排名因素 | B35: (1)出价 | C35: 广告排名得分 = 广告出价 x 广告质量得分 实际点击扣费 = 下一位广告排名得分 / 你的广告质量得分 + 0.01 广告质量得分 = 转化率 x 点击率 x 广告历史表现 x 类目节点 x 相关度
B36: (2)关键词竞争情况
B37: (3)点击率
B38: (4)转化率
B39: (5)相关性
B40: (6)用户满意度
A41: 如何优化AcoAs | B41: 打好核心词的自然位，提高自然订单 | C41: 自然位稳定后，如竞争不是非常激烈，可以适当调低核心词广告位，不需要一直抢首行
B42: 权重积累较好后，可以降低CPC | C42: 测试：1. 每次降低0.1美金，观察3天；2. 降低CPC，广告位置保持不变；3. 广告预算能花完，数据波动不大
B43: 扩展额外的低Acos的流量 | C43: 捡漏广告、ASIN广告、类目广告、展示性广告等一系列可以低成本增加订单的广告组
A44: 相关公式 | B44: bid极限值=利润率 x 客单价 x 转化率 | C44: 需要盈利的广告bid不要超过极限值，这里的利润率不计算广告花费，老品AcoAs原则不超过13%
A45: 广告前准备 （务必在到货前完善） | B45: 打造高转化listing | C45: 标题：需完整包含核心推广词，含有核心卖点和主要场景
C46: 五点：继续埋核心词和长尾词
C47: 长描述：埋流量词、场景词、人群词
C48: ST：再次埋入核心词和大流量词
C49: 主图：提前至少做好2个版本，根据广告点击率而定使用哪个，无明显差异情况下，长期做A/B Test
C50: 附图：根据卖点重要程度和转化率情况调整附图排序，要上满9张图片，图片命名为不同关键词
B51: 制作否定词库 | C51: 用于提前否定无效流量 Tips：在广告的时候，会出现Suggestion，出现了一些不相关的词语或者大词，为了控制成本，我们也是可以先提前否定
B52: 检查收录 | C52: 产品到货后，先用产品关键词+ASIN在前台搜索，检查listing是否被亚马逊收录，然后查询关键词标签
B53: 关键词标签 | C53: 根据关键词标签的情况制定广告策略（3种情况） 如：产品是杯子送杯垫，杯垫关键词也被收录，这种则为较宽泛 | D53: 当关键词标签与产品本身相关度较低时--开自动广告之前看一下后台的推荐词，如与产品不相关，需优化文案 关键词标签比较宽泛时--关键词比较相关但是还是有一部分不相关的，也先不要开自动干广告，先去开手动精准/广泛广告去纠正标签 关键词标签已经精准时---可以直接开自动广告。
B54: 判断产品属性 | C54: 如何判断重关键词类目：竞争对手top5放到sif查，看流量结构，若结构都是10个关键词以上的结构，说明该产品关联属性较强若都是某个关键词出单占比超50%，相对来说是重关键词的产品 重关键词：紧密匹配+同类（bid在前三页能搜索到） 重关联：宽泛匹配+关联（bid在前三页能搜索到）
B55: 品牌旗舰店装修 | C55: 做垂直类目，且有多款产品上架后，优化好旗舰店可以带来很多关联流量，新品也会更好起量
A57: 广告FAQ
A58: 序号 | B58: Q | C58: A
A59: 1 | B59: 前期给建议CPC或更高，但很少曝光
A60: 2 | B60: 有曝光，但点击率很少
