Workbook

Sheet 日常跟踪表 DE
A1: 时间 | B1: 星期 | C1: 工作内容 | D1: 售价 | E1: PD | F1: 划线价 折扣 | G1: CP | H1: 最低 成交价 | I1: SC最低 成交价毛利率 | J1: VC采购价毛利率 | K1: 移动 | L1: PC | M1: 访问 | N1: 总转化率 | O1: 实际自然订单 | P1: 自然订单（除测评、站外） | Q1: 总订单 | R1: VC订单 | S1: B2B订单 | T1: 测评计划出单 | U1: 测评总出单 | V1: 测评完成率 | W1: Vine | X1: 销售额 | Y1: 核心词ABA排名 | AG1: sif前三页关键词收录数量 | AH1: 大类排名 | AI1: 小类排名 | AJ1: 评论 | AK1: 评分 | AL1: 广告数据 | AZ1: 毛利数据 | BG1: 站外 | BM1: 库存监控
Y2: matratzenreiniger | AA2: milbensauger | AC2: milbensauger für matratzen | AE2: milbensauger für matratzen testsieger | AL2: 曝光 | AM2: 点击 | AN2: 点击率 | AO2: 订单 | AP2: CPC | AQ2: ACOS | AR2: 广告转化 | AS2: 广告订单占比 | AT2: 花费（$） | AU2: 广告花费占比 | AV2: CPA | AW2: 广告销售额 | AX2: 广告销售额/店铺总销售额 | AY2: 退款率 | AZ2: 广告订单毛利P1$ | BA2: 自然订单毛利P1$ | BB2: 总订单毛利P1$ | BC2: 总订单毛利率P1 | BD2: 国内总成本$ | BE2: 回款金额 | BF2: 测评亏损 | BG2: 站外毛利$ | BH2: 站外出单 | BI2: 站外售价 | BJ2: 站外折扣 | BK2: 自然流量 | BL2: 自然转化 | BM2: VC仓库存 | BN2: 海外仓库存 | BO2: 总库存 | BP2: VC其他订单数 | BQ2: 备注
A3: 45992 | B3: 星期一 | C3: B0FNMBQFBC | D3: 54.99 | F3: 0 | G3: 0 | H3: 33.43 | I3: - | J3: - | K3: ='德国ERP数据'!BC2 | L3: ='德国ERP数据'!BA2 | M3: =K3+L3 | N3: =IFERROR(Q3/M3,0) | O3: =P3-AO3 | P3: =Q3-U3-BH3 | Q3: ='德国ERP数据'!R2 | T3: 0 | U3: 0 | V3: 0 | W3: 0 | X3: ='德国ERP数据'!Q2 | Y3: / | AA3: / | AC3: / | AE3: 32 | AG3: 0 | AH3: 0 | AI3: 0 | AJ3: 0 | AK3: 5 | AL3: 0 | AM3: 0 | AN3: =IFERROR(AM3/AL3,0) | AO3: 0 | AP3: =IFERROR(AT3/AM3,0) | AQ3: =IFERROR(AT3/AW3,0) | AR3: =IFERROR(AO3/AM3,0) | AS3: =IFERROR(AO3/Q3,0) | AT3: 0 | AU3: =IFERROR(AT3/X3,0) | AV3: =IFERROR(AT3/AO3,0) | AW3: 0 | AX3: =IFERROR(AW3/X3,0)
A4: 45993 | B4: 星期二 | D4: 54.99 | F4: 0 | G4: 0 | H4: 33.43 | I4: - | J4: - | K4: ='德国ERP数据'!BC3 | L4: ='德国ERP数据'!BA3 | M4: =K4+L4 | N4: =IFERROR(Q4/M4,0) | O4: =P4-AO4 | P4: =Q4-U4-BH4 | Q4: ='德国ERP数据'!R3 | R4: - | S4: ='德国ERP数据'!Z3 | T4: 0 | U4: 0 | V4: 0 | W4: 0 | X4: ='德国ERP数据'!Q3 | Y4: / | AA4: / | AC4: / | AE4: 32 | AG4: 0 | AH4: 0 | AI4: 0 | AJ4: 0 | AK4: 5 | AL4: 0 | AM4: 0 | AN4: =IFERROR(AM4/AL4,0) | AO4: 0 | AP4: =IFERROR(AT4/AM4,0) | AQ4: =IFERROR(AT4/AW4,0) | AR4: =IFERROR(AO4/AM4,0) | AS4: =IFERROR(AO4/Q4,0) | AT4: 0 | AU4: =IFERROR(AT4/X4,0) | AV4: =IFERROR(AT4/AO4,0) | AW4: 0 | AX4: =IFERROR(AW4/X4,0)
A5: 45994 | B5: 星期三 | D5: 54.99 | F5: 0 | G5: 0 | H5: 33.43 | I5: - | J5: - | K5: ='德国ERP数据'!BC4 | L5: ='德国ERP数据'!BA4 | M5: =K5+L5 | N5: =IFERROR(Q5/M5,0) | O5: =P5-AO5 | P5: =Q5-U5-BH5 | Q5: ='德国ERP数据'!R4 | R5: - | S5: ='德国ERP数据'!Z4 | T5: 0 | U5: 0 | V5: 0 | W5: 0 | X5: ='德国ERP数据'!Q4 | Y5: / | AA5: / | AC5: / | AE5: 32 | AG5: 0 | AH5: 0 | AI5: 0 | AJ5: 0 | AK5: 5 | AL5: 0 | AM5: 0 | AN5: =IFERROR(AM5/AL5,0) | AO5: 0 | AP5: =IFERROR(AT5/AM5,0) | AQ5: =IFERROR(AT5/AW5,0) | AR5: =IFERROR(AO5/AM5,0) | AS5: =IFERROR(AO5/Q5,0) | AT5: 0 | AU5: =IFERROR(AT5/X5,0) | AV5: =IFERROR(AT5/AO5,0) | AW5: 0 | AX5: =IFERROR(AW5/X5,0)
A6: 45995 | B6: 星期四 | D6: 54.99 | F6: 0 | G6: 0 | H6: 33.43 | I6: - | J6: - | K6: ='德国ERP数据'!BC5 | L6: ='德国ERP数据'!BA5 | M6: =K6+L6 | N6: =IFERROR(Q6/M6,0) | O6: =P6-AO6 | P6: =Q6-U6-BH6 | Q6: ='德国ERP数据'!R5 | R6: - | S6: ='德国ERP数据'!Z5 | T6: 0 | U6: 0 | V6: 0 | W6: 0 | X6: ='德国ERP数据'!Q5 | Y6: / | AA6: / | AC6: / | AE6: 32 | AG6: 0 | AH6: 0 | AI6: 0 | AJ6: 0 | AK6: 5 | AL6: 0 | AM6: 0 | AN6: =IFERROR(AM6/AL6,0) | AO6: 0 | AP6: =IFERROR(AT6/AM6,0) | AQ6: =IFERROR(AT6/AW6,0) | AR6: =IFERROR(AO6/AM6,0) | AS6: =IFERROR(AO6/Q6,0) | AT6: 0 | AU6: =IFERROR(AT6/X6,0) | AV6: =IFERROR(AT6/AO6,0) | AW6: 0 | AX6: =IFERROR(AW6/X6,0)
A7: 45996 | B7: 星期五 | D7: 54.99 | F7: 0 | G7: 0 | H7: 33.43 | I7: - | J7: - | K7: ='德国ERP数据'!BC6 | L7: ='德国ERP数据'!BA6 | M7: =K7+L7 | N7: =IFERROR(Q7/M7,0) | O7: =P7-AO7 | P7: =Q7-U7-BH7 | Q7: ='德国ERP数据'!R6 | R7: - | S7: ='德国ERP数据'!Z6 | T7: 0 | U7: 0 | V7: 0 | W7: 0 | X7: ='德国ERP数据'!Q6 | Y7: / | AA7: / | AC7: / | AE7: 32 | AG7: 0 | AH7: 0 | AI7: 0 | AJ7: 0 | AK7: 5 | AL7: 0 | AM7: 0 | AN7: =IFERROR(AM7/AL7,0) | AO7: 0 | AP7: =IFERROR(AT7/AM7,0) | AQ7: =IFERROR(AT7/AW7,0) | AR7: =IFERROR(AO7/AM7,0) | AS7: =IFERROR(AO7/Q7,0) | AT7: 0 | AU7: =IFERROR(AT7/X7,0) | AV7: =IFERROR(AT7/AO7,0) | AW7: 0 | AX7: =IFERROR(AW7/X7,0)
A8: 45997 | B8: 星期六 | D8: 54.99 | F8: 0 | G8: 0 | H8: 33.43 | I8: - | J8: - | K8: ='德国ERP数据'!BC7 | L8: ='德国ERP数据'!BA7 | M8: =K8+L8 | N8: =IFERROR(Q8/M8,0) | O8: =P8-AO8 | P8: =Q8-U8-BH8 | Q8: ='德国ERP数据'!R7 | R8: - | S8: ='德国ERP数据'!Z7 | T8: 0 | U8: 0 | V8: 0 | W8: 0 | X8: ='德国ERP数据'!Q7 | Y8: / | AA8: / | AC8: / | AE8: 32 | AG8: 0 | AH8: 0 | AI8: 0 | AJ8: 0 | AK8: 5 | AL8: 0 | AM8: 0 | AN8: =IFERROR(AM8/AL8,0) | AO8: 0 | AP8: =IFERROR(AT8/AM8,0) | AQ8: =IFERROR(AT8/AW8,0) | AR8: =IFERROR(AO8/AM8,0) | AS8: =IFERROR(AO8/Q8,0) | AT8: 0 | AU8: =IFERROR(AT8/X8,0) | AV8: =IFERROR(AT8/AO8,0) | AW8: 0 | AX8: =IFERROR(AW8/X8,0)
A9: 45998 | B9: 星期日 | D9: 54.99 | F9: 0 | G9: 0 | H9: 33.43 | I9: - | J9: - | K9: ='德国ERP数据'!BC8 | L9: ='德国ERP数据'!BA8 | M9: =K9+L9 | N9: =IFERROR(Q9/M9,0) | O9: =P9-AO9 | P9: =Q9-U9-BH9 | Q9: ='德国ERP数据'!R8 | R9: - | S9: ='德国ERP数据'!Z8 | T9: 0 | U9: 0 | V9: 0 | W9: 0 | X9: ='德国ERP数据'!Q8 | Y9: / | AA9: / | AC9: / | AE9: 32 | AG9: 0 | AH9: 0 | AI9: 0 | AJ9: 0 | AK9: 5 | AL9: 0 | AM9: 0 | AN9: =IFERROR(AM9/AL9,0) | AO9: 0 | AP9: =IFERROR(AT9/AM9,0) | AQ9: =IFERROR(AT9/AW9,0) | AR9: =IFERROR(AO9/AM9,0) | AS9: =IFERROR(AO9/Q9,0) | AT9: 0 | AU9: =IFERROR(AT9/X9,0) | AV9: =IFERROR(AT9/AO9,0) | AW9: 0 | AX9: =IFERROR(AW9/X9,0)
A10: 45999 | B10: 星期一 | D10: 54.99 | F10: 0 | G10: 0 | H10: 33.43 | I10: - | J10: - | K10: ='德国ERP数据'!BC9 | L10: ='德国ERP数据'!BA9 | M10: =K10+L10 | N10: =IFERROR(Q10/M10,0) | O10: =P10-AO10 | P10: =Q10-U10-BH10 | Q10: ='德国ERP数据'!R9 | R10: - | S10: ='德国ERP数据'!Z9 | T10: 0 | U10: 0 | V10: 0 | W10: 0 | X10: ='德国ERP数据'!Q9 | Y10: / | AA10: / | AC10: / | AE10: 32 | AG10: 0 | AH10: 0 | AI10: 0 | AJ10: 0 | AK10: 5 | AL10: 0 | AM10: 0 | AN10: =IFERROR(AM10/AL10,0) | AO10: 0 | AP10: =IFERROR(AT10/AM10,0) | AQ10: =IFERROR(AT10/AW10,0) | AR10: =IFERROR(AO10/AM10,0) | AS10: =IFERROR(AO10/Q10,0) | AT10: 0 | AU10: =IFERROR(AT10/X10,0) | AV10: =IFERROR(AT10/AO10,0) | AW10: 0 | AX10: =IFERROR(AW10/X10,0)
A11: 46000 | B11: 星期二 | D11: 54.99 | F11: 0 | G11: 0 | H11: 33.43 | I11: - | J11: - | K11: ='德国ERP数据'!BC10 | L11: ='德国ERP数据'!BA10 | M11: =K11+L11 | N11: =IFERROR(Q11/M11,0) | O11: =P11-AO11 | P11: =Q11-U11-BH11 | Q11: ='德国ERP数据'!R10 | R11: - | S11: ='德国ERP数据'!Z10 | T11: 0 | U11: 0 | V11: 0 | W11: 0 | X11: ='德国ERP数据'!Q10 | Y11: / | AA11: / | AC11: / | AE11: 32 | AG11: 0 | AH11: 0 | AI11: 0 | AJ11: 0 | AK11: 5 | AL11: 0 | AM11: 0 | AN11: =IFERROR(AM11/AL11,0) | AO11: 0 | AP11: =IFERROR(AT11/AM11,0) | AQ11: =IFERROR(AT11/AW11,0) | AR11: =IFERROR(AO11/AM11,0) | AS11: =IFERROR(AO11/Q11,0) | AT11: 0 | AU11: =IFERROR(AT11/X11,0) | AV11: =IFERROR(AT11/AO11,0) | AW11: 0 | AX11: =IFERROR(AW11/X11,0)
A12: 46001 | B12: 星期三 | D12: 54.99 | F12: 0 | G12: 0 | H12: 33.43 | I12: - | J12: - | K12: ='德国ERP数据'!BC11 | L12: ='德国ERP数据'!BA11 | M12: =K12+L12 | N12: =IFERROR(Q12/M12,0) | O12: =P12-AO12 | P12: =Q12-U12-BH12 | Q12: ='德国ERP数据'!R11 | R12: - | S12: ='德国ERP数据'!Z11 | T12: 0 | U12: 0 | V12: 0 | W12: 0 | X12: ='德国ERP数据'!Q11 | Y12: / | AA12: / | AC12: / | AE12: 32 | AG12: 0 | AH12: 0 | AI12: 0 | AJ12: 0 | AK12: 5 | AL12: 0 | AM12: 0 | AN12: =IFERROR(AM12/AL12,0) | AO12: 0 | AP12: =IFERROR(AT12/AM12,0) | AQ12: =IFERROR(AT12/AW12,0) | AR12: =IFERROR(AO12/AM12,0) | AS12: =IFERROR(AO12/Q12,0) | AT12: 0 | AU12: =IFERROR(AT12/X12,0) | AV12: =IFERROR(AT12/AO12,0) | AW12: 0 | AX12: =IFERROR(AW12/X12,0)
A13: 46002 | B13: 星期四 | D13: 54.99 | F13: 0 | G13: 0 | H13: 33.43 | I13: - | J13: - | K13: ='德国ERP数据'!BC12 | L13: ='德国ERP数据'!BA12 | M13: =K13+L13 | N13: =IFERROR(Q13/M13,0) | O13: =P13-AO13 | P13: =Q13-U13-BH13 | Q13: ='德国ERP数据'!R12 | R13: - | S13: ='德国ERP数据'!Z12 | T13: 0 | U13: 0 | V13: 0 | W13: 0 | X13: ='德国ERP数据'!Q12 | Y13: / | AA13: / | AC13: / | AE13: 32 | AG13: 0 | AH13: 0 | AI13: 0 | AJ13: 0 | AK13: 5 | AL13: 0 | AM13: 0 | AN13: =IFERROR(AM13/AL13,0) | AO13: 0 | AP13: =IFERROR(AT13/AM13,0) | AQ13: =IFERROR(AT13/AW13,0) | AR13: =IFERROR(AO13/AM13,0) | AS13: =IFERROR(AO13/Q13,0) | AT13: 0 | AU13: =IFERROR(AT13/X13,0) | AV13: =IFERROR(AT13/AO13,0) | AW13: 0 | AX13: =IFERROR(AW13/X13,0)
A14: 46003 | B14: 星期五 | D14: 54.99 | F14: 0 | G14: 0 | H14: 33.43 | I14: - | J14: - | K14: ='德国ERP数据'!BC13 | L14: ='德国ERP数据'!BA13 | M14: =K14+L14 | N14: =IFERROR(Q14/M14,0) | O14: =P14-AO14 | P14: =Q14-U14-BH14 | Q14: ='德国ERP数据'!R13 | R14: - | S14: ='德国ERP数据'!Z13 | T14: 0 | U14: 0 | V14: 0 | W14: 0 | X14: ='德国ERP数据'!Q13 | Y14: / | AA14: / | AC14: / | AE14: 32 | AG14: 0 | AH14: 0 | AI14: 0 | AJ14: 0 | AK14: 5 | AL14: 0 | AM14: 0 | AN14: =IFERROR(AM14/AL14,0) | AO14: 0 | AP14: =IFERROR(AT14/AM14,0) | AQ14: =IFERROR(AT14/AW14,0) | AR14: =IFERROR(AO14/AM14,0) | AS14: =IFERROR(AO14/Q14,0) | AT14: 0 | AU14: =IFERROR(AT14/X14,0) | AV14: =IFERROR(AT14/AO14,0) | AW14: 0 | AX14: =IFERROR(AW14/X14,0)
A15: 46004 | B15: 星期六 | D15: 54.99 | F15: 0 | G15: 0 | H15: 33.43 | I15: - | J15: - | K15: ='德国ERP数据'!BC14 | L15: ='德国ERP数据'!BA14 | M15: =K15+L15 | N15: =IFERROR(Q15/M15,0) | O15: =P15-AO15 | P15: =Q15-U15-BH15 | Q15: ='德国ERP数据'!R14 | R15: - | S15: ='德国ERP数据'!Z14 | T15: 0 | U15: 0 | V15: 0 | W15: 0 | X15: ='德国ERP数据'!Q14 | Y15: / | AA15: / | AC15: / | AE15: 32 | AG15: 0 | AH15: 0 | AI15: 0 | AJ15: 0 | AK15: 5 | AL15: 0 | AM15: 0 | AN15: =IFERROR(AM15/AL15,0) | AO15: 0 | AP15: =IFERROR(AT15/AM15,0) | AQ15: =IFERROR(AT15/AW15,0) | AR15: =IFERROR(AO15/AM15,0) | AS15: =IFERROR(AO15/Q15,0) | AT15: 0 | AU15: =IFERROR(AT15/X15,0) | AV15: =IFERROR(AT15/AO15,0) | AW15: 0 | AX15: =IFERROR(AW15/X15,0)
... A26: 46015 | B26: 星期三 | D26: 54.99 | F26: 0 | G26: 0 | H26: 33.43 | I26: - | J26: - | K26: ='德国ERP数据'!BC25 | L26: ='德国ERP数据'!BA25 | M26: =K26+L26 | N26: =IFERROR(Q26/M26,0) | O26: =P26-AO26 | P26: =Q26-U26-BH26 | Q26: ='德国ERP数据'!R25 | R26: - | S26: ='德国ERP数据'!Z25 | T26: 0 | U26: 0 | V26: 0 | W26: 0 | X26: ='德国ERP数据'!Q25 | Y26: / | AA26: / | AC26: / | AE26: 32 | AG26: 0 | AH26: 0 | AI26: 0 | AJ26: 0 | AK26: 5 | AL26: 0 | AM26: 0 | AN26: =IFERROR(AM26/AL26,0) | AO26: 0 | AP26: =IFERROR(AT26/AM26,0) | AQ26: =IFERROR(AT26/AW26,0) | AR26: =IFERROR(AO26/AM26,0) | AS26: =IFERROR(AO26/Q26,0) | AT26: 0 | AU26: =IFERROR(AT26/X26,0) | AV26: =IFERROR(AT26/AO26,0) | AW26: 0 | AX26: =IFERROR(AW26/X26,0)
A27: 46016 | B27: 星期四 | D27: 54.99 | F27: 0 | G27: 0 | H27: 33.43 | I27: - | J27: - | K27: ='德国ERP数据'!BC226 | L27: ='德国ERP数据'!BA226 | M27: =K27+L27 | N27: =IFERROR(Q27/M27,0) | O27: =P27-AO27 | P27: =Q27-U27-BH27 | Q27: ='德国ERP数据'!R226 | R27: - | S27: ='德国ERP数据'!Z226 | T27: 0 | U27: 0 | V27: 0 | W27: 0 | X27: ='德国ERP数据'!Q226 | Y27: / | AA27: / | AC27: / | AE27: 32 | AG27: 0 | AH27: 0 | AI27: 0 | AJ27: 0 | AK27: 5 | AL27: 0 | AM27: 0 | AN27: =IFERROR(AM27/AL27,0) | AO27: 0 | AP27: =IFERROR(AT27/AM27,0) | AQ27: =IFERROR(AT27/AW27,0) | AR27: =IFERROR(AO27/AM27,0) | AS27: =IFERROR(AO27/Q27,0) | AT27: 0 | AU27: =IFERROR(AT27/X27,0) | AV27: =IFERROR(AT27/AO27,0) | AW27: 0 | AX27: =IFERROR(AW27/X27,0)
A28: 46017 | B28: 星期五 | D28: 54.99 | F28: 0 | G28: 0 | H28: 33.43 | I28: - | J28: - | K28: ='德国ERP数据'!BC227 | L28: ='德国ERP数据'!BA227 | M28: =K28+L28 | N28: =IFERROR(Q28/M28,0) | O28: =P28-AO28 | P28: =Q28-U28-BH28 | Q28: ='德国ERP数据'!R227 | R28: - | S28: ='德国ERP数据'!Z227 | T28: 0 | U28: 0 | V28: 0 | W28: 0 | X28: ='德国ERP数据'!Q227 | Y28: / | AA28: / | AC28: / | AE28: 32 | AG28: 0 | AH28: 0 | AI28: 0 | AJ28: 0 | AK28: 5 | AL28: 0 | AM28: 0 | AN28: =IFERROR(AM28/AL28,0) | AO28: 0 | AP28: =IFERROR(AT28/AM28,0) | AQ28: =IFERROR(AT28/AW28,0) | AR28: =IFERROR(AO28/AM28,0) | AS28: =IFERROR(AO28/Q28,0) | AT28: 0 | AU28: =IFERROR(AT28/X28,0) | AV28: =IFERROR(AT28/AO28,0) | AW28: 0 | AX28: =IFERROR(AW28/X28,0)
A29: 46018 | B29: 星期六 | D29: 54.99 | F29: 0 | G29: 0 | H29: 33.43 | I29: - | J29: - | K29: ='德国ERP数据'!BC228 | L29: ='德国ERP数据'!BA228 | M29: =K29+L29 | N29: =IFERROR(Q29/M29,0) | O29: =P29-AO29 | P29: =Q29-U29-BH29 | Q29: ='德国ERP数据'!R228 | R29: - | S29: ='德国ERP数据'!Z228 | T29: 0 | U29: 0 | V29: 0 | W29: 0 | X29: ='德国ERP数据'!Q228 | Y29: / | AA29: / | AC29: / | AE29: 32 | AG29: 0 | AH29: 0 | AI29: 0 | AJ29: 0 | AK29: 5 | AL29: 0 | AM29: 0 | AN29: =IFERROR(AM29/AL29,0) | AO29: 0 | AP29: =IFERROR(AT29/AM29,0) | AQ29: =IFERROR(AT29/AW29,0) | AR29: =IFERROR(AO29/AM29,0) | AS29: =IFERROR(AO29/Q29,0) | AT29: 0 | AU29: =IFERROR(AT29/X29,0) | AV29: =IFERROR(AT29/AO29,0) | AW29: 0 | AX29: =IFERROR(AW29/X29,0)
A30: 46019 | B30: 星期日 | D30: 54.99 | F30: 0 | G30: 0 | H30: 33.43 | I30: - | J30: - | K30: ='德国ERP数据'!BC229 | L30: ='德国ERP数据'!BA229 | M30: =K30+L30 | N30: =IFERROR(Q30/M30,0) | O30: =P30-AO30 | P30: =Q30-U30-BH30 | Q30: ='德国ERP数据'!R229 | R30: - | S30: ='德国ERP数据'!Z229 | T30: 0 | U30: 0 | V30: 0 | W30: 0 | X30: ='德国ERP数据'!Q229 | Y30: / | AA30: / | AC30: / | AE30: 32 | AG30: 0 | AH30: 0 | AI30: 0 | AJ30: 0 | AK30: 5 | AL30: 0 | AM30: 0 | AN30: =IFERROR(AM30/AL30,0) | AO30: 0 | AP30: =IFERROR(AT30/AM30,0) | AQ30: =IFERROR(AT30/AW30,0) | AR30: =IFERROR(AO30/AM30,0) | AS30: =IFERROR(AO30/Q30,0) | AT30: 0 | AU30: =IFERROR(AT30/X30,0) | AV30: =IFERROR(AT30/AO30,0) | AW30: 0 | AX30: =IFERROR(AW30/X30,0)
A31: 46020 | B31: 星期一 | D31: 54.99 | F31: 0 | G31: 0 | H31: 33.43 | I31: - | J31: - | K31: ='德国ERP数据'!BC230 | L31: ='德国ERP数据'!BA230 | M31: =K31+L31 | N31: =IFERROR(Q31/M31,0) | O31: =P31-AO31 | P31: =Q31-U31-BH31 | Q31: ='德国ERP数据'!R230 | R31: - | S31: ='德国ERP数据'!Z230 | T31: 0 | U31: 0 | V31: 0 | W31: 0 | X31: ='德国ERP数据'!Q230 | Y31: / | AA31: / | AC31: / | AE31: 32 | AG31: 0 | AH31: 0 | AI31: 0 | AJ31: 0 | AK31: 5 | AL31: 0 | AM31: 0 | AN31: =IFERROR(AM31/AL31,0) | AO31: 0 | AP31: =IFERROR(AT31/AM31,0) | AQ31: =IFERROR(AT31/AW31,0) | AR31: =IFERROR(AO31/AM31,0) | AS31: =IFERROR(AO31/Q31,0) | AT31: 0 | AU31: =IFERROR(AT31/X31,0) | AV31: =IFERROR(AT31/AO31,0) | AW31: 0 | AX31: =IFERROR(AW31/X31,0)
A32: 46021 | B32: 星期二 | D32: 54.99 | F32: 0 | G32: 0 | H32: 33.43 | I32: - | J32: - | K32: ='德国ERP数据'!BC231 | L32: ='德国ERP数据'!BA231 | M32: =K32+L32 | N32: =IFERROR(Q32/M32,0) | O32: =P32-AO32 | P32: =Q32-U32-BH32 | Q32: ='德国ERP数据'!R231 | R32: - | S32: ='德国ERP数据'!Z231 | T32: 0 | U32: 0 | V32: 0 | W32: 0 | X32: ='德国ERP数据'!Q231 | Y32: / | AA32: / | AC32: / | AE32: 32 | AG32: 0 | AH32: 0 | AI32: 0 | AJ32: 0 | AK32: 5 | AL32: 0 | AM32: 0 | AN32: =IFERROR(AM32/AL32,0) | AO32: 0 | AP32: =IFERROR(AT32/AM32,0) | AQ32: =IFERROR(AT32/AW32,0) | AR32: =IFERROR(AO32/AM32,0) | AS32: =IFERROR(AO32/Q32,0) | AT32: 0 | AU32: =IFERROR(AT32/X32,0) | AV32: =IFERROR(AT32/AO32,0) | AW32: 0 | AX32: =IFERROR(AW32/X32,0)
A33: 46022 | B33: 星期三 | D33: 54.99 | F33: 0 | G33: 0 | H33: 33.43 | I33: - | J33: - | K33: ='德国ERP数据'!BC232 | L33: ='德国ERP数据'!BA232 | M33: =K33+L33 | N33: =IFERROR(Q33/M33,0) | O33: =P33-AO33 | P33: =Q33-U33-BH33 | Q33: ='德国ERP数据'!R232 | R33: - | S33: ='德国ERP数据'!Z232 | T33: 0 | U33: 0 | V33: 0 | W33: 0 | X33: ='德国ERP数据'!Q232 | Y33: / | AA33: / | AC33: / | AE33: 32 | AG33: 0 | AH33: 0 | AI33: 0 | AJ33: 0 | AK33: 5 | AL33: 0 | AM33: 0 | AN33: =IFERROR(AM33/AL33,0) | AO33: 0 | AP33: =IFERROR(AT33/AM33,0) | AQ33: =IFERROR(AT33/AW33,0) | AR33: =IFERROR(AO33/AM33,0) | AS33: =IFERROR(AO33/Q33,0) | AT33: 0 | AU33: =IFERROR(AT33/X33,0) | AV33: =IFERROR(AT33/AO33,0) | AW33: 0 | AX33: =IFERROR(AW33/X33,0)
A34: 46023 | B34: 星期四 | D34: 54.99 | F34: 0 | G34: 0 | H34: 33.43 | I34: - | J34: - | K34: ='德国ERP数据'!BC233 | L34: ='德国ERP数据'!BA233 | M34: =K34+L34 | N34: =IFERROR(Q34/M34,0) | O34: =P34-AO34 | P34: =Q34-U34-BH34 | Q34: ='德国ERP数据'!R233 | R34: - | S34: ='德国ERP数据'!Z233 | T34: 0 | U34: 0 | V34: 0 | W34: 0 | X34: ='德国ERP数据'!Q233 | Y34: / | AA34: / | AC34: / | AE34: 32 | AG34: 0 | AH34: 0 | AI34: 0 | AJ34: 0 | AK34: 5 | AL34: 0 | AM34: 0 | AN34: =IFERROR(AM34/AL34,0) | AO34: 0 | AP34: =IFERROR(AT34/AM34,0) | AQ34: =IFERROR(AT34/AW34,0) | AR34: =IFERROR(AO34/AM34,0) | AS34: =IFERROR(AO34/Q34,0) | AT34: 0 | AU34: =IFERROR(AT34/X34,0) | AV34: =IFERROR(AT34/AO34,0) | AW34: 0 | AX34: =IFERROR(AW34/X34,0)
A35: 46024 | B35: 星期五 | D35: 54.99 | F35: 0 | G35: 0 | H35: 33.43 | I35: - | J35: - | K35: ='德国ERP数据'!BC234 | L35: ='德国ERP数据'!BA234 | M35: =K35+L35 | N35: =IFERROR(Q35/M35,0) | O35: =P35-AO35 | P35: =Q35-U35-BH35 | Q35: ='德国ERP数据'!R234 | R35: - | S35: ='德国ERP数据'!Z234 | T35: 0 | U35: 0 | V35: 0 | W35: 0 | X35: ='德国ERP数据'!Q234 | Y35: / | AA35: / | AC35: / | AE35: 32 | AG35: 0 | AH35: 0 | AI35: 0 | AJ35: 0 | AK35: 5 | AL35: 0 | AM35: 0 | AN35: =IFERROR(AM35/AL35,0) | AO35: 0 | AP35: =IFERROR(AT35/AM35,0) | AQ35: =IFERROR(AT35/AW35,0) | AR35: =IFERROR(AO35/AM35,0) | AS35: =IFERROR(AO35/Q35,0) | AT35: 0 | AU35: =IFERROR(AT35/X35,0) | AV35: =IFERROR(AT35/AO35,0) | AW35: 0 | AX35: =IFERROR(AW35/X35,0)
A36: 46025 | B36: 星期六 | D36: 54.99 | F36: 0 | G36: 0 | H36: 33.43 | I36: - | J36: - | K36: ='德国ERP数据'!BC235 | L36: ='德国ERP数据'!BA235 | M36: =K36+L36 | N36: =IFERROR(Q36/M36,0) | O36: =P36-AO36 | P36: =Q36-U36-BH36 | Q36: ='德国ERP数据'!R235 | R36: - | S36: ='德国ERP数据'!Z235 | T36: 0 | U36: 0 | V36: 0 | W36: 0 | X36: ='德国ERP数据'!Q235 | Y36: / | AA36: / | AC36: / | AE36: 32 | AG36: 0 | AH36: 0 | AI36: 0 | AJ36: 0 | AK36: 5 | AL36: 0 | AM36: 0 | AN36: =IFERROR(AM36/AL36,0) | AO36: 0 | AP36: =IFERROR(AT36/AM36,0) | AQ36: =IFERROR(AT36/AW36,0) | AR36: =IFERROR(AO36/AM36,0) | AS36: =IFERROR(AO36/Q36,0) | AT36: 0 | AU36: =IFERROR(AT36/X36,0) | AV36: =IFERROR(AT36/AO36,0) | AW36: 0 | AX36: =IFERROR(AW36/X36,0)
A37: 46026 | B37: 星期日 | D37: 54.99 | F37: 0 | G37: 0 | H37: 33.43 | I37: - | J37: - | K37: ='德国ERP数据'!BC236 | L37: ='德国ERP数据'!BA236 | M37: =K37+L37 | N37: =IFERROR(Q37/M37,0) | O37: =P37-AO37 | P37: =Q37-U37-BH37 | Q37: ='德国ERP数据'!R236 | R37: - | S37: ='德国ERP数据'!Z236 | T37: 0 | U37: 0 | V37: 0 | W37: 0 | X37: ='德国ERP数据'!Q236 | Y37: / | AA37: / | AC37: / | AE37: 32 | AG37: 0 | AH37: 0 | AI37: 0 | AJ37: 0 | AK37: 5 | AL37: 0 | AM37: 0 | AN37: =IFERROR(AM37/AL37,0) | AO37: 0 | AP37: =IFERROR(AT37/AM37,0) | AQ37: =IFERROR(AT37/AW37,0) | AR37: =IFERROR(AO37/AM37,0) | AS37: =IFERROR(AO37/Q37,0) | AT37: 0 | AU37: =IFERROR(AT37/X37,0) | AV37: =IFERROR(AT37/AO37,0) | AW37: 0 | AX37: =IFERROR(AW37/X37,0)
A38: 46027 | B38: 星期一 | D38: 54.99 | F38: 0 | G38: 0 | H38: 33.43 | I38: - | J38: - | K38: ='德国ERP数据'!BC237 | L38: ='德国ERP数据'!BA237 | M38: =K38+L38 | N38: =IFERROR(Q38/M38,0) | O38: =P38-AO38 | P38: =Q38-U38-BH38 | Q38: ='德国ERP数据'!R237 | R38: - | S38: ='德国ERP数据'!Z237 | T38: 0 | U38: 0 | V38: 0 | W38: 0 | X38: ='德国ERP数据'!Q237 | Y38: / | AA38: / | AC38: / | AE38: 32 | AG38: 0 | AH38: 0 | AI38: 0 | AJ38: 0 | AK38: 5 | AL38: 0 | AM38: 0 | AN38: =IFERROR(AM38/AL38,0) | AO38: 0 | AP38: =IFERROR(AT38/AM38,0) | AQ38: =IFERROR(AT38/AW38,0) | AR38: =IFERROR(AO38/AM38,0) | AS38: =IFERROR(AO38/Q38,0) | AT38: 0 | AU38: =IFERROR(AT38/X38,0) | AV38: =IFERROR(AT38/AO38,0) | AW38: 0 | AX38: =IFERROR(AW38/X38,0)
... A69: 46058 | B69: 星期四 | D69: 54.99 | F69: 0 | G69: 0 | H69: 33.43 | I69: - | J69: - | K69: ='德国ERP数据'!BC268 | L69: ='德国ERP数据'!BA268 | M69: =K69+L69 | N69: =IFERROR(Q69/M69,0) | O69: =P69-AO69 | P69: =Q69-U69-BH69 | Q69: ='德国ERP数据'!R268 | R69: - | S69: ='德国ERP数据'!Z268 | T69: 0 | U69: 0 | V69: 0 | W69: 0 | X69: ='德国ERP数据'!Q268 | Y69: / | AA69: / | AC69: / | AE69: 32 | AG69: 0 | AH69: 0 | AI69: 0 | AJ69: 0 | AK69: 5 | AL69: 0 | AM69: 0 | AN69: =IFERROR(AM69/AL69,0) | AO69: 0 | AP69: =IFERROR(AT69/AM69,0) | AQ69: =IFERROR(AT69/AW69,0) | AR69: =IFERROR(AO69/AM69,0) | AS69: =IFERROR(AO69/Q69,0) | AT69: 0 | AU69: =IFERROR(AT69/X69,0) | AV69: =IFERROR(AT69/AO69,0) | AW69: 0 | AX69: =IFERROR(AW69/X69,0)
A70: 46059 | B70: 星期五 | D70: 54.99 | F70: 0 | G70: 0 | H70: 33.43 | I70: - | J70: - | K70: ='德国ERP数据'!BC269 | L70: ='德国ERP数据'!BA269 | M70: =K70+L70 | N70: =IFERROR(Q70/M70,0) | O70: =P70-AO70 | P70: =Q70-U70-BH70 | Q70: ='德国ERP数据'!R269 | R70: - | S70: ='德国ERP数据'!Z269 | T70: 0 | U70: 0 | V70: 0 | W70: 0 | X70: ='德国ERP数据'!Q269 | Y70: /
A71: 46060 | B71: 星期六 | D71: 54.99 | F71: 0 | G71: 0 | H71: 33.43 | I71: - | J71: - | K71: ='德国ERP数据'!BC270 | L71: ='德国ERP数据'!BA270 | M71: =K71+L71 | N71: =IFERROR(Q71/M71,0) | O71: =P71-AO71 | P71: =Q71-U71-BH71 | Q71: ='德国ERP数据'!R270 | R71: - | S71: ='德国ERP数据'!Z270 | T71: 0 | U71: 0 | V71: 0 | W71: 0 | X71: ='德国ERP数据'!Q270 | Y71: /
A72: 46061 | B72: 星期日 | D72: 54.99 | F72: 0 | G72: 0 | H72: 33.43 | I72: - | J72: - | K72: ='德国ERP数据'!BC271 | L72: ='德国ERP数据'!BA271 | M72: =K72+L72 | N72: =IFERROR(Q72/M72,0) | O72: =P72-AO72 | P72: =Q72-U72-BH72 | Q72: ='德国ERP数据'!R271 | R72: - | S72: ='德国ERP数据'!Z271 | T72: 0 | U72: 0 | V72: 0 | W72: 0 | X72: ='德国ERP数据'!Q271 | Y72: /
A73: 46062 | B73: 星期一 | D73: 54.99 | F73: 0 | G73: 0 | H73: 33.43 | I73: - | J73: - | K73: ='德国ERP数据'!BC272 | L73: ='德国ERP数据'!BA272 | M73: =K73+L73 | N73: =IFERROR(Q73/M73,0) | O73: =P73-AO73 | P73: =Q73-U73-BH73 | Q73: ='德国ERP数据'!R272 | R73: - | S73: ='德国ERP数据'!Z272 | T73: 0 | U73: 0 | V73: 0 | W73: 0 | X73: ='德国ERP数据'!Q272 | Y73: /
A74: 46063 | B74: 星期二 | D74: 54.99 | F74: 0 | G74: 0 | H74: 33.43 | I74: - | J74: - | K74: ='德国ERP数据'!BC273 | L74: ='德国ERP数据'!BA273 | M74: =K74+L74 | N74: =IFERROR(Q74/M74,0) | O74: =P74-AO74 | P74: =Q74-U74-BH74 | Q74: ='德国ERP数据'!R273 | R74: - | S74: ='德国ERP数据'!Z273 | T74: 0 | U74: 0 | V74: 0 | W74: 0 | X74: ='德国ERP数据'!Q273 | Y74: /
A75: 46064 | B75: 星期三 | D75: 54.99 | F75: 0 | G75: 0 | H75: 33.43 | I75: - | J75: - | K75: ='德国ERP数据'!BC274 | L75: ='德国ERP数据'!BA274 | M75: =K75+L75 | N75: =IFERROR(Q75/M75,0) | O75: =P75-AO75 | P75: =Q75-U75-BH75 | Q75: ='德国ERP数据'!R274 | R75: - | S75: ='德国ERP数据'!Z274 | T75: 0 | U75: 0 | V75: 0 | W75: 0 | X75: ='德国ERP数据'!Q274 | Y75: /
A76: 46065 | B76: 星期四 | D76: 54.99 | F76: 0 | G76: 0 | H76: 33.43 | I76: - | J76: - | K76: ='德国ERP数据'!BC275 | L76: ='德国ERP数据'!BA275 | M76: =K76+L76 | N76: =IFERROR(Q76/M76,0) | O76: =P76-AO76 | P76: =Q76-U76-BH76 | Q76: ='德国ERP数据'!R275 | R76: - | S76: ='德国ERP数据'!Z275 | T76: 0 | U76: 0 | V76: 0 | W76: 0 | X76: ='德国ERP数据'!Q275 | Y76: /
A77: 46066 | B77: 星期五 | D77: 54.99 | F77: 0 | G77: 0 | H77: 33.43 | I77: - | J77: - | K77: ='德国ERP数据'!BC276 | L77: ='德国ERP数据'!BA276 | M77: =K77+L77 | N77: =IFERROR(Q77/M77,0) | O77: =P77-AO77 | P77: =Q77-U77-BH77 | Q77: ='德国ERP数据'!R276 | R77: - | S77: ='德国ERP数据'!Z276 | T77: 0 | U77: 0 | V77: 0 | W77: 0 | X77: ='德国ERP数据'!Q276 | Y77: /
A78: 46067 | B78: 星期六
A79: 46068 | B79: 星期日
A80: 46069 | B80: 星期一
A81: 46070 | B81: 星期二
A82: 46071 | B82: 星期三
A83: 46072 | B83: 星期四
A84: 46073 | B84: 星期五
A85: 46074 | B85: 星期六
A86: 46075 | B86: 星期日
A87: 46076 | B87: 星期一
A88: 46077 | B88: 星期二
A89: 46078 | B89: 星期三
... A161: 46150 | B161: 星期五
A162: 46151 | D162: 139.99 | H162: 88.19 | K162: =SUM(K3:K161) | L162: =SUM(L3:L161) | M162: =SUM(M3:M161) | N162: =Q162/M162 | O162: =SUM(O3:O161) | P162: =SUM(P3:P161) | Q162: =SUM(Q3:Q161) | T162: =SUM(T3:T31) | U162: =SUM(U3:U31) | V162: 1 | W162: 10 | X162: =SUM(X3:X32) | AL162: =SUM(AL3:AL161) | AM162: =SUM(AM3:AM161) | AN162: =AM162/AL162 | AO162: =SUM(AO3:AO161) | AP162: =AT162/AM162 | AQ162: =AT162/(AO162*D162) | AR162: =AO162/AM162 | AS162: =AO162/P162 | AT162: =SUM(AT3:AT161) | AU162: =AT162/X162 | AV162: =AT162/AO162 | AW162: =SUM(AW3:AW161) | AX162: =AW162/X162 | BB162: =SUM(BB44:BB92) | BC162: =BB162/X162 | BE162: =SUM(BE44:BE92) | BG162: =SUM(BG44:BG92) | BH162: =SUM(BH44:BH92) | BK162: =M162-AM162 | BL162: =O162/BK162
A163: 46152
A164: 46153
A165: 46154
A166: 46155
A167: 46156
A168: 46157
A169: 46158
A170: 46159
A171: 46160
A172: 46161
A173: 46162
A174: 46163
A175: 46164

Sheet 日常跟踪表 FR
A1: 时间 | B1: 星期 | C1: 工作内容 | D1: 售价 | E1: PD | F1: 划线价 折扣 | G1: CP | H1: 最低 成交价 | I1: SC最低 成交价毛利率 | J1: VC采购价毛利率 | K1: 移动 | L1: PC | M1: 访问 | N1: 总转化率 | O1: 实际自然订单 | P1: 自然订单 | Q1: 总订单 | R1: VC订单 | S1: B2B订单 | T1: 测评计划出单 | U1: 测评总出单 | V1: 测评完成率 | W1: Vine | X1: 销售额 | Y1: 核心词ABA排名 | AC1: sif前三页关键词收录数量 | AD1: 大类排名 | AE1: 小类排名 | AF1: 评论数 | AG1: 评分 | AH1: 广告数据 | AU1: 毛利数据 | BB1: 站外 | BH1: 库存监控
AH2: 曝光 | AI2: 点击 | AJ2: 点击率 | AK2: 订单 | AL2: CPC | AM2: ACOS | AN2: 广告转化 | AO2: 广告订单占比 | AP2: 花费（$） | AQ2: 广告花费占比 | AR2: CPA | AS2: 广告销售额 | AT2: 退款率 | AU2: 广告订单毛利P1$ | AV2: 自然订单毛利P1$ | AW2: 总订单毛利P1$ | AX2: 总订单毛利率P1 | AY2: 国内总成本$ | AZ2: 回款金额 | BA2: 测评亏损 | BB2: 站外毛利$ | BC2: 站外出单 | BD2: 站外售价 | BE2: 站外折扣 | BF2: 自然流量 | BG2: 自然转化 | BH2: VC仓库存 | BI2: 海外仓库存 | BJ2: 总库存 | BK2: VC其他订单数 | BL2: 备注
A3: 45992 | B3: 星期一 | D3: 59.99 | E3: 0 | F3: 0 | G3: 0 | H3: =D3*(1-F3)*(1-G3) | I3: - | J3: - | K3: ='法国ERP数据'!BC2 | L3: ='法国ERP数据'!BA2 | M3: =K3+L3 | N3: =IFERROR(Q3/M3,0) | O3: =P3-AK3 | P3: =Q3-U3-BC3 | Q3: ='法国ERP数据'!R2 | S3: ='法国ERP数据'!Z2 | T3: 0 | U3: 0 | V3: 0 | W3: 0 | X3: 0 | AC3: 8 | AF3: 0 | AG3: 0 | AH3: 0 | AI3: 0 | AJ3: =AI3/AH3 | AK3: 0 | AL3: =AP3/AI3 | AM3: =AP3/AS3 | AN3: =AK3/AI3 | AO3: =AK3/P3 | AP3: 0 | AQ3: =AP3/W3 | AR3: =AP3/AK3 | AS3: 0
A4: 45993 | B4: 星期二 | D4: 59.99 | E4: 0 | F4: 0 | G4: 0 | H4: =D4*(1-F4)*(1-G4) | I4: - | J4: - | K4: ='法国ERP数据'!BC3 | L4: ='法国ERP数据'!BA3 | M4: =K4+L4 | N4: =IFERROR(Q4/M4,0) | O4: =P4-AK4 | P4: =Q4-U4-BC4 | Q4: ='法国ERP数据'!R3 | S4: ='法国ERP数据'!Z3 | T4: 0 | U4: 0 | V4: 0 | W4: 0 | X4: 0 | AC4: 13 | AF4: 0 | AG4: 0 | AH4: 0 | AI4: 0 | AJ4: =AI4/AH4 | AK4: 0 | AL4: =AP4/AI4 | AM4: =AP4/AS4 | AN4: =AK4/AI4 | AO4: =AK4/P4 | AP4: 0 | AQ4: =AP4/W4 | AR4: =AP4/AK4 | AS4: 0
A5: 45994 | B5: 星期三 | D5: 59.99 | E5: 0 | F5: 0 | G5: 0 | H5: =D5*(1-F5)*(1-G5) | I5: - | J5: - | K5: ='法国ERP数据'!BC4 | L5: ='法国ERP数据'!BA4 | M5: =K5+L5 | N5: =IFERROR(Q5/M5,0) | O5: =P5-AK5 | P5: =Q5-U5-BC5 | Q5: ='法国ERP数据'!R4 | S5: ='法国ERP数据'!Z4 | T5: 0 | U5: 0 | V5: 0 | W5: 2 | X5: 0 | AC5: 14 | AF5: 0 | AG5: 0 | AH5: 0 | AI5: 0 | AJ5: =AI5/AH5 | AK5: 0 | AL5: =AP5/AI5 | AM5: =AP5/AS5 | AN5: =AK5/AI5 | AO5: =AK5/P5 | AP5: 0 | AQ5: =AP5/W5 | AR5: =AP5/AK5 | AS5: 0
A6: 45995 | B6: 星期四 | D6: 59.99 | E6: 0 | F6: 0 | G6: 0 | H6: =D6*(1-F6)*(1-G6) | I6: - | J6: - | K6: ='法国ERP数据'!BC5 | L6: ='法国ERP数据'!BA5 | M6: =K6+L6 | N6: =IFERROR(Q6/M6,0) | O6: =P6-AK6 | P6: =Q6-U6-BC6 | Q6: ='法国ERP数据'!R5 | S6: ='法国ERP数据'!Z5 | T6: 0 | U6: 0 | V6: 0 | W6: 0 | X6: 0 | AC6: 23 | AF6: 0 | AG6: 0 | AH6: 0 | AI6: 0 | AJ6: =AI6/AH6 | AK6: 0 | AL6: =AP6/AI6 | AM6: =AP6/AS6 | AN6: =AK6/AI6 | AO6: =AK6/P6 | AP6: 0 | AQ6: =AP6/W6 | AR6: =AP6/AK6 | AS6: 0
A7: 45996 | B7: 星期五 | D7: 59.99 | E7: 0 | F7: 0 | G7: 0 | H7: =D7*(1-F7)*(1-G7) | I7: - | J7: - | K7: ='法国ERP数据'!BC6 | L7: ='法国ERP数据'!BA6 | M7: =K7+L7 | N7: =IFERROR(Q7/M7,0) | O7: =P7-AK7 | P7: =Q7-U7-BC7 | Q7: ='法国ERP数据'!R6 | S7: ='法国ERP数据'!Z6 | T7: 0 | U7: 0 | V7: 0 | W7: 0 | X7: 0 | AF7: 0 | AG7: 0 | AH7: 0 | AI7: 0 | AJ7: =AI7/AH7 | AK7: 0 | AL7: =AP7/AI7 | AM7: =AP7/AS7 | AN7: =AK7/AI7 | AO7: =AK7/P7 | AP7: 0 | AQ7: =AP7/W7 | AR7: =AP7/AK7 | AS7: 0
A8: 45997 | B8: 星期六 | D8: 59.99 | E8: 0 | F8: 0 | G8: 0 | H8: =D8*(1-F8)*(1-G8) | I8: - | J8: - | K8: ='法国ERP数据'!BC7 | L8: ='法国ERP数据'!BA7 | M8: =K8+L8 | N8: =IFERROR(Q8/M8,0) | O8: =P8-AK8 | P8: =Q8-U8-BC8 | Q8: ='法国ERP数据'!R7 | S8: ='法国ERP数据'!Z7 | T8: 0 | U8: 0 | V8: 0 | W8: 0 | X8: 0 | AF8: 0 | AG8: 0 | AH8: 0 | AI8: 0 | AJ8: =AI8/AH8 | AK8: 0 | AL8: =AP8/AI8 | AM8: =AP8/AS8 | AN8: =AK8/AI8 | AO8: =AK8/P8 | AP8: 0 | AQ8: =AP8/W8 | AR8: =AP8/AK8 | AS8: 0
A9: 45998 | B9: 星期日 | D9: 59.99 | E9: 0 | F9: 0 | G9: 0 | H9: =D9*(1-F9)*(1-G9) | I9: - | J9: - | K9: ='法国ERP数据'!BC8 | L9: ='法国ERP数据'!BA8 | M9: =K9+L9 | N9: =IFERROR(Q9/M9,0) | O9: =P9-AK9 | P9: =Q9-U9-BC9 | Q9: ='法国ERP数据'!R8 | S9: ='法国ERP数据'!Z8 | T9: 1 | U9: 1 | V9: =U9/T9 | W9: 0 | X9: 0 | AF9: 0 | AG9: 0 | AH9: 0 | AI9: 0 | AJ9: =AI9/AH9 | AK9: 0 | AL9: =AP9/AI9 | AM9: =AP9/AS9 | AN9: =AK9/AI9 | AO9: =AK9/P9 | AP9: 0 | AQ9: =AP9/W9 | AR9: =AP9/AK9 | AS9: 0
A10: 45999 | B10: 星期一 | D10: 59.99 | E10: 0 | F10: 0 | G10: 0 | H10: =D10*(1-F10)*(1-G10) | I10: - | J10: - | K10: ='法国ERP数据'!BC9 | L10: ='法国ERP数据'!BA9 | M10: =K10+L10 | N10: =IFERROR(Q10/M10,0) | O10: =P10-AK10 | P10: =Q10-U10-BC10 | Q10: ='法国ERP数据'!R9 | S10: ='法国ERP数据'!Z9 | T10: 0 | U10: 0 | V10: 0 | W10: 0 | AF10: 1 | AG10: 4 | AH10: 0 | AI10: 0 | AJ10: =AI10/AH10 | AK10: 0 | AL10: =AP10/AI10 | AM10: =AP10/AS10 | AN10: =AK10/AI10 | AO10: =AK10/P10 | AP10: 0 | AQ10: =AP10/W10 | AR10: =AP10/AK10 | AS10: 0
A11: 46000 | B11: 星期二 | D11: 59.99 | E11: 0 | F11: 0 | G11: 0 | H11: =D11*(1-F11)*(1-G11) | I11: - | J11: - | K11: ='法国ERP数据'!BC10 | L11: ='法国ERP数据'!BA10 | M11: =K11+L11 | N11: =IFERROR(Q11/M11,0) | O11: =P11-AK11 | P11: =Q11-U11-BC11 | Q11: ='法国ERP数据'!R10 | S11: ='法国ERP数据'!Z10 | T11: 0 | U11: 0 | V11: 0 | W11: 0 | AF11: 1 | AG11: 4 | AH11: 0 | AI11: 0 | AJ11: =AI11/AH11 | AK11: 0 | AL11: =AP11/AI11 | AM11: =AP11/AS11 | AN11: =AK11/AI11 | AO11: =AK11/P11 | AP11: 0 | AQ11: =AP11/W11 | AR11: =AP11/AK11 | AS11: 0
A12: 46001 | B12: 星期三 | D12: 59.99 | E12: 0 | F12: 0 | G12: 0 | H12: =D12*(1-F12)*(1-G12) | I12: - | J12: - | K12: ='法国ERP数据'!BC11 | L12: ='法国ERP数据'!BA11 | M12: =K12+L12 | N12: =IFERROR(Q12/M12,0) | O12: =P12-AK12 | P12: =Q12-U12-BC12 | Q12: ='法国ERP数据'!R11 | S12: ='法国ERP数据'!Z11 | T12: 0 | U12: 0 | V12: 0 | W12: 0 | AF12: 1 | AG12: 4 | AH12: 0 | AI12: 0 | AJ12: =AI12/AH12 | AK12: 0 | AL12: =AP12/AI12 | AM12: =AP12/AS12 | AN12: =AK12/AI12 | AO12: =AK12/P12 | AP12: 0 | AQ12: =AP12/W12 | AR12: =AP12/AK12 | AS12: 0
A13: 46002 | B13: 星期四 | D13: 59.99 | E13: 0 | F13: 0 | G13: 0 | H13: =D13*(1-F13)*(1-G13) | I13: - | J13: - | K13: ='法国ERP数据'!BC12 | L13: ='法国ERP数据'!BA12 | M13: =K13+L13 | N13: =IFERROR(Q13/M13,0) | O13: =P13-AK13 | P13: =Q13-U13-BC13 | Q13: ='法国ERP数据'!R12 | S13: ='法国ERP数据'!Z12 | T13: 0 | U13: 0 | V13: 0 | W13: 0 | AF13: 1 | AG13: 4 | AH13: 0 | AI13: 0 | AJ13: =AI13/AH13 | AK13: 0 | AL13: =AP13/AI13 | AM13: =AP13/AS13 | AN13: =AK13/AI13 | AO13: =AK13/P13 | AP13: 0 | AQ13: =AP13/W13 | AR13: =AP13/AK13 | AS13: 0
A14: 46003 | B14: 星期五 | D14: 59.99 | E14: 0 | F14: 0 | G14: 0 | H14: =D14*(1-F14)*(1-G14) | I14: - | J14: - | K14: ='法国ERP数据'!BC13 | L14: ='法国ERP数据'!BA13 | M14: =K14+L14 | N14: =IFERROR(Q14/M14,0) | O14: =P14-AK14 | P14: =Q14-U14-BC14 | Q14: ='法国ERP数据'!R13 | S14: ='法国ERP数据'!Z13 | T14: 0 | U14: 0 | V14: 0 | W14: 0 | AF14: 1 | AG14: 4 | AH14: 0 | AI14: 0 | AJ14: =AI14/AH14 | AK14: 0 | AL14: =AP14/AI14 | AM14: =AP14/AS14 | AN14: =AK14/AI14 | AO14: =AK14/P14 | AP14: 0 | AQ14: =AP14/W14 | AR14: =AP14/AK14 | AS14: 0
A15: 46004 | B15: 星期六 | D15: 59.99 | E15: 0 | F15: 0 | G15: 0 | H15: =D15*(1-F15)*(1-G15) | I15: - | J15: - | K15: ='法国ERP数据'!BC14 | L15: ='法国ERP数据'!BA14 | M15: =K15+L15 | N15: =IFERROR(Q15/M15,0) | O15: =P15-AK15 | P15: =Q15-U15-BC15 | Q15: ='法国ERP数据'!R14 | S15: ='法国ERP数据'!Z14 | T15: 0 | U15: 0 | V15: 0 | W15: 0 | AF15: 1 | AG15: 4 | AH15: 0 | AI15: 0 | AJ15: =AI15/AH15 | AK15: 0 | AL15: =AP15/AI15 | AM15: =AP15/AS15 | AN15: =AK15/AI15 | AO15: =AK15/P15 | AP15: 0 | AQ15: =AP15/W15 | AR15: =AP15/AK15 | AS15: 0
A16: 46005 | B16: 星期日 | D16: 59.99 | E16: 0 | F16: 0 | G16: 0 | H16: =D16*(1-F16)*(1-G16) | I16: - | J16: - | K16: ='法国ERP数据'!BC15 | L16: ='法国ERP数据'!BA15 | M16: =K16+L16 | N16: =IFERROR(Q16/M16,0) | O16: =P16-AK16 | P16: =Q16-U16-BC16 | Q16: ='法国ERP数据'!R15 | S16: ='法国ERP数据'!Z15 | T16: 0 | U16: 0 | V16: 0 | W16: 0 | AF16: 1 | AG16: 4 | AH16: 0 | AI16: 0 | AJ16: =AI16/AH16 | AK16: 0 | AL16: =AP16/AI16 | AM16: =AP16/AS16 | AN16: =AK16/AI16 | AO16: =AK16/P16 | AP16: 0 | AQ16: =AP16/W16 | AR16: =AP16/AK16 | AS16: 0
A17: 46006 | B17: 星期一 | D17: 59.99 | E17: 0 | F17: 0 | G17: 0 | H17: =D17*(1-F17)*(1-G17) | I17: - | J17: - | K17: ='法国ERP数据'!BC16 | L17: ='法国ERP数据'!BA16 | M17: =K17+L17 | N17: =IFERROR(Q17/M17,0) | O17: =P17-AK17 | P17: =Q17-U17-BC17 | Q17: ='法国ERP数据'!R16 | S17: ='法国ERP数据'!Z16 | T17: 0 | U17: 0 | V17: 0 | W17: 0 | AF17: 1 | AG17: 4 | AH17: 0 | AI17: 0 | AJ17: =AI17/AH17 | AK17: 0 | AL17: =AP17/AI17 | AM17: =AP17/AS17 | AN17: =AK17/AI17 | AO17: =AK17/P17 | AP17: 0 | AQ17: =AP17/W17 | AR17: =AP17/AK17 | AS17: 0
A18: 46007 | B18: 星期二 | D18: 59.99 | E18: 0 | F18: 0 | G18: 0 | H18: =D18*(1-F18)*(1-G18) | I18: - | J18: - | K18: ='法国ERP数据'!BC17 | L18: ='法国ERP数据'!BA17 | M18: =K18+L18 | N18: =IFERROR(Q18/M18,0) | O18: =P18-AK18 | P18: =Q18-U18-BC18 | Q18: ='法国ERP数据'!R17 | S18: ='法国ERP数据'!Z17 | T18: 0 | U18: 0 | V18: 0 | W18: 0 | AF18: 1 | AG18: 4 | AH18: 0 | AI18: 0 | AJ18: =AI18/AH18 | AK18: 0 | AL18: =AP18/AI18 | AM18: =AP18/AS18 | AN18: =AK18/AI18 | AO18: =AK18/P18 | AP18: 0 | AQ18: =AP18/W18 | AR18: =AP18/AK18 | AS18: 0
A19: 46008 | B19: 星期三 | D19: 59.99 | E19: 0 | F19: 0 | G19: 0 | H19: =D19*(1-F19)*(1-G19) | I19: - | J19: - | K19: ='法国ERP数据'!BC18 | L19: ='法国ERP数据'!BA18 | M19: =K19+L19 | N19: =IFERROR(Q19/M19,0) | O19: =P19-AK19 | P19: =Q19-U19-BC19 | Q19: ='法国ERP数据'!R18 | S19: ='法国ERP数据'!Z18 | T19: 0 | U19: 0 | V19: 0 | W19: 0 | AF19: 1 | AG19: 4 | AH19: 0 | AI19: 0 | AJ19: =AI19/AH19 | AK19: 0 | AL19: =AP19/AI19 | AM19: =AP19/AS19 | AN19: =AK19/AI19 | AO19: =AK19/P19 | AP19: 0 | AQ19: =AP19/W19 | AR19: =AP19/AK19 | AS19: 0
A20: 46009 | B20: 星期四 | D20: 59.99 | E20: 0 | F20: 0 | G20: 0 | H20: =D20*(1-F20)*(1-G20) | I20: - | J20: - | K20: ='法国ERP数据'!BC19 | L20: ='法国ERP数据'!BA19 | M20: =K20+L20 | N20: =IFERROR(Q20/M20,0) | O20: =P20-AK20 | P20: =Q20-U20-BC20 | Q20: ='法国ERP数据'!R19 | S20: ='法国ERP数据'!Z19 | T20: 0 | U20: 0 | V20: 0 | W20: 0 | AF20: 1 | AG20: 4 | AH20: 0 | AI20: 0 | AJ20: =AI20/AH20 | AK20: 0 | AL20: =AP20/AI20 | AM20: =AP20/AS20 | AN20: =AK20/AI20 | AO20: =AK20/P20 | AP20: 0 | AQ20: =AP20/W20 | AR20: =AP20/AK20 | AS20: 0
A21: 46010 | B21: 星期五 | D21: 59.99 | E21: 0 | F21: 0 | G21: 0 | H21: =D21*(1-F21)*(1-G21) | I21: - | J21: - | K21: ='法国ERP数据'!BC20 | L21: ='法国ERP数据'!BA20 | M21: =K21+L21 | N21: =IFERROR(Q21/M21,0) | O21: =P21-AK21 | P21: =Q21-U21-BC21 | Q21: ='法国ERP数据'!R20 | S21: ='法国ERP数据'!Z20 | T21: 0 | U21: 0 | V21: 0 | W21: 0 | AF21: 1 | AG21: 4 | AH21: 0 | AI21: 0 | AJ21: =AI21/AH21 | AK21: 0 | AL21: =AP21/AI21 | AM21: =AP21/AS21 | AN21: =AK21/AI21 | AO21: =AK21/P21 | AP21: 0 | AQ21: =AP21/W21 | AR21: =AP21/AK21 | AS21: 0
... A47: 46036 | B47: 星期三 | D47: 59.99 | E47: 0 | F47: 0 | G47: 0 | H47: =D47*(1-F47)*(1-G47) | I47: - | J47: - | K47: ='法国ERP数据'!BC46 | L47: ='法国ERP数据'!BA46 | M47: =K47+L47 | N47: =IFERROR(Q47/M47,0) | O47: =P47-AK47 | P47: =Q47-U47-BC47 | Q47: ='法国ERP数据'!R46 | S47: ='法国ERP数据'!Z46 | T47: 0 | U47: 0 | V47: 0 | W47: 0 | AF47: 1 | AG47: 4 | AH47: 0 | AI47: 0 | AJ47: =AI47/AH47 | AK47: 0 | AL47: =AP47/AI47 | AM47: =AP47/AS47 | AN47: =AK47/AI47 | AO47: =AK47/P47 | AP47: 0 | AQ47: =AP47/W47 | AR47: =AP47/AK47 | AS47: 0
A48: 46037 | B48: 星期四 | S48: ='法国ERP数据'!Z47
A49: 46038 | B49: 星期五 | S49: ='法国ERP数据'!Z48
A50: 46039 | B50: 星期六 | S50: ='法国ERP数据'!Z49
A51: 46040 | B51: 星期日 | S51: ='法国ERP数据'!Z50
A52: 46041 | B52: 星期一 | S52: ='法国ERP数据'!Z51
A53: 46042 | B53: 星期二 | S53: ='法国ERP数据'!Z52
A54: 46043 | B54: 星期三 | S54: ='法国ERP数据'!Z53
A55: 46044 | B55: 星期四 | S55: ='法国ERP数据'!Z54
A56: 46045 | B56: 星期五 | S56: ='法国ERP数据'!Z55
A57: 46046 | B57: 星期六 | S57: ='法国ERP数据'!Z56
A58: 46047 | B58: 星期日 | S58: ='法国ERP数据'!Z57
A59: 46048 | B59: 星期一 | S59: ='法国ERP数据'!Z58
... A161: 46150 | B161: 星期五 | S161: ='法国ERP数据'!Z160
A162: 46151 | D162: 39.99 | M162: =SUM(M44:M92) | N162: 0.1746 | O162: =SUM(O44:O92) | P162: =SUM(P44:P92) | Q162: =SUM(Q44:Q92) | S162: ='法国ERP数据'!Z161 | X162: =SUM(X44:X92) | AH162: =SUM(AH44:AH92) | AI162: =SUM(AI44:AI92) | AJ162: =AI162/AH162 | AK162: =SUM(AK44:AK92) | AL162: =AI162/AP162 | AM162: =AP162/(AK162*D162) | AN162: =AK162/AI162 | AO162: =AK162/P162 | AP162: =SUM(AP44:AP92) | AQ162: =AP162/X162 | AS162: =AP162/AK162 | AW162: =SUM(AW44:AW92) | AX162: =AW162/X162 | AZ162: =SUM(AZ44:AZ92) | BB162: =SUM(BB44:BB92) | BC162: =SUM(BC44:BC92) | BF162: =M162-AI162 | BG162: =O162/BF162

Sheet SC定价表
A1: VC活动价 | B1: 汇率 | C1: 报价比例 | D1: 售价欧元 含税 | E1: 售价欧元 不含税 | F1: 报价欧元 不含税 | G1: 采购价 | H1: 头程 | I1: 国内总成本 | J1: 装箱数量 | K1: 移仓费/个 | L1: 换标费 0/个 | M1: 入库费/箱/0/ | N1: 装箱费 /箱 | O1: 箱唛 0/张/箱 | P1: 出库费 0/箱 | Q1: 二程运费 7.5/箱 | R1: 入库总费用 | S1: 入库单个费用rmb | T1: 利润P0 | U1: 回款扣点 | V1: 广告费占比 | W1: 广告费 | X1: 活动促销比例 | Y1: 活动促销/欧元 | Z1: 最低活动价/欧元 不含税 | AA1: 最低活动价/欧元 含税 | AB1: 利润P3 | AC1: P1--VC | AD1: P1--SC | AE1: P3对应的投资回报率=P3/国内成本 | AF1: 国内成本占比 | AG1: 一期回款金额70%/美金 | AI1: 一期回款毛利P2=回款-国内总成本-海外仓费用 | AK1: 一期回款比例=一期回款/商品成本 | AL1: 一期回款比例=一期回款/（国内+海外仓） | AM1: 一期投资回报=70^%部分的毛利/成本 | AN1: 营销费/cost
A2: 德国空净100卡航 | B2: 7.4 | C2: 0.8632 | D2: 119.99 | E2: =D2*0.84 | F2: =E2*C2 | G2: =138.5/1.13 | H2: 67.7 | I2: =SUM(G2:H2) | J2: 4 | K2: 0 | L2: 0 | M2: 0 | N2: 0 | O2: 0 | P2: 0 | Q2: 7.5 | R2: =SUM(M2:Q2)+(K2+L2)*J2 | S2: =R2/J2*B2 | T2: =F2*B2-I2-S2 | U2: 0.02 | V2: 0.15 | W2: =D2*V2*B2 | X2: 0.15 | Y2: =D2*X2 | Z2: =D2-Y2 | AA2: =Z2/0.84 | AB2: =T2-F2*U2*B2-W2-Y2*B2 | AC2: =AB2/(F2*B2) | AD2: =AB2/(E2*B2) | AE2: =AB2/I2 | AF2: =I2/B2/F2 | AG2: =F2*0.7 | AI2: =AG2*B2-S2-I2 | AK2: =AG2*B2/I2 | AL2: =AG2*B2/(I2+S2) | AM2: =AI2/I2 | AN2: =(W2/B2+Y2)/F2
A3: 德国空净100铁路 | B3: 7.4 | C3: 0.8632 | D3: 119.99 | E3: =D3*0.84 | F3: =E3*C3 | G3: =138.5/1.13 | H3: 43.22 | I3: =SUM(G3:H3) | J3: 4 | K3: 0 | L3: 0 | M3: 0 | N3: 0 | O3: 0 | P3: 0 | Q3: 7.5 | R3: =SUM(M3:Q3)+(K3+L3)*J3 | S3: =R3/J3*B3 | T3: =F3*B3-I3-S3 | U3: 0.02 | V3: 0.15 | W3: =D3*V3*B3 | X3: 0.15 | Y3: =D3*X3 | Z3: =D3-Y3 | AA3: =Z3/0.84 | AB3: =T3-F3*U3*B3-W3-Y3*B3 | AC3: =AB3/(F3*B3) | AD3: =AB3/(E3*B3) | AE3: =AB3/I3 | AF3: =I3/B3/F3 | AG3: =F3*0.7 | AI3: =AG3*B3-S3-I3 | AK3: =AG3*B3/I3 | AL3: =AG3*B3/(I3+S3) | AM3: =AI3/I3 | AN3: =(W3/B3+Y3)/F3
A4: 德国空净100海运 | B4: 7.4 | C4: 0.8632 | D4: 119.99 | E4: =D4*0.84 | F4: =E4*C4 | G4: =138.5/1.13 | H4: 20.54 | I4: =SUM(G4:H4) | J4: 4 | K4: 0 | L4: 0 | M4: 0 | N4: 0 | O4: 0 | P4: 0 | Q4: 7.5 | R4: =SUM(M4:Q4)+(K4+L4)*J4 | S4: =R4/J4*B4 | T4: =F4*B4-I4-S4 | U4: 0.02 | V4: 0.15 | W4: =D4*V4*B4 | X4: 0.15 | Y4: =D4*X4 | Z4: =D4-Y4 | AA4: =Z4/0.84 | AB4: =T4-F4*U4*B4-W4-Y4*B4 | AC4: =AB4/(F4*B4) | AD4: =AB4/(E4*B4) | AE4: =AB4/I4 | AF4: =I4/B4/F4 | AG4: =F4*0.7 | AI4: =AG4*B4-S4-I4 | AK4: =AG4*B4/I4 | AL4: =AG4*B4/(I4+S4) | AM4: =AI4/I4 | AN4: =(W4/B4+Y4)/F4
A6: SC站内推广 | B6: 汇率 | C6: 国家 | D6: 国家代码 | E6: 有无VAT | F6: 成本价(0边利) | G6: 建议价(20%边利) | H6: 实际定价 | I6: 采购价 | J6: FBA Fee | K6: 佣金比例 | L6: VAT | M6: 预估退货率 | N6: 推广费率 | O6: FBA仓储费 | P6: 其他费用 | Q6: 长 | R6: 宽 | S6: 高 | T6: 包装后实重 | U6: 体积重 | V6: 计费重 | W6: 运输方式 | X6: 运费单价 | Y6: 运费 | Z6: 利润/欧元 | AA6: 利润率/欧元
A7: 德国空净100日常价走海运 | B7: 7.4 | C7: DE | D7: DE | E7: 有 | F7: =IF(E7="有",(I7/B7+J7+Y7/B7)/(0.99999-K7-L7-M7-N7),(I7/B7+J7+Y7/B7)/(0.99999-K7-M7-N7)) | G7: =IF(E7="有",(I7/B7+J7+Y7/B7)/(0.8-K7-L7-M7-N7-O7-P7),(I7/B7+J7+Y7/B7)/(0.8-K7-M7-N7-O7-P7)) | H7: 129.99 | I7: 122.57 | J7: 5.69 | K7: 0.15 | L7: 0.16 | M7: 0.07 | N7: 0.15 | O7: =0.61/H7 | P7: 0.02 | Q7: 33.5 | R7: 26.5 | S7: 25 | T7: 2.3 | U7: =Q7*R7*S7/6000 | V7: =MAX(T7:U7) | W7: 海运 | X7: 5.55254 | Y7: =V7*X7 | Z7: =H7-SUM(K7:P7)*H7-J7-I7/B7-Y7/B7 | AA7: =Z7/H7
A8: 德国空净100活动价走海运 | B8: 7.4 | C8: DE | D8: DE | E8: 有 | F8: =IF(E8="有",(I8/B8+J8+Y8/B8)/(0.99999-K8-L8-M8-N8),(I8/B8+J8+Y8/B8)/(0.99999-K8-M8-N8)) | G8: =IF(E8="有",(I8/B8+J8+Y8/B8)/(0.8-K8-L8-M8-N8-O8-P8),(I8/B8+J8+Y8/B8)/(0.8-K8-M8-N8-O8-P8)) | H8: 119.99 | I8: 122.57 | J8: 5.69 | K8: 0.15 | L8: 0.16 | M8: 0.07 | N8: 0.15 | O8: =0.61/H8 | P8: 0.02 | Q8: 33.5 | R8: 26.5 | S8: 25 | T8: 2.3 | U8: =Q8*R8*S8/6000 | V8: =MAX(T8:U8) | W8: 海运 | X8: 5.55254 | Y8: =V8*X8 | Z8: =H8-SUM(K8:P8)*H8-J8-I8/B8-Y8/B8 | AA8: =Z8/H8
A9: 德国空净100最底价走海运 | B9: 7.4 | C9: DE | D9: DE | E9: 有 | F9: =IF(E9="有",(I9/B9+J9+Y9/B9)/(0.99999-K9-L9-M9-N9),(I9/B9+J9+Y9/B9)/(0.99999-K9-M9-N9)) | G9: =IF(E9="有",(I9/B9+J9+Y9/B9)/(0.8-K9-L9-M9-N9-O9-P9),(I9/B9+J9+Y9/B9)/(0.8-K9-M9-N9-O9-P9)) | H9: 109.99 | I9: 122.57 | J9: 5.69 | K9: 0.15 | L9: 0.16 | M9: 0.07 | N9: 0.15 | O9: =0.61/H9 | P9: 0.02 | Q9: 33.5 | R9: 26.5 | S9: 25 | T9: 2.3 | U9: =Q9*R9*S9/6000 | V9: =MAX(T9:U9) | W9: 海运 | X9: 5.55254 | Y9: =V9*X9 | Z9: =H9-SUM(K9:P9)*H9-J9-I9/B9-Y9/B9 | AA9: =Z9/H9
A11: 德国空净100最底价走铁路 | B11: 7.4 | C11: DE | D11: DE | E11: 有 | F11: =IF(E11="有",(I11/B11+J11+Y11/B11)/(0.99999-K11-L11-M11-N11),(I11/B11+J11+Y11/B11)/(0.99999-K11-M11-N11)) | G11: =IF(E11="有",(I11/B11+J11+Y11/B11)/(0.8-K11-L11-M11-N11-O11-P11),(I11/B11+J11+Y11/B11)/(0.8-K11-M11-N11-O11-P11)) | H11: 119.99 | I11: 122.57 | J11: 5.69 | K11: 0.15 | L11: 0.16 | M11: 0.07 | N11: 0.15 | O11: =0.61/H11 | P11: 0.02 | Q11: 33.5 | R11: 26.5 | S11: 25 | T11: 2.3 | U11: =Q11*R11*S11/6000 | V11: =MAX(T11:U11) | W11: 铁路 | X11: 11.68408 | Y11: =V11*X11 | Z11: =H11-SUM(K11:P11)*H11-J11-I11/B11-Y11/B11 | AA11: =Z11/H11
A12: 德国空净100最底价走铁路 | B12: 7.4 | C12: DE | D12: DE | E12: 有 | F12: =IF(E12="有",(I12/B12+J12+Y12/B12)/(0.99999-K12-L12-M12-N12),(I12/B12+J12+Y12/B12)/(0.99999-K12-M12-N12)) | G12: =IF(E12="有",(I12/B12+J12+Y12/B12)/(0.8-K12-L12-M12-N12-O12-P12),(I12/B12+J12+Y12/B12)/(0.8-K12-M12-N12-O12-P12)) | H12: 114.99 | I12: 122.57 | J12: 5.69 | K12: 0.15 | L12: 0.16 | M12: 0.07 | N12: 0.15 | O12: =0.61/H12 | P12: 0.02 | Q12: 33.5 | R12: 26.5 | S12: 25 | T12: 2.3 | U12: =Q12*R12*S12/6000 | V12: =MAX(T12:U12) | W12: 铁路 | X12: 11.68408 | Y12: =V12*X12 | Z12: =H12-SUM(K12:P12)*H12-J12-I12/B12-Y12/B12 | AA12: =Z12/H12
A13: 德国空净100最底价走铁路 | B13: 7.4 | C13: DE | D13: DE | E13: 有 | F13: =IF(E13="有",(I13/B13+J13+Y13/B13)/(0.99999-K13-L13-M13-N13),(I13/B13+J13+Y13/B13)/(0.99999-K13-M13-N13)) | G13: =IF(E13="有",(I13/B13+J13+Y13/B13)/(0.8-K13-L13-M13-N13-O13-P13),(I13/B13+J13+Y13/B13)/(0.8-K13-M13-N13-O13-P13)) | H13: 109.99 | I13: 122.57 | J13: 5.69 | K13: 0.15 | L13: 0.16 | M13: 0.07 | N13: 0.15 | O13: =0.61/H13 | P13: 0.02 | Q13: 33.5 | R13: 26.5 | S13: 25 | T13: 2.3 | U13: =Q13*R13*S13/6000 | V13: =MAX(T13:U13) | W13: 铁路 | X13: 11.68408 | Y13: =V13*X13 | Z13: =H13-SUM(K13:P13)*H13-J13-I13/B13-Y13/B13 | AA13: =Z13/H13
A16: 站外推广 | B16: 汇率 | C16: 国家 | D16: 国家代码 | E16: 有无VAT | F16: 成本价(0边利) | G16: 建议价(20%边利) | H16: 实际定价 | I16: 采购价 | J16: FBA Fee | K16: 佣金比例 | L16: VAT | M16: 预估退货率 | N16: 折扣力度 | O16: FBA仓储费 | P16: 其他费用 | Q16: 长 | R16: 宽 | S16: 高 | T16: 包装后实重 | U16: 体积重 | V16: 计费重 | W16: 运输方式 | X16: 运费单价 | Y16: 运费 | Z16: 利润/欧元 | AA16: 利润率/欧元
A17: 除螨仪站外 | B17: 7.4 | C17: DE | D17: DE | E17: 有 | F17: =I17/B17+J17+Y17/B17+(H17*(1-N17)*(K17+M17+O17+P17)) | G17: =(I17/B17+J17+Y17/B17+(H17*(1-N17)*(K17+M17+O17+P17)))/0.8 | H17: 129.99 | I17: 122.57 | J17: 5.69 | K17: 0.15 | L17: 0.16 | M17: 0.07 | N17: 0.6 | O17: =0.02/H17 | P17: 0.02 | Q17: 33.5 | R17: 26.5 | S17: 25 | T17: 2.3 | U17: =Q17*R17*S17/6000 | V17: =MAX(T17:U17) | W17: 铁路 | X17: 14.65 | Y17: =V17*X17 | Z17: =(H17*(1-N17))-I17/B17-J17-Y17/B17-(K17+M17+O17+P17)*(H17*(1-N17)) | AA17: =Z17/H17
AB18: 国家 | AC18: 二程费用 | AD18: 二程*销量占比 | AE18: 佣金 | AF18: 销量占比 | AH18: 佣金*销量占比 | AI18: 百分百-佣金，报价 | AJ18: 整箱 | AK18: 单个产品
A20: Woot美国 | B20: 汇率 | C20: 报价比例 | D20: 国家代码 | E20: 售价欧元 | F20: 报价欧元 | G20: 采购价 | H20: 头程 | I20: 国内总成本 | J20: 广告费占比 | K20: 广告费 | L20: 利润/RMB | M20: Woot利润率 | N20: 活动价 | AB20: 德国DHL | AC20: 7.5 | AD20: =AC20*AF20 | AE20: 0.1695 | AF20: 0.3 | AG20: 0.0509 | AH20: =AE20*AF20 | AI20: =100%-AE20
A21: 除螨仪 | B21: 7.4 | C21: 0.44 | D21: / | E21: 129.99 | F21: =E21*C21 | G21: 122.57 | H21: 5.69 | I21: =SUM(G21:H21) | J21: 0.15 | K21: =E21*B21*J21 | L21: =F21*B21-I21-K21 | M21: =L21/(E21*B21) | N21: =E21*C21 | AB21: 法国 | AC21: 14 | AD21: =AC21*AF21 | AE21: 0.198 | AF21: 0.2 | AG21: 0.0396 | AH21: =AE21*AF21 | AI21: =100%-AE21
AB22: 意大利 | AC22: 15 | AD22: =AC22*AF22 | AE22: 0.1846 | AF22: 0.15 | AG22: 0.0277 | AH22: =AE22*AF22 | AI22: =100%-AE22
AB23: 西班牙 | AC23: 19 | AD23: =AC23*AF23 | AE23: 0.1646 | AF23: 0.1 | AG23: 0.0165 | AH23: =AE23*AF23 | AI23: =100%-AE23
AB24: 波兰 | AC24: 13.8 | AD24: =AC24*AF24 | AE24: 0.158 | AF24: 0.1 | AG24: 0.0158 | AH24: =AE24*AF24 | AI24: =100%-AE24
AB25: 捷克 | AC25: 12.8 | AD25: =AC25*AF25 | AE25: 0.158 | AF25: 0.15 | AG25: 0.0237 | AH25: =AE25*AF25 | AI25: =100%-AE25
AB26: 英国 | AC26: 7.6 | AD26: =AC26*AF26 | AE26: 0.158 | AF26: 0.05 | AG26: 0.0237 | AH26: 0.0237 | AI26: =100%-AE26
P33: V

Sheet VC定价表
A1: 站点 | B1: SKU | C1: ASIN | D1: 产品名称 | E1: Brand | F1: 原PO售价 外币 | G1: 原建议售价(含税) 亚马逊售价-外币 | H1: 后台PO价 | I1: 对比 PO价 | J1: PO售价 外币 | K1: 建议售价(含税) 亚马逊售价-外币 | L1: 毛利 外币 | M1: 毛利率 | N1: 建议售价 不含税外币 | O1: Profit Margin (%) | P1: 亚马逊毛利 外币 | Q1: 成本 | R1: 二程外币 | S1: 装箱数 | T1: 汇率 | U1: 广告 占比 | V1: 前台广告 占比 | W1: 促销 占比 | X1: 其他 占比 | Y1: 成本 占比 | Z1: 尾程 占比 | AA1: 佣金 占比 | AB1: 广告 外币 | AC1: 促销 外币 | AD1: 其它 外币 | AE1: 佣金 外币 | AF1: 采购成本 ¥含税 | AG1: 采购成本 ¥不含税 | AH1: 头程 欧元 | AI1: 采购占比 | AJ1: 头程占比 | AK1: 头程 RMB | AL1: NET PPM | AM1: 说明 | AN1: 佣金 占比 | AO1: 2025年 3月 | AP1: 4月 | AQ1: 5月 | AR1: 6月 | AS1: 7月 | AT1: 8月 | AU1: 9月 | AV1: 10月 | AW1: 11月 | AX1: 12月 | AY1: 24年 1月 | AZ1: 2月 | BA1: 3月 | BB1: 4月 | BC1: 5月 | BD1: 6月 | BE1: 7月 | BF1: 8月 | BG1: 9月 | BH1: 10月 | BI1: 11月 | BJ1: 12月 | BK1: 25年 1月 | BL1: 2月 | BM1: 3月 | BN1: 4月 | BO1: 5月 | BP1: 6月 | BQ1: 7月 | BR1: 8月 | BS1: 9月 | BT1: 10月 | BU1: 11月 | BV1: 12月 | BW1: PO价 监控 | BX1: 运营
A2: UK | B2: R0001UK | C2: B0F1F535PC | D2: 空净100P英国灰色 | E2: HYCHIKA | F2: 87 | G2: =K2 | H2: =INDEX(#NULL!,MATCH(1,(#NULL!=A2)*(#NULL!=C2),0)) | I2: =H2=J2 | J2: 87 | K2: 119.99 | L2: =J2-Q2/T2-AE2-AB2-R2-AC2-AD2 | M2: =L2/J2 | N2: =K2/1.2 | O2: =(N2-J2)/N2 | P2: =K2/1.2-J2 | Q2: =AG2+AH2 | R2: =IFERROR(IF(A2="UK",8.95/S2,IF(A2="DE",11.43/S2,IF(A2="FR",15.27/S2,IF(A2="IT",16.34/S2,IF(A2="ES",20.62/S2,IF(A2="NL",12/S2,IF(A2="PL",15.06/S2,IF(A2="SE",18.5/S2,IF(A2="BE",15.27/S2))))))))),0) | S2: 4 | T2: 8.5 | U2: 0.1 | V2: =AB2/K2 | W2: 0.15 | X2: 0.01 | Y2: =Q2/(J2*T2) | Z2: =R2/J2 | AA2: 0.158 | AB2: =J2*U2 | AC2: =J2*W2 | AD2: =J2*X2 | AE2: =J2*AA2 | AF2: 138.5 | AG2: =AF2/1.13 | AH2: =49.7/8.5 | AI2: =AG2/(J2*T2) | AJ2: =AH2/T2/J2 | AK2: 54.2 | AL2: =(N2-J2+AE2-AC2)/N2 | AM2: (N2-J2+AE2-AC2)/N2 | AN2: UK是15.80% | AY2: ☆ | AZ2: ☆ | BA2: ☆ | BB2: ☆ | BC2: ☆ | BD2: ☆ | BE2: ☆ | BF2: ☆ | BG2: ☆ | BH2: ☆ | BI2: ☆ | BJ2: ☆ | BK2: ☆ | BL2: ☆ | BM2: ☆ | BN2: ☆ | BO2: ☆ | BP2: ☆ | BQ2: ☆ | BR2: ☆ | BS2: ☆ | BT2: ☆ | BU2: ☆ | BV2: ☆ | BX2: #VALUE!
A3: DE | B3: R0001EU | C3: B0F1F7J8V3 | D3: 空净100P德国灰色 | E3: HYCHIKA | F3: 87 | G3: =K3 | H3: =INDEX(#NULL!,MATCH(1,(#NULL!=A3)*(#NULL!=C3),0)) | I3: =H3=J3 | J3: 87 | K3: 119.99 | L3: =J3-Q3/T3-AE3-AB3-R3-AC3-AD3 | M3: =L3/J3 | N3: =K3/1.2 | O3: =(N3-J3)/N3 | P3: =K3/1.2-J3 | Q3: =AG3+AH3 | R3: =IFERROR(IF(A3="UK",8.95/S3,IF(A3="DE",11.43/S3,IF(A3="FR",15.27/S3,IF(A3="IT",16.34/S3,IF(A3="ES",20.62/S3,IF(A3="NL",12/S3,IF(A3="PL",15.06/S3,IF(A3="SE",18.5/S3,IF(A3="BE",15.27/S3))))))))),0) | S3: 4 | T3: 7.4 | U3: 0.1 | V3: =AB3/K3 | W3: 0.15 | X3: 0.01 | Y3: =Q3/(J3*T3) | Z3: =R3/J3 | AA3: 0.1695 | AB3: =J3*U3 | AC3: =J3*W3 | AD3: =J3*X3 | AE3: =J3*AA3 | AF3: 138.5 | AG3: =AF3/1.13 | AH3: =49.7/7.4 | AI3: =AG3/(J3*T3) | AJ3: =AH3/T3/J3 | AK3: 54.2 | AL3: =(N3-J3+AE3-AC3)/N3 | AM3: （建议售价 不含税外币-PO售价外币+佣金外币-促销外币）/建议售价 不含税外币 | AN3: DE是16.95% | AY3: ☆ | AZ3: ☆ | BA3: ☆ | BB3: ☆ | BC3: ☆ | BD3: ☆ | BE3: ☆ | BF3: ☆ | BG3: ☆ | BH3: ☆ | BI3: ☆ | BJ3: ☆ | BK3: ☆ | BL3: ☆ | BM3: ☆ | BN3: ☆ | BO3: ☆ | BP3: ☆ | BQ3: ☆ | BR3: ☆ | BS3: ☆ | BT3: ☆ | BU3: ☆ | BV3: ☆ | BX3: #VALUE!
A4: FR | B4: R0001EU | C4: B0F1F7J8V3 | D4: 空净100P法国灰色 | E4: HYCHIKA | F4: 87 | G4: =K4 | H4: =INDEX(#NULL!,MATCH(1,(#NULL!=A4)*(#NULL!=C4),0)) | I4: =H4=J4 | J4: 87 | K4: 119.99 | L4: =J4-Q4/T4-AE4-AB4-R4-AC4-AD4 | M4: =L4/J4 | N4: =K4/1.2 | O4: =(N4-J4)/N4 | P4: =K4/1.2-J4 | Q4: =AG4+AH4 | R4: =IFERROR(IF(A4="UK",8.95/S4,IF(A4="DE",11.43/S4,IF(A4="FR",15.27/S4,IF(A4="IT",16.34/S4,IF(A4="ES",20.62/S4,IF(A4="NL",12/S4,IF(A4="PL",15.06/S4,IF(A4="SE",18.5/S4,IF(A4="BE",15.27/S4))))))))),0) | S4: 4 | T4: 7.4 | U4: 0.1 | V4: =AB4/K4 | W4: 0.05 | X4: 0.01 | Y4: =Q4/(J4*T4) | Z4: =R4/J4 | AA4: 0.198 | AB4: =J4*U4 | AC4: =J4*W4 | AD4: =J4*X4 | AE4: =J4*AA4 | AF4: 138.5 | AG4: =AF4/1.13 | AH4: =49.7/7.4 | AI4: =AG4/(J4*T4) | AJ4: =AH4/T4/J4 | AK4: 54.2 | AL4: =(N4-J4+AE4-AC4)/N4 | AM4: (不含税MSRP-COST+佣金-促销)/不含税MSRP | AN4: FR是19.80% | AY4: ☆ | AZ4: ☆ | BA4: ☆ | BB4: ☆ | BC4: ☆ | BD4: ☆ | BE4: ☆ | BF4: ☆ | BG4: ☆ | BH4: ☆ | BI4: ☆ | BJ4: ☆ | BK4: ☆ | BL4: ☆ | BM4: ☆ | BN4: ☆ | BO4: ☆ | BP4: ☆ | BQ4: ☆ | BR4: ☆ | BS4: ☆ | BT4: ☆ | BU4: ☆ | BV4: ☆ | BX4: #VALUE!
A5: IT | B5: R0001EU | C5: B0F1F7J8V3 | D5: 空净100P意大利灰 | E5: HYCHIKA | F5: 87 | G5: =K5 | H5: =INDEX(#NULL!,MATCH(1,(#NULL!=A5)*(#NULL!=C5),0)) | I5: =H5=J5 | J5: 87 | K5: 119.99 | L5: =J5-Q5/T5-AE5-AB5-R5-AC5-AD5 | M5: =L5/J5 | N5: =K5/1.2 | O5: =(N5-J5)/N5 | P5: =K5/1.2-J5 | Q5: =AG5+AH5 | R5: =IFERROR(IF(A5="UK",8.95/S5,IF(A5="DE",11.43/S5,IF(A5="FR",15.27/S5,IF(A5="IT",16.34/S5,IF(A5="ES",20.62/S5,IF(A5="NL",12/S5,IF(A5="PL",15.06/S5,IF(A5="SE",18.5/S5,IF(A5="BE",15.27/S5))))))))),0) | S5: 4 | T5: 7.4 | U5: 0.1 | V5: =AB5/K5 | W5: 0.05 | X5: 0.01 | Y5: =Q5/(J5*T5) | Z5: =R5/J5 | AA5: 0.1846 | AB5: =J5*U5 | AC5: =J5*W5 | AD5: =J5*X5 | AE5: =J5*AA5 | AF5: 138.5 | AG5: =AF5/1.13 | AH5: =49.7/7.4 | AI5: =AG5/(J5*T5) | AJ5: =AH5/T5/J5 | AK5: 54.2 | AL5: =(N5-J5+AE5-AC5)/N5 | AM5: {(不含税MSRP-COST+COST*佣金占比-COST*促销占比)/不含税MSRP} | AN5: IT是18.46% | AY5: ☆ | AZ5: ☆ | BA5: ☆ | BB5: ☆ | BC5: ☆ | BD5: ☆ | BE5: ☆ | BF5: ☆ | BG5: ☆ | BH5: ☆ | BI5: ☆ | BJ5: ☆ | BK5: ☆ | BL5: ☆ | BM5: ☆ | BN5: ☆ | BO5: ☆ | BP5: ☆ | BQ5: ☆ | BR5: ☆ | BS5: ☆ | BT5: ☆ | BU5: ☆ | BV5: ☆ | BX5: #VALUE!
A6: ES | B6: R0001EU | C6: B0F1F7J8V3 | D6: 空净100P西班牙灰 | E6: HYCHIKA | F6: 87 | G6: =K6 | H6: =INDEX(#NULL!,MATCH(1,(#NULL!=A6)*(#NULL!=C6),0)) | I6: =H6=J6 | J6: 87 | K6: 119.99 | L6: =J6-Q6/T6-AE6-AB6-R6-AC6-AD6 | M6: =L6/J6 | N6: =K6/1.2 | O6: =(N6-J6)/N6 | P6: =K6/1.2-J6 | Q6: =AG6+AH6 | R6: =IFERROR(IF(A6="UK",8.95/S6,IF(A6="DE",11.43/S6,IF(A6="FR",15.27/S6,IF(A6="IT",16.34/S6,IF(A6="ES",20.62/S6,IF(A6="NL",12/S6,IF(A6="PL",15.06/S6,IF(A6="SE",18.5/S6,IF(A6="BE",15.27/S6))))))))),0) | S6: 4 | T6: 7.4 | U6: 0.1 | V6: =AB6/K6 | W6: 0.05 | X6: 0.01 | Y6: =Q6/(J6*T6) | Z6: =R6/J6 | AA6: 0.1646 | AB6: =J6*U6 | AC6: =J6*W6 | AD6: =J6*X6 | AE6: =J6*AA6 | AF6: 138.5 | AG6: =AF6/1.13 | AH6: =49.7/7.4 | AI6: =AG6/(J6*T6) | AJ6: =AH6/T6/J6 | AK6: 54.2 | AL6: =(N6-J6+AE6-AC6)/N6 | AM6: COST就是PO不含税售价 外币 不含税价 | AN6: ES是16.46% | AY6: ☆ | AZ6: ☆ | BA6: ☆ | BB6: ☆ | BC6: ☆ | BD6: ☆ | BE6: ☆ | BF6: ☆ | BG6: ☆ | BH6: ☆ | BI6: ☆ | BJ6: ☆ | BK6: ☆ | BL6: ☆ | BM6: ☆ | BN6: ☆ | BO6: ☆ | BP6: ☆ | BQ6: ☆ | BR6: ☆ | BS6: ☆ | BT6: ☆ | BU6: ☆ | BV6: ☆ | BX6: #VALUE!
A7: NL | B7: R0001EU | C7: B0F1F7J8V3 | D7: 空净100P荷兰灰色 | E7: HYCHIKA | F7: 97.09 | G7: =K7 | H7: =INDEX(#NULL!,MATCH(1,(#NULL!=A7)*(#NULL!=C7),0)) | I7: =H7=J7 | J7: 97.09 | K7: 135.99 | L7: =J7-Q7/T7-AE7-AB7-R7-AC7-AD7 | M7: =L7/J7 | N7: =K7/1.2 | O7: =(N7-J7)/N7 | P7: =K7/1.2-J7 | Q7: =AG7+AH7 | R7: =IFERROR(IF(A7="UK",8.95/S7,IF(A7="DE",11.43/S7,IF(A7="FR",15.27/S7,IF(A7="IT",16.34/S7,IF(A7="ES",20.62/S7,IF(A7="NL",12/S7,IF(A7="PL",15.06/S7,IF(A7="SE",18.5/S7,IF(A7="BE",15.27/S7))))))))),0) | S7: 4 | T7: 7.4 | U7: 0.1 | V7: =AB7/K7 | W7: 0.05 | X7: 0.01 | Y7: =Q7/(J7*T7) | Z7: =R7/J7 | AA7: 0.158 | AB7: =J7*U7 | AC7: =J7*W7 | AD7: =J7*X7 | AE7: =J7*AA7 | AF7: 138.5 | AG7: =AF7/1.13 | AH7: =49.7/7.4 | AI7: =AG7/(J7*T7) | AJ7: =AH7/T7/J7 | AK7: 54.2 | AL7: =(N7-J7+AE7-AC7)/N7 | AM7: COST就是PO不含税售价 外币 不含税价 | AN7: NL是15.80% | AY7: ☆ | AZ7: ☆ | BA7: ☆ | BB7: ☆ | BC7: ☆ | BD7: ☆ | BE7: ☆ | BF7: ☆ | BG7: ☆ | BH7: ☆ | BI7: ☆ | BJ7: ☆ | BK7: ☆ | BL7: ☆ | BM7: ☆ | BN7: ☆ | BO7: ☆ | BP7: ☆ | BQ7: ☆ | BR7: ☆ | BS7: ☆ | BT7: ☆ | BU7: ☆ | BV7: ☆ | BW7: =IF(H7<J7,1,0) | BX7: #VALUE!
A8: PL | B8: R0001EU | C8: B0F1F7J8V3 | D8: 空净100P波兰灰色 | E8: HYCHIKA | F8: 138.54 | G8: =K8 | H8: =INDEX(#NULL!,MATCH(1,(#NULL!=A8)*(#NULL!=C8),0)) | I8: =H8=J8 | J8: 128.54 | K8: 168 | L8: =J8-Q8/T8-AE8-AB8-R8-AC8-AD8 | M8: =L8/J8 | N8: =K8/1.2 | O8: =(N8-J8)/N8 | P8: =K8/1.2-J8 | Q8: =AG8+AH8 | R8: =IFERROR(IF(A8="UK",8.95/S8,IF(A8="DE",11.43/S8,IF(A8="FR",15.27/S8,IF(A8="IT",16.34/S8,IF(A8="ES",20.62/S8,IF(A8="NL",12/S8,IF(A8="PL",15.06/S8,IF(A8="SE",18.5/S8,IF(A8="BE",15.27/S8))))))))),0) | S8: 4 | T8: 1.6 | U8: 0.1 | V8: =AB8/K8 | W8: 0.05 | X8: 0.01 | Y8: =Q8/(J8*T8) | Z8: =R8/J8 | AA8: 0.158 | AB8: =J8*U8 | AC8: =J8*W8 | AD8: =J8*X8 | AE8: =J8*AA8 | AF8: 138.5 | AG8: =AF8/1.13 | AH8: =49.7/7.4 | AI8: =AG8/(J8*T8) | AJ8: =AH8/T8/J8 | AK8: 54.2 | AL8: =(N8-J8+AE8-AC8)/N8 | AM8: COST就是PO不含税售价 外币 不含税价 | AN8: PL是15.80% | AY8: ☆ | AZ8: ☆ | BA8: ☆ | BB8: ☆ | BC8: ☆ | BD8: ☆ | BE8: ☆ | BF8: ☆ | BG8: ☆ | BH8: ☆ | BI8: ☆ | BJ8: ☆ | BK8: ☆ | BL8: ☆ | BM8: ☆ | BN8: ☆ | BO8: ☆ | BP8: ☆ | BQ8: ☆ | BR8: ☆ | BS8: ☆ | BT8: ☆ | BU8: ☆ | BV8: ☆ | BW8: =IF(H8<J8,1,0) | BX8: #VALUE!
A9: SE | B9: R0001EU | C9: B0F1F7J8V3 | D9: 空净100P瑞典灰色 | E9: HYCHIKA | F9: 389.61 | G9: =K9 | H9: =INDEX(#NULL!,MATCH(1,(#NULL!=A9)*(#NULL!=C9),0)) | I9: =H9=J9 | J9: 389.61 | K9: 538 | L9: =J9-Q9/T9-AE9-AB9-R9-AC9-AD9 | M9: =L9/J9 | N9: =K9/1.2 | O9: =(N9-J9)/N9 | P9: =K9/1.2-J9 | Q9: =AG9+AH9 | R9: =IFERROR(IF(A9="UK",8.95/S9,IF(A9="DE",11.43/S9,IF(A9="FR",15.27/S9,IF(A9="IT",16.34/S9,IF(A9="ES",20.62/S9,IF(A9="NL",12/S9,IF(A9="PL",15.06/S9,IF(A9="SE",18.5/S9,IF(A9="BE",15.27/S9))))))))),0) | S9: 4 | T9: 0.6 | U9: 0.1 | V9: =AB9/K9 | W9: 0.05 | X9: 0.01 | Y9: =Q9/(J9*T9) | Z9: =R9/J9 | AA9: 0.223 | AB9: =J9*U9 | AC9: =J9*W9 | AD9: =J9*X9 | AE9: =J9*AA9 | AF9: 138.5 | AG9: =AF9/1.13 | AH9: =49.7/7.4 | AI9: =AG9/(J9*T9) | AJ9: =AH9/T9/J9 | AK9: 54.2 | AL9: =(N9-J9+AE9-AC9)/N9 | AM9: COST就是PO不含税售价 外币 不含税价 | AN9: SE是22.30% | AY9: ☆ | AZ9: ☆ | BA9: ☆ | BB9: ☆ | BC9: ☆ | BD9: ☆ | BE9: ☆ | BF9: ☆ | BG9: ☆ | BH9: ☆ | BI9: ☆ | BJ9: ☆ | BK9: ☆ | BL9: ☆ | BM9: ☆ | BN9: ☆ | BO9: ☆ | BP9: ☆ | BQ9: ☆ | BR9: ☆ | BS9: ☆ | BT9: ☆ | BU9: ☆ | BV9: ☆ | BW9: =IF(H9<J9,1,0) | BX9: #VALUE!
A10: BE | B10: R0001EU | C10: B0F1F7J8V3 | D10: 空净100P比利时灰 | E10: HYCHIKA | F10: 87 | G10: =K10 | H10: =INDEX(#NULL!,MATCH(1,(#NULL!=A10)*(#NULL!=C10),0)) | I10: =H10=J10 | J10: 87 | K10: 119.99 | L10: =J10-Q10/T10-AE10-AB10-R10-AC10-AD10 | M10: =L10/J10 | N10: =K10/1.2 | O10: =(N10-J10)/N10 | P10: =K10/1.2-J10 | Q10: =AG10+AH10 | R10: =IFERROR(IF(A10="UK",8.95/S10,IF(A10="DE",11.43/S10,IF(A10="FR",15.27/S10,IF(A10="IT",16.34/S10,IF(A10="ES",20.62/S10,IF(A10="NL",12/S10,IF(A10="PL",15.06/S10,IF(A10="SE",18.5/S10,IF(A10="BE",15.27/S10))))))))),0) | S10: 4 | T10: 7.4 | U10: 0.1 | V10: =AB10/K10 | W10: 0.05 | X10: 0.01 | Y10: =Q10/(J10*T10) | Z10: =R10/J10 | AA10: 0.158 | AB10: =J10*U10 | AC10: =J10*W10 | AD10: =J10*X10 | AE10: =J10*AA10 | AF10: 138.5 | AG10: =AF10/1.13 | AH10: =49.7/7.4 | AI10: =AG10/(J10*T10) | AJ10: =AH10/T10/J10 | AK10: 54.2 | AL10: =(N10-J10+AE10-AC10)/N10 | AM10: COST就是PO不含税售价 外币 不含税价 | AN10: BE是15.80% | AY10: ☆ | AZ10: ☆ | BA10: ☆ | BB10: ☆ | BC10: ☆ | BD10: ☆ | BE10: ☆ | BF10: ☆ | BG10: ☆ | BH10: ☆ | BI10: ☆ | BJ10: ☆ | BK10: ☆ | BL10: ☆ | BM10: ☆ | BN10: ☆ | BO10: ☆ | BP10: ☆ | BQ10: ☆ | BR10: ☆ | BS10: ☆ | BT10: ☆ | BU10: ☆ | BV10: ☆ | BW10: =IF(H10<J10,1,0) | BX10: #VALUE!
A11: AE | B11: R0001EU | C11: B0F1F7J8V3 | D11: 空净100P AE时灰 | E11: HYCHIKA | F11: 87 | G11: =K11 | H11: =INDEX(#NULL!,MATCH(1,(#NULL!=A11)*(#NULL!=C11),0)) | I11: =H11=J11 | J11: 87 | K11: 119.99 | L11: =J11-Q11/T11-AE11-AB11-R11-AC11-AD11 | M11: =L11/J11 | N11: =K11/1.2 | O11: =(N11-J11)/N11 | P11: =K11/1.2-J11 | Q11: =AG11+AH11 | R11: =IFERROR(IF(A11="UK",8.95/S11,IF(A11="DE",11.43/S11,IF(A11="FR",15.27/S11,IF(A11="IT",16.34/S11,IF(A11="ES",20.62/S11,IF(A11="NL",12/S11,IF(A11="PL",15.06/S11,IF(A11="SE",18.5/S11,IF(A11="BE",15.27/S11))))))))),0) | S11: 4 | T11: 7.4 | U11: 0.1 | V11: =AB11/K11 | W11: 0.05 | X11: 0.01 | Y11: =Q11/(J11*T11) | Z11: =R11/J11 | AA11: 0.158 | AB11: =J11*U11 | AC11: =J11*W11 | AD11: =J11*X11 | AE11: =J11*AA11 | AF11: 138.5 | AG11: =AF11/1.13 | AH11: =49.7/7.4 | AI11: =AG11/(J11*T11) | AJ11: =AH11/T11/J11 | AK11: 54.2 | AL11: =(N11-J11+AE11-AC11)/N11 | AM11: COST就是PO不含税售价 外币 不含税价 | AN11: BE是15.80% | AY11: ☆ | AZ11: ☆ | BA11: ☆ | BB11: ☆ | BC11: ☆ | BD11: ☆ | BE11: ☆ | BF11: ☆ | BG11: ☆ | BH11: ☆ | BI11: ☆ | BJ11: ☆ | BK11: ☆ | BL11: ☆ | BM11: ☆ | BN11: ☆ | BO11: ☆ | BP11: ☆ | BQ11: ☆ | BR11: ☆ | BS11: ☆ | BT11: ☆ | BU11: ☆ | BV11: ☆ | BW11: =IF(H11<J11,1,0) | BX11: #VALUE!

Sheet 欧洲测评总表格
A1: 站点 | B1: 类别 | C1: 提交时间 | D1: 订单号 | E1: 订单价格 | F1: 返款比率 | G1: 佣金币种 | H1: 佣金价格 | I1: 备注 | J1: 下单日期 | K1: 回评时间 | L1: 星级 | M1: reveiw链接 | N1: 删评时间 | O1: ASIN | P1: 品名 | Q1: 订单编号 | R1: 订单日期 | S1: 店铺名称 | T1: 订单状态 | U1: 销售渠道 | V1: 国家 | W1: 单价 | X1: 订单金额 | Y1: 发货日期
A2: 德国 | B2: 直评 | C2: 45791 | D2: - | H2: 30 | I2: 2025年5月25日评价于德国 | J2: - | K2: 45802 | L2: 5星 | M2: https://www.amazon.de/-/en/gp/customer-reviews/R2TXX03FE6F4KN/ref=cm_cr_arp_d_rvw_ttl?ie=UTF8&ASIN=B0F1F7J8V3 | O2: B0F1F7J8V3 | P2: 德国除螨仪 | Q2: 407-7914060-9458750 | R2: 45817.7 | S2: XLN_EU_IT | T2: Pending | U2: Amazon.it | V2: 意大利 | W2: 97.99 | X2: 97.99 | Y2: 2025-6-10周二~2025-6-10周二
A3: 德国
A4: 德国
A5: 德国
A6: 德国
A7: 德国
A8: 德国
A9: 德国
A10: 德国
A11: 德国
A12: 德国
A13: 德国
A14: 德国
... A105: 德国

Sheet 目标&经营分析
A1: 里程碑（以欧元核算）KJ | C1: 第一阶段（SC推广为主‎） | G1: 第二阶段（ po在途，SC/VC过渡期 ‎） | K1: 第三阶段（ VC主推 BD活动 ‎） | O1: 第四阶段（ VC主推 BD活动 ‎ ‎） | S1: 第五阶段（ VC主推 BD活动 ‎ ‎） | W1: 第六阶段（ VC主推 BD活动 ‎ ‎）
A2: 8 | C2: 1. 此阶段为SC售卖，主要目的为完善listing基本面，同时刺激销量来PO单； 2. SC根据推广计划表备足1个月库存，同时VC根据预测销量8周备货量分批次发往海外仓； 3. SC根据以目标为主的运营端流程完善基本面，包括前期评论布局，关键词库建立，网红视频等； 4. 根据推广计划制定营销策略，以达到目标单量从而刺激VCPO来单； 5. 预估VC上架时间，提前至少23天提报BD，一次性把能报的都报上，后续可随时取消和调整； | G2: 1. 后台关注货件入海外仓时间，提前预约入库，提醒仓库人员上架； 2. 一旦入库上架成功，及时通知Spotter业务开启PO接单； 3. 每周一和每周四关注PO来单情况，确认可用库存，24h内完成接单； 4. 关注货件实际提货时间，及实际运输时长及到仓时间； 5. VCPO库存一旦入仓，就会抢走SC购物车，但此时前台处于预售阶段，会影响转化，SC可尝试适当降低价格抢回购物车，降级幅度不得低于VC活动价； 6. 若第一周未来PO单，可同步创建手动订单刺激来PO，注意手动订单上架77天内未卖完会有罚款； | K2: 1. 切换购物车到VC，重新在广告子账号开广告推广，由于广告权重清零，这期间广告效果波动较大，需要盯紧广告预算和转化，尽快调整到稳定的状态； 2. 现在BD时长为28天，中间间隔3天，然后又是28天BD，BD价格为报价的90%（大促及节假日折扣要求为85%）； 3. 根据销量预测，PO来单及现有库存情况及时补货； 4. SC库存保留半个月左右库存，在秒杀间隔期根据库存情况及时调整购物车，或及时从海外仓补货到FBA仓； 5. 关注库存转运及其他导致库存不可售等异常情况； | O2: 1. 持续关注海外仓，VC亚马逊仓，国内到海外仓在途，海外仓到VC亚马逊仓在途库存情况，及时补货保证能接PO单，随时准备发手动订单刺激和补货PO库存； 2. 持续调整广告效果，保证VC亚马逊销量预测持续走高，保证PO单持续不断； 3. 关注库存转运及其他导致库存不可售等异常情况； 4. 关注链接BD状态，变体合并情况导致链接异常； 5. 因为转VC后，售后问题由亚马逊官方负责，需要持续关注客诉问题和每月退货情况变化，防止链接被下架； | S2: 1. 持续关注海外仓，VC亚马逊仓，国内到海外仓在途，海外仓到VC亚马逊仓在途库存情况，及时补货保证能接PO单，随时准备发手动订单刺激和补货PO库存； 2. 持续调整广告效果，保证VC亚马逊销量预测持续走高，保证PO单持续不断； 3. 关注库存转运及其他导致库存不可售等异常情况； 4. 关注链接BD状态，变体合并情况导致链接异常； 5. 因为转VC后，售后问题由亚马逊官方负责，需要持续关注客诉问题和每月退货情况变化，防止链接被下架； | W2: 1. 持续关注海外仓，VC亚马逊仓，国内到海外仓在途，海外仓到VC亚马逊仓在途库存情况，及时补货保证能接PO单，随时准备发手动订单刺激和补货PO库存； 2. 持续调整广告效果，保证VC亚马逊销量预测持续走高，保证PO单持续不断； 3. 关注库存转运及其他导致库存不可售等异常情况； 4. 关注链接BD状态，变体合并情况导致链接异常； 5. 因为转VC后，售后问题由亚马逊官方负责，需要持续关注客诉问题和每月退货情况变化，防止链接被下架；
A3: 销售周期 | C3: 第一周 | D3: 第二周 | E3: 第三周 | F3: 第四周 | G3: 第一周 | H3: 第二周 | I3: 第三周 | J3: 第四周 | K3: 第一周 | L3: 第二周 | M3: 第三周 | N3: 第四周 | O3: 第一周 | P3: 第二周 | Q3: 第三周 | R3: 第四周 | S3: 第一周 | T3: 第二周 | U3: 第三周 | V3: 第四周 | W3: 第一周 | X3: 第二周 | Y3: 第三周 | Z3: 第四周
A4: 具体时间 | B4: 日期 | C4: 5.26-6.1 | D4: 6.2-6.8 | E4: 6.9-6.15 | F4: 6.16-6.22 | G4: 6.23-6.29 | H4: 6.30-7.6 | I4: 7.7-7.13 | J4: 7.14-7.20 | K4: 7.21-7.27 | L4: 7.28-8.3 | M4: 8.4-8.10 | N4: 8.11-8.17 | O4: 8.18-8.24 | P4: 8.25-8.31 | Q4: 9.1-9.7 | R4: 9.8-9.14 | S4: 9.15-9.21 | T4: 9.22-9.28 | U4: 9.29-10.5 | V4: 10.6-10.12 | W4: 10.13-10.19 | X4: 10.20-10.26 | Y4: 10.27-11.2 | Z4: 11.3-11.9
A5: 目标竞对 | B5: 竞对综合信息（附上链接） | C5: 1. 竞对第一个月销量: 165-229 2.竞对第一个月结束时排名:从376-到了24，目前稳定在前20-30 129.99减38% 折后价79.99 3.竞对第一个月是否有参加站外,站外效果有多少倍: 没有站外 0倍无站外 4.竞对是否有woot等活动资格，跑活动时销量提升多少倍: 无 5.竞对链接： https://www.amazon.de/dp/B0DKPGKSYS | G5: 1.竞对第一个月销量: 2.竞对第一个月结束时排名: 3.竞对第一个月是否有参加站外,站外效果有多少倍: 是否有BD 7DD秒杀 4.竞对是否有woot等活动资格，跑活动时销量提升多少倍: 5.竞对链接： https://www.amazon.de/dp/B0DL5J6MK4 | K5: 1.竞对第一个月销量: 2.竞对第一个月结束时排名: 3.竞对第一个月是否有参加站外,站外效果有多少倍: 是否有BD 7DD秒杀 4.竞对是否有woot等活动资格，跑活动时销量提升多少倍: 5.竞对链接： https://www.amazon.de/dp/B0DQT1MKZ3
A6: 售价 | B6: 销售定价（日常价） | C6: 139.99 | D6: 139.99 | E6: =139.99*0.7 | F6: =139.99*0.7 | G6: =139.99*0.7 | H6: =139.99*0.7 | I6: =139.99*0.7 | J6: =139.99*0.7 | K6: =139.99*0.7 | L6: =139.99*0.7 | ... Z6: =139.99*0.7
B7: 成交价 （活动价/促销价） | C7: =C6 | D7: =D6 | E7: =E6*1 | F7: =F6*0.9 | G7: =G6*0.9 | H7: =H6*0.9 | I7: =I6*0.9*0.8 | J7: =J6*0.9 | K7: =K6*0.9*0.8 | L7: =L6*0.9 | M7: =M6*0.9*0.8 | N7: =N6*0.9 | O7: =O6*0.9*0.8 | P7: =P6*0.9 | Q7: =Q6*0.9*0.8 | R7: =R6*0.9 | S7: =S6*0.9*0.8 | T7: =T6*0.9 | U7: =U6*0.9*0.8 | V7: =V6*0.9 | W7: =W6*0.9*0.8 | X7: =X6*0.9 | Y7: =Y6*0.9*0.8 | Z7: =Z6*0.9
A8: 产品排名 | B8: 目标排名 | C8: 162 | D8: 150 | E8: 140 | F8: 120
B9: 实际排名(取周均值) | C9: 225 | D9: 115
A10: 销量 | B10: 目标总销售额 | C10: 0 | D10: =(D12-32)*D7*$A$2 | E10: =E12*E7*$A$2 | F10: =F12*F7*$A$2 | G10: =G12*G7*$A$2 | H10: =H12*H7*$A$2 | I10: =I12*I7*$A$2 | J10: =J12*J7*$A$2 | K10: =K12*K7*$A$2 | L10: =L12*L7*$A$2 | ... Z10: =Z12*Z7*$A$2
B11: 实际总销售额 | C11: =(C13-26)*C7*$A$2 | D11: =(D13-5)*D7*$A$2 | E11: =(E13)*E7*$A$2 | F11: =(F13)*F7*$A$2 | G11: =(G13)*G7*$A$2 | H11: =(H13)*H7*$A$2 | I11: =(I13)*I7*$A$2 | J11: =(J13)*J7*$A$2 | K11: =(K13)*K7*$A$2 | L11: =(L13)*L7*$A$2 | ... Z11: =(Z13)*Z7*$A$2
B12: 目标总销量 | C12: 0 | D12: 38 | E12: =3+1+2 | F12: 29 | G12: 33 | H12: 40 | I12: 51 | J12: 54 | K12: 68 | L12: 70 | M12: 80 | N12: 90 | O12: 100 | P12: 110 | Q12: 120 | R12: 130 | S12: 140 | T12: 140 | U12: 150 | V12: 150 | W12: 160 | X12: 160 | Y12: 170 | Z12: 170
B13: 实际总销量 | C13: 28 | D13: 15 | E13: 8 | F13: 29
B14: 目标日均 | C14: =C12/7 | D14: =D12/7 | E14: =E12/7 | F14: =F12/7 | G14: =G12/7 | H14: =H12/7 | I14: =I12/7 | J14: =J12/7 | ... Z14: =Z12/7
B15: 实际日均 | C15: =C13/7 | D15: =D13/7 | E15: =E13/7 | F15: =F13/7 | G15: =G13/7 | H15: =H13/7 | I15: =I13/7 | J15: =J13/7 | ... Z15: =Z13/7
B16: 预计PO单量 | C16: - | D16: - | E16: - | F16: - | G16: - | H16: - | I16: - | J16: - | K16: - | L16: - | M16: - | N16: -
B17: 实际PO单量 | C17: - | D17: - | E17: - | F17: - | G17: - | H17: - | I17: - | J17: - | K17: - | L17: - | M17: - | N17: -
A18: 利润 | B18: 目标利润额 | C18: =C10-C28-C46 | D18: =D10-D28-D46 | E18: =E10-E28-E46 | F18: =F10-F28-F46 | G18: =G10-G28-G46 | H18: =H10-H28-H46 | I18: =I10-I28-I46 | J18: =J10-J28-J46 | ... Z18: =Z10-Z28-Z46
B19: 实际利润额 | C19: =C11-C29-C55 | D19: =D11-D29-D55 | E19: =E11-E29-E55 | F19: =F11-F29-F55 | G19: =G11-G29-G55 | H19: =H11-H29-H55 | I19: =I11-I29-I55 | J19: =J11-J29-J55 | ... Z19: =Z11-Z29-Z55
B20: 目标利润率 | C20: =C18/C10 | D20: =D18/D10 | E20: =E18/E10 | F20: =F18/F10 | G20: =G18/G10 | H20: =H18/H10 | I20: =I18/I10 | J20: =J18/J10 | ... Z20: =Z18/Z10
B21: 实际利润率 | C21: =C19/C11 | D21: =D19/D11 | E21: =E19/E11 | F21: =F19/F11 | G21: =G19/G11 | H21: =H19/H11 | I21: =I19/I11 | J21: =J19/J11 | ... Z21: =Z19/Z11
A22: 营销推广 | B22: 预计广告花费 | C22: 0 | D22: 0 | E22: 0 | F22: =4*15*7*$A$2 | G22: =4*20*7*$A$2 | H22: =4*25*7*$A$2 | I22: =4*50*7*$A$2 | J22: =4*50*7*$A$2 | K22: =4*60*7*$A$2 | L22: =4*50*7*$A$2 | M22: =4*60*7*$A$2 | N22: =4*50*7*$A$2 | O22: =4*60*7*$A$2 | P22: =4*50*7*$A$2 | Q22: =4*60*7*$A$2 | R22: =4*50*7*$A$2 | S22: =4*60*7*$A$2 | T22: =4*50*7*$A$2 | U22: =4*60*7*$A$2 | V22: =4*50*7*$A$2 | W22: =4*60*7*$A$2 | X22: =4*50*7*$A$2 | Y22: =4*60*7*$A$2 | Z22: =4*50*7*$A$2
B23: 实际广告花费 | C23: 0 | D23: =5.45*A2
B24: 预计站外花费 | C24: 0 | D24: 0 | E24: 0 | F24: 0 | G24: 0 | H24: 0 | I24: 0 | J24: 0 | K24: 0 | L24: 0 | M24: 0 | N24: 0 | O24: 0 | P24: 0 | Q24: 0 | R24: 0 | S24: 0 | T24: 0 | U24: 0 | V24: 0 | W24: 0 | X24: 0 | Y24: 0 | Z24: 0
B25: 实际站外花费 | C25: 0 | D25: 0 | E25: 0 | F25: 0
B26: 预计测评费用 | C26: =1*30 | D26: =3*70*A2+4*120+2*60+6*D7*A2 | E26: =6*60+6*E7*$A$2 | F26: =6*60+6*F7*$A$2 | G26: =3*60+3*G7*$A$2 | H26: =3*60+3*H7*$A$2 | I26: =3*60+3*I7*$A$2 | J26: 0 | K26: 0 | L26: 0 | M26: 0 | N26: 0 | O26: 0 | P26: 0 | Q26: 0 | R26: 0 | S26: 0 | T26: 0 | U26: 0 | V26: 0 | W26: 0 | X26: 0 | Y26: 0 | Z26: 0
B27: 实际测评费用 | C27: =4*30+28*6.6*A2+28*0.4*A2+2*C7*A2+2*60 | D27: =5*7*A2+10*60+10*D7*A2
B28: 预计总费用汇总 | C28: =C22+C24+C26 | D28: =D22+D24+D26 | E28: =E22+E24+E26 | F28: =F22+F24+F26 | G28: =G22+G24+G26 | H28: =H22+H24+H26 | I28: =I22+I24+I26 | J28: =J22+J24+J26 | ... Z28: =Z22+Z24+Z26
B29: 实际总费用汇总 | C29: =C23+C25+C27 | D29: =D23+D25+D27 | E29: =E23+E25+E27 | F29: =F23+F25+F27 | G29: =G23+G25+G27 | H29: =H23+H25+H27 | I29: =I23+I25+I27 | J29: =J23+J25+J27 | ... Z29: =Z23+Z25+Z27
A30: 营销占比 | B30: 预计广告占比 | C30: =C22/C10 | D30: =D22/D10 | E30: =E22/E10 | F30: =F22/F10 | G30: =G22/G10 | H30: =H22/H10 | I30: =I22/I10 | J30: =J22/J10 | ... Z30: =Z22/Z10
B31: 实际广告占比 | C31: =C23/C11 | D31: =D23/D11 | E31: =E23/E11 | F31: =F23/F11 | G31: =G23/G11 | H31: =H23/H11 | I31: =I23/I11 | J31: =J23/J11 | ... Z31: =Z23/Z11
B32: 预计站外占比 | C32: =C24/C11 | D32: =D24/D11 | E32: =E24/E11 | F32: =F24/F11 | G32: =G24/G11 | H32: =H24/H11 | I32: =I24/I11 | J32: =J24/J11 | ... Z32: =Z24/Z11
B33: 实际站外占比 | C33: =C25/C11 | D33: =D25/D11 | E33: =E25/E11 | F33: =F25/F11 | G33: =G25/G11 | H33: =H25/H11 | I33: =I25/I11 | J33: =J25/J11 | ... Z33: =Z25/Z11
B34: 预计测评费用占比 | C34: =C26/C10 | D34: =D26/D10 | E34: =E26/E10 | F34: =F26/F10 | G34: =G26/G10 | H34: =H26/H10 | I34: =I26/I10 | J34: =J26/J10 | ... Z34: =Z26/Z10
B35: 实际测评费用占比 | C35: =C27/C11 | D35: =D27/D11 | E35: =E27/E11 | F35: =F27/F11 | G35: =G27/G11 | H35: =H27/H11 | I35: =I27/I11 | J35: =J27/J11 | ... Z35: =Z27/Z11
B36: 预计总费用占比 | C36: =C28/C10 | D36: =D28/D10 | E36: =E28/E10 | F36: =F28/F10 | G36: =G28/G10 | H36: =H28/H10 | I36: =I28/I10 | J36: =J28/J10 | ... Z36: =Z28/Z10
B37: 实际总费用占比 | C37: =C29/C11 | D37: =D29/D11 | E37: =E29/E11 | F37: =F29/F11 | G37: =G29/G11 | H37: =H29/H11 | I37: =I29/I11 | J37: =J29/J11 | ... Z37: =Z29/Z11
A38: 预计成本中心 | B38: 采购成本（122.57） | C38: =C12*122.57 | D38: =D12*122.57 | E38: =E12*122.57 | F38: =F12*122.57 | G38: =G12*122.57 | H38: =H12*122.57 | I38: =I12*122.57 | J38: =J12*122.57 | ... Z38: =Z12*122.57
B39: 头程成本（26） | C39: =C12*26 | D39: =D12*26 | E39: =E12*26 | F39: =F12*26 | G39: =G12*26 | H39: =H12*26 | I39: =I12*26 | J39: =J12*26 | ... Z39: =Z12*26
B40: 二程成本 | C40: 0 | D40: 0 | E40: 0 | F40: 0 | G40: 0 | H40: 0 | I40: 0 | J40: 0 | K40: 0 | L40: 0 | M40: 0 | N40: 0 | O40: 0 | P40: 0 | Q40: 0 | R40: 0 | S40: 0 | T40: 0 | U40: 0 | V40: 0 | W40: 0 | X40: 0 | Y40: 0 | Z40: 0
B41: 尾程成本（5.69） | C41: =C12*5.69*$A$2 | D41: =D12*5.69*$A$2 | E41: =E12*5.69*$A$2 | F41: =F12*5.69*$A$2 | G41: =G12*5.69*$A$2 | H41: =H12*5.69*$A$2 | I41: =I12*5.69*$A$2 | J41: =J12*5.69*$A$2 | ... Z41: =Z12*5.69*$A$2
B42: 佣金成本 | C42: =C10*C60 | D42: =D10*D60 | E42: =E10*E60 | F42: =F10*F60 | G42: =G10*G60 | H42: =H10*H60 | I42: =I10*I60 | J42: =J10*J60 | ... Z42: =Z10*Z60
B43: 仓储成本 | C43: 0 | D43: 0 | E43: 0 | F43: 0 | G43: 0 | H43: 0 | I43: 0 | J43: 0 | K43: 0 | L43: 0 | M43: 0 | N43: 0 | O43: 0 | P43: 0 | Q43: 0 | R43: 0 | S43: 0 | T43: 0 | U43: 0 | V43: 0 | W43: 0 | X43: 0 | Y43: 0 | Z43: 0
B44: 退货成本 | C44: =C62*C10 | D44: =D62*D10 | E44: =E62*E10 | F44: =F62*F10 | G44: =G62*G10 | H44: =H62*H10 | I44: =I62*I10 | J44: =J62*J10 | ... Z44: =Z62*Z10
B45: 其它成本 | C45: =C63*C10 | D45: =D63*D10 | E45: =E63*E10 | F45: =F63*F10 | G45: =G63*G10 | H45: =H63*H10 | I45: =I63*I10 | J45: =J63*J10 | ... Z45: =Z63*Z10
B46: 总成本汇总 | C46: =SUM(C38:C45) | D46: =SUM(D38:D45) | E46: =SUM(E38:E45) | F46: =SUM(F38:F45) | G46: =SUM(G38:G45) | H46: =SUM(H38:H45) | I46: =SUM(I38:I45) | J46: =SUM(J38:J45) | ... Z46: =SUM(Z38:Z45)
A47: 实际成本中心 | B47: 采购成本（122.57） | C47: =C13*122.57 | D47: =D13*122.57 | E47: =E13*122.57 | F47: =F13*122.57 | G47: =G13*122.57 | H47: =H13*122.57 | I47: =I13*122.57 | J47: =J13*122.57 | ... Z47: =Z13*122.57
B48: 头程成本（26） | C48: =C13*26 | D48: =D13*26 | E48: =E13*26 | F48: =F13*26 | G48: =G13*26 | H48: =H13*26 | I48: =I13*26 | J48: =J13*26 | ... Z48: =Z13*26
B49: 二程成本 | C49: 0 | D49: 0 | E49: 0 | F49: 0 | G49: 0 | H49: 0 | I49: 0 | J49: 0 | K49: 0 | L49: 0 | M49: 0 | N49: 0 | O49: 0 | P49: 0 | Q49: 0 | R49: 0 | S49: 0 | T49: 0 | U49: 0 | V49: 0 | W49: 0 | X49: 0 | Y49: 0 | Z49: 0
B50: 尾程成本（5.69） | C50: =C13*5.69*$A$2 | D50: =D13*5.69*$A$2 | E50: =E13*5.69*$A$2 | F50: =F13*5.69*$A$2 | G50: =G13*5.69*$A$2 | H50: =H13*5.69*$A$2 | I50: =I13*5.69*$A$2 | J50: =J13*5.69*$A$2 | ... Z50: =Z13*5.69*$A$2
B51: 佣金成本 | C51: =C11*C60 | D51: =D11*D60 | E51: =E11*E60 | F51: =F11*F60 | G51: =G11*G60 | H51: =H11*H60 | I51: =I11*I60 | J51: =J11*J60 | ... Z51: =Z11*Z60
B52: 仓储成本 | C52: 0 | D52: 0 | E52: 0 | F52: 0 | G52: 0 | H52: 0 | I52: 0 | J52: 0 | K52: 0 | L52: 0 | M52: 0 | N52: 0 | O52: 0 | P52: 0 | Q52: 0 | R52: 0 | S52: 0 | T52: 0 | U52: 0 | V52: 0 | W52: 0 | X52: 0 | Y52: 0 | Z52: 0
B53: 退货成本 | C53: =C62*C13 | D53: =D62*D13 | E53: =E62*E13 | F53: =F62*F13 | G53: =G62*G13 | H53: =H62*H13 | I53: =I62*I13 | J53: =J62*J13 | ... Z53: =Z62*Z13
B54: 其它成本 | C54: =C13*C63 | D54: =D11*D63 | E54: =E11*E63 | F54: =F11*F63 | G54: =G11*G63 | H54: =H11*H63 | I54: =I11*I63 | J54: =J11*J63 | K54: =K11*K63 | ... Z54: =Z11*Z63
B55: 总成本汇总 | C55: =SUM(C47:C54) | D55: =SUM(D47:D54) | E55: =SUM(E47:E54) | F55: =SUM(F47:F54) | G55: =SUM(G47:G54) | H55: =SUM(H47:H54) | I55: =SUM(I47:I54) | J55: =SUM(J47:J54) | ... Z55: =SUM(Z47:Z54)
A56: 成本占比 | B56: 采购占比 | C56: =C38/C11 | D56: =D38/D10 | E56: =E38/E10 | F56: =F38/F10 | G56: =G38/G10 | H56: =H38/H10 | I56: =I38/I10 | J56: =J38/J10 | K56: =K38/K10 | ... Z56: =Z38/Z10
B57: 头程占比 | C57: =C39/C11 | D57: =D39/D10 | E57: =E39/E10 | F57: =F39/F10 | G57: =G39/G10 | H57: =H39/H10 | I57: =I39/I10 | J57: =J39/J10 | K57: =K39/K10 | ... Z57: =Z39/Z10
B58: 二程占比 | C58: =C40/C11 | D58: =D40/D10 | E58: =E40/E10 | F58: =F40/F10 | G58: =G40/G10 | H58: =H40/H10 | I58: =I40/I10 | J58: =J40/J10 | K58: =K40/K10 | ... Z58: =Z40/Z10
B59: 尾程占比 | C59: =C41/C11 | D59: =D41/D10 | E59: =E41/E10 | F59: =F41/F10 | G59: =G41/G10 | H59: =H41/H10 | I59: =I41/I10 | J59: =J41/J10 | K59: =K41/K10 | ... Z59: =Z41/Z10
B60: 佣金占比 | C60: 0.15 | D60: 0.15 | E60: 0.15 | F60: 0.15 | G60: 0.15 | H60: 0.15 | I60: 0.15 | J60: 0.15 | K60: 0.15 | L60: 0.15 | M60: 0.15 | N60: 0.15 | O60: 0.15 | P60: 0.15 | Q60: 0.15 | R60: 0.15 | S60: 0.15 | T60: 0.15 | U60: 0.15 | V60: 0.15 | W60: 0.15 | X60: 0.15 | Y60: 0.15 | Z60: 0.15
B61: 仓租占比 | C61: =C43/C11 | D61: =D43/D10 | E61: =E43/E10 | F61: =F43/F10 | G61: =G43/G10 | H61: =H43/H10 | I61: =I43/I10 | J61: =J43/J10 | K61: =K43/K10 | ... Z61: =Z43/Z10
B62: 退货占比 | C62: 0 | D62: 0 | E62: 0 | F62: 0.05 | G62: 0.05 | H62: 0.05 | I62: 0.05 | J62: 0.05 | K62: 0.05 | L62: 0.05 | M62: 0.05 | N62: 0.05 | O62: 0.05 | P62: 0.05 | Q62: 0.05 | R62: 0.05 | S62: 0.05 | T62: 0.05 | U62: 0.05 | V62: 0.05 | W62: 0.05 | X62: 0.05 | Y62: 0.05 | Z62: 0.05
B63: 其它占比 | C63: 0.02 | D63: 0.02 | E63: 0.02 | F63: 0.02 | G63: 0.02 | H63: 0.02 | I63: 0.02 | J63: 0.02 | K63: 0.02 | L63: 0.02 | M63: 0.02 | N63: 0.02 | O63: 0.02 | P63: 0.02 | Q63: 0.02 | R63: 0.02 | S63: 0.02 | T63: 0.02 | U63: 0.02 | V63: 0.02 | W63: 0.02 | X63: 0.02 | Y63: 0.02 | Z63: 0.02
B64: 总占比汇总 | C64: =C46/C10 | D64: =D46/D10 | E64: =E46/E10 | F64: =F46/F10 | G64: =G46/G10 | H64: =H46/H10 | I64: =I46/I10 | J64: =J46/J10 | ... Z64: =Z46/Z10
A65: 库存 | B65: 周总库存盘点 | C65: 1500 | D65: =C65-C13 | E65: =D65-D13 | F65: =E65-E13 | G65: =F65-F13 | H65: =G65-G12 | I65: =H65-H12 | J65: =I65-I12 | K65: =J65-J12 | L65: =K65-K12 | M65: =L65-L12 | N65: =M65-M12 | O65: =N65-N12 | ... Z65: =Y65-Y12
B66: 总库存资金 | C66: =C65*122.57 | D66: =D65*122.57 | E66: =E65*122.57 | F66: =F65*122.57 | G66: =G65*122.57 | H66: =H65*122.57 | I66: =I65*122.57 | J66: =J65*122.57 | ... Z66: =Z65*122.57
A67: 总预算 | B67: 预计资金占用 | C67: =C66+C38+C39+C43+C45+C28 | D67: =D66+D38+D39+D43+D45+D28 | E67: =E66+E38+E39+E43+E45+E28 | F67: =F66+F38+F39+F43+F45+F28 | G67: =G66+G38+G39+G43+G45+G28 | H67: =H66+H38+H39+H43+H45+H28 | I67: =I66+I38+I39+I43+I45+I28 | J67: =J66+J38+J39+J43+J45+J28 | ... M67: =M66+M38+M39+M43+M45+M28 | N67: =N66+#NULL!+N28+N38+N43 | O67: =O66+#NULL!+O28+O38+O43 | P67: =P66+#NULL!+P28+P38+P43 | Q67: =Q66+#NULL!+Q28+Q38+Q43 | R67: =R66+#NULL!+R28+R38+R43 | S67: =S66+#NULL!+S28+S38+S43 | T67: =T66+#NULL!+T28+T38+T43 | U67: =U66+#NULL!+U28+U38+U43 | ... Z67: =Z66+#NULL!+Z28+Z38+Z43 | AA67: =SUM(C67:Z67)
B68: 实际资金占用 | C68: =C66+C38+C39+C40+C43+C45+C29 | D68: =D66+D38+D39+D40+D43+D45+D29 | E68: =E66+E38+E39+E40+E43+E45+E29 | F68: =F66+F38+F39+F40+F43+F45+F29 | G68: =G66+G38+G39+G40+G43+G45+G29 | H68: =H66+H38+H39+H40+H43+H45+H29 | I68: =I66+I38+I39+I40+I43+I45+I29 | J68: =J66+J38+J39+J40+J43+J45+J29 | ... M68: =M66+M38+M39+M40+M43+M45+M29 | N68: =N66+#NULL!+N44+N41+N29 | O68: =O66+#NULL!+O44+O41+O29 | P68: =P66+#NULL!+P44+P41+P29 | Q68: =Q66+#NULL!+Q44+Q41+Q29 | R68: =R66+#NULL!+R44+R41+R29 | S68: =S66+#NULL!+S44+S41+S29 | T68: =T66+#NULL!+T44+T41+T29 | U68: =U66+#NULL!+U44+U41+U29 | ... Z68: =Z66+#NULL!+Z44+Z41+Z29 | AA68: =SUM(C68:Z68)

Sheet 目标&经营分析表-旧
A1: 里程碑（以欧元核算） | C1: 第一阶段（SC推广为主‎） | G1: 第二阶段（ po在途，SC/VC过渡期 ‎） | K1: 第三阶段（ VC主推 BD活动 ‎） | O1: 第四阶段（ VC主推 BD活动 ‎ ‎） | S1: 第五阶段（ VC主推 BD活动 ‎ ‎） | W1: 第六阶段（ VC主推 BD活动 ‎ ‎）
A2: 注意事项 | C2: 1. 此阶段为SC售卖，主要目的为完善listing基本面，同时刺激销量来PO单； 2. SC根据推广计划表备足1个月库存，同时VC根据预测销量8周备货量分批次发往海外仓； 3. SC根据以目标为主的运营端流程完善基本面，包括前期评论布局，关键词库建立，网红视频等； 4. 根据推广计划制定营销策略，以达到目标单量从而刺激VCPO来单； 5. 预估VC上架时间，提前至少23天提报BD，一次性把能报的都报上，后续可随时取消和调整； | G2: 1. 后台关注货件入海外仓时间，提前预约入库，提醒仓库人员上架； 2. 一旦入库上架成功，及时通知Spotter业务开启PO接单； 3. 每周一和每周四关注PO来单情况，确认可用库存，24h内完成接单； 4. 关注货件实际提货时间，及实际运输时长及到仓时间； 5. VCPO库存一旦入仓，就会抢走SC购物车，但此时前台处于预售阶段，会影响转化，SC可尝试适当降低价格抢回购物车，降级幅度不得低于VC活动价； 6. 若第一周未来PO单，可同步创建手动订单刺激来PO，注意手动订单上架77天内未卖完会有罚款； | K2: 1. 切换购物车到VC，重新在广告子账号开广告推广，由于广告权重清零，这期间广告效果波动较大，需要盯紧广告预算和转化，尽快调整到稳定的状态； 2. 现在BD时长为28天，中间间隔3天，然后又是28天BD，BD价格为报价的90%（大促及节假日折扣要求为85%）； 3. 根据销量预测，PO来单及现有库存情况及时补货； 4. SC库存保留半个月左右库存，在秒杀间隔期根据库存情况及时调整购物车，或及时从海外仓补货到FBA仓； 5. 关注库存转运及其他导致库存不可售等异常情况； | O2: 1. 持续关注海外仓，VC亚马逊仓，国内到海外仓在途，海外仓到VC亚马逊仓在途库存情况，及时补货保证能接PO单，随时准备发手动订单刺激和补货PO库存； 2. 持续调整广告效果，保证VC亚马逊销量预测持续走高，保证PO单持续不断； 3. 关注库存转运及其他导致库存不可售等异常情况； 4. 关注链接BD状态，变体合并情况导致链接异常； 5. 因为转VC后，售后问题由亚马逊官方负责，需要持续关注客诉问题和每月退货情况变化，防止链接被下架； | S2: 1. 持续关注海外仓，VC亚马逊仓，国内到海外仓在途，海外仓到VC亚马逊仓在途库存情况，及时补货保证能接PO单，随时准备发手动订单刺激和补货PO库存； 2. 持续调整广告效果，保证VC亚马逊销量预测持续走高，保证PO单持续不断； 3. 关注库存转运及其他导致库存不可售等异常情况； 4. 关注链接BD状态，变体合并情况导致链接异常； 5. 因为转VC后，售后问题由亚马逊官方负责，需要持续关注客诉问题和每月退货情况变化，防止链接被下架； | W2: 1. 持续关注海外仓，VC亚马逊仓，国内到海外仓在途，海外仓到VC亚马逊仓在途库存情况，及时补货保证能接PO单，随时准备发手动订单刺激和补货PO库存； 2. 持续调整广告效果，保证VC亚马逊销量预测持续走高，保证PO单持续不断； 3. 关注库存转运及其他导致库存不可售等异常情况； 4. 关注链接BD状态，变体合并情况导致链接异常； 5. 因为转VC后，售后问题由亚马逊官方负责，需要持续关注客诉问题和每月退货情况变化，防止链接被下架；
A3: 销售周期 | C3: 第一周 | D3: 第二周 | E3: 第三周 | F3: 第四周 | G3: 第一周 | H3: 第二周 | I3: 第三周 | J3: 第四周 | K3: 第一周 | L3: 第二周 | M3: 第三周 | N3: 第四周 | O3: 第一周 | P3: 第二周 | Q3: 第三周 | R3: 第四周 | S3: 第一周 | T3: 第二周 | U3: 第三周 | V3: 第四周 | W3: 第一周 | X3: 第二周 | Y3: 第三周 | Z3: 第四周
A4: 具体时间 | B4: 日期 | C4: 5.26-6.1 | D4: 6.2-6.8 | E4: 6.9-6.15 | F4: 6.16-6.22 | G4: 6.23-6.29 | H4: 6.30-7.6 | I4: 7.7-7.13 | J4: 7.14-7.20 | K4: 7.21-7.27 | L4: 7.28-8.3 | M4: 8.4-8.10 | N4: 8.11-8.17 | O4: 8.18-8.24 | P4: 8.25-8.31 | Q4: 9.1-9.7 | R4: 9.8-9.14 | S4: 9.15-9.21 | T4: 9.22-9.28 | U4: 9.29-10.5 | V4: 10.6-10.12 | W4: 10.13-10.19 | X4: 10.20-10.26 | Y4: 10.27-11.2 | Z4: 11.3-11.9
A5: 目标竞对 | B5: 竞对综合信息（附上链接） | C5: 1. 竞对第一个月销量: 165-229 2.竞对第一个月结束时排名:从376-到了24，目前稳定在前20-30 129.99减38% 折后价79.99 3.竞对第一个月是否有参加站外,站外效果有多少倍: 没有站外 0倍无站外 4.竞对是否有woot等活动资格，跑活动时销量提升多少倍: 无 5.竞对链接： https://www.amazon.de/dp/B0DKPGKSYS | G5: 1.竞对第一个月销量: 2.竞对第一个月结束时排名: 3.竞对第一个月是否有参加站外,站外效果有多少倍: 是否有BD 7DD秒杀 4.竞对是否有woot等活动资格，跑活动时销量提升多少倍: 5.竞对链接： https://www.amazon.de/dp/B0DL5J6MK4 | K5: 1.竞对第一个月销量: 2.竞对第一个月结束时排名: 3.竞对第一个月是否有参加站外,站外效果有多少倍: 是否有BD 7DD秒杀 4.竞对是否有woot等活动资格，跑活动时销量提升多少倍: 5.竞对链接： https://www.amazon.de/dp/B0DQT1MKZ3
A6: 售价 | B6: 销售定价（日常价）（自填） | C6: 139.99 | D6: 139.99 | E6: 139.99 | F6: 139.99 | G6: 139.99 | H6: 139.99 | I6: 139.99 | J6: 139.99 | K6: 139.99 | L6: 139.99 | M6: 139.99 | N6: 139.99 | O6: 139.99 | P6: 129.99 | Q6: 129.99 | R6: 129.99 | S6: 129.99 | T6: 129.99 | U6: 129.99 | V6: 129.99 | W6: 129.99 | X6: 129.99 | Y6: 129.99 | Z6: 129.99
B7: 活动价/促销价（自填） | C7: =C6*1 | D7: 118.99 | E7: 118.99 | F7: 118.99 | G7: 118.99 | H7: 118.99 | I7: 118.99 | J7: 118.99 | K7: 118.99 | L7: 118.99 | M7: 118.99 | N7: 118.99 | O7: 118.99 | P7: 121.99 | Q7: 121.99 | R7: 121.99 | S7: 129.99 | T7: 129.99 | U7: 129.99 | V7: 129.99 | W7: 129.99 | X7: 129.99 | Y7: 129.99 | Z7: 129.99
A8: 产品排名 | B8: 目标排名（自填）
B9: 实际排名(取周均值)（自填）
A10: 销量 | B10: 目标总销售额（自填） | C10: =C12*C6 | D10: =D12*D6 | E10: =E12*E6 | F10: =F12*F6 | G10: =G12*G6 | H10: =H12*H6 | I10: =I12*I6 | J10: =J12*J6 | K10: =K12*K7 | L10: =L12*L7 | M10: =M12*M7 | N10: =N12*N7 | O10: =O12*O7 | P10: =P12*P7 | Q10: =Q12*Q7 | R10: =R12*R7 | ... Z10: =Z12*Z7
B11: 实际总销售额（自填）
B12: 目标总销量（自填） | C12: 44 | D12: 74 | E12: 48 | F12: 48 | G12: 52 | H12: 50 | I12: 58 | J12: 50 | K12: 55 | L12: 65 | M12: 72 | N12: 75 | O12: 80 | P12: 85 | Q12: 95 | R12: 100 | S12: 80 | T12: 60 | U12: 65 | V12: 75 | W12: 80 | X12: 90 | Y12: 95 | Z12: 100
B13: 实际总销量（自填）
B14: 目标日均（自填） | C14: =C12/7 | D14: =D12/7 | E14: =E12/7 | F14: =F12/7 | G14: =G12/7 | H14: =H12/7 | I14: =I12/7 | J14: =J12/7 | ... Z14: =Z12/7
B15: 实际日均（自填）
B16: 预计PO单量（自填） | G16: 45 | H16: 45 | I16: 48 | J16: 50 | K16: 48 | L16: 48 | M16: 80 | N16: 48 | O16: 48 | P16: 48 | Q16: 48 | R16: 48
B17: 实际PO单量（自填）
A18: 利润率 | B18: 目标利润额（公式） | C18: =C10*C20 | D18: =D10*D20 | E18: =E10*E20 | F18: =F10*F20 | G18: =G10*G20 | H18: =H10*H20 | I18: =I10*I20 | J18: =J10*J20 | ... Z18: =Z10*Z20
B19: 实际利润额（自填）
B20: 目标利润率（自填） | C20: 0.057 | D20: 0.087 | E20: 0.107 | F20: 0.127 | G20: 0.136 | H20: 0.146 | I20: 0.156 | J20: 0.15 | K20: 0.15 | L20: 0.15 | M20: 0.15 | N20: 0.15 | O20: 0.15 | P20: 0.15 | Q20: 0.15 | R20: 0.15 | S20: 0.15 | T20: 0.15 | U20: 0.15 | V20: 0.15 | W20: 0.15 | X20: 0.15 | Y20: 0.15 | Z20: 0.15
B21: 实际利润率（公式） | X21: =IFERROR(X19/X11,0) | Y21: =IFERROR(Y19/Y11,0) | Z21: =IFERROR(Z19/Z11,0)
A22: 营销推广 | B22: 预计广告花费（自填） | C22: =C10*0.15 | D22: =D10*0.15 | E22: =E10*0.15 | F22: =F10*0.15 | G22: =G10*0.12 | H22: =H10*0.12 | I22: =I10*0.1 | J22: =J10*0.1 | K22: =K10*0.08 | L22: =L10*0.08 | M22: =M10*0.08 | N22: =N10*0.08 | O22: =O10*0.08 | P22: =P10*0.08 | Q22: =Q10*0.08 | R22: =R10*0.08 | S22: =S10*0.06 | T22: =T10*0.06 | U22: =U10*0.06 | V22: =V10*0.06 | W22: =W10*0.05 | X22: =X10*0.05 | Y22: =Y10*0.05 | Z22: =Z10*0.05
B23: 实际广告花费（自填） | Q23: 20.83
B24: 预计站外推广花费（自填） | C24: 0 | D24: 0 | E24: 0 | F24: 0 | G24: 0 | H24: 0 | I24: 0 | J24: 0 | K24: 0 | L24: 0 | M24: 0 | N24: 0 | O24: 0 | P24: 0 | Q24: 0 | R24: 0 | S24: 0 | T24: 0 | U24: 0 | V24: 0 | W24: 0 | X24: 0 | Y24: 0 | Z24: 0
B25: 实际站外推广花费（自填） | Q25: 0
B26: 预计其他辅助花费（自填） | C26: 270 | D26: 0 | E26: 0 | F26: 0 | G26: 0 | H26: 0 | I26: 0 | J26: 0 | K26: 0 | L26: 0 | M26: 0 | N26: 0 | O26: 0 | P26: 0 | Q26: 0 | R26: 0 | S26: 0 | T26: 0 | U26: 0 | V26: 0 | W26: 0 | X26: 0 | Y26: 0 | Z26: 0
B27: 实际其他辅助花费（自填）
B28: 预计所有营销费用汇总（公式） | C28: =C22+C24+C26+C27 | D28: =D22+D24+D26 | E28: =E22+E24+E26 | F28: =F22+F24+F26 | G28: =G22+G24+G26 | H28: =H22+H24+H26 | I28: =I22+I24+I26 | J28: =J22+J24+J26 | K28: =K22+K24+K26 | ... Z28: =Z22+Z24+Z26
B29: 预计所有营销费用占比（公式） | C29: =C28/C10 | D29: =D28/D10 | E29: =E28/E10 | F29: =F28/F10 | G29: =G28/G10 | H29: =H28/H10 | I29: =I28/I10 | J29: =J28/J10 | ... Z29: =Z28/Z10
B30: 实际所有营销费用汇总（公式） | C30: =C23+C25+C27 | D30: =D23+D25+D27 | E30: =E23+E25+E27 | F30: =F23+F25+F27 | G30: =G23+G25+G27 | H30: =H23+H25+H27 | I30: =I23+I25+I27 | J30: =J23+J25+J27 | ... Z30: =Z23+Z25+Z27
B31: 实际所有营销费用占比（公式） | C31: =IFERROR(C30/C11,0) | D31: =IFERROR(D30/D11,0) | E31: =IFERROR(E30/E11,0) | F31: =IFERROR(F30/F11,0) | G31: =IFERROR(G30/G11,0) | H31: =IFERROR(H30/H11,0) | I31: =IFERROR(I30/I11,0) | J31: =IFERROR(J30/J11,0) | ... Z31: =IFERROR(Z30/Z11,0)
A32: 成本中心 | B32: 预计产品成本（半公式） | C32: =122.56*C12/7.4 | D32: =122.56*D12/7.4 | E32: =122.56*E12/7.4 | F32: =122.56*F12/7.4 | G32: =122.56*G12/7.4 | H32: =122.56*H12/7.4 | I32: =122.56*I12/7.4 | J32: =122.56*J12/7.4 | ... P32: =122.56*P12/7.4 | Q32: =46*Q12/7.34 | R32: =46*R12/7.34 | S32: =46*S12/7.34 | T32: =46*T12/7.34 | U32: =46*U12/7.34 | V32: =46*V12/7.34 | W32: =46*W12/7.34 | X32: =46*X12/7.34 | ... Z32: =46*Z12/7.34
B33: 预计产品成本占比（公式） | C33: =C32/C10 | D33: =D32/D10 | E33: =E32/E10 | F33: =F32/F10 | G33: =G32/G10 | H33: =H32/H10 | I33: =I32/I10 | J33: =J32/J10 | ... Z33: =Z32/Z10
B34: 实际产品成本（半公式） | C34: =70*C13/6.8 | D34: =70*D13/6.8 | E34: =70*E13/6.8 | F34: =70*F13/6.8 | G34: =70*G13/6.8 | H34: =70*H13/6.8 | I34: =70*I13/6.8 | J34: =70*J13/6.8 | ... Z34: =70*Z13/6.8
B35: 预计物流成本（半公式） | C35: =5.69*C12/7.4+54.2*C12 | D35: =5.69*D12/7.4+54.2*D12 | E35: =5.69*E12/7.4+54.2*E12 | F35: =5.69*F12/7.4+54.2*F12 | G35: =5.69*G12/7.4+54.2*G12 | H35: =5.69*H12/7.4+54.2*H12 | I35: =5.69*I12/7.4+54.2*I12 | J35: =5.69*J12/7.4+54.2*J12 | ... Z35: =5.69*Z12/7.4+54.2*Z12
B36: 实际物流成本（半公式） | C36: =2.78*C13/7.34+2.84*C13 | D36: =2.78*D13/7.34+2.84*D13 | E36: =2.78*E13/7.34+2.84*E13 | F36: =2.78*F13/7.34+2.84*F13 | G36: =2.78*G13/7.34+2.84*G13 | H36: =2.78*H13/7.34+2.84*H13 | I36: =2.78*I13/7.34+2.84*I13 | J36: =2.78*J13/7.34+2.84*J13 | ... P36: =2.78*P13/7.34+2.84*P13 | Q36: =10.32*Q13/6.8+6.62*Q13 | R36: =10.32*R13/6.8+6.62*R13 | S36: =10.32*S13/6.8+6.62*S13 | T36: =10.32*T13/6.8+6.62*T13 | U36: =10.32*U13/6.8+6.62*U13 | V36: =10.32*V13/6.8+6.62*V13 | W36: =10.32*W13/6.8+6.62*W13 | X36: =10.32*X13/6.8+6.62*X13 | ... Z36: =10.32*Z13/6.8+6.62*Z13
B37: 预计物流成本占比（公式） | C37: =C35/C10 | D37: =D35/D10 | E37: =E35/E10 | F37: =F35/F10 | G37: =G35/G10 | H37: =H35/H10 | I37: =I35/I10 | J37: =J35/J10 | ... Z37: =Z35/Z10
B38: 预计固定成本（自填） | C38: =(3.84+46)*C39 | D38: =(3.84+46)*D39 | E38: =(3.84+46)*E39 | F38: =(3.84+46)*F39 | G38: =(3.84+46)*G39 | H38: =(3.84+46)*H39 | I38: =(3.84+46)*I39 | J38: =(3.84+46)*J39 | ... Z38: =(3.84+46)*Z39
A39: 库存 | B39: 周总库存盘点 （自填） | C39: 1500 | D39: =C39-C12 | E39: =D39-D12 | F39: =E39-E12 | G39: =F39-F12 | H39: =G39-G12 | I39: =H39-H12 | J39: =I39-I12 | K39: =J39-J12 | ... Z39: =Y39-Y12
B40: 总库存资金（自填） | C40: =C39*64 | D40: =D39*64 | E40: =E39*64 | F40: =F39*64 | G40: =G39*64 | H40: =H39*64 | I40: =I39*64 | J40: =J39*64 | ... Z40: =Z39*64
A41: 总预算 | B41: 预计资金占用（公式） | C41: =C40+C38+C28+C32+C35 | D41: =D40+D38+D28+D32+D35 | E41: =E40+E38+E28+E32+E35 | F41: =F40+F38+F28+F32+F35 | G41: =G40+G38+G28+G32+G35 | H41: =H40+H38+H28+H32+H35 | I41: =I40+I38+I28+I32+I35 | J41: =J40+J38+J28+J32+J35 | ... Z41: =Z40+Z38+Z28+Z32+Z35 | AA41: =SUM(C41:Z41)
B42: 实际资金占用（公式） | C42: =C40+C38+C36+C34+C30 | D42: =D40+D38+D36+D34+D30 | E42: =E40+E38+E36+E34+E30 | F42: =F40+F38+F36+F34+F30 | G42: =G40+G38+G36+G34+G30 | H42: =H40+H38+H36+H34+H30 | I42: =I40+I38+I36+I34+I30 | J42: =J40+J38+J36+J34+J30 | ... Z42: =Z40+Z38+Z36+Z34+Z30 | AA42: =SUM(C42:Z42)

Sheet 德国ERP数据
A1: 时间 | B1: SKU | C1: 父ASIN | D1: ASIN | E1: MSKU | F1: 品名 | G1: 售价(总价) | H1: 价格 | I1: FBA-可售 | J1: FBM可售 | K1: AWD在库 | L1: AWD可用量 | M1: AWD待发货量 | N1: AWD标发在途 | O1: 可用库存 | P1: 销量 | Q1: 销售额 | R1: 订单量 | S1: 净销售额 | T1: 销量环比 | U1: 销售额环比 | V1: 订单量环比 | W1: 销量同比 | X1: 订单量同比 | Y1: 销量额同比 | Z1: B2B 销量 | AA1: B2B 销售额 | AB1: B2B 订单量 | AC1: FBM买家运费 | AD1: 促销销量 | AE1: 促销销售额 | AF1: 促销订单量 | AG1: 促销折扣 | AH1: 日均销量 | AI1: 日均销售额 | AJ1: 日均订单量 | AK1: 销售均价 | AL1: 大类排名 | AM1: 小类排名 | AN1: 退款量 | AO1: 退款金额 | AP1: 退款率 | AQ1: 评分 | AR1: 评论数 | AS1: 留评率 | AT1: 结算毛利润 | AU1: 订单毛利润 | AV1: 结算毛利率 | AW1: 订单毛利率 | AX1: ROI | AY1: 退货量 | AZ1: 退货率 | BA1: Sessions-Browser | BB1: Sessions-Browser-Percentage | BC1: Sessions-Mobile | BD1: Sessions-Mobile-Percentage | BE1: Sessions-Total | BF1: PV-Browser | BG1: PV-Mobile | BH1: PV-Total | BI1: CVR | BJ1: 销量CVR | BK1: Buybox赢得率 | BL1: CPC | BM1: CTR | BN1: 广告花费 | BO1: SB广告费 | BP1: SBV广告费 | BQ1: SD广告费 | BR1: SP广告费 | BS1: ROAS | BT1: ACOS | BU1: ACoAS | BV1: ASoAS | BW1: CPO | BX1: CPU | BY1: CPM | BZ1: 广告销售额 | CA1: 广告订单量 | CB1: 直接成交订单量 | CC1: 直接成交销售额 | CD1: 广告订单占比 | CE1: 广告CVR | CF1: 展示 | CG1: 点击 | CH1: 自然订单量 | CI1: 自然点击量 | CJ1: 自然CVR | CK1: Sessions-Percentage | CL1: Unit-Sessions-Percentage | CM1: PV-Browser-Percentage | CN1: PV-Mobile-Percentage | CO1: PV-Percentage | CP1: Sessions-Browser(B2B) | CQ1: Sessions-Browser-Percentage(B2B) | CR1: Sessions-Mobile(B2B) | CS1: Sessions-Mobile-Percentage(B2B) | CT1: Sessions-Total(B2B) | CU1: Sessions-Percentage(B2B) | CV1: Unit-Sessions-Percentage(B2B) | CW1: PV-Browser(B2B) | CX1: PV-Browser-Percentage(B2B) | CY1: PV-Mobile(B2B) | CZ1: PV-Mobile-Percentage(B2B) | DA1: PV-Total(B2B) | DB1: PV-Percentage(B2B) | DC1: CVR(B2B) | DD1: 销量CVR(B2B) | DE1: Buybox赢得率(B2B) | DF1: 运营日志
A2: 2025-12-01 | B2: R0007EU | C2: B0FNMBQFBC | D2: B0FNMBQFBC | E2: R0007EU | F2: HYCHIKA-AP100A-空净 | G2: 64.99 | H2: 64.99 | I2: 0 | J2: 0 | K2: 0 | L2: 0 | M2: 0 | N2: 0 | O2: 0 | P2: 0 | Q2: 0 | R2: 0 | S2: 0 | T2: 0.00% | U2: 0.00% | V2: 0.00% | W2: 0.00% | X2: 0.00% | Y2: 0.00% | Z2: 0 | AA2: 0 | AB2: 0 | AC2: 0 | AD2: 0 | AE2: 0 | AF2: 0 | AG2: 0 | AH2: 0 | AI2: 0 | AJ2: 0 | AK2: 0 | AN2: 0 | AO2: 0 | AP2: 0.00% | AQ2: 0 | AR2: 0 | AS2: 0.00% | AT2: ** | AU2: ** | AV2: ** | AW2: ** | AX2: ** | AY2: 0 | AZ2: 0.00% | BA2: 0 | BB2: 0.00% | BC2: 0 | BD2: 0.00% | BE2: 0 | BF2: 0 | BG2: 0 | BH2: 0 | BI2: 0.00% | BJ2: 0.00% | BK2: 0.00% | BL2: 0 | BM2: 0.00% | BN2: 0 | BO2: 0 | BP2: 0 | BQ2: 0 | BR2: 0 | BS2: 0 | BT2: 0.00% | BU2: 0.00% | BV2: 0.00% | BW2: 0 | BX2: 0 | BY2: 0 | BZ2: 0 | CA2: 0 | CB2: 0 | CC2: 0 | CD2: 0.00% | CE2: 0.00% | CF2: 0 | CG2: 0 | CH2: 0 | CI2: 0 | CJ2: 0.00% | CK2: 0.00% | CL2: 0.00% | CM2: 0.00% | CN2: 0.00% | CO2: 0.00% | CP2: 0 | CQ2: 0.00% | CR2: 0 | CS2: 0.00% | CT2: 0 | CU2: 0.00% | CV2: 0.00% | CW2: 0 | CX2: 0.00% | CY2: 0 | CZ2: 0.00% | DA2: 0 | DB2: 0.00% | DC2: 0.00% | DD2: 0.00% | DE2: 0.00%
A3: 2025-12-02 | B3: R0007EU | C3: B0FNMBQFBC | D3: B0FNMBQFBC | E3: R0007EU | F3: HYCHIKA-AP100A-空净 | G3: 64.99 | H3: 64.99 | I3: 0 | J3: 0 | K3: 0 | L3: 0 | M3: 0 | N3: 0 | O3: 0 | P3: 0 | Q3: 0 | R3: 0 | S3: 0 | T3: 0.00% | U3: 0.00% | V3: 0.00% | W3: 0.00% | X3: 0.00% | Y3: 0.00% | Z3: 0 | AA3: 0 | AB3: 0 | AC3: 0 | AD3: 0 | AE3: 0 | AF3: 0 | AG3: 0 | AH3: 0 | AI3: 0 | AJ3: 0 | AK3: 0 | AN3: 0 | AO3: 0 | AP3: 0.00% | AQ3: 0 | AR3: 0 | AS3: 0.00% | AT3: ** | AU3: ** | AV3: ** | AW3: ** | AX3: ** | AY3: 0 | AZ3: 0.00% | BA3: 0 | BB3: 0.00% | BC3: 0 | BD3: 0.00% | BE3: 0 | BF3: 0 | BG3: 0 | BH3: 0 | BI3: 0.00% | BJ3: 0.00% | BK3: 0.00% | BL3: 0 | BM3: 0.00% | BN3: 0 | BO3: 0 | BP3: 0 | BQ3: 0 | BR3: 0 | BS3: 0 | BT3: 0.00% | BU3: 0.00% | BV3: 0.00% | BW3: 0 | BX3: 0 | BY3: 0 | BZ3: 0 | CA3: 0 | CB3: 0 | CC3: 0 | CD3: 0.00% | CE3: 0.00% | CF3: 0 | CG3: 0 | CH3: 0 | CI3: 0 | CJ3: 0.00% | CK3: 0.00% | CL3: 0.00% | CM3: 0.00% | CN3: 0.00% | CO3: 0.00% | CP3: 0 | CQ3: 0.00% | CR3: 0 | CS3: 0.00% | CT3: 0 | CU3: 0.00% | CV3: 0.00% | CW3: 0 | CX3: 0.00% | CY3: 0 | CZ3: 0.00% | DA3: 0 | DB3: 0.00% | DC3: 0.00% | DD3: 0.00% | DE3: 0.00%
A4: 2025-12-03 | B4: R0007EU | C4: B0FNMBQFBC | D4: B0FNMBQFBC | E4: R0007EU | F4: HYCHIKA-AP100A-空净 | G4: 64.99 | H4: 64.99 | I4: 0 | J4: 0 | K4: 0 | L4: 0 | M4: 0 | N4: 0 | O4: 0 | P4: 0 | Q4: 0 | R4: 0 | S4: 0 | T4: 0.00% | U4: 0.00% | V4: 0.00% | W4: 0.00% | X4: 0.00% | Y4: 0.00% | Z4: 0 | AA4: 0 | AB4: 0 | AC4: 0 | AD4: 0 | AE4: 0 | AF4: 0 | AG4: 0 | AH4: 0 | AI4: 0 | AJ4: 0 | AK4: 0 | AN4: 0 | AO4: 0 | AP4: 0.00% | AQ4: 0 | AR4: 0 | AS4: 0.00% | AT4: ** | AU4: ** | AV4: ** | AW4: ** | AX4: ** | AY4: 0 | AZ4: 0.00% | BA4: 0 | BB4: 0.00% | BC4: 0 | BD4: 0.00% | BE4: 0 | BF4: 0 | BG4: 0 | BH4: 0 | BI4: 0.00% | BJ4: 0.00% | BK4: 0.00% | BL4: 0 | BM4: 0.00% | BN4: 0 | BO4: 0 | BP4: 0 | BQ4: 0 | BR4: 0 | BS4: 0 | BT4: 0.00% | BU4: 0.00% | BV4: 0.00% | BW4: 0 | BX4: 0 | BY4: 0 | BZ4: 0 | CA4: 0 | CB4: 0 | CC4: 0 | CD4: 0.00% | CE4: 0.00% | CF4: 0 | CG4: 0 | CH4: 0 | CI4: 0 | CJ4: 0.00% | CK4: 0.00% | CL4: 0.00% | CM4: 0.00% | CN4: 0.00% | CO4: 0.00% | CP4: 0 | CQ4: 0.00% | CR4: 0 | CS4: 0.00% | CT4: 0 | CU4: 0.00% | CV4: 0.00% | CW4: 0 | CX4: 0.00% | CY4: 0 | CZ4: 0.00% | DA4: 0 | DB4: 0.00% | DC4: 0.00% | DD4: 0.00% | DE4: 0.00%
A5: 2025-12-04 | B5: R0007EU | C5: B0FNMBQFBC | D5: B0FNMBQFBC | E5: R0007EU | F5: HYCHIKA-AP100A-空净 | G5: 64.99 | H5: 64.99 | I5: 0 | J5: 0 | K5: 0 | L5: 0 | M5: 0 | N5: 0 | O5: 0 | P5: 0 | Q5: 0 | R5: 0 | S5: 0 | T5: 0.00% | U5: 0.00% | V5: 0.00% | W5: 0.00% | X5: 0.00% | Y5: 0.00% | Z5: 0 | AA5: 0 | AB5: 0 | AC5: 0 | AD5: 0 | AE5: 0 | AF5: 0 | AG5: 0 | AH5: 0 | AI5: 0 | AJ5: 0 | AK5: 0 | AN5: 0 | AO5: 0 | AP5: 0.00% | AQ5: 0 | AR5: 0 | AS5: 0.00% | AT5: ** | AU5: ** | AV5: ** | AW5: ** | AX5: ** | AY5: 0 | AZ5: 0.00% | BA5: 0 | BB5: 0.00% | BC5: 0 | BD5: 0.00% | BE5: 0 | BF5: 0 | BG5: 0 | BH5: 0 | BI5: 0.00% | BJ5: 0.00% | BK5: 0.00% | BL5: 0 | BM5: 0.00% | BN5: 0 | BO5: 0 | BP5: 0 | BQ5: 0 | BR5: 0 | BS5: 0 | BT5: 0.00% | BU5: 0.00% | BV5: 0.00% | BW5: 0 | BX5: 0 | BY5: 0 | BZ5: 0 | CA5: 0 | CB5: 0 | CC5: 0 | CD5: 0.00% | CE5: 0.00% | CF5: 0 | CG5: 0 | CH5: 0 | CI5: 0 | CJ5: 0.00% | CK5: 0.00% | CL5: 0.00% | CM5: 0.00% | CN5: 0.00% | CO5: 0.00% | CP5: 0 | CQ5: 0.00% | CR5: 0 | CS5: 0.00% | CT5: 0 | CU5: 0.00% | CV5: 0.00% | CW5: 0 | CX5: 0.00% | CY5: 0 | CZ5: 0.00% | DA5: 0 | DB5: 0.00% | DC5: 0.00% | DD5: 0.00% | DE5: 0.00%
A6: 2025-12-05 | B6: R0007EU | C6: B0FNMBQFBC | D6: B0FNMBQFBC | E6: R0007EU | F6: HYCHIKA-AP100A-空净 | G6: 64.99 | H6: 64.99 | I6: 0 | J6: 0 | K6: 0 | L6: 0 | M6: 0 | N6: 0 | O6: 0 | P6: 0 | Q6: 0 | R6: 0 | S6: 0 | T6: 0.00% | U6: 0.00% | V6: 0.00% | W6: 0.00% | X6: 0.00% | Y6: 0.00% | Z6: 0 | AA6: 0 | AB6: 0 | AC6: 0 | AD6: 0 | AE6: 0 | AF6: 0 | AG6: 0 | AH6: 0 | AI6: 0 | AJ6: 0 | AK6: 0 | AN6: 0 | AO6: 0 | AP6: 0.00% | AQ6: 0 | AR6: 0 | AS6: 0.00% | AT6: ** | AU6: ** | AV6: ** | AW6: ** | AX6: ** | AY6: 0 | AZ6: 0.00% | BA6: 0 | BB6: 0.00% | BC6: 0 | BD6: 0.00% | BE6: 0 | BF6: 0 | BG6: 0 | BH6: 0 | BI6: 0.00% | BJ6: 0.00% | BK6: 0.00% | BL6: 0 | BM6: 0.00% | BN6: 0 | BO6: 0 | BP6: 0 | BQ6: 0 | BR6: 0 | BS6: 0 | BT6: 0.00% | BU6: 0.00% | BV6: 0.00% | BW6: 0 | BX6: 0 | BY6: 0 | BZ6: 0 | CA6: 0 | CB6: 0 | CC6: 0 | CD6: 0.00% | CE6: 0.00% | CF6: 0 | CG6: 0 | CH6: 0 | CI6: 0 | CJ6: 0.00% | CK6: 0.00% | CL6: 0.00% | CM6: 0.00% | CN6: 0.00% | CO6: 0.00% | CP6: 0 | CQ6: 0.00% | CR6: 0 | CS6: 0.00% | CT6: 0 | CU6: 0.00% | CV6: 0.00% | CW6: 0 | CX6: 0.00% | CY6: 0 | CZ6: 0.00% | DA6: 0 | DB6: 0.00% | DC6: 0.00% | DD6: 0.00% | DE6: 0.00%
A7: 2025-12-06 | B7: R0007EU | C7: B0FNMBQFBC | D7: B0FNMBQFBC | E7: R0007EU | F7: HYCHIKA-AP100A-空净 | G7: 64.99 | H7: 64.99 | I7: 0 | J7: 0 | K7: 0 | L7: 0 | M7: 0 | N7: 0 | O7: 0 | P7: 0 | Q7: 0 | R7: 0 | S7: 0 | T7: 0.00% | U7: 0.00% | V7: 0.00% | W7: 0.00% | X7: 0.00% | Y7: 0.00% | Z7: 0 | AA7: 0 | AB7: 0 | AC7: 0 | AD7: 0 | AE7: 0 | AF7: 0 | AG7: 0 | AH7: 0 | AI7: 0 | AJ7: 0 | AK7: 0 | AN7: 0 | AO7: 0 | AP7: 0.00% | AQ7: 0 | AR7: 0 | AS7: 0.00% | AT7: ** | AU7: ** | AV7: ** | AW7: ** | AX7: ** | AY7: 0 | AZ7: 0.00% | BA7: 0 | BB7: 0.00% | BC7: 0 | BD7: 0.00% | BE7: 0 | BF7: 0 | BG7: 0 | BH7: 0 | BI7: 0.00% | BJ7: 0.00% | BK7: 0.00% | BL7: 0 | BM7: 0.00% | BN7: 0 | BO7: 0 | BP7: 0 | BQ7: 0 | BR7: 0 | BS7: 0 | BT7: 0.00% | BU7: 0.00% | BV7: 0.00% | BW7: 0 | BX7: 0 | BY7: 0 | BZ7: 0 | CA7: 0 | CB7: 0 | CC7: 0 | CD7: 0.00% | CE7: 0.00% | CF7: 0 | CG7: 0 | CH7: 0 | CI7: 0 | CJ7: 0.00% | CK7: 0.00% | CL7: 0.00% | CM7: 0.00% | CN7: 0.00% | CO7: 0.00% | CP7: 0 | CQ7: 0.00% | CR7: 0 | CS7: 0.00% | CT7: 0 | CU7: 0.00% | CV7: 0.00% | CW7: 0 | CX7: 0.00% | CY7: 0 | CZ7: 0.00% | DA7: 0 | DB7: 0.00% | DC7: 0.00% | DD7: 0.00% | DE7: 0.00%
A8: 2025-12-07 | B8: R0007EU | C8: B0FNMBQFBC | D8: B0FNMBQFBC | E8: R0007EU | F8: HYCHIKA-AP100A-空净 | G8: 64.99 | H8: 64.99 | I8: 0 | J8: 0 | K8: 0 | L8: 0 | M8: 0 | N8: 0 | O8: 0 | P8: 0 | Q8: 0 | R8: 0 | S8: 0 | T8: 0.00% | U8: 0.00% | V8: 0.00% | W8: 0.00% | X8: 0.00% | Y8: 0.00% | Z8: 0 | AA8: 0 | AB8: 0 | AC8: 0 | AD8: 0 | AE8: 0 | AF8: 0 | AG8: 0 | AH8: 0 | AI8: 0 | AJ8: 0 | AK8: 0 | AN8: 0 | AO8: 0 | AP8: 0.00% | AQ8: 0 | AR8: 0 | AS8: 0.00% | AT8: ** | AU8: ** | AV8: ** | AW8: ** | AX8: ** | AY8: 0 | AZ8: 0.00% | BA8: 0 | BB8: 0.00% | BC8: 0 | BD8: 0.00% | BE8: 0 | BF8: 0 | BG8: 0 | BH8: 0 | BI8: 0.00% | BJ8: 0.00% | BK8: 0.00% | BL8: 0 | BM8: 0.00% | BN8: 0 | BO8: 0 | BP8: 0 | BQ8: 0 | BR8: 0 | BS8: 0 | BT8: 0.00% | BU8: 0.00% | BV8: 0.00% | BW8: 0 | BX8: 0 | BY8: 0 | BZ8: 0 | CA8: 0 | CB8: 0 | CC8: 0 | CD8: 0.00% | CE8: 0.00% | CF8: 0 | CG8: 0 | CH8: 0 | CI8: 0 | CJ8: 0.00% | CK8: 0.00% | CL8: 0.00% | CM8: 0.00% | CN8: 0.00% | CO8: 0.00% | CP8: 0 | CQ8: 0.00% | CR8: 0 | CS8: 0.00% | CT8: 0 | CU8: 0.00% | CV8: 0.00% | CW8: 0 | CX8: 0.00% | CY8: 0 | CZ8: 0.00% | DA8: 0 | DB8: 0.00% | DC8: 0.00% | DD8: 0.00% | DE8: 0.00%
A9: 2025-12-08 | B9: R0007EU | C9: B0FNMBQFBC | D9: B0FNMBQFBC | E9: R0007EU | F9: HYCHIKA-AP100A-空净 | G9: 64.99 | H9: 64.99 | I9: 0 | J9: 0 | K9: 0 | L9: 0 | M9: 0 | N9: 0 | O9: 0 | P9: 0 | Q9: 0 | R9: 0 | S9: 0 | T9: 0.00% | U9: 0.00% | V9: 0.00% | W9: 0.00% | X9: 0.00% | Y9: 0.00% | Z9: 0 | AA9: 0 | AB9: 0 | AC9: 0 | AD9: 0 | AE9: 0 | AF9: 0 | AG9: 0 | AH9: 0 | AI9: 0 | AJ9: 0 | AK9: 0 | AN9: 0 | AO9: 0 | AP9: 0.00% | AQ9: 0 | AR9: 0 | AS9: 0.00% | AT9: ** | AU9: ** | AV9: ** | AW9: ** | AX9: ** | AY9: 0 | AZ9: 0.00% | BA9: 0 | BB9: 0.00% | BC9: 0 | BD9: 0.00% | BE9: 0 | BF9: 0 | BG9: 0 | BH9: 0 | BI9: 0.00% | BJ9: 0.00% | BK9: 0.00% | BL9: 0 | BM9: 0.00% | BN9: 0 | BO9: 0 | BP9: 0 | BQ9: 0 | BR9: 0 | BS9: 0 | BT9: 0.00% | BU9: 0.00% | BV9: 0.00% | BW9: 0 | BX9: 0 | BY9: 0 | BZ9: 0 | CA9: 0 | CB9: 0 | CC9: 0 | CD9: 0.00% | CE9: 0.00% | CF9: 0 | CG9: 0 | CH9: 0 | CI9: 0 | CJ9: 0.00% | CK9: 0.00% | CL9: 0.00% | CM9: 0.00% | CN9: 0.00% | CO9: 0.00% | CP9: 0 | CQ9: 0.00% | CR9: 0 | CS9: 0.00% | CT9: 0 | CU9: 0.00% | CV9: 0.00% | CW9: 0 | CX9: 0.00% | CY9: 0 | CZ9: 0.00% | DA9: 0 | DB9: 0.00% | DC9: 0.00% | DD9: 0.00% | DE9: 0.00%
A10: 2025-12-09 | B10: R0007EU | C10: B0FNMBQFBC | D10: B0FNMBQFBC | E10: R0007EU | F10: HYCHIKA-AP100A-空净 | G10: 64.99 | H10: 64.99 | I10: 0 | J10: 0 | K10: 0 | L10: 0 | M10: 0 | N10: 0 | O10: 0 | P10: 0 | Q10: 0 | R10: 0 | S10: 0 | T10: 0.00% | U10: 0.00% | V10: 0.00% | W10: 0.00% | X10: 0.00% | Y10: 0.00% | Z10: 0 | AA10: 0 | AB10: 0 | AC10: 0 | AD10: 0 | AE10: 0 | AF10: 0 | AG10: 0 | AH10: 0 | AI10: 0 | AJ10: 0 | AK10: 0 | AN10: 0 | AO10: 0 | AP10: 0.00% | AQ10: 0 | AR10: 0 | AS10: 0.00% | AT10: ** | AU10: ** | AV10: ** | AW10: ** | AX10: ** | AY10: 0 | AZ10: 0.00% | BA10: 0 | BB10: 0.00% | BC10: 0 | BD10: 0.00% | BE10: 0 | BF10: 0 | BG10: 0 | BH10: 0 | BI10: 0.00% | BJ10: 0.00% | BK10: 0.00% | BL10: 0 | BM10: 0.00% | BN10: 0 | BO10: 0 | BP10: 0 | BQ10: 0 | BR10: 0 | BS10: 0 | BT10: 0.00% | BU10: 0.00% | BV10: 0.00% | BW10: 0 | BX10: 0 | BY10: 0 | BZ10: 0 | CA10: 0 | CB10: 0 | CC10: 0 | CD10: 0.00% | CE10: 0.00% | CF10: 0 | CG10: 0 | CH10: 0 | CI10: 0 | CJ10: 0.00% | CK10: 0.00% | CL10: 0.00% | CM10: 0.00% | CN10: 0.00% | CO10: 0.00% | CP10: 0 | CQ10: 0.00% | CR10: 0 | CS10: 0.00% | CT10: 0 | CU10: 0.00% | CV10: 0.00% | CW10: 0 | CX10: 0.00% | CY10: 0 | CZ10: 0.00% | DA10: 0 | DB10: 0.00% | DC10: 0.00% | DD10: 0.00% | DE10: 0.00%
A11: 2025-12-10 | B11: R0007EU | C11: B0FNMBQFBC | D11: B0FNMBQFBC | E11: R0007EU | F11: HYCHIKA-AP100A-空净 | G11: 64.99 | H11: 64.99 | I11: 0 | J11: 0 | K11: 0 | L11: 0 | M11: 0 | N11: 0 | O11: 0 | P11: 0 | Q11: 0 | R11: 0 | S11: 0 | T11: 0.00% | U11: 0.00% | V11: 0.00% | W11: 0.00% | X11: 0.00% | Y11: 0.00% | Z11: 0 | AA11: 0 | AB11: 0 | AC11: 0 | AD11: 0 | AE11: 0 | AF11: 0 | AG11: 0 | AH11: 0 | AI11: 0 | AJ11: 0 | AK11: 0 | AN11: 0 | AO11: 0 | AP11: 0.00% | AQ11: 0 | AR11: 0 | AS11: 0.00% | AT11: ** | AU11: ** | AV11: ** | AW11: ** | AX11: ** | AY11: 0 | AZ11: 0.00% | BA11: 0 | BB11: 0.00% | BC11: 0 | BD11: 0.00% | BE11: 0 | BF11: 0 | BG11: 0 | BH11: 0 | BI11: 0.00% | BJ11: 0.00% | BK11: 0.00% | BL11: 0 | BM11: 0.00% | BN11: 0 | BO11: 0 | BP11: 0 | BQ11: 0 | BR11: 0 | BS11: 0 | BT11: 0.00% | BU11: 0.00% | BV11: 0.00% | BW11: 0 | BX11: 0 | BY11: 0 | BZ11: 0 | CA11: 0 | CB11: 0 | CC11: 0 | CD11: 0.00% | CE11: 0.00% | CF11: 0 | CG11: 0 | CH11: 0 | CI11: 0 | CJ11: 0.00% | CK11: 0.00% | CL11: 0.00% | CM11: 0.00% | CN11: 0.00% | CO11: 0.00% | CP11: 0 | CQ11: 0.00% | CR11: 0 | CS11: 0.00% | CT11: 0 | CU11: 0.00% | CV11: 0.00% | CW11: 0 | CX11: 0.00% | CY11: 0 | CZ11: 0.00% | DA11: 0 | DB11: 0.00% | DC11: 0.00% | DD11: 0.00% | DE11: 0.00%
A12: 2025-12-11 | B12: R0007EU | C12: B0FNMBQFBC | D12: B0FNMBQFBC | E12: R0007EU | F12: HYCHIKA-AP100A-空净 | G12: 64.99 | H12: 64.99 | I12: 0 | J12: 0 | K12: 0 | L12: 0 | M12: 0 | N12: 0 | O12: 0 | P12: 0 | Q12: 0 | R12: 0 | S12: 0 | T12: 0.00% | U12: 0.00% | V12: 0.00% | W12: 0.00% | X12: 0.00% | Y12: 0.00% | Z12: 0 | AA12: 0 | AB12: 0 | AC12: 0 | AD12: 0 | AE12: 0 | AF12: 0 | AG12: 0 | AH12: 0 | AI12: 0 | AJ12: 0 | AK12: 0 | AN12: 0 | AO12: 0 | AP12: 0.00% | AQ12: 0 | AR12: 0 | AS12: 0.00% | AT12: ** | AU12: ** | AV12: ** | AW12: ** | AX12: ** | AY12: 0 | AZ12: 0.00% | BA12: 0 | BB12: 0.00% | BC12: 0 | BD12: 0.00% | BE12: 0 | BF12: 0 | BG12: 0 | BH12: 0 | BI12: 0.00% | BJ12: 0.00% | BK12: 0.00% | BL12: 0 | BM12: 0.00% | BN12: 0 | BO12: 0 | BP12: 0 | BQ12: 0 | BR12: 0 | BS12: 0 | BT12: 0.00% | BU12: 0.00% | BV12: 0.00% | BW12: 0 | BX12: 0 | BY12: 0 | BZ12: 0 | CA12: 0 | CB12: 0 | CC12: 0 | CD12: 0.00% | CE12: 0.00% | CF12: 0 | CG12: 0 | CH12: 0 | CI12: 0 | CJ12: 0.00% | CK12: 0.00% | CL12: 0.00% | CM12: 0.00% | CN12: 0.00% | CO12: 0.00% | CP12: 0 | CQ12: 0.00% | CR12: 0 | CS12: 0.00% | CT12: 0 | CU12: 0.00% | CV12: 0.00% | CW12: 0 | CX12: 0.00% | CY12: 0 | CZ12: 0.00% | DA12: 0 | DB12: 0.00% | DC12: 0.00% | DD12: 0.00% | DE12: 0.00%
A13: 2025-12-12 | B13: R0007EU | C13: B0FNMBQFBC | D13: B0FNMBQFBC | E13: R0007EU | F13: HYCHIKA-AP100A-空净 | G13: 64.99 | H13: 64.99 | I13: 0 | J13: 0 | K13: 0 | L13: 0 | M13: 0 | N13: 0 | O13: 0 | P13: 0 | Q13: 0 | R13: 0 | S13: 0 | T13: 0.00% | U13: 0.00% | V13: 0.00% | W13: 0.00% | X13: 0.00% | Y13: 0.00% | Z13: 0 | AA13: 0 | AB13: 0 | AC13: 0 | AD13: 0 | AE13: 0 | AF13: 0 | AG13: 0 | AH13: 0 | AI13: 0 | AJ13: 0 | AK13: 0 | AN13: 0 | AO13: 0 | AP13: 0.00% | AQ13: 0 | AR13: 0 | AS13: 0.00% | AT13: ** | AU13: ** | AV13: ** | AW13: ** | AX13: ** | AY13: 0 | AZ13: 0.00% | BA13: 0 | BB13: 0.00% | BC13: 0 | BD13: 0.00% | BE13: 0 | BF13: 0 | BG13: 0 | BH13: 0 | BI13: 0.00% | BJ13: 0.00% | BK13: 0.00% | BL13: 0 | BM13: 0.00% | BN13: 0 | BO13: 0 | BP13: 0 | BQ13: 0 | BR13: 0 | BS13: 0 | BT13: 0.00% | BU13: 0.00% | BV13: 0.00% | BW13: 0 | BX13: 0 | BY13: 0 | BZ13: 0 | CA13: 0 | CB13: 0 | CC13: 0 | CD13: 0.00% | CE13: 0.00% | CF13: 0 | CG13: 0 | CH13: 0 | CI13: 0 | CJ13: 0.00% | CK13: 0.00% | CL13: 0.00% | CM13: 0.00% | CN13: 0.00% | CO13: 0.00% | CP13: 0 | CQ13: 0.00% | CR13: 0 | CS13: 0.00% | CT13: 0 | CU13: 0.00% | CV13: 0.00% | CW13: 0 | CX13: 0.00% | CY13: 0 | CZ13: 0.00% | DA13: 0 | DB13: 0.00% | DC13: 0.00% | DD13: 0.00% | DE13: 0.00%
... A21: 2025-12-20 | B21: R0007EU | C21: B0FNMBQFBC | D21: B0FNMBQFBC | E21: R0007EU | F21: HYCHIKA-AP100A-空净 | G21: 54.99 | H21: 64.99 | I21: 201 | J21: 0 | K21: 0 | L21: 0 | M21: 0 | N21: 0 | O21: 201 | P21: 2 | Q21: 109.98 | R21: 2 | S21: 0 | T21: 0.00% | U21: 100.00% | V21: 0.00% | W21: 0.00% | X21: 100.00% | Y21: 0.00% | Z21: 0 | AA21: 0 | AB21: 0 | AC21: 0 | AD21: 2 | AE21: 109.98 | AF21: 2 | AG21: 109.98 | AH21: 2 | AI21: 109.98 | AJ21: 2 | AK21: 0 | AN21: 0 | AO21: 0 | AP21: 0.00% | AQ21: 0 | AR21: 0 | AS21: 0.00% | AT21: ** | AU21: ** | AV21: ** | AW21: ** | AX21: ** | AY21: 0 | AZ21: 0.00% | BA21: 6 | BB21: 1.27% | BC21: 4 | BD21: 0.00% | BE21: 10 | BF21: 6 | BG21: 4 | BH21: 10 | BI21: 20.00% | BJ21: 20.00% | BK21: 100.00% | BL21: 0 | BM21: 0.00% | BN21: 0 | BO21: 0 | BP21: 0 | BQ21: 0 | BR21: 0 | BS21: 0 | BT21: 0.00% | BU21: 0.00% | BV21: 0.00% | BW21: 0 | BX21: 0 | BY21: 0 | BZ21: 0 | CA21: 0 | CB21: 0 | CC21: 0 | CD21: 0.00% | CE21: 0.00% | CF21: 0 | CG21: 0 | CH21: 2 | CI21: 10 | CJ21: 20.00% | CK21: 1.00% | CL21: 20.00% | CM21: 0.50% | CN21: 0.00% | CO21: 1.00% | CP21: 0 | CQ21: 0.00% | CR21: 0 | CS21: 0.00% | CT21: 0 | CU21: 0.00% | CV21: 0.00% | CW21: 0 | CX21: 0.00% | CY21: 0 | CZ21: 0.00% | DA21: 0 | DB21: 0.00% | DC21: 0.00% | DD21: 0.00% | DE21: 0.00%
A22: 2025-12-21 | B22: R0007EU | C22: B0FNMBQFBC | D22: B0FNMBQFBC | E22: R0007EU | F22: HYCHIKA-AP100A-空净 | G22: 54.99 | H22: 64.99 | I22: 200 | J22: 0 | K22: 0 | L22: 0 | M22: 0 | N22: 0 | O22: 200 | P22: 0 | Q22: 0 | R22: 0 | S22: 0 | T22: 0.00% | U22: 0.00% | V22: 0.00% | W22: 0.00% | X22: 0.00% | Y22: 0.00% | Z22: 0 | AA22: 0 | AB22: 0 | AC22: 0 | AD22: 0 | AE22: 0 | AF22: 0 | AG22: 0 | AH22: 0 | AI22: 0 | AJ22: 0 | AK22: 0 | AL22: Küche, Haushalt & Wohnen：89408 | AM22: Luftreiniger：141 | AN22: 0 | AO22: 0 | AP22: 0.00% | AQ22: 0 | AR22: 0 | AS22: 0.00% | AT22: ** | AU22: ** | AV22: ** | AW22: ** | AX22: ** | AY22: 0 | AZ22: 0.00% | BA22: 2 | BB22: 0.40% | BC22: 1 | BD22: 0.00% | BE22: 3 | BF22: 4 | BG22: 1 | BH22: 5 | BI22: 0.00% | BJ22: 0.00% | BK22: 100.00% | BL22: 0 | BM22: 0.00% | BN22: 0 | BO22: 0 | BP22: 0 | BQ22: 0 | BR22: 0 | BS22: 0 | BT22: 0.00% | BU22: 0.00% | BV22: 0.00% | BW22: 0 | BX22: 0 | BY22: 0 | BZ22: 0 | CA22: 0 | CB22: 0 | CC22: 0 | CD22: 0.00% | CE22: 0.00% | CF22: 0 | CG22: 0 | CH22: 0 | CI22: 3 | CJ22: 0.00% | CK22: 0.00% | CL22: 0.00% | CM22: 0.23% | CN22: 0.00% | CO22: 0.00% | CP22: 0 | CQ22: 0.00% | CR22: 0 | CS22: 0.00% | CT22: 0 | CU22: 0.00% | CV22: 0.00% | CW22: 0 | CX22: 0.00% | CY22: 0 | CZ22: 0.00% | DA22: 0 | DB22: 0.00% | DC22: 0.00% | DD22: 0.00% | DE22: 0.00%
A23: 2025-12-22 | B23: R0007EU | C23: B0FNMBQFBC | D23: B0FNMBQFBC | E23: R0007EU | F23: HYCHIKA-AP100A-空净 | G23: 54.99 | H23: 54.99 | I23: 198 | J23: 0 | K23: 0 | L23: 0 | M23: 0 | N23: 0 | O23: 198 | P23: 1 | Q23: 54.99 | R23: 1 | S23: 54.99 | T23: 0.00% | U23: 100.00% | V23: 0.00% | W23: 0.00% | X23: 100.00% | Y23: 0.00% | Z23: 0 | AA23: 0 | AB23: 0 | AC23: 0 | AD23: 0 | AE23: 0 | AF23: 0 | AG23: 0 | AH23: 1 | AI23: 54.99 | AJ23: 1 | AK23: 54.99 | AL23: Küche, Haushalt & Wohnen：89408 | AM23: Luftreiniger：141 | AN23: 0 | AO23: 0 | AP23: 0.00% | AQ23: 0 | AR23: 0 | AS23: 0.00% | AT23: ** | AU23: ** | AV23: ** | AW23: ** | AX23: ** | AY23: 0 | AZ23: 0.00% | BA23: 4 | BB23: 0.89% | BC23: 1 | BD23: 0.00% | BE23: 5 | BF23: 10 | BG23: 2 | BH23: 12 | BI23: 20.00% | BJ23: 20.00% | BK23: 100.00% | BL23: 0 | BM23: 0.00% | BN23: 0 | BO23: 0 | BP23: 0 | BQ23: 0 | BR23: 0 | BS23: 0 | BT23: 0.00% | BU23: 0.00% | BV23: 0.00% | BW23: 0 | BX23: 0 | BY23: 0 | BZ23: 0 | CA23: 0 | CB23: 0 | CC23: 0 | CD23: 0.00% | CE23: 0.00% | CF23: 0 | CG23: 0 | CH23: 1 | CI23: 5 | CJ23: 20.00% | CK23: 0.00% | CL23: 20.00% | CM23: 0.62% | CN23: 0.00% | CO23: 1.00% | CP23: 0 | CQ23: 0.00% | CR23: 0 | CS23: 0.00% | CT23: 0 | CU23: 0.00% | CV23: 0.00% | CW23: 0 | CX23: 0.00% | CY23: 0 | CZ23: 0.00% | DA23: 0 | DB23: 0.00% | DC23: 0.00% | DD23: 0.00% | DE23: 0.00%
A24: 2025-12-23 | B24: R0007EU | C24: B0FNMBQFBC | D24: B0FNMBQFBC | E24: R0007EU | F24: HYCHIKA-AP100A-空净 | G24: 54.99 | H24: 54.99 | I24: 193 | J24: 0 | K24: 0 | L24: 0 | M24: 0 | N24: 0 | O24: 193 | P24: 0 | Q24: 0 | R24: 0 | S24: 0 | T24: 0.00% | U24: 0.00% | V24: 0.00% | W24: 0.00% | X24: 0.00% | Y24: 0.00% | Z24: 0 | AA24: 0 | AB24: 0 | AC24: 0 | AD24: 0 | AE24: 0 | AF24: 0 | AG24: 0 | AH24: 0 | AI24: 0 | AJ24: 0 | AK24: 0 | AL24: Küche, Haushalt & Wohnen：177496 | AM24: Luftreiniger：311 | AN24: 0 | AO24: 0 | AP24: 0.00% | AQ24: 0 | AR24: 0 | AS24: 0.00% | AT24: ** | AU24: ** | AV24: ** | AW24: ** | AX24: ** | AY24: 0 | AZ24: 0.00% | BA24: 0 | BB24: 0.00% | BC24: 0 | BD24: 0.00% | BE24: 0 | BF24: 0 | BG24: 0 | BH24: 0 | BI24: 0.00% | BJ24: 0.00% | BK24: 0.00% | BL24: 0 | BM24: 0.00% | BN24: 0 | BO24: 0 | BP24: 0 | BQ24: 0 | BR24: 0 | BS24: 0 | BT24: 0.00% | BU24: 0.00% | BV24: 0.00% | BW24: 0 | BX24: 0 | BY24: 0 | BZ24: 0 | CA24: 0 | CB24: 0 | CC24: 0 | CD24: 0.00% | CE24: 0.00% | CF24: 0 | CG24: 0 | CH24: 0 | CI24: 0 | CJ24: 0.00% | CK24: 0.00% | CL24: 0.00% | CM24: 0.00% | CN24: 0.00% | CO24: 0.00% | CP24: 0 | CQ24: 0.00% | CR24: 0 | CS24: 0.00% | CT24: 0 | CU24: 0.00% | CV24: 0.00% | CW24: 0 | CX24: 0.00% | CY24: 0 | CZ24: 0.00% | DA24: 0 | DB24: 0.00% | DC24: 0.00% | DD24: 0.00% | DE24: 0.00%
A25: 2025-12-24 | B25: R0007EU | C25: B0FNMBQFBC | D25: B0FNMBQFBC | E25: R0007EU | F25: HYCHIKA-AP100A-空净 | G25: 54.99 | H25: 54.99 | I25: 193 | J25: 0 | K25: 0 | L25: 0 | M25: 0 | N25: 0 | O25: 193 | P25: 0 | Q25: 0 | R25: 0 | S25: 0 | T25: 0.00% | U25: 0.00% | V25: 0.00% | W25: 0.00% | X25: 0.00% | Y25: 0.00% | Z25: 0 | AA25: 0 | AB25: 0 | AC25: 0 | AD25: 0 | AE25: 0 | AF25: 0 | AG25: 0 | AH25: 0 | AI25: 0 | AJ25: 0 | AK25: 0 | AL25: Küche, Haushalt & Wohnen：177496 | AM25: Luftreiniger：311 | AN25: 0 | AO25: 0 | AP25: 0.00% | AQ25: 0 | AR25: 0 | AS25: 0.00% | AT25: ** | AU25: ** | AV25: ** | AW25: ** | AX25: ** | AY25: 0 | AZ25: 0.00% | BA25: 0 | BB25: 0.00% | BC25: 0 | BD25: 0.00% | BE25: 0 | BF25: 0 | BG25: 0 | BH25: 0 | BI25: 0.00% | BJ25: 0.00% | BK25: 0.00% | BL25: 0 | BM25: 0.00% | BN25: 0 | BO25: 0 | BP25: 0 | BQ25: 0 | BR25: 0 | BS25: 0 | BT25: 0.00% | BU25: 0.00% | BV25: 0.00% | BW25: 0 | BX25: 0 | BY25: 0 | BZ25: 0 | CA25: 0 | CB25: 0 | CC25: 0 | CD25: 0.00% | CE25: 0.00% | CF25: 0 | CG25: 0 | CH25: 0 | CI25: 0 | CJ25: 0.00% | CK25: 0.00% | CL25: 0.00% | CM25: 0.00% | CN25: 0.00% | CO25: 0.00% | CP25: 0 | CQ25: 0.00% | CR25: 0 | CS25: 0.00% | CT25: 0 | CU25: 0.00% | CV25: 0.00% | CW25: 0 | CX25: 0.00% | CY25: 0 | CZ25: 0.00% | DA25: 0 | DB25: 0.00% | DC25: 0.00% | DD25: 0.00% | DE25: 0.00%

Sheet 法国ERP数据
A1: 时间 | B1: SKU | C1: 父ASIN | D1: ASIN | E1: MSKU | F1: 品名 | G1: 售价(总价) | H1: 价格 | I1: FBA-可售 | J1: FBM可售 | K1: AWD在库 | L1: AWD可用量 | M1: AWD待发货量 | N1: AWD标发在途 | O1: 可用库存 | P1: 销量 | Q1: 销售额 | R1: 订单量 | S1: 净销售额 | T1: 销量环比 | U1: 销售额环比 | V1: 订单量环比 | W1: 销量同比 | X1: 订单量同比 | Y1: 销量额同比 | Z1: B2B 销量 | AA1: B2B 销售额 | AB1: B2B 订单量 | AC1: FBM买家运费 | AD1: 促销销量 | AE1: 促销销售额 | AF1: 促销订单量 | AG1: 促销折扣 | AH1: 日均销量 | AI1: 日均销售额 | AJ1: 日均订单量 | AK1: 销售均价 | AL1: 大类排名 | AM1: 小类排名 | AN1: 退款量 | AO1: 退款金额 | AP1: 退款率 | AQ1: 评分 | AR1: 评论数 | AS1: 留评率 | AT1: 结算毛利润 | AU1: 订单毛利润 | AV1: 结算毛利率 | AW1: 订单毛利率 | AX1: ROI | AY1: 退货量 | AZ1: 退货率 | BA1: Sessions-Browser | BB1: Sessions-Browser-Percentage | BC1: Sessions-Mobile | BD1: Sessions-Mobile-Percentage | BE1: Sessions-Total | BF1: PV-Browser | BG1: PV-Mobile | BH1: PV-Total | BI1: CVR | BJ1: 销量CVR | BK1: Buybox赢得率 | BL1: CPC | BM1: CTR | BN1: 广告花费 | BO1: SB广告费 | BP1: SBV广告费 | BQ1: SD广告费 | BR1: SP广告费 | BS1: ROAS | BT1: ACOS | BU1: ACoAS | BV1: ASoAS | BW1: CPO | BX1: CPU | BY1: CPM | BZ1: 广告销售额 | CA1: 广告订单量 | CB1: 直接成交订单量 | CC1: 直接成交销售额 | CD1: 广告订单占比 | CE1: 广告CVR | CF1: 展示 | CG1: 点击 | CH1: 自然订单量 | CI1: 自然点击量 | CJ1: 自然CVR | CK1: Sessions-Percentage | CL1: Unit-Sessions-Percentage | CM1: PV-Browser-Percentage | CN1: PV-Mobile-Percentage | CO1: PV-Percentage | CP1: Sessions-Browser(B2B) | CQ1: Sessions-Browser-Percentage(B2B) | CR1: Sessions-Mobile(B2B) | CS1: Sessions-Mobile-Percentage(B2B) | CT1: Sessions-Total(B2B) | CU1: Sessions-Percentage(B2B) | CV1: Unit-Sessions-Percentage(B2B) | CW1: PV-Browser(B2B) | CX1: PV-Browser-Percentage(B2B) | CY1: PV-Mobile(B2B) | CZ1: PV-Mobile-Percentage(B2B) | DA1: PV-Total(B2B) | DB1: PV-Percentage(B2B) | DC1: CVR(B2B) | DD1: 销量CVR(B2B) | DE1: Buybox赢得率(B2B) | DF1: 运营日志
A2: 2025-12-01 | B2: R0007EU | C2: B0FNMBQFBC | D2: B0FNMBQFBC | E2: R0007EU | F2: HYCHIKA-AP100A-空净 | G2: 0 | H2: 0 | I2: 0 | J2: 0 | K2: 0 | L2: 0 | M2: 0 | N2: 0 | O2: 0 | P2: 0 | Q2: 0 | R2: 0 | S2: 0 | T2: 0.00% | U2: 0.00% | V2: 0.00% | W2: 0.00% | X2: 0.00% | Y2: 0.00% | Z2: 0 | AA2: 0 | AB2: 0 | AC2: 0 | AD2: 0 | AE2: 0 | AF2: 0 | AG2: 0 | AH2: 0 | AI2: 0 | AJ2: 0 | AK2: 0 | AN2: 0 | AO2: 0 | AP2: 0.00% | AQ2: 0 | AR2: 0 | AS2: 0.00% | AT2: ** | AU2: ** | AV2: ** | AW2: ** | AX2: ** | AY2: 0 | AZ2: 0.00% | BA2: 0 | BB2: 0.00% | BC2: 0 | BD2: 0.00% | BE2: 0 | BF2: 0 | BG2: 0 | BH2: 0 | BI2: 0.00% | BJ2: 0.00% | BK2: 0.00% | BL2: 0 | BM2: 0.00% | BN2: 0 | BO2: 0 | BP2: 0 | BQ2: 0 | BR2: 0 | BS2: 0 | BT2: 0.00% | BU2: 0.00% | BV2: 0.00% | BW2: 0 | BX2: 0 | BY2: 0 | BZ2: 0 | CA2: 0 | CB2: 0 | CC2: 0 | CD2: 0.00% | CE2: 0.00% | CF2: 0 | CG2: 0 | CH2: 0 | CI2: 0 | CJ2: 0.00% | CK2: 0.00% | CL2: 0.00% | CM2: 0.00% | CN2: 0.00% | CO2: 0.00% | CP2: 0 | CQ2: 0.00% | CR2: 0 | CS2: 0.00% | CT2: 0 | CU2: 0.00% | CV2: 0.00% | CW2: 0 | CX2: 0.00% | CY2: 0 | CZ2: 0.00% | DA2: 0 | DB2: 0.00% | DC2: 0.00% | DD2: 0.00% | DE2: 0.00%
A3: 2025-12-02 | B3: R0007EU | C3: B0FNMBQFBC | D3: B0FNMBQFBC | E3: R0007EU | F3: HYCHIKA-AP100A-空净 | G3: 0 | H3: 0 | I3: 0 | J3: 0 | K3: 0 | L3: 0 | M3: 0 | N3: 0 | O3: 0 | P3: 0 | Q3: 0 | R3: 0 | S3: 0 | T3: 0.00% | U3: 0.00% | V3: 0.00% | W3: 0.00% | X3: 0.00% | Y3: 0.00% | Z3: 0 | AA3: 0 | AB3: 0 | AC3: 0 | AD3: 0 | AE3: 0 | AF3: 0 | AG3: 0 | AH3: 0 | AI3: 0 | AJ3: 0 | AK3: 0 | AN3: 0 | AO3: 0 | AP3: 0.00% | AQ3: 0 | AR3: 0 | AS3: 0.00% | AT3: ** | AU3: ** | AV3: ** | AW3: ** | AX3: ** | AY3: 0 | AZ3: 0.00% | BA3: 0 | BB3: 0.00% | BC3: 0 | BD3: 0.00% | BE3: 0 | BF3: 0 | BG3: 0 | BH3: 0 | BI3: 0.00% | BJ3: 0.00% | BK3: 0.00% | BL3: 0 | BM3: 0.00% | BN3: 0 | BO3: 0 | BP3: 0 | BQ3: 0 | BR3: 0 | BS3: 0 | BT3: 0.00% | BU3: 0.00% | BV3: 0.00% | BW3: 0 | BX3: 0 | BY3: 0 | BZ3: 0 | CA3: 0 | CB3: 0 | CC3: 0 | CD3: 0.00% | CE3: 0.00% | CF3: 0 | CG3: 0 | CH3: 0 | CI3: 0 | CJ3: 0.00% | CK3: 0.00% | CL3: 0.00% | CM3: 0.00% | CN3: 0.00% | CO3: 0.00% | CP3: 0 | CQ3: 0.00% | CR3: 0 | CS3: 0.00% | CT3: 0 | CU3: 0.00% | CV3: 0.00% | CW3: 0 | CX3: 0.00% | CY3: 0 | CZ3: 0.00% | DA3: 0 | DB3: 0.00% | DC3: 0.00% | DD3: 0.00% | DE3: 0.00%
A4: 2025-12-03 | B4: R0007EU | C4: B0FNMBQFBC | D4: B0FNMBQFBC | E4: R0007EU | F4: HYCHIKA-AP100A-空净 | G4: 0 | H4: 0 | I4: 0 | J4: 0 | K4: 0 | L4: 0 | M4: 0 | N4: 0 | O4: 0 | P4: 0 | Q4: 0 | R4: 0 | S4: 0 | T4: 0.00% | U4: 0.00% | V4: 0.00% | W4: 0.00% | X4: 0.00% | Y4: 0.00% | Z4: 0 | AA4: 0 | AB4: 0 | AC4: 0 | AD4: 0 | AE4: 0 | AF4: 0 | AG4: 0 | AH4: 0 | AI4: 0 | AJ4: 0 | AK4: 0 | AN4: 0 | AO4: 0 | AP4: 0.00% | AQ4: 0 | AR4: 0 | AS4: 0.00% | AT4: ** | AU4: ** | AV4: ** | AW4: ** | AX4: ** | AY4: 0 | AZ4: 0.00% | BA4: 0 | BB4: 0.00% | BC4: 0 | BD4: 0.00% | BE4: 0 | BF4: 0 | BG4: 0 | BH4: 0 | BI4: 0.00% | BJ4: 0.00% | BK4: 0.00% | BL4: 0 | BM4: 0.00% | BN4: 0 | BO4: 0 | BP4: 0 | BQ4: 0 | BR4: 0 | BS4: 0 | BT4: 0.00% | BU4: 0.00% | BV4: 0.00% | BW4: 0 | BX4: 0 | BY4: 0 | BZ4: 0 | CA4: 0 | CB4: 0 | CC4: 0 | CD4: 0.00% | CE4: 0.00% | CF4: 0 | CG4: 0 | CH4: 0 | CI4: 0 | CJ4: 0.00% | CK4: 0.00% | CL4: 0.00% | CM4: 0.00% | CN4: 0.00% | CO4: 0.00% | CP4: 0 | CQ4: 0.00% | CR4: 0 | CS4: 0.00% | CT4: 0 | CU4: 0.00% | CV4: 0.00% | CW4: 0 | CX4: 0.00% | CY4: 0 | CZ4: 0.00% | DA4: 0 | DB4: 0.00% | DC4: 0.00% | DD4: 0.00% | DE4: 0.00%
A5: 2025-12-04 | B5: R0007EU | C5: B0FNMBQFBC | D5: B0FNMBQFBC | E5: R0007EU | F5: HYCHIKA-AP100A-空净 | G5: 0 | H5: 0 | I5: 0 | J5: 0 | K5: 0 | L5: 0 | M5: 0 | N5: 0 | O5: 0 | P5: 0 | Q5: 0 | R5: 0 | S5: 0 | T5: 0.00% | U5: 0.00% | V5: 0.00% | W5: 0.00% | X5: 0.00% | Y5: 0.00% | Z5: 0 | AA5: 0 | AB5: 0 | AC5: 0 | AD5: 0 | AE5: 0 | AF5: 0 | AG5: 0 | AH5: 0 | AI5: 0 | AJ5: 0 | AK5: 0 | AN5: 0 | AO5: 0 | AP5: 0.00% | AQ5: 0 | AR5: 0 | AS5: 0.00% | AT5: ** | AU5: ** | AV5: ** | AW5: ** | AX5: ** | AY5: 0 | AZ5: 0.00% | BA5: 0 | BB5: 0.00% | BC5: 0 | BD5: 0.00% | BE5: 0 | BF5: 0 | BG5: 0 | BH5: 0 | BI5: 0.00% | BJ5: 0.00% | BK5: 0.00% | BL5: 0 | BM5: 0.00% | BN5: 0 | BO5: 0 | BP5: 0 | BQ5: 0 | BR5: 0 | BS5: 0 | BT5: 0.00% | BU5: 0.00% | BV5: 0.00% | BW5: 0 | BX5: 0 | BY5: 0 | BZ5: 0 | CA5: 0 | CB5: 0 | CC5: 0 | CD5: 0.00% | CE5: 0.00% | CF5: 0 | CG5: 0 | CH5: 0 | CI5: 0 | CJ5: 0.00% | CK5: 0.00% | CL5: 0.00% | CM5: 0.00% | CN5: 0.00% | CO5: 0.00% | CP5: 0 | CQ5: 0.00% | CR5: 0 | CS5: 0.00% | CT5: 0 | CU5: 0.00% | CV5: 0.00% | CW5: 0 | CX5: 0.00% | CY5: 0 | CZ5: 0.00% | DA5: 0 | DB5: 0.00% | DC5: 0.00% | DD5: 0.00% | DE5: 0.00%
A6: 2025-12-05 | B6: R0007EU | C6: B0FNMBQFBC | D6: B0FNMBQFBC | E6: R0007EU | F6: HYCHIKA-AP100A-空净 | G6: 0 | H6: 0 | I6: 0 | J6: 0 | K6: 0 | L6: 0 | M6: 0 | N6: 0 | O6: 0 | P6: 0 | Q6: 0 | R6: 0 | S6: 0 | T6: 0.00% | U6: 0.00% | V6: 0.00% | W6: 0.00% | X6: 0.00% | Y6: 0.00% | Z6: 0 | AA6: 0 | AB6: 0 | AC6: 0 | AD6: 0 | AE6: 0 | AF6: 0 | AG6: 0 | AH6: 0 | AI6: 0 | AJ6: 0 | AK6: 0 | AN6: 0 | AO6: 0 | AP6: 0.00% | AQ6: 0 | AR6: 0 | AS6: 0.00% | AT6: ** | AU6: ** | AV6: ** | AW6: ** | AX6: ** | AY6: 0 | AZ6: 0.00% | BA6: 0 | BB6: 0.00% | BC6: 0 | BD6: 0.00% | BE6: 0 | BF6: 0 | BG6: 0 | BH6: 0 | BI6: 0.00% | BJ6: 0.00% | BK6: 0.00% | BL6: 0 | BM6: 0.00% | BN6: 0 | BO6: 0 | BP6: 0 | BQ6: 0 | BR6: 0 | BS6: 0 | BT6: 0.00% | BU6: 0.00% | BV6: 0.00% | BW6: 0 | BX6: 0 | BY6: 0 | BZ6: 0 | CA6: 0 | CB6: 0 | CC6: 0 | CD6: 0.00% | CE6: 0.00% | CF6: 0 | CG6: 0 | CH6: 0 | CI6: 0 | CJ6: 0.00% | CK6: 0.00% | CL6: 0.00% | CM6: 0.00% | CN6: 0.00% | CO6: 0.00% | CP6: 0 | CQ6: 0.00% | CR6: 0 | CS6: 0.00% | CT6: 0 | CU6: 0.00% | CV6: 0.00% | CW6: 0 | CX6: 0.00% | CY6: 0 | CZ6: 0.00% | DA6: 0 | DB6: 0.00% | DC6: 0.00% | DD6: 0.00% | DE6: 0.00%
A7: 2025-12-06 | B7: R0007EU | C7: B0FNMBQFBC | D7: B0FNMBQFBC | E7: R0007EU | F7: HYCHIKA-AP100A-空净 | G7: 0 | H7: 0 | I7: 0 | J7: 0 | K7: 0 | L7: 0 | M7: 0 | N7: 0 | O7: 0 | P7: 0 | Q7: 0 | R7: 0 | S7: 0 | T7: 0.00% | U7: 0.00% | V7: 0.00% | W7: 0.00% | X7: 0.00% | Y7: 0.00% | Z7: 0 | AA7: 0 | AB7: 0 | AC7: 0 | AD7: 0 | AE7: 0 | AF7: 0 | AG7: 0 | AH7: 0 | AI7: 0 | AJ7: 0 | AK7: 0 | AN7: 0 | AO7: 0 | AP7: 0.00% | AQ7: 0 | AR7: 0 | AS7: 0.00% | AT7: ** | AU7: ** | AV7: ** | AW7: ** | AX7: ** | AY7: 0 | AZ7: 0.00% | BA7: 0 | BB7: 0.00% | BC7: 0 | BD7: 0.00% | BE7: 0 | BF7: 0 | BG7: 0 | BH7: 0 | BI7: 0.00% | BJ7: 0.00% | BK7: 0.00% | BL7: 0 | BM7: 0.00% | BN7: 0 | BO7: 0 | BP7: 0 | BQ7: 0 | BR7: 0 | BS7: 0 | BT7: 0.00% | BU7: 0.00% | BV7: 0.00% | BW7: 0 | BX7: 0 | BY7: 0 | BZ7: 0 | CA7: 0 | CB7: 0 | CC7: 0 | CD7: 0.00% | CE7: 0.00% | CF7: 0 | CG7: 0 | CH7: 0 | CI7: 0 | CJ7: 0.00% | CK7: 0.00% | CL7: 0.00% | CM7: 0.00% | CN7: 0.00% | CO7: 0.00% | CP7: 0 | CQ7: 0.00% | CR7: 0 | CS7: 0.00% | CT7: 0 | CU7: 0.00% | CV7: 0.00% | CW7: 0 | CX7: 0.00% | CY7: 0 | CZ7: 0.00% | DA7: 0 | DB7: 0.00% | DC7: 0.00% | DD7: 0.00% | DE7: 0.00%
A8: 2025-12-07 | B8: R0007EU | C8: B0FNMBQFBC | D8: B0FNMBQFBC | E8: R0007EU | F8: HYCHIKA-AP100A-空净 | G8: 0 | H8: 0 | I8: 0 | J8: 0 | K8: 0 | L8: 0 | M8: 0 | N8: 0 | O8: 0 | P8: 0 | Q8: 0 | R8: 0 | S8: 0 | T8: 0.00% | U8: 0.00% | V8: 0.00% | W8: 0.00% | X8: 0.00% | Y8: 0.00% | Z8: 0 | AA8: 0 | AB8: 0 | AC8: 0 | AD8: 0 | AE8: 0 | AF8: 0 | AG8: 0 | AH8: 0 | AI8: 0 | AJ8: 0 | AK8: 0 | AN8: 0 | AO8: 0 | AP8: 0.00% | AQ8: 0 | AR8: 0 | AS8: 0.00% | AT8: ** | AU8: ** | AV8: ** | AW8: ** | AX8: ** | AY8: 0 | AZ8: 0.00% | BA8: 0 | BB8: 0.00% | BC8: 0 | BD8: 0.00% | BE8: 0 | BF8: 0 | BG8: 0 | BH8: 0 | BI8: 0.00% | BJ8: 0.00% | BK8: 0.00% | BL8: 0 | BM8: 0.00% | BN8: 0 | BO8: 0 | BP8: 0 | BQ8: 0 | BR8: 0 | BS8: 0 | BT8: 0.00% | BU8: 0.00% | BV8: 0.00% | BW8: 0 | BX8: 0 | BY8: 0 | BZ8: 0 | CA8: 0 | CB8: 0 | CC8: 0 | CD8: 0.00% | CE8: 0.00% | CF8: 0 | CG8: 0 | CH8: 0 | CI8: 0 | CJ8: 0.00% | CK8: 0.00% | CL8: 0.00% | CM8: 0.00% | CN8: 0.00% | CO8: 0.00% | CP8: 0 | CQ8: 0.00% | CR8: 0 | CS8: 0.00% | CT8: 0 | CU8: 0.00% | CV8: 0.00% | CW8: 0 | CX8: 0.00% | CY8: 0 | CZ8: 0.00% | DA8: 0 | DB8: 0.00% | DC8: 0.00% | DD8: 0.00% | DE8: 0.00%
A9: 2025-12-08 | B9: R0007EU | C9: B0FNMBQFBC | D9: B0FNMBQFBC | E9: R0007EU | F9: HYCHIKA-AP100A-空净 | G9: 0 | H9: 0 | I9: 0 | J9: 0 | K9: 0 | L9: 0 | M9: 0 | N9: 0 | O9: 0 | P9: 0 | Q9: 0 | R9: 0 | S9: 0 | T9: 0.00% | U9: 0.00% | V9: 0.00% | W9: 0.00% | X9: 0.00% | Y9: 0.00% | Z9: 0 | AA9: 0 | AB9: 0 | AC9: 0 | AD9: 0 | AE9: 0 | AF9: 0 | AG9: 0 | AH9: 0 | AI9: 0 | AJ9: 0 | AK9: 0 | AN9: 0 | AO9: 0 | AP9: 0.00% | AQ9: 0 | AR9: 0 | AS9: 0.00% | AT9: ** | AU9: ** | AV9: ** | AW9: ** | AX9: ** | AY9: 0 | AZ9: 0.00% | BA9: 0 | BB9: 0.00% | BC9: 0 | BD9: 0.00% | BE9: 0 | BF9: 0 | BG9: 0 | BH9: 0 | BI9: 0.00% | BJ9: 0.00% | BK9: 0.00% | BL9: 0 | BM9: 0.00% | BN9: 0 | BO9: 0 | BP9: 0 | BQ9: 0 | BR9: 0 | BS9: 0 | BT9: 0.00% | BU9: 0.00% | BV9: 0.00% | BW9: 0 | BX9: 0 | BY9: 0 | BZ9: 0 | CA9: 0 | CB9: 0 | CC9: 0 | CD9: 0.00% | CE9: 0.00% | CF9: 0 | CG9: 0 | CH9: 0 | CI9: 0 | CJ9: 0.00% | CK9: 0.00% | CL9: 0.00% | CM9: 0.00% | CN9: 0.00% | CO9: 0.00% | CP9: 0 | CQ9: 0.00% | CR9: 0 | CS9: 0.00% | CT9: 0 | CU9: 0.00% | CV9: 0.00% | CW9: 0 | CX9: 0.00% | CY9: 0 | CZ9: 0.00% | DA9: 0 | DB9: 0.00% | DC9: 0.00% | DD9: 0.00% | DE9: 0.00%
A10: 2025-12-09 | B10: R0007EU | C10: B0FNMBQFBC | D10: B0FNMBQFBC | E10: R0007EU | F10: HYCHIKA-AP100A-空净 | G10: 0 | H10: 0 | I10: 0 | J10: 0 | K10: 0 | L10: 0 | M10: 0 | N10: 0 | O10: 0 | P10: 0 | Q10: 0 | R10: 0 | S10: 0 | T10: 0.00% | U10: 0.00% | V10: 0.00% | W10: 0.00% | X10: 0.00% | Y10: 0.00% | Z10: 0 | AA10: 0 | AB10: 0 | AC10: 0 | AD10: 0 | AE10: 0 | AF10: 0 | AG10: 0 | AH10: 0 | AI10: 0 | AJ10: 0 | AK10: 0 | AN10: 0 | AO10: 0 | AP10: 0.00% | AQ10: 0 | AR10: 0 | AS10: 0.00% | AT10: ** | AU10: ** | AV10: ** | AW10: ** | AX10: ** | AY10: 0 | AZ10: 0.00% | BA10: 0 | BB10: 0.00% | BC10: 0 | BD10: 0.00% | BE10: 0 | BF10: 0 | BG10: 0 | BH10: 0 | BI10: 0.00% | BJ10: 0.00% | BK10: 0.00% | BL10: 0 | BM10: 0.00% | BN10: 0 | BO10: 0 | BP10: 0 | BQ10: 0 | BR10: 0 | BS10: 0 | BT10: 0.00% | BU10: 0.00% | BV10: 0.00% | BW10: 0 | BX10: 0 | BY10: 0 | BZ10: 0 | CA10: 0 | CB10: 0 | CC10: 0 | CD10: 0.00% | CE10: 0.00% | CF10: 0 | CG10: 0 | CH10: 0 | CI10: 0 | CJ10: 0.00% | CK10: 0.00% | CL10: 0.00% | CM10: 0.00% | CN10: 0.00% | CO10: 0.00% | CP10: 0 | CQ10: 0.00% | CR10: 0 | CS10: 0.00% | CT10: 0 | CU10: 0.00% | CV10: 0.00% | CW10: 0 | CX10: 0.00% | CY10: 0 | CZ10: 0.00% | DA10: 0 | DB10: 0.00% | DC10: 0.00% | DD10: 0.00% | DE10: 0.00%
A11: 2025-12-10 | B11: R0007EU | C11: B0FNMBQFBC | D11: B0FNMBQFBC | E11: R0007EU | F11: HYCHIKA-AP100A-空净 | G11: 0 | H11: 0 | I11: 0 | J11: 0 | K11: 0 | L11: 0 | M11: 0 | N11: 0 | O11: 0 | P11: 0 | Q11: 0 | R11: 0 | S11: 0 | T11: 0.00% | U11: 0.00% | V11: 0.00% | W11: 0.00% | X11: 0.00% | Y11: 0.00% | Z11: 0 | AA11: 0 | AB11: 0 | AC11: 0 | AD11: 0 | AE11: 0 | AF11: 0 | AG11: 0 | AH11: 0 | AI11: 0 | AJ11: 0 | AK11: 0 | AN11: 0 | AO11: 0 | AP11: 0.00% | AQ11: 0 | AR11: 0 | AS11: 0.00% | AT11: ** | AU11: ** | AV11: ** | AW11: ** | AX11: ** | AY11: 0 | AZ11: 0.00% | BA11: 0 | BB11: 0.00% | BC11: 0 | BD11: 0.00% | BE11: 0 | BF11: 0 | BG11: 0 | BH11: 0 | BI11: 0.00% | BJ11: 0.00% | BK11: 0.00% | BL11: 0 | BM11: 0.00% | BN11: 0 | BO11: 0 | BP11: 0 | BQ11: 0 | BR11: 0 | BS11: 0 | BT11: 0.00% | BU11: 0.00% | BV11: 0.00% | BW11: 0 | BX11: 0 | BY11: 0 | BZ11: 0 | CA11: 0 | CB11: 0 | CC11: 0 | CD11: 0.00% | CE11: 0.00% | CF11: 0 | CG11: 0 | CH11: 0 | CI11: 0 | CJ11: 0.00% | CK11: 0.00% | CL11: 0.00% | CM11: 0.00% | CN11: 0.00% | CO11: 0.00% | CP11: 0 | CQ11: 0.00% | CR11: 0 | CS11: 0.00% | CT11: 0 | CU11: 0.00% | CV11: 0.00% | CW11: 0 | CX11: 0.00% | CY11: 0 | CZ11: 0.00% | DA11: 0 | DB11: 0.00% | DC11: 0.00% | DD11: 0.00% | DE11: 0.00%
A12: 2025-12-11 | B12: R0007EU | C12: B0FNMBQFBC | D12: B0FNMBQFBC | E12: R0007EU | F12: HYCHIKA-AP100A-空净 | G12: 0 | H12: 0 | I12: 0 | J12: 0 | K12: 0 | L12: 0 | M12: 0 | N12: 0 | O12: 0 | P12: 0 | Q12: 0 | R12: 0 | S12: 0 | T12: 0.00% | U12: 0.00% | V12: 0.00% | W12: 0.00% | X12: 0.00% | Y12: 0.00% | Z12: 0 | AA12: 0 | AB12: 0 | AC12: 0 | AD12: 0 | AE12: 0 | AF12: 0 | AG12: 0 | AH12: 0 | AI12: 0 | AJ12: 0 | AK12: 0 | AN12: 0 | AO12: 0 | AP12: 0.00% | AQ12: 0 | AR12: 0 | AS12: 0.00% | AT12: ** | AU12: ** | AV12: ** | AW12: ** | AX12: ** | AY12: 0 | AZ12: 0.00% | BA12: 0 | BB12: 0.00% | BC12: 0 | BD12: 0.00% | BE12: 0 | BF12: 0 | BG12: 0 | BH12: 0 | BI12: 0.00% | BJ12: 0.00% | BK12: 0.00% | BL12: 0 | BM12: 0.00% | BN12: 0 | BO12: 0 | BP12: 0 | BQ12: 0 | BR12: 0 | BS12: 0 | BT12: 0.00% | BU12: 0.00% | BV12: 0.00% | BW12: 0 | BX12: 0 | BY12: 0 | BZ12: 0 | CA12: 0 | CB12: 0 | CC12: 0 | CD12: 0.00% | CE12: 0.00% | CF12: 0 | CG12: 0 | CH12: 0 | CI12: 0 | CJ12: 0.00% | CK12: 0.00% | CL12: 0.00% | CM12: 0.00% | CN12: 0.00% | CO12: 0.00% | CP12: 0 | CQ12: 0.00% | CR12: 0 | CS12: 0.00% | CT12: 0 | CU12: 0.00% | CV12: 0.00% | CW12: 0 | CX12: 0.00% | CY12: 0 | CZ12: 0.00% | DA12: 0 | DB12: 0.00% | DC12: 0.00% | DD12: 0.00% | DE12: 0.00%
A13: 2025-12-12 | B13: R0007EU | C13: B0FNMBQFBC | D13: B0FNMBQFBC | E13: R0007EU | F13: HYCHIKA-AP100A-空净 | G13: 0 | H13: 0 | I13: 0 | J13: 0 | K13: 0 | L13: 0 | M13: 0 | N13: 0 | O13: 0 | P13: 0 | Q13: 0 | R13: 0 | S13: 0 | T13: 0.00% | U13: 0.00% | V13: 0.00% | W13: 0.00% | X13: 0.00% | Y13: 0.00% | Z13: 0 | AA13: 0 | AB13: 0 | AC13: 0 | AD13: 0 | AE13: 0 | AF13: 0 | AG13: 0 | AH13: 0 | AI13: 0 | AJ13: 0 | AK13: 0 | AN13: 0 | AO13: 0 | AP13: 0.00% | AQ13: 0 | AR13: 0 | AS13: 0.00% | AT13: ** | AU13: ** | AV13: ** | AW13: ** | AX13: ** | AY13: 0 | AZ13: 0.00% | BA13: 0 | BB13: 0.00% | BC13: 0 | BD13: 0.00% | BE13: 0 | BF13: 0 | BG13: 0 | BH13: 0 | BI13: 0.00% | BJ13: 0.00% | BK13: 0.00% | BL13: 0 | BM13: 0.00% | BN13: 0 | BO13: 0 | BP13: 0 | BQ13: 0 | BR13: 0 | BS13: 0 | BT13: 0.00% | BU13: 0.00% | BV13: 0.00% | BW13: 0 | BX13: 0 | BY13: 0 | BZ13: 0 | CA13: 0 | CB13: 0 | CC13: 0 | CD13: 0.00% | CE13: 0.00% | CF13: 0 | CG13: 0 | CH13: 0 | CI13: 0 | CJ13: 0.00% | CK13: 0.00% | CL13: 0.00% | CM13: 0.00% | CN13: 0.00% | CO13: 0.00% | CP13: 0 | CQ13: 0.00% | CR13: 0 | CS13: 0.00% | CT13: 0 | CU13: 0.00% | CV13: 0.00% | CW13: 0 | CX13: 0.00% | CY13: 0 | CZ13: 0.00% | DA13: 0 | DB13: 0.00% | DC13: 0.00% | DD13: 0.00% | DE13: 0.00%
... A24: 2025-12-23 | B24: R0007EU | C24: B0FNMBQFBC | D24: B0FNMBQFBC | E24: R0007EU | F24: HYCHIKA-AP100A-空净 | G24: 59.99 | H24: 59.99 | I24: 192 | J24: 0 | K24: 0 | L24: 0 | M24: 0 | N24: 0 | O24: 192 | P24: 0 | Q24: 0 | R24: 0 | S24: 0 | T24: 0.00% | U24: 0.00% | V24: 0.00% | W24: 0.00% | X24: 0.00% | Y24: 0.00% | Z24: 0 | AA24: 0 | AB24: 0 | AC24: 0 | AD24: 0 | AE24: 0 | AF24: 0 | AG24: 0 | AH24: 0 | AI24: 0 | AJ24: 0 | AK24: 0 | AN24: 0 | AO24: 0 | AP24: 0.00% | AQ24: 0 | AR24: 0 | AS24: 0.00% | AT24: ** | AU24: ** | AV24: ** | AW24: ** | AX24: ** | AY24: 0 | AZ24: 0.00% | BA24: 0 | BB24: 0.00% | BC24: 0 | BD24: 0.00% | BE24: 0 | BF24: 0 | BG24: 0 | BH24: 0 | BI24: 0.00% | BJ24: 0.00% | BK24: 0.00% | BL24: 0 | BM24: 0.00% | BN24: 0 | BO24: 0 | BP24: 0 | BQ24: 0 | BR24: 0 | BS24: 0 | BT24: 0.00% | BU24: 0.00% | BV24: 0.00% | BW24: 0 | BX24: 0 | BY24: 0 | BZ24: 0 | CA24: 0 | CB24: 0 | CC24: 0 | CD24: 0.00% | CE24: 0.00% | CF24: 0 | CG24: 0 | CH24: 0 | CI24: 0 | CJ24: 0.00% | CK24: 0.00% | CL24: 0.00% | CM24: 0.00% | CN24: 0.00% | CO24: 0.00% | CP24: 0 | CQ24: 0.00% | CR24: 0 | CS24: 0.00% | CT24: 0 | CU24: 0.00% | CV24: 0.00% | CW24: 0 | CX24: 0.00% | CY24: 0 | CZ24: 0.00% | DA24: 0 | DB24: 0.00% | DC24: 0.00% | DD24: 0.00% | DE24: 0.00%
A25: 2025-12-24 | B25: R0007EU | C25: B0FNMBQFBC | D25: B0FNMBQFBC | E25: R0007EU | F25: HYCHIKA-AP100A-空净 | G25: 59.99 | H25: 59.99 | I25: 193 | J25: 0 | K25: 0 | L25: 0 | M25: 0 | N25: 0 | O25: 193 | P25: 0 | Q25: 0 | R25: 0 | S25: 0 | T25: 0.00% | U25: 0.00% | V25: 0.00% | W25: 0.00% | X25: 0.00% | Y25: 0.00% | Z25: 0 | AA25: 0 | AB25: 0 | AC25: 0 | AD25: 0 | AE25: 0 | AF25: 0 | AG25: 0 | AH25: 0 | AI25: 0 | AJ25: 0 | AK25: 0 | AL25: Cuisine et Maison：139806 | AM25: Petits appareils：5950 | AN25: 0 | AO25: 0 | AP25: 0.00% | AQ25: 0 | AR25: 0 | AS25: 0.00% | AT25: ** | AU25: ** | AV25: ** | AW25: ** | AX25: ** | AY25: 0 | AZ25: 0.00% | BA25: 0 | BB25: 0.00% | BC25: 0 | BD25: 0.00% | BE25: 0 | BF25: 0 | BG25: 0 | BH25: 0 | BI25: 0.00% | BJ25: 0.00% | BK25: 0.00% | BL25: 0 | BM25: 0.00% | BN25: 0 | BO25: 0 | BP25: 0 | BQ25: 0 | BR25: 0 | BS25: 0 | BT25: 0.00% | BU25: 0.00% | BV25: 0.00% | BW25: 0 | BX25: 0 | BY25: 0 | BZ25: 0 | CA25: 0 | CB25: 0 | CC25: 0 | CD25: 0.00% | CE25: 0.00% | CF25: 0 | CG25: 0 | CH25: 0 | CI25: 0 | CJ25: 0.00% | CK25: 0.00% | CL25: 0.00% | CM25: 0.00% | CN25: 0.00% | CO25: 0.00% | CP25: 0 | CQ25: 0.00% | CR25: 0 | CS25: 0.00% | CT25: 0 | CU25: 0.00% | CV25: 0.00% | CW25: 0 | CX25: 0.00% | CY25: 0 | CZ25: 0.00% | DA25: 0 | DB25: 0.00% | DC25: 0.00% | DD25: 0.00% | DE25: 0.00%

Sheet 意大利ERP数据
A1: 时间 | B1: SKU | C1: 父ASIN | D1: ASIN | E1: MSKU | F1: 品名 | G1: 售价(总价) | H1: 价格 | I1: FBA-可售 | J1: FBM可售 | K1: AWD在库 | L1: AWD可用量 | M1: AWD待发货量 | N1: AWD标发在途 | O1: 可用库存 | P1: 销量 | Q1: 销售额 | R1: 订单量 | S1: 净销售额 | T1: 销量环比 | U1: 销售额环比 | V1: 订单量环比 | W1: 销量同比 | X1: 订单量同比 | Y1: 销量额同比 | Z1: B2B 销量 | AA1: B2B 销售额 | AB1: B2B 订单量 | AC1: FBM买家运费 | AD1: 促销销量 | AE1: 促销销售额 | AF1: 促销订单量 | AG1: 促销折扣 | AH1: 日均销量 | AI1: 日均销售额 | AJ1: 日均订单量 | AK1: 销售均价 | AL1: 大类排名 | AM1: 小类排名 | AN1: 退款量 | AO1: 退款金额 | AP1: 退款率 | AQ1: 评分 | AR1: 评论数 | AS1: 留评率 | AT1: 结算毛利润 | AU1: 订单毛利润 | AV1: 结算毛利率 | AW1: 订单毛利率 | AX1: ROI | AY1: 退货量 | AZ1: 退货率 | BA1: Sessions-Browser | BB1: Sessions-Browser-Percentage | BC1: Sessions-Mobile | BD1: Sessions-Mobile-Percentage | BE1: Sessions-Total | BF1: PV-Browser | BG1: PV-Mobile | BH1: PV-Total | BI1: CVR | BJ1: 销量CVR | BK1: Buybox赢得率 | BL1: CPC | BM1: CTR | BN1: 广告花费 | BO1: SB广告费 | BP1: SBV广告费 | BQ1: SD广告费 | BR1: SP广告费 | BS1: ROAS | BT1: ACOS | BU1: ACoAS | BV1: ASoAS | BW1: CPO | BX1: CPU | BY1: CPM | BZ1: 广告销售额 | CA1: 广告订单量 | CB1: 直接成交订单量 | CC1: 直接成交销售额 | CD1: 广告订单占比 | CE1: 广告CVR | CF1: 展示 | CG1: 点击 | CH1: 自然订单量 | CI1: 自然点击量 | CJ1: 自然CVR | CK1: Sessions-Percentage | CL1: Unit-Sessions-Percentage | CM1: PV-Browser-Percentage | CN1: PV-Mobile-Percentage | CO1: PV-Percentage | CP1: Sessions-Browser(B2B) | CQ1: Sessions-Browser-Percentage(B2B) | CR1: Sessions-Mobile(B2B) | CS1: Sessions-Mobile-Percentage(B2B) | CT1: Sessions-Total(B2B) | CU1: Sessions-Percentage(B2B) | CV1: Unit-Sessions-Percentage(B2B) | CW1: PV-Browser(B2B) | CX1: PV-Browser-Percentage(B2B) | CY1: PV-Mobile(B2B) | CZ1: PV-Mobile-Percentage(B2B) | DA1: PV-Total(B2B) | DB1: PV-Percentage(B2B) | DC1: CVR(B2B) | DD1: 销量CVR(B2B) | DE1: Buybox赢得率(B2B) | DF1: 运营日志
A2: 2025-12-01 | B2: R0007EU | C2: B0FNMBQFBC | D2: B0FNMBQFBC | E2: R0007EU | F2: HYCHIKA-AP100A-空净 | G2: 0 | H2: 64.99 | I2: 0 | J2: 0 | K2: 0 | L2: 0 | M2: 0 | N2: 0 | O2: 0 | P2: 0 | Q2: 0 | R2: 0 | S2: 0 | T2: 0.00% | U2: 0.00% | V2: 0.00% | W2: 0.00% | X2: 0.00% | Y2: 0.00% | Z2: 0 | AA2: 0 | AB2: 0 | AC2: 0 | AD2: 0 | AE2: 0 | AF2: 0 | AG2: 0 | AH2: 0 | AI2: 0 | AJ2: 0 | AK2: 0 | AN2: 0 | AO2: 0 | AP2: 0.00% | AQ2: 0 | AR2: 0 | AS2: 0.00% | AT2: ** | AU2: ** | AV2: ** | AW2: ** | AX2: ** | AY2: 0 | AZ2: 0.00% | BA2: 0 | BB2: 0.00% | BC2: 0 | BD2: 0.00% | BE2: 0 | BF2: 0 | BG2: 0 | BH2: 0 | BI2: 0.00% | BJ2: 0.00% | BK2: 0.00% | BL2: 0 | BM2: 0.00% | BN2: 0 | BO2: 0 | BP2: 0 | BQ2: 0 | BR2: 0 | BS2: 0 | BT2: 0.00% | BU2: 0.00% | BV2: 0.00% | BW2: 0 | BX2: 0 | BY2: 0 | BZ2: 0 | CA2: 0 | CB2: 0 | CC2: 0 | CD2: 0.00% | CE2: 0.00% | CF2: 0 | CG2: 0 | CH2: 0 | CI2: 0 | CJ2: 0.00% | CK2: 0.00% | CL2: 0.00% | CM2: 0.00% | CN2: 0.00% | CO2: 0.00% | CP2: 0 | CQ2: 0.00% | CR2: 0 | CS2: 0.00% | CT2: 0 | CU2: 0.00% | CV2: 0.00% | CW2: 0 | CX2: 0.00% | CY2: 0 | CZ2: 0.00% | DA2: 0 | DB2: 0.00% | DC2: 0.00% | DD2: 0.00% | DE2: 0.00%
A3: 2025-12-02 | B3: R0007EU | C3: B0FNMBQFBC | D3: B0FNMBQFBC | E3: R0007EU | F3: HYCHIKA-AP100A-空净 | G3: 0 | H3: 64.99 | I3: 0 | J3: 0 | K3: 0 | L3: 0 | M3: 0 | N3: 0 | O3: 0 | P3: 0 | Q3: 0 | R3: 0 | S3: 0 | T3: 0.00% | U3: 0.00% | V3: 0.00% | W3: 0.00% | X3: 0.00% | Y3: 0.00% | Z3: 0 | AA3: 0 | AB3: 0 | AC3: 0 | AD3: 0 | AE3: 0 | AF3: 0 | AG3: 0 | AH3: 0 | AI3: 0 | AJ3: 0 | AK3: 0 | AN3: 0 | AO3: 0 | AP3: 0.00% | AQ3: 0 | AR3: 0 | AS3: 0.00% | AT3: ** | AU3: ** | AV3: ** | AW3: ** | AX3: ** | AY3: 0 | AZ3: 0.00% | BA3: 0 | BB3: 0.00% | BC3: 0 | BD3: 0.00% | BE3: 0 | BF3: 0 | BG3: 0 | BH3: 0 | BI3: 0.00% | BJ3: 0.00% | BK3: 0.00% | BL3: 0 | BM3: 0.00% | BN3: 0 | BO3: 0 | BP3: 0 | BQ3: 0 | BR3: 0 | BS3: 0 | BT3: 0.00% | BU3: 0.00% | BV3: 0.00% | BW3: 0 | BX3: 0 | BY3: 0 | BZ3: 0 | CA3: 0 | CB3: 0 | CC3: 0 | CD3: 0.00% | CE3: 0.00% | CF3: 0 | CG3: 0 | CH3: 0 | CI3: 0 | CJ3: 0.00% | CK3: 0.00% | CL3: 0.00% | CM3: 0.00% | CN3: 0.00% | CO3: 0.00% | CP3: 0 | CQ3: 0.00% | CR3: 0 | CS3: 0.00% | CT3: 0 | CU3: 0.00% | CV3: 0.00% | CW3: 0 | CX3: 0.00% | CY3: 0 | CZ3: 0.00% | DA3: 0 | DB3: 0.00% | DC3: 0.00% | DD3: 0.00% | DE3: 0.00%
A4: 2025-12-03 | B4: R0007EU | C4: B0FNMBQFBC | D4: B0FNMBQFBC | E4: R0007EU | F4: HYCHIKA-AP100A-空净 | G4: 0 | H4: 64.99 | I4: 0 | J4: 0 | K4: 0 | L4: 0 | M4: 0 | N4: 0 | O4: 0 | P4: 0 | Q4: 0 | R4: 0 | S4: 0 | T4: 0.00% | U4: 0.00% | V4: 0.00% | W4: 0.00% | X4: 0.00% | Y4: 0.00% | Z4: 0 | AA4: 0 | AB4: 0 | AC4: 0 | AD4: 0 | AE4: 0 | AF4: 0 | AG4: 0 | AH4: 0 | AI4: 0 | AJ4: 0 | AK4: 0 | AN4: 0 | AO4: 0 | AP4: 0.00% | AQ4: 0 | AR4: 0 | AS4: 0.00% | AT4: ** | AU4: ** | AV4: ** | AW4: ** | AX4: ** | AY4: 0 | AZ4: 0.00% | BA4: 0 | BB4: 0.00% | BC4: 0 | BD4: 0.00% | BE4: 0 | BF4: 0 | BG4: 0 | BH4: 0 | BI4: 0.00% | BJ4: 0.00% | BK4: 0.00% | BL4: 0 | BM4: 0.00% | BN4: 0 | BO4: 0 | BP4: 0 | BQ4: 0 | BR4: 0 | BS4: 0 | BT4: 0.00% | BU4: 0.00% | BV4: 0.00% | BW4: 0 | BX4: 0 | BY4: 0 | BZ4: 0 | CA4: 0 | CB4: 0 | CC4: 0 | CD4: 0.00% | CE4: 0.00% | CF4: 0 | CG4: 0 | CH4: 0 | CI4: 0 | CJ4: 0.00% | CK4: 0.00% | CL4: 0.00% | CM4: 0.00% | CN4: 0.00% | CO4: 0.00% | CP4: 0 | CQ4: 0.00% | CR4: 0 | CS4: 0.00% | CT4: 0 | CU4: 0.00% | CV4: 0.00% | CW4: 0 | CX4: 0.00% | CY4: 0 | CZ4: 0.00% | DA4: 0 | DB4: 0.00% | DC4: 0.00% | DD4: 0.00% | DE4: 0.00%
A5: 2025-12-04 | B5: R0007EU | C5: B0FNMBQFBC | D5: B0FNMBQFBC | E5: R0007EU | F5: HYCHIKA-AP100A-空净 | G5: 0 | H5: 64.99 | I5: 0 | J5: 0 | K5: 0 | L5: 0 | M5: 0 | N5: 0 | O5: 0 | P5: 0 | Q5: 0 | R5: 0 | S5: 0 | T5: 0.00% | U5: 0.00% | V5: 0.00% | W5: 0.00% | X5: 0.00% | Y5: 0.00% | Z5: 0 | AA5: 0 | AB5: 0 | AC5: 0 | AD5: 0 | AE5: 0 | AF5: 0 | AG5: 0 | AH5: 0 | AI5: 0 | AJ5: 0 | AK5: 0 | AN5: 0 | AO5: 0 | AP5: 0.00% | AQ5: 0 | AR5: 0 | AS5: 0.00% | AT5: ** | AU5: ** | AV5: ** | AW5: ** | AX5: ** | AY5: 0 | AZ5: 0.00% | BA5: 0 | BB5: 0.00% | BC5: 0 | BD5: 0.00% | BE5: 0 | BF5: 0 | BG5: 0 | BH5: 0 | BI5: 0.00% | BJ5: 0.00% | BK5: 0.00% | BL5: 0 | BM5: 0.00% | BN5: 0 | BO5: 0 | BP5: 0 | BQ5: 0 | BR5: 0 | BS5: 0 | BT5: 0.00% | BU5: 0.00% | BV5: 0.00% | BW5: 0 | BX5: 0 | BY5: 0 | BZ5: 0 | CA5: 0 | CB5: 0 | CC5: 0 | CD5: 0.00% | CE5: 0.00% | CF5: 0 | CG5: 0 | CH5: 0 | CI5: 0 | CJ5: 0.00% | CK5: 0.00% | CL5: 0.00% | CM5: 0.00% | CN5: 0.00% | CO5: 0.00% | CP5: 0 | CQ5: 0.00% | CR5: 0 | CS5: 0.00% | CT5: 0 | CU5: 0.00% | CV5: 0.00% | CW5: 0 | CX5: 0.00% | CY5: 0 | CZ5: 0.00% | DA5: 0 | DB5: 0.00% | DC5: 0.00% | DD5: 0.00% | DE5: 0.00%
A6: 2025-12-05 | B6: R0007EU | C6: B0FNMBQFBC | D6: B0FNMBQFBC | E6: R0007EU | F6: HYCHIKA-AP100A-空净 | G6: 0 | H6: 64.99 | I6: 0 | J6: 0 | K6: 0 | L6: 0 | M6: 0 | N6: 0 | O6: 0 | P6: 0 | Q6: 0 | R6: 0 | S6: 0 | T6: 0.00% | U6: 0.00% | V6: 0.00% | W6: 0.00% | X6: 0.00% | Y6: 0.00% | Z6: 0 | AA6: 0 | AB6: 0 | AC6: 0 | AD6: 0 | AE6: 0 | AF6: 0 | AG6: 0 | AH6: 0 | AI6: 0 | AJ6: 0 | AK6: 0 | AN6: 0 | AO6: 0 | AP6: 0.00% | AQ6: 0 | AR6: 0 | AS6: 0.00% | AT6: ** | AU6: ** | AV6: ** | AW6: ** | AX6: ** | AY6: 0 | AZ6: 0.00% | BA6: 0 | BB6: 0.00% | BC6: 0 | BD6: 0.00% | BE6: 0 | BF6: 0 | BG6: 0 | BH6: 0 | BI6: 0.00% | BJ6: 0.00% | BK6: 0.00% | BL6: 0 | BM6: 0.00% | BN6: 0 | BO6: 0 | BP6: 0 | BQ6: 0 | BR6: 0 | BS6: 0 | BT6: 0.00% | BU6: 0.00% | BV6: 0.00% | BW6: 0 | BX6: 0 | BY6: 0 | BZ6: 0 | CA6: 0 | CB6: 0 | CC6: 0 | CD6: 0.00% | CE6: 0.00% | CF6: 0 | CG6: 0 | CH6: 0 | CI6: 0 | CJ6: 0.00% | CK6: 0.00% | CL6: 0.00% | CM6: 0.00% | CN6: 0.00% | CO6: 0.00% | CP6: 0 | CQ6: 0.00% | CR6: 0 | CS6: 0.00% | CT6: 0 | CU6: 0.00% | CV6: 0.00% | CW6: 0 | CX6: 0.00% | CY6: 0 | CZ6: 0.00% | DA6: 0 | DB6: 0.00% | DC6: 0.00% | DD6: 0.00% | DE6: 0.00%
A7: 2025-12-06 | B7: R0007EU | C7: B0FNMBQFBC | D7: B0FNMBQFBC | E7: R0007EU | F7: HYCHIKA-AP100A-空净 | G7: 0 | H7: 64.99 | I7: 0 | J7: 0 | K7: 0 | L7: 0 | M7: 0 | N7: 0 | O7: 0 | P7: 0 | Q7: 0 | R7: 0 | S7: 0 | T7: 0.00% | U7: 0.00% | V7: 0.00% | W7: 0.00% | X7: 0.00% | Y7: 0.00% | Z7: 0 | AA7: 0 | AB7: 0 | AC7: 0 | AD7: 0 | AE7: 0 | AF7: 0 | AG7: 0 | AH7: 0 | AI7: 0 | AJ7: 0 | AK7: 0 | AN7: 0 | AO7: 0 | AP7: 0.00% | AQ7: 0 | AR7: 0 | AS7: 0.00% | AT7: ** | AU7: ** | AV7: ** | AW7: ** | AX7: ** | AY7: 0 | AZ7: 0.00% | BA7: 0 | BB7: 0.00% | BC7: 0 | BD7: 0.00% | BE7: 0 | BF7: 0 | BG7: 0 | BH7: 0 | BI7: 0.00% | BJ7: 0.00% | BK7: 0.00% | BL7: 0 | BM7: 0.00% | BN7: 0 | BO7: 0 | BP7: 0 | BQ7: 0 | BR7: 0 | BS7: 0 | BT7: 0.00% | BU7: 0.00% | BV7: 0.00% | BW7: 0 | BX7: 0 | BY7: 0 | BZ7: 0 | CA7: 0 | CB7: 0 | CC7: 0 | CD7: 0.00% | CE7: 0.00% | CF7: 0 | CG7: 0 | CH7: 0 | CI7: 0 | CJ7: 0.00% | CK7: 0.00% | CL7: 0.00% | CM7: 0.00% | CN7: 0.00% | CO7: 0.00% | CP7: 0 | CQ7: 0.00% | CR7: 0 | CS7: 0.00% | CT7: 0 | CU7: 0.00% | CV7: 0.00% | CW7: 0 | CX7: 0.00% | CY7: 0 | CZ7: 0.00% | DA7: 0 | DB7: 0.00% | DC7: 0.00% | DD7: 0.00% | DE7: 0.00%
A8: 2025-12-07 | B8: R0007EU | C8: B0FNMBQFBC | D8: B0FNMBQFBC | E8: R0007EU | F8: HYCHIKA-AP100A-空净 | G8: 0 | H8: 64.99 | I8: 0 | J8: 0 | K8: 0 | L8: 0 | M8: 0 | N8: 0 | O8: 0 | P8: 0 | Q8: 0 | R8: 0 | S8: 0 | T8: 0.00% | U8: 0.00% | V8: 0.00% | W8: 0.00% | X8: 0.00% | Y8: 0.00% | Z8: 0 | AA8: 0 | AB8: 0 | AC8: 0 | AD8: 0 | AE8: 0 | AF8: 0 | AG8: 0 | AH8: 0 | AI8: 0 | AJ8: 0 | AK8: 0 | AN8: 0 | AO8: 0 | AP8: 0.00% | AQ8: 0 | AR8: 0 | AS8: 0.00% | AT8: ** | AU8: ** | AV8: ** | AW8: ** | AX8: ** | AY8: 0 | AZ8: 0.00% | BA8: 0 | BB8: 0.00% | BC8: 0 | BD8: 0.00% | BE8: 0 | BF8: 0 | BG8: 0 | BH8: 0 | BI8: 0.00% | BJ8: 0.00% | BK8: 0.00% | BL8: 0 | BM8: 0.00% | BN8: 0 | BO8: 0 | BP8: 0 | BQ8: 0 | BR8: 0 | BS8: 0 | BT8: 0.00% | BU8: 0.00% | BV8: 0.00% | BW8: 0 | BX8: 0 | BY8: 0 | BZ8: 0 | CA8: 0 | CB8: 0 | CC8: 0 | CD8: 0.00% | CE8: 0.00% | CF8: 0 | CG8: 0 | CH8: 0 | CI8: 0 | CJ8: 0.00% | CK8: 0.00% | CL8: 0.00% | CM8: 0.00% | CN8: 0.00% | CO8: 0.00% | CP8: 0 | CQ8: 0.00% | CR8: 0 | CS8: 0.00% | CT8: 0 | CU8: 0.00% | CV8: 0.00% | CW8: 0 | CX8: 0.00% | CY8: 0 | CZ8: 0.00% | DA8: 0 | DB8: 0.00% | DC8: 0.00% | DD8: 0.00% | DE8: 0.00%
A9: 2025-12-08 | B9: R0007EU | C9: B0FNMBQFBC | D9: B0FNMBQFBC | E9: R0007EU | F9: HYCHIKA-AP100A-空净 | G9: 0 | H9: 64.99 | I9: 0 | J9: 0 | K9: 0 | L9: 0 | M9: 0 | N9: 0 | O9: 0 | P9: 0 | Q9: 0 | R9: 0 | S9: 0 | T9: 0.00% | U9: 0.00% | V9: 0.00% | W9: 0.00% | X9: 0.00% | Y9: 0.00% | Z9: 0 | AA9: 0 | AB9: 0 | AC9: 0 | AD9: 0 | AE9: 0 | AF9: 0 | AG9: 0 | AH9: 0 | AI9: 0 | AJ9: 0 | AK9: 0 | AN9: 0 | AO9: 0 | AP9: 0.00% | AQ9: 0 | AR9: 0 | AS9: 0.00% | AT9: ** | AU9: ** | AV9: ** | AW9: ** | AX9: ** | AY9: 0 | AZ9: 0.00% | BA9: 0 | BB9: 0.00% | BC9: 0 | BD9: 0.00% | BE9: 0 | BF9: 0 | BG9: 0 | BH9: 0 | BI9: 0.00% | BJ9: 0.00% | BK9: 0.00% | BL9: 0 | BM9: 0.00% | BN9: 0 | BO9: 0 | BP9: 0 | BQ9: 0 | BR9: 0 | BS9: 0 | BT9: 0.00% | BU9: 0.00% | BV9: 0.00% | BW9: 0 | BX9: 0 | BY9: 0 | BZ9: 0 | CA9: 0 | CB9: 0 | CC9: 0 | CD9: 0.00% | CE9: 0.00% | CF9: 0 | CG9: 0 | CH9: 0 | CI9: 0 | CJ9: 0.00% | CK9: 0.00% | CL9: 0.00% | CM9: 0.00% | CN9: 0.00% | CO9: 0.00% | CP9: 0 | CQ9: 0.00% | CR9: 0 | CS9: 0.00% | CT9: 0 | CU9: 0.00% | CV9: 0.00% | CW9: 0 | CX9: 0.00% | CY9: 0 | CZ9: 0.00% | DA9: 0 | DB9: 0.00% | DC9: 0.00% | DD9: 0.00% | DE9: 0.00%
A10: 2025-12-09 | B10: R0007EU | C10: B0FNMBQFBC | D10: B0FNMBQFBC | E10: R0007EU | F10: HYCHIKA-AP100A-空净 | G10: 0 | H10: 64.99 | I10: 0 | J10: 0 | K10: 0 | L10: 0 | M10: 0 | N10: 0 | O10: 0 | P10: 0 | Q10: 0 | R10: 0 | S10: 0 | T10: 0.00% | U10: 0.00% | V10: 0.00% | W10: 0.00% | X10: 0.00% | Y10: 0.00% | Z10: 0 | AA10: 0 | AB10: 0 | AC10: 0 | AD10: 0 | AE10: 0 | AF10: 0 | AG10: 0 | AH10: 0 | AI10: 0 | AJ10: 0 | AK10: 0 | AN10: 0 | AO10: 0 | AP10: 0.00% | AQ10: 0 | AR10: 0 | AS10: 0.00% | AT10: ** | AU10: ** | AV10: ** | AW10: ** | AX10: ** | AY10: 0 | AZ10: 0.00% | BA10: 0 | BB10: 0.00% | BC10: 0 | BD10: 0.00% | BE10: 0 | BF10: 0 | BG10: 0 | BH10: 0 | BI10: 0.00% | BJ10: 0.00% | BK10: 0.00% | BL10: 0 | BM10: 0.00% | BN10: 0 | BO10: 0 | BP10: 0 | BQ10: 0 | BR10: 0 | BS10: 0 | BT10: 0.00% | BU10: 0.00% | BV10: 0.00% | BW10: 0 | BX10: 0 | BY10: 0 | BZ10: 0 | CA10: 0 | CB10: 0 | CC10: 0 | CD10: 0.00% | CE10: 0.00% | CF10: 0 | CG10: 0 | CH10: 0 | CI10: 0 | CJ10: 0.00% | CK10: 0.00% | CL10: 0.00% | CM10: 0.00% | CN10: 0.00% | CO10: 0.00% | CP10: 0 | CQ10: 0.00% | CR10: 0 | CS10: 0.00% | CT10: 0 | CU10: 0.00% | CV10: 0.00% | CW10: 0 | CX10: 0.00% | CY10: 0 | CZ10: 0.00% | DA10: 0 | DB10: 0.00% | DC10: 0.00% | DD10: 0.00% | DE10: 0.00%
A11: 2025-12-10 | B11: R0007EU | C11: B0FNMBQFBC | D11: B0FNMBQFBC | E11: R0007EU | F11: HYCHIKA-AP100A-空净 | G11: 0 | H11: 64.99 | I11: 0 | J11: 0 | K11: 0 | L11: 0 | M11: 0 | N11: 0 | O11: 0 | P11: 0 | Q11: 0 | R11: 0 | S11: 0 | T11: 0.00% | U11: 0.00% | V11: 0.00% | W11: 0.00% | X11: 0.00% | Y11: 0.00% | Z11: 0 | AA11: 0 | AB11: 0 | AC11: 0 | AD11: 0 | AE11: 0 | AF11: 0 | AG11: 0 | AH11: 0 | AI11: 0 | AJ11: 0 | AK11: 0 | AN11: 0 | AO11: 0 | AP11: 0.00% | AQ11: 0 | AR11: 0 | AS11: 0.00% | AT11: ** | AU11: ** | AV11: ** | AW11: ** | AX11: ** | AY11: 0 | AZ11: 0.00% | BA11: 0 | BB11: 0.00% | BC11: 0 | BD11: 0.00% | BE11: 0 | BF11: 0 | BG11: 0 | BH11: 0 | BI11: 0.00% | BJ11: 0.00% | BK11: 0.00% | BL11: 0 | BM11: 0.00% | BN11: 0 | BO11: 0 | BP11: 0 | BQ11: 0 | BR11: 0 | BS11: 0 | BT11: 0.00% | BU11: 0.00% | BV11: 0.00% | BW11: 0 | BX11: 0 | BY11: 0 | BZ11: 0 | CA11: 0 | CB11: 0 | CC11: 0 | CD11: 0.00% | CE11: 0.00% | CF11: 0 | CG11: 0 | CH11: 0 | CI11: 0 | CJ11: 0.00% | CK11: 0.00% | CL11: 0.00% | CM11: 0.00% | CN11: 0.00% | CO11: 0.00% | CP11: 0 | CQ11: 0.00% | CR11: 0 | CS11: 0.00% | CT11: 0 | CU11: 0.00% | CV11: 0.00% | CW11: 0 | CX11: 0.00% | CY11: 0 | CZ11: 0.00% | DA11: 0 | DB11: 0.00% | DC11: 0.00% | DD11: 0.00% | DE11: 0.00%
A12: 2025-12-11 | B12: R0007EU | C12: B0FNMBQFBC | D12: B0FNMBQFBC | E12: R0007EU | F12: HYCHIKA-AP100A-空净 | G12: 0 | H12: 64.99 | I12: 0 | J12: 0 | K12: 0 | L12: 0 | M12: 0 | N12: 0 | O12: 0 | P12: 0 | Q12: 0 | R12: 0 | S12: 0 | T12: 0.00% | U12: 0.00% | V12: 0.00% | W12: 0.00% | X12: 0.00% | Y12: 0.00% | Z12: 0 | AA12: 0 | AB12: 0 | AC12: 0 | AD12: 0 | AE12: 0 | AF12: 0 | AG12: 0 | AH12: 0 | AI12: 0 | AJ12: 0 | AK12: 0 | AN12: 0 | AO12: 0 | AP12: 0.00% | AQ12: 0 | AR12: 0 | AS12: 0.00% | AT12: ** | AU12: ** | AV12: ** | AW12: ** | AX12: ** | AY12: 0 | AZ12: 0.00% | BA12: 0 | BB12: 0.00% | BC12: 0 | BD12: 0.00% | BE12: 0 | BF12: 0 | BG12: 0 | BH12: 0 | BI12: 0.00% | BJ12: 0.00% | BK12: 0.00% | BL12: 0 | BM12: 0.00% | BN12: 0 | BO12: 0 | BP12: 0 | BQ12: 0 | BR12: 0 | BS12: 0 | BT12: 0.00% | BU12: 0.00% | BV12: 0.00% | BW12: 0 | BX12: 0 | BY12: 0 | BZ12: 0 | CA12: 0 | CB12: 0 | CC12: 0 | CD12: 0.00% | CE12: 0.00% | CF12: 0 | CG12: 0 | CH12: 0 | CI12: 0 | CJ12: 0.00% | CK12: 0.00% | CL12: 0.00% | CM12: 0.00% | CN12: 0.00% | CO12: 0.00% | CP12: 0 | CQ12: 0.00% | CR12: 0 | CS12: 0.00% | CT12: 0 | CU12: 0.00% | CV12: 0.00% | CW12: 0 | CX12: 0.00% | CY12: 0 | CZ12: 0.00% | DA12: 0 | DB12: 0.00% | DC12: 0.00% | DD12: 0.00% | DE12: 0.00%
A13: 2025-12-12 | B13: R0007EU | C13: B0FNMBQFBC | D13: B0FNMBQFBC | E13: R0007EU | F13: HYCHIKA-AP100A-空净 | G13: 0 | H13: 64.99 | I13: 0 | J13: 0 | K13: 0 | L13: 0 | M13: 0 | N13: 0 | O13: 0 | P13: 0 | Q13: 0 | R13: 0 | S13: 0 | T13: 0.00% | U13: 0.00% | V13: 0.00% | W13: 0.00% | X13: 0.00% | Y13: 0.00% | Z13: 0 | AA13: 0 | AB13: 0 | AC13: 0 | AD13: 0 | AE13: 0 | AF13: 0 | AG13: 0 | AH13: 0 | AI13: 0 | AJ13: 0 | AK13: 0 | AN13: 0 | AO13: 0 | AP13: 0.00% | AQ13: 0 | AR13: 0 | AS13: 0.00% | AT13: ** | AU13: ** | AV13: ** | AW13: ** | AX13: ** | AY13: 0 | AZ13: 0.00% | BA13: 0 | BB13: 0.00% | BC13: 0 | BD13: 0.00% | BE13: 0 | BF13: 0 | BG13: 0 | BH13: 0 | BI13: 0.00% | BJ13: 0.00% | BK13: 0.00% | BL13: 0 | BM13: 0.00% | BN13: 0 | BO13: 0 | BP13: 0 | BQ13: 0 | BR13: 0 | BS13: 0 | BT13: 0.00% | BU13: 0.00% | BV13: 0.00% | BW13: 0 | BX13: 0 | BY13: 0 | BZ13: 0 | CA13: 0 | CB13: 0 | CC13: 0 | CD13: 0.00% | CE13: 0.00% | CF13: 0 | CG13: 0 | CH13: 0 | CI13: 0 | CJ13: 0.00% | CK13: 0.00% | CL13: 0.00% | CM13: 0.00% | CN13: 0.00% | CO13: 0.00% | CP13: 0 | CQ13: 0.00% | CR13: 0 | CS13: 0.00% | CT13: 0 | CU13: 0.00% | CV13: 0.00% | CW13: 0 | CX13: 0.00% | CY13: 0 | CZ13: 0.00% | DA13: 0 | DB13: 0.00% | DC13: 0.00% | DD13: 0.00% | DE13: 0.00%
... A23: 2025-12-22 | B23: R0007EU | C23: B0FNMBQFBC | D23: B0FNMBQFBC | E23: R0007EU | F23: HYCHIKA-AP100A-空净 | G23: 54.99 | H23: 54.99 | I23: 198 | J23: 0 | K23: 0 | L23: 0 | M23: 0 | N23: 0 | O23: 198 | P23: 0 | Q23: 0 | R23: 0 | S23: 0 | T23: 0.00% | U23: 0.00% | V23: 0.00% | W23: 0.00% | X23: 0.00% | Y23: 0.00% | Z23: 0 | AA23: 0 | AB23: 0 | AC23: 0 | AD23: 0 | AE23: 0 | AF23: 0 | AG23: 0 | AH23: 0 | AI23: 0 | AJ23: 0 | AK23: 0 | AN23: 0 | AO23: 0 | AP23: 0.00% | AQ23: 0 | AR23: 0 | AS23: 0.00% | AT23: ** | AU23: ** | AV23: ** | AW23: ** | AX23: ** | AY23: 0 | AZ23: 0.00% | BA23: 3 | BB23: 0.41% | BC23: 3 | BD23: 0.00% | BE23: 6 | BF23: 12 | BG23: 6 | BH23: 18 | BI23: 0.00% | BJ23: 0.00% | BK23: 94.00% | BL23: 0 | BM23: 0.00% | BN23: 0 | BO23: 0 | BP23: 0 | BQ23: 0 | BR23: 0 | BS23: 0 | BT23: 0.00% | BU23: 0.00% | BV23: 0.00% | BW23: 0 | BX23: 0 | BY23: 0 | BZ23: 0 | CA23: 0 | CB23: 0 | CC23: 0 | CD23: 0.00% | CE23: 0.00% | CF23: 0 | CG23: 0 | CH23: 0 | CI23: 6 | CJ23: 0.00% | CK23: 0.00% | CL23: 0.00% | CM23: 0.60% | CN23: 0.00% | CO23: 1.00% | CP23: 0 | CQ23: 0.00% | CR23: 0 | CS23: 0.00% | CT23: 0 | CU23: 0.00% | CV23: 0.00% | CW23: 0 | CX23: 0.00% | CY23: 0 | CZ23: 0.00% | DA23: 0 | DB23: 0.00% | DC23: 0.00% | DD23: 0.00% | DE23: 0.00%
A24: 2025-12-23 | B24: R0007EU | C24: B0FNMBQFBC | D24: B0FNMBQFBC | E24: R0007EU | F24: HYCHIKA-AP100A-空净 | G24: 54.99 | H24: 54.99 | I24: 192 | J24: 0 | K24: 0 | L24: 0 | M24: 0 | N24: 0 | O24: 192 | P24: 1 | Q24: 54.99 | R24: 1 | S24: 54.99 | T24: 0.00% | U24: 100.00% | V24: 0.00% | W24: 0.00% | X24: 100.00% | Y24: 0.00% | Z24: 0 | AA24: 0 | AB24: 0 | AC24: 0 | AD24: 0 | AE24: 0 | AF24: 0 | AG24: 0 | AH24: 1 | AI24: 54.99 | AJ24: 1 | AK24: 54.99 | AL24: Casa e cucina：149617 | AM24: Purificatori d'aria：180 | AN24: 0 | AO24: 0 | AP24: 0.00% | AQ24: 0 | AR24: 0 | AS24: 0.00% | AT24: ** | AU24: ** | AV24: ** | AW24: ** | AX24: ** | AY24: 0 | AZ24: 0.00% | BA24: 0 | BB24: 0.00% | BC24: 0 | BD24: 0.00% | BE24: 0 | BF24: 0 | BG24: 0 | BH24: 0 | BI24: 0.00% | BJ24: 0.00% | BK24: 0.00% | BL24: 0 | BM24: 0.00% | BN24: 0 | BO24: 0 | BP24: 0 | BQ24: 0 | BR24: 0 | BS24: 0 | BT24: 0.00% | BU24: 0.00% | BV24: 0.00% | BW24: 0 | BX24: 0 | BY24: 0 | BZ24: 0 | CA24: 0 | CB24: 0 | CC24: 0 | CD24: 0.00% | CE24: 0.00% | CF24: 0 | CG24: 0 | CH24: 1 | CI24: 0 | CJ24: 100.00% | CK24: 0.00% | CL24: 0.00% | CM24: 0.00% | CN24: 0.00% | CO24: 0.00% | CP24: 0 | CQ24: 0.00% | CR24: 0 | CS24: 0.00% | CT24: 0 | CU24: 0.00% | CV24: 0.00% | CW24: 0 | CX24: 0.00% | CY24: 0 | CZ24: 0.00% | DA24: 0 | DB24: 0.00% | DC24: 0.00% | DD24: 0.00% | DE24: 0.00%
A25: 2025-12-24 | B25: R0007EU | C25: B0FNMBQFBC | D25: B0FNMBQFBC | E25: R0007EU | F25: HYCHIKA-AP100A-空净 | G25: 54.99 | H25: 54.99 | I25: 193 | J25: 0 | K25: 0 | L25: 0 | M25: 0 | N25: 0 | O25: 193 | P25: 0 | Q25: 0 | R25: 0 | S25: 0 | T25: 0.00% | U25: 0.00% | V25: 0.00% | W25: 0.00% | X25: 0.00% | Y25: 0.00% | Z25: 0 | AA25: 0 | AB25: 0 | AC25: 0 | AD25: 0 | AE25: 0 | AF25: 0 | AG25: 0 | AH25: 0 | AI25: 0 | AJ25: 0 | AK25: 0 | AL25: Casa e cucina：149617 | AM25: Purificatori d'aria：180 | AN25: 0 | AO25: 0 | AP25: 0.00% | AQ25: 0 | AR25: 0 | AS25: 0.00% | AT25: ** | AU25: ** | AV25: ** | AW25: ** | AX25: ** | AY25: 0 | AZ25: 0.00% | BA25: 0 | BB25: 0.00% | BC25: 0 | BD25: 0.00% | BE25: 0 | BF25: 0 | BG25: 0 | BH25: 0 | BI25: 0.00% | BJ25: 0.00% | BK25: 0.00% | BL25: 0 | BM25: 0.00% | BN25: 0 | BO25: 0 | BP25: 0 | BQ25: 0 | BR25: 0 | BS25: 0 | BT25: 0.00% | BU25: 0.00% | BV25: 0.00% | BW25: 0 | BX25: 0 | BY25: 0 | BZ25: 0 | CA25: 0 | CB25: 0 | CC25: 0 | CD25: 0.00% | CE25: 0.00% | CF25: 0 | CG25: 0 | CH25: 0 | CI25: 0 | CJ25: 0.00% | CK25: 0.00% | CL25: 0.00% | CM25: 0.00% | CN25: 0.00% | CO25: 0.00% | CP25: 0 | CQ25: 0.00% | CR25: 0 | CS25: 0.00% | CT25: 0 | CU25: 0.00% | CV25: 0.00% | CW25: 0 | CX25: 0.00% | CY25: 0 | CZ25: 0.00% | DA25: 0 | DB25: 0.00% | DC25: 0.00% | DD25: 0.00% | DE25: 0.00%
A26: 2025-12-24 | B26: R0007EU | C26: B0FNMBQFBC | D26: B0FNMBQFBC | E26: R0007EU | F26: HYCHIKA-AP100A-空净 | G26: 54.99 | H26: 54.99 | I26: 193 | J26: 0 | K26: 0 | L26: 0 | M26: 0 | N26: 0 | O26: 193 | P26: 0 | Q26: 0 | R26: 0 | S26: 0 | T26: 0.00% | U26: 0.00% | V26: 0.00% | W26: 0.00% | X26: 0.00% | Y26: 0.00% | Z26: 0 | AA26: 0 | AB26: 0 | AC26: 0 | AD26: 0 | AE26: 0 | AF26: 0 | AG26: 0 | AH26: 0 | AI26: 0 | AJ26: 0 | AK26: 0 | AL26: Casa e cucina：149617 | AM26: Purificatori d'aria：180 | AN26: 0 | AO26: 0 | AP26: 0.00% | AQ26: 0 | AR26: 0 | AS26: 0.00% | AT26: ** | AU26: ** | AV26: ** | AW26: ** | AX26: ** | AY26: 0 | AZ26: 0.00% | BA26: 0 | BB26: 0.00% | BC26: 0 | BD26: 0.00% | BE26: 0 | BF26: 0 | BG26: 0 | BH26: 0 | BI26: 0.00% | BJ26: 0.00% | BK26: 0.00% | BL26: 0 | BM26: 0.00% | BN26: 0 | BO26: 0 | BP26: 0 | BQ26: 0 | BR26: 0 | BS26: 0 | BT26: 0.00% | BU26: 0.00% | BV26: 0.00% | BW26: 0 | BX26: 0 | BY26: 0 | BZ26: 0 | CA26: 0 | CB26: 0 | CC26: 0 | CD26: 0.00% | CE26: 0.00% | CF26: 0 | CG26: 0 | CH26: 0 | CI26: 0 | CJ26: 0.00% | CK26: 0.00% | CL26: 0.00% | CM26: 0.00% | CN26: 0.00% | CO26: 0.00% | CP26: 0 | CQ26: 0.00% | CR26: 0 | CS26: 0.00% | CT26: 0 | CU26: 0.00% | CV26: 0.00% | CW26: 0 | CX26: 0.00% | CY26: 0 | CZ26: 0.00% | DA26: 0 | DB26: 0.00% | DC26: 0.00% | DD26: 0.00% | DE26: 0.00%

Sheet 西班牙ERP数据
A1: 时间 | B1: SKU | C1: 父ASIN | D1: ASIN | E1: MSKU | F1: 品名 | G1: 售价(总价) | H1: 价格 | I1: FBA-可售 | J1: FBM可售 | K1: AWD在库 | L1: AWD可用量 | M1: AWD待发货量 | N1: AWD标发在途 | O1: 可用库存 | P1: 销量 | Q1: 销售额 | R1: 订单量 | S1: 净销售额 | T1: 销量环比 | U1: 销售额环比 | V1: 订单量环比 | W1: 销量同比 | X1: 订单量同比 | Y1: 销量额同比 | Z1: B2B 销量 | AA1: B2B 销售额 | AB1: B2B 订单量 | AC1: FBM买家运费 | AD1: 促销销量 | AE1: 促销销售额 | AF1: 促销订单量 | AG1: 促销折扣 | AH1: 日均销量 | AI1: 日均销售额 | AJ1: 日均订单量 | AK1: 销售均价 | AL1: 大类排名 | AM1: 小类排名 | AN1: 退款量 | AO1: 退款金额 | AP1: 退款率 | AQ1: 评分 | AR1: 评论数 | AS1: 留评率 | AT1: 结算毛利润 | AU1: 订单毛利润 | AV1: 结算毛利率 | AW1: 订单毛利率 | AX1: ROI | AY1: 退货量 | AZ1: 退货率 | BA1: Sessions-Browser | BB1: Sessions-Browser-Percentage | BC1: Sessions-Mobile | BD1: Sessions-Mobile-Percentage | BE1: Sessions-Total | BF1: PV-Browser | BG1: PV-Mobile | BH1: PV-Total | BI1: CVR | BJ1: 销量CVR | BK1: Buybox赢得率 | BL1: CPC | BM1: CTR | BN1: 广告花费 | BO1: SB广告费 | BP1: SBV广告费 | BQ1: SD广告费 | BR1: SP广告费 | BS1: ROAS | BT1: ACOS | BU1: ACoAS | BV1: ASoAS | BW1: CPO | BX1: CPU | BY1: CPM | BZ1: 广告销售额 | CA1: 广告订单量 | CB1: 直接成交订单量 | CC1: 直接成交销售额 | CD1: 广告订单占比 | CE1: 广告CVR | CF1: 展示 | CG1: 点击 | CH1: 自然订单量 | CI1: 自然点击量 | CJ1: 自然CVR | CK1: Sessions-Percentage | CL1: Unit-Sessions-Percentage | CM1: PV-Browser-Percentage | CN1: PV-Mobile-Percentage | CO1: PV-Percentage | CP1: Sessions-Browser(B2B) | CQ1: Sessions-Browser-Percentage(B2B) | CR1: Sessions-Mobile(B2B) | CS1: Sessions-Mobile-Percentage(B2B) | CT1: Sessions-Total(B2B) | CU1: Sessions-Percentage(B2B) | CV1: Unit-Sessions-Percentage(B2B) | CW1: PV-Browser(B2B) | CX1: PV-Browser-Percentage(B2B) | CY1: PV-Mobile(B2B) | CZ1: PV-Mobile-Percentage(B2B) | DA1: PV-Total(B2B) | DB1: PV-Percentage(B2B) | DC1: CVR(B2B) | DD1: 销量CVR(B2B) | DE1: Buybox赢得率(B2B) | DF1: 运营日志
A2: 2025-12-01 | B2: R0007EU | C2: B0FNMBQFBC | D2: B0FNMBQFBC | E2: R00007EU,R0007EU | F2: HYCHIKA-AP100A-空净 | G2: 0 | H2: 0 | I2: 0 | J2: 0 | K2: 0 | L2: 0 | M2: 0 | N2: 0 | O2: 0 | P2: 0 | Q2: 0 | R2: 0 | S2: 0 | T2: 0.00% | U2: 0.00% | V2: 0.00% | W2: 0.00% | X2: 0.00% | Y2: 0.00% | Z2: 0 | AA2: 0 | AB2: 0 | AC2: 0 | AD2: 0 | AE2: 0 | AF2: 0 | AG2: 0 | AH2: 0 | AI2: 0 | AJ2: 0 | AK2: 0 | AN2: 0 | AO2: 0 | AP2: 0.00% | AQ2: 0 | AR2: 0 | AS2: 0.00% | AT2: ** | AU2: ** | AV2: ** | AW2: ** | AX2: ** | AY2: 0 | AZ2: 0.00% | BA2: 0 | BB2: 0.00% | BC2: 0 | BD2: 0.00% | BE2: 0 | BF2: 0 | BG2: 0 | BH2: 0 | BI2: 0.00% | BJ2: 0.00% | BK2: 0.00% | BL2: 0 | BM2: 0.00% | BN2: 0 | BO2: 0 | BP2: 0 | BQ2: 0 | BR2: 0 | BS2: 0 | BT2: 0.00% | BU2: 0.00% | BV2: 0.00% | BW2: 0 | BX2: 0 | BY2: 0 | BZ2: 0 | CA2: 0 | CB2: 0 | CC2: 0 | CD2: 0.00% | CE2: 0.00% | CF2: 0 | CG2: 0 | CH2: 0 | CI2: 0 | CJ2: 0.00% | CK2: 0.00% | CL2: 0.00% | CM2: 0.00% | CN2: 0.00% | CO2: 0.00% | CP2: 0 | CQ2: 0.00% | CR2: 0 | CS2: 0.00% | CT2: 0 | CU2: 0.00% | CV2: 0.00% | CW2: 0 | CX2: 0.00% | CY2: 0 | CZ2: 0.00% | DA2: 0 | DB2: 0.00% | DC2: 0.00% | DD2: 0.00% | DE2: 0.00%
A3: 2025-12-02 | B3: R0007EU | C3: B0FNMBQFBC | D3: B0FNMBQFBC | E3: R00007EU,R0007EU | F3: HYCHIKA-AP100A-空净 | G3: 0 | H3: 0 | I3: 0 | J3: 0 | K3: 0 | L3: 0 | M3: 0 | N3: 0 | O3: 0 | P3: 0 | Q3: 0 | R3: 0 | S3: 0 | T3: 0.00% | U3: 0.00% | V3: 0.00% | W3: 0.00% | X3: 0.00% | Y3: 0.00% | Z3: 0 | AA3: 0 | AB3: 0 | AC3: 0 | AD3: 0 | AE3: 0 | AF3: 0 | AG3: 0 | AH3: 0 | AI3: 0 | AJ3: 0 | AK3: 0 | AN3: 0 | AO3: 0 | AP3: 0.00% | AQ3: 0 | AR3: 0 | AS3: 0.00% | AT3: ** | AU3: ** | AV3: ** | AW3: ** | AX3: ** | AY3: 0 | AZ3: 0.00% | BA3: 0 | BB3: 0.00% | BC3: 0 | BD3: 0.00% | BE3: 0 | BF3: 0 | BG3: 0 | BH3: 0 | BI3: 0.00% | BJ3: 0.00% | BK3: 0.00% | BL3: 0 | BM3: 0.00% | BN3: 0 | BO3: 0 | BP3: 0 | BQ3: 0 | BR3: 0 | BS3: 0 | BT3: 0.00% | BU3: 0.00% | BV3: 0.00% | BW3: 0 | BX3: 0 | BY3: 0 | BZ3: 0 | CA3: 0 | CB3: 0 | CC3: 0 | CD3: 0.00% | CE3: 0.00% | CF3: 0 | CG3: 0 | CH3: 0 | CI3: 0 | CJ3: 0.00% | CK3: 0.00% | CL3: 0.00% | CM3: 0.00% | CN3: 0.00% | CO3: 0.00% | CP3: 0 | CQ3: 0.00% | CR3: 0 | CS3: 0.00% | CT3: 0 | CU3: 0.00% | CV3: 0.00% | CW3: 0 | CX3: 0.00% | CY3: 0 | CZ3: 0.00% | DA3: 0 | DB3: 0.00% | DC3: 0.00% | DD3: 0.00% | DE3: 0.00%
A4: 2025-12-03 | B4: R0007EU | C4: B0FNMBQFBC | D4: B0FNMBQFBC | E4: R00007EU,R0007EU | F4: HYCHIKA-AP100A-空净 | G4: 0 | H4: 0 | I4: 0 | J4: 0 | K4: 0 | L4: 0 | M4: 0 | N4: 0 | O4: 0 | P4: 0 | Q4: 0 | R4: 0 | S4: 0 | T4: 0.00% | U4: 0.00% | V4: 0.00% | W4: 0.00% | X4: 0.00% | Y4: 0.00% | Z4: 0 | AA4: 0 | AB4: 0 | AC4: 0 | AD4: 0 | AE4: 0 | AF4: 0 | AG4: 0 | AH4: 0 | AI4: 0 | AJ4: 0 | AK4: 0 | AN4: 0 | AO4: 0 | AP4: 0.00% | AQ4: 0 | AR4: 0 | AS4: 0.00% | AT4: ** | AU4: ** | AV4: ** | AW4: ** | AX4: ** | AY4: 0 | AZ4: 0.00% | BA4: 0 | BB4: 0.00% | BC4: 0 | BD4: 0.00% | BE4: 0 | BF4: 0 | BG4: 0 | BH4: 0 | BI4: 0.00% | BJ4: 0.00% | BK4: 0.00% | BL4: 0 | BM4: 0.00% | BN4: 0 | BO4: 0 | BP4: 0 | BQ4: 0 | BR4: 0 | BS4: 0 | BT4: 0.00% | BU4: 0.00% | BV4: 0.00% | BW4: 0 | BX4: 0 | BY4: 0 | BZ4: 0 | CA4: 0 | CB4: 0 | CC4: 0 | CD4: 0.00% | CE4: 0.00% | CF4: 0 | CG4: 0 | CH4: 0 | CI4: 0 | CJ4: 0.00% | CK4: 0.00% | CL4: 0.00% | CM4: 0.00% | CN4: 0.00% | CO4: 0.00% | CP4: 0 | CQ4: 0.00% | CR4: 0 | CS4: 0.00% | CT4: 0 | CU4: 0.00% | CV4: 0.00% | CW4: 0 | CX4: 0.00% | CY4: 0 | CZ4: 0.00% | DA4: 0 | DB4: 0.00% | DC4: 0.00% | DD4: 0.00% | DE4: 0.00%
A5: 2025-12-04 | B5: R0007EU | C5: B0FNMBQFBC | D5: B0FNMBQFBC | E5: R00007EU,R0007EU | F5: HYCHIKA-AP100A-空净 | G5: 0 | H5: 0 | I5: 0 | J5: 0 | K5: 0 | L5: 0 | M5: 0 | N5: 0 | O5: 0 | P5: 0 | Q5: 0 | R5: 0 | S5: 0 | T5: 0.00% | U5: 0.00% | V5: 0.00% | W5: 0.00% | X5: 0.00% | Y5: 0.00% | Z5: 0 | AA5: 0 | AB5: 0 | AC5: 0 | AD5: 0 | AE5: 0 | AF5: 0 | AG5: 0 | AH5: 0 | AI5: 0 | AJ5: 0 | AK5: 0 | AN5: 0 | AO5: 0 | AP5: 0.00% | AQ5: 0 | AR5: 0 | AS5: 0.00% | AT5: ** | AU5: ** | AV5: ** | AW5: ** | AX5: ** | AY5: 0 | AZ5: 0.00% | BA5: 0 | BB5: 0.00% | BC5: 0 | BD5: 0.00% | BE5: 0 | BF5: 0 | BG5: 0 | BH5: 0 | BI5: 0.00% | BJ5: 0.00% | BK5: 0.00% | BL5: 0 | BM5: 0.00% | BN5: 0 | BO5: 0 | BP5: 0 | BQ5: 0 | BR5: 0 | BS5: 0 | BT5: 0.00% | BU5: 0.00% | BV5: 0.00% | BW5: 0 | BX5: 0 | BY5: 0 | BZ5: 0 | CA5: 0 | CB5: 0 | CC5: 0 | CD5: 0.00% | CE5: 0.00% | CF5: 0 | CG5: 0 | CH5: 0 | CI5: 0 | CJ5: 0.00% | CK5: 0.00% | CL5: 0.00% | CM5: 0.00% | CN5: 0.00% | CO5: 0.00% | CP5: 0 | CQ5: 0.00% | CR5: 0 | CS5: 0.00% | CT5: 0 | CU5: 0.00% | CV5: 0.00% | CW5: 0 | CX5: 0.00% | CY5: 0 | CZ5: 0.00% | DA5: 0 | DB5: 0.00% | DC5: 0.00% | DD5: 0.00% | DE5: 0.00%
A6: 2025-12-05 | B6: R0007EU | C6: B0FNMBQFBC | D6: B0FNMBQFBC | E6: R00007EU,R0007EU | F6: HYCHIKA-AP100A-空净 | G6: 0 | H6: 0 | I6: 0 | J6: 0 | K6: 0 | L6: 0 | M6: 0 | N6: 0 | O6: 0 | P6: 0 | Q6: 0 | R6: 0 | S6: 0 | T6: 0.00% | U6: 0.00% | V6: 0.00% | W6: 0.00% | X6: 0.00% | Y6: 0.00% | Z6: 0 | AA6: 0 | AB6: 0 | AC6: 0 | AD6: 0 | AE6: 0 | AF6: 0 | AG6: 0 | AH6: 0 | AI6: 0 | AJ6: 0 | AK6: 0 | AN6: 0 | AO6: 0 | AP6: 0.00% | AQ6: 0 | AR6: 0 | AS6: 0.00% | AT6: ** | AU6: ** | AV6: ** | AW6: ** | AX6: ** | AY6: 0 | AZ6: 0.00% | BA6: 0 | BB6: 0.00% | BC6: 0 | BD6: 0.00% | BE6: 0 | BF6: 0 | BG6: 0 | BH6: 0 | BI6: 0.00% | BJ6: 0.00% | BK6: 0.00% | BL6: 0 | BM6: 0.00% | BN6: 0 | BO6: 0 | BP6: 0 | BQ6: 0 | BR6: 0 | BS6: 0 | BT6: 0.00% | BU6: 0.00% | BV6: 0.00% | BW6: 0 | BX6: 0 | BY6: 0 | BZ6: 0 | CA6: 0 | CB6: 0 | CC6: 0 | CD6: 0.00% | CE6: 0.00% | CF6: 0 | CG6: 0 | CH6: 0 | CI6: 0 | CJ6: 0.00% | CK6: 0.00% | CL6: 0.00% | CM6: 0.00% | CN6: 0.00% | CO6: 0.00% | CP6: 0 | CQ6: 0.00% | CR6: 0 | CS6: 0.00% | CT6: 0 | CU6: 0.00% | CV6: 0.00% | CW6: 0 | CX6: 0.00% | CY6: 0 | CZ6: 0.00% | DA6: 0 | DB6: 0.00% | DC6: 0.00% | DD6: 0.00% | DE6: 0.00%
A7: 2025-12-06 | B7: R0007EU | C7: B0FNMBQFBC | D7: B0FNMBQFBC | E7: R00007EU,R0007EU | F7: HYCHIKA-AP100A-空净 | G7: 0 | H7: 0 | I7: 0 | J7: 0 | K7: 0 | L7: 0 | M7: 0 | N7: 0 | O7: 0 | P7: 0 | Q7: 0 | R7: 0 | S7: 0 | T7: 0.00% | U7: 0.00% | V7: 0.00% | W7: 0.00% | X7: 0.00% | Y7: 0.00% | Z7: 0 | AA7: 0 | AB7: 0 | AC7: 0 | AD7: 0 | AE7: 0 | AF7: 0 | AG7: 0 | AH7: 0 | AI7: 0 | AJ7: 0 | AK7: 0 | AN7: 0 | AO7: 0 | AP7: 0.00% | AQ7: 0 | AR7: 0 | AS7: 0.00% | AT7: ** | AU7: ** | AV7: ** | AW7: ** | AX7: ** | AY7: 0 | AZ7: 0.00% | BA7: 0 | BB7: 0.00% | BC7: 0 | BD7: 0.00% | BE7: 0 | BF7: 0 | BG7: 0 | BH7: 0 | BI7: 0.00% | BJ7: 0.00% | BK7: 0.00% | BL7: 0 | BM7: 0.00% | BN7: 0 | BO7: 0 | BP7: 0 | BQ7: 0 | BR7: 0 | BS7: 0 | BT7: 0.00% | BU7: 0.00% | BV7: 0.00% | BW7: 0 | BX7: 0 | BY7: 0 | BZ7: 0 | CA7: 0 | CB7: 0 | CC7: 0 | CD7: 0.00% | CE7: 0.00% | CF7: 0 | CG7: 0 | CH7: 0 | CI7: 0 | CJ7: 0.00% | CK7: 0.00% | CL7: 0.00% | CM7: 0.00% | CN7: 0.00% | CO7: 0.00% | CP7: 0 | CQ7: 0.00% | CR7: 0 | CS7: 0.00% | CT7: 0 | CU7: 0.00% | CV7: 0.00% | CW7: 0 | CX7: 0.00% | CY7: 0 | CZ7: 0.00% | DA7: 0 | DB7: 0.00% | DC7: 0.00% | DD7: 0.00% | DE7: 0.00%
A8: 2025-12-07 | B8: R0007EU | C8: B0FNMBQFBC | D8: B0FNMBQFBC | E8: R00007EU,R0007EU | F8: HYCHIKA-AP100A-空净 | G8: 0 | H8: 0 | I8: 0 | J8: 0 | K8: 0 | L8: 0 | M8: 0 | N8: 0 | O8: 0 | P8: 0 | Q8: 0 | R8: 0 | S8: 0 | T8: 0.00% | U8: 0.00% | V8: 0.00% | W8: 0.00% | X8: 0.00% | Y8: 0.00% | Z8: 0 | AA8: 0 | AB8: 0 | AC8: 0 | AD8: 0 | AE8: 0 | AF8: 0 | AG8: 0 | AH8: 0 | AI8: 0 | AJ8: 0 | AK8: 0 | AN8: 0 | AO8: 0 | AP8: 0.00% | AQ8: 0 | AR8: 0 | AS8: 0.00% | AT8: ** | AU8: ** | AV8: ** | AW8: ** | AX8: ** | AY8: 0 | AZ8: 0.00% | BA8: 0 | BB8: 0.00% | BC8: 0 | BD8: 0.00% | BE8: 0 | BF8: 0 | BG8: 0 | BH8: 0 | BI8: 0.00% | BJ8: 0.00% | BK8: 0.00% | BL8: 0 | BM8: 0.00% | BN8: 0 | BO8: 0 | BP8: 0 | BQ8: 0 | BR8: 0 | BS8: 0 | BT8: 0.00% | BU8: 0.00% | BV8: 0.00% | BW8: 0 | BX8: 0 | BY8: 0 | BZ8: 0 | CA8: 0 | CB8: 0 | CC8: 0 | CD8: 0.00% | CE8: 0.00% | CF8: 0 | CG8: 0 | CH8: 0 | CI8: 0 | CJ8: 0.00% | CK8: 0.00% | CL8: 0.00% | CM8: 0.00% | CN8: 0.00% | CO8: 0.00% | CP8: 0 | CQ8: 0.00% | CR8: 0 | CS8: 0.00% | CT8: 0 | CU8: 0.00% | CV8: 0.00% | CW8: 0 | CX8: 0.00% | CY8: 0 | CZ8: 0.00% | DA8: 0 | DB8: 0.00% | DC8: 0.00% | DD8: 0.00% | DE8: 0.00%
A9: 2025-12-08 | B9: R0007EU | C9: B0FNMBQFBC | D9: B0FNMBQFBC | E9: R00007EU,R0007EU | F9: HYCHIKA-AP100A-空净 | G9: 0 | H9: 0 | I9: 0 | J9: 0 | K9: 0 | L9: 0 | M9: 0 | N9: 0 | O9: 0 | P9: 0 | Q9: 0 | R9: 0 | S9: 0 | T9: 0.00% | U9: 0.00% | V9: 0.00% | W9: 0.00% | X9: 0.00% | Y9: 0.00% | Z9: 0 | AA9: 0 | AB9: 0 | AC9: 0 | AD9: 0 | AE9: 0 | AF9: 0 | AG9: 0 | AH9: 0 | AI9: 0 | AJ9: 0 | AK9: 0 | AN9: 0 | AO9: 0 | AP9: 0.00% | AQ9: 0 | AR9: 0 | AS9: 0.00% | AT9: ** | AU9: ** | AV9: ** | AW9: ** | AX9: ** | AY9: 0 | AZ9: 0.00% | BA9: 0 | BB9: 0.00% | BC9: 0 | BD9: 0.00% | BE9: 0 | BF9: 0 | BG9: 0 | BH9: 0 | BI9: 0.00% | BJ9: 0.00% | BK9: 0.00% | BL9: 0 | BM9: 0.00% | BN9: 0 | BO9: 0 | BP9: 0 | BQ9: 0 | BR9: 0 | BS9: 0 | BT9: 0.00% | BU9: 0.00% | BV9: 0.00% | BW9: 0 | BX9: 0 | BY9: 0 | BZ9: 0 | CA9: 0 | CB9: 0 | CC9: 0 | CD9: 0.00% | CE9: 0.00% | CF9: 0 | CG9: 0 | CH9: 0 | CI9: 0 | CJ9: 0.00% | CK9: 0.00% | CL9: 0.00% | CM9: 0.00% | CN9: 0.00% | CO9: 0.00% | CP9: 0 | CQ9: 0.00% | CR9: 0 | CS9: 0.00% | CT9: 0 | CU9: 0.00% | CV9: 0.00% | CW9: 0 | CX9: 0.00% | CY9: 0 | CZ9: 0.00% | DA9: 0 | DB9: 0.00% | DC9: 0.00% | DD9: 0.00% | DE9: 0.00%
A10: 2025-12-09 | B10: R0007EU | C10: B0FNMBQFBC | D10: B0FNMBQFBC | E10: R00007EU,R0007EU | F10: HYCHIKA-AP100A-空净 | G10: 0 | H10: 0 | I10: 0 | J10: 0 | K10: 0 | L10: 0 | M10: 0 | N10: 0 | O10: 0 | P10: 0 | Q10: 0 | R10: 0 | S10: 0 | T10: 0.00% | U10: 0.00% | V10: 0.00% | W10: 0.00% | X10: 0.00% | Y10: 0.00% | Z10: 0 | AA10: 0 | AB10: 0 | AC10: 0 | AD10: 0 | AE10: 0 | AF10: 0 | AG10: 0 | AH10: 0 | AI10: 0 | AJ10: 0 | AK10: 0 | AN10: 0 | AO10: 0 | AP10: 0.00% | AQ10: 0 | AR10: 0 | AS10: 0.00% | AT10: ** | AU10: ** | AV10: ** | AW10: ** | AX10: ** | AY10: 0 | AZ10: 0.00% | BA10: 0 | BB10: 0.00% | BC10: 0 | BD10: 0.00% | BE10: 0 | BF10: 0 | BG10: 0 | BH10: 0 | BI10: 0.00% | BJ10: 0.00% | BK10: 0.00% | BL10: 0 | BM10: 0.00% | BN10: 0 | BO10: 0 | BP10: 0 | BQ10: 0 | BR10: 0 | BS10: 0 | BT10: 0.00% | BU10: 0.00% | BV10: 0.00% | BW10: 0 | BX10: 0 | BY10: 0 | BZ10: 0 | CA10: 0 | CB10: 0 | CC10: 0 | CD10: 0.00% | CE10: 0.00% | CF10: 0 | CG10: 0 | CH10: 0 | CI10: 0 | CJ10: 0.00% | CK10: 0.00% | CL10: 0.00% | CM10: 0.00% | CN10: 0.00% | CO10: 0.00% | CP10: 0 | CQ10: 0.00% | CR10: 0 | CS10: 0.00% | CT10: 0 | CU10: 0.00% | CV10: 0.00% | CW10: 0 | CX10: 0.00% | CY10: 0 | CZ10: 0.00% | DA10: 0 | DB10: 0.00% | DC10: 0.00% | DD10: 0.00% | DE10: 0.00%
A11: 2025-12-10 | B11: R0007EU | C11: B0FNMBQFBC | D11: B0FNMBQFBC | E11: R00007EU,R0007EU | F11: HYCHIKA-AP100A-空净 | G11: 0 | H11: 0 | I11: 0 | J11: 0 | K11: 0 | L11: 0 | M11: 0 | N11: 0 | O11: 0 | P11: 0 | Q11: 0 | R11: 0 | S11: 0 | T11: 0.00% | U11: 0.00% | V11: 0.00% | W11: 0.00% | X11: 0.00% | Y11: 0.00% | Z11: 0 | AA11: 0 | AB11: 0 | AC11: 0 | AD11: 0 | AE11: 0 | AF11: 0 | AG11: 0 | AH11: 0 | AI11: 0 | AJ11: 0 | AK11: 0 | AN11: 0 | AO11: 0 | AP11: 0.00% | AQ11: 0 | AR11: 0 | AS11: 0.00% | AT11: ** | AU11: ** | AV11: ** | AW11: ** | AX11: ** | AY11: 0 | AZ11: 0.00% | BA11: 0 | BB11: 0.00% | BC11: 0 | BD11: 0.00% | BE11: 0 | BF11: 0 | BG11: 0 | BH11: 0 | BI11: 0.00% | BJ11: 0.00% | BK11: 0.00% | BL11: 0 | BM11: 0.00% | BN11: 0 | BO11: 0 | BP11: 0 | BQ11: 0 | BR11: 0 | BS11: 0 | BT11: 0.00% | BU11: 0.00% | BV11: 0.00% | BW11: 0 | BX11: 0 | BY11: 0 | BZ11: 0 | CA11: 0 | CB11: 0 | CC11: 0 | CD11: 0.00% | CE11: 0.00% | CF11: 0 | CG11: 0 | CH11: 0 | CI11: 0 | CJ11: 0.00% | CK11: 0.00% | CL11: 0.00% | CM11: 0.00% | CN11: 0.00% | CO11: 0.00% | CP11: 0 | CQ11: 0.00% | CR11: 0 | CS11: 0.00% | CT11: 0 | CU11: 0.00% | CV11: 0.00% | CW11: 0 | CX11: 0.00% | CY11: 0 | CZ11: 0.00% | DA11: 0 | DB11: 0.00% | DC11: 0.00% | DD11: 0.00% | DE11: 0.00%
A12: 2025-12-11 | B12: R0007EU | C12: B0FNMBQFBC | D12: B0FNMBQFBC | E12: R00007EU,R0007EU | F12: HYCHIKA-AP100A-空净 | G12: 0 | H12: 0 | I12: 0 | J12: 0 | K12: 0 | L12: 0 | M12: 0 | N12: 0 | O12: 0 | P12: 0 | Q12: 0 | R12: 0 | S12: 0 | T12: 0.00% | U12: 0.00% | V12: 0.00% | W12: 0.00% | X12: 0.00% | Y12: 0.00% | Z12: 0 | AA12: 0 | AB12: 0 | AC12: 0 | AD12: 0 | AE12: 0 | AF12: 0 | AG12: 0 | AH12: 0 | AI12: 0 | AJ12: 0 | AK12: 0 | AN12: 0 | AO12: 0 | AP12: 0.00% | AQ12: 0 | AR12: 0 | AS12: 0.00% | AT12: ** | AU12: ** | AV12: ** | AW12: ** | AX12: ** | AY12: 0 | AZ12: 0.00% | BA12: 0 | BB12: 0.00% | BC12: 0 | BD12: 0.00% | BE12: 0 | BF12: 0 | BG12: 0 | BH12: 0 | BI12: 0.00% | BJ12: 0.00% | BK12: 0.00% | BL12: 0 | BM12: 0.00% | BN12: 0 | BO12: 0 | BP12: 0 | BQ12: 0 | BR12: 0 | BS12: 0 | BT12: 0.00% | BU12: 0.00% | BV12: 0.00% | BW12: 0 | BX12: 0 | BY12: 0 | BZ12: 0 | CA12: 0 | CB12: 0 | CC12: 0 | CD12: 0.00% | CE12: 0.00% | CF12: 0 | CG12: 0 | CH12: 0 | CI12: 0 | CJ12: 0.00% | CK12: 0.00% | CL12: 0.00% | CM12: 0.00% | CN12: 0.00% | CO12: 0.00% | CP12: 0 | CQ12: 0.00% | CR12: 0 | CS12: 0.00% | CT12: 0 | CU12: 0.00% | CV12: 0.00% | CW12: 0 | CX12: 0.00% | CY12: 0 | CZ12: 0.00% | DA12: 0 | DB12: 0.00% | DC12: 0.00% | DD12: 0.00% | DE12: 0.00%
A13: 2025-12-12 | B13: R0007EU | C13: B0FNMBQFBC | D13: B0FNMBQFBC | E13: R00007EU,R0007EU | F13: HYCHIKA-AP100A-空净 | G13: 0 | H13: 0 | I13: 0 | J13: 0 | K13: 0 | L13: 0 | M13: 0 | N13: 0 | O13: 0 | P13: 0 | Q13: 0 | R13: 0 | S13: 0 | T13: 0.00% | U13: 0.00% | V13: 0.00% | W13: 0.00% | X13: 0.00% | Y13: 0.00% | Z13: 0 | AA13: 0 | AB13: 0 | AC13: 0 | AD13: 0 | AE13: 0 | AF13: 0 | AG13: 0 | AH13: 0 | AI13: 0 | AJ13: 0 | AK13: 0 | AN13: 0 | AO13: 0 | AP13: 0.00% | AQ13: 0 | AR13: 0 | AS13: 0.00% | AT13: ** | AU13: ** | AV13: ** | AW13: ** | AX13: ** | AY13: 0 | AZ13: 0.00% | BA13: 0 | BB13: 0.00% | BC13: 0 | BD13: 0.00% | BE13: 0 | BF13: 0 | BG13: 0 | BH13: 0 | BI13: 0.00% | BJ13: 0.00% | BK13: 0.00% | BL13: 0 | BM13: 0.00% | BN13: 0 | BO13: 0 | BP13: 0 | BQ13: 0 | BR13: 0 | BS13: 0 | BT13: 0.00% | BU13: 0.00% | BV13: 0.00% | BW13: 0 | BX13: 0 | BY13: 0 | BZ13: 0 | CA13: 0 | CB13: 0 | CC13: 0 | CD13: 0.00% | CE13: 0.00% | CF13: 0 | CG13: 0 | CH13: 0 | CI13: 0 | CJ13: 0.00% | CK13: 0.00% | CL13: 0.00% | CM13: 0.00% | CN13: 0.00% | CO13: 0.00% | CP13: 0 | CQ13: 0.00% | CR13: 0 | CS13: 0.00% | CT13: 0 | CU13: 0.00% | CV13: 0.00% | CW13: 0 | CX13: 0.00% | CY13: 0 | CZ13: 0.00% | DA13: 0 | DB13: 0.00% | DC13: 0.00% | DD13: 0.00% | DE13: 0.00%
... A25: 2025-12-24 | B25: R0007EU | C25: B0FNMBQFBC | D25: B0FNMBQFBC | E25: R00007EU,R0007EU | F25: HYCHIKA-AP100A-空净 | G25: 0 | H25: 69 | I25: 193 | J25: 0 | K25: 0 | L25: 0 | M25: 0 | N25: 0 | O25: 193 | P25: 0 | Q25: 0 | R25: 0 | S25: 0 | T25: 0.00% | U25: 0.00% | V25: 0.00% | W25: 0.00% | X25: 0.00% | Y25: 0.00% | Z25: 0 | AA25: 0 | AB25: 0 | AC25: 0 | AD25: 0 | AE25: 0 | AF25: 0 | AG25: 0 | AH25: 0 | AI25: 0 | AJ25: 0 | AK25: 0 | AN25: 0 | AO25: 0 | AP25: 0.00% | AQ25: 0 | AR25: 0 | AS25: 0.00% | AT25: ** | AU25: ** | AV25: ** | AW25: ** | AX25: ** | AY25: 0 | AZ25: 0.00% | BA25: 0 | BB25: 0.00% | BC25: 0 | BD25: 0.00% | BE25: 0 | BF25: 0 | BG25: 0 | BH25: 0 | BI25: 0.00% | BJ25: 0.00% | BK25: 0.00% | BL25: 0 | BM25: 0.00% | BN25: 0 | BO25: 0 | BP25: 0 | BQ25: 0 | BR25: 0 | BS25: 0 | BT25: 0.00% | BU25: 0.00% | BV25: 0.00% | BW25: 0 | BX25: 0 | BY25: 0 | BZ25: 0 | CA25: 0 | CB25: 0 | CC25: 0 | CD25: 0.00% | CE25: 0.00% | CF25: 0 | CG25: 0 | CH25: 0 | CI25: 0 | CJ25: 0.00% | CK25: 0.00% | CL25: 0.00% | CM25: 0.00% | CN25: 0.00% | CO25: 0.00% | CP25: 0 | CQ25: 0.00% | CR25: 0 | CS25: 0.00% | CT25: 0 | CU25: 0.00% | CV25: 0.00% | CW25: 0 | CX25: 0.00% | CY25: 0 | CZ25: 0.00% | DA25: 0 | DB25: 0.00% | DC25: 0.00% | DD25: 0.00% | DE25: 0.00%
A26: 46016 | B26: R0007EU | C26: B0FNMBQFBC | D26: B0FNMBQFBC | E26: R00007EU,R0007EU | F26: HYCHIKA-AP100A-空净 | G26: 0 | H26: 69 | I26: 193 | J26: 0 | K26: 0 | L26: 0 | M26: 0 | N26: 0 | O26: 193 | P26: 0 | Q26: 0 | R26: 0 | S26: 0 | T26: 0.00% | U26: 0.00% | V26: 0.00% | W26: 0.00% | X26: 0.00% | Y26: 0.00% | Z26: 0 | AA26: 0 | AB26: 0 | AC26: 0 | AD26: 0 | AE26: 0 | AF26: 0 | AG26: 0 | AH26: 0 | AI26: 0 | AJ26: 0 | AK26: 0 | AN26: 0 | AO26: 0 | AP26: 0.00% | AQ26: 0 | AR26: 0 | AS26: 0.00% | AT26: ** | AU26: ** | AV26: ** | AW26: ** | AX26: ** | AY26: 0 | AZ26: 0.00% | BA26: 0 | BB26: 0.00% | BC26: 0 | BD26: 0.00% | BE26: 0 | BF26: 0 | BG26: 0 | BH26: 0 | BI26: 0.00% | BJ26: 0.00% | BK26: 0.00% | BL26: 0 | BM26: 0.00% | BN26: 0 | BO26: 0 | BP26: 0 | BQ26: 0 | BR26: 0 | BS26: 0 | BT26: 0.00% | BU26: 0.00% | BV26: 0.00% | BW26: 0 | BX26: 0 | BY26: 0 | BZ26: 0 | CA26: 0 | CB26: 0 | CC26: 0 | CD26: 0.00% | CE26: 0.00% | CF26: 0 | CG26: 0 | CH26: 0 | CI26: 0 | CJ26: 0.00% | CK26: 0.00% | CL26: 0.00% | CM26: 0.00% | CN26: 0.00% | CO26: 0.00% | CP26: 0 | CQ26: 0.00% | CR26: 0 | CS26: 0.00% | CT26: 0 | CU26: 0.00% | CV26: 0.00% | CW26: 0 | CX26: 0.00% | CY26: 0 | CZ26: 0.00% | DA26: 0 | DB26: 0.00% | DC26: 0.00% | DD26: 0.00% | DE26: 0.00%

Sheet 日常跟踪表 IT
A1: 时间 | B1: 星期 | C1: 工作内容 | D1: 售价 | E1: PD | F1: 划线价 折扣 | G1: CP | H1: 最低 成交价 | I1: SC最低 成交价毛利率 | J1: VC采购价毛利率 | K1: 移动 | L1: PC | M1: 访问 | N1: 总转化率 | O1: 实际自然订单 | P1: 自然订单 | Q1: 总订单 | R1: VC订单 | S1: B2B订单 | T1: 测评计划出单 | U1: 测评总出单 | V1: 测评完成率 | W1: Vine | X1: 销售额 | Y1: 核心词ABA排名 | AC1: sif前三页关键词收录数量 | AD1: 大类排名 | AE1: 小类排名 | AF1: 评论数 | AG1: 评分 | AH1: 广告数据 | AU1: 毛利数据 | BB1: 站外 | BH1: 库存监控
AH2: 曝光 | AI2: 点击 | AJ2: 点击率 | AK2: 订单 | AL2: CPC | AM2: ACOS | AN2: 广告转化 | AO2: 广告订单占比 | AP2: 花费（$） | AQ2: 广告花费占比 | AR2: CPA | AS2: 广告销售额 | AT2: 退款率 | AU2: 广告订单毛利P1$ | AV2: 自然订单毛利P1$ | AW2: 总订单毛利P1$ | AX2: 总订单毛利率P1 | AY2: 国内总成本$ | AZ2: 回款金额 | BA2: 测评亏损 | BB2: 站外毛利$ | BC2: 站外出单 | BD2: 站外售价 | BE2: 站外折扣 | BF2: 自然流量 | BG2: 自然转化 | BH2: VC仓库存 | BI2: 海外仓库存 | BJ2: 总库存 | BK2: VC其他订单数 | BL2: 备注
A3: 45992 | B3: 星期一 | D3: 54.99 | E3: 0 | F3: 0 | G3: 0 | H3: =D3*(1-F3)*(1-G3) | I3: - | J3: - | K3: ='意大利ERP数据'!BC2 | L3: ='意大利ERP数据'!BA2 | M3: =K3+L3 | N3: =IFERROR(Q3/M3,0) | O3: =P3-AK3 | P3: =Q3-U3-BC3 | Q3: ='意大利ERP数据'!R2 | S3: ='意大利ERP数据'!Z2 | T3: 0 | U3: 0 | V3: 0 | W3: 0 | X3: 0 | AD3: 0 | AE3: 0 | AF3: 0 | AG3: 0 | AH3: 0 | AI3: 0 | AJ3: =AI3/AH3 | AK3: 0 | AL3: =AP3/AI3 | AM3: =AP3/AS3 | AN3: =AK3/AI3 | AO3: =AK3/P3 | AP3: 0 | AQ3: =AP3/W3 | AR3: =AP3/AK3 | AS3: 0
A4: 45993 | B4: 星期二 | D4: 54.99 | E4: 0 | F4: 0 | G4: 0 | H4: =D4*(1-F4)*(1-G4) | I4: - | J4: - | K4: ='意大利ERP数据'!BC3 | L4: ='意大利ERP数据'!BA3 | M4: =K4+L4 | N4: =IFERROR(Q4/M4,0) | O4: =P4-AK4 | P4: =Q4-U4-BC4 | Q4: ='意大利ERP数据'!R3 | S4: ='意大利ERP数据'!Z3 | T4: 0 | U4: 0 | V4: 0 | W4: 0 | X4: 0 | AD4: 0 | AE4: 0 | AF4: 0 | AG4: 0 | AH4: 0 | AI4: 0 | AJ4: =AI4/AH4 | AK4: 0 | AL4: =AP4/AI4 | AM4: =AP4/AS4 | AN4: =AK4/AI4 | AO4: =AK4/P4 | AP4: 0 | AQ4: =AP4/W4 | AR4: =AP4/AK4 | AS4: 0
A5: 45994 | B5: 星期三 | D5: 54.99 | E5: 0 | F5: 0 | G5: 0 | H5: =D5*(1-F5)*(1-G5) | I5: - | J5: - | K5: ='意大利ERP数据'!BC4 | L5: ='意大利ERP数据'!BA4 | M5: =K5+L5 | N5: =IFERROR(Q5/M5,0) | O5: =P5-AK5 | P5: =Q5-U5-BC5 | Q5: ='意大利ERP数据'!R4 | S5: ='意大利ERP数据'!Z4 | T5: 0 | U5: 0 | V5: 0 | W5: 10 | X5: 0 | AD5: 0 | AE5: 0 | AF5: 0 | AG5: 0 | AH5: 0 | AI5: 0 | AJ5: =AI5/AH5 | AK5: 0 | AL5: =AP5/AI5 | AM5: =AP5/AS5 | AN5: =AK5/AI5 | AO5: =AK5/P5 | AP5: 0 | AQ5: =AP5/W5 | AR5: =AP5/AK5 | AS5: 0
A6: 45995 | B6: 星期四 | D6: 54.99 | E6: 0 | F6: 0 | G6: 0 | H6: =D6*(1-F6)*(1-G6) | I6: - | J6: - | K6: ='意大利ERP数据'!BC5 | L6: ='意大利ERP数据'!BA5 | M6: =K6+L6 | N6: =IFERROR(Q6/M6,0) | O6: =P6-AK6 | P6: =Q6-U6-BC6 | Q6: ='意大利ERP数据'!R5 | S6: ='意大利ERP数据'!Z5 | T6: 0 | U6: 0 | V6: 0 | W6: 0 | X6: 0 | AD6: 0 | AE6: 333 | AF6: 0 | AG6: 0 | AH6: 0 | AI6: 0 | AJ6: =AI6/AH6 | AK6: 0 | AL6: =AP6/AI6 | AM6: =AP6/AS6 | AN6: =AK6/AI6 | AO6: =AK6/P6 | AP6: 0 | AQ6: =AP6/W6 | AR6: =AP6/AK6 | AS6: 0
A7: 45996 | B7: 星期五 | D7: 54.99 | E7: 0 | F7: 0 | G7: 0 | H7: =D7*(1-F7)*(1-G7) | I7: - | J7: - | K7: ='意大利ERP数据'!BC6 | L7: ='意大利ERP数据'!BA6 | M7: =K7+L7 | N7: =IFERROR(Q7/M7,0) | O7: =P7-AK7 | P7: =Q7-U7-BC7 | Q7: ='意大利ERP数据'!R6 | S7: ='意大利ERP数据'!Z6 | T7: 0 | U7: 0 | V7: 0 | W7: 0 | X7: 0 | AD7: 33523 | AE7: 129 | AF7: 0 | AG7: 0 | AH7: 0 | AI7: 0 | AJ7: =AI7/AH7 | AK7: 0 | AL7: =AP7/AI7 | AM7: =AP7/AS7 | AN7: =AK7/AI7 | AO7: =AK7/P7 | AP7: 0 | AQ7: =AP7/W7 | AR7: =AP7/AK7 | AS7: 0
A8: 45997 | B8: 星期六 | D8: 54.99 | E8: 0 | F8: 0 | G8: 0 | H8: =D8*(1-F8)*(1-G8) | I8: - | J8: - | K8: ='意大利ERP数据'!BC7 | L8: ='意大利ERP数据'!BA7 | M8: =K8+L8 | N8: =IFERROR(Q8/M8,0) | O8: =P8-AK8 | P8: =Q8-U8-BC8 | Q8: ='意大利ERP数据'!R7 | S8: ='意大利ERP数据'!Z7 | T8: 0 | U8: 0 | V8: 0 | W8: 0 | X8: 0 | AD8: 63392 | AE8: 207 | AF8: 0 | AG8: 0 | AH8: 0 | AI8: 0 | AJ8: =AI8/AH8 | AK8: 0 | AL8: =AP8/AI8 | AM8: =AP8/AS8 | AN8: =AK8/AI8 | AO8: =AK8/P8 | AP8: 0 | AQ8: =AP8/W8 | AR8: =AP8/AK8 | AS8: 0
A9: 45998 | B9: 星期日 | D9: 54.99 | E9: 0 | F9: 0 | G9: 0 | H9: =D9*(1-F9)*(1-G9) | I9: - | J9: - | K9: ='意大利ERP数据'!BC8 | L9: ='意大利ERP数据'!BA8 | M9: =K9+L9 | N9: =IFERROR(Q9/M9,0) | O9: =P9-AK9 | P9: =Q9-U9-BC9 | Q9: ='意大利ERP数据'!R8 | S9: ='意大利ERP数据'!Z8 | T9: 0 | U9: 0 | V9: 1 | W9: 0 | X9: 0 | AD9: 108016 | AE9: 273 | AF9: 0 | AG9: 0 | AH9: 0 | AI9: 0 | AJ9: =AI9/AH9 | AK9: 0 | AL9: =AP9/AI9 | AM9: =AP9/AS9 | AN9: =AK9/AI9 | AO9: =AK9/P9 | AP9: 0 | AQ9: =AP9/W9 | AR9: =AP9/AK9 | AS9: 0
A10: 45999 | B10: 星期一 | D10: 54.99 | E10: 0 | F10: 0 | G10: 0 | H10: =D10*(1-F10)*(1-G10) | I10: - | J10: - | K10: ='意大利ERP数据'!BC9 | L10: ='意大利ERP数据'!BA9 | M10: =K10+L10 | N10: =IFERROR(Q10/M10,0) | O10: =P10-AK10 | P10: =Q10-U10-BC10 | Q10: ='意大利ERP数据'!R9 | S10: ='意大利ERP数据'!Z9 | T10: 0 | U10: 0 | V10: 0 | W10: 0 | X10: 0 | AD10: 108016 | AE10: 273 | AF10: 2 | AG10: 4.5 | AH10: 0 | AI10: 0 | AJ10: =AI10/AH10 | AK10: 0 | AL10: =AP10/AI10 | AM10: =AP10/AS10 | AN10: =AK10/AI10 | AO10: =AK10/P10 | AP10: 0 | AQ10: =AP10/W10 | AR10: =AP10/AK10 | AS10: 0
A11: 46000 | B11: 星期二 | D11: 54.99 | E11: 0 | F11: 0 | G11: 0 | H11: =D11*(1-F11)*(1-G11) | I11: - | J11: - | K11: ='意大利ERP数据'!BC10 | L11: ='意大利ERP数据'!BA10 | M11: =K11+L11 | N11: =IFERROR(Q11/M11,0) | O11: =P11-AK11 | P11: =Q11-U11-BC11 | Q11: ='意大利ERP数据'!R10 | S11: ='意大利ERP数据'!Z10 | T11: 0 | U11: 0 | V11: 0 | W11: 0 | X11: 0 | AD11: 0 | AE11: 0 | AF11: 0 | AG11: 0 | AH11: 0 | AI11: 0 | AJ11: =AI11/AH11 | AK11: 0 | AL11: =AP11/AI11 | AM11: =AP11/AS11 | AN11: =AK11/AI11 | AO11: =AK11/P11 | AP11: 0 | AQ11: =AP11/W11 | AR11: =AP11/AK11 | AS11: 0
A12: 46001 | B12: 星期三 | D12: 54.99 | E12: 0 | F12: 0 | G12: 0 | H12: =D12*(1-F12)*(1-G12) | I12: - | J12: - | K12: ='意大利ERP数据'!BC11 | L12: ='意大利ERP数据'!BA11 | M12: =K12+L12 | N12: =IFERROR(Q12/M12,0) | O12: =P12-AK12 | P12: =Q12-U12-BC12 | Q12: ='意大利ERP数据'!R11 | S12: ='意大利ERP数据'!Z11 | T12: 0 | U12: 0 | V12: 0 | W12: 0 | X12: 0 | AD12: 0 | AE12: 0 | AF12: 0 | AG12: 0 | AH12: 0 | AI12: 0 | AJ12: =AI12/AH12 | AK12: 0 | AL12: =AP12/AI12 | AM12: =AP12/AS12 | AN12: =AK12/AI12 | AO12: =AK12/P12 | AP12: 0 | AQ12: =AP12/W12 | AR12: =AP12/AK12 | AS12: 0
A13: 46002 | B13: 星期四 | D13: 54.99 | E13: 0 | F13: 0 | G13: 0 | H13: =D13*(1-F13)*(1-G13) | I13: - | J13: - | K13: ='意大利ERP数据'!BC12 | L13: ='意大利ERP数据'!BA12 | M13: =K13+L13 | N13: =IFERROR(Q13/M13,0) | O13: =P13-AK13 | P13: =Q13-U13-BC13 | Q13: ='意大利ERP数据'!R12 | S13: ='意大利ERP数据'!Z12 | T13: 0 | U13: 0 | V13: 1 | W13: 0 | X13: 0 | AD13: 0 | AE13: 0 | AF13: 0 | AG13: 0 | AH13: 0 | AI13: 0 | AJ13: =AI13/AH13 | AK13: 0 | AL13: =AP13/AI13 | AM13: =AP13/AS13 | AN13: =AK13/AI13 | AO13: =AK13/P13 | AP13: 0 | AQ13: =AP13/W13 | AR13: =AP13/AK13 | AS13: 0
A14: 46003 | B14: 星期五 | D14: 54.99 | E14: 0 | F14: 0 | G14: 0 | H14: =D14*(1-F14)*(1-G14) | I14: - | J14: - | K14: ='意大利ERP数据'!BC13 | L14: ='意大利ERP数据'!BA13 | M14: =K14+L14 | N14: =IFERROR(Q14/M14,0) | O14: =P14-AK14 | P14: =Q14-U14-BC14 | Q14: ='意大利ERP数据'!R13 | S14: ='意大利ERP数据'!Z13 | T14: 0 | U14: 0 | V14: 0 | W14: 0 | X14: 0 | AD14: 0 | AE14: 0 | AF14: 0 | AG14: 0 | AH14: 0 | AI14: 0 | AJ14: =AI14/AH14 | AK14: 0 | AL14: =AP14/AI14 | AM14: =AP14/AS14 | AN14: =AK14/AI14 | AO14: =AK14/P14 | AP14: 0 | AQ14: =AP14/W14 | AR14: =AP14/AK14 | AS14: 0
... A23: 46012 | B23: 星期日 | D23: 54.99 | E23: 0 | F23: 0 | G23: 0 | H23: =D23*(1-F23)*(1-G23) | I23: - | J23: - | K23: ='意大利ERP数据'!BC22 | L23: ='意大利ERP数据'!BA22 | M23: =K23+L23 | N23: =IFERROR(Q23/M23,0) | O23: =P23-AK23 | P23: =Q23-U23-BC23 | Q23: ='意大利ERP数据'!R22 | S23: ='意大利ERP数据'!Z22 | T23: 0 | U23: 0 | V23: 1 | W23: 0 | X23: 0 | AD23: 0 | AE23: 0 | AF23: 0 | AG23: 0 | AH23: 4194 | AI23: 13 | AJ23: =AI23/AH23 | AK23: 1 | AL23: =AP23/AI23 | AM23: =AP23/AS23 | AN23: =AK23/AI23 | AO23: =AK23/P23 | AP23: 12.63 | AQ23: =AP23/W23 | AR23: =AP23/AK23 | AS23: 73.43
A24: 46013 | B24: 星期一 | D24: 54.99 | E24: 0 | F24: 0 | G24: 0 | H24: =D24*(1-F24)*(1-G24) | I24: - | J24: - | K24: ='意大利ERP数据'!BC23 | L24: ='意大利ERP数据'!BA23 | M24: =K24+L24 | N24: =IFERROR(Q24/M24,0) | O24: =P24-AK24 | P24: =Q24-U24-BC24 | Q24: ='意大利ERP数据'!R23 | S24: ='意大利ERP数据'!Z23 | T24: 0 | U24: 0 | V24: 1 | W24: 0 | X24: 0 | AD24: 0 | AE24: 0 | AF24: 0 | AG24: 0 | AH24: 3973 | AI24: 25 | AJ24: =AI24/AH24 | AK24: 0 | AL24: =AP24/AI24 | AM24: =0 | AN24: =AK24/AI24 | AO24: =AK24/P24 | AP24: 27.01 | AQ24: =AP24/W24 | AR24: =AP24/AK24 | AS24: 0
A25: 46014 | B25: 星期二 | D25: 54.99 | E25: 0 | F25: 0 | G25: 0 | H25: =D25*(1-F25)*(1-G25) | I25: - | J25: - | K25: ='意大利ERP数据'!BC24 | L25: ='意大利ERP数据'!BA24 | M25: =K25+L25 | N25: =IFERROR(Q25/M25,0) | O25: =P25-AK25 | P25: =Q25-U25-BC25 | Q25: ='意大利ERP数据'!R24 | S25: ='意大利ERP数据'!Z24 | T25: 0 | U25: 0 | V25: 1 | W25: 0 | X25: 0 | AD25: 0 | AE25: 0 | AF25: 0 | AG25: 0 | AH25: 3425 | AI25: 19 | AJ25: =AI25/AH25 | AK25: 2 | AL25: =AP25/AI25 | AM25: =AP25/AS25 | AN25: =AK25/AI25 | AO25: =AK25/P25 | AP25: 22.53 | AQ25: =AP25/W25 | AR25: =AP25/AK25 | AS25: 146.86
A26: 46015 | B26: 星期三 | D26: 54.99 | E26: 0 | F26: 0 | G26: 0 | H26: =D26*(1-F26)*(1-G26) | I26: - | J26: - | K26: ='意大利ERP数据'!BC25 | L26: ='意大利ERP数据'!BA25 | M26: =K26+L26 | N26: =IFERROR(Q26/M26,0) | O26: =P26-AK26 | P26: =Q26-U26-BC26 | Q26: ='意大利ERP数据'!R25 | S26: ='意大利ERP数据'!Z25 | T26: 0 | U26: 0 | V26: 1 | W26: 0 | X26: 0 | AD26: 0 | AE26: 0 | AF26: 0 | AG26: 0 | AH26: 5162 | AI26: 26 | AJ26: =AI26/AH26 | AK26: 1 | AL26: =AP26/AI26 | AM26: =AP26/AS26 | AN26: =AK26/AI26 | AO26: =AK26/P26 | AP26: 36.83 | AQ26: =AP26/W26 | AR26: =AP26/AK26 | AS26: 73.43
A27: 46016 | B27: 星期四 | D27: 54.99 | E27: 0 | F27: 0 | G27: 0 | H27: =D27*(1-F27)*(1-G27) | I27: - | J27: - | K27: ='意大利ERP数据'!BC26 | L27: ='意大利ERP数据'!BA26 | M27: =K27+L27 | N27: =IFERROR(Q27/M27,0) | O27: =P27-AK27 | P27: =Q27-U27-BC27 | Q27: ='意大利ERP数据'!R26 | S27: ='意大利ERP数据'!Z26 | T27: 0 | U27: 0 | V27: 1 | W27: 0 | X27: 0 | AD27: 0 | AE27: 0 | AF27: 0 | AG27: 0 | AH27: 4557 | AI27: 44 | AJ27: =AI27/AH27 | AK27: 1 | AL27: =AP27/AI27 | AM27: =AP27/AS27 | AN27: =AK27/AI27 | AO27: =AK27/P27 | AP27: 71.92 | AQ27: =AP27/W27 | AR27: =AP27/AK27 | AS27: 73.43
A28: 46017 | B28: 星期五 | D28: 54.99 | E28: 0 | F28: 0 | G28: 0 | H28: =D28*(1-F28)*(1-G28) | I28: - | J28: - | K28: ='意大利ERP数据'!BC27 | L28: ='意大利ERP数据'!BA27 | M28: =K28+L28 | N28: =IFERROR(Q28/M28,0) | O28: =P28-AK28 | P28: =Q28-U28-BC28 | Q28: ='意大利ERP数据'!R27 | S28: ='意大利ERP数据'!Z27 | T28: 0 | U28: 0 | V28: 1 | W28: 0 | X28: 0 | AD28: 0 | AE28: 0 | AF28: 0 | AG28: 0 | AH28: 6389 | AI28: 59 | AJ28: =AI28/AH28 | AK28: 4 | AL28: =AP28/AI28 | AM28: =AP28/AS28 | AN28: =AK28/AI28 | AO28: =AK28/P28 | AP28: 99.1 | AQ28: =AP28/W28 | AR28: =AP28/AK28 | AS28: 293.72
A29: 46018 | B29: 星期六 | D29: 54.99 | E29: 0 | F29: 0 | G29: 0 | H29: =D29*(1-F29)*(1-G29) | I29: - | J29: - | K29: ='意大利ERP数据'!BC28 | L29: ='意大利ERP数据'!BA28 | M29: =K29+L29 | N29: =IFERROR(Q29/M29,0) | O29: =P29-AK29 | P29: =Q29-U29-BC29 | Q29: ='意大利ERP数据'!R28 | S29: ='意大利ERP数据'!Z28 | T29: 0 | U29: 0 | V29: 1 | W29: 0 | X29: 0 | AD29: 0 | AE29: 0 | AF29: 0 | AG29: 0 | AH29: 12558 | AI29: 110 | AJ29: =AI29/AH29 | AK29: 7 | AL29: =AP29/AI29 | AM29: =AP29/AS29 | AN29: =AK29/AI29 | AO29: =AK29/P29 | AP29: 182.22 | AQ29: =AP29/W29 | AR29: =AP29/AK29 | AS29: 514.01
A30: 46019 | B30: 星期日 | D30: 54.99 | E30: 0 | F30: 0 | G30: 0 | H30: =D30*(1-F30)*(1-G30) | I30: - | J30: - | K30: ='意大利ERP数据'!BC29 | L30: ='意大利ERP数据'!BA29 | M30: =K30+L30 | N30: =IFERROR(Q30/M30,0) | O30: =P30-AK30 | P30: =Q30-U30-BC30 | Q30: ='意大利ERP数据'!R29 | S30: ='意大利ERP数据'!Z29 | T30: 0 | U30: 0 | V30: 1 | W30: 0 | X30: 0 | AD30: 0 | AE30: 0 | AF30: 0 | AG30: 0 | AH30: 12478 | AI30: 144 | AJ30: =AI30/AH30 | AK30: 5 | AL30: =AP30/AI30 | AM30: =AP30/AS30 | AN30: =AK30/AI30 | AO30: =AK30/P30 | AP30: 222.8 | AQ30: =AP30/W30 | AR30: =AP30/AK30 | AS30: 367.15
A31: 46020 | B31: 星期一 | D31: 54.99 | E31: 0 | F31: 0 | G31: 0 | H31: =D31*(1-F31)*(1-G31) | I31: - | J31: - | K31: ='意大利ERP数据'!BC30 | L31: ='意大利ERP数据'!BA30 | M31: =K31+L31 | N31: =IFERROR(Q31/M31,0) | O31: =P31-AK31 | P31: =Q31-U31-BC31 | Q31: ='意大利ERP数据'!R30 | S31: ='意大利ERP数据'!Z30 | T31: 0 | U31: 0 | V31: 1 | W31: 0 | X31: 0 | AD31: 0 | AE31: 0 | AF31: 0 | AG31: 0 | AH31: 8754 | AI31: 109 | AJ31: =AI31/AH31 | AK31: 8 | AL31: =AP31/AI31 | AM31: =AP31/AS31 | AN31: =AK31/AI31 | AO31: =AK31/P31 | AP31: 158.61 | AQ31: =AP31/W31 | AR31: =AP31/AK31 | AS31: 587.44
A32: 46021 | B32: 星期二 | D32: 54.99 | E32: 0 | F32: 0 | G32: 0 | H32: =D32*(1-F32)*(1-G32) | I32: - | J32: - | K32: ='意大利ERP数据'!BC31 | L32: ='意大利ERP数据'!BA31 | M32: =K32+L32 | N32: =IFERROR(Q32/M32,0) | O32: =P32-AK32 | P32: =Q32-U32-BC32 | Q32: ='意大利ERP数据'!R31 | S32: ='意大利ERP数据'!Z31 | T32: 0 | U32: 0 | V32: 1 | W32: 0 | X32: 0 | AD32: 0 | AE32: 0 | AF32: 0 | AG32: 0 | AH32: 7937 | AI32: 62 | AJ32: =AI32/AH32 | AK32: 4 | AL32: =AP32/AI32 | AM32: =AP32/AS32 | AN32: =AK32/AI32 | AO32: =AK32/P32 | AP32: 94.26 | AQ32: =AP32/W32 | AR32: =AP32/AK32 | AS32: 293.78
A33: 46022 | B33: 星期三 | D33: 54.99 | E33: 0 | F33: 0 | G33: 0 | H33: =D33*(1-F33)*(1-G33) | I33: - | J33: - | K33: ='意大利ERP数据'!BC32 | L33: ='意大利ERP数据'!BA32 | M33: =K33+L33 | N33: =IFERROR(Q33/M33,0) | O33: =P33-AK33 | P33: =Q33-U33-BC33 | Q33: ='意大利ERP数据'!R32 | S33: ='意大利ERP数据'!Z32 | T33: 0 | U33: 0 | V33: 1 | W33: 0 | X33: 0 | AD33: 0 | AE33: 0 | AF33: 0 | AG33: 0 | AH33: 8988 | AI33: 44 | AJ33: =AI33/AH33 | AK33: 0 | AL33: =AP33/AI33 | AM33: =AP33/AS33 | AN33: =AK33/AI33 | AO33: =AK33/P33 | AP33: 0 | AQ33: =AP33/W33 | AR33: =AP33/AK33 | AS33: 0
A34: 46023 | B34: 星期四 | D34: 54.99 | E34: 0 | F34: 0 | G34: 0 | H34: =D34*(1-F34)*(1-G34) | I34: - | J34: - | K34: ='意大利ERP数据'!BC33 | L34: ='意大利ERP数据'!BA33 | M34: =K34+L34 | N34: =IFERROR(Q34/M34,0) | O34: =P34-AK34 | P34: =Q34-U34-BC34 | Q34: ='意大利ERP数据'!R33 | S34: ='意大利ERP数据'!Z33 | T34: 0 | U34: 0 | V34: 1 | W34: 0 | X34: 0 | AD34: 0 | AE34: 0 | AF34: 0 | AG34: 0 | AH34: 8700 | AI34: 38 | AJ34: =AI34/AH34 | AK34: 0 | AL34: =AP34/AI34 | AM34: =AP34/AS34 | AN34: =AK34/AI34 | AO34: =AK34/P34 | AP34: 0 | AQ34: =AP34/W34 | AR34: =AP34/AK34 | AS34: 0
A35: 46024 | B35: 星期五 | D35: 54.99 | E35: 0 | F35: 0 | G35: 0 | H35: =D35*(1-F35)*(1-G35) | I35: - | J35: - | K35: ='意大利ERP数据'!BC34 | L35: ='意大利ERP数据'!BA34 | M35: =K35+L35 | N35: =IFERROR(Q35/M35,0) | O35: =P35-AK35 | P35: =Q35-U35-BC35 | Q35: ='意大利ERP数据'!R34 | S35: ='意大利ERP数据'!Z34 | T35: 0 | U35: 0 | V35: 1 | W35: 0 | X35: 0 | AD35: 0 | AE35: 0 | AF35: 0 | AG35: 0 | AH35: 0 | AI35: 0 | AJ35: =AI35/AH35 | AK35: 0 | AL35: =AP35/AI35 | AM35: =AP35/AS35 | AN35: =AK35/AI35 | AO35: =AK35/P35 | AP35: 0 | AQ35: =AP35/W35 | AR35: =AP35/AK35 | AS35: 0
A36: 46025 | B36: 星期六 | D36: 54.99 | E36: 0 | F36: 0 | G36: 0 | H36: =D36*(1-F36)*(1-G36) | I36: - | J36: - | K36: ='意大利ERP数据'!BC35 | L36: ='意大利ERP数据'!BA35 | M36: =K36+L36 | N36: =IFERROR(Q36/M36,0) | O36: =P36-AK36 | P36: =Q36-U36-BC36 | Q36: ='意大利ERP数据'!R35 | S36: ='意大利ERP数据'!Z35 | T36: 0 | U36: 0 | V36: 1 | W36: 0 | X36: 0 | AD36: 0 | AE36: 0 | AF36: 0 | AG36: 0 | AH36: 0 | AI36: 0 | AJ36: =AI36/AH36 | AK36: 0 | AL36: =AP36/AI36 | AM36: =AP36/AS36 | AN36: =AK36/AI36 | AO36: =AK36/P36 | AP36: 0 | AQ36: =AP36/W36 | AR36: =AP36/AK36 | AS36: 0
... A47: 46036 | B47: 星期三 | D47: 54.99 | E47: 0 | F47: 0 | G47: 0 | H47: =D47*(1-F47)*(1-G47) | I47: - | J47: - | K47: ='意大利ERP数据'!BC46 | L47: ='意大利ERP数据'!BA46 | M47: =K47+L47 | N47: =IFERROR(Q47/M47,0) | O47: =P47-AK47 | P47: =Q47-U47-BC47 | Q47: ='意大利ERP数据'!R46 | S47: ='意大利ERP数据'!Z46 | T47: 0 | U47: 0 | V47: 1 | W47: 0 | X47: 0 | AD47: 0 | AE47: 0 | AF47: 0 | AG47: 0 | AH47: 0 | AI47: 0 | AJ47: =AI47/AH47 | AK47: 0 | AL47: =AP47/AI47 | AM47: =AP47/AS47 | AN47: =AK47/AI47 | AO47: =AK47/P47 | AP47: 0 | AQ47: =AP47/W47 | AR47: =AP47/AK47 | AS47: 0
A48: 46037 | B48: 星期四 | D48: 54.99 | E48: 0 | F48: 0 | G48: 0 | S48: ='意大利ERP数据'!Z47
A49: 46038 | B49: 星期五 | D49: 54.99 | E49: 0 | F49: 0 | G49: 0 | S49: ='意大利ERP数据'!Z48
A50: 46039 | B50: 星期六 | D50: 54.99 | E50: 0 | F50: 0 | G50: 0 | S50: ='意大利ERP数据'!Z49
A51: 46040 | B51: 星期日 | D51: 54.99 | E51: 0 | F51: 0 | G51: 0 | S51: ='意大利ERP数据'!Z50
A52: 46041 | B52: 星期一 | D52: 54.99 | E52: 0 | F52: 0 | G52: 0 | S52: ='意大利ERP数据'!Z51
A53: 46042 | B53: 星期二 | D53: 54.99 | E53: 0 | F53: 0 | G53: 0 | S53: ='意大利ERP数据'!Z52
A54: 46043 | B54: 星期三 | D54: 54.99 | E54: 0 | F54: 0 | G54: 0 | S54: ='意大利ERP数据'!Z53
A55: 46044 | B55: 星期四 | D55: 54.99 | E55: 0 | F55: 0 | G55: 0 | S55: ='意大利ERP数据'!Z54
A56: 46045 | B56: 星期五 | D56: 54.99 | E56: 0 | F56: 0 | G56: 0 | S56: ='意大利ERP数据'!Z55
A57: 46046 | B57: 星期六 | D57: 54.99 | E57: 0 | F57: 0 | G57: 0 | S57: ='意大利ERP数据'!Z56
A58: 46047 | B58: 星期日 | D58: 54.99 | E58: 0 | F58: 0 | G58: 0 | S58: ='意大利ERP数据'!Z57
A59: 46048 | B59: 星期一 | D59: 54.99 | E59: 0 | F59: 0 | G59: 0 | S59: ='意大利ERP数据'!Z58
... A161: 46150 | B161: 星期五 | D161: 54.99 | E161: 0 | F161: 0 | G161: 0 | S161: ='意大利ERP数据'!Z160
A162: 汇总 这一行不编辑，增加行 插入就行 | D162: 139.99 | M162: =SUM(M44:M92) | N162: 0.1746 | O162: =SUM(O44:O92) | P162: =SUM(P44:P92) | Q162: =SUM(Q44:Q92) | S162: ='意大利ERP数据'!Z161 | X162: =SUM(X44:X92) | AH162: =SUM(AH44:AH92) | AI162: =SUM(AI44:AI92) | AJ162: =AI162/AH162 | AK162: =SUM(AK44:AK92) | AL162: =AI162/AP162 | AM162: =AP162/(AK162*D162) | AN162: =AK162/AI162 | AO162: =AK162/P162 | AP162: =SUM(AP44:AP92) | AQ162: =AP162/X162 | AS162: =AP162/AK162 | AW162: =SUM(AW44:AW92) | AX162: =AW162/X162 | AZ162: =SUM(AZ44:AZ92) | BB162: =SUM(BB44:BB92) | BC162: =SUM(BC44:BC92) | BF162: =M162-AI162 | BG162: =O162/BF162

Sheet 日常跟踪表 ES
A1: 时间 | B1: 星期 | C1: 工作内容 | D1: 售价 | E1: FBA价 | F1: 划线价 折扣 | G1: CP | H1: 最低 成交价 | I1: SC最低 成交价毛利率 | J1: VC采购价毛利率 | K1: 移动 | L1: PC | M1: 访问 | N1: 总转化率 | O1: 实际自然订单 | P1: 自然订单 | Q1: 总订单 | R1: VC订单 | S1: B2B订单 | T1: 测评计划出单 | U1: 测评总出单 | V1: 测评完成率 | W1: Vine | X1: 销售额 | Y1: 核心词ABA排名 | AC1: sif前三页关键词收录数量 | AD1: 大类排名 | AE1: 小类排名 | AF1: 评论数 | AG1: 评分 | AH1: 广告数据 | AW1: 毛利数据 | BD1: 站外 | BJ1: 库存监控
AH2: 曝光 | AI2: 点击 | AJ2: 点击率 | AK2: 订单 | AL2: CPC | AM2: ACOS | AN2: 广告转化 | AO2: 广告订单占比 | AP2: 花费（$） | AQ2: 广告花费占比 | AR2: CPA | AS2: 广告销售额 | AT2: 广告销售额占店铺总销售额 | AV2: 退款率 | AW2: 广告订单毛利P1$ | AX2: 自然订单毛利P1$ | AY2: 总订单毛利P1$ | AZ2: 总订单毛利率P1 | BA2: 国内总成本$ | BB2: 回款金额 | BC2: 测评亏损 | BD2: 站外毛利$ | BE2: 站外出单 | BF2: 站外售价 | BG2: 站外折扣 | BH2: 自然流量 | BI2: 自然转化 | BJ2: VC仓库存 | BK2: 海外仓库存 | BL2: 总库存 | BM2: VC其他订单数 | BN2: 备注
A3: 45992 | B3: 星期一 | D3: 54.99 | F3: 0 | G3: 0 | H3: =D3*(1-F3)*(1-G3) | I3: - | J3: - | K3: ='西班牙ERP数据'!BC2 | L3: ='西班牙ERP数据'!BA2 | M3: =K3+L3 | N3: =IFERROR(Q3/M3,0) | O3: =P3-AK3 | P3: =Q3-U3-BE3 | Q3: ='西班牙ERP数据'!R2 | S3: ='西班牙ERP数据'!Z2 | T3: 0 | U3: 0 | V3: 0 | W3: 0 | X3: 0 | AD3: 0 | AE3: 0 | AF3: 0 | AG3: 0 | AH3: 0 | AI3: 0 | AJ3: =AI3/AH3 | AK3: 0 | AL3: =AP3/AI3 | AM3: =AP3/AS3 | AN3: =AK3/AI3 | AO3: =AK3/P3 | AP3: 0 | AQ3: =AP3/W3 | AR3: =AP3/AK3 | AS3: 0
A4: 45993 | B4: 星期二 | D4: 54.99 | F4: 0 | G4: 0 | H4: =D4*(1-F4)*(1-G4) | I4: - | J4: - | K4: ='西班牙ERP数据'!BC3 | L4: ='西班牙ERP数据'!BA3 | M4: =K4+L4 | N4: =IFERROR(Q4/M4,0) | O4: =P4-AK4 | P4: =Q4-U4-BE4 | Q4: ='西班牙ERP数据'!R3 | S4: ='西班牙ERP数据'!Z3 | T4: 0 | U4: 0 | V4: 0 | W4: 0 | X4: 0 | AD4: 0 | AE4: 0 | AF4: 0 | AG4: 0 | AH4: 0 | AI4: 0 | AJ4: =AI4/AH4 | AK4: 0 | AL4: =AP4/AI4 | AM4: =AP4/AS4 | AN4: =AK4/AI4 | AO4: =AK4/P4 | AP4: 0 | AQ4: =AP4/W4 | AR4: =AP4/AK4 | AS4: 0
A5: 45994 | B5: 星期三 | D5: 54.99 | F5: 0 | G5: 0 | H5: =D5*(1-F5)*(1-G5) | I5: - | J5: - | K5: ='西班牙ERP数据'!BC4 | L5: ='西班牙ERP数据'!BA4 | M5: =K5+L5 | N5: =IFERROR(Q5/M5,0) | O5: =P5-AK5 | P5: =Q5-U5-BE5 | Q5: ='西班牙ERP数据'!R4 | S5: ='西班牙ERP数据'!Z4 | T5: 0 | U5: 0 | V5: 0 | W5: 0 | X5: 0 | AD5: 0 | AE5: 0 | AF5: 0 | AG5: 0 | AH5: 0 | AI5: 0 | AJ5: =AI5/AH5 | AK5: 0 | AL5: =AP5/AI5 | AM5: =AP5/AS5 | AN5: =AK5/AI5 | AO5: =AK5/P5 | AP5: 0 | AQ5: =AP5/W5 | AR5: =AP5/AK5 | AS5: 0
A6: 45995 | B6: 星期四 | D6: 54.99 | F6: 0 | G6: 0 | H6: =D6*(1-F6)*(1-G6) | I6: - | J6: - | K6: ='西班牙ERP数据'!BC5 | L6: ='西班牙ERP数据'!BA5 | M6: =K6+L6 | N6: =IFERROR(Q6/M6,0) | O6: =P6-AK6 | P6: =Q6-U6-BE6 | Q6: ='西班牙ERP数据'!R5 | S6: ='西班牙ERP数据'!Z5 | T6: 0 | U6: 0 | V6: 0 | W6: 0 | X6: 0 | AD6: 0 | AE6: 0 | AF6: 0 | AG6: 0 | AH6: 0 | AI6: 0 | AJ6: =AI6/AH6 | AK6: 0 | AL6: =AP6/AI6 | AM6: =AP6/AS6 | AN6: =AK6/AI6 | AO6: =AK6/P6 | AP6: 0 | AQ6: =AP6/W6 | AR6: =AP6/AK6 | AS6: 0
A7: 45996 | B7: 星期五 | D7: 54.99 | F7: 0 | G7: 0 | H7: =D7*(1-F7)*(1-G7) | I7: - | J7: - | K7: ='西班牙ERP数据'!BC6 | L7: ='西班牙ERP数据'!BA6 | M7: =K7+L7 | N7: =IFERROR(Q7/M7,0) | O7: =P7-AK7 | P7: =Q7-U7-BE7 | Q7: ='西班牙ERP数据'!R6 | S7: ='西班牙ERP数据'!Z6 | T7: 1 | U7: 1 | V7: 0 | W7: 0 | X7: 0 | AD7: 0 | AE7: 0 | AF7: 0 | AG7: 0 | AH7: 0 | AI7: 0 | AJ7: =AI7/AH7 | AK7: 0 | AL7: =AP7/AI7 | AM7: =AP7/AS7 | AN7: =AK7/AI7 | AO7: =AK7/P7 | AP7: 0 | AQ7: =AP7/W7 | AR7: =AP7/AK7 | AS7: 0
A8: 45997 | B8: 星期六 | D8: 54.99 | F8: 0 | G8: 0 | H8: =D8*(1-F8)*(1-G8) | I8: - | J8: - | K8: ='西班牙ERP数据'!BC7 | L8: ='西班牙ERP数据'!BA7 | M8: =K8+L8 | N8: =IFERROR(Q8/M8,0) | O8: =P8-AK8 | P8: =Q8-U8-BE8 | Q8: ='西班牙ERP数据'!R7 | S8: ='西班牙ERP数据'!Z7 | T8: 1 | U8: 1 | V8: 0 | W8: 0 | X8: 0 | AD8: 0 | AE8: 0 | AF8: 0 | AG8: 0 | AH8: 0 | AI8: 0 | AJ8: =AI8/AH8 | AK8: 0 | AL8: =AP8/AI8 | AM8: =AP8/AS8 | AN8: =AK8/AI8 | AO8: =AK8/P8 | AP8: 0 | AQ8: =AP8/W8 | AR8: =AP8/AK8 | AS8: 0
A9: 45998 | B9: 星期日 | D9: 54.99 | F9: 0 | G9: 0 | H9: =D9*(1-F9)*(1-G9) | I9: - | J9: - | K9: ='西班牙ERP数据'!BC8 | L9: ='西班牙ERP数据'!BA8 | M9: =K9+L9 | N9: =IFERROR(Q9/M9,0) | O9: =P9-AK9 | P9: =Q9-U9-BE9 | Q9: ='西班牙ERP数据'!R8 | S9: ='西班牙ERP数据'!Z8 | T9: 0 | U9: 0 | V9: 0 | W9: 0 | X9: 0 | AD9: 0 | AE9: 0 | AF9: 1 | AG9: 0 | AH9: 0 | AI9: 0 | AJ9: =AI9/AH9 | AK9: 0 | AL9: =AP9/AI9 | AM9: =AP9/AS9 | AN9: =AK9/AI9 | AO9: =AK9/P9 | AP9: 0 | AQ9: =AP9/W9 | AR9: =AP9/AK9 | AS9: 0
A10: 45999 | B10: 星期一 | D10: 54.99 | F10: 0 | G10: 0 | H10: =D10*(1-F10)*(1-G10) | I10: - | J10: - | K10: ='西班牙ERP数据'!BC9 | L10: ='西班牙ERP数据'!BA9 | M10: =K10+L10 | N10: =IFERROR(Q10/M10,0) | O10: =P10-AK10 | P10: =Q10-U10-BE10 | Q10: ='西班牙ERP数据'!R9 | S10: ='西班牙ERP数据'!Z9 | T10: 0 | U10: 0 | V10: 0 | W10: 0 | X10: 0 | AD10: 0 | AE10: 0 | AF10: 1 | AG10: 4 | AH10: 0 | AI10: 0 | AJ10: =AI10/AH10 | AK10: 0 | AL10: =AP10/AI10 | AM10: =AP10/AS10 | AN10: =AK10/AI10 | AO10: =AK10/P10 | AP10: 0 | AQ10: =AP10/W10 | AR10: =AP10/AK10 | AS10: 0
A11: 46000 | B11: 星期二 | D11: 54.99 | F11: 0 | G11: 0 | H11: =D11*(1-F11)*(1-G11) | I11: - | J11: - | K11: ='西班牙ERP数据'!BC10 | L11: ='西班牙ERP数据'!BA10 | M11: =K11+L11 | N11: =IFERROR(Q11/M11,0) | O11: =P11-AK11 | P11: =Q11-U11-BE11 | Q11: ='西班牙ERP数据'!R10 | S11: ='西班牙ERP数据'!Z10 | T11: 0 | U11: 0 | V11: 0 | W11: 0 | X11: 0 | AD11: 0 | AE11: 0 | AF11: 1 | AG11: 4 | AH11: 0 | AI11: 0 | AJ11: =AI11/AH11 | AK11: 0 | AL11: =AP11/AI11 | AM11: =AP11/AS11 | AN11: =AK11/AI11 | AO11: =AK11/P11 | AP11: 0 | AQ11: =AP11/W11 | AR11: =AP11/AK11 | AS11: 0
A12: 46001 | B12: 星期三 | D12: 54.99 | F12: 0 | G12: 0 | H12: =D12*(1-F12)*(1-G12) | I12: - | J12: - | K12: ='西班牙ERP数据'!BC11 | L12: ='西班牙ERP数据'!BA11 | M12: =K12+L12 | N12: =IFERROR(Q12/M12,0) | O12: =P12-AK12 | P12: =Q12-U12-BE12 | Q12: ='西班牙ERP数据'!R11 | S12: ='西班牙ERP数据'!Z11 | T12: 0 | U12: 0 | V12: 0 | W12: 0 | X12: 0 | AD12: 0 | AE12: 0 | AF12: 2 | AG12: 4.5 | AH12: 0 | AI12: 0 | AJ12: =AI12/AH12 | AK12: 0 | AL12: =AP12/AI12 | AM12: =AP12/AS12 | AN12: =AK12/AI12 | AO12: =AK12/P12 | AP12: 0 | AQ12: =AP12/W12 | AR12: =AP12/AK12 | AS12: 0
A13: 46002 | B13: 星期四 | D13: 54.99 | F13: 0 | G13: 0 | H13: =D13*(1-F13)*(1-G13) | I13: - | J13: - | K13: ='西班牙ERP数据'!BC12 | L13: ='西班牙ERP数据'!BA12 | M13: =K13+L13 | N13: =IFERROR(Q13/M13,0) | O13: =P13-AK13 | P13: =Q13-U13-BE13 | Q13: ='西班牙ERP数据'!R12 | S13: ='西班牙ERP数据'!Z12 | T13: 0 | U13: 0 | V13: 0 | W13: 0 | X13: 0 | AD13: 0 | AE13: 0 | AF13: 3 | AG13: 4.6 | AH13: 0 | AI13: 0 | AJ13: =AI13/AH13 | AK13: 0 | AL13: =AP13/AI13 | AM13: =AP13/AS13 | AN13: =AK13/AI13 | AO13: =AK13/P13 | AP13: 0 | AQ13: =AP13/W13 | AR13: =AP13/AK13 | AS13: 0
A14: 46003 | B14: 星期五 | D14: 54.99 | F14: 0 | G14: 0 | H14: =D14*(1-F14)*(1-G14) | I14: - | J14: - | K14: ='西班牙ERP数据'!BC13 | L14: ='西班牙ERP数据'!BA13 | M14: =K14+L14 | N14: =IFERROR(Q14/M14,0) | O14: =P14-AK14 | P14: =Q14-U14-BE14 | Q14: ='西班牙ERP数据'!R13 | S14: ='西班牙ERP数据'!Z13 | T14: 0 | U14: 0 | V14: 0 | W14: 0 | X14: 0 | AD14: 0 | AE14: 0 | AF14: 10 | AG14: 4.7 | AH14: 0 | AI14: 0 | AJ14: =AI14/AH14 | AK14: 0 | AL14: =AP14/AI14 | AM14: =AP14/AS14 | AN14: =AK14/AI14 | AO14: =AK14/P14 | AP14: 0 | AQ14: =AP14/W14 | AR14: =AP14/AK14 | AS14: 0
... A21: 46010 | B21: 星期五 | D21: 54.99 | F21: 0 | G21: 0 | H21: =D21*(1-F21)*(1-G21) | I21: - | J21: - | K21: ='西班牙ERP数据'!BC20 | L21: ='西班牙ERP数据'!BA20 | M21: =K21+L21 | N21: =IFERROR(Q21/M21,0) | O21: =P21-AK21 | P21: =Q21-U21-BE21 | Q21: ='西班牙ERP数据'!R20 | S21: ='西班牙ERP数据'!Z20 | T21: 0 | U21: 0 | V21: 0 | W21: 0 | X21: 0 | AD21: 0 | AE21: 0 | AF21: 25 | AG21: 4.8 | AH21: 0 | AI21: 0 | AJ21: =AI21/AH21 | AK21: 0 | AL21: =AP21/AI21 | AM21: =AP21/AS21 | AN21: =AK21/AI21 | AO21: =AK21/P21 | AP21: 0 | AQ21: =AP21/W21 | AR21: =AP21/AK21 | AS21: 0
A22: 46011 | B22: 星期六 | D22: 54.99 | F22: 0 | G22: 0 | H22: =D22*(1-F22)*(1-G22) | I22: - | J22: - | K22: ='西班牙ERP数据'!BC21 | L22: ='西班牙ERP数据'!BA21 | M22: =K22+L22 | N22: =IFERROR(Q22/M22,0) | O22: =P22-AK22 | P22: =Q22-U22-BE22 | Q22: ='西班牙ERP数据'!R21 | S22: ='西班牙ERP数据'!Z21 | T22: 0 | U22: 0 | V22: 0 | W22: 0 | X22: 88.03 | AD22: 91234 | AE22: 237 | AF22: 25 | AG22: 4.8 | AH22: 0 | AI22: 0 | AJ22: =AI22/AH22 | AK22: 0 | AL22: =AP22/AI22 | AM22: =AP22/AS22 | AN22: =AK22/AI22 | AO22: =AK22/P22 | AP22: 0 | AQ22: =IFERROR(AP22/X22,0) | AR22: =AP22/AK22 | AS22: 0
A23: 46012 | B23: 星期日 | D23: 54.99 | F23: 0 | G23: 0 | H23: =D23*(1-F23)*(1-G23) | I23: - | J23: - | K23: ='西班牙ERP数据'!BC22 | L23: ='西班牙ERP数据'!BA22 | M23: =K23+L23 | N23: =IFERROR(Q23/M23,0) | O23: =P23-AK23 | P23: =Q23-U23-BE23 | Q23: ='西班牙ERP数据'!R22 | S23: ='西班牙ERP数据'!Z22 | T23: 0 | U23: 0 | V23: 0 | W23: 0 | X23: 0 | AD23: 59308 | AE23: 165 | AF23: 26 | AG23: 4.8 | AH23: 2794 | AI23: 17 | AJ23: =AI23/AH23 | AK23: 0 | AL23: =AP23/AI23 | AM23: =AP23/AS23 | AN23: =AK23/AI23 | AO23: =AK23/P23 | AP23: 18.7 | AQ23: =IFERROR(AP23/X23,0) | AR23: =AP23/AK23 | AS23: 148.08 | AT23: =IFERROR(AS23/X23,0)
A24: 46013 | B24: 星期一 | D24: 54.99 | F24: 0 | G24: 0 | H24: =D24*(1-F24)*(1-G24) | I24: - | J24: - | K24: ='西班牙ERP数据'!BC23 | L24: ='西班牙ERP数据'!BA23 | M24: =K24+L24 | N24: =IFERROR(Q24/M24,0) | O24: =P24-AK24 | P24: =Q24-U24-BE24 | Q24: ='西班牙ERP数据'!R23 | S24: ='西班牙ERP数据'!Z23 | T24: 0 | U24: 0 | V24: 0 | W24: 0 | X24: 0 | AD24: 63426 | AE24: 180 | AF24: 29 | AG24: 4.8 | AH24: 3570 | AI24: 26 | AJ24: =AI24/AH24 | AK24: 0 | AL24: =AP24/AI24 | AM24: =AP24/AS24 | AN24: =AK24/AI24 | AO24: =AK24/P24 | AP24: 29.84 | AQ24: =IFERROR(AP24/X24,0) | AR24: 0 | AS24: 0 | AT24: =IFERROR(AS24/X24,0)
A25: 46014 | B25: 星期二 | D25: 54.99 | F25: 0 | G25: 0 | H25: =D25*(1-F25)*(1-G25) | I25: - | J25: - | K25: ='西班牙ERP数据'!BC24 | L25: ='西班牙ERP数据'!BA24 | M25: =K25+L25 | N25: =IFERROR(Q25/M25,0) | O25: =P25-AK25 | P25: =Q25-U25-BE25 | Q25: ='西班牙ERP数据'!R24 | S25: ='西班牙ERP数据'!Z24 | T25: 0 | U25: 0 | V25: 0 | W25: 0 | X25: 621.76 | AD25: 78356 | AE25: 193 | AF25: 39 | AG25: 4.9 | AH25: 3098 | AI25: 41 | AJ25: =AI25/AH25 | AK25: 0 | AL25: =AP25/AI25 | AM25: =AP25/AS25 | AN25: =AK25/AI25 | AO25: =AK25/P25 | AP25: 47.8 | AQ25: =IFERROR(AP25/X25,0) | AR25: =AP25/AK25 | AS25: 444.24 | AT25: =IFERROR(AS25/X25,0)
A26: 46015 | B26: 星期三 | D26: 54.99 | F26: 0 | G26: 0 | H26: =D26*(1-F26)*(1-G26) | I26: - | J26: - | K26: ='西班牙ERP数据'!BC25 | L26: ='西班牙ERP数据'!BA25 | M26: =K26+L26 | N26: =IFERROR(Q26/M26,0) | O26: =P26-AK26 | P26: =Q26-U26-BE26 | Q26: ='西班牙ERP数据'!R25 | S26: ='西班牙ERP数据'!Z25 | T26: 0 | U26: 0 | V26: 0 | W26: 0 | X26: 264.1 | AD26: 78356 | AE26: 193 | AF26: 42 | AG26: 4.9 | AH26: 3369 | AI26: 36 | AJ26: =AI26/AH26 | AK26: 0 | AL26: =AP26/AI26 | AM26: =AP26/AS26 | AN26: =AK26/AI26 | AO26: =AK26/P26 | AP26: 43.42 | AQ26: =IFERROR(AP26/X26,0) | AR26: =AP26/AK26 | AS26: 296.16 | AT26: =IFERROR(AS26/X26,0)
A27: 46016 | B27: 星期四 | D27: 54.99 | F27: 0 | G27: 0 | H27: =D27*(1-F27)*(1-G27) | I27: - | J27: - | K27: ='西班牙ERP数据'!BC26 | L27: ='西班牙ERP数据'!BA26 | M27: =K27+L27 | N27: =IFERROR(Q27/M27,0) | O27: =P27-AK27 | P27: =Q27-U27-BE27 | Q27: ='西班牙ERP数据'!R26 | S27: ='西班牙ERP数据'!Z26 | T27: 0 | U27: 0 | V27: 0 | W27: 0 | X27: 607.69 | AD27: 9593 | AE27: 38 | AF27: 43 | AG27: 4.9 | AH27: 7693 | AI27: 60 | AJ27: =AI27/AH27 | AK27: 0 | AL27: =AP27/AI27 | AM27: =AP27/AS27 | AN27: =AK27/AI27 | AO27: =AK27/P27 | AP27: 83.1 | AQ27: =IFERROR(AP27/X27,0) | AR27: =AP27/AK27 | AS27: 296.16 | AT27: =IFERROR(AS27/X27,0)
A28: 46017 | B28: 星期五 | D28: 54.99 | F28: 0 | G28: 0 | H28: =D28*(1-F28)*(1-G28) | I28: - | J28: - | K28: ='西班牙ERP数据'!BC27 | L28: ='西班牙ERP数据'!BA27 | M28: =K28+L28 | N28: =IFERROR(Q28/M28,0) | O28: =P28-AK28 | P28: =Q28-U28-BE28 | Q28: ='西班牙ERP数据'!R27 | S28: ='西班牙ERP数据'!Z27 | T28: 0 | U28: 0 | V28: 0 | W28: 0 | X28: 264.1 | AD28: 6816 | AE28: 30 | AF28: 44 | AG28: 4.9 | AH28: 7263 | AI28: 69 | AJ28: =AI28/AH28 | AK28: 0 | AL28: =AP28/AI28 | AM28: =AP28/AS28 | AN28: =AK28/AI28 | AO28: =AK28/P28 | AP28: 108.66 | AQ28: =IFERROR(AP28/X28,0) | AR28: =AP28/AK28 | AS28: 370.2 | AT28: =IFERROR(AS28/X28,0)
A29: 46018 | B29: 星期六 | D29: 54.99 | F29: 0 | G29: 0 | H29: =D29*(1-F29)*(1-G29) | I29: - | J29: - | K29: ='西班牙ERP数据'!BC28 | L29: ='西班牙ERP数据'!BA28 | M29: =K29+L29 | N29: =IFERROR(Q29/M29,0) | O29: =P29-AK29 | P29: =Q29-U29-BE29 | Q29: ='西班牙ERP数据'!R28 | S29: ='西班牙ERP数据'!Z28 | T29: 0 | U29: 0 | V29: 0 | W29: 0 | X29: 444.06 | AD29: 7097 | AE29: 30 | AF29: 43 | AG29: 4.9 | AH29: 6617 | AI29: 75 | AJ29: =AI29/AH29 | AK29: 0 | AL29: =AP29/AI29 | AM29: =AP29/AS29 | AN29: =AK29/AI29 | AO29: =AK29/P29 | AP29: 103.27 | AQ29: =IFERROR(AP29/X29,0) | AR29: =AP29/AK29 | AS29: 148.08 | AT29: =IFERROR(AS29/X29,0)
A30: 46019 | B30: 星期日 | D30: 54.99 | F30: 0 | G30: 0 | H30: =D30*(1-F30)*(1-G30) | I30: - | J30: - | K30: ='西班牙ERP数据'!BC29 | L30: ='西班牙ERP数据'!BA29 | M30: =K30+L30 | N30: =IFERROR(Q30/M30,0) | O30: =P30-AK30 | P30: =Q30-U30-BE30 | Q30: ='西班牙ERP数据'!R29 | S30: ='西班牙ERP数据'!Z29 | T30: 0 | U30: 0 | V30: 0 | W30: 0 | X30: 264.1 | AD30: 7200 | AE30: 33 | AF30: 46 | AG30: 4.9 | AH30: 4671 | AI30: 54 | AJ30: =AI30/AH30 | AK30: 0 | AL30: =AP30/AI30 | AM30: =AP30/AS30 | AN30: =AK30/AI30 | AO30: =AK30/P30 | AP30: 82.61 | AQ30: =IFERROR(AP30/X30,0) | AR30: =AP30/AK30 | AS30: 74.04 | AT30: =IFERROR(AS30/X30,0)
A31: 46020 | B31: 星期一 | D31: 54.99 | F31: 0 | G31: 0 | H31: =D31*(1-F31)*(1-G31) | I31: - | J31: - | K31: ='西班牙ERP数据'!BC30 | L31: ='西班牙ERP数据'!BA30 | M31: =K31+L31 | N31: =IFERROR(Q31/M31,0) | O31: =P31-AK31 | P31: =Q31-U31-BE31 | Q31: ='西班牙ERP数据'!R30 | S31: ='西班牙ERP数据'!Z30 | T31: 0 | U31: 0 | V31: 0 | W31: 0 | X31: 268.77 | AD31: 12165 | AE31: 52 | AF31: 46 | AG31: 4.9 | AH31: 6422 | AI31: 52 | AJ31: =AI31/AH31 | AK31: 0 | AL31: =AP31/AI31 | AM31: =AP31/AS31 | AN31: =AK31/AI31 | AO31: =AK31/P31 | AP31: 73.61 | AQ31: =IFERROR(AP31/X31,0) | AR31: =AP31/AK31 | AS31: 74.04 | AT31: =IFERROR(AS31/X31,0)
A32: 46021 | B32: 星期二 | D32: 54.99 | F32: 0 | G32: 0 | H32: =D32*(1-F32)*(1-G32) | I32: - | J32: - | K32: ='西班牙ERP数据'!BC31 | L32: ='西班牙ERP数据'!BA31 | M32: =K32+L32 | N32: =IFERROR(Q32/M32,0) | O32: =P32-AK32 | P32: =Q32-U32-BE32 | Q32: ='西班牙ERP数据'!R31 | S32: ='西班牙ERP数据'!Z31 | T32: 0 | U32: 0 | V32: 0 | W32: 0 | X32: 264.11 | AD32: 12925 | AE32: 54 | AF32: 46 | AG32: 4.9 | AH32: 2162 | AI32: 22 | AJ32: =AI32/AH32 | AK32: 0 | AL32: =AP32/AI32 | AM32: =AP32/AS32 | AN32: =AK32/AI32 | AO32: =AK32/P32 | AP32: 1 | AQ32: =IFERROR(AP32/X32,0) | AR32: =AP32/AK32 | AS32: 74.04 | AT32: =IFERROR(AS32/X32,0)
A33: 46022 | B33: 星期三 | D33: 54.99 | F33: 0 | G33: 0 | H33: =D33*(1-F33)*(1-G33) | I33: - | J33: - | K33: ='西班牙ERP数据'!BC32 | L33: ='西班牙ERP数据'!BA32 | M33: =K33+L33 | N33: =IFERROR(Q33/M33,0) | O33: =P33-AK33 | P33: =Q33-U33-BE33 | Q33: ='西班牙ERP数据'!R32 | S33: ='西班牙ERP数据'!Z32 | T33: 0 | U33: 0 | V33: 0 | W33: 0 | X33: 264.11 | AD33: 12925 | AE33: 54 | AF33: 46 | AG33: 4.9 | AH33: 2162 | AI33: 14 | AJ33: =AI33/AH33 | AK33: 0 | AL33: =AP33/AI33 | AM33: =AP33/AS33 | AN33: =AK33/AI33 | AO33: =AK33/P33 | AP33: 1 | AQ33: =IFERROR(AP33/X33,0) | AR33: =AP33/AK33 | AS33: 74.04 | AT33: =IFERROR(AS33/X33,0)
A34: 46023 | B34: 星期四 | D34: 54.99 | F34: 0 | G34: 0 | H34: =D34*(1-F34)*(1-G34) | I34: - | J34: - | K34: ='西班牙ERP数据'!BC33 | L34: ='西班牙ERP数据'!BA33 | M34: =K34+L34 | N34: =IFERROR(Q34/M34,0) | O34: =P34-AK34 | P34: =Q34-U34-BE34 | Q34: ='西班牙ERP数据'!R33 | S34: ='西班牙ERP数据'!Z33 | T34: 0 | U34: 0 | V34: 0 | W34: 0 | X34: 264.11 | AD34: 12925 | AE34: 54 | AF34: 46 | AG34: 4.9 | AH34: 2162 | AI34: 14 | AJ34: =AI34/AH34 | AK34: 0 | AL34: =AP34/AI34 | AM34: =AP34/AS34 | AN34: =AK34/AI34 | AO34: =AK34/P34 | AP34: 1 | AQ34: =IFERROR(AP34/X34,0) | AR34: =AP34/AK34 | AS34: 74.04 | AT34: =IFERROR(AS34/X34,0)
A35: 46024 | B35: 星期五 | D35: 54.99 | F35: 0 | G35: 0 | H35: =D35*(1-F35)*(1-G35) | I35: - | J35: - | K35: ='西班牙ERP数据'!BC34 | L35: ='西班牙ERP数据'!BA34 | M35: =K35+L35 | N35: =IFERROR(Q35/M35,0) | O35: =P35-AK35 | P35: =Q35-U35-BE35 | Q35: ='西班牙ERP数据'!R34 | S35: ='西班牙ERP数据'!Z34 | T35: 0 | U35: 0 | V35: 0 | W35: 0 | X35: 264.11 | AD35: 12925 | AE35: 54 | AF35: 46 | AG35: 4.9 | AH35: 0 | AI35: 0 | AJ35: =AI35/AH35 | AK35: 0 | AL35: =AP35/AI35 | AM35: =AP35/AS35 | AN35: =AK35/AI35 | AO35: =AK35/P35 | AP35: 0 | AQ35: =IFERROR(AP35/X35,0) | AR35: =AP35/AK35 | AS35: 0 | AT35: =IFERROR(AS35/X35,0)
A36: 46025 | B36: 星期六 | D36: 54.99 | F36: 0 | G36: 0 | H36: =D36*(1-F36)*(1-G36) | I36: - | J36: - | K36: ='西班牙ERP数据'!BC35 | L36: ='西班牙ERP数据'!BA35 | M36: =K36+L36 | N36: =IFERROR(Q36/M36,0) | O36: =P36-AK36 | P36: =Q36-U36-BE36 | Q36: ='西班牙ERP数据'!R35 | S36: ='西班牙ERP数据'!Z35 | T36: 0 | U36: 0 | V36: 0 | W36: 0 | X36: 264.11 | AD36: 12925 | AE36: 54 | AF36: 46 | AG36: 4.9 | AH36: 0 | AI36: 0 | AJ36: =AI36/AH36 | AK36: 0 | AL36: =AP36/AI36 | AM36: =AP36/AS36 | AN36: =AK36/AI36 | AO36: =AK36/P36 | AP36: 0 | AQ36: =IFERROR(AP36/X36,0) | AR36: =AP36/AK36 | AS36: 0 | AT36: =IFERROR(AS36/X36,0)
... A57: 46046 | B57: 星期六 | D57: 54.99 | F57: 0 | G57: 0 | H57: =D57*(1-F57)*(1-G57) | I57: - | J57: - | K57: ='西班牙ERP数据'!BC56 | L57: ='西班牙ERP数据'!BA56 | M57: =K57+L57 | N57: =IFERROR(Q57/M57,0) | O57: =P57-AK57 | P57: =Q57-U57-BE57 | Q57: ='西班牙ERP数据'!R56 | S57: ='西班牙ERP数据'!Z56 | T57: 0 | U57: 0 | V57: 0 | W57: 0 | X57: 264.11 | AD57: 12925 | AE57: 54 | AF57: 46 | AG57: 4.9 | AH57: 2162 | AI57: 0 | AJ57: =AI57/AH57 | AK57: 0 | AL57: =AP57/AI57 | AM57: =AP57/AS57 | AN57: =AK57/AI57 | AO57: =AK57/P57 | AP57: 35.13 | AQ57: =IFERROR(AP57/X57,0) | AR57: =AP57/AK57 | AS57: 74.04 | AT57: =IFERROR(AS57/X57,0)
A58: 46047 | B58: 星期日
A59: 46048 | B59: 星期一
A60: 46049 | B60: 星期二
A61: 46050 | B61: 星期三
A62: 46051 | B62: 星期四
A63: 46052 | B63: 星期五
A64: 46053 | B64: 星期六
A65: 46054 | B65: 星期日
A66: 46055 | B66: 星期一
A67: 46056 | B67: 星期二
A68: 46057 | B68: 星期三
A69: 46058 | B69: 星期四
... A161: 46150 | B161: 星期五
A162: 汇总 | D162: 39.99 | M162: =SUM(M4:M161) | N162: 0.1746 | O162: =SUM(O4:O161) | P162: =SUM(P4:P161) | Q162: =SUM(Q4:Q161) | X162: =SUM(X44:X92) | AH162: =SUM(AH44:AH92) | AI162: =SUM(AI44:AI92) | AJ162: =AI162/AH162 | AK162: =SUM(AK44:AK92) | AL162: =AI162/AP162 | AM162: =AP162/(AK162*D162) | AN162: =AK162/AI162 | AO162: =AK162/P162 | AP162: =SUM(AP44:AP92) | AQ162: =AP162/X162 | AS162: =AP162/AK162 | AY162: =SUM(AY44:AY92) | AZ162: =AY162/X162 | BB162: =SUM(BB44:BB92) | BD162: =SUM(BD44:BD92) | BE162: =SUM(BE44:BE92) | BH162: =M162-AI162 | BI162: =O162/BH162

Sheet Coupon
A1: 站点 | B1: 售价 | C1: 折扣 | D1: 折前利润 | E1: 折后利润 | F1: 文本 | G1: 开始时间 | H1: 结束时间 | I1: 状态
A2: 德国 | B2: 139.99 | C2: 0.1 | D2: 0.2669 | E2: 0.2345 | G2: 45797 | H2: 45828 | I2: 暂停

Sheet 采购计划
A1: 月份 | B1: 期初库存 | C1: 入库数量 | D1: 待发PO | E1: 普通PO | F1: PO计划 月销 | G1: PO实际 月销 | H1: 前台 月销 | I1: 前台期初库存 | J1: 入库备注 | K1: 到货时间 | L1: 出货时间 | M1: 下单时间 | N1: 订单状态 | O1: 采购单号 | P1: 物流 交期 | Q1: 生产 交期
A2: 45839 | B2: =1140-200 | C2: 0 | D2: 0 | E2: =F2-D2 | F2: 800 | G2: 940 | H2: 559 | I2: =G2-H2 | P2: 65 | Q2: 30
A3: 45870 | B3: =B2-G2+C2 | D3: 0 | E3: =F3-D3 | F3: 340 | G3: 0 | H3: 312 | I3: =G3+I2-H3 | L3: =K3-55 | M3: =L3-55 | P3: 65 | Q3: 30
A4: 45901 | B4: 0 | C4: 1500 | D4: 0 | E4: =F4-D4 | F4: 500 | G4: 624 | H4: 70 | I4: =G4+I3-H4 | J4: 已入库 | K4: 45901 | L4: =K4-P4 | M4: =L4-Q4 | P4: 30 | Q4: 30
A5: 45931 | B5: =B4-G4+C4 | C5: 0 | D5: 0 | E5: =F5-D5 | F5: 740 | G5: 876 | H5: 434 | I5: =G5+I4-H5 | L5: =K5-P5 | M5: =L5-Q5 | P5: 65 | Q5: 30
A6: 45962 | B6: 0 | C6: 1000 | D6: 0 | E6: =F6-D6 | F6: 800 | G6: 1000 | H6: 566 | I6: =G6+I5-H6 | J6: 已入库 | K6: 45962 | L6: =K6-P6 | M6: =L6-Q6 | P6: 65 | Q6: 30
A7: 45992 | B7: =B6-G6+C6 | C7: 2000 | D7: 0 | E7: =F7-D7 | F7: 900 | H7: 700 | J7: 在途 | K7: 46011 | L7: =K7-P7 | M7: =L7-Q7 | P7: 65 | Q7: 30
A8: 46023 | B8: =B7-F7+C7 | C8: 500 | D8: 0 | E8: =F8-D8 | F8: 900 | H8: 600 | J8: 已下单 | K8: 46042 | L8: =K8-P8 | M8: =L8-Q8 | P8: 60 | Q8: 30
A9: 46054 | B9: =B8-F8+C8 | C9: 800 | D9: 0 | E9: =F9-D9 | F9: 800 | H9: 650 | J9: 已下单 | K9: 46073 | L9: =K9-P9 | M9: =L9-Q9 | P9: 65 | Q9: 30
A10: 46082 | B10: =B9-F9+C9 | C10: 1000 | D10: 0 | E10: =F10-D10 | F10: 750 | H10: 700 | J10: 已下单 | K10: 46101 | L10: =K10-P10 | M10: =L10-Q10 | P10: 65 | Q10: 30
A11: 46113 | B11: =B10-F10+C10 | C11: 0 | D11: 0 | E11: =F11-D11 | F11: 800 | H11: 750 | K11: 46122 | L11: =K11-P11 | M11: =L11-Q11 | P11: 65 | Q11: 30
A12: 46143 | B12: =B11-F11+C11 | C12: 1000 | D12: 0 | E12: =F12-D12 | F12: 800 | H12: 800 | J12: 已下单 | K12: 46143 | L12: =K12-P12 | M12: =L12-Q12 | P12: 65 | Q12: 30
A13: 46174 | B13: =B12-F12+C12 | C13: 1000 | D13: 0 | E13: =F13-D13 | F13: 1000 | H13: 800 | K13: 46174 | L13: =K13-P13 | M13: =L13-Q13 | P13: 65 | Q13: 30
A14: 46204 | B14: =B13-F13+C13 | C14: 1000 | D14: 0 | E14: =F14-D14 | F14: 800 | H14: 900 | K14: 46204 | L14: =K14-P14 | M14: =L14-Q14 | P14: 65 | Q14: 30
A15: 46235 | B15: =B14-F14+C14 | C15: 1000 | D15: 0 | E15: =F15-D15 | F15: 800 | H15: 800 | K15: 46249 | L15: =K15-P15 | M15: =L15-Q15 | P15: 65 | Q15: 30
A16: 46266 | B16: =B15-F15+C15 | C16: 0 | D16: 0 | E16: =F16-D16 | F16: 900 | H16: 800 | K16: 46275 | L16: =K16-P16 | M16: =L16-Q16 | P16: 65 | Q16: 30
A17: 46296 | B17: =B16-F16+C16 | C17: 1000 | D17: 0 | E17: =F17-D17 | F17: 1000 | H17: 900 | K17: 46296 | L17: =K17-P17 | M17: =L17-Q17 | P17: 65 | Q17: 30
A18: 46327 | B18: =B17-F17+C17 | C18: 1000 | D18: 0 | E18: =F18-D18 | F18: 1000 | H18: 1000 | K18: 46327 | L18: =K18-P18 | M18: =L18-Q18 | P18: 65 | Q18: 30
A19: 46357 | B19: =B18-F18+C18 | D19: 0 | E19: =F19-D19 | F19: 800 | H19: 1000 | L19: =K19-P19 | M19: =L19-Q19 | P19: 65 | Q19: 30
